Workbook
Name IQ_CH: 110000
Name IQ_CQ: 5000
Name IQ_CY: 10000
Name IQ_DAILY: 500000
Name IQ_FH: 100000
Name IQ_FQ: 500
Name IQ_FY: 1000
Name IQ_LTM: 2000
Name IQ_MONTH: 15000
Name IQ_NTM: 6000
Name IQ_WEEK: 50000
Name IQ_YTD: 3000

Sheet Table for SF_for publication
A3: Special Feature Online Annex 1.1 Fiscal Measures in Selected Economies in Response to the COVID-19 Pandemic
A4: The Special Feature Online Annex summarizes key fiscal measures governments have announced or taken in selected economies in response to COVID-19 pandemic from January 1 to April 8, 2020. The special feature categorizes different types of fiscal support (for example, above-the-line and below-the-line measures) that have different implications for the public finances in the near term and beyond. Please refer to Box 1.1 of the April 2020 Fiscal Monitor for details. The Special Feature is not meant for comparison across members as responses vary depending on country-specific circumstances, including the impact of the pandemic and other shocks. It focuses on government discretionary measures that supplement existing automatic stabilizers. These existing stabilizers differ across countries in their breadth and scope. Estimates included here are preliminary as governments are taking additional measures or finalizing the details of individual measures. The information does not represent views of the IMF on the measures listed. For a broad range of countries on their monetary and fiscal policies in response to the pandemic, please see IMF Policy Tracker (https://www.imf.org/en/Topics/imf-and-covid19/Policy-Responses-to-COVID-19).
A5: Online Annex Table 1.1. Selected Fiscal Measures in Response to COVID-19 Pandemic (as of April 8 2020)
C7: Above-the line measures | J7: Below the line measures | O7: Contingent liabilities | S7: Other measures | U7: Links
A8: Country / Country group | D8: Total size /1 /2 | E8: Total size /2 | F8: Spending and revenue measures in the health sector | G8: Total size | H8: Spending and revenue measures in areas other than health | K8: Total size | L8: Total size /2 | M8: Equity injections, asset purchases, loans, debt assumptions, quasi-fiscal operations, use of extra-budgetary funds | P8: Total size /2 | Q8: Guarantees on loans and other contingent liabilities | S8: Automatic stabilizers, contingency lines
A9: G20 advanced economies
A10: Australia | C10: LC bn | D10: 197.4 | E10: 3.6 | F10: Spending measures (AUS $3.6 bn): • Support for primary and aged care, hospitals, and research to ensure effective diagnosis and treatment of the infected and minimize the spread of the virus. • The Commonwealth government to pay for half of all additional costs incurred by states and territories in diagnosing and treating patients with COVID-19. | G10: =D10-E10 -> 193.8 | H10: Spending measures (AUS $188 bn): Tax-free cash payments to eligible small businesses to continue operations; wage subsidies for small businesses to keep their workers; payments to lower-income Australians, including pensioners, other social security and veteran income support recipients, and eligible concession card holders. Revenue measures (AUS 5.8 bn): Asset write-off; accelerated depreciation deductions to support investment; tax reliefs for Australian airlines and airports; waiver of fees and charges for tourism businesses in most affected regions and communities. | J10: LC bn | K10: 35 | L10: 15 | M10: • Government to provide the Australian Office of Financial Management with an investment capacity (AUS $15 bn) to invest in structured finance markets used by smaller lenders. | O10: LC bn | P10: 20 | Q10: • Under a Coronavirus SME Guarantee Scheme, government to guarantee 50 percent of loans (up to AUS $40 bn) offered by local lenders to SMEs. | S10: Parliament approved an advance authorization of A$40 billion for unforeseen events. | U10: https://treasury.gov.au/coronavirus
C11: USD bn | D11: =D10/#REF! -> #REF! | J11: USD bn | K11: =K10/VLOOKUP(A10,#REF!,7,0) -> #REF! | L11: =L10/VLOOKUP(A10,#REF!,7,0) -> #REF! | O11: USD bn | P11: =K11-L11 -> #REF!
C12: % GDP | D12: =(D10/VLOOKUP(A10,#REF!,4,0))*100 -> #REF! | J12: % GDP | K12: =(K10/VLOOKUP(A10,#REF!,4,0))*100 -> #REF! | L12: =(L10/VLOOKUP(A10,#REF!,4,0))*100 -> #REF! | O12: % GDP | P12: =(P10/VLOOKUP(A10,#REF!,4,0))*100 -> #REF!
A13: Canada | C13: LC bn | D13: =190-85+E13 -> 108.175 | E13: =1.125+2.05 -> 3.175 | F13: Spending measures (CAN $3.2 bn): Support to the health system including for increased testing, vaccine development, medical supplies, mitigation efforts; and greater support for Indigenous communities. | G13: 105 | H13: Spending measures (CAN $105 bn): Income support for firms and people , including payments to workers without access to sick leave and employment insurance, an increase in existing GST tax credits and child care benefits, support to the most vulnerable including through a new Indigenous Community Support Fund, and a firm subsidy equal to 75 percent of employee wages for up to 3 months. Deferral of payments (CAN $85 bn): Liquidity support through temporary interest-free tax deferrals for businesses and self employed, amounting to CAN $55 bn in deferred income taxes and CAN $30 bn in deferred GST/HST and customs duties for imports. | J13: LC bn | K13: 70 | L13: 5 | M13: • Farm Credit Canada will receive support from the government that will allow for an additional CAN $5 bn in lending capacity to producers, agribusinesses, and food processors. | O13: LC bn | P13: 65 | Q13: • Canada Emergency Business Account program will provide up to CAN $25 bn in funds and guarantees for eligible financial institutions to provide interest-free loans to small businesses. • SME Loan and Guarantee program will guarantee up to CAN $40 bn in lending, supported through Export Development Canada and Business Development Bank. | U13: https://www.canada.ca/en/public-health/services/diseases/coronavirus-disease-covid-19.html | V13: $100 million to support federal public health measures such as enhanced surveillance, increased testing at the National Microbiology Laboratory. The package includes $275 million for additional research such as vaccine development, $200 million for federal medical supplies, and support for Indigenous communities and education efforts. $500 million to provinces and territories for critical health care system needs and to support mitigation efforts, including access to testing, equipment and to enhance surveillance and monitoring. $50 million for Public Health Agency of Canada's COVID-19 communications and public education efforts. $2 bn to support diagnostic testing and to purchase ventilators and protective personal equipment, including for bulk purchases with provinces and territories. Personal protective equipment includes things like more masks and face shields, gowns, and hand sanitizer. $50 million has been made available in funding for members of the Next Generation Manufacturing Supercluster to develop and scale-up new, in-demand technologies, equipment, and medical products.
C14: USD bn | D14: =D13/VLOOKUP(A13,#REF!,7,0) -> #REF! | J14: USD bn | L14: =L13/VLOOKUP(A13,#REF!,7,0) -> #REF! | O14: USD bn | P14: =P13/VLOOKUP(A13,#REF!,7,0) -> #REF!
C15: % GDP | D15: =(D13/VLOOKUP(A13,#REF!,4,0))*100 -> #REF! | J15: % GDP | L15: =(L13/VLOOKUP(A13,#REF!,4,0))*100 -> #REF! | O15: % GDP | P15: =(P13/VLOOKUP(A13,#REF!,4,0))*100 -> #REF!
A16: Euro Area/ European Union | C16: LC bn | D16: 37 | E16: 0.05 | F16: Spending measures (€0.05 bn): The European Commission redirected funding of €47.5 million towards research on COVID-19 vaccine development, treatment, and diagnostics. | G16: 37 | H16: Spending measures (€37 bn): • The European Commission announced that the size of the Corona Response Investment Initiative will be raised to €37 bn, to support public investment for hospitals, labor markets, and stressed regions. • The Commission proposed to extend the scope of the EU Solidarity Fund by also including a public health crisis within its scope, in view of mobilizing it if needed for the hardest hit EU member states. Up to €0.8 bn is available in 2020. | J16: LC bn | K16: 1 | O16: LC bn | P16: 1 | Q16: • Redirecting €1 bn from the EU Budget as a guarantee to the European Investment Fund to incentivize banks to provide liquidity to hit SMEs and midcaps. | S16: The European Commission also activated the general escape clause in the EU fiscal rules, which suspends the fiscal adjustment requirements for countries not at their medium-term objective and allow countries to run deficits in excess of 3 percent of GDP. Credit holidays to existing debtors that are negatively affected will be provided.
C17: USD bn | D17: =D16/VLOOKUP(A16,#REF!,6,0) -> #REF! | J17: USD bn | O17: USD bn | P17: =P16/VLOOKUP(A16,#REF!,7,0) -> #REF!
C18: % GDP | D18: =(D16/VLOOKUP(A16,#REF!,4,0))*100 -> #REF! | J18: % GDP | O18: % GDP | P18: =(P16/VLOOKUP(A16,#REF!,4,0))*100 -> #REF!
A19: France | C19: LC bn | D19: =11+5.5 -> 16.5 | E19: 2 | F19: Spending measures (€5.5 bn): Support for streamlining and boosting health insurance for the sick or their caregivers, and higher spending on health supplies . | G19: 9.5 | H19: Spending measures (€11 bn): Subsidies for wages of workers under the reduced-hour scheme and direct financial support to affected SMEs and independent workers. Deferral of payments/advance pay of liabilities (€48.5 bn): • Liquidity support through postponement of social security contributions and tax payment for companies, and rent and utility payments for affected SMEs. • Accelerated refund of tax credits (e.g. CIT and VAT). | J19: LC bn | K19: =P19 -> 312 | O19: LC bn | P19: 312 | Q19: • State guarantees for bank loans to companies (€300 bn). | S19: Liquidity support through postponement of social security contributions and tax payment for companies (€33.5 bn). | U19: https://www.economie.gouv.fr/coronavirus-soutien-entreprises#
C20: USD bn | D20: =D19/VLOOKUP(A19,#REF!,7,0) -> #REF! | J20: USD bn | K20: =P20 -> #REF! | O20: USD bn | P20: =P19/VLOOKUP(A19,#REF!,7,0) -> #REF!
C21: % GDP | D21: =(D19/VLOOKUP(A19,#REF!,4,0))*100 -> #REF! | J21: % GDP | K21: =P21 -> #REF! | O21: % GDP | P21: =(P19/VLOOKUP(A19,#REF!,4,0))*100 -> #REF!
A22: Germany | C22: LC bn | D22: 143 | E22: 11.2 | F22: Spending measures (€11.2 bn): Additional spending on hospital capacity, medical equipment, research, and information campaigns . | G22: =D22-E22 -> 131.8 | H22: Spending measures (€131.8 bn): including grants to hard hit small businesses and self-employed, increased access to childcare and basic social security benefits, and temporary relief to affected tenants. There is also support to firms and households provided through the “Kurzabeit” program, part of which could be considered discretionary because the program parameters have been changed. Deferral of payments: including options for deferring tax payments and reducing prepayments until the year-end without penalties. | J22: LC bn | K22: 1025 | L22: 200 | M22: • An economic stabilization fund (WSF) of €600 bn is setup with three components: (i) €100 bn for government equity investments in significantly affected companies; (ii) €100 bn loan to state development bank KfW for financing affected firms that do not have access to KfW’s existing programs; | O22: LC bn | P22: =825-63 -> 762 | Q22: (iii) €400 bn to provide additional state guarantees to non-financial corporations to alleviate liquidity bottlenecks and support refinancing. • An expansion of the existing KfW-programs, by increasing the guarantee framework for KfW to €822 bn from the current €460 bn. • Total guarantees provided by state governments to be increased by €63 bn. | S22: The government provides options for deferring tax payments and reducing prepayments; while tax penalties will not be levied until the end of this year. | U22: https://www.bundesregierung.de/breg-de/themen/coronavirus
C23: USD bn | D23: =D22/VLOOKUP(A22,#REF!,7,0) -> #REF! | J23: USD bn | L23: =L22/VLOOKUP(A22,#REF!,7,0) -> #REF! | O23: USD bn | P23: =P22/VLOOKUP(A22,#REF!,7,0) -> #REF!
C24: % GDP | D24: =(D22/VLOOKUP(A22,#REF!,4,0))*100 -> #REF! | J24: % GDP | L24: =(L22/VLOOKUP(A22,#REF!,4,0))*100 -> #REF! | O24: % GDP | P24: =(P22/VLOOKUP(A22,#REF!,4,0))*100 -> #REF!
A25: Italy | C25: LC bn | D25: 20 | E25: 3.2 | F25: Spending measures (€3.2 bn): including on medical equipment and staff, as well as civil protection. | G25: 10.3 | H25: Spending measures (€16.7 bn): including Income support to laid-off workers and the self-employed by broadening the wage supplementation fund (€10.3). Deferral of payments: including postponement of certain tax and social security payments for SMEs, as well as taxes and utility bill payments in most affected municipalities. | J25: LC bn | K25: 65.1 | O25: LC bn | P25: 530 | Q25: • SME loans subject to moratorium (€70 bn). The guarantee covers up to 30% of the value. • Enhancement of the SME Guarantee Fund from €40 bn to over €100 bn. • State guarantee of €0.5 bn to the state development bank—Cassa Deposit e Prestiti—to support lending and liquidity to banks to enable them to finance medium to large enterprises. • All business, the guarantee (€200) will cover between 70% and 90% of the amount financed. • Co-insurance scheme for exporters (€200). | S25: Other measures to support businesses, including tax deferrals and postponement of utility bill payments in most affected municipalities (€6.4 bn), a moratorium on loan repayments for households and SMEs, including on mortgages and overdrafts (€220 bn), incentives for financial and non-financial companies in the form of Deferred Tax Activities | U25: http://www.mef.gov.it/en/inevidenza/Protect-health-support-the-economy-preserve-employment-levels-and-incomes-00001/
C26: USD bn | D26: =D25/VLOOKUP(A25,#REF!,7,0) -> #REF! | J26: USD bn | O26: USD bn | P26: =P25/VLOOKUP(A25,#REF!,7,0) -> #REF! | U26: http://www.governo.it/it/articolo/comunicato-stampa-del-consiglio-dei-ministri-n-39/14417
C27: % GDP | D27: =(D25/VLOOKUP(A25,#REF!,4,0))*100 -> #REF! | J27: % GDP | O27: % GDP | P27: =(P25/VLOOKUP(A25,#REF!,4,0))*100 -> #REF!
A28: Japan | C28: LC bn /3 | D28: 53000 | E28: 62 | F28: Spending measures: - Transfers to local governments which could be spent on COVID-19 related measures (JPY 1.1 trillion) - Production, procurement and distribution of critical equipment such as masks and ventilators (JPY 0.2 trillion) - Other health-related measures (Support for development of vaccines, etc.) | G28: =383-78 -> 305 | H28: Spending measures: - Cash handout to affected households (JPY 300,000 per eligible household) (JPY 4.0 trillion). - Lump-sum transfer to affected firms (JPY 2 million per firm for SMEs, JPY 1 million for the self-employed) (JPY 2.3 trillion). - Subsidies for public/private financial institutions' lending (JPY 3.8 trillion) - Measures to accelerate recovery and rebuild resilient economic structure such as incentive measures for consumption in affected service sectors and infrastructure investments (in the post-containment phase) (JPY 10.8 trillion). Revenue measures: - Reduction of property tax, expansion of the loss carry-back program, etc. Deferral of payment: - Deferral of payment of taxes and social security premiums by affected firms and households for one year. | J28: LC bn | L28: 53200 | M28: - The government boosted special financing and guarantees primarily for micro, small and medium-sized business operators affected by COVID-19 through the Japan Finance Corporation and other institutions. (JPY 45 trillion) - Other off-budget operations using the Development Bank of Japan and other agencies (primarily for infrastructure projects in the post-containment phase) (JPY 8 trillion) | O28: LC bn | P28: 2000 | Q28: - Guarantees on bonds/borrowing by the Development Bank of Japan and the Japan Finance Corporation (JPY 1 trillion) - Guarantees on external bonds issued by the Development Bank of Japan and Japan Bank for International Cooperation (JPY 1 trillion) | S28: Japan has made a contribution of SDR14 million (US$19 million) to the IMF’s Catastrophe Containment and Relief Trust. The deadline for tax return filing and payment of personal income tax, gift tax, and consumption tax (for the self-employed) was extended from mid-March to mid-April; tax payments for people and businesses negatively impacted by the COVID-19 outbreak are deferred. In addition, the ¥26 trillion (about 4.8 percent of GDP) December 2019 stimulus package is being used to offset the adverse impact of COVID-19 on the economy as well as counter the economic slowdown.
C29: USD bn | D29: =D28/VLOOKUP(A28,#REF!,7,0) -> #REF! | J29: USD bn | L29: =L28/VLOOKUP(A28,#REF!,7,0) -> #REF! | O29: USD bn | P29: =P28/VLOOKUP(A28,#REF!,7,0) -> #REF!
C30: % GDP | D30: =(D28/VLOOKUP(A28,#REF!,4,0))*100 -> #REF! | J30: % GDP | L30: =(L28/VLOOKUP(A28,#REF!,4,0))*100 -> #REF! | O30: % GDP | P30: =(P28/VLOOKUP(A28,#REF!,4,0))*100 -> #REF!
A31: Korea | C31: LC bn | D31: 26000 | E31: 2500 | F31: Spending measures (KRW 2.5 tn): Epidemic prevention and treatment, support for medical institutions and quarantined households. | G31: 23500 | H31: Spending measures (KRW 21 tn): • Support for households, including employment retention support, consumption coupons for the poor, emergency family care support, and cash transfers to bottom 70% of households. • Support for local communities, including local gift certificates and local government grants for infection prevention. Support for firms, including for wages and rent for small merchants. Revenue measures (KRW 2.5 tn): Consumption tax cut for auto purchases; temporary income tax cuts for landlords who reduce commercial rents; VAT reduction for the self-employed; social security contribution cut for households. Deferral of payments: Tax deferral covering a broad range of taxes for small businesses and the self-employed in medical, tourism, performance, hospitality, and other affected sectors; social security contribution payment deferral for households. | J31: LC bn | L31: 70000 | M31: • Expand lending of both state-owned and commercial banks to SMEs, small merchants, mid-sized firms, and large companies (the latter on a case-by-case basis) including emergency lending, partial and full guarantees, and collateralization of loan obligations. | O31: LC bn | S31: Tax payment deferral covering a broad range of taxes for small businesses and the self-employed in medical, tourism, performance, hospitality, and other affected sectors. Social security contribution payment deferral for households | U31: https://english.moef.go.kr/pc/selectTbPressCenterDtl.do?boardCd=N0001&seq=4860
C32: USD bn | D32: =D31/VLOOKUP(A31,#REF!,7,0) -> #REF! | J32: USD bn | L32: =L31/VLOOKUP(A31,#REF!,7,0) -> #REF! | O32: USD bn
C33: % GDP | D33: =(D31/VLOOKUP(A31,#REF!,4,0))*100 -> #REF! | J33: % GDP | L33: =(L31/VLOOKUP(A31,#REF!,4,0))*100 -> #REF! | O33: % GDP
A34: Spain | C34: LC bn | D34: 13.9 | E34: 3.9 | F34: Spending measures (€3.9 bn): • Budget support from the contingency fund to the Ministry of Health (€1 bn); advance transfer to the regions for the regional health services (€2.8 bn); additional funding for research related to the development of drugs and vaccines (€0.1 bn). • An emergency management process for the procurement of all goods and services needed by the public sector to implement any measure to address the pandemic. | G34: =8.9-3.9 -> 5 | H34: Spending measures (€10 bn depending on the usage and duration of the measures and could be higher): · Entitlement of unemployment benefit for workers temporarily laid off under the Temporary Employment Adjustment Schemes owing to the pandemic, with no requirement for prior minimum contribution or reduction of accumulated entitlement. · Increased sick pay for COVID-19 infected workers or those quarantined, from 60 to 75 percent of the regulatory base, paid by the Social Security budget; allowance for self-employed workers affected. · A temporary subsidy for affected household employees and for temporary workers whose contract expires during the state of emergency and are not entitled to collect unemployment benefits; and additional provision of assistance to dependents. · Transfer to autonomous communities funding meals for children affected by the school closure; new rental assistance programs for certain vulnerable renters; and extension of the social benefit for energy provision. Revenue measures: • Exemptions of social contributions for affected companies that maintain employment, and a 50 percent exemption from employer’s social security contributions for workers with permanent discontinuous contracts in the tourism sector and related activities (from February to June 2020). • A 6-month suspension of social security contributions for the self-employed (for April-June), subject to a condition of continued activity in May and June; and more flexibility for workers to access savings from their pension plans. Deferral of payments of taxes for small and medium enterprises and self-employed for six months (€14 bn). | J34: LC bn | L34: 10 | M34: • Additional funding for the Instituto de Crédito Official (ICO) credit lines (€10 bn) | O34: LC bn | P34: 102 | Q34: • The government has approved a line of public guarantees and guarantees worth up to €100 bn. An additional guarantees of €2 bn for exporters through the Spanish Export Insurance Credit Company; some guarantees for loan maturity extensions to farmers using the special 2017 drought credit lines. | U34: https://www.lamoncloa.gob.es/consejodeministros/resumenes/Paginas/2020/170320-pg-consejo.aspx | V34: =849+223 -> 1072
C35: USD bn | D35: =D34/VLOOKUP(A34,#REF!,7,0) -> #REF! | J35: USD bn | L35: =L34/#REF! -> #REF! | O35: USD bn | P35: =P34/VLOOKUP(A34,#REF!,7,0) -> #REF!
C36: % GDP | D36: =(D34/VLOOKUP(A34,#REF!,4,0))*100 -> #REF! | J36: % GDP | L36: =L34/#REF!*100 -> #REF! | O36: % GDP | P36: =(P34/VLOOKUP(A34,#REF!,4,0))*100 -> #REF!
A37: United Kingdom | C37: LC bn | D37: 65 | E37: 5 | F37: Spending measures (£5 bn): • Additional funding for the National Health Service, including to expand the number of hospital beds, medical staff and equipment. Revenue measures: • Waiver of VAT and duties on critical medical imports. | G37: 60 | H37: Spending measures (£60 bn): • Income support, including a Job Retention Scheme to subsidize furloughed employees' wages and firms' social security contributions; an income support scheme for the self-employed; direct grants for small firms in the most-affected sectors; compensation for paid sick leave; strengthening the social safety net to support vulnerable people (by nearly £7 bn) under the Universal Credit and other benefit schemes; support for renters by increasing the Local Housing Allowance. • International support, with £150 million made available to the IMF’s Catastrophe Containment and Relief Trust. Revenue measures: property tax (business rate) holiday for firms in affected sectors. Deferral of payments: Liquidity support, including deferral of income tax for the self employed and VAT payments; Time to Pay arrangements (tax debt restructuring) for businesses and individuals. | J37: LC bn | K37: 330 | L37: 330 | M37: • The Coronavirus Business Interruption Loan Scheme (CBILS) launched with the British Business Bank will support SMEs with access to loans of up to £5 million and for up to 6 years. The government will cover the first 12 months of interest payments and any lender-levied fees. • Under the new Covid-19 Corporate Financing Facility (CCFF), the Bank of England will buy short term debt from larger companies. The combined size of the CBILS and CCCF schemes is £330 bn (15% of GDP). | O37: LC bn | Q37: • Under CBILS, the government will provide lenders with a guarantee of 80% on each loan. • The Coronavirus Large Business Interruption Loan Scheme (CLBILS) will provide a government guarantee of 80 percent to enable banks to make loans of up to £25 million to firms with an annual turnover of between £45 million and £500 million. | S37: Deferral of income tax for the self employed and VAT payments; property tax (business rate) holiday for firms in most affected sectors, Time to Pay arrangements (tax debt restructuring) for businesses and individuals. To support the international response, the government has made available £150 million to the IMF’s Catastrophe Containment and Relief Trust. | U37: https://www.gov.uk/government/publications/guidance-to-employers-and-businesses-about-covid-19/covid-19-support-for-businesses
C38: USD bn | D38: =D37/VLOOKUP(A37,#REF!,7,0) -> #REF! | J38: USD bn | L38: =L37/VLOOKUP(A37,#REF!,7,0) -> #REF! | O38: USD bn
C39: % GDP | D39: =(D37/VLOOKUP(A37,#REF!,4,0))*100 -> #REF! | J39: % GDP | L39: =(L37/VLOOKUP(A37,#REF!,4,0))*100 -> #REF! | O39: % GDP
A40: United States | C40: LC bn | D40: 1395 | E40: 141 | F40: Spending measures: • Coronavirus Preparedness and Response Supplemental Appropriations Act (March 6, 2020) approved with $8.3bn for treatments, drugs, and public health measures, of which US$1.25 bn is included for international assistance. • Coronavirus Aid, Relief, and Economic Security Act (March 27, 2020) approved $100 bn for hospitals, $1.32 bn for community centers, $4.3 bn for the Center of Disease Control, and $27 bn for vaccine development. | G40: =D40-E40 -> 1254 | H40: Spending measures: • Families First Coronavirus Response Act (March 16, 2020) includes an estimated $83.3 bn for 2 weeks paid sick leave, up to 3 months emergency leave for those infected (at 2/3 pay), food assistance, free virus testing; and federal transfers to states for Medicaid (increased by 6.2% during emergency period); and $1 bn in expanded unemployment insurance. • Coronavirus Aid, Relief, and Economic Security Act (March 27, 2020) includes extended unemployment insurance payments ($250 bn); transfers to state and local governments ($150 bn), food assistance ($24 bn), education funding ($30 bn), transit funding ($25 bn). Revenue measures: • Tax rebates ($250 bn) of $1,200 for singles/$2,400 for married couples filing jointly and $500 per qualifying child, employee retention tax credit ($50 bn). Deferral of payments: • IRS extended income tax filing deadline by 90 days; employers' payroll taxes are delayed to 2021 and 2022. | J40: LC bn | K40: 859 | L40: 859 | M40: • Coronavirus Aid, Relief, and Economic Security Act (March 27, 2020) includes $510 bn in loans and loan guarantees for large businesses, $349 bn in loans for small businesses. | O40: LC bn | S40: IRS extended income tax filing deadline by 90 days; Delay of employers' payroll taxes to 2021 and 2022
C41: USD bn | D41: =D40/VLOOKUP(A40,#REF!,7,0) -> #REF! | J41: USD bn | L41: =L40/VLOOKUP(A40,#REF!,7,0) -> #REF! | O41: USD bn
C42: % GDP | D42: =(D40/VLOOKUP(A40,#REF!,4,0))*100 -> #REF! | J42: % GDP | L42: =(L40/VLOOKUP(A40,#REF!,4,0))*100 -> #REF! | O42: % GDP
A44: G20 emerging market economies
A45: Argentina | C45: LC bn | D45: 350 | F45: Spending measures: • Budget increase for Health Ministry, including for improvements in virus diagnostics, purchases of hospital equipment; and construction of temporary emergency treatment centers. | G45: 200 | H45: Spending measures (ARS $290 bn): • Support for workers and vulnerable groups, including through increased transfers to poor families, increased social security benefits (especially to low-income beneficiaries), higher unemployment insurance benefits, and payments to minimum-wage workers. • Demand support, including spending on public works. Revenue measures (AR$ 60bn): • Support for hard-hit sectors, including an exemption from social security contributions. Deferral of payments: • Extension of the grace period of repayment of loans granted by the Social Security to retirees and beneficiaries of non-contributory pensions. | J45: LC bn | M45: • Support for hard-hit sectors, including subsidized loans for construction activities. | O45: LC bn | P45: 350 | Q45: • Credit guarantees will be provided to banks’ lending to micro, small and medium enterprises (SMEs) for the production of foods and basic supplies. | U45: =300/D46*350 -> 19444.444
C46: USD bn /4 | D46: 5.4 | J46: USD bn | O46: USD bn 4/ | P46: 5.4 | S46: Credit lines amounting to ARS 350 billion will be provided to finance wage payments and production inputs of small and medium sized industries and commerce. The funds will come almost entirely (ARS 320 billion) from local banks. The BCRA will announce in coming days a specific regulation facilitating this.
C47: % GDP | D47: =(D45/VLOOKUP("Argentina",#REF!,4,0))*100 -> #REF! | J47: % GDP | O47: % GDP | P47: =(P45/VLOOKUP("Argentina",#REF!,4,0))*100 -> #REF!
A48: Brazil | C48: LC bn | D48: 205 | E48: 20 | F48: Spending measures: • Additional funding for the public health system to fight the disease (R$ 8 bn), including from the reallocation of funds originating from mandatory car insurance (R$ 4.5 bn). • Access to 20 percent of the Health Guarantee Fund resources (about US$ 2 bn) to provide the private health insurance companies with funding for investment in assistance infrastructure. Revenue measures: Temporary tax cuts/exemption on health products to fight covid-19. | H48: Spending measures: • Temporary income support to vulnerable households (2 percent of GDP), including advance social benefit payments to pensioners and wage bonuses to low income workers, expanding the Bolsa Familia program with the inclusion of over 1 million more beneficiaries, introducing a new “Covid-19” voucher payment of BRL600 a month (USD40) to 30 million poor families for the next three months, partial unemployment insurance benefits for workers with reduced hours or wages, reallocating resources to the workers’ severance fund (FGTS) to facilitate new withdrawals. Deferral of payments: Payment of employers’ contributions to the FGTS and small business taxes will be postponed by 3 months. Small businesses will also be given a temporary reduction in non FGTS type of employer contributions. These measures will add up to 0.8 percent of GDP. | J48: LC bn | K48: 264 | L48: 230 | M48: • Expanded credit line for SMEs to hire new workers and maintain existing employment (R $5 bn). • Temporary suspension of debt service payments from state governments to the federal government (R $12.6 bn). • Public banks announced credit lines totaling R $212 bn. | O48: LC bn | P48: 34 | Q48: • Government will back (assuming 85% of the risk) a R $40 bn credit line operated by private banks for SMEs, specifically to cover payroll costs. Interest rates are capped at the policy rate (3.75%). | S48: Payment of employers’ contributions to the FGTS and small business taxes will be postponed by 3 months.
C49: USD bn | D49: =D48/VLOOKUP(A48,#REF!,7,0) -> #REF! | J49: USD bn | L49: =L48/VLOOKUP(A48,#REF!,7,0) -> #REF! | O49: USD bn | P49: =P48/VLOOKUP(A48,#REF!,7,0) -> #REF!
C50: % GDP | D50: =(D48/VLOOKUP(A48,#REF!,4,0))*100 -> #REF! | J50: % GDP | L50: =(L48/VLOOKUP(A48,#REF!,4,0))*100 -> #REF! | O50: % GDP | P50: =(P48/VLOOKUP(A48,#REF!,4,0))*100 -> #REF!
A51: China | C51: LC bn | D51: 2560 | E51: 110 | F51: Spending measures: • Expenditure to improve epidemic prevention and control and the national public health emergency management system. Revenue measures: • Tariffs were exempted for the import of medicines, medical supplies, and other vehicles used to fight against the outbreak. | G51: 2390 | H51: Spending measures: • Front-loaded government spending possibly on infrastructure and through issuance of special local government bonds. • A refund of 2019 unemployment insurance premiums for companies that minimize layoffs . Revenue measures: • VAT exemptions for a wide range of goods and services related to epidemic control, as well as for small taxpayers in Hubei; and VAT rate cut from 3% to 1% in other regions for 3 months. • Corporate income tax relief for businesses in affected sectors through a longer tax loss carryover period to 8 years or one-off 100 percent expensing deduction for investment in equipment to expand production capacity. • Social security contributions by employers in Hubei province and SMEs (50 percent for large firms) in the other provinces are waived until June (April). Deferral of payments: Firms are also allowed to defer their social security payments by 6 months, and the due date for contributing to the “housing provident fund” is extended to end-June. | J51: LC bn | O51: LC bn | S51: Road tolls were exempted; some service fees charged by airports and railways were cut; and the price of electricity was cut by 5% with an estimated cost reduction of 60 bn RMB Railway logistic fee lowered by 50% until Jun 30 with an estimated cost of RMB 350 million. From Mar 1 to Jun 30, the port construction fee will be exempted and fees such as ‘harbor dues on cargo’ will be cut by 20%.
C52: USD bn | D52: =D51/VLOOKUP(A51,#REF!,7,0) -> #REF! | J52: USD bn | O52: USD bn
C53: % GDP | D53: =(D51/VLOOKUP(A51,#REF!,4,0))*100 -> #REF! | J53: % GDP | O53: % GDP
A54: India | C54: LC bn | D54: 1570 | E54: 150 | F54: Spending measures (Rs 0.15 tn): • Additional spending on health infrastructure, including for COVID-19 testing facilities, personal protective equipment, isolation beds, ICU beds, and ventilators. | G54: 1700 | H54: Spending measures (Rs 1.42 tn): • The central government has announced a package that provides insurance coverage for workers in the healthcare sector, substantial in-kind (food; cooking gas) and cash transfers, as well as wage support to poor households (in some cases for those still working, and in other cases by easing the criteria for receiving benefits in the event of job loss). These measures sum to about 0.6 percent of GDP, per IMF staff estimates. Increases in fuel excise taxes announced in early March (0.2 percent of GDP) will partly finance these measures. • The state of Kerala has announced a package (0.1 percent of national GDP), including Rs 110bn of arrears paid, Rs 14bn advanced pensions, Rs 20bn loans to women, Rs 20bn front-loaded rural jobs, 2 times Rs 1000 per month to 10mn poor without pensions. Numerous other states have also announced stimulus packages, mainly in the form of cash- and in-kind transfers to poor households (cumulatively about 0.1 percent of national GDP). • The central government has directed states to make allocations to low-wage construction workers from an existing pool of resources (0.2 percent of GDP). Deferral of payments: • Extension of income tax filing deadline (3 months); reduction of penalty for late payments; date for filing fiscal year 18/19 GST tax liability extended (3 months); other miscellaneous relaxation of tax regulatory/administrative requirements. | J54: LC bn | O54: LC bn | U54: https://pib.gov.in/PressReleseDetail.aspx?PRID=1607911
C55: USD bn | D55: =D54/VLOOKUP(A54,#REF!,7,0) -> #REF! | E55: 0.1 | G55: 0.8 | J55: USD bn | O55: USD bn
C56: % GDP | D56: =(D54/VLOOKUP(A54,#REF!,4,0))*100 -> #REF! | J56: % GDP | O56: % GDP
A57: Indonesia | C57: LC bn | D57: 289000 | E57: 76000 | F57: Spending measures (IDR 76 tn): • IDR 1 trillion initially allocated to cover various outlays, including personal protective equipment, enhanced surveillance at entry gates to Indonesia, hospital treatment, and hospital infrastructure. • On March 31, 2020, the government announced a third larger fiscal package, including IDR75 trillion (0.5 percent of GDP) for health spending to boost testing and treatment capability, including the acquisition of personal protective equipment, test kits, ventilators, and the upgrade of 132 referral hospitals to handle COVID-19 patients. | G57: 213000 | H57: Spending measures: • The first fiscal package of IDR10.3 trillion comprises support to the tourism sector (tax cuts and discounts on airplane tickets and jet-fuel) and to low-income households (social assistance and subsidy for home buyers) starting from March 1 for most measures. • The third fiscal package includes IDR110 trillion (0.7 percent of GDP) additional social assistance spending, including increasing benefits and coverage of existing social safety nets such as food aid and unemployment benefits, and electricity subsidies. Revenue measures: • Tax cuts for the tourism sector. • The second fiscal package of IDR33.2 trillion includes income tax exemptions to workers in the industrial sectors (with an income ceiling) and support to businesses through delayed payments for income tax and acceleration in VAT refund from April to September. • The third package also includes various tax reliefs and incentives, including exemption and reduction of income taxes (with an income ceiling) and a reduction of the corporate income tax from 25 percent to 22 percent. | J57: LC bn | O57: LC bn | P57: 150000 | Q57: The third fiscal package includes IDR 150 trillion (0.9 percent of GDP) financing for a national economic program, including to support credit guarantees for the private sector.
C58: USD bn | D58: =D57/VLOOKUP(A57,#REF!,7,0) -> #REF! | J58: USD bn | O58: USD bn | P58: =P57/#REF! -> #REF!
C59: % GDP | D59: =(D57/VLOOKUP(A57,#REF!,4,0))*100 -> #REF! | J59: % GDP | O59: % GDP | P59: =P57/#REF!*100 -> #REF! | S59: The first package (10.3), second package (22.9) and tax and expenditure measures from the third package (255.1). How the 150 trillion from the third package will be used is not fully clear yet (, but most likely in the form of liquid support for firms (thus below the line in the budget).
A60: Mexico | C60: LC bn | D60: 180 | F60: Spending measures: Set-up a Health Emergency Fund to request additional resources from Congress, that could reach up to 180 bn pesos (0.7 percent of 2019 GDP). | H60: Advance pay of liabilities: · Social pension and disability payments have been frontloaded by four months. · Procurement processes and VAT refunds are to be accelerated. | J60: LC bn | L60: 75 | M60: • Small- and medium-scale enterprises (SMEs) could receive up to 25 bn pesos (0.1 percent of GDP) in loans. • Development banks could provide liquidity support of about 0.2 percent of GDP | O60: LC bn | S60: At the state-level, several state governments have announced support, including deferral of tax payments or tax holidays. | U60: http://www5.diputados.gob.mx/index.php/esl/Comunicacion/Boletines/2020/Marzo/18/3509-Aprueban-crear-el-Fondo-para-la-Prevencion-y-Atencion-de-Emergencias
C61: USD bn | D61: =D60/VLOOKUP(A60,#REF!,7,0) -> #REF! | J61: USD bn | L61: =L60/VLOOKUP(A60,#REF!,7,0) -> #REF! | O61: USD bn
C62: % GDP | D62: =(D60/VLOOKUP(A60,#REF!,4,0))*100 -> #REF! | J62: % GDP | L62: =(L60/VLOOKUP(A60,#REF!,4,0))*100 -> #REF! | O62: % GDP
A63: Russia | C63: LC bn | D63: 900 | E63: 78.4 | F63: Spending measures: • Increased salaries for medical staff, and also for health and safety inspectors (staff of the Federal Service for Surveillance on Consumer Rights Protection and Human Wellbeing). • Bonus fund of RUB 11.8 bn for medical staff dealing with COVID-19. • Over RUB 23 bn from the government's reserve fund disbursed for public procurement of coronavirus-related supplies. • The government allocated RUB 8.8 bn to the Ministry of Defense to construct 16 infection hospitals for military staff. • The government disbursed RUB 1.4 bn from its reserve fund for R&D on diagnostics and prevention of COVID-19. • The government allocated RUB 33.4 bn to 77 regions for additional Coronavirus beds and equipment. | H63: Spending measures: • Quarantined or self-isolating individuals to receive sick leave benefits from the Social Insurance Fund. • Interest rate subsidies for SMEs. • All children up to 3 years of age in families eligible for maternity capital to receive an additional RUB 5,000 for 3 months; earlier announced expansion of child benefits to children aged 3-7 to start in June, rather than July. • Sick leave pay to equal at least the minimum wage until the end of 2020. • Cap on unemployment benefits raised to the minimum wage until the end of 2020. Revenue measures: • Social contributions on wages in excess of the minimum wage by SMEs reduced from 30 to 15 percent, permanently. • Tourism companies not to pay contributions to the tourist sector reserve fund. Deferral of payments: • Tax holiday until May 1 for SMEs and affected industries (tourism, aviation, sports, art, culture, cinema). • 3-month grace periods for SME payments of social contributions. • Tax holiday for 6 months for all taxes (except VAT) for all SMEs in affected sectors. | J63: LC bn | L63: 570 | M63: • Subsidized and guaranteed loans for SMEs, retailers, and distributors. • Government loans to assist debt restructuring by regions (RUB 70 bn). • Recapitalization of leasing firms due to potential problems of their clients in the transportation sector. • The Central Bank of Russia (CBR) has put in place, a new lending facility with a refinancing limit of 500 bn rubles, with a view to shoring up SME lending. Up to 150 bn rubles will be allocated to support bank lending to SMEs to ensure the uninterrupted fulfillment of their obligation to pay wages to their staff. | O63: LC bn
C64: USD bn | D64: =D63/VLOOKUP(A63,#REF!,7,0) -> #REF! | J64: USD bn | L64: =L63/VLOOKUP(A63,#REF!,7,0) -> #REF! | O64: USD bn
C65: % GDP | D65: =(D63/VLOOKUP(A63,#REF!,4,0))*100 -> #REF! | J65: % GDP | L65: =(L63/VLOOKUP(A63,#REF!,4,0))*100 -> #REF! | O65: % GDP
A66: Saudi Arabia | C66: LC bn | D66: n.a. | E66: 10 | F66: Spending measures: • Budget reallocation within the Ministry of Health budget for emergency spending to fight COVID19. | H66: Spending reallocation from lower priority areas (SAR 50 bn, 1.9 percent of GDP) Deferral of payments: • SAR 48bn for deferred declaration & payment of taxes for 3 months, waiver of customs duties (30 days to 3 months), waiver of expat fees for 3 months; and waiver of municipal fees on companies for 3 months. | J66: LC bn | K66: 22 | L66: 22 | M66: • Liquidity support provided by the National Development Funds (NDF): SAR 22 bn (0.85 percent of GDP) distributed as follows: (i) loan rescheduling/restructuring and different loan programs to SMEs: SAR13 bn (0.5 percent of GDP). (ii) support to employment programs in the private sector: SAR 5 bn (0.2 percent of GDP). (iii) social loans to families with low incomes: SAR4 bn (0.15 percent of GDP). | O66: LC bn | U66: https://www.mof.gov.sa/en/MediaCenter/news/Pages/News_20032020.aspx
C67: USD bn | J67: USD bn | L67: =L66/VLOOKUP(A66,#REF!,7,0) -> #REF! | O67: USD bn
C68: % GDP | J68: % GDP | L68: =(L66/VLOOKUP(A66,#REF!,4,0))*100 -> #REF! | O68: % GDP
A69: South Africa | C69: LC bn | D69: n.a. | F69: Revenue measures: Tax exemptions for essential sanitary products during the pandemic (e.g. hand sanitizers). | H69: Spending measures: Allocations from the Departments of Small Business Development and the Department of Tourism of R700 million made available to assist small and medium enterprises that are in distress including in tourism and hospitality sector. Revenue measures: Tax subsidy of up to R500 per month for the next four months for those private sector employees earning below R6,500 under the Employment Tax Incentive. Deferral of payments: • Revenue authority (SARS) to accelerate reimbursements and tax credits, changing from twice yearly payments to monthly. • Firms with less than ZAR50 million turnover will be allowed to defer 20 percent of PAYE liabilities for four months and an unknown portion of corporate income tax payments for six months. | J69: LC bn | L69: 30.15 | M69: • South Africa’s extra-budgetary Unemployment Insurance Fund made R30 bn available to support unemployed workers. The money will compensate workers for layoffs of as long as three months if companies are struggling to stay profitable. • A Solidarity Fund, with an initial government transfer of R150 million. Most of the funds are expected to come from private donations. • Industrial funding package to fast-track financing for companies including those that are critical in the fight against Covid-19 provided by the Industrial Development Corporation (IDC). | O69: LC bn
C70: USD bn | J70: USD bn | L70: =L69/VLOOKUP(A69,#REF!,7,0) -> #REF! | O70: USD bn
C71: % GDP | J71: % GDP | L71: =(L69/VLOOKUP(A69,#REF!,4,0))*100 -> #REF! | O71: % GDP
A72: Turkey | C72: LC bn | D72: 75 | G72: 75 | H72: Spending measures: • Raising minimum pension and cash assistance to families in need; direct support to Turkish Airlines and other affected entities; and income support to employees in work places that suspend activities (short-term work allowance). Deferral of payments: • Reduced/postponed taxes for affected industries (particularly tourism); and extension of personal and corporate income tax filing deadlines. | J72: LC bn | K72: 25 | M72: • Lending by public banks. | O72: LC bn | P72: 25 | Q72: • Doubling the size of the credit guarantee fund from TL25 to TL50 bn.
C73: USD bn | D73: =D72/VLOOKUP(A72,#REF!,7,0) -> #REF! | J73: USD bn | O73: USD bn | P73: =P72/VLOOKUP(A72,#REF!,7,0) -> #REF!
C74: % GDP | D74: =(D72/VLOOKUP(A72,#REF!,4,0))*100 -> #REF! | J74: % GDP | O74: % GDP | P74: =(P72/VLOOKUP(A72,#REF!,4,0))*100 -> #REF!
A76: Selected advanced economies outside the G20
A77: Denmark | C77: LC bn | D77: 60 | F77: Part of the increased spending will finance additional health care needs. | H77: Spending measures: • Temporary compensation scheme for companies’ fixed costs between 100% and 25% depending on severity of impact. Temporary compensation scheme for self-employed and freelancers that are experiencing more than a 30% decrease in turnover will be entitled to a 75% compensation (max 23,000 DKK per month). • Introduced a compensation scheme for cancelling or postponing major business events owing to the pandemic. • Temporary wage subsidies at levels between 75 and 90 percent of workers' salary and reimbursement for sickness benefits. Deferral of payments: • Temporary postponement (4 months) of payment deadlines for withholding tax (A-tax) and labor market contributions, and for provisional tax paid by self-employed business (B-tax); one month deferral of VAT for businesses. VAT for small firms is extended from 6 months to 12 months in 2020, while the extension for medium-sized enterprises is from 3 months to 6 months for the first half of 2020. | J77: LC bn | O77: LC bn | P77: 65 | Q77: • The government will guarantee 70 percent of new loan value to large companies that can demonstrate a fall in turnover over more than 30 percent; it guarantees 70 percent of new bank loan values to SMEs that have operating profits fallen by more than 30 percent. • It provides a credit guarantee for Scandinavian Airlines (SAS). | S77: Another 2.5 percent of GDP in countercyclical support is expected to come through the stronger automatic stabilizers—including from weaker tax receipts and higher social benefits. | U77: https://virksomhedsguiden.dk/erhvervsfremme/content/temaer/coronavirus_og_din_virksomhed/artikler/garantiordning-for-nye-laan/3b45ceac-2e72-477c-9fe1-e1d119c23b49/
C78: USD bn | D78: =D77/VLOOKUP(A77,#REF!,7,0) -> #REF! | J78: USD bn | O78: USD bn | P78: =P77/VLOOKUP(A77,#REF!,7,0) -> #REF! | U78: https://virksomhedsguiden.dk/erhvervsfremme/content/temaer/coronavirus_og_din_virksomhed/artikler/udvidet-ret-til-arbejdsgiverrefusionsygedagpenge-til-selvstaendige/2512f642-74bb-478e-9ffa-af2f6aeb321f/
C79: % GDP | D79: =(D77/VLOOKUP(A77,#REF!,4,0))*100 -> #REF! | J79: % GDP | O79: % GDP | P79: =(P77/VLOOKUP(A77,#REF!,4,0))*100 -> #REF!
A80: Finland | C80: LC bn | D80: =1.5+2.4 -> 3.9 | E80: 0.2 | F80: Spending measures (0.1 percent of GDP): for healthcare and testing, protection and medical equipment, public safety and border controls, and research on the coronavirus epidemic, in particular to develop methods for rapid diagnostics and vaccines and timely decision-making. • Finland contributes €5 million to international efforts to develop a vaccine. | G80: =1.5-0.2 -> 1.3 | H80: Spending measures (1.1 percent of GDP): Increase in Business Finland grant authorization for SMEs. Unemployment insurance is expanded by €2.4 bn. Revenue measures (0.4 percent of GDP): Reduce pension contributions through the remainder of 2020 (€900 million). Deferral of payments: Deferral of tax and pension payments for 3 months are expected to provide additional short-run relief of €4.5 bn. | J80: LC bn | L80: 1 | M80: The State Pension Fund will invest in commercial paper (€1 bn). | O80: LC bn | P80: 10.6 | Q80: Finland’s Export Credit Agency expands its lending and guarantee capacity to SMEs by €10 bn and the government will increase its coverage of the agency’s credit and guarantee losses from 50 to 80 percent. State guarantee for Finnair (€ 0.6 bn). | S80: Deferral of tax and pension payments for 3 months are expected to provide additional short-run relief of €3-4.5 bn. Automatic stabilizers are expected to increase the fiscal deficit significantly, including through an expansion of the coverage of existing unemployment benefits. | U80: https://valtioneuvosto.fi/artikkeli/-/asset_publisher/10616/hallitus-antoi-eduskunnalle-lisatalousarvioesityksen-koronaviruksen-vuoksi
C81: USD bn | D81: =D80/VLOOKUP(A80,#REF!,7,0) -> #REF! | J81: USD bn | L81: =L80/VLOOKUP(A80,#REF!,7,0) -> #REF! | O81: USD bn | P81: =P80/VLOOKUP(A80,#REF!,7,0) -> #REF!
C82: % GDP | D82: =(D80/VLOOKUP(A80,#REF!,4,0))*100 -> #REF! | J82: % GDP | L82: =(L80/VLOOKUP(A80,#REF!,4,0))*100 -> #REF! | O82: % GDP | P82: =(P80/VLOOKUP(A80,#REF!,4,0))*100 -> #REF! | S82: Short-run relief of €3-4.5 bn (1.9 percent of GDP).
A83: The Netherlands | C83: LC bn | D83: 20 | H83: Spending measures (€10-20bn or more depending on take up): · Compensation of up to 90 percent of labor costs for companies expecting a reduction in revenues of 20 percent or more; compensation for affected sectors (for example, hospitality services and travel). · Scaling up of the short-time working scheme (unemployment benefit compensation available to companies needing to reduce their staff by at least 20 percent). · Income support for self-proprietorships and self-employed (administered at municipal level) for a period of three months through expedited procedures. Deferral of payments (€35–45 bn): Companies can defer tax payments without penalties, and calculate provisional taxes on the basis of expected reduced activity levels. | J83: LC bn | O83: LC bn | P83: n.a. | Q83: The loan guarantee program for SMEs (especially those affected by the outbreak) is expanded to cover up to 75 percent of total loan, with maturity of 1 year or less. | S83: Tax deferrals for companies that are in financial distress. Temporary suspension of penalties for late tax payments. Interest rate on tax deferral is reduced from 4 percent to just above 0. Stronger automatic stabilizers given the broad social safety nets. | U83: https://www.rijksoverheid.nl/actueel/nieuws/2020/03/17/coronavirus-kabinet-neemt-pakket-nieuwe-maatregelen-voor-banen-en-economie
C84: USD bn | D84: =D83/VLOOKUP(A83,#REF!,7,0) -> #REF! | J84: USD bn | O84: USD bn
C85: % GDP | D85: =(D83/VLOOKUP(A83,#REF!,4,0))*100 -> #REF! | J85: % GDP | O85: % GDP
A86: Norway | C86: LC bn | D86: 76.8 | F86: Transfers to municipalities that have large health expenses due to the pandemic. | H86: Spending measures: · Expenditure measures include larger wage subsidies for temporary lay-offs and more generous unemployment benefits; expanded sickness benefits; grants for start-ups; subsidies for domestic air routes. · Grants to counties are increased to strengthen support for skills upgrade and in-house training for companies affected by the virus outbreak. Revenue measures: · The reduced VAT rate is temporarily cut from 12 to 8 percent (from April 1st to 30th October 2020). • Aviation taxes on air passengers are suspended from January 2020 to October 2020; aviation charges until 31 June 2020. · Corporate income tax regulations are amended so that companies can re-allocate their current losses towards previous years’ taxed profits, thus lowering their tax liabilities. Owners of lossmaking companies can postpone payments of wealth tax in 2020. ·Temporary cut of employers’ social insurance contributions. Deferral of payments: for various taxes. | J86: LC bn | L86: 50 | M86: The reinstatement of a government fund that buys bonds issued by Norwegian companies to increase liquidity and access to capital in the Norwegian bond market, with a ceiling of NOK 50 bn. | O86: LC bn | P86: 50 | Q86: Establish a government guarantee scheme for bank loans to SMEs, with a ceiling of NOK 50 bn. | S86: Automatic stabilizers, contingency lines, advance payments and tax deferrals, international aid; Deferral of various tax payments. | U86: https://www.regjeringen.no/en/aktuelt/economic-measures-in-norway-in-response-to-covid-19/id2694274/
C87: USD bn | D87: =D86/VLOOKUP(A86,#REF!,7,0) -> #REF! | J87: USD bn | L87: =L86/VLOOKUP(A86,#REF!,7,0) -> #REF! | O87: USD bn | P87: =P86/VLOOKUP(A86,#REF!,7,0) -> #REF!
C88: % GDP | D88: =((D86/#REF!))*100 -> #REF! | J88: % GDP | L88: =((L86/#REF!))*100 -> #REF! | O88: % GDP | P88: =((P86/#REF!))*100 -> #REF!
A89: Singapore | C89: LC bn | D89: 34.4 | F89: Measures to contain the outbreak, provided mainly to the Ministry of Health. | H89: Spending measures. · The Care and Support Package provides support to households (S$1.6 bn), including through a cash payout and an additional goods and services tax (GST) voucher. · The Stabilization and Support Package provides support to businesses (S$4.0 bn), including wage subsidies as well as additional support for industries directly affected and self-employed persons. Revenue measures: Corporate income tax rebate and property tax rebates; carry-back provisions for qualifying deductions and faster write-downs for qualifying investments. | J89: LC bn | L89: 20 | M89: Setting aside loan capital of S$20 bn. | O89: LC bn
C90: USD bn | D90: =D89/VLOOKUP(A89,#REF!,7,0) -> #REF! | J90: USD bn | L90: =L89/VLOOKUP(A89,#REF!,7,0) -> #REF! | O90: USD bn
C91: % GDP | D91: =(D89/VLOOKUP(A89,#REF!,4,0))*100 -> #REF! | J91: % GDP | L91: =(L89/VLOOKUP(A89,#REF!,4,0))*100 -> #REF! | O91: % GDP
A92: Sweden | C92: LC bn | D92: 103 | H92: Spending measures: · Additional expenditures on wage subsidies for short-term leave, increase in transfers to relevant agencies to deal with the coronavirus outbreak. · Temporary payment of sick leave, extra funding to the cultural sector and sports sector, rent subsidies to certain sectors, more generous unemployment benefits, expanded active labor market policies, more funding for education and training, increased testing for COVID-19 and grants to municipalities and regions. · The government has contributed SEK 40 million to the WHO’s Contingency Fund for Emergencies. Revenue measures: Temporary reduction in employers' social security contributions. Deferral of payments: Companies can defer a maximum of three months on social contribution fees, VAT, and payroll taxes for a period of up to 12 months. | J92: LC bn | O92: LC bn | P92: 235 | Q92: Credit guarantees for Swedish airlines; and expansion of the Swedish Export Credit Agency’s credit guarantee framework and the programs under the Swedish Export Credit Corporation, loan guarantees for SMEs, and expansion of the National Board of Health and Welfare's credit framework.
C93: USD bn | D93: =D92/VLOOKUP(A92,#REF!,7,0) -> #REF! | J93: USD bn | O93: USD bn | P93: =P92/VLOOKUP(A92,#REF!,7,0) -> #REF!
C94: % GDP | D94: =(D92/VLOOKUP(A92,#REF!,4,0))*100 -> #REF! | J94: % GDP | O94: % GDP | P94: =(P92/VLOOKUP(A92,#REF!,4,0))*100 -> #REF!
A96: Selected emerging market economies outside the G20
A97: Albania | C97: LC bn | D97: 12 | E97: 3.5 | F97: Additional funding for health sector in the amount of Lk 3.5 bn, including some allocation to the Reserve Fund. | G97: =12-3.5 -> 8.5 | H97: Spending measures Lk6.5bn: · Support of small businesses/self-employed that are forced to close activities due to the pandemic (a minimum wage of Lk26,000 per month), and people in family businesses (with declared but unpaid family members in the payroll, for up to two minimum wages). These measures will last up to 3 months from April. · Reprioritize LK 2bn of defense spending toward humanitarian relief for the most vulnerable. Deferral of payments. Small businesses (those below an annual turnover threshold) can defer payments of the profit tax installments in the second half of the year. | J97: LC bn | O97: LC bn | P97: 11 | Q97: Lk11bn (0.6 percent of GDP) Government has offered a sovereign guarantee for large businesses to tap overdraft or credit lines in the banking sector to pay worker salaries (Details of the scheme have yet to be finalized).
C98: USD bn | D98: =D97/VLOOKUP(A97,#REF!,7,0) -> #REF! | J98: USD bn | O98: USD bn | P98: =P97/VLOOKUP(A97,#REF!,7,0) -> #REF!
C99: % GDP | D99: =(D97/VLOOKUP(A97,#REF!,4,0))*100 -> #REF! | J99: % GDP | O99: % GDP | P99: =(P97/VLOOKUP(A97,#REF!,4,0))*100 -> #REF!
A100: Bulgaria | C100: LC bn | D100: =1.42+0.47 -> 1.89 | F100: · Additional remunerations in the ministries of health, interior and defense (0.5 bn). · Enhanced use of EU funds for expansion of social patronage services for the elderly and disabled people and purchase of medical supplies and equipment. | H100: Spending measures (BGN 1.4 bn): Measures to cover 60 percent of the wages for employees in affected sectors that would have been otherwise laid off. Deferral of payments (BGN 0.6 bn). Deferral of corporate taxes until June 30. | J100: LC bn | L100: 0.7 | M100: · BGN 0.5 bn to the Bulgarian Development Bank for guarantees before the commercial banks to extend loans to firms. · BGN 0.2 bn to the development bank for interest-free loans to employees in non-paid leave up to BGN 1500. | O100: LC bn | S100: Deferment of the payment of corporate taxes until June 30 (about 0.5 percent of 2019 GDP)
C101: USD bn | D101: =D100/VLOOKUP(A100,#REF!,7,0) -> #REF! | J101: USD bn | L101: =L100/VLOOKUP(A100,#REF!,7,0) -> #REF! | O101: USD bn
C102: % GDP | D102: =(D100/VLOOKUP(A100,#REF!,4,0))*100 -> #REF! | J102: % GDP | L102: =(L100/VLOOKUP(A100,#REF!,4,0))*100 -> #REF! | O102: % GDP
A103: Chile | C103: LC bn | D103: 3750 | F103: Spending measures (1,000bn or 0.7 percent of GDP): Financing of additional healthcare equipment, instruments, laboratories, contracting of emergency personnel and extension of working hours, etc. | H103: Spending measures (0.1 percent of GDP): Includes additional fiscal support and cash transfers for most vulnerable. Revenue measures (1.1 percent of GDP): Suspension of monthly provisional payments of corporate income tax for the next 3 months (allow liquidity of up to US $ 2.4 bn); reduction of the Stamp and Seals tax. Deferral of payments and advanced pay of liabilities (1.8 percent of GDP): postponement of VAT payment for the next 3 months for all companies with sales below 350,000, and allow monthly instalments at zero real interest rates (a liquidity of 1.5 bn). Early tax refunds of SMEs, postponement of tax payment until July 2020. | J103: LC bn | L103: 1950 | M103: Liquidity provision to SMEs and households, including through the state-owned Banco del Estado (0.2 percent of GDP). A state injection to the unemployment insurance system (0.8 percent of GDP). | O103: LC bn | S103: (Total US$6.7 bn) Suspension of monthly provisional payments of corporate income tax for the next 3 months (allow liquidity of up to US $ 2.4 bn); postponement of VAT payment for the next 3 months for all companies with sales below 350,000, and allow monthly instalments at zero real interest rates (a liquidity of 1.5 bn). Tax refunds of SMEs, postponement of tax payment until July 2020. | U103: https://prensa.presidencia.cl/comunicado.aspx?id=148684
C104: USD bn | D104: =D103/VLOOKUP(A103,#REF!,7,0) -> #REF! | J104: USD bn | L104: =L103/VLOOKUP(A103,#REF!,7,0) -> #REF! | O104: USD bn
C105: % GDP | D105: =(D103/VLOOKUP(A103,#REF!,4,0))*100 -> #REF! | J105: % GDP | L105: =(L103/VLOOKUP(A103,#REF!,4,0))*100 -> #REF! | O105: % GDP
A106: Colombia | C106: LC bn | D106: n.a. | F106: Health sector budgetary support from central government and a reduction of tariffs for strategic health imports. | H106: Spending measures. · Faster direct contracting for services associated with the emergency response and expanded transfers for vulnerable groups. · Expanded transfers for vulnerable groups (Including accelerated VAT reimbursements). · Created a National Emergency Mitigation Fund (FOME, worth around 1.5 percent of GDP), partially funded from regional and stabilization funds. Deferral of payments: Delayed tax collection for the tourism and air transportation sectors. | J106: LC bn | L106: 320 | M106: • Bancoldex (Colombian Development Bank) launched a special line of credit for COP250 bn for the tourism and transport sectors · Access to oil stabilization and pension funds in case of emergency. • Capitalization of the National Guarantee Fund to leverage loans to SMEs (COP 70 bn) | O106: LC bn
...

Sheet Abweichungen
B3: AP Link für GDP Werte | D3: https://api.worldbank.org/v2/country/AUS;CAN;FRA;DEU;ITA;JPN;KOR;ESP;GBR;USA;MEX;TUR;AUT;BEL;CZE;DNK;EST;FIN;GRC;ISL;IRL;ISR;LVA;LTU;LUX;NLD;NZL;NOR;PRT;SVK;SVN;SWE;CHE;CHL;COL;CRI;HUN;POL/indicator/NY.GDP.MKTP.KD?date=2019:2019&downloadformat=excel
A8: Country | B8: Werte IMF | C8: Werte Datenbank | D8: Differenz in PP | F8: Description of the differences
A9: =Summary.Global!B9 -> Australia | B9: 0.199 | C9: 0.1841 | D9: =C9-B9 -> -0.0149 | E9: =(C9-B9)/B9 -> -0.074874372 | F9: Others than health has also consist spending of 2022. As we do not record those elements we have to subtract it, the subtraction of those 30 bn leads to almost a perfect hit
A10: =Summary.Global!B10 -> Canada | B10: 0.227 | C10: 0.216 | D10: =C10-B10 -> -0.011 | E10: =(C10-B10)/B10 -> -0.04845815
A11: =Summary.Global!B11 -> France | B11: =Summary.Global!Q11 -> 0.25003382 | C11: =Summary.Global!R11 -> 0.2612 | D11: =C11-B11 -> 0.011166183 | E11: =(C11-B11)/B11 -> 0.044658691
A12: =Summary.Global!B12 -> Germany | B12: =Summary.Global!Q12 -> 0.44833033 | C12: =Summary.Global!R12 -> 0.4595 | D12: =C12-B12 -> 0.011169673 | E12: =(C12-B12)/B12 -> 0.024913936
A13: =Summary.Global!B13 -> Italy | B13: =Summary.Global!Q13 -> 0.45259746 | C13: 0.4466 | D13: =C13-B13 -> -0.0059974566 | E13: =(C13-B13)/B13 -> -0.013251194
A14: =Summary.Global!B14 -> Japan | B14: 0.4435 | C14: 0.4303 | D14: =C14-B14 -> -0.0132 | E14: =(C14-B14)/B14 -> -0.029763247
A15: =Summary.Global!B15 -> Korea | B15: 0.1653 | C15: 0.16 | D15: =C15-B15 -> -0.0053 | E15: =(C15-B15)/B15 -> -0.032062916
A16: =Summary.Global!B16 -> Spain | B16: =Summary.Global!Q16 -> 0.21857252 | C16: =Summary.Global!R16 -> 0.2257 | D16: =C16-B16 -> 0.0071274756 | E16: =(C16-B16)/B16 -> 0.032609202
A17: =Summary.Global!B17 -> United Kingdom | B17: =Summary.Global!Q17 -> 0.30887124 | C17: 0.3199 | D17: =C17-B17 -> 0.011028758 | E17: =(C17-B17)/B17 -> 0.035706653
A18: =Summary.Global!B18 -> United States | B18: =Summary.Global!Q18 -> 0.28960396 | C18: 0.283 | D18: =C18-B18 -> -0.0066039604 | E18: =(C18-B18)/B18 -> -0.022803419
A19: =Summary.Global!B19 -> Mexico | B19: 0.0219 | C19: 0.02192 | D19: =C19-B19 -> 2e-05 | E19: =(C19-B19)/B19 -> 0.00091324201
A20: =Summary.Global!B20 -> Turkey | B20: 0.1672 | C20: 0.142 | D20: =C20-B20 -> -0.0252 | E20: =(C20-B20)/B20 -> -0.1507177 | F20: All measures are reliable and matching IMF estimates, th eonly part is I do not count the Quasi-fiscal operations (noncommercial activity of public corporations on behalf of government) as it is not a government spending as well as not special backed by the government-> this would increase the share to the numbers of the IMF
A21: =Summary.Global!B21 -> Austria | B21: =Summary.Global!Q21 -> 0.18857318 | C21: 0.1762 | D21: =C21-B21 -> -0.012373176 | E21: =(C21-B21)/B21 -> -0.06561472 | F21: 0.1762 | G21: Difference is due to FX differences and the fact that IMF counted also the automatic stabilizaotr as extra spending despite this was in the regular budget. Especially they only record the % of GDP and gives no decription of the measures in the categorys. Checking the Tracker shows that I have included all https://www.imf.org/en/topics/imf-and-covid19/policy-responses-to-covid-19?path=Topics&path=imf-and-covid19&path=Policy-Responses-to-COVID-19
A22: =Summary.Global!B22 -> Belgium | B22: =Summary.Global!Q22 -> 0.20903867 | C22: =Summary.Global!R22 -> 0.214 | D22: =C22-B22 -> 0.0049613271 | E22: =(C22-B22)/B22 -> 0.023734016
A23: =Summary.Global!B23 -> Czech republic | B23: 0.247 | C23: =Summary.Global!R23 -> 0.2464 | D23: =C23-B23 -> -0.0006 | E23: =(C23-B23)/B23 -> -0.0024291498
A24: =Summary.Global!B24 -> Denmark | B24: =Summary.Global!Q24 -> 0.20422753 | C24: 0.2083 | D24: =C24-B24 -> 0.0040724655 | E24: =(C24-B24)/B24 -> 0.019940825 | F24: 0.2083 | G24: IMF Data is wrong, they completely miss out the health spending, I've got all the sources that perfectly add up to 500
A25: =Summary.Global!B25 -> Estonia | B25: =Summary.Global!Q25 -> 0.10854569 | C25: 0.1578 | D25: =C25-B25 -> 0.049254315 | E25: =(C25-B25)/B25 -> 0.45376575 | F25: 0.1578 | G25: Difference is the tax deferral https://news.err.ee/1073742/supplementary-budget-passes-its-first-riigikogu-reading who is completely missed out in the IMF document. When withdrawing thi smeasure I will be around 11%
A26: =Summary.Global!B26 -> Finland | B26: 0.142 | C26: 0.1489 | D26: =C26-B26 -> 0.0069 | E26: =(C26-B26)/B26 -> 0.048591549
A27: =Summary.Global!B27 -> Greece | B27: =Summary.Global!Q27 -> 0.19442999 | C27: 0.188 | D27: =C27-B27 -> -0.0064299858 | E27: =(C27-B27)/B27 -> -0.033070957
A28: =Summary.Global!B28 -> Iceland | B28: =Summary.Global!Q28 -> 0.11765787 | C28: 0.112 | D28: =C28-B28 -> -0.0056578686 | E28: =(C28-B28)/B28 -> -0.048087464
A29: =Summary.Global!B29 -> Ireland | B29: 0.143 | C29: 0.125 | D29: =C29-B29 -> -0.018 | E29: =(C29-B29)/B29 -> -0.12587413 | F29: Effectiv number were lot lower, official report and budget/statement of government proving that as well as ESRB https://www.esrb.europa.eu/home/search/coronavirus/countries/html/esrb.covidpmc_Ireland.en.html
A30: =Summary.Global!B30 -> Israel | B30: =Summary.Global!Q30 -> 0.16311979 | C30: 0.1636 | D30: =C30-B30 -> 0.00048020785 | E30: =(C30-B30)/B30 -> 0.0029438969
A31: =Summary.Global!B31 -> Latvia | B31: =Summary.Global!Q31 -> 0.1437927 | C31: 0.1441 | D31: =C31-B31 -> 0.00030730102 | E31: =(C31-B31)/B31 -> 0.0021371114
A32: =Summary.Global!B32 -> Lithuania | B32: =Summary.Global!Q32 -> 0.12193285 | C32: 0.117 | D32: =C32-B32 -> -0.0049328485 | E32: =(C32-B32)/B32 -> -0.040455452
A33: =Summary.Global!B33 -> Luxembourg | B33: 0.109 | C33: 0.104 | D33: =C33-B33 -> -0.005 | E33: =(C33-B33)/B33 -> -0.04587156
A34: =Summary.Global!B34 -> The Netherlands | B34: 0.159 | C34: 0.1597 | D34: =C34-B34 -> 0.0007 | E34: =(C34-B34)/B34 -> 0.0044025157
A35: =Summary.Global!B35 -> New Zealand | B35: 0.1535 | C35: 0.17 | D35: =C35-B35 -> 0.0165 | E35: =(C35-B35)/B35 -> 0.10749186 | F35: The sum of all listed measures are simply wrong in the IMF database (overestimate it by 6 pp. Wage subsidies was effective used by 18bn and IMF onli records the first bracket swith 13.9bn. This can be shown in the official report https://www.msd.govt.nz/documents/about-msd-and-our-work/publications-resources/statistics/covid-19/who-received-the-2021-covid-19-wage-subsidies.pdf. Another difference arised in the loans, the IMF do not ocunt the spoken loan amounts of 2.26bn but is clearly statet in the official report https://www.taxpolicy.ird.govt.nz/-/media/project/ir/tp/publications/2021/2021-ir-crsp-activation/2021-ir-crsp-activation.pdf?modified=20210728054252 As well as the wrong numbers in the guarantee section that is also documented in official sources: https://www.treasury.govt.nz/news-and-events/news/business-finance-guarantee-scheme-open-business | G35: This all adds up to a difference of like 9bn what woul leave us with the exact same amount from the imf->e.g., 42bn
A36: =Summary.Global!B36 -> Norway | B36: 0.102 | C36: =Summary.Global!R36 -> 0.0988 | D36: =C36-B36 -> -0.0032 | E36: =(C36-B36)/B36 -> -0.031372549
A37: =Summary.Global!B37 -> Portugal | B37: =Summary.Global!Q37 -> 0.12139874 | C37: 0.149 | D37: =C37-B37 -> 0.027601264 | E37: =(C37-B37)/B37 -> 0.22736039 | F37: 0.149 | G37: Difference is due to the wrong counted value of the guarantees in the IMF document-> when we adjust it to the IMF values we hit 12.5%-> see here: https://ec.europa.eu/competition/state_aid/cases1/202015/285326_2145493_24_2.pdf#:~:text=,its%20approval%20until%2031%20DecemberEC:%20https://ec.europa.eu/commission/presscorner/detail/en/ip_20_599EC%20detail:%20https://ec.europa.eu/competition/state_aid/cases1/202015/285326_2145493_24_2.pdfGovt:%20https://www.portugal.gov.pt/pt/gc22/comunicacao/noticia?i=linha-de-credito-covid-19-acessivel-a-todos-os-setores-economicos-e-a-empresarios-individuais
A38: =Summary.Global!B38 -> Slovak Republic | B38: 0.087 | C38: 0.117 | D38: =C38-B38 -> 0.03 | E38: =(C38-B38)/B38 -> 0.34482759 | F38: IMF has to low Guarantee sheme with about 2.4bn https://ec.europa.eu/commission/presscorner/detail/en/mex_20_1132
A39: =Summary.Global!B39 -> Slovenia | B39: =Summary.Global!Q39 -> 0.17399103 | C39: =Summary.Global!R39 -> 0.1769 | D39: =C39-B39 -> 0.0029089715 | E39: =(C39-B39)/B39 -> 0.016719089
A40: =Summary.Global!B40 -> Sweden | B40: 0.1603 | C40: 0.135 | D40: =C40-B40 -> -0.0253 | E40: =(C40-B40)/B40 -> -0.15782907 | F40: Differenz ist aufgrund von viel zu überhöhten Tax Deferrals des IMF-> rund 200bn SEK zu hoch wie effektiv. Dafür aber ca. 150 zu tiefe Guarantees envelope. Bereinigt um diese elemente sind die zahlen konsistent-> Source: https://www.riksrevisionen.se/en/news-archive/nyhetsarkiv-eng/2025-02-20-deferred-tax-payments-more-costly-than-expected.html
A41: =Summary.Global!B41 -> Switzerland | B41: 0.137 | C41: 0.126 | D41: =C41-B41 -> -0.011 | E41: =(C41-B41)/B41 -> -0.080291971 | F41: Differenz entsteht durch die falsche angabe vom IMF bezüglich der Kurzarbeit (Ankündigung) und Loan an das IMF-> Keine inlädnische Wirkung. Der Bund trug 2020–2022 laut Bundesratsbericht rund 82 % der Corona-bedingten öffentlichen Ausgaben, der Rest entfiel auf Kantone/Gemeinden.
A42: =Summary.Global!B42 -> Chile | B42: 0.1693 | C42: 0.288 | D42: =C42-B42 -> 0.1187 | E42: =(C42-B42)/B42 -> 0.70112227 | F42: 0.288 | G42: Informe de Gestión y Sostenibilidad 2021
A43: =Summary.Global!B43 -> Colombia | B43: 0.0961 | C43: 0.085 | D43: =C43-B43 -> -0.0111 | E43: =(C43-B43)/B43 -> -0.11550468 | F43: Differences are due to different estimation about "other than health" spending where the IMF used the announced values and: IMF list equity injection "Equity injection for capitalization of Findeter and Bancoldex (Colombian Development Banks) for the purpose of credit lines" whom is not belegbar mit quellen, weder from the government side nor from the bank sid. find in the following th ststements of both banks from 2021 where we do not see a change in equity. | G43: bancoldex_estados_financieros_separados_2021-2020_0.pdf
A44: =Summary.Global!B44 -> Costa Rica | B44: =Summary.Global!Q44 -> 0.015532172 | C44: 0.0176 | D44: =C44-B44 -> 0.0020678276 | E44: =(C44-B44)/B44 -> 0.1331319 | F44: Differences are due to the differences between FX rate and also IMF uses onli announced values
A45: =Summary.Global!B45 -> Hungary | B45: =Summary.Global!Q45 -> 0.16392116 | C45: =Summary.Global!R45 -> 0.1559 | D45: =C45-B45 -> -0.0080211559 | E45: =(C45-B45)/B45 -> -0.048933012
A46: =Summary.Global!B46 -> Poland | B46: 0.1153 | C46: 0.1143 | D46: =C46-B46 -> -0.001 | E46: =(C46-B46)/B46 -> -0.0086730269

Sheet Database
C2: Fiscal Monitor: Database of Country Fiscal Measures in Response to the COVID-19 Pandemic
H4: A. Above-the line measures | Q4: B. Below the line measures | T4: C. Contingent liabilities | Y4: Other measures | AA4: Links
A5: G20 + Spain | B5: Country Group | C5: s | D5: Government Level | F5: Unit | G5: Total on-budget (A-D) | H5: Total size | I5: Additional spending and forgone revenue in the health sector | J5: Total size | K5: Additional spending and forgone revenue in areas other than health | L5: Total size | M5: D. Accelerated spending and deferred revenue in areas other than health | O5: Unit | P5: Total off-budget (B+C) | Q5: Total size | R5: Equity injections, asset purchases, loans, debt assumptions, including through extra-budgetary funds | T5: Unit | U5: Total size | V5: Guarantees (on loans, deposits etc.) | W5: Total size | X5: Quasi-fiscal operations (noncommercial activity of public corporations on behalf of government) | Y5: Automatic stabilizers, contingency lines | AD5: lookupID
A6: 1 | B6: AE | C6: Australia | D6: General Government | F6: LC bn | G6: 361.7 | H6: 20 | I6: Additional spending (AUD 20.0 bn): •Australia is co-funding the WHO’s Pacific regional coronavirus response plan (together with New Zealand). •The Commonwealth government increased the budget to secure access to COVID-19 vaccines and roll out a national Vaccination Program. •The health spending package provides support across primary care, aged care, hospitals and research, to diagnose and treat people with the Coronavirus. •In relation to aged care, temporary measures will be introduced to support the aged care sector, which helps ensure the continuity of residential and home care. •The Commonwealth government will pay for half of all additional costs incurred by states and territories in diagnosing and treating patients with, or suspected of having, COVID-19, and efforts to minimize the spread of the virus. • The 2020-21 Mid-Year Economic and FIscal Outlook (MYEFO), released on December 17, includes cost of vaccine procurement and rollout. | J6: 341.7 | K6: Additional spending (AUD 239.2 bn): At the Commonwealth government level • Measures include tax-free cash flow assistance, wage subsidies, payments to lower-income Australians (pensioners, other social security and veteran income support recipients, and eligible concession cardholders), and the Home Builder program. • FY2021 budget, released on October 6, includes additional spending measures under the JobMaker program, comprising job hiring credit, infrastructure projects, and others for job creation. • The 2020-21 MYEFO extends coronavirus supplement and other income support measures through end-March 2021. • The FY2022 budget adds spending on infrastructure investment, extension of aviation and tourism support, women’s economic support package, and various programs for job creation At state and local government levels • Measures include discount utility bills, cash payments to vulnerable households, and construction and infrastructure projects. • The Commonwealth government will help finance fast-track infrastructure projects across States and Territories and the arts industry for job creation, as well as the new home care package for the senior citizens. • Pandemic Leave Disaster Payment has been arranged with the State and Territory governments, which provides a lump sum payment to help workers during their 14-day self-isolation period. Forgone revenue (AUD 102.5 bn): At the Commonwealth government level • Measures include raising the asset write-off threshold, accelerated depreciation deductions, and COVID-19 Relief and Recovery Fund which provides waiver of fees and charges to affected industries (e.g., aviation industry), regions, and communities. • FY2021 budget includes additional revenue measures under the JobMaker program, comprising extension of immediate expensing, loss carry-backs, income tax cut for lower- and middle-income earners, and tax incentives for R&D. • The FY2022 budget extends temporary full expensing and loss carry-backs for businesses, and retains the low- and middle-income tax offset for FY2021-22. At state and local government levels • Measures include payroll tax relief for businesses. | O6: LC bn | P6: 35 | Q6: 15 | R6: • The Government’s Structured Finance Support Fund provides up to AUD15 bn to the Australian Office of Financial Management to support continued access to structured finance markets used by smaller lenders, providing both consumer and business credit. | T6: LC bn | U6: 20 | V6: • The Coronavirus SME Guarantee Scheme provides a loan guarantee arrangement between the government and participating banks to cover the immediate cash flow needs of SMEs. In mid-July 2020, this scheme was extended through June 2021, with the maximum loan size raised from A$250,000 to A$1 million and the maximum maturity extended to five years. • In March 2021, the government renamed it the SME Recovery Loan Scheme, under which the government guarantees 80 percent (previously: 50 percent) of new SME loan amounts (starting April 2021), with the maximum loan size raised to A$5 million and the maximum maturity extended to ten years. The scheme also offers up to 24 months of repayment holidays. | Y6: Parliament approved an advance authorization of A$40 billion for unforeseen events. | AA6: https://treasury.gov.au/coronavirus | AD6: =C6&F6 -> AustraliaLC bn
F7: USD bn | G7: 249.7258 | H7: 13.808449 | J7: 235.91735 | O7: USD bn | P7: 24.164785 | Q7: 10.356337 | T7: USD bn | U7: 13.808449 | AD7: =C6&F7 -> AustraliaUSD bn
F8: % GDP | G8: 18.370673 | H8: 1.0157961 | J8: 17.354877 | O8: % GDP | P8: 1.7776432 | Q8: 0.7618471 | T8: % GDP | U8: 1.0157961 | AD8: =C6&F8 -> Australia% GDP
A9: 1 | B9: AE | C9: Canada | D9: Central Government | F9: LC bn | G9: 351.1 | H9: 61.2 | I9: Additional spending (CAD 61.2 bn): Support to the health system including Safe Restart Agreement, Safe Return to Class, Vaccines and Therapeutics, PPE and Medical Equipment, Long-Term Care, Helping Health Care Systems Recover, Canada’s COVID-19 Immunization Plan, Supporting the Mental Health of Those Most Affected by COVID-19, Supporting Indigenous Communities in the Fight Against COVID-19, Safe Return to School on Reserve, International COVID-19 Response and Recovery, Enhanced Border and Quarantine Measures, and Other Public Health Support | J9: 289.9 | K9: Additional spending (CAD 289.9 bn): Households (CAN 253.6 bn) of which: • Emergency response benefit, Recovery benefits, and enhanced employment insurance (CAN 120.2 bn) • Wage subsidies and protecting jobs (CAN 110.5.2 bn) • Others, including support to students, seniors, and vulnerable groups (CAN 22.9 bn) Businesses (CAN 36.2 bn) of which: • Emergency business account with 25% loan forgiveness (CAN 13.8 bn) • Emergency rent subsidy (CAN 8.4 bn) • Others, including sector-specific support and sub-nationals support (CAN 14 bn) | L9: 85.1 | M9: Deferred revenue (CAD 85.1 bn): Income Tax Payment Deferral until September 30, 2020 ($55 billion); Sales Tax Remittance and Customs Duty Payments Deferral ($30 billion); and Supporting Jobs and Safe Operations of Junior Mining Companies ($50 million) | O9: LC bn | P9: 87.1 | Q9: 5.2 | R9: • Supporting Farm Credit Canada by allowing an additional $5.2 billion in lending capacity to producers, agribusinesses, and food processors. This is a capital injection. | T9: LC bn | U9: 81.9 | V9: • Established a Business Credit Availability Program (BCAP) to provide support through the Business Development Bank of Canada (BDC) and Export Development Canada (EDC), which work with private sector lenders to coordinate on credit solutions for individual businesses, including in sectors such as oil and gas, air transportation, exportation, and tourism. This includes combination of loan guarantees and shared financing arrangements. The BCAP consists of: the Canada Emergency Business Account (for small firms), the Mid-Market Guarantee and Financing Program, the Large Employer Emergency Financing Facility, and Support for the Agriculture and Agri-Food Sector. | AA9: https://www.canada.ca/en/public-health/services/diseases/coronavirus-disease-covid-19.html | AB9: $100 million to support federal public health measures such as enhanced surveillance, increased testing at the National Microbiology Laboratory. The package includes $275 million for additional research such as vaccine development, $200 million for federal medical supplies, and support for Indigenous communities and education efforts. $500 million to provinces and territories for critical health care system needs and to support mitigation efforts, including access to testing, equipment and to enhance surveillance and monitoring. $50 million for Public Health Agency of Canada's COVID-19 communications and public education efforts. $2 bn to support diagnostic testing and to purchase ventilators and protective personal equipment, including for bulk purchases with provinces and territories. Personal protective equipment includes things like more masks and face shields, gowns, and hand sanitizer. $50 million has been made available in funding for members of the Next Generation Manufacturing Supercluster to develop and scale-up new, in-demand technologies, equipment, and medical products. | AD9: =C9&F9 -> CanadaLC bn
F10: USD bn | G10: 261.78973 | H10: 45.632389 | J10: 216.15734 | L10: 68.027304 | O10: USD bn | P10: 64.944135 | Q10: 3.8772618 | T10: USD bn | U10: 61.066873 | AD10: =C9&F10 -> CanadaUSD bn
F11: % GDP | G11: 15.923589 | H11: 2.7756298 | J11: 13.147959 | L11: 3.8595767 | O11: % GDP | P11: 3.9502836 | Q11: 0.23583783 | T11: % GDP | U11: 3.7144457 | AD11: =C9&F11 -> Canada% GDP
A12: n.a. | B12: n.a. | C12: European Union | F12: LC bn | G12: 427.85 | H12: 0.05 | I12: Additional spending (€0.05 bn): The European Commission redirected funding of €47.5 mn towards research on COVID-19 vaccine development, treatment, and diagnostics. | J12: 427.8 | K12: Additional spending (€427.8 bn): • In April 2020, the European Commission announced that the size of the Corona Response Investment Initiative will be raised to €37 bn, which includes an upfront cash injection of €8 bn from the EU cohesion funds, to support public investment for hospitals, labor markets, and stressed regions. The Commission extended the scope of the EU Solidarity Fund by also including a public health crisis within its scope, in view of mobilizing it if needed for the hardest hit EU member states. The Coronavirus Response Investment Initiative Plus (CRII+) introduced greater flexibility to allow that all non-utilized support from the European cohesion funds can be mobilized to the fullest. This flexibility is provided for through: transfer possibilities across the three cohesion policy funds (the European Regional Development Fund, European Social Fund and Cohesion Fund); transfers between the different categories of regions; flexibility when it comes to thematic concentration; and a 100% EU co-financing rate for cohesion policy programs for the accounting year 2020-2021, allowing Member States to benefit for full EU financing for crisis-related measures. •On December 11, EU leaders agreed on the Next Generation EU (NGEU) recovery package, which includes €390 bn in grants to EU members. The main instrument is the Recovery and Resilience Facility (RRF), which will fund member countries’ investments and reforms. The NGEU’s grant element comprises: €312.5 bn is from the RRF and will be committed in 2021–2023 (70 percent for 2021 and 2022 and 30 percent for 2023); €47.5 bn to top up cohesion funds (ReactEU) that can be used for investments and expenditures related to the crisis (e.g., investing in active labor market policies, short-time work schemes); €10 bn to top up to the Just Transition Fund to help regions/workers dependent on carbon intensive industries transition away from those industries; R&D (€5 bn); support for private sector investment (€5.6 bn), rural development (€7.5 bn), and rescEU (€1.9 bn). • As of early June, 2021, 24 EU countries had submitted national Recovery and Resilience Plans (RRPs). These are being assessed by the European Commission. The EC has raised 45 billion euros in bond issuance by end-July which will help finance pre-financing portion in 2021 (13% of total loans and grants, which amounts to 491 billion euros as of August). | O12: LC bn | P12: 765 | Q12: 700 | R12: On April 9 2020, the euro area finance ministers (Eurogroup) agreed on establishing safety nets for workers, businesses and sovereigns, amounting to a package of which €340 bn were below-the-line measures: •A new and temporary EU unemployment reinsurance fund (SURE) will provide up to €100 bn in loans on favorable terms to governments, in support of national unemployment, short-time work schemes, and health-related measures. Loans will be guaranteed by the EU budget and EU member states. The instrument will then be operational until 31 December 2022. •The ESM will provide Pandemic Crisis Support to its members to finance crisis-related health spending of up to 2 percent of a requesting member’s 2019 GDP. Should all 19 countries draw from the credit line, this would amount to around €240 bn.The loans from the ESM are meant to finance direct and indirect health-related spending in response to the Covid-19 crisis. On July 21, the European Council approved the Next Generation EU recovery fund. Part of this is EUR 360 billion in loans available from the Recovery and Resilience Facility (RRF) that EU members can apply for to finance parts of their national recovery and resilience plans. | T12: LC bn | U12: 65 | V12: •The EU Council agreed on a new pan-European guarantee fund of €25 bn, which could support €200 bn of total financing for hard-hit SMEs throughout the European Investment Bank or national development banks. The guarantee fund comes on top of an earlier support package of up to €40 bn for the European Investment Bank in March, and both packages are likely to be funded by voluntary contributions from member states. | Y12: The European Commission also activated the general escape clause in the EU fiscal rules, which suspends the fiscal adjustment requirements for countries not at their medium-term objective and allow countries to run deficits in excess of 3 percent of GDP. Credit holidays to existing debtors that are negatively affected will be provided. | AD12: =C12&F12 -> European UnionLC bn
F13: USD bn | G13: 488.29744 | H13: 0.057064093 | J13: 488.24038 | O13: USD bn | P13: 873.08062 | Q13: 798.8973 | T13: USD bn | U13: 74.183321 | AD13: =C12&F13 -> European UnionUSD bn
F14: % GDP | G14: 3.7559633 | H14: 0.00043893459 | J14: 3.7555243 | O14: % GDP | P14: 6.7156992 | Q14: 6.1450842 | T14: % GDP | U14: 0.57061496 | AD14: =C12&F14 -> European Union% GDP
A15: 1 | B15: AE | C15: France | D15: General Government | F15: LC bn | G15: 221.9 | H15: 33.9 | I15: Additional spending (€33.9 bn): • Support for streamlining and boosting health insurance (paid sick leave) for the sick or their caregivers, higher spending on health supplies; bonuses for health workers. • Additional investment and equipment in the health sector announced in the recovery plan for 2021 and beyond. | J15: 188 | K15: Additional spending (€155.4 bn): Support for wages of workers under the subsidized short-time work scheme; direct financial support for affected small and very small enterprises (and regardless of size for heavily affected firms in December 2020), liberal professions, and independent workers; direct transfers for low-income families; extension of expiring unemployment and other benefits; additional transfers for self-employed; additional spending in social programs; incentives to purchase greener vehicles; subsidies for green investment for the auto and aerospace sectors. Foregone revenue (€32.6 bn): Exoneration of social security contributions for affected firms in selected sectors; carry back for corporate income taxes; permanent cuts in production taxes (recovery plan) for 2021 onward. (The amount reported for forgone revenue includes the equivalent cuts in production taxes for 2 years) | L15: 69.5 | M15: Accelerated spending (€17.5 bn): Accelerated refund of tax credits (e.g. CIT and VAT). Deferred revenue (€52 bn): Postponement of social security contributions and tax payment for companies. | O15: LC bn | P15: 350.3 | Q15: 15.8 | R15: • Envelope for direct equity support (mostly for strategic companies, e.g., Air France-KLM, SNCF). | T15: LC bn | U15: 334.5 | V15: • State guarantees for bank loans to companies and credit reinsurance schemes (€315 bn); other guarantees (€12.5 bn). • The recovery plan also includes the creation of a up to €20 bn fund leveraged by public guarantees (€7 bn), to provide quasi-equity support or equity loans to firms. | Y15: Liquidity support through postponement of social security contributions and tax payment for companies (€33.5 bn). | AA15: https://www.economie.gouv.fr/coronavirus-soutien-entreprises# | AD15: =C15&F15 -> FranceLC bn
F16: USD bn | G16: 252.88464 | H16: 38.63357 | J16: 214.25107 | L16: 79.204517 | O16: USD bn | P16: 399.21356 | Q16: 18.006207 | T16: USD bn | U16: 381.20735 | AD16: =C15&F16 -> FranceUSD bn
F17: % GDP | G17: 9.6358441 | H17: 1.4720825 | J17: 8.1637616 | L17: 3.0179863 | O17: % GDP | P17: 15.21152 | Q17: 0.68610337 | T17: % GDP | U17: 14.525416 | AD17: =C15&F17 -> France% GDP
A18: 1 | B18: AE | C18: Germany | D18: General Government | F18: LC bn | G18: 516 | H18: 61 | I18: Additional spending (€61 bn): on vaccines, equipment, research, information campaigns, as well as broader measures to modernize and improve the capacity of hospitals. | J18: 455 | K18: Additional spending (€346 bn): including grants to hard hit small businesses and self-employed, increased access to childcare and basic social security benefits, temporary relief to affected tenants, income support for families, and incentivizing green and digital investment. There is also support to firms and households provided through the “Kurzabeit” program, part of which is considered discretionary because the program parameters have been changed. Forgone revenue (€109 bn): a temporary VAT reduction (the general VAT cut was expired at end-2020, but special VAT cuts for restaurants and food services remain in place), corporate tax reliefs, personal income tax reliefs, and social security contribution reduction. | M18: Deferred revenue: including options for deferring tax payments and reducing prepayments until the year-end without penalties. | O18: LC bn | P18: 927 | Q18: 100 | R18: • An economic stabilization fund (WSF) of €600 bn is established with three components: (i) €100 bn for government equity investments in significantly affected companies; (ii) €100 bn loan to state development bank KfW for financing affected firms that do not have access to KfW’s existing programs; | T18: LC bn | U18: 827 | V18: (iii) €400 bn to provide additional state guarantees to non-financial corporations to alleviate liquidity bottlenecks and support refinancing. • For the new and expansion of the existing KfW-programs, the guarantee framework of the federal government was increased by €357 bn. • Total guarantees provided by state governments to be increased by €70 bn. | Y18: The government provides options for deferring tax payments and reducing prepayments; while tax penalties will not be levied until the end of this year. | AA18: https://www.bundesregierung.de/breg-de/themen/coronavirus | AD18: =C18&F18 -> GermanyLC bn
F19: USD bn | G19: 588.90144 | H19: 69.618193 | J19: 519.28325 | O19: USD bn | P19: 1057.9683 | Q19: 114.12819 | T19: USD bn | U19: 943.8401 | AD19: =C18&F19 -> GermanyUSD bn
F20: % GDP | G20: 15.322667 | H20: 1.8114005 | J20: 13.638353 | O20: % GDP | P20: 27.786271 | Q20: 2.9974402 | T20: % GDP | U20: 24.78883 | AD20: =C18&F20 -> Germany% GDP
A21: 1 | B21: AE | C21: Italy | D21: General Government | F21: LC bn | G21: 180 | H21: 20 | I21: Additional spending (€19.5 bn): including on medical equipment, staff, and vaccine. Forgone revenue (€0.5 bn): zero VAT rate on targeted medical equipment. | J21: 160 | K21: Additional spending (€150 bn): including broadening the wage supplementation fund to provide income support to laid-off workers and the self-employed, vouchers for the payment of babysitters (€80 bn), grants for SME (€60 bn), education (€4 bn), and other (€10 bn). Forgone revenue (€10 bn): corporate income tax credits (€4 bn) and social security contribution reduction (€6 bn). | L21: 7 | M21: Deferred revenue: mostly due to postponement of VAT, CIT, and social security contributions as well as property taxes. | O21: LC bn | P21: 582.25 | Q21: 3.25 | R21: • Equity injection to Alitalia (€3.3 bn) | T21: LC bn | U21: 579 | V21: The total guarantee is estimated at about 579 bn euros, aimed to unlock more than 750 billion euros of liquidity for businesses and households. (Note that the amount reported here is the originally announced ceiling, and the current level of contracted guarantees is about one-fourth of the announced). | Y21: Other measures to support businesses, including tax deferrals and postponement of utility bill payments in most affected municipalities (€6.4 bn), a moratorium on loan repayments for households and SMEs, including on mortgages and overdrafts (€220 bn), incentives for financial and non-financial companies in the form of Deferred Tax Activities | AA21: http://www.mef.gov.it/en/inevidenza/Protect-health-support-the-economy-preserve-employment-levels-and-incomes-00001/ | AD21: =C21&F21 -> ItalyLC bn
F22: USD bn | G22: 205.43073 | H22: 22.825637 | J22: 182.6051 | L22: 7.988973 | O22: USD bn | P22: 664.51136 | Q22: 3.709166 | T22: USD bn | U22: 660.8022 | AA22: http://www.governo.it/it/articolo/comunicato-stampa-del-consiglio-dei-ministri-n-39/14417 | AD22: =C21&F22 -> ItalyUSD bn
F23: % GDP | G23: 10.898556 | H23: 1.2109506 | J23: 9.687605 | L23: 0.42383272 | O23: % GDP | P23: 35.2538 | Q23: 0.19677948 | T23: % GDP | U23: 35.057021 | AD23: =C21&F23 -> Italy% GDP
A24: 1 | B24: AE | C24: Japan | D24: General Government | F24: LC bn | G24: 90100 | H24: 11200 | I24: Additional spending: • Production, procurement and distribution of critical equipment such as masks and ventilators (JPY 0.8 tn) •Transfers to local governments to be used for their health- and long-term care related measures including cash handouts to medical and long-term care practitioners (JPY 3.7 tn) • Other health-related measures (procurement of vaccines, etc.) (JPY 6.7 tn). | J24: 78900 | K24: Additional spending (JPY 78.9 tn): Key spending measures in the Emergency Economics Package against COVID-19 include: • Cash handout of JPY 100K per person (JPY 12.9 tn); • Lump-sum transfer to affected firms (JPY 2 mn per SME, JPY 1 mn for the self-employed) (JPY 2.3 tn); • Subsidies for financial institutions' lending (JPY 3.8 tn); • Expansion of work subsidies (JPY 0.9 tn); • Incentives to accelerate recovery, including for consumption in service sectors and infrastructure investments (JPY 10.8 tn); • Transfers to local governments for COVID-19 (JPY 1 tn). Additional measures announced May 27, 2020 include: • Transfers to local governments (JPY 2 tn); • Expansion of work subsidies (JPY 1.3 tn); • Subsidies for public/private financial institutions' lending (JPY 9.3 tn); • Replenishment of cash transfers for firms (JPY 1.9 tn); • Subsidies to affected firms for rent payment (JPY 2 tn). The government announced additional measures on December 8 2020, including: • Incentives for firms to invest in green technologies (JPY 2.0 tn) • Subsidies to accelerate business restructuring of SMEs (JPY 1.1 tn) • Extension of the Employment Adjustment Subsidy (JPY 1.5 tn) • Transfers to the local governments (JPY1.5 tn) • Subsidies for financial institutions' lending (JPY 3.2 tn) • Measures to enhance national resilience (primarily public investments) (JPY 4.4 tn) In April 2020 onwards, the government decided to spend a part of the COVID-19 reserve fund on the health and non-health measures totaling JPY 11.2 tn (excluding the spending approved on December 11 2020). The measures include: • Cash transfers to affected firms (JPY 1.2 tn) • Replenishment of the emergency loan program for affected households (JPY 1.0 tn) • Enhancement of healthcare capacity (JPY1.7 tn) • Procurement of vaccines (JPY 2.0 tn) • Top up the Employment Adjustment Subsidy (JPY 0.5 tn) • Transfers to the local governments (JPY 3.9 tn) Forgone revenue : Revenue measures included in the past economic packages include expansion of the loss carry-back and carry-forward schemes, tax incentives for firms’ decarbonization and digitalization, and reduction of property tax and the aviation fuel tax. | L24: 2900 | M24: Deferred revenue (JPY 3 tn): Deferral of payment of taxes and social security premiums by affected firms and households for one year. | O24: LC bn | P24: 152600 | T24: LC bn | U24: 15700 | V24: • Guarantees on bonds/borrowing by the Development Bank of Japan and the Japan Finance Corporation (JPY 7.6 tn). • Guarantees on external bonds issued by the Development Bank of Japan and Japan Bank for International Cooperation (JPY 1.1 tn). • Guarantees on bonds/borrowings by other public financial institutions for their equity injection programs. (JPY2.5 tn). • Expanded the guarantee cap on the capital injection scheme into banks (JPY 3 tn). • Expanded the insurance capacity of the Nippon Export and Investment Insurance (JPY1.5 tn). | W24: 136900 | X24: • Concessional loans and guarantees to affected firms through the public and private financial institutions. (JPY 112 tn)• Public financial institutions' provision of subordinated loans (quasi-equity) and equities (JPY 2.7 tn) • Public financial institutions' loans to affected hospitals and clinics (JPY 3.5 tn) • The university fund (JPY 4.0 tn) • Other quasi-fiscal operations using the Development Bank of Japan and other agencies (primarily for infrastructure projects) (JPY 15 tn) | Y24: Japan has made a contribution of SDR14 mn (US$19 mn) to the IMF’s Catastrophe Containment and Relief Trust. The deadline for tax return filing and payment of personal income tax, gift tax, and consumption tax (for the self-employed) was extended from mid-March to mid-April; tax payments for people and businesses negatively impacted by the COVID-19 outbreak are deferred. In addition, the ¥26 tn (about 4.8 percent of GDP) December 2019 stimulus package is being used to offset the adverse impact of COVID-19 on the economy as well as counter the economic slowdown. | AD24: =C24&F24 -> JapanLC bn
F25: USD bn | G25: 843.83379 | H25: 104.89388 | J25: 738.93991 | L25: 27.160022 | O25: USD bn | P25: 1429.1791 | T25: USD bn | U25: 147.03874 | W25: 1282.1403 | AD25: =C24&F25 -> JapanUSD bn
F26: % GDP | G26: 16.725807 | H26: 2.0791236 | J26: 14.646684 | L26: 0.53834452 | O26: % GDP | P26: 28.32806 | T26: % GDP | U26: 2.9144858 | W26: 25.413574 | AD26: =C24&F26 -> Japan% GDP
A27: 1 | B27: AE | C27: Korea | D27: General Government | F27: LC bn | G27: 123700 | H27: 14100 | I27: Additional spending: • Emergency spending and first supplementary budget (KRW 2.1 tn): Epidemic prevention and treatment, support for medical institutions and quarantined households. • Third supplementary budget (KRW 2.4 tn): Expanding diagnostic and treatment facilities and smart medical centers; promoting treatment and vaccine development; promoting test-trace-treatment to be a global standard and increasing official development aid of K COVID-19 response kits and tools. • Additional health spending (KRW 600 bn). • Customized Relief Package (December 2020; KRW 0.8 tn) Strengthen disease prevention measures and reinforce medical system and facilities • 2021 supplementary budget (KRW 4.2 tn) : COVID-19 vaccination, compensation for medical institutions. • 2021 2nd supplementary budget (4.9 trillion won), vaccine rollouts and development, testing and quarantine, rewards to private medical institutions. | J27: 109600 | K27: Additional Spending (KRW 106.2 tn): • The government has announced consumption coupons for the poor, emergency family care support, and support for business re-opening (KRW 5.6 tn). • The 1st supplementary budget included support for SMEs, additional consumption coupons, and grants to local governments (KRW 8.8 tn). • The 2nd supplementary budget included cash transfers to whole households (KRW 14.3 tn). • The 3rd supplementary budget includes support for companies, employment, and social safety nets; boost to consumption, investment, and local economies; and Korean new deal for digital and green investment (KRW 23.7 tn). • The 4th supplementary budget: KRW 7.8 tn (KRW 3.9 tn for SME support, KRW 1.5 tn for employment relationship, KRW 0.4 tn support for unemployed and low income household, KRW 1.8 tn in daycare support and mobile bills, and KRW 0.2 tn for emergency disease prevention). • Customized Relief Package (December 2020; KRW 4.6 tn): Rent subsidy for small business owners and income support for freelancers, platform workers, and etc. • 2021 supplementary budget: KRW 10.7 tn (KRW 8.2 tn support for SME and vulnerable workers, KRW 2.5 tn support for employment) • 2021 2nd supplementary budget (30 trillion won): pandemic relief package, employment support, and support for local governments. Forgone revenue (KRW 3.4 tn): • Temporary corporate/income tax cuts for landlords who reduce commercial rents. • Rental fees reduction for tenants of public properties • Rental fees reduction for tenants of commercial properties and reduction in airport facility fees, ports and terminal charges. • VAT reduction for the self-employed (KRW 0.7 tn). • Corporation tax cut for SMEs located in disaster areas (KRW 0.3 tn). • Consumption tax cut for auto purchases (KRW 0.8 tn). • Raising income tax deduction for credit/debit card and cash receipt expenditure (KRW 0.4 tn). • Raising ceiling of deductible entertainment expenses when calculating corporation tax (KRW 0.2 tn). • Social security (healthcare insurance) contribution cut for households (KRW 0.9 tn). | L27: 33000 | M27: Accelerated spending (KRW 3.3 tn): Make early purchases and prepayments for cash-strapped businesses (KRW 2.1 tn) and frontload construction investment (KRW 1.2 tn), temporarily relaxing government procurement rules. Deferred revenue (KRW 29.7 tn): Tax payment deferral including Corporate Income Tax and VAT, deferment in tax investigation, early tax refund have been conducted(KRW 42.9 tn); social security contribution payment deferral for households & electricity charge deferral (KRW 0.5 tn) | O27: LC bn | P27: 195900 | T27: LC bn | U27: 70900 | V27: • First financial support program for small merchants (KRW 16.4 tn). • Second financial support program for small merchants (KRW 10.0 tn). • Full & special guarantees for SMEs and small merchants provided by state-backed financial institutions (policy banks) (KRW 16.8 tn). • Preferential guarantees for SMEs and export companies (KRW 7.9 tn). • P-CBO for companies affected by COVID-19 (KRW 11.7 tn). • Guarantees/loans related to trade financing and overseas projects (KRW 6 tn). • Guarantees/loans for venture capital and start-up (KRW 2.1 tn). | W27: 125000 | X27: • Credit recovery program by KAMCO (KRW 2.0 tn). • Loan expansion to SMEs provided by state-backed financial institutions (KRW 21.2 tn). • Support package to stabilize corporate bond and short-term funding market, except P-CBO (KRW 11.1 tn). • Low-rated corporate bond and CP purchase program (KRW 20.0 tn). • Key Industry Stabilization Fund (KRW 40.0 tn). • Stock Market Stabilization Fund (KRW 10.7 tn). • Bond Market Stabilization Fund (KRW 20.0 tn). | Y27: Tax payment deferral covering a broad range of taxes for small businesses and the self-employed in medical, tourism, performance, hospitality, and other affected sectors. Social security contribution payment deferral for households | AA27: https://english.moef.go.kr/pc/selectTbPressCenterDtl.do?boardCd=N0001&seq=4860 | AD27: =C27&F27 -> KoreaLC bn
F28: USD bn | G28: 104.83005 | H28: 11.9491 | J28: 92.880946 | L28: 27.965978 | O28: USD bn | P28: 166.01622 | T28: USD bn | U28: 60.084481 | W28: 105.93174 | AD28: =C27&F28 -> KoreaUSD bn
F29: % GDP | G29: 6.3988747 | H29: 0.7293786 | J29: 5.6694961 | L29: 1.7070563 | O29: % GDP | P29: 10.133707 | T29: % GDP | U29: 3.6675846 | W29: 6.4661224 | AD29: =C27&F29 -> Korea% GDP
A30: 1 | B30: AE | C30: Spain | D30: General Government | F30: LC bn | G30: 94.15 | H30: 19.21 | I30: Additional spending (17.88 bn): • Budget support from the contingency fund to the Ministry of Health (€1.4 bn); transfer to the regions for health services (€12.4 bn); additional healthcare related spending including research related to COVID-19 (€270 mn). Forgone revenue (1.33 bn): • Reduction in VAT for surgical disposable masks; • Reduction in VAT for surgical disposable masks; • Temporary zero VAT on purchases of certain medical material, as well COVID-19 tests and vaccines | J30: 74.94 | K30: Additional spending (74.14 bn): • Unemployment benefit for workers temporary laid off under the ERTE due to COVID-19, with no requirement for prior minimum contribution or reduction of accumulated entitlement (about €21.7 bn); and exemptions of social contributions for companies that maintain employment under the ERTEs (about €7.7 bn); • An allowance for self-employed workers affected by economic activity suspension (about €6.5 bn), and exemption of social contributions for self-employed that receive this benefit (about €3.3 bn); • Corporate solvency support (€10 bn); • Measures taken by regional governments on social services, education and support to firms (about €5.5 bn); • Introduction of a new means-tested "minimum income scheme"(about €3 bn annually); and new rental assistance programs for certain vulnerable renters and additional state contribution to the State Housing Plan 2018-21; • Various measures to expand existing benefits for workers and other support for households and firms; Forgone revenue (0.8bn): • Flexibility in filing income tax and VAT installment payment for SMEs and self-employed; • Tax incentives for landlords that reduce rents of properties used for activities related to the hotel, restaurant and tourism industries; • Reduction in the contribution for Employed Agricultural Workers who have completed a maximum of 55 real days of contribution in 2019; • Other revenue measures. | L30: 0.045 | M30: Deferred revenue: Deferral of social security contribution and debts for companies and the self-employed; Deferral of tax debts and debts arising from customs declaration; tax payment deferrals for small and medium enterprises and self-employed, with the first three/four months exempt from interest. | O30: LC bn | P30: 161.239 | Q30: 0.639 | R30: • Loans through the State Financial Fund for Tourism Competitiveness (FOCIT) to promote the transformation of the tourism sector towards a more sustainable business model (€515 mn). • Loans for the industrial sector to promote digital transformation and modernization (€124 mn). | T30: LC bn | U30: 150.6 | V30: • Up to €100 bn government guarantees for firms and self-employed, covering both loans and commercial paper of medium-sized companies that participate in Spain’s Alternative Fixed Income Market (MARF) • A new Instituto de Crédito Oficial (ICO) line of guarantees to promote investment activities particularly in the areas of environmental sustainability and digitization (€40 billion); • Guarantees for financing operations carried out by the European investment Bank (€2.8 billion) and endorsement to the European SURE instrument (€2.3 billion) • Additional guarantees of up to €2 bn for exporters through the Spanish Export Insurance Credit Company • Guarantees to provide financial assistance on housing expenses for vulnerable households (€1.2 billion); up to €2 billion public guarantees for exporters through the Spanish Export Insurance Credit Company; expansion of the ICO credit lines for the tourism sector (€200 million) • Additional loan guarantees for SMEs and self-employed through the Compañía Española de Reafianzamiento (€1.1 bn) and line of guarantees for listed companies (€1 billion) | W30: 10 | X30: • Additional funding for the Instituto de Crédito Official (ICO) credit lines (€10 bn) | AA30: https://www.lamoncloa.gob.es/consejodeministros/resumenes/Paginas/2020/170320-pg-consejo.aspx | AB30: =849+223 -> 1072 | AD30: =C30&F30 -> SpainLC bn
F31: USD bn | G31: 107.45169 | H31: 21.924025 | J31: 85.527663 | L31: 0.051357684 | O31: USD bn | P31: 184.01915 | Q31: 0.72927911 | T31: USD bn | U31: 171.87705 | W31: 11.412819 | AD31: =C30&F31 -> SpainUSD bn
F32: % GDP | G32: 8.3916545 | H32: 1.7122006 | J32: 6.6794539 | L32: 0.0040108811 | O32: % GDP | P32: 14.371343 | Q32: 0.056954511 | T32: % GDP | U32: 13.423082 | W32: 0.89130691 | AD32: =C30&F32 -> Spain% GDP
A33: 1 | B33: AE | C33: United Kingdom | D33: Central Government | F33: LC bn | G33: 407 | H33: 102 | I33: Additional spending (£100 bn): • Funding for the National Health Service, including to expand the number of hospital beds, medical staff and equipment. Forgone revenue (£2.0bn): • Waiver of VAT and customs duties on critical medical import. | J33: 305 | K33: Additional spending (£271 bn): • Coronavirus Job Retention Scheme to subsidise furloughed employees' wages (initially for 3 months and extended several times until September 2021) and firms' social security contributions (until the 1st August 2020); • Income support for the self-employed (initially for 3 months, but extended too until September 2021); • Paid sick leave for self-isolating individuals and compensation for small firms needing to close for over 2 weeks, and support for low-income people in need to self-isolate. • Grant support for sectors impacted by local and national restrictions; • Support for low-income households by temporarily increasing Universal Credit and Working Tax Credit by £20 per week in 2020-21. The increase to Universal Credit was extended by a further 6 months from April 2021 and a one-off payment of £500 was provided to eligible Working Tax Credit claimants in April 2021; • Rent support by increasing the Local Housing Allowance; • International support, with £150 million made available to the IMF’s Catastrophe Containment and Relief Trust and £2.2 billion loan to the IMF Poverty Reduction and Growth Trust to help low-income countries; • Government support for charities; • Cover the cost of 25 hours' work a week at the National Minimum Wage for six months for hired unemployed up to 24 years old. • Boost of Active Labour Market Poilicies, including 250,000 subsidized jobs for young people. • Entitle every diner to a 50% discount of up to £10 in August. • Public sector and social housing decarbonization and Green Homes Grant. • Support for low-income people in need to self-isolate • Funding of 40,000 traineeships and doubling the number of work coaches to 27,000. • Additional transfers to devolved administrations. Forgone revenue (£34 bn): • Property tax (business rate) holiday for firms in affected sectors. • Temporary cut on stamp duty land tax until June 2021. • VAT reduced at 5% for hospitality, accommodation, and attractions until the end of September 2021, at 12.5% until March 2022, aftern which it will return to normal. | L33: 12.5 | M33: Accelerated spending (£5 bn): • Bring forward public infrastructure spending to FY2020/21. Deferred revenue (£7.5 bn): • Deferral of VAT for the second quarter of 2020 until June 21; • Deferral of income tax (self-assessment) of the self-employed until the end of January 2021. • Extension to reduced VAT rate for hospitality, accommodation and attractions (5% to 30 September 2021 then 12.5% to 31 March 2022) • Extension the window for starting deferred payments through the VAT New Payment Scheme by up to three months • Stamp Duty Land Tax: maintain nil-rate band at £500k until 30 June 2021, £250k until 30 September 2021 • Fuel Duty: one year freeze in 2021-22 Alcohol Duty: one year freeze in 2021-22 | O33: LC bn | P33: 353.03 | Q33: 1.03 | R33: • The government has put in place a £1 bn program to support firms driving innovation and development through grants and loans. • The government has provided a £30 mn convertible loan to the steel company, Celsa. | T33: LC bn | U33: 352 | V33: • The Coronavirus Business Interruption Loan Scheme (CBILS) launched with the British Business Bank supports SMEs with access to loans of up to £5 mn and for up to 6 years. The government provides lenders with a guarantee of 80% on each loan, and cover the first 12 months of interest payments and any lender-levied fees. • The Coronavirus Large Business Interruption Loan Scheme (CLBILS) provides a government guarantee of 80 percent to enable banks to make loans of up to 25 percent of companies' turnover, or up to £200 mn to firms with an annual turnover above £45 mn. • Under the Covid-19 Corporate Financing Facility (CCFF), the Bank of England will buy short term debt from larger companies. • The Bounce Back Loan Scheme will help SMEs to borrow between £2K and £50K for up to 6 years, with the government guaranteeing 100 percent of the loan and SMEs not paying any fees or interest in the first 12 months. The combined cost of the CBILS, CLBILS, CCCF, and BBLS was £112bn as of their expiration in end-March 2021. • In March 2021, a new government-backed loan scheme – the Recovery Loan Scheme (RLS) – was announced. The RLS is to help businesses of any size access loans and other kinds of finance, with up to £10 million per business. The government guarantees 80 percent of the financing. The scheme is open until 31 December 2021, subject to review, and is estimated to cost £12bn. • Trade credit Insurance for business-to-business transactions will receive up to £10 billion of government guarantees through the Trade Credit Reinsurance scheme. The scheme is for 9 months. | Y33: Deferral of income tax for the self employed and VAT payments; property tax (business rate) holiday for firms in most affected sectors, Time to Pay arrangements (tax debt restructuring) for businesses and individuals. To support the international response, the government has made available £150 million to the IMF’s Catastrophe Containment and Relief Trust. | AA33: https://www.gov.uk/government/publications/guidance-to-employers-and-businesses-about-covid-19/covid-19-support-for-businesses | AD33: =C33&F33 -> United KingdomLC bn
F34: USD bn | G34: 522.16797 | H34: 130.86273 | J34: 391.30523 | L34: 16.0371 | O34: USD bn | P34: 452.92619 | Q34: 1.321457 | T34: USD bn | U34: 451.60473 | AD34: =C33&F34 -> United KingdomUSD bn
F35: % GDP | G35: 19.270477 | H35: 4.8294563 | J35: 14.441021 | L35: 0.59184513 | O35: % GDP | P35: 16.715127 | Q35: 0.048768039 | T35: % GDP | U35: 16.666359 | AD35: =C33&F35 -> United Kingdom% GDP
A36: 1 | B36: AE | C36: United States | D36: Central Government | F36: LC bn | G36: 5328.3 | H36: 687.3 | I36: Additional spending ($622.3 bn) • Coronavirus Preparedness and Response Supplemental Appropriations Act (March 6, 2020) approved with $6.8 bn for treatments, drugs, and public health measures. • Families First Coronavirus Response Act (March 18, 2020) includes health provisions that increase outlays in Medicare, Medicaid, and other programs with federal matching by an estimated $178.9 bn. • Coronavirus Aid, Relief, and Economic Security Act (March 27, 2020) approved $128.8 bn for additional health spending, which includes funding for hospital ($100 bn), the Center of Disease Control ($4.3bn) and vaccine development and expanding Medicare payments and providing tax advantage for certain medical expense. • Paycheck Protection Program and Health Care Enhancement Act (April 23, 2020) includes $75 bn for hospitals and $25 bn for testing, with estimated budget cost of $99.6 bn. • Consolidated Appropriation Act (Dec.21, 2020) includes $23bn for vaccine procument, $9bn for vaccine distribution, $22bn for testing/tracing/covid mitigation programs, with a total estimated cost of 65.4 bn. • American Rescue Plan (Mar.12, 2021) includes $95.8bn for various activities related to vaccine distributions, testing for, treating, and responding to COVID-19 and other COVID-19 related activities, $14.3bn for preserving private health coverage of workers during the pandemic, $24.4bn for subsidizing health insurance through the government exchange/marketplaces and $23.1bn for expanding and supporting Medicaid, CHIPs and Medicare. The total estimated cost is $151.5bn. Forgone revenue ($65 bn) • CARES act includes expansion of qualified medical expenses which is estimated to reduce revenue by $9 bn. • American Rescue Plan (Mar.12, 2021) will lead to revenue changes due to preserving private health coverage of workers during the pandemic, subsidizing health insurance through the government exchange/marketplaces and expanding and supporting Medicaid, CHIPs and Medicare. The total estimated revenue loss is $56.2bn. | J36: 4641 | K36: Additional spending ($4263 bn): • Coronavirus Preparedness and Response Supplemental Appropriation (March 6, 2020) of $1.2 bn. • Families First Coronavirus Response Act (March 16, 2020) includes 2 weeks paid sick leave, up to 3 months emergency leave for those infected (at 2/3 pay), food assistance, free virus testing; federal transfers to states for Medicaid (increased by 6.2 percent during emergency period); and $1 bn in expanded unemployment insurance. Estimated increase in spending from this Act is $38.8 bn. • Coronavirus Aid, Relief, and Economic Security Act (March 27, 2020) includes $437 bn unemployment insurance and $350 bn in emergency appropriations, and $349 bn forgivable small business loans and other items. Estimated increase in spending from this Act is $1512bn. • Paycheck Protection Program and Health Care Enhancement Act (April 23, 2020) includes $62.1 bn for the Small Business Administration's loans programs and other expense, and $321 bn for the Paycheck Protection Program and small business assistance (of the $310 for the Paycheck Protection Program only $176bn was used). • The federal government (through an Executive Order by President Trump on August 8, 2020) reallocated $44 billion from the Department of Homeland Security's Disaster Relief Fund to provide extra unemployment benefits of $300 dollar per week following the expiration of the enhanced unemployment benefits mad available by the CARES act. Of the $44 billion, it is estimated that $18 billion is pre-COVID-19 appropriated funds (and therefore represents additional COVID-19 expenditure) • Consolidated Appropriation Act (Dec.21, 2020) includes $329bn support to households, $347bn support for businesses, $92bn for education and childcare, and support for other areas. The total estimated cost is $796.9bn. • American Rescue Plan (Mar.12, 2021) includes $794.2bn support to households, $86.4bn support for business, $362.1bn support for state, local and triable governments, $171bn support for education, $38.9bn support for providing childcare, and other spending in areas including transportation, federal emergency management authority, international response and others. The total estimated cost is $1646.4bn. Forgone revenue ($378 bn): • Coronavirus Aid, Relief, and Economic Security Act (March 27, 2020) includes tax rebates: phaseout rate of 5% for Adjusted Gross Income over $75,000 for single/$112,500 for head of household/$150,000 for married filing jointly. The Act also includes higher limits on losses for corporations and individual taxpayers, employee retention credit for affected employers, and other revenue provisions. The total estimated revenue cost is $288 bn. •Families First Coronavirus Response Act (March 16, 2020) has revenue implications on the budget, estimated to cost around $94 bn. •Consolidated Appropriation Act (Dec.21, 2021) provides an extension of the employee retention tax credit and also expands the usage of the earned income tax credit and child tax credit. The estimated revenue loss is $5bn. • American Rescue Plan (Mar.12, 2020) will lead to revenue changes due to the provision of the recovery rebates, child tax credit, earned income tax credit, dependent care assistance, credit for paid sick and family leave, employee retention credit and supporting pension plans. The estimated revenue change is $10bn. Please note that the support of pension plans is estimated to introduce revenue gains, which outweighs revenue losses from other measures. | L36: 17.98 | M36: Deferred revenue: • Coronavirus Aid, Relief, and Economic Security Act (March 27, 2020) includes extension of IRS income tax filing deadline by 90 days and delay of employers' payroll taxes to 2021 and 2022. • The federal government (through Executive Orders by President Trump on August 8, 2020) introduced deferral of employee social security payroll tax ($1.7 bn) and extended the delay payment of federal student loans ($4.3 bn). | O36: LC bn | P36: 510 | Q36: 56 | R36: • Coronavirus Aid, Relief, and Economic Security Act (March 27, 2020) includes $56 bn in loans for distress businesses (e.g., passenger and cargo air carriers, postal service). | T36: LC bn | U36: 454 | V36: • Coronavirus Aid, Relief, and Economic Security Act (March 27, 2020) includes $454 bn to backstop section 13(3) Federal Reserve facilities that purchase corporate obligations in primary or secondary market. | Y36: IRS extended income tax filing deadline by 90 days; Delay of employers' payroll taxes to 2021 and 2022 | AD36: =C36&F36 -> United StatesLC bn
F37: USD bn | G37: 5328.3 | H37: 687.3 | J37: 4641 | L37: 17.98 | O37: USD bn | P37: 510 | Q37: 56 | T37: USD bn | U37: 454 | AD37: =C36&F37 -> United StatesUSD bn
F38: % GDP | G38: 25.501885 | H38: 3.2895004 | J38: 22.212384 | L38: 0.086054442 | O38: % GDP | P38: 2.4409213 | Q38: 0.26802273 | T38: % GDP | U38: 2.1728986 | AD38: =C36&F38 -> United States% GDP
A39: 1 | B39: EM | C39: Argentina | D39: Central Government | F39: LC bn | G39: 1470.1 | H39: 348.6 | I39: Additional spending (AR $264.3 bn): • Budget increase for Health Ministry to improve virus diagnostics, purchase and distribute vaccines, hospital equipment, and build temporary emergency treatment centers. • Budget transfers to specific hospitals. • Monthly bonuses of AR $5K for healthcare workers (most recent April-June 2021). • Health Strategy for Families and Communities. • Financial Assistance for Health Insurance Agents. • Other (non-costed) support for the health sector includes discretionary transfers related to healthcare to provinces. Forgone revenue (AR $84.3 bn): • Exemption from import duties and statistical tax for medical supplies (April-August 2020). • Tax aliquots on credits and debits in bank accounts and other operations of 2.5 and 5 percent for health service operations (April 2020 - December 2021). • 95 percent reduction in the aliquot of employer social security contributions for a period of 90 days for health workers (April 2020 - December 2021). • Special tax compensation scheme for those who make sales of essential goods, including a VAT refund for milk sales. | J39: 1121.5 | K39: Additional spending (AR $994.3 bn): • One-off additional allowances in 2020 for pensioners, beneficiaries of child, pregnancy, and other social allowances, as well as food stamps. Additional allowances for beneficiaries of child allowances and single-taxpayers in April 2021. • Emergency family allowance for monotributistas, informal workers, and unemployed - three payments in 2020. • Assistance to community kitchens (comedores) and retiree centers for food distribution. • Transfers to provincial governments. • Wage subsidies and complementary wages for affected SMEs. • Higher spending on public works/infrastructure. • Unemployment insurance increased by AR $4K to AR $10K. • Financing for infrastructure in industrial parks. • Small-scale supports for tourism and entertainment industries, science, education, external and security sectors. • Transfers to state-guaranteed funds (FOGAR/FONDEP) for credit to SMEs and monotributistas. • Support for hard hit and critical sectors: extension of the employment support program (REPRO II) in April 21; supplementary salaries. Forgone revenue (AR $127.3 bn): • Reduction in employers' contributions to Social Security: most affected sectors granted 95% reduction in employers’ contributions to the pension system (April - May 2020); extended for employers in the REPRO II program (2021). • Special benefits (tax breaks) for police and security at the forefront of COVID response. | L39: 10 | M39: Deferred revenue: • Extension of the grace period of repayment of loans granted by the Social Security to retirees and beneficiaries of non-contributory pensions. • Deferrals in employers’ contributions to Social Security for 60 days. | O39: LC bn | P39: 703.3 | Q39: 70.3 | R39: • Loans to provinces through the Provincial Development Trust Fund (FFDP) | T39: LC bn | U39: 633 | V39: • State guaranteed, subsidized bank and provincial lending, including for working capital and payment of salaries; • Banco Nación and ANSES loans, subsidies, and transfers for housing projects; • Subsidized loans for the construction and repair of houses; • Financing for SMEs to help implement remote working facilities; • Suspension of public service cuts for 180 days due to non-payment of up to 3 consecutive invoices. | AD39: =C39&F39 -> ArgentinaLC bn
F40: USD bn | G40: 20.812696 | H40: 4.9352464 | J40: 15.877449 | L40: 0.14157333 | O40: USD bn | P40: 9.9568526 | Q40: 0.99526054 | T40: USD bn | U40: 8.9615921 | Y40: Credit lines amounting to ARS 350 billion will be provided to finance wage payments and production inputs of small and medium sized industries and commerce. The funds will come almost entirely (ARS 320 billion) from local banks. The BCRA will announce in coming days a specific regulation facilitating this. | AD40: =C39&F40 -> ArgentinaUSD bn
F41: % GDP | G41: 5.3494286 | H41: 1.2684925 | J41: 4.0809361 | L41: 0.036388195 | O41: % GDP | P41: 2.5591818 | Q41: 0.25580901 | T41: % GDP | U41: 2.3033728 | AD41: =C39&F41 -> Argentina% GDP
A42: 1 | B42: EM | C42: Brazil | D42: General Government | F42: LC bn | G42: 687.9 | H42: 108.8 | I42: Additional spending (BRL101.7 bn): Federal Government spending (BRL91.7 bn), including BRL 24.5 bn for vaccination purposes, and transfers to Local Governments (BRL 10 bn) to combat the health crisis and cover higher health spending. Forgone revenue (BRL 7.1 bn): a temporary reduction in taxes (IPI, the Industrialized Products Tax, and zero import taxes) for listed imported and domestic goods necessary to combat Covid-19. | J42: 579.1 | K42: Additional spending (BRL 560 bn): • Targeted assistance for the elderly, poor, and unemployed, including (i) expanding the cash transfer program 'Bolsa Família' to accommodate 1.2 million new beneficiaries; (ii) “Covid-19” cash transfer ("Emergency Aid) for informal workers and low-income households, of BRL600 per month in April-August and BRL 300 per month in September-December 2020 and BRL 250 per month in April - July 2021; (iii) a subsidized job retention scheme, allowing temporary suspension or reduction of private sector employees working contracts; and (iv) temporary electricity consumption subsidies for poor families. The Federal Government provided extraordinary transfers to subnational governments to compensate for revenue losses and cover larger social assistance and health costs, and granted a stay on debt service payments. Subnational governments were also allowed to renegotiate debts with public banks. Forgone revenue (BRL 19.1 bn): • Elimination of the financial transactions tax (during 9 months) | L42: 229.6 | M42: Accelerated spending (BRL 58.7 bn): Advance payment of 13th pension benefit, wage bonuses to low-income workers, and sickness/disability benefits. Deferred revenue (BRL 170.9 bn): • 2020: 4-month deferral of social contributions paid by firms and employers, 3-month deferral of small business taxes, and delayed PIT filling. Deferral of taxes paid by the telecommunications sector and of tax debt payment obligations. • 2021: 3 month deferral of small business taxes. | O42: LC bn | P42: 458.1 | Q42: 79.9 | R42: • BRL 6.8 billion credit line to SMEs (to finance payroll costs during 7 months); BRL 48.1 billion support to funds which lend to microbusinesses; BRL 20 billion support to a investment guarantee fund (to finance SMEs), 5bn credit support to the tourism sector. | T42: LC bn | W42: 378.2 | X42: Credit lines from public banks to SMEs, micro-firms, and individuals (BNDES: BRL 55.4bn, Caixa: BRL 154bn, Banco do Brasil: BRL100): • BNDES opened a working capital loan line for tourism and service sectors (small and medium-sized firms); renegotiated loan terms benefiting sectors such as oil and gas, airports, ports, energy, transportation, urban mobility, health, industry and commerce and services; and expanded credit lines to micro and small firms; created a BRL 2 bn credit line to expand emergency beds and purchase of medical and hospital equipment, for regions with less infrastructure. • Caixa extended credit lines to small-and medium-sized firms to finance working capital, purchased payroll-backed and vehicle loan portfolios from small and medium-size banks, expanded real estate and agricultural credit, and renegotiated credit to hospitals. • Banco do Brasil announced an increase in its credit lines for businesses (working capital, investments, prepayment of receivables, agribusiness) and to individuals. • Authorization of new withdrawals from mandatory savings accounts for unemployment (FGTS) - BRL 36.2 bn • Temporary cut of small employers contributions to training funds (Sistema S) and deferral of all employers contributions to an extra-budgetary mandatory savings fund (FGTS) - BRL 32.2 bn. | Y42: Payment of employers’ contributions to the FGTS and small business taxes will be postponed by 3 months. | AD42: =C42&F42 -> BrazilLC bn
F43: USD bn | G43: 133.43722 | H43: 21.104767 | J43: 112.33245 | L43: 44.537266 | O43: USD bn | P43: 88.861157 | Q43: 15.498814 | T43: USD bn | W43: 73.362344 | AD43: =C42&F43 -> BrazilUSD bn
F44: % GDP | G44: 9.2362126 | H44: 1.4608227 | J44: 7.7753899 | L44: 3.0827655 | O44: % GDP | P44: 6.1507617 | Q44: 1.0727917 | T44: % GDP | W44: 5.0779701 | AD44: =C42&F44 -> Brazil% GDP
A45: 1 | B45: EM | C45: China | D45: General Government | F45: LC bn | G45: 4904 | H45: 147 | I45: Additional spending (RMB 147 bn): Expenditure to improve epidemic prevention and control and the national public health emergency management system. Forgone revenue: Tariffs were exempted for the import of medicines, medical supplies, and other vehicles used to fight against the outbreak. | J45: 4757 | K45: Additional spending (RMB 3 tn):K48 • Help local governments finance employment initiatives, meet basic living needs, and protect market entities. • Increase the coverage and benefits of Dibao: extending social assistance programs to cover families affected by the COVID-19 and falling into poverty. • Companies that do not lay off employees or minimize layoffs receive a refund of 2019 insurance premiums. • Two-year extension of NEV (New Emission Vehicle) subsidy on purchases to the end of 2022. • Extend unemployment benefits or "minimum living guarantees" (e.g. social transfers) to migrant workers. • Increasing ceiling on special local government bond issuance, which can be spent on investment projects. Forgone revenue (RMB 1.8 tn): • VAT exemptions for goods and services related to epidemic control and for small taxpayers in Hubei; and VAT rate cut from 3% to 1% in other regions until the year end. The VAT rate cut was subsequently extended for all SMEs to end-2021. • The temporary lowering of the rates of unemployment insurance and work-related injury insurance was set to expire at the end of April 2021. It will be extended for another year until April 30, 2022. • VAT exemption for public transportation, catering, accommodation, tourism, entertainment, cultural, sports were extended to December 31, 2021. • Waived VAT on interest payments to financial institutions who extend loans of RMB 1 million or less to SMEs and sole proprietors. Instituted a 0.5 percentage point VAT reduction on secondhand vehicles sold by dealers from May until end-2023. • Corporate income tax relief for businesses in affected sectors through a longer tax loss carryover to 8 years or one-off 100 percent investment expensing deduction. • Social security contributions by employers in Hubei province and SMEs (50 percent for large firms) in the other provinces are waived until the end of December. • Allow companies suffering from serious difficulties to postpone social insurance payments until end-2020. | L45: 1600 | M45: Accelerated spending: Accelerated issuance of an increase in special local government bonds (RMB 1.6 tn). Deferred revenue: Firms are allowed to defer their social security payments by 6 months, and the due date for contributing to the “housing provident fund” is extended to end-June. In late June, the government announced that it will allow companies suffering from serious production or operation difficulties to postpone social insurance payments until the end of 2020. Collection of income tax for small and micro enterprises and self-employed deferred until 2021. | O45: LC bn | P45: 1330 | Q45: 0 | R45: • Allow China’s state-funded infrastructure projects to use up to 15% of investment for a project to pay wages. Previously only 10 percent was earmarked for worker salaries. • The central government transfer payment rate to provinces was increased from 3% to 4% for pensions. • Tax collection retention ratio for local budgets raised to 5% (March 1 to June 30). | T45: LC bn | U45: 400 | V45: • The national guarantee fund will work with banks providing loan guarantee services, planning to increase re-guarantee business by RMB 400 bn in 2020. Local government-backed guarantee/re-guarantee agencies are required to lower guarantee service costs to below 1 percent for SMEs. | W45: 930 | X45: • Starting May 21, three policy banks will issue coupons that waive loan interest payments to qualified small/micro firms and individually-owned businesses (no estimate). • The State Council announced SOEs will expand recruitment for college graduates for two consecutive years. Also, Central SOEs should provide more positions for job seekers in counties under the poverty line after surveying employment demand (no estimate). • Road tolls were exempted beginning February 17, and some service fees charged by airports and railways were cut. Road tolls were reinstated on May 6. • Electricity prices were cut by 5%, which were extended to end-2020 except those in high-energy-consuming industries. • Railway logistic fee was lowered by 50% until end-June. • The port construction fee has been exempted till end-2020, and some other port-related fees were cut. • Exempt rent payments by SMEs in the service sector on state-owned properties for three months. Landlords who offer rent reduction or exemption will receive tax cuts and loans with preferential interest rates. | Y45: Road tolls were exempted; some service fees charged by airports and railways were cut; and the price of electricity was cut by 5% with an estimated cost reduction of 60 bn RMB Railway logistic fee lowered by 50% until Jun 30 with an estimated cost of RMB 350 million. From Mar 1 to Jun 30, the port construction fee will be exempted and fees such as ‘harbor dues on cargo’ will be cut by 20%. | AD45: =C45&F45 -> ChinaLC bn
F46: USD bn | G46: 710.64739 | H46: 21.302032 | J46: 689.34536 | L46: 231.85886 | O46: USD bn | P46: 192.73267 | T46: USD bn | U46: 57.964714 | W46: 134.76796 | AD46: =C45&F46 -> ChinaUSD bn
F47: % GDP | G47: 4.7801157 | H47: 0.1432865 | J47: 4.6368292 | L47: 1.559581 | O47: % GDP | P47: 1.2964017 | T47: % GDP | U47: 0.38989524 | W47: 0.90650644 | AD47: =C45&F47 -> China% GDP
A48: 1 | B48: EM | C48: India | D48: Central Government | F48: LC bn | G48: 8084.44 | H48: 1041.23 | I48: Additional spending (Rs 1041 bn): • Additional spending on health infrastructure, including for COVID-19 testing facilities, personal protective equipment, isolation beds, ICU beds, ventilators and medical screening. • The budget for FY2020/21 released on February 1, 2021 provisioned 350 billion Rs for the country's vaccination program with the possibility of expanding the envelope. • In June 2021, the central government announced support to states for purchase of vaccines (100 billion Rs). • In July 2021 a package of health care infrastructure spending (India COVID 19 Emergency Response and Health Systems Preparedness Package, about 230 billion Rs) was announced. | J48: 7043.21 | K48: Additional spending (Rs 7043.2 bn): • On March 26, the central government announced a package that provides insurance coverage for workers in the healthcare sector, substantial in-kind (food; cooking gas) and cash transfers, as well as wage support to poor households (Rs 1.49 tn). • Between May 13 and 17, additions to this initial package were announced. These focused on extending the government's existing rural employment guarantee scheme (additional Rs 400 bn), extension of food support to migrants (Rs 35 bn) and miscellaneous other measures (about Rs 93 bn). • On June 30, authorities extended the provision of food rations to vulnerable households (Rs 829 bn). • On August 20, authorities extended and expanded unemployment benefits for workers who are covered under the Employees State Insurance Corporation (ESIC) scheme. • On October 12, authorities announced measures targeting consumption and public investment. On the consumption side authorities: i) offered public sector employees a cash payment which can be used to buy (via digital mode) goods that attract GST of 12% or more (i.e. discretionary, nonessential items) (Rs 56.8 bn): ii) a Special Festive Advance Scheme which is an interest-free advance to central government employees (Rs 40 bn). On the public investment side authorities announced i) additional spending by the central government (Rs 250 bn) and a lending scheme for state governments, involving a 50-year interest free loan (Rs 120 bn). • On November 12, authorities announced a new package (Rs 2650.8 bn) which included: (i) a Production Linked Incentive scheme targeting 13 priority sectors (1459.8 billion Rs.) to be disbursed over 5 years (no impact on the current fiscal year); (ii) more spending on fertilizer subsidies (650 billion Rs.); (iii) spending on urban housing projects (180 billion Rs.); (iv) additional capital expenditure and industrial infrastructure and incentives (102 billion Rs.); (v) support for rural employment (100 billion Rs.) and employment support in the formal sector (60 billion Rs.). • In April 2021, in response to the recent surge in infections, the authorities announced that free food grains to individuals in May and June (260 billion Rs). The authorities also extended a scheme for providing interest-free loans to states for capital expenditure to FY2021/22 (150 billion Rs.) and expedited the release of Disaster Response Fund to state governments (from June to May). In June 2021, in response to the second wave, the additional food grains were extended from end-June to end-November and additional fertilizer subsidies were announced. | L48: 1340 | M48: Accelerated Spending (Rs 660 bn: • On March 26, 2020, the government accelerated the first installment of payments to lower income farmers under PM KISAN (160 billion rupees). As part of the scheme announced on June 20th, 2020, the government expedited the implementation of a set of public works projects spanning 12 different ministries, to boost employment and livelihood opportunities for migrant workers returning to villages (500 billion rupees) Deferred revenue (Rs 680 bn): • Extension of income tax filing deadline (3 months); reduction of penalty for late payments; date for filing fiscal year 18/19 GST tax liability extended (3 months); other miscellaneous relaxation of tax regulatory/administrative requirements. • Reduction in up-front tax deductions for workers (Rs 500bn). • On June 12, the GST council announced that it would halve the interest rate charged on overdue filings of small businesses. | O48: LC bn | P48: 12291 | Q48: 641 | R48: • Equity infusion for micro, small, and medium-sized enterprises (500 billion Rs.) and a viability-gap funding scheme for private sector involvement in social infrastructure (81 billion Rs.), both announced in May; and equity infusion in infrastructure financing funds and platforms (60 billion Rs.) announced in November. | T48: LC bn | U48: 10450 | V48: • Full guarantees for a collateral-free lending program (Rs 3 tn). • Liquidity provision and partial credit-guarantee schemes for non-bank financial companies (Rs 750 bn). • Subordinate debt provision for MSME sector (Rs 200 bn). • Credit provisions to be guaranteed by government to farmers on concessional terms (Rs 3 tn) and for street vendors and other miscellaneous measures (Rs 160 bn). • Government to provide a guarantee for credit under a new infrastructure fund for agriculture (Rs 1 tn) and for micro-food enterprises (Rs 100 bn). • Numerous miscellaneous guarantee items (Rs 321 bn). •On November 12, the collateral-free lending program was extended to March 31, 2021 and expanded to provide additional support to 26 stressed sectors. • In June 2021, a new loan guarantee scheme for Covid-affected sectors was announced (500 billion Rs) and the existing credit guarantee scheme was extended (1500 billion Rs). | W48: 1200 | X48: • Loans to companies in the electricity distribution sector (initially 900 billion but expanded to 1200 billion Rs), carried out by Power Finance Crops and Rural Electrification Corps (both SOEs) under state government guarantees. Government also relaxed the borrowing limits of DISCOM companies on a one-time basis, allowing more electricity distribution companies to take advantage of the borrowing scheme. | AA48: https://pib.gov.in/PressReleseDetail.aspx?PRID=1607911 | AD48: =C48&F48 -> IndiaLC bn
F49: USD bn | G49: 108.91796 | H49: 14.028016 | J49: 94.889947 | L49: 18.053207 | O49: USD bn | P49: 165.59102 | Q49: 8.6358999 | T49: USD bn | U49: 140.78807 | W49: 16.167051 | AD49: =C48&F49 -> IndiaUSD bn
F50: % GDP | G50: 4.094285 | H50: 0.52732067 | J50: 3.5669643 | L50: 0.6786298 | O50: % GDP | P50: 6.2246558 | Q50: 0.32462813 | T50: % GDP | U50: 5.2922995 | W50: 0.60772818 | AD50: =C48&F50 -> India% GDP
A51: 1 | B51: EM | C51: Indonesia | D51: Central Government | F51: LC bn | G51: 1439950 | H51: 314450 | I51: Additional spending (IDR 276 tn): • Several fiscal packages have been announced by the government amounting to IDR 314.5 tn for the years 2020 and 2021. .• For 2020 Economic recovery program (PEN), health budget is around IDR 100 tn. • 2021 PEN budget for 2021 stands at IDR 215 tn as of September 14, 2021. | J51: 1125500 | K51: Additional spending (IDR 942.1 tn): •The approved budget for 2020 is IDR 475.1 tn including social protection, cash transfer etc •The approved budget for 2021 is IDR 467.0 tn . Several revisions have been announced by the government but details remain to be known. Forgone revenue (IDR 183.4 tn): • For 2020, approved tax incentives amounted to IDR 120 tn. • For 2021, the approved budget is IDR 63.4 tn •Packages include various tax reliefs and incentives: exemption and reduction of income taxes (with an income ceiling) and a reduction of the corporate income tax from 25 percent to 22 percent. | M51: Accelerated spending: The second fiscal package includes acceleration in VAT refund from April to September. Deferred revenue: The second fiscal package includes delayed payments of income tax for businesses from April to September. | O51: LC bn | P51: 135150 | Q51: 35150 | R51: • Capital injection to SOEs. | T51: LC bn | U51: 100000 | V51: • Government guarantees for bank lending to micro, small, and medium enterprises (IDR 150 tn), expected to be financed by Bank of Indonesia's purchase of new government recovery bonds. | AD51: =C51&F51 -> IndonesiaLC bn
F52: USD bn | G52: 98.860321 | H52: 21.588686 | J52: 77.271635 | O52: USD bn | P52: 9.2787752 | Q52: 2.4132368 | T52: USD bn | U52: 6.8655384 | AD52: =C51&F52 -> IndonesiaUSD bn
F53: % GDP | G53: 9.3296348 | H53: 2.037365 | J53: 7.2922699 | O53: % GDP | P53: 0.87565551 | Q53: 0.2277417 | T53: % GDP | U53: 0.6479138 | Y53: The first package (10.3), second package (22.9) and tax and expenditure measures from the third package (255.1). How the 150 tn from the third package will be used is not fully clear yet, but most likely in the form of liquid support for firms (thus below the line in the budget). | AD53: =C51&F53 -> Indonesia% GDP
A54: 1 | B54: EM | C54: Mexico | D54: Non-financial Public Sector | F54: LC bn | G54: 151 | H54: 103.2 | I54: Additional spending: The authorities have increased public health spending to ensure sufficient supply of medical equipment and materials. | J54: 47.8 | K54: Additional spending: • Loans with optional repayment to be granted by the Ministry of Economy to SMEs that maintain employees on payroll, self-employed, and domestic workers. Eligibility is assessed using IMSS database. • Loans with optional repayment to be granted by the Ministry of Economy to family businesses, previously registered in the Welfare Census. • Unemployment subsidy for 3 months to workers that hold a mortgage with the Housing Institute. • Housing program. | L54: 92 | M54: Accelerated spending: • Frontloaded social pension payments for the elderly and people with special needs. • Procurement processes and VAT refunds are to be accelerated. | O54: LC bn | P54: 288.2 | Q54: 19.2 | R54: • Institute for Social Security and Services (ISSSTE) loans to state workers with low interest rates. • Personal loans granted by the Institute of the National Fund for the Consumption of Workers (Fonacot). • Special Program to Reactivate the Economy against COVID by Housing Fund of the Institute for Social Security and Services(Fovissste). | T54: LC bn | U54: 6 | V54: • Development bank guarantees program | W54: 263 | X54: • Development banks to provide loans, particularly to small- and medium-scale enterprises. | Y54: At the state-level, several state governments have announced support, including deferral of tax payments or tax holidays. | AA54: Credits loans SME (MXN 25 bn) 1. CRÉDITO SOLIDARIO A LA PALABRA 1.1 Crédito solidario a la palabra para empresarios solidarios http://www.imss.gob.mx/prensa/archivo/202005/280 1.2 Crédito solidario a la palabra para trabajadoras del hogar- http://www.imss.gob.mx/prensa/archivo/202005/289 1.3 Crédito solidario a la palabra para trabajadores independiente http://www.imss.gob.mx/prensa/archivo/202005/289 Credits loans to family business of Welfare Census (MXN 25 bn) https://www.gob.mx/se/articulos/ante-la-pandemia-del-coronavirus-fortalece-gobierno-federal-apoyo-a-pequenos-negocios?idiom=es Loans ISSSTE (MXN 35 bn) https://www.gob.mx/issste/prensa/redisena-el-issste-programa-de-prestamos-personales-2020-para-ayudar-a-reactivar-la-economia-en-el-pais?idiom=es VAT refunds accelerated https://www.gob.mx/sat/prensa/las-devoluciones-de-impuestos-se-realizan-en-tiempo-y-forma-de-acuerdo-con-la-normatividad-aplicable-17-2020?idiom=es Frontload pensions (MXN 46.4 bn) https://www.gob.mx/bienestar/prensa/en-apoyo-a-la-economia-popular-se-adelanta-pago-de-pensiones-de-adultos-mayores-y-personas-con-discapacidad?idiom=es Payment extensions, unemployment insurance to workers that hold a mortgage with the Housing Institute (MXN 20 bn) http://www5.diputados.gob.mx/index.php/esl/Comunicacion/Boletines/2020/Marzo/18/3510-La-Comision-de-Vivienda-se-reunio-con-el-titular-del-Infonavit https://portalmx.infonavit.org.mx/wps/portal/infonavit.web/el-instituto/el-infonavit/sala-de-prensa/!ut/p/z1/jZFNa4NAEIZ_Sw8e67xrqmx6syVd80FQwhI7l6LBbATjBmMr_fdN014CiWZuMzwPvLxDTClxnX2VJmtLW2fVaX_n4CNQQPT6JJZyMfeRIJ4rzCBWY9D6DHgSUC8QSyUjifBtMp2MFyNPaUF84QexhyRKBOKV9KD9fx83JsR9fg_A9-TvAbg_3pr4jNxqwMcAIIaA3w6HUsyITWXzv4eFdT6ShrgptkVTNO5nczrv2vZwfHbgoOs611hrqsLd2L2Da8rOHltKL0k67LXWKcrpI-ffXfjwA2ChJss!/dz/d5/L2dBISEvZ0FBIS9nQSEh/?numeroBoletin=024&mes=abril&anio=2020 Fonacot Loans (MXN 3 bn) https://www.fonacot.gob.mx/SaladePrensa/Paginas/comunicados.aspx?idc=396 | AD54: =C54&F54 -> MexicoLC bn
F55: USD bn | G55: 7.0279602 | H55: 4.8032152 | J55: 2.224745 | L55: 4.281936 | O55: USD bn | P55: 13.41363 | Q55: 0.89362143 | T55: USD bn | U55: 0.2792567 | W55: 12.240752 | AD55: =C54&F55 -> MexicoUSD bn
F56: % GDP | G56: 0.65442397 | H56: 0.44726194 | J56: 0.20716202 | L56: 0.39872189 | O56: % GDP | P56: 1.2490397 | Q56: 0.083211524 | T56: % GDP | U56: 0.026003601 | W56: 1.1398245 | AD56: =C54&F56 -> Mexico% GDP
A57: 1 | B57: EM | C57: Russia | D57: Central Government | F57: LC bn | G57: 5354 | H57: 775 | I57: Additional spending: • RUB 224 billion – new infection hospitals, additional beds and re-equipment of existing beds, special ambulances and equipment, medicine • RUB 346 billion – bonus fund for medical staff, R&D in diagnostics and prevention • RUB 32 billion – other • RUB 141 billion expected in 2021. • Medical staff directly engaged in coronavirus efforts will receive additional federal compensation Forgone revenue: • RUB 32 bn - zero import duties for pharmaceuticals, medical supplies and equipment. | J57: 4579 | K57: Additional spending (RUB 3.64 tn): • Quarantined or self-isolating individuals to receive sick leave benefits from the Social Insurance Fund. ·Sick leave benefits for the quarantined or self-isolating individuals and increases in unemployment and child benefits • Interest rate subsidies for affected companies to finance minimum wages. • Interest rate subsidies for systemically important companies, conditional on employment keeping above 90 percent, to support working capital. • Support for large companies (construction, car-makers, air transportation, light industry). • Credit to affected sectors to protect employment with partial/full asset write-offs if employment is kept above 80%. • Grants for SMEs in affected industries to cover salaries and disinfection/COVID-19 prevention measures. • Support to airlines (RUB 23 bn) (subsidies), airports (RUR 11 billion) (subsidies) and car-K60makers (RUB 25 bn) (state procurement and interest rate subsidies). • Federal transfers to regions. • Construction sector support, including subsidized rates for a new mortgage program (costed at RUB 6 bn). • Expected expenditure measures in 2021: 1721 billion : 851 billion to the corporate sector (employment retention programs- 477 billion, and industry specific support and development programs-373 billion) and 100 billion to local governments; 270 billion of extra social spending announced in the President State of Nation Address (another RUB10 thousand one-off benefit to all schoolchildren, 170 billion; 500 billion of RUB10 thousand one-off benefit to all pensioners and RUB15 thousand one-off benefit to all military and law-enforcement personnel. Forgone revenue (RUB 939 bn): • Social contributions by SMEs on wages in excess of the minimum wage reduced from 30 to 15 percent, permanently. • Taxes and social contributions for Q2 written off (excluding VAT) targeting SMEs, Social NGO, sole proprietors (covers 1.5 mn enterprises). • Refund for the self-employed on 2019 taxes and credit of one minimum salary toward 2020 taxes. • Sole proprietors will get a tax credit of one minimum salary toward their social insurance payments. • For SMEs in the affected sectors: zero rent to the federal government for three months. • Tourism firms not to contribute to the tourist reserve fund. | L57: 460 | M57: Deferred revenue: • Tax deferrals for SMEs and most affected companies on most taxes (excluding VAT, PIT, MET, and social contributions). • Deferrals on social contributions for SMEs in affected sectors for 6 months. • For SMEs in the affected sectors: deferrals on rent payments to all levels of government until the end of the year. | O57: LC bn | P57: 1567 | Q57: 567 | R57: • RUB 67 billion for restructuring regional debt to the federal government. • RUB 500 billion for recapitalization of leasing firms due to potential problems of their clients in the transportation sector; VEB recapitalization to support new investment projects; Sberbank recapitalization | T57: LC bn | U57: 500 | V57: • The federal government announced guarantees of up to RUB 500 bn on bank lending to firms, including (1) RUB 220 bn in guarantees to VEB to guarantee bank credit to systematically-important enterprises; (2) RUB 160 in supporting domestic aircraft makers by issuing guarantees on domestic leasing companies 2020-21 borrowings for purchasing domestically produced passenger aircrafts and helicopters. | W57: 500 | X57: • The CBR has introduced a new RUB 500 bn facility for SME lending and reduced the interest rate on the existing RUB 175 bn facility. As part of the new RUB 500 bn facility, CBR has introduced a RUB 150 bn credit line to finance 6-month zero-interest loans to SMEs and individual entrepreneurs to cover payroll. | AD57: =C57&F57 -> RussiaLC bn
F58: USD bn | G58: 74.006321 | H58: 10.712532 | J58: 63.293788 | L58: 6.3584063 | O58: USD bn | P58: 21.660049 | Q58: 7.8374269 | T58: USD bn | U58: 6.9113112 | W58: 6.9113112 | AD58: =C57&F58 -> RussiaUSD bn
F59: % GDP | G59: 5.0052605 | H59: 0.7245194 | J59: 4.2807411 | L59: 0.43003732 | O59: % GDP | P59: 1.4649315 | Q59: 0.53006774 | T59: % GDP | U59: 0.46743187 | W59: 0.46743187 | AD59: =C57&F59 -> Russia% GDP
A60: 1 | B60: EM | C60: Saudi Arabia | D60: General Government | F60: LC bn | G60: 67.6 | H60: 54 | I60: Additional spending (SAR 54 bn): Budget reallocation within the Ministry of Health budget or a reallocation from other parts of the budget for emergency spending to fight COVID-19. | J60: 13.6 | K60: Additional spending (SAR 9.6 bn): • Wage benefits to employers who keep their workers to be provided through the unemployment insurance scheme, SANED (SAR 8 bn). This wage benefits have been extended. • Ministry of Energy announced temporary electricity subsidies to commercial, industrial, and agricultural sectors (SAR 0.9 bn). • The Ministry of Finance program to help businesses defer loan payment due this year (SAR 0.67 bn). Forgeone revenue (SAR 4 bn) * Expat levy exemption | L60: 42.5 | M60: Accelerated spending (SAR 4 bn) Deferred revenue (SAR 38.5 bn): Deferred declaration & payment of taxes for 3 months, waiver of customs duties (30 days to 3 months), waiver of expat fees for 3 months; and waiver of municipal fees on companies for 3 months. | O60: LC bn | P60: 25.7 | Q60: 25.7 | R60: • Off-budget support provided by the National Development Funds (NDF): SAR 22 bn distributed as follows: (i) loan rescheduling/restructuring and different loan programs to SMEs: SAR13 bn. (ii) support to employment programs in the private sector: SAR 5 bn. (iii) social loans to families with low incomes: SAR4 bn. Saudi Industrial Development Fund (SIDF) support to 536 private sector industrial enterprises impacted by the coronavirus pandemic SAR 3.7 billion | T60: LC bn | AA60: https://www.mof.gov.sa/en/MediaCenter/news/Pages/News_20032020.aspx | AD60: =C60&F60 -> Saudi ArabiaLC bn
F61: USD bn | G61: 18.026667 | H61: 14.4 | J61: 3.6266667 | L61: 11.333333 | O61: USD bn | P61: 6.8533333 | Q61: 6.8533333 | T61: USD bn | AD61: =C60&F61 -> Saudi ArabiaUSD bn
F62: % GDP | G62: 2.5748045 | H62: 2.0567965 | J62: 0.51800802 | L62: 1.618775 | O62: % GDP | P62: 0.97888278 | Q62: 0.97888278 | T62: % GDP | AD62: =C60&F62 -> Saudi Arabia% GDP
A63: 1 | B63: EM | C63: South Africa | D63: General Government | F63: LC bn | G63: 291.3 | H63: 38.3 | I63: Additional spending: for medical equipment and staff for health facilities, and policing the lockdown, vaccine program and rollout, and second wave management. Forgone revenue: VAT and customs duty exemptions for essential sanitary products during the pandemic (immune boosters, hand sanitizers, patient monitoring devices, etc.). | J63: 253 | K63: Additional spending (R 227 bn): • Measures to support workers’ unemployment insurance benefits (with R 80 bn funding from Unemployment Insurance Fund); create a New Covid-19 Social Relief of distress grant for the unemployed who do not receive grant or UI payment (extended to April 2021). • Increase transfers to households: grants and food distribution and public work program expansions. • Increase child support and all other grants from May till Oct 2020. • Distribute food parcels and provide transfers to SMEs. • Municipalities to use higher central transfers to fund emergency water supply, sanitation of public transport and facilities, and food and shelter for the homeless (R 20 bn). • Contribute R 150 mn Rand to a solidarity fund to combat virus spread, track spread, ill care, support for disrupted lives. • Additional allocations by the Department of Industry and Trade, Department of Tourism, and Department of small enterprises to assist SMEs in distress (R 2.7 bn). Forgone revenue (R 26 bn): • Tax subsidy of up to R 750 to employees with an income below R 6,500 per month. • Skills development levy holiday for four months. | L63: 44 | M63: Deferred revenue: • Deferral of 35 percent of PAYE liability for four months for businesses with expected gross income of less than R 100 mn. • Deferral of 35 percent of provisional tax payments for the next six months for businesses and the self-employed with expected gross income of less than R 100 mn. • A 90-day deferral for alcohol and tobacco excise duty due to be paid in May and June 2020. • Three-month deferral for filing and payment date of carbon tax. | O63: LC bn | P63: 203 | T63: LC bn | U63: 200 | V63: The Treasury will guarantee up to R 200 bn in loans where also the banks are taking part of the risk to help businesses (with a cap of R100 million per loan) pay operating expenses and restart, suppliers etc (extended to June 11 2021). | W63: 3 | X63: Programs from the industrial development corporation to support businesses. | AD63: =C63&F63 -> South AfricaLC bn
F64: USD bn | G64: 17.693238 | H64: 2.3262994 | J64: 15.366939 | L64: 2.6725111 | O64: USD bn | P64: 12.329994 | T64: USD bn | U64: 12.147778 | W64: 0.18221667 | AD64: =C63&F64 -> South AfricaUSD bn
F65: % GDP | G65: 5.2761463 | H65: 0.69370547 | J65: 4.5824408 | L65: 0.88478225 | O65: % GDP | P65: 4.0820636 | T65: % GDP | U65: 4.0217375 | W65: 0.060326062 | AD65: =C63&F65 -> South Africa% GDP
A66: 1 | B66: EM | C66: Turkey | D66: Non-financial Public Sector | F66: LC bn | G66: 176.9 | H66: 19.4 | I66: Additional spending: including medicine, vaccine and medical equipment spending, protective equipment and other needs of University Hospitals and Institutions, SUT expenditure, performance pay for medics. | J66: 157.5 | K66: Additional spending: • Cash aid and raised minimum pension (TL 29.8 bn); • Unemployment benefits (TL 7.3 bn); • Short-time work allowance (TL 36.7 bn); • Cash aid to employees (TL 14 bn). • Normalization support (TL 4.8 bn). • Social Support Program (TL 9.9 bn). Forgone revenue (TL 44.6 bn): 40,6 bn TL forgone tax revenue and 4 bn TL Financing cost of Tax and SSP Deferrals • VAT rate on food and beverage, cinema, theatre, museum and accommodation services was reduced from 8% to 1% until 31 December, 2020. It is prolonged for five months for 2021.It was again prolonged to end of September 2021. • VAT rate on workplace rental services, passenger transportation, maintenance and repair of small home appliances, wedding and marriage organizations, residential maintenance, repair, painting, and cleaning services was reduced from 18% to 8% until 31 December, 2020. It is prolonged for five months for 2021. It was again prolonged to end of September 2021. • Withholding tax on workplace rent was reduced from 20% to 10% until 31 December, 2020. It is prolonged for five months for 2021.It was again prolonged to end of September. • VAT rate on passenger transportation by air was reduced to 1% from 1 April, 2020 to 30 June, 2020. • VAT rate on education and training services between 1 September, 2020 and 30 June, 2021 was reduced from 8% to 1% temporarily. It was again prolonged to end of September 2021. · Support to tradespeople (TL 9 bn), Supports for Artists (TL 0,2 bn) and Additional Payments for Treasury Interest Supported Loans Given to Agricultural Producers and Tradesmen (1,2 bn) | L66: 70.2 | M66: Accelerated spending: Early annual bonus payment to pensioners. Deferred revenue: •Tax deferrals for the self-employed, farmers, tailors, grocers, lawyers, financial advisers, architects, engineers, doctors, and dentists. • Tax deferrals for those aged over 65 or those with chronic illnesses. • Postponed payments regarding withholding tax returns and VAT declarations, as well as Social Security Contribution premiums (e.g., for retail/shopping malls, iron-steel, automobiles, logistics-transportation sectors). • Land occupation and revenue sharing payments in leasing of hotels postponed for 6 months. • Accommodation tax deferred. • Retail, shopping malls, iron-steel, automobiles, logistics-transportation, etc. are offered to postpone VAT and Social Security Contribution. | O66: LC bn | P66: 486.2 | Q66: 21 | R66: • Turkey Wealth Fund (TWF) has been granted new rights to take equity in firms affected by Covid-19, and was assigned to inject a core capital of 0.4 percent of GDP into three state banks, funded by issuance of Treasury bonds. | T66: LC bn | U66: 322 | V66: • Treasury-backed credit guarantee system. • Credit guarantee fund doubled in size from TL25 to 50 billion as part of the fiscal package. | W66: 143.2 | X66: • All public banks: Principal and interest payments by those firms whose cash flows are affected adversely by Covid-19 will be postponed by minimum 3 months and provided with refinancing. • Various state bank lending schemes, including: extending repayment terms on specified credit card loans; low interest credit packages for low income households; April, May and June repayments by tradespeople extended without penalty; new low interest loans for tradespeople; and new credit cards for merchants with longer repayment periods; new lending campaigns directed to firms "maintaining" employees. • On June 1, public deposit banks (Ziraat Bank, Halkbank and Vakifbank) launched new retail loan campaigns for house purchases and consumer spending. • Farmers’ loans that will become due in May and June have been postponed by six months. | AD66: =C66&F66 -> TurkeyLC bn
F67: USD bn | G67: 25.234121 | H67: 2.7673372 | J67: 22.466784 | L67: 10.013767 | O67: USD bn | P67: 69.354606 | Q67: 2.9955712 | T67: USD bn | U67: 45.932092 | W67: 20.426943 | AD67: =C66&F67 -> TurkeyUSD bn
F68: % GDP | G68: 3.5051336 | H68: 0.38439565 | J68: 3.1207379 | L68: 1.3909575 | O68: % GDP | P68: 9.6336684 | Q68: 0.41609839 | T68: % GDP | U68: 6.3801753 | W68: 2.8373947 | AD68: =C66&F68 -> Turkey% GDP
A69: 0 | B69: AE | C69: Belgium | D69: General Government | F69: LC bn | G69: 37.2 | H69: 9.6 | I69: Additional spending (€9.6 bn): on medical equipment, tests, contact tracing, administration, etc. Measures also include advance payments to hospitals (2bn allocated based on Covid-related cost pressures and revenue losses) as well as a structural increase in the budget for mental health care (200mn annually; for 2020 prorated from Sept) and the federal health sector (wage increases and improvement in working conditions; 350mn in 2021, 600mn thereafter). An additional, one-off 200mn was allocated to federal health workers in 2020. Additional spending on vaccine rollout. | J69: 27.6 | K69: Additional spending (€23.4 bn): • Federal government eased access to temporary unemployment for firms affected by Covid-19, raised the benefit replacement rate, and introduced a daily premium, as well as eased access to replacement income for the self-employed. It also introduced Covid-19 parental leave and increased unemployment benefits (extension of switching on allowance for the young, freezing of degressivity, etc.), social assistance benefits, and support to local social services. Additional measures have been taken to support hard-hit sectors and vulnerable groups as the pandemic evolved, while key temporary measures have been extended until end-December 2021. • Regional governments provided transfers for companies and self-employed affected by closures or significantly reduced turnover; further support to specific, affected sectors in addition to the health care sector; support for utility bills for affected households; and a host of smaller support measures. Similar measures have been reintroduced in Oct-Nov 2021 in the context of the re-imposition of restrictions and the second lockdown. These are expiring in 2021. Forgone revenue (€4.2 bn): Loss carry backward for CIT and PIT, tax exemption for regional support measures (for firms affected by closures and reduced turnover), social security contribution exemption for self-employed, temporary reduction in VAT in the hospitality sector (e.g., food and non-alcoholic beverages), increase in the investment allowance for SMEs and natural persons (extended until end-2022), and increase in the CIT allowance for restaurant and reception costs. Suspension of penalties for delays or non-performance of suppliers to the public sector. | L69: 12.9 | M69: Deferred revenue (€12.9 bn): • Deferred payment of tax and social security contributions for affected firms, self-employed, and households, without application of interest charges and penalties, estimated at about 10 billion euros, and deferral of advance VAT payment in December 2020. Additional deferral of SSC payments due in Q4 for firms affected by the second lockdown. | O69: LC bn | P69: 53.6 | Q69: 1.6 | R69: Government loans (1.3bn): • Federal loan to Brussels Airlines; and various (subordinated) loans provided by regional governments for companies and self-employed affected by Covid-19 (facing liquidity problems, etc.); some of which channeled through regional investment vehicles. Equity injections (0.3bn): • Capital increase in Flemish and Brussels regional investment companies that will use the funds to provide capital support to firms in need. | T69: LC bn | U69: 52 | V69: • Federal government launched a guarantee mechanism for all new credits and credit lines, initially with a maximum maturity of 12 months granted by banks to viable non-financial corporations and self-employed (ended Dec 2020). Second scheme introduced end-July 2020 to extend the maturity to 36 months, replace the loss tranching by uniform loss sharing between government and banks (80-20), and ease the viability criterion. The second scheme carved 10bn out of the total envelope of 50bn and is targeted at SMEs. Take-up is about 2.1bn. The scheme has been extended until end-2021. · Regional governments also provide guarantees for affected companies and self-employed in need of bridge loans. Take-up is about 0.5bn. · The federal government signed a memorandum of understanding with Credendo ECA, Assuralia and private credit-insurance firms, committing to provide reinsurance for short-term (< 2yrs) trade credit insurance. | AD69: =C69&F69 -> BelgiumLC bn
F70: USD bn | G70: 42.455685 | H70: 10.956306 | J70: 31.499379 | L70: 14.722536 | O70: USD bn | P70: 61.172708 | Q70: 1.826051 | T70: USD bn | U70: 59.346657 | AD70: =C69&F70 -> BelgiumUSD bn
F71: % GDP | G71: 8.2451011 | H71: 2.127768 | J71: 6.1173331 | L71: 2.8591883 | O71: % GDP | P71: 11.880038 | Q71: 0.35462801 | T71: % GDP | U71: 11.52541 | AD71: =C69&F71 -> Belgium% GDP
A72: 0 | B72: AE | C72: Czech Republic | D72: General Government | F72: LC bn | G72: 523.4 | H72: 148.4 | I72: Additional spending: • Purchases of medical equipment, vaccine, tests, etc. (CZK 29.9bn). • The government approved higher premium payments on state-covered health insurance--increase by CZK500 per person as of June 2020 (CZK 20.9bn) and by CZK200 per person since January 2021 (CZK50.9bn). • Debt relief of hospitals (CZK 6.6bn). • Bonus for workers in social services, hospitals, emergency responders, hygienically stations (CZK 35.8 bn). • Other health measures: (mobile collection teams, Smart Quarantine establishment, anti-covid programmes for technological firms) (CZK 1.7bn). Forgone revenue: • Remission of VAT on purchase of the vaccine, tests, respirators (CZK 2.6bn) | J72: 375 | K72: Additional spending: • Payments for employment support: Employees affected during the shutdown due to government measures will receive full wages of which the government covered 80 percent up to CZK 39,000/month (since October the government has covered 100% up to CZK 50,000/month in case of business shutdown due to government measures). Staff in businesses affected receive 60-100% of gross wages with a state contribution of 60% of total labor costs per employee (up to CZK 29,000/month) (CZK 49.2bn). • Care Allowance to parents, who cannot work because they need to care for children up to 13 years, of 80% of eligible income until end of June 2020 (calculated based on a progressive table) for sick leave. During the other waves of COVID, care allowance to parents with children up to 10 years, 70% of eligible income - since March 2021 80% of eligible income (in total CZK 13.2bn). • Care Allowance to self-employed persons (CZK 434 per day in March 2020, CZK 500 per day since April), who cannot work because they need to care for children up to 13 years. During the other waves of COVID for parents with children up to 10 years, CZK 400 per day (CZK 3.1bn) • The state covers half of business property rents in Q2-Q4 2020 (CZK 9.9bn). • Programs in support of the sports, culture, tourism, transport, restaurants, agriculture and other closed sectors (CZK 45.7bn). • One-off cash benefit for pensioners in amount of CZK 5000 (CZK 15.0bn). • Loss carryback measure: Taxpayers who report tax losses in 2020 due to the state of emergency, will be able to reduce their tax bases for the tax years 2019 and 2018 by this loss (maximum CZK 30 million) (CZK 4.3bn). • Self-employed receive lump sum of CZK 500 per day during Mar 12 and Jun 8 (CZK 20.2bn), additional lump-sum assistance grant (CZK 500 per day) to small business (Ltd) during Mar 12 and Jun 8 (CZK 1.7bn) and additional lump-sum assistance grant (CZK 350 per day) to contractors (CZK 0.1bn). The subjects in affected sectors received identical lump-sum during Oct 5 2020 and Feb 15 2021 (CZK 7.6bn) and lump-sum of CZK 1000 per day during Feb 1 and May 31 2021 (CZK 14bn) • Other expenditure (CZK 9.6bn). Forgone Revenue: • The effective reduction in the personal income taxation and increase in the basic rebate for taxpayers (in total CZK 99.1bn). • Waived social security contributions paid by employers (24.8%) with a maximum of 50 employees for the period between June and August. This support will be provided concurrently with the wage compensation if two conditions are satisfied – minimum employment level of 90% and wages paid in March 2020 are at least 90% (CZK 13.3bn). • Introduction of extraordinary allowance at CZK 370 per day for employees who have been ordered to quarantine (CZK 1.1bn). • Reduced VAT rate to 10% for accommodation, sports and culture services (CZK 2.6bn). • Reduced road tax rate for vehicles above 3.5t (CZK 2bn) and decrease in excise tax on diesel oil (CZK 5.6bn). • Abolition of the real property acquisition tax (CZK 27.6bn). • Lower dividends from Airport Prague (CZK 1.5bn). • Introduction of extraordinary accelerated depreciation on assets (in the 1st and 2nd depreciation classes), acquired in 2020 and 2021 (CZK 25bn); increase in the limit for the depreciation of tangible fixed assets and other measures (CZK 3.7bn). | L72: 14.3 | M72: Deferred revenue: • Postponement of advance payments on social security and health insurance contributions for self-employed by 6 months (CZK 14.3bn) | O72: LC bn | P72: 881.3 | Q72: 0.9 | R72: Government loans: • The CMZRB provided CZK 0.9bn through interest-free loans, the rest will be handled through state guarantees on loans of commercial banks (COVID I Programme). | T72: LC bn | U72: 880.4 | V72: • COVID III Program (Guarantees will cover up to 30% of loan principal. The state will issue 80-90% of the guarantees (total amount of CZK 150bn). Estimates of the amount of guarantees offered will allow SMEs to access loans amounting to CZK500bn. • COVID II Program of state guarantees in total amount of CZK 20bn (loans up to CZK 15 million, state contribution on interest costs up to CZK 1 million, state guarantee up to 80% of loan, 3-year maturity) • COVID Plus Program of state guarantees provided by Export Guarantee and Insurance Corporation in the amount of CZK 330bn. • COVID Prague Program (CZK 1.6bn). • COVID Sport Guarantee Program (CZK 4bn). • COVID Travel Agency Guarantee Program (CZK 0.3bn) • Other guarantees (National guarantee, Expansion guarantee) (CZK 24.5bn). | AD72: =C72&F72 -> Czech RepublicLC bn
F73: USD bn | G73: 22.550382 | H73: 6.3937269 | J73: 16.156655 | L73: 0.61610711 | O73: USD bn | P73: 37.970293 | Q73: 0.038775972 | T73: USD bn | U73: 37.931517 | AD73: =C72&F73 -> Czech RepublicUSD bn
F74: % GDP | G74: 9.1911264 | H74: 2.6059671 | J74: 6.5851594 | L74: 0.25111408 | O74: % GDP | P74: 15.476003 | Q74: 0.015804382 | T74: % GDP | U74: 15.460198 | AD74: =C72&F74 -> Czech Republic% GDP
A75: 0 | B75: AE | C75: Denmark | D75: General Government | F75: LC bn | G75: 79.5 | J75: 79.5 | K75: Additional spending: Grants to businesses (announced: DKK 35.8 bn; uptake: DKK 22.6 bn) Employment support & unemployment benefits (announced DKK 30.8 bn; uptake DKK 20.9 bn) Boosting business activity (announced: DKK 9.6 bn; uptake 6.5 bn) Consumption support to Households (announced: DKK 2.2 bn; uptake 2.2 bn) Upskilling & Education (announced: DKK 1.1; uptake 1.1 bn) | L75: 318.8 | M75: Accelerated spending (1 bn): • Advance payment of tax credits (DKK 1 bn) Deferred revenue (317.8 bn): Tax deferrals (2020 & 2021) (announced 317.8; uptake 206.0) | O75: LC bn | P75: 364.2 | Q75: 282 | R75: Government loans (264 bn): • Government (interest free) loans (2020 & 2021) (announced: DKK 264.0; uptake: DKK 40.8 bn) Equity injections or asset purchases (18 bn): • SAS AB has completed a recapitalisation of the company to which the Danish State (among others) has contributed (DKK 3.8 bn) • Danish Recapitalization Fund (DKK 10 bn) Danish state will invest in equity as an investor of last resort by acquiring preferred shares of the beneficiaries affected by Covid-19 • A recapitalisation scheme administered by The Danish Growth Fund aimed at strengthening the solvency of SMEs and smaller midcaps (DKK 3 bn). • Equity to start ups (DKK 1.2 bn). | T75: LC bn | U75: 82.2 | V75: Guarantees (inc. trade credit insurance) (announced DKK 82.2 bn; uptake DKK 36.5 bn).V78 | Y75: Another 2 percent of GDP in countercyclical support is expected to come through the stronger automatic stabilizers—including from weaker tax receipts and higher social benefits. | AA75: https://fm.dk/nyheder/nyhedsarkiv/2020/marts/regeringen-og-alle-folketingets-partier-er-enige-om-omfattende-hjaelpepakke-til-dansk-oekonomi/ | AD75: =C75&F75 -> DenmarkLC bn
F76: USD bn | G76: 12.151964 | J76: 12.151964 | L76: 48.730141 | O76: USD bn | P76: 55.669753 | Q76: 43.105081 | T76: USD bn | U76: 12.564673 | AA76: https://fm.dk/nyheder/nyhedsarkiv/2020/marts/regeringen-og-arbejdsmarkedets-parter-styrker-trepartsaftalen-om-midlertidig-loenkompensation/ | AD76: =C75&F76 -> DenmarkUSD bn
F77: % GDP | G77: 3.4126602 | J77: 3.4126602 | L77: 13.684982 | O77: % GDP | P77: 15.633847 | Q77: 12.105285 | T77: % GDP | U77: 3.5285618 | AA77: https://fm.dk/nyheder/nyhedsarkiv/2020/april/regeringen-og-alle-folketingets-partier-er-enige-om-at-justere-og-udvide-hjaelpepakker-til-dansk-oekonomi/ | AD77: =C75&F77 -> Denmark% GDP
A78: 0 | B78: AE | C78: Finland | D78: General Government | F78: LC bn | G78: 11.3 | H78: 4.1 | I78: Additional spending: • Health and social services resources and equipment purchases, and covid-19 research (3.1) • Other expenditure increases arising from the coronavirus situation (0.9) | J78: 7.2 | K78: Additional spending (€6.1 billion): • Support for enterprises: grants provided for companies by Business Finland and ELY Centres, support for solvency of sole entrepreneurs, support for catering entrepreneurs, support for agricultural and natural resource economy enterprises, general cost support for companies, estimated increase in Finnvera’s loss compensation etc. (€4 billion) • Extension of unemployment security: eliminating the waiting period, speeding up the layoff procedure, making entrepreneurs eligible for unemployment security, extending the payment period of startup grants, streamlining unemployment benefit payments etc. (€700 million) • Extension of social benefits: support for individuals arriving from other countries and parents of small children, temporary increase in social assistance (€200 million) • Children and young people, and wellbeing of the elderly: free leisure activities, early childhood education and care, basic education and general upper secondary education, guidance counselling and youth work, student health care, ensuring properly functioning services for the elderly (€300 million) • Investment projects: basic transport infrastructure maintenance, developing the transport network, renovation construction, and public transport support. The sums for the years 2021 and 2022 are based on a technical assumption concerning the timing of the projects. (€400 million) • R&D&I, competence and wellbeing: additional starting places for higher education and developing continuous learning, research appropriations for the Academy of Finland, public employment and business services and developing the service structure. (€400 million) Forgone revenue (€1.1 billion): • Lowering of private sector pension contributions for the period May 1 - 31 December 2020 (1.1) | L78: 0.5 | M78: Deferred revenue: Easing of payment terms for taxes and lowering the interest on late payments from 7% to 2.5%. Assessing the impacts of the delays of 2020 and 2021 tax revenue to 2022 and 2023 (€500 million) | O78: LC bn | P78: 17.4 | Q78: 1.2 | R78: • Injecting capital into Finnish Industry Investment for the setting up of a new stability programme (€400 million) • Equity investment in Finnish Minerals Group (€500 million) • Capitalisation arrangements in Finnair Plc and other state owned companies (€300 million) | T78: LC bn | U78: 12.2 | V78: • Increasing Finnvera’s domestic financing authorisations from EUR 4.2 to EUR 12 billion. About EUR 2 billion of the existing authorisations have already been used in spring and thus the increase in authorisations was about EUR 10 billion. (€10 billion) • Increasing Business Finland’s lending authorisations, total increase for the period 2020-2022 (€300 million) • State guarantees to cover Finnair’s financing needs (€500 million) • State guarantees to shipping companies to ensure cargo traffic important to security of supply (€600 million) • State guarantees for the loans granted within the framework of the European instrument for temporary Support to mitigate Unemployment Risks in an Emergency (SURE) (€400 million) • State guarantees for any losses arising from the Pan-European covid-19 guarantee fund to be established under the European Investment Bank (€400 million) | W78: 4 | X78: • The State Pension Fund will invest in commercial paper (€1 billion). • Bank of Finland's investments in commercial paper (€1 billion). • Authorizing the Financial Stability Fund to borrow funds to meet its X81statutory obligations concerning the deposit guarantee (€2 billion) | Y78: Deferral of tax and pension payments for 3 months are expected to provide additional short-run relief of €3-4.5 bn. Automatic stabilizers are expected to increase the fiscal deficit significantly, including through an expansion of the coverage of existing unemployment benefits. | AA78: https://valtioneuvosto.fi/artikkeli/-/asset_publisher/10616/hallitus-antoi-eduskunnalle-lisatalousarvioesityksen-koronaviruksen-vuoksi | AD78: =C78&F78 -> FinlandLC bn
F79: USD bn | G79: 12.896485 | H79: 4.6792556 | J79: 8.2172294 | L79: 0.57064093 | O79: USD bn | P79: 19.858304 | Q79: 1.3695382 | T79: USD bn | U79: 13.923639 | W79: 4.5651274 | AD79: =C78&F79 -> FinlandUSD bn
F80: % GDP | G80: 4.7843244 | H80: 1.7359053 | J80: 3.0484191 | L80: 0.21169577 | O80: % GDP | P80: 7.3670127 | Q80: 0.50806984 | T80: % GDP | U80: 5.1653767 | W80: 1.6935661 | Y80: Short-run relief of €3-4.5 bn (1.9 percent of GDP). | AD80: =C78&F80 -> Finland% GDP
A81: 0 | B81: AE | C81: The Netherlands | D81: General Government | F81: LC bn | G81: 82.3 | H81: 16.6 | I81: Additional spending: including on purchase, distribution and sale of medical devices; vaccine research contribution; healthcare costs in the Caribbean Netherlands; training for healthcare personnel and bonusses; research. The reported 16.6 billion covers 2020-2022. | J81: 65.7 | K81: Additional spending (61.1 bn): • Companies expecting a reduction in revenues over 20% can request a compensation for labor costs (max 90% of labor costs) to allow companies to continue paying wages; compensation for affected sectors (for example, hospitality and travel). • Income support for entrepreneurs and self-employed (administered at municipal and regional level) for a period of three months through expedited procedures. • Support for start-ups and small innovation companies through loans provided by government regional agencies. • Scaling up of the short-time working scheme (unemployment benefit compensation available to companies needing to reduce their staff by at least 20 percent). • Allowances for SMEs affected by the outbreak to help them finance their fixed costs. • 60.4 billion in 2020-2022. Forgone revenue (info not available for 2021-2022, 4.6 bn in 2020): • Reduction of tourist taxes and taxes in the culture sector. • The interest rate on tax deferrals is reduced from 4% to just above 0%. | L81: 11.5 | M81: Deferred revenue: Tax deferrals for companies that are in financial distress due to the covid-19 crisis. Temporary suspension of penalties for late tax payments. Entrepreneurs can request a deferral of tax payment, without the need to provide evidence. Businesses can calculate provisional tax payments on an expected (reduced) basis. | O81: LC bn | P81: 34.8 | T81: LC bn | U81: 34.8 | V81: • The loan guarantee program for businesses (especially those affected by the outbreak) was expanded to cover up to 90 percent of total loan for SMEs (with maturity of 1 year or less) and 80 percent for large firms. • V84A guarantee scheme for supplier credit was also established. • A guarantee scheme for supplier credit was also established. | Y81: Tax deferrals for companies that are in financial distress. Temporary suspension of penalties for late tax payments. Interest rate on tax deferral is reduced from 4 percent to just above 0. Stronger automatic stabilizers given the broad social safety nets. | AA81: https://www.rijksoverheid.nl/actueel/nieuws/2020/03/17/coronavirus-kabinet-neemt-pakket-nieuwe-maatregelen-voor-banen-en-economie | AD81: =C81&F81 -> The NetherlandsLC bn
F82: USD bn | G82: 93.927497 | H82: 18.945279 | J82: 74.982218 | L82: 13.124741 | O82: USD bn | P82: 39.716609 | T82: USD bn | U82: 39.716609 | AD82: =C81&F82 -> The NetherlandsUSD bn
F83: % GDP | G83: 10.286279 | H83: 2.0747536 | J83: 8.2115249 | L83: 1.4373293 | O83: % GDP | P83: 4.3494835 | T83: % GDP | U83: 4.3494835 | AD83: =C81&F83 -> The Netherlands% GDP
A84: 0 | B84: AE | C84: New Zealand | D84: Central Government | F84: LC bn | G84: 62.1 | H84: 5.1 | I84: Additional spending: doubling resources for public health units; expanding intensive care capacity and equipment at hospitals; expanding health line capacity; support for primary care; the purchasing of vaccines, the cost of managed isolation. | J84: 57 | K84: Additional spending (NZ$48.4 bn): including wage subsidies available for all employers that are significantly affected by the impact of COVID-19 (NZ$13.9 billion); income relief payment to support people who have lost their job (NZ$570 million); financial support for workers that are not paid normally during self-isolation (NZ$126 million); temporary increase in winter energy payment (NZ$480 million); permanent increase in benefits (NZ$2.4 billion in next four years); infrastructure investment (NZ$3.8 billion); support package for the aviation sector (NZ$600 million); tourism recovery package (NZ$400 million); housing and urban development (NZ$ 4.7 billion); education (NZ$3.4 billion); transport projects (NZ$600 million); government R&D (NZ$196 million); targeted training and apprenticeship fund (NZ$ 320million); and Flexi-wage subsidies (NZ$311 million). Forgone revenue (NZ$8.6 bn): including the reinstatement of depreciation deductions for commercial and industrial buildings at a 2% diminishing value applying from the 2020-21 tax year (permanent); increasing the threshold for provisional tax from NZ $2.5K to NZ $5K applying from the FY2020-21 tax year (permanent); increasing the threshold for writing off low value assets to NZ $5K for the next tax year, before reverting to NZ$1K in the longer term; time-limited discretion of Inland Revenue to remit use of money interest (the interest on tax debt) if a taxpayer is unable to pay on time due to COVID-19; and tax loss carry-back mechanism for firms to offset a loss in a particular tax year against a profit in a previous year, and receive a refund on the tax paid in the previous profitable year. | O84: LC bn | P84: 6.3 | Q84: 3.4 | R84: • NZ$ 900 mn loan is granted to Air New Zealand, an airline company, of which the government owns 52 percent of shares. • Maximum NZ$100 thousand loan is granted to small businesses that employ 50 or fewer full time equivalent employees (NZ$ 1.7 bn). • NZ$150 million short-term R&D scheme to support private sector R&D investment. | T84: LC bn | U84: 2.9 | V84: • A loan guarantee scheme for firms with a turnover of between NZ$ 250 thousand and NZ$ 80 mn per annum, with the Government carrying 80% of the credit risk. The loans will be limited to NZ$ 5 mn for a maximum of five years and expected to be provided by the banks at competitive, transparent rates. | AD84: =C84&F84 -> New ZealandLC bn
F85: USD bn | G85: 40.366334 | H85: 3.3151095 | J85: 37.051224 | O85: USD bn | P85: 4.0951353 | Q85: 2.210073 | T85: USD bn | U85: 1.8850623 | AD85: =C84&F85 -> New ZealandUSD bn
F86: % GDP | G86: 19.278649 | H86: 1.5832707 | J86: 17.695379 | O86: % GDP | P86: 1.955805 | Q86: 1.0555138 | T86: % GDP | U86: 0.9002912 | AD86: =C84&F86 -> New Zealand% GDP
A87: 0 | B87: AE | C87: Norway | D87: Central Government | F87: LC bn | G87: 225.2 | H87: 24.7 | I87: Additional spending: • Strengthening the financial situation in the hospital trust through increased appropriations and temporary reduced employer tax (NOK 6 bn). • Increased appropriations to cover expenses for necessary medicines, medical equipment and laboratory analyzes (NOK 4.8 bn). • Other measures. Forgone revenue: • Strengthening the financial situation in the hospital trust by NOK 6 bn through increased appropriations and temporary reduced employer tax. | J87: 200.5 | K87: Additional spending: • Include household income protection scheme offering larger wage subsidies for temporary lay-offs, more generous unemployment benefits, and expanded sickness and child care; • Measures for business offering a scheme to compensate heavily affected but otherwise sustainable businesses for unavoidable fixed costs, grants for start-ups and subsidies of domestic air routes; • Strengthening of critical sectors other than healthcare (public transport, municipalities); Forgone revenue: • Lowering of reduced VAT rate from 12 to 6 percent; • Change in CIT regulations so that lossmaking companies can re-allocate their losses towards previous years’ taxed profits • Temporary amendments to the petroleum tax system to improve liquidity in the sector. • Suspension of aviation charges. • Temporary lowering of the employers’ social insurance contributions. | M87: • Deferral of various tax payments. | O87: LC bn | P87: 137.5 | Q87: 59.5 | R87: • The reinstatement of a government fund that buys bonds issued by Norwegian companies to increase liquidity and access to capital in the Norwegian bond market, with a ceiling of NOK 50 bn. • Increased funding for Innovation Norway and Research Council (NOK 5.4 bn). • Grant to help alleviate the financial situation in Avinor (NOK 3.6 bn). • Other (NOK 0.5 bn) | T87: LC bn | U87: 78 | V87: • Government guarantee scheme for bank loans to SMEs (NOK 50 bn). • A scheme for re-insurance of private credit insurance providers (NOK 20 bn). • A guarantee scheme for the aviation industry (NOK 6 bn). • A loan scheme for package tour operators (NOK 2 bn). | Y87: Automatic stabilizers, contingency lines, advance payments and tax deferrals, international aid; Deferral of various tax payments. | AA87: https://www.regjeringen.no/en/aktuelt/economic-measures-in-norway-in-response-to-covid-19/id2694274/ | AD87: =C87&F87 -> NorwayLC bn
F88: USD bn | G88: 23.917161 | H88: 2.623241 | J88: 21.29392 | O88: USD bn | P88: 14.603062 | Q88: 6.3191433 | T88: USD bn | U88: 8.2839189 | AD88: =C87&F88 -> NorwayUSD bn
F89: % GDP 2/ | G89: 7.4022943 | H89: 0.81188574 | J89: 6.5904086 | O89: % GDP 2/ | P89: 4.5196069 | Q89: 1.9557572 | T89: % GDP | U89: 2.5638497 | AD89: Norway% GDP
C90: Portugal | D90: General Government | F90: LC bn | G90: 12.1 | H90: 2.2 | I90: Additional spending (€2.2 bn): • Medicines, personal protective equipment, complementary means of diagnosis and therapy; • COVID-19 tests and vaccines; • Personnel expenses, incl. extraordinary health insurance subsidies for health professionals; • Profilactic isolation; • Investment to expand intensive care services of the National Health Service. | J90: 9.9 | K90: Additional spending (€8.7 bn): • Support measures for employment and resumption of activity (€3.0 bn); • Non-repayble subsidies to businesses affected by the pandemic, program Apoiar.pt (€1.1 bn); • Social protection programs, such as extension of unemployment coverage and support to self-employed and informal workers (€0.6 bn); • Extraordinary financial incentive (subsidy) to businesses for normalization of economic activity (€0.3 bn); • Family support programs (€0.2 bn); • Other support measures (€0.2 bn); • Investment, incl. digital education, teleworking (€0.4 bn); • Investment under the Recovery and Resilience Plan in 2021 (€0.5 bn); • Support to national airlines (€1.3 bn in 2020 and €1.1 bn in 2021); Forgone revenue (€1.2 bn): • Exemption from payment of the Single Social Fee (€0.7 bn); • Lowering of reduced electricity VAT rate (€0.2 bn); • Temporary waiver of VAT on purchases of certain medical material; • VAT refund program for catering, accommodation and culture (€0.2); • Other tax relief measures, such as road toll reductions,property rents, SME taxes (€0.1). | L90: 1.1 | M90: Deferred revenue: Figures refer to 2020 eop stock of: • Suspension of payments on CIT account (0.7 bn). • Suspension of tax foreclosures from Tax Revenue (estimate) (0.1 bn) • Suspension of payment of installment plans and contributory execution processes Policy measures for 2021: • Reduction of PIT withholding tax (0.2 bn)+M91 • FYI: short-term intra-year measures, that we included earlier, are not covered. | O90: LC bn | P90: 11.5 | T90: LC bn | U90: 11.5 | V90: A maximum of €13 billion authorized under the EU Temporary State Aid Framework. Public guarantee programs rolled out in 2020 include: • Credit lines rolled out in April 2020 targeting micro, SMEs and mid-cap companies (€6.2bn), including: restaurants (€.6 bn); travel agencies (€0.2M); tourism (€0.9M); and industry (€4.5bn). • Capitalizar credit line in May 2020 (€0.4bn) targeting working capital needs and open to large companies; • Credit line for treasury needs of micro companies in the tourism sector (€0.06 bn); • Credit insurances guaranteed on export operations: metallurgy and construction (€0.4 bn); short-term export (€0.3 bn); • Credit line targeting companies in Madeira region (€0.1 bn); • Creidt line fo SMEs in November 2020 (€0.8bn), of which 20% is non-repayable; Introduced for the first half of 2021: • New and expanded credit lines targeting SMEs (€0.750 bn); • Industry and tourism exporting companies (€1.050 bn), with loans up to €4,000 per worker, of which 20 percent can be converted into a non-refundable subsidy if jobs are maintained; • Credit line for event organizers (€0.050 bn), 20% non-refundable; Credit line for large companies in the sectors most affected (€0.750 bn); • Travel agencies and tour operators, including SMEs (€0.4 bn). | AD90: =C90&F90 -> PortugalLC bn
F91: USD bn | G91: 13.80951 | H91: 2.5108201 | J91: 11.29869 | L91: 1.25541 | O91: USD bn | P91: 13.124741 | T91: USD bn | U91: 13.124741 | AD91: =C90&F91 -> PortugalUSD bn
F92: % GDP | G92: 6.0473513 | H92: 1.0995184 | J92: 4.9478328 | L92: 0.54975921 | O92: % GDP | P92: 5.7474826 | T92: % GDP | U92: 5.7474826 | AD92: =C90&F92 -> Portugal% GDP
A93: 0 | B93: AE | C93: Singapore | D93: Central Government | F93: LC bn | G93: 86.3 | H93: 18.6 | I93: Additional spending: For COVID-19 testing, clinical management, tracing, vaccination and therapeutics, and isolation facilities. | J93: 67.7 | K93: Additional spending: • Support to households, including a cash payout to all Singaporeans (higher for families with children under 20), and additional payments for lower-income individuals and the unemployed. • Support to businesses and workers, including wage subsidies; support to cover rental costs, an enhancement of financing schemes, and additional support for the self-employed and industries most directly affected.. • Other measures: e.g. support to R&D investment, a national stockpile of health supplies, and a program on food resilience. Forgone revenue: • Corporate income tax rebate and property tax rebates; carry-back provisions for qualifying deductions; faster write-downs for qualifying investments; foreign worker levy waivers. | O93: LC bn | P93: 22 | Q93: 22 | R93: • S$22 bn in loan capital was set aside to help businesses facing cash flow challenges with loan obligations and insurance premium payments. | T93: LC bn | AD93: =C93&F93 -> SingaporeLC bn
F94: USD bn | G94: 62.546528 | H94: 13.48048 | J94: 49.066048 | O94: USD bn | P94: 15.944654 | Q94: 15.944654 | T94: USD bn | AD94: =C93&F94 -> SingaporeUSD bn
F95: % GDP | G95: 18.397091 | H95: 3.9650741 | J95: 14.432017 | O95: % GDP | P95: 4.6898726 | Q95: 4.6898726 | T95: % GDP | AD95: =C93&F95 -> Singapore% GDP
A96: 0 | B96: AE | C96: Sweden | D96: Central Government | F96: LC bn | G96: 207 | H96: 38 | I96: Additional spending: • Increased testing and tracing for Covid-19 (SEK 7 bn); funding of extraordinary costs associated with Covid-19 for municipalities and regions (SEK 5 bn) and elderly care boost (SEK 2.2 bn). • Extra funding to train up to 10,000 people in health and social care during 2020Q4. Folk high schools' adult vocational training was also to be expanded with 1000 seats during 2020, focusing on health and social care. • The National Board of Health and Welfare’s credit framework has increased to enable purchases of personal protective equipment and intensive care equipment. • Removal of income ceiling for student aid to enable health and medical care students to help out in the health care sector without their student aid being reduced. | J96: 169 | K96: Additional spending (SEK 136 bn): additional expenditures on wage subsidies for short-term leave, temporary payment of sick leave, more funding to the media, cultural and sports sectors and for education and training, rent subsidies to certain sectors, more generous unemployment benefits, expanded active labor market policies, temporary grants to businesses based on their loss of turnover to cover their fixed costs; supplementary housing allowances to families with children, infrastructure investment, extra support to public transport, measures to prevent Covid-19 fraud, general grants to municipalities and regions. Forgone revenue (SEK 33 bn): temporary reduction in employers' social security contributions. | L96: 335 | M96: Deferred revenues: Deferral of a maximum of three month worth of payments of companies’ social contributions, VAT and payroll taxes for a period of up to 12 months (SEK 27 bn if uptake similar to GFC, and SEK 315 bn if fully used by all firms), deferral of annual VAT for 2019 (SEK 7 bn) and deferral of SME taxes (SEK 13 bn). | O96: LC bn | P96: 261.7 | Q96: 11.7 | R96: • SEK 8.3 bn capital injection to the Scandinavian carrier SAS, the state-owned airport operator Swedavia Lernia (state-owned education and matching firm) • SEK 3.4 bn capital injection to ALMI (the Swedish SME and Entrepreneur Agency) | T96: LC bn | U96: 250 | V96: • Credit guarantees for Swedish airlines (SEK 5 bn). • Expansion of the Swedish Export Credit Agency’s credit guarantee framework and the programs under the Swedish Export Credit Corporation (SEK 125 bn). • Central government guarantees for loans to companies (SEK 100 bn) • Guarantees to the EU for loans to member states, SURE, and to the European Investment Bank for a guarantee fund for support to companies (SEK 20 bn). | AD96: =C96&F96 -> SwedenLC bn
F97: USD bn | G97: 22.474816 | H97: 4.1258116 | J97: 18.349004 | L97: 36.372287 | O97: USD bn | P97: 28.413813 | Q97: 1.2703157 | T97: USD bn | U97: 27.143497 | AD97: =C96&F97 -> SwedenUSD bn
F98: % GDP | G98: 4.1538214 | H98: 0.76253727 | J98: 3.3912842 | L98: 6.722368 | O98: % GDP | P98: 5.2514738 | Q98: 0.23478121 | T98: % GDP | U98: 5.0166925 | AD98: =C96&F98 -> Sweden% GDP
A99: 0 | B99: AE | C99: Switzerland | D99: Central Government | F99: LC bn | G99: 55.844 | H99: 7.219 | I99: Additional spending: Includes: • Medical goods including vaccines (CHF3.765 billion) • Covid-19 tests (CHF3.036 billion) • Additional spending on medication, health protection and prevention, and by Federal Department of Health (CHF0.418 billion) | J99: 48.625 | K99: Additional spending: • Benefits COVID income replacement directly and indirectly affected (CHF 8.44 bn) • Financing for short term work program and the unemployment fund (CHF 26.2 bn) • COVID bridging loan losses (CHF 2.387 bn) • Support to cantonal hardship programs (CHF 8.232 billion); and other measures | O99: LC bn | P99: 43.875 | Q99: 1.1 | R99: • Loan support to sports clubs (CHF400 million) • Loan to ICRC (CHF 200 mn) • Financial support to air traffic control company Skyguide (CHF500 mn) | T99: LC bn | U99: 42.775 | V99: • Guarantees for Covid-19 bridge loans for firms with annual turnover up to CHF 500 mn (CHF 40 bn) • Guarantees for startups (CHF 0.1 bn) • Guarantees for airlines (CHF 1.275 bn) • Guarantees for flight-related business (CHF 0.6 bn) • Guarantees for SNB loan to IMF (CHF 0.8 bn) | AD99: =C99&F99 -> SwitzerlandLC bn
F100: USD bn | G100: 59.481808 | H100: 7.6892625 | J100: 51.792546 | O100: USD bn | P100: 46.73312 | Q100: 1.1716566 | T100: USD bn | U100: 45.561463 | AD100: =C99&F100 -> SwitzerlandUSD bn
F101: % GDP | G101: 7.9111095 | H101: 1.0226757 | J101: 6.8884339 | O101: % GDP | P101: 6.2155277 | Q101: 0.15583089 | T101: % GDP | U101: 6.0596968 | AD101: =C99&F101 -> Switzerland% GDP
