Workbook
Name IQ_CH: 110000
Name IQ_CQ: 5000
Name IQ_CY: 10000
Name IQ_DAILY: 500000
Name IQ_FH: 100000
Name IQ_FQ: 500
Name IQ_FY: 1000
Name IQ_LTM: 2000
Name IQ_MONTH: 15000
Name IQ_NTM: 6000
Name IQ_WEEK: 50000
Name IQ_YTD: 3000

Sheet 2020
B1: Table 1. Summary of Country Fiscal Measures in Response to the COVID-19 Pandemic
B2: (USD billion and percent of GDP)
B3: USD Billion
C4: Above the line measures | G4: Liquidity support | K4: Above the line measures | P4: Liquidity support
C5: Additional spending or foregone revenues | F5: Accelerated spending / deferred revenue | H5: Below the line measures: equity injections, loans, asset purchase or debt assumptions. | I5: Contingent liabilities | K5: Additional spending or foregone revenues | N5: Accelerated spending / deferred revenue | Q5: Below the line measures: equity injections, loans, asset purchase or debt assumptions. | R5: Contingent liabilities
C6: Subtotal | D6: Health sector | E6: Non-health sector | G6: Subtotal | I6: Guarantees | J6: Quasi-fiscal operations | K6: Subtotal | L6: Health sector | M6: Non-health sector | P6: Subtotal | R6: Guarantees | S6: Quasi-fiscal operations
B7: G20: Advanced economies
B8: Australia | C8: 218.44778 | D8: 11.460914 | E8: 206.98687 | F8: 0 | G8: 24.164577 | H8: 10.356247 | I8: 13.80833 | J8: 0 | K8: 16.177852 | L8: 0.8487748 | M8: 15.329077 | N8: 0 | P8: 1.7895854 | Q8: 0.76696518 | R8: 1.0226202 | S8: 0
B9: Canada | C9: 240.10444 | D9: 39.211354 | E9: 200.89308 | F9: 63.244119 | G9: 65.922694 | H9: 3.869052 | I9: 62.053642 | J9: 0 | K9: 14.646142 | L9: 2.3918552 | M9: 12.254287 | N9: 3.8578309 | P9: 4.0212214 | Q9: 0.23600848 | R9: 3.7852129 | S9: 0
B10: France | C10: 198.05783 | D10: 20.261089 | E10: 177.79675 | F10: 62.604488 | G10: 404.65264 | H10: 23.903532 | I10: 380.74911 | J10: 0 | K10: 7.7103009 | L10: 0.78875492 | M10: 6.921546 | N10: 2.4371641 | P10: 15.752942 | Q10: 0.93055356 | R10: 14.822389 | S10: 0
B11: Germany | C11: 417.74267 | D11: 45.530537 | E11: 372.21214 | F11: 0 | G11: 1054.3734 | H11: 113.82634 | I11: 940.54706 | J11: 0 | K11: 11.033705 | L11: 1.2025837 | M11: 9.8311217 | N11: 0 | P11: 27.848832 | Q11: 3.0064592 | R11: 24.842373 | S11: 0
B12: Italy | C12: 127.4855 | D12: 10.813502 | E12: 116.672 | F12: 7.9678439 | G12: 662.75387 | H12: 3.6993561 | I12: 659.05452 | J12: 0 | K12: 6.8248555 | L12: 0.57889399 | M12: 6.2459615 | N12: 0.42655347 | P12: 35.480108 | Q12: 0.19804268 | R12: 35.282066 | S12: 0
B13: Japan | C13: 782.33295 | D13: 89.837276 | E13: 692.49567 | F13: 243.30929 | G13: 1428.0384 | H13: 0 | I13: 146.92138 | J13: 1281.117 | K13: 15.580393 | L13: 1.789136 | M13: 13.791257 | N13: 4.8455768 | P13: 28.439808 | Q13: 0 | R13: 2.9259829 | S13: 25.513825
B14: Korea | C14: 56.080292 | D14: 4.3138686 | E14: 51.766423 | F14: 27.913268 | G14: 165.70331 | H14: 0 | I14: 59.971232 | J14: 105.73207 | K14: 3.4422077 | L14: 0.26478521 | M14: 3.1774225 | N14: 1.713316 | P14: 10.170867 | Q14: 0 | R14: 3.6810335 | S14: 6.4898335
B15: Spain | C15: 52.473943 | D15: 5.008359 | E15: 47.465584 | F15: 0.61466224 | G15: 183.53245 | H15: 0.72735032 | I15: 171.42247 | J15: 11.382634 | K15: 4.1298486 | L15: 0.3941721 | M15: 3.7356765 | N15: 0.048375667 | P15: 14.444526 | Q15: 0.057244539 | R15: 13.491436 | S15: 0.89584568
B16: United Kingdom | C16: 440.54616 | D16: 144.71429 | E16: 295.83187 | F16: 8.964602 | G16: 436.70419 | H16: 1.2806574 | I16: 435.42353 | J16: 0 | K16: 16.258004 | L16: 5.3405653 | M16: 10.917439 | N16: 0.33083148 | P16: 16.116219 | Q16: 0.04726164 | R16: 16.068957 | S16: 0
B17: United States | C17: 3503.3 | D17: 483.8 | E17: 3019.5 | F17: 18 | G17: 510 | H17: 56 | I17: 454 | J17: 0 | K17: 16.719306 | L17: 2.3089088 | M17: 14.410397 | N17: 0.085904007 | P17: 2.4339469 | Q17: 0.26725691 | R17: 2.16669 | S17: 0
B18: Mexico | C18: 7.2279883 | D18: 2.3467495 | E18: 4.8812389 | F18: 4.318019 | G18: 13.588243 | H18: 1.8445451 | I18: 1.1504705 | J18: 10.593227 | K18: 0.68126555 | L18: 0.22119012 | M18: 0.46007544 | N18: 0.40698981 | P18: 1.2807439 | Q18: 0.17385543 | R18: 0.10843624 | S18: 0.99845218
B19: Turkey | C19: 7.6102085 | D19: 2.0161373 | E19: 5.5940711 | F19: 9.8677143 | G19: 63.976864 | H19: 2.9816115 | I19: 43.446339 | J19: 17.548914 | K19: 1.0708244 | L19: 0.28368856 | M19: 0.78713585 | N19: 1.3884757 | P19: 9.0021171 | Q19: 0.41953941 | R19: 6.1132886 | S19: 2.4692891
... B42: Colombia | C42: 11.060054 | D42: 2.9135225 | E42: 8.1465315 | F42: 0.10756165 | G42: 15.411434 | H42: 8.5363618 | I42: 6.875072 | J42: 0 | K42: 4.1001316 | L42: 1.0800875 | M42: 3.0200441 | N42: 0.039874754 | P42: 5.7132548 | Q42: 3.1645602 | R42: 2.5486946 | S42: 0
B43: Costa Rica | C43: 0.84666153 | D43: 0.19538343 | E43: 0.6512781 | F43: 0.40447798 | H43: 0 | I43: 0 | J43: 0 | K43: 1.4290119 | L43: 0.32977198 | M43: 1.0992399 | N43: 0.68268585 | P43: 0 | Q43: 0 | R43: 0 | S43: 0
B44: Hungary | C44: 5.997549 | D44: 1.769415 | E44: 4.228134 | F44: 0 | G44: 6.6270226 | H44: 0 | I44: 6.6270226 | J44: 0 | K44: 4 | L44: 1.1800921 | M44: 2.8199079 | N44: 0 | P44: 4.4198205 | Q44: 0 | R44: 4.4198205 | S44: 0
B45: Poland | C45: 44.709731 | D45: 2.1654286 | E45: 42.544303 | F45: 0 | G45: 31.589782 | H45: 12.737815 | I45: 18.851967 | J45: 0 | K45: 7.6769895 | L45: 0.37182 | M45: 7.3051695 | N45: 0 | P45: 5.4241977 | Q45: 2.1871765 | R45: 3.2370212 | S45: 0

Sheet 2021
B1: Table 1. Summary of Country Fiscal Measures in Response to the COVID-19 Pandemic since January 2020
B2: (USD billion and percent of 2020 GDP)
B3: USD Billion
C4: Above the line measures | G4: Liquidity support | K4: Above the line measures | O4: Liquidity support
C5: Additional spending or foregone revenues | F5: Accelerated spending / deferred revenue | H5: Below the line measures: equity injections, loans, asset purchase or debt assumptions. | I5: Contingent liabilities | K5: Additional spending or foregone revenues | N5: Accelerated spending / deferred revenue | P5: Below the line measures: equity injections, loans, asset purchase or debt assumptions. | Q5: Contingent liabilities
C6: Subtotal | D6: Health sector | E6: Non-health sector | G6: Subtotal | I6: Guarantees | J6: Quasi-fiscal operations | K6: Subtotal | L6: Health sector | M6: Non-health sector | O6: Subtotal | Q6: Guarantees | R6: Quasi-fiscal operations
B7: G20: Advanced economies | S7: GDP 2020 Usbn
B8: Australia | C8: 249.7258 | D8: 13.808449 | E8: 235.91735 | F8: 0 | G8: 24.164785 | H8: 10.356337 | I8: 13.808449 | J8: 0 | K8: 18.370673 | L8: 1.0157961 | M8: 17.354877 | N8: 0 | O8: =P8+Q8 -> 1.7776432 | P8: 0.7618471 | Q8: 1.0157961 | R8: 0 | S8: =('2020'!C8/'2020'!K8)*100 -> 1350.2891
B9: Canada | C9: 261.78973 | D9: 45.632389 | E9: 216.15734 | F9: 68.027304 | G9: 64.944135 | H9: 3.8772618 | I9: 61.066873 | J9: 0 | K9: 15.923589 | L9: 2.7756298 | M9: 13.147959 | N9: 3.8595767 | O9: =P9+Q9 -> 3.9502836 | P9: 0.23583783 | Q9: 3.7144457 | R9: 0 | S9: =('2020'!C9/'2020'!K9)*100 -> 1639.3699
B10: France | C10: 252.88464 | D10: 38.63357 | E10: 214.25107 | F10: 79.204517 | G10: 399.21356 | H10: 18.006207 | I10: 381.20735 | J10: 0 | K10: 9.6358441 | L10: 1.4720825 | M10: 8.1637616 | N10: 3.0179863 | O10: =P10+Q10 -> 15.21152 | P10: 0.68610337 | Q10: 14.525416 | R10: 0 | S10: =('2020'!C10/'2020'!K10)*100 -> 2568.7432
B11: Germany | C11: 588.90144 | D11: 69.618193 | E11: 519.28325 | F11: 0 | G11: 1057.9683 | H11: 114.12819 | I11: 943.8401 | J11: 0 | K11: 15.322667 | L11: 1.8114005 | M11: 13.638353 | N11: 0 | O11: =P11+Q11 -> 27.786271 | P11: 2.9974402 | Q11: 24.78883 | R11: 0 | S11: =('2020'!C11/'2020'!K11)*100 -> 3786.0597
B12: Italy | C12: 205.43073 | D12: 22.825637 | E12: 182.6051 | F12: 7.988973 | G12: 664.51136 | H12: 3.709166 | I12: 660.8022 | J12: 0 | K12: 10.898556 | L12: 1.2109506 | M12: 9.687605 | N12: 0.42383272 | O12: =P12+Q12 -> 35.2538 | P12: 0.19677948 | Q12: 35.057021 | R12: 0 | S12: =('2020'!C12/'2020'!K12)*100 -> 1867.959
B13: Japan | C13: 843.83379 | D13: 104.89388 | E13: 738.93991 | F13: 27.160022 | G13: 1429.1791 | H13: 0 | I13: 147.03874 | J13: 1282.1403 | K13: 16.725807 | L13: 2.0791236 | M13: 14.646684 | N13: 0.53834452 | O13: =P13+Q13 -> 2.9144858 | P13: 0 | Q13: 2.9144858 | R13: 25.413574 | S13: =('2020'!C13/'2020'!K13)*100 -> 5021.2658
B14: Korea | C14: 104.83005 | D14: 11.9491 | E14: 92.880946 | F14: 27.965978 | G14: 166.01622 | H14: 0 | I14: 60.084481 | J14: 105.93174 | K14: 6.3988747 | L14: 0.7293786 | M14: 5.6694961 | N14: 1.7070563 | O14: =P14+Q14 -> 3.6675846 | P14: 0 | Q14: 3.6675846 | R14: 6.4661224 | S14: =('2020'!C14/'2020'!K14)*100 -> 1629.1955
B15: Spain | C15: 107.45169 | D15: 21.924025 | E15: 85.527663 | F15: 0.051357684 | G15: 184.01915 | H15: 0.72927911 | I15: 171.87705 | J15: 11.412819 | K15: 8.3916545 | L15: 1.7122006 | M15: 6.6794539 | N15: 0.0040108811 | O15: =P15+Q15 -> 13.480037 | P15: 0.056954511 | Q15: 13.423082 | R15: 0.89130691 | S15: =('2020'!C15/'2020'!K15)*100 -> 1270.6021
B16: United Kingdom | C16: 522.16797 | D16: 130.86273 | E16: 391.30523 | F16: 16.0371 | G16: 452.92619 | H16: 1.321457 | I16: 451.60473 | J16: 0 | K16: 19.270477 | L16: 4.8294563 | M16: 14.441021 | N16: 0.59184513 | O16: =P16+Q16 -> 16.715127 | P16: 0.048768039 | Q16: 16.666359 | R16: 0 | S16: =('2020'!C16/'2020'!K16)*100 -> 2709.7186
B17: United States | C17: 5328.3 | D17: 687.3 | E17: 4641 | F17: 17.98 | G17: 510 | H17: 56 | I17: 454 | J17: 0 | K17: 25.501885 | L17: 3.2895004 | M17: 22.212384 | N17: 0.086054442 | O17: =P17+Q17 -> 2.4409213 | P17: 0.26802273 | Q17: 2.1728986 | R17: 0 | S17: =('2020'!C17/'2020'!K17)*100 -> 20953.621
B18: Mexico | C18: 7.0279602 | D18: 4.8032152 | E18: 2.224745 | F18: 4.281936 | G18: 13.41363 | H18: 0.89362143 | I18: 0.2792567 | J18: 12.240752 | K18: 0.65442397 | L18: 0.44726194 | M18: 0.20716202 | N18: 0.39872189 | O18: =P18+Q18 -> 0.10921513 | P18: 0.083211524 | Q18: 0.026003601 | R18: 1.1398245 | S18: =('2020'!C18/'2020'!K18)*100 -> 1060.9649
B19: Turkey | C19: 25.234121 | D19: 2.7673372 | E19: 22.466784 | F19: 10.013767 | G19: 69.354606 | H19: 2.9955712 | I19: 45.932092 | J19: 20.426943 | K19: 3.5051336 | L19: 0.38439565 | M19: 3.1207379 | N19: 1.3909575 | O19: =P19+Q19 -> 6.7962737 | P19: 0.41609839 | Q19: 6.3801753 | R19: 2.8373947 | S19: =('2020'!C19/'2020'!K19)*100 -> 710.68687
... B45: Poland | C45: 38.516359 | D45: 3.7695771 | E45: 34.746782 | F45: 0 | G45: 28.720588 | H45: 9.7444851 | I45: 18.976103 | J45: 0 | K45: 6.463387 | L45: 0.6325685 | M45: 5.8308185 | N45: 0 | O45: =P45+Q45 -> 4.8195695 | P45: 1.6352111 | Q45: 3.1843584 | R45: 0 | S45: =('2020'!C45/'2020'!K45)*100 -> 582.38625

Sheet data
A1: Country | B1: Quarter | C1: ab_us | D1: health_us | E1: nhealth_us | F1: acc_us | G1: of_us | H1: be_us | I1: gu_us | J1: qf_us | K1: ab_per | L1: ab_ppp | M1: health_per | N1: health_ppp | O1: nhealth_per | P1: nhealth_ppp | Q1: acc_per | R1: acc_ppp | S1: of_per | T1: of_ppp | U1: be_per | V1: be_ppp | W1: gu_per | X1: gu_ppp | Y1: qf_us | Z1: qf_ppp | AA1: GDP 2019 in US Dollar constant PPP 2019 | AB1: in bn | AC1: GDP 2019 in US Dollar constant Prices 2015 | AD1: in bn
A2: AUS | B2: Q1.2020 | C2: =D2+E2 -> 110.0051 | D2: 2.1168 | E2: 107.8883 | F2: 0 | G2: =H2+I2 -> 24.0029 | H2: 10.3255 | I2: 13.6774 | J2: 0 | K2: =M2+O2 -> 7.3593163 | L2: =N2+P2 -> 8.9689107 | M2: =($D2/$AD2)*100 -> 0.14161344 | N2: =($D2/$AB2)*100 -> 0.17258646 | O2: =($E2/$AD2)*100 -> 7.2177029 | P2: =($E2/$AB2)*100 -> 8.7963243 | Q2: =($F2/$AD2)*100 -> 0 | R2: =($F2/$AB2)*100 -> 0 | S2: =U2+W2 -> 1.6057886 | T2: =V2+X2 -> 1.956999 | U2: =($H2/$AD2)*100 -> 0.69077361 | V2: =($H2/AB2)*100 -> 0.84185631 | W2: =($I2/$AD2)*100 -> 0.91501497 | X2: =($I2/$AB2)*100 -> 1.1151427 | Y2: =($J2/$AD2)*100 -> 0 | Z2: =($J2/$AB2)*100 -> 0 | AA2: 1.2265157e+12 | AB2: 1226.5157 | AC2: 1.4947734e+12 | AD2: 1494.7734
A3: CAN | B3: Q1.2020 | C3: =D3+E3 -> 81 | D3: 2.4 | E3: 78.6 | F3: 63.75 | G3: =H3+I3 -> 51.7 | H3: 3.7 | I3: 48 | J3: 0 | K3: =M3+O3 -> 4.7742401 | L3: =N3+P3 -> 4.6997712 | M3: =($D3/$AD3)*100 -> 0.14145896 | N3: =($D3/$AB3)*100 -> 0.13925248 | O3: =($E3/$AD3)*100 -> 4.6327811 | P3: =($E3/$AB3)*100 -> 4.5605187 | Q3: =($F3/$AD3)*100 -> 3.7575038 | R3: =($F3/$AB3)*100 -> 3.698894 | S3: =U3+W3 -> 3.0472619 | T3: =V3+X3 -> 2.9997305 | U3: =($H3/$AD3)*100 -> 0.21808257 | V3: =($H3/AB3)*100 -> 0.21468091 | W3: =($I3/$AD3)*100 -> 2.8291793 | X3: =($I3/$AB3)*100 -> 2.7850496 | Y3: =($J3/$AD3)*100 -> 0 | Z3: =($J3/$AB3)*100 -> 0 | AA3: 1.7234882e+12 | AB3: 1723.4882 | AC3: 1.6966051e+12 | AD3: 1696.6051
A4: FRA | B4: Q1.2020 | C4: =D4+E4 -> 16.5 | D4: 5.5 | E4: 11 | F4: 48.5 | G4: =H4+I4 -> 348 | H4: 0 | I4: 348 | J4: 0 | K4: =M4+O4 -> 0.63053811 | L4: =N4+P4 -> 0.56757784 | M4: =($D4/$AD4)*100 -> 0.21017937 | N4: =($D4/$AB4)*100 -> 0.18919261 | O4: =($E4/$AD4)*100 -> 0.42035874 | P4: =($E4/$AB4)*100 -> 0.37838523 | Q4: =($F4/$AD4)*100 -> 1.8533999 | R4: =($F4/$AB4)*100 -> 1.6683349 | S4: =U4+W4 -> 13.298622 | T4: =V4+X4 -> 11.970733 | U4: =($H4/$AD4)*100 -> 0 | V4: =($H4/AB4)*100 -> 0 | W4: =($I4/$AD4)*100 -> 13.298622 | X4: =($I4/$AB4)*100 -> 11.970733 | Y4: =($J4/$AD4)*100 -> 0 | Z4: =($J4/$AB4)*100 -> 0 | AA4: 2.9070902e+12 | AB4: 2907.0902 | AC4: 2.6168125e+12 | AD4: 2616.8125
A5: DEU | B5: Q1.2020 | C5: =D5+E5 -> 143 | D5: 11.2 | E5: 131.8 | F5: 0 | G5: =H5+I5 -> 1072 | H5: 223 | I5: 849 | J5: 0 | K5: =M5+O5 -> 3.9751845 | L5: =N5+P5 -> 3.4360259 | M5: =($D5/$AD5)*100 -> 0.31134312 | N5: =($D5/$AB5)*100 -> 0.26911531 | O5: =($E5/$AD5)*100 -> 3.6638413 | P5: =($E5/$AB5)*100 -> 3.1669106 | Q5: =($F5/$AD5)*100 -> 0 | R5: =($F5/$AB5)*100 -> 0 | S5: =U5+W5 -> 29.799984 | T5: =V5+X5 -> 25.75818 | U5: =($H5/$AD5)*100 -> 6.1990639 | V5: =($H5/AB5)*100 -> 5.3582781 | W5: =($I5/$AD5)*100 -> 23.60092 | X5: =($I5/$AB5)*100 -> 20.399902 | Y5: =($J5/$AD5)*100 -> 0 | Z5: =($J5/$AB5)*100 -> 0 | AA5: 4.1617847e+12 | AB5: 4161.7847 | AC5: 3.5973173e+12 | AD5: 3597.3173
A6: ITA | B6: Q1.2020 | C6: =D6+E6 -> 22 | D6: 3.63 | E6: 18.37 | F6: 0 | G6: =H6+I6 -> 591 | H6: 0 | I6: 591 | J6: 0 | K6: =M6+O6 -> 1.1469339 | L6: =N6+P6 -> 0.94111213 | M6: =($D6/$AD6)*100 -> 0.18924409 | N6: =($D6/$AB6)*100 -> 0.1552835 | O6: =($E6/$AD6)*100 -> 0.95768981 | P6: =($E6/$AB6)*100 -> 0.78582863 | Q6: =($F6/$AD6)*100 -> 0 | R6: =($F6/$AB6)*100 -> 0 | S6: =U6+W6 -> 30.810815 | T6: =V6+X6 -> 25.281694 | U6: =($H6/$AD6)*100 -> 0 | V6: =($H6/AB6)*100 -> 0 | W6: =($I6/$AD6)*100 -> 30.810815 | X6: =($I6/$AB6)*100 -> 25.281694 | Y6: =($J6/$AD6)*100 -> 0 | Z6: =($J6/$AB6)*100 -> 0 | AA6: 2.3376598e+12 | AB6: 2337.6598 | AC6: 1.9181576e+12 | AD6: 1918.1576
A7: JPN | B7: Q1.2020 | C7: =D7+E7 -> 497 | D7: 12.1906 | E7: 484.8094 | F7: 0 | G7: =H7+I7 -> 19 | H7: 0 | I7: 19 | J7: 0 | K7: =M7+O7 -> 10.888777 | L7: =N7+P7 -> 9.3335923 | M7: =($D7/$AD7)*100 -> 0.26708396 | N7: =($D7/$AB7)*100 -> 0.22893781 | O7: =($E7/$AD7)*100 -> 10.621693 | P7: =($E7/$AB7)*100 -> 9.1046545 | Q7: =($F7/$AD7)*100 -> 0 | R7: =($F7/$AB7)*100 -> 0 | S7: =U7+W7 -> 0.41627116 | T7: =V7+X7 -> 0.35681741 | U7: =($H7/$AD7)*100 -> 0 | V7: =($H7/AB7)*100 -> 0 | W7: =($I7/$AD7)*100 -> 0.41627116 | X7: =($I7/$AB7)*100 -> 0.35681741 | Y7: =($J7/$AD7)*100 -> 0 | Z7: =($J7/$AB7)*100 -> 0 | AA7: 5.3248522e+12 | AB7: 5324.8522 | AC7: 4.5643326e+12 | AD7: 4564.3326
A8: KOR | B8: Q1.2020 | C8: =D8+E8 -> 24 | D8: 2.5 | E8: 21.5 | F8: 14 | G8: =H8+I8 -> 215 | H8: 101 | I8: 114 | J8: 0 | K8: =M8+O8 -> 1.46507 | L8: =N8+P8 -> 1.112894 | M8: =($D8/$AD8)*100 -> 0.15261146 | N8: =($D8/$AB8)*100 -> 0.11592646 | O8: =($E8/$AD8)*100 -> 1.3124586 | P8: =($E8/$AB8)*100 -> 0.99696756 | Q8: =($F8/$AD8)*100 -> 0.85462418 | R8: =($F8/$AB8)*100 -> 0.64918818 | S8: =U8+W8 -> 13.124586 | T8: =V8+X8 -> 9.9696756 | U8: =($H8/$AD8)*100 -> 6.165503 | V8: =($H8/AB8)*100 -> 4.683429 | W8: =($I8/$AD8)*100 -> 6.9590826 | X8: =($I8/$AB8)*100 -> 5.2862466 | Y8: =($J8/$AD8)*100 -> 0 | Z8: =($J8/$AB8)*100 -> 0 | AA8: 2.1565396e+12 | AB8: 2156.5396 | AC8: 1.638147e+12 | AD8: 1638.147
A9: ESP | B9: Q1.2020 | C9: =D9+E9 -> 14.8929 | D9: 4.1786 | E9: 10.7143 | F9: 0 | G9: =H9+I9 -> 175.6152 | H9: 11 | I9: 164.6152 | J9: 11.4316 | K9: =M9+O9 -> 1.1249106 | L9: =N9+P9 -> 0.82898249 | M9: =($D9/$AD9)*100 -> 0.31562366 | N9: =($D9/$AB9)*100 -> 0.23259313 | O9: =($E9/$AD9)*100 -> 0.80928698 | P9: =($E9/$AB9)*100 -> 0.59638936 | Q9: =($F9/$AD9)*100 -> 0 | R9: =($F9/$AB9)*100 -> 0 | S9: =U9+W9 -> 13.264805 | T9: =V9+X9 -> 9.775257 | U9: =($H9/$AD9)*100 -> 0.83086686 | V9: =($H9/AB9)*100 -> 0.61229226 | W9: =($I9/$AD9)*100 -> 12.433938 | X9: =($I9/$AB9)*100 -> 9.1629648 | Y9: =($J9/$AD9)*100 -> 0.86346706 | Z9: =($J9/$AB9)*100 -> 0.63631638 | AA9: 1.7965277e+12 | AB9: 1796.5277 | AC9: 1.3239185e+12 | AD9: 1323.9185
A10: GBR | B10: Q1.2020 | C10: =D10+E10 -> 83 | D10: 6.3846154 | E10: 76.615385 | F10: 0 | G10: =H10+I10 -> 423 | H10: 423 | I10: 0 | J10: 0 | K10: =M10+O10 -> 2.628755 | L10: =N10+P10 -> 2.8212212 | M10: =($D10/$AD10)*100 -> 0.20221192 | N10: =($D10/$AB10)*100 -> 0.21701702 | O10: =($E10/$AD10)*100 -> 2.4265431 | P10: =($E10/$AB10)*100 -> 2.6042042 | Q10: =($F10/$AD10)*100 -> 0 | R10: =($F10/$AB10)*100 -> 0 | S10: =U10+W10 -> 13.397149 | T10: =V10+X10 -> 14.378031 | U10: =($H10/$AD10)*100 -> 13.397149 | V10: =($H10/AB10)*100 -> 14.378031 | W10: =($I10/$AD10)*100 -> 0 | X10: =($I10/$AB10)*100 -> 0 | Y10: =($J10/$AD10)*100 -> 0 | Z10: =($J10/$AB10)*100 -> 0 | AA10: 2.9419883e+12 | AB10: 2941.9883 | AC10: 3.1573882e+12 | AD10: 3157.3882
A11: USA | B11: Q1.2020 | C11: =D11+E11 -> 1395 | D11: 9.45 | E11: 1385.55 | F11: 0 | G11: =H11+I11 -> 510 | H11: 56 | I11: 454 | J11: 0 | K11: =M11+O11 -> 6.9998582 | L11: =N11+P11 -> 6.9840045 | M11: =($D11/$AD11)*100 -> 0.047418394 | N11: =($D11/$AB11)*100 -> 0.047310998 | O11: =($E11/$AD11)*100 -> 6.9524398 | P11: =($E11/$AB11)*100 -> 6.9366935 | Q11: =($F11/$AD11)*100 -> 0 | R11: =($F11/$AB11)*100 -> 0 | S11: =U11+W11 -> 2.5590879 | T11: =V11+X11 -> 2.553292 | U11: =($H11/$AD11)*100 -> 0.28099789 | V11: =($H11/AB11)*100 -> 0.28036147 | W11: =($I11/$AD11)*100 -> 2.27809 | X11: =($I11/$AB11)*100 -> 2.2729305 | Y11: =($J11/$AD11)*100 -> 0 | Z11: =($J11/$AB11)*100 -> 0 | AA11: 1.9974214e+13 | AB11: 19974.214 | AC11: 19928975197000 | AD11: 19928.975
A12: MEX | B12: Q1.2020 | C12: =D12+E12 -> 1.862 | D12: 1.862 | E12: 0 | F12: 0 | G12: =H12+I12 -> 3.3 | H12: 3.3 | I12: 0 | J12: 0 | K12: =M12+O12 -> 0.14556526 | L12: =N12+P12 -> 0.078180517 | M12: =($D12/$AD12)*100 -> 0.14556526 | N12: =($D12/$AB12)*100 -> 0.078180517 | O12: =($E12/$AD12)*100 -> 0 | P12: =($E12/$AB12)*100 -> 0 | Q12: =($F12/$AD12)*100 -> 0 | R12: =($F12/$AB12)*100 -> 0 | S12: =U12+W12 -> 0.25798355 | T12: =V12+X12 -> 0.13855838 | U12: =($H12/$AD12)*100 -> 0.25798355 | V12: =($H12/AB12)*100 -> 0.13855838 | W12: =($I12/$AD12)*100 -> 0 | X12: =($I12/$AB12)*100 -> 0 | Y12: =($J12/$AD12)*100 -> 0 | Z12: =($J12/$AB12)*100 -> 0 | AA12: 2.3816676e+12 | AB12: 2381.6676 | AC12: 1.2791513e+12 | AD12: 1279.1513
A13: TUR | B13: Q1.2020 | C13: =D13+E13 -> 0 | D13: 0 | E13: 0 | F13: 0 | G13: =H13+I13 -> 3.8 | H13: 0 | I13: 3.8 | J13: 0 | K13: =M13+O13 -> 0 | L13: =N13+P13 -> 0 | M13: =($D13/$AD13)*100 -> 0 | N13: =($D13/$AB13)*100 -> 0 | O13: =($E13/$AD13)*100 -> 0 | P13: =($E13/$AB13)*100 -> 0 | Q13: =($F13/$AD13)*100 -> 0 | R13: =($F13/$AB13)*100 -> 0 | S13: =U13+W13 -> 0.38112296 | T13: =V13+X13 -> 0.16282574 | U13: =($H13/$AD13)*100 -> 0 | V13: =($H13/AB13)*100 -> 0 | W13: =($I13/$AD13)*100 -> 0.38112296 | X13: =($I13/$AB13)*100 -> 0.16282574 | Y13: =($J13/$AD13)*100 -> 0 | Z13: =($J13/$AB13)*100 -> 0 | AA13: 2.3337834e+12 | AB13: 2333.7834 | AC13: 9.9705355e+11 | AD13: 997.05355
... A27: NLD | B27: Q1.2020 | C27: =D27+E27 -> 22 | D27: 0 | E27: 22 | F27: 45 | G27: =H27+I27 -> 0 | H27: 0 | I27: 0 | J27: 0 | K27: =M27+O27 -> 2.618267 | L27: =N27+P27 -> 2.3594 | M27: =($D27/$AD27)*100 -> 0 | N27: =($D27/$AB27)*100 -> 0 | O27: =($E27/$AD27)*100 -> 2.618267 | P27: =($E27/$AB27)*100 -> 2.3594 | Q27: =($F27/$AD27)*100 -> 5.3555462 | R27: =($F27/$AB27)*100 -> 4.8260455 | S27: =U27+W27 -> 0 | T27: =V27+X27 -> 0 | U27: =($H27/$AD27)*100 -> 0 | V27: =($H27/AB27)*100 -> 0 | W27: =($I27/$AD27)*100 -> 0 | X27: =($I27/$AB27)*100 -> 0 | Y27: =($J27/$AD27)*100 -> 0 | Z27: =($J27/$AB27)*100 -> 0 | AA27: 9.3244043e+11 | AB27: 932.44043 | AC27: 8.4025043e+11 | AD27: 840.25043
A28: NZL | B28: Q1.2020 | C28: =D28+E28 -> 11.088516 | D28: 0.31570903 | E28: 10.772806 | F28: 0 | G28: =H28+I28 -> 6.6522016 | H28: 2.7058387 | I28: 3.9463629 | K28: =M28+O28 -> 5.4639624 | L28: =N28+P28 -> 5.7165015 | M28: =($D28/$AD28)*100 -> 0.15556837 | N28: =($D28/$AB28)*100 -> 0.16275859 | O28: =($E28/$AD28)*100 -> 5.3083941 | P28: =($E28/$AB28)*100 -> 5.5537429 | Q28: =($F28/$AD28)*100 -> 0 | R28: =($F28/$AB28)*100 -> 0 | S28: =U28+W28 -> 3.2779302 | T28: =V28+X28 -> 3.429433 | U28: =($H28/$AD28)*100 -> 1.3333256 | V28: =($H28/AB28)*100 -> 1.3949506 | W28: =($I28/$AD28)*100 -> 1.9446046 | X28: =($I28/$AB28)*100 -> 2.0344824 | Y28: =($J28/$AD28)*100 -> 0 | Z28: =($J28/$AB28)*100 -> 0 | AA28: 1.9397381e+11 | AB28: 193.97381 | AC28: 2.0293909e+11 | AD28: 202.93909
A29: NOR | B29: Q1.2020 | C29: =D29+E29 -> 8.1 | D29: 0 | E29: 8.1 | F29: 0 | G29: =H29+I29 -> 10.6 | H29: 5.3 | I29: 5.3 | J29: 0 | K29: =M29+O29 -> 1.9744091 | L29: =N29+P29 -> 2.4511712 | M29: =($D29/$AD29)*100 -> 0 | N29: =($D29/$AB29)*100 -> 0 | O29: =($E29/$AD29)*100 -> 1.9744091 | P29: =($E29/$AB29)*100 -> 2.4511712 | Q29: =($F29/$AD29)*100 -> 0 | R29: =($F29/$AB29)*100 -> 0 | S29: =U29+W29 -> 2.5837946 | T29: =V29+X29 -> 3.2077056 | U29: =($H29/$AD29)*100 -> 1.2918973 | V29: =($H29/AB29)*100 -> 1.6038528 | W29: =($I29/$AD29)*100 -> 1.2918973 | X29: =($I29/$AB29)*100 -> 1.6038528 | Y29: =($J29/$AD29)*100 -> 0 | Z29: =($J29/$AB29)*100 -> 0 | AA29: 3.3045427e+11 | AB29: 330.45427 | AC29: 4.1024933e+11 | AD29: 410.24933
A30: PRT | B30: Q1.2020 | C30: =D30+E30 -> 7.2019168 | D30: 1.8290582 | E30: 5.3728586 | F30: 9.030975 | G30: =H30+I30 -> 14.861098 | H30: 0 | I30: 14.861098 | J30: 0 | K30: =M30+O30 -> 3.2388198 | L30: =N30+P30 -> 2.1106626 | M30: =($D30/$AD30)*100 -> 0.82255741 | N30: =($D30/$AB30)*100 -> 0.53604129 | O30: =($E30/$AD30)*100 -> 2.4162624 | P30: =($E30/$AB30)*100 -> 1.5746213 | Q30: =($F30/$AD30)*100 -> 4.0613772 | R30: =($F30/$AB30)*100 -> 2.6467038 | S30: =U30+W30 -> 6.6832789 | T30: =V30+X30 -> 4.3553354 | U30: =($H30/$AD30)*100 -> 0 | V30: =($H30/AB30)*100 -> 0 | W30: =($I30/$AD30)*100 -> 6.6832789 | X30: =($I30/$AB30)*100 -> 4.3553354 | Y30: =($J30/$AD30)*100 -> 0 | Z30: =($J30/$AB30)*100 -> 0 | AA30: 3.4121593e+11 | AB30: 341.21593 | AC30: 2.2236238e+11 | AD30: 222.36238
A31: SVK | B31: Q1.2020 | C31: =D31+E31 -> 2.5149551 | D31: 0.18290582 | E31: 2.3320493 | F31: 1.4060885 | G31: =H31+I31 -> 4.5840772 | H31: 0 | I31: 4.5840772 | J31: 0 | K31: =M31+O31 -> 2.5278709 | L31: =N31+P31 -> 1.3840355 | M31: =($D31/$AD31)*100 -> 0.18384516 | N31: =($D31/$AB31)*100 -> 0.10065713 | O31: =($E31/$AD31)*100 -> 2.3440258 | P31: =($E31/$AB31)*100 -> 1.2833784 | Q31: =($F31/$AD31)*100 -> 1.4133097 | R31: =($F31/$AB31)*100 -> 0.77380168 | S31: =U31+W31 -> 4.6076193 | T31: =V31+X31 -> 2.5227193 | U31: =($H31/$AD31)*100 -> 0 | V31: =($H31/AB31)*100 -> 0 | W31: =($I31/$AD31)*100 -> 4.6076193 | X31: =($I31/$AB31)*100 -> 2.5227193 | Y31: =($J31/$AD31)*100 -> 0 | Z31: =($J31/$AB31)*100 -> 0 | AA31: 1.8171174e+11 | AB31: 181.71174 | AC31: 9.9489061e+10 | AD31: 99.489061
A32: SVN | B32: Q1.2020 | C32: =D32+E32 -> 4.115381 | D32: 0.11431614 | E32: 4.0010649 | F32: 0 | G32: =H32+I32 -> 3.3151681 | H32: 0.68589684 | I32: 2.6292712 | J32: 0.11431614 | K32: =M32+O32 -> 8.162527 | L32: =N32+P32 -> 5.412314 | M32: =($D32/$AD32)*100 -> 0.22673686 | N32: =($D32/$AB32)*100 -> 0.15034206 | O32: =($E32/$AD32)*100 -> 7.9357901 | P32: =($E32/$AB32)*100 -> 5.261972 | Q32: =($F32/$AD32)*100 -> 0 | R32: =($F32/$AB32)*100 -> 0 | S32: =U32+W32 -> 6.575369 | T32: =V32+X32 -> 4.3599196 | U32: =($H32/$AD32)*100 -> 1.3604212 | V32: =($H32/AB32)*100 -> 0.90205234 | W32: =($I32/$AD32)*100 -> 5.2149478 | X32: =($I32/$AB32)*100 -> 3.4578673 | Y32: =($J32/$AD32)*100 -> 0.22673686 | Z32: =($J32/$AB32)*100 -> 0.15034206 | AA32: 7.6037366e+10 | AB32: 76.037366 | AC32: 5.0417978e+10 | AD32: 50.417978
A33: SWE | B33: Q1.2020 | C33: =D33+E33 -> 11 | D33: 0 | E33: 11 | F33: 0 | G33: =H33+I33 -> 25 | H33: 0 | I33: 25 | J33: 0 | K33: =M33+O33 -> 2.0006501 | L33: =N33+P33 -> 2.1113062 | M33: =($D33/$AD33)*100 -> 0 | N33: =($D33/$AB33)*100 -> 0 | O33: =($E33/$AD33)*100 -> 2.0006501 | P33: =($E33/$AB33)*100 -> 2.1113062 | Q33: =($F33/$AD33)*100 -> 0 | R33: =($F33/$AB33)*100 -> 0 | S33: =U33+W33 -> 4.546932 | T33: =V33+X33 -> 4.7984231 | U33: =($H33/$AD33)*100 -> 0 | V33: =($H33/AB33)*100 -> 0 | W33: =($I33/$AD33)*100 -> 4.546932 | X33: =($I33/$AB33)*100 -> 4.7984231 | Y33: =($J33/$AD33)*100 -> 0 | Z33: =($J33/$AB33)*100 -> 0 | AA33: 5.2100449e+11 | AB33: 521.00449 | AC33: 5.4982128e+11 | AD33: 549.82128
A34: CHE | B34: Q1.2020 | C34: =D34+E34 -> 1.6825977 | D34: 0 | E34: 1.6825977 | F34: 0 | G34: =H34+I34 -> 0.21161296 | H34: =0.0516129+0.05677419 -> 0.10838709 | I34: =0.10322587 -> 0.10322587 | J34: 0 | K34: =M34+O34 -> 0.22521425 | L34: =N34+P34 -> 0.28479303 | M34: =($D34/$AD34)*100 -> 0 | N34: =($D34/$AB34)*100 -> 0 | O34: =($E34/$AD34)*100 -> 0.22521425 | P34: =($E34/$AB34)*100 -> 0.28479303 | Q34: =($F34/$AD34)*100 -> 0 | R34: =($F34/$AB34)*100 -> 0 | S34: =U34+W34 -> 0.028324212 | T34: =V34+X34 -> 0.035817175 | U34: =($H34/$AD34)*100 -> 0.014507519 | V34: =($H34/AB34)*100 -> 0.018345376 | W34: =($I34/$AD34)*100 -> 0.013816694 | X34: =($I34/$AB34)*100 -> 0.017471799 | Y34: =($J34/$AD34)*100 -> 0 | Z34: =($J34/$AB34)*100 -> 0 | AA34: 5.9081422e+11 | AB34: 590.81422 | AC34: 7.4710978e+11 | AD34: 747.10978
A35: CHL | B35: Q1.2020 | C35: =D35+E35 -> 4.6 | D35: 1 | E35: 3.6 | F35: 4.7152702 | G35: =H35+I35 -> 2.4 | H35: 2.4 | I35: 0 | J35: 0 | K35: =M35+O35 -> 1.7559969 | L35: =N35+P35 -> 1.0424015 | M35: =($D35/$AD35)*100 -> 0.38173846 | N35: =($D35/$AB35)*100 -> 0.22660903 | O35: =($E35/$AD35)*100 -> 1.3742585 | P35: =($E35/$AB35)*100 -> 0.81579252 | Q35: =($F35/$AD35)*100 -> 1.8 | R35: =($F35/$AB35)*100 -> 1.0685228 | S35: =U35+W35 -> 0.91617231 | T35: =V35+X35 -> 0.54386168 | U35: =($H35/$AD35)*100 -> 0.91617231 | V35: =($H35/AB35)*100 -> 0.54386168 | W35: =($I35/$AD35)*100 -> 0 | X35: =($I35/$AB35)*100 -> 0 | Y35: =($J35/$AD35)*100 -> 0 | Z35: =($J35/$AB35)*100 -> 0 | AA35: 4.4128868e+11 | AB35: 441.28868 | AC35: 2.6195946e+11 | AD35: 261.95946
A36: COL | B36: Q1.2020 | C36: =D36+E36 -> 0 | D36: 0 | E36: 0 | F36: 0 | G36: =H36+I36 -> 0.1 | H36: 0.1 | I36: 0 | J36: 0 | K36: =M36+O36 -> 0 | L36: =N36+P36 -> 0 | M36: =($D36/$AD36)*100 -> 0 | N36: =($D36/$AB36)*100 -> 0 | O36: =($E36/$AD36)*100 -> 0 | P36: =($E36/$AB36)*100 -> 0 | Q36: =($F36/$AD36)*100 -> 0 | R36: =($F36/$AB36)*100 -> 0 | S36: =U36+W36 -> 0.031113334 | T36: =V36+X36 -> 0.014482907 | U36: =($H36/$AD36)*100 -> 0.031113334 | V36: =($H36/AB36)*100 -> 0.014482907 | W36: =($I36/$AD36)*100 -> 0 | X36: =($I36/$AB36)*100 -> 0 | Y36: =($J36/$AD36)*100 -> 0 | Z36: =($J36/$AB36)*100 -> 0 | AA36: 6.9046913e+11 | AB36: 690.46913 | AC36: 3.2140561e+11 | AD36: 321.40561
A37: CRI | B37: Q1.2020 | C37: =D37+E37 -> 0.717434 | D37: 0.17 | E37: 0.547434 | F37: 0 | G37: =H37+I37 -> 0 | H37: 0 | I37: 0 | J37: 0 | K37: =M37+O37 -> 1.1143309 | L37: =N37+P37 -> 0.78637134 | M37: =($D37/$AD37)*100 -> 0.26404693 | N37: =($D37/$AB37)*100 -> 0.18633509 | O37: =($E37/$AD37)*100 -> 0.85028393 | P37: =($E37/$AB37)*100 -> 0.60003625 | Q37: =($F37/$AD37)*100 -> 0 | R37: =($F37/$AB37)*100 -> 0 | S37: =U37+W37 -> 0 | T37: =V37+X37 -> 0 | U37: =($H37/$AD37)*100 -> 0 | V37: =($H37/AB37)*100 -> 0 | W37: =($I37/$AD37)*100 -> 0 | X37: =($I37/$AB37)*100 -> 0 | Y37: =($J37/$AD37)*100 -> 0 | Z37: =($J37/$AB37)*100 -> 0 | AA37: 9.1233488e+10 | AB37: 91.233488 | AC37: 6.4382494e+10 | AD37: 64.382494
A38: HUN | B38: Q1.2020 | C38: =D38+E38 -> 4.419749 | D38: 0 | E38: 4.419749 | F38: 0 | G38: =H38+I38 -> 0 | H38: 0 | I38: 0 | J38: 0 | K38: =M38+O38 -> 2.9987989 | L38: =N38+P38 -> 1.42624 | M38: =($D38/$AD38)*100 -> 0 | N38: =($D38/$AB38)*100 -> 0 | O38: =($E38/$AD38)*100 -> 2.9987989 | P38: =($E38/$AB38)*100 -> 1.42624 | Q38: =($F38/$AD38)*100 -> 0 | R38: =($F38/$AB38)*100 -> 0 | S38: =U38+W38 -> 0 | T38: =V38+X38 -> 0 | U38: =($H38/$AD38)*100 -> 0 | V38: =($H38/AB38)*100 -> 0 | W38: =($I38/$AD38)*100 -> 0 | X38: =($I38/$AB38)*100 -> 0 | Y38: =($J38/$AD38)*100 -> 0 | Z38: =($J38/$AB38)*100 -> 0 | AA38: 3.0988816e+11 | AB38: 309.88816 | AC38: 1.4738397e+11 | AD38: 147.38397
A39: POL | B39: Q1.2020 | C39: =D39+E39 -> 17 | D39: 8 | E39: 9 | F39: 0 | G39: =H39+I39 -> 17 | H39: 0 | I39: 17 | J39: 0 | K39: =M39+O39 -> 2.9746119 | L39: =N39+P39 -> 1.3986902 | M39: =($D39/$AD39)*100 -> 1.3998174 | N39: =($D39/$AB39)*100 -> 0.65820713 | O39: =($E39/$AD39)*100 -> 1.5747946 | P39: =($E39/$AB39)*100 -> 0.74048302 | Q39: =($F39/$AD39)*100 -> 0 | R39: =($F39/$AB39)*100 -> 0 | S39: =U39+W39 -> 2.9746119 | T39: =V39+X39 -> 1.3986902 | U39: =($H39/$AD39)*100 -> 0 | V39: =($H39/AB39)*100 -> 0 | W39: =($I39/$AD39)*100 -> 2.9746119 | X39: =($I39/$AB39)*100 -> 1.3986902 | Y39: =($J39/$AD39)*100 -> 0 | Z39: =($J39/$AB39)*100 -> 0 | AA39: 1.2154229e+12 | AB39: 1215.4229 | AC39: 5.7150312e+11 | AD39: 571.50312
A41: AUS | B41: Q2.2020 | C41: =D41+E41 -> 110.37182 | D41: 3.2712453 | E41: 107.10057 | F41: 0 | G41: =H41+I41 -> 22.898717 | H41: 9.8137358 | I41: 13.084981 | J41: 0 | K41: =M41+O41 -> 7.3838495 | L41: =N41+P41 -> 8.9988097 | M41: =($D41/$AD41)*100 -> 0.21884557 | N41: =($D41/$AB41)*100 -> 0.26671042 | O41: =($E41/$AD41)*100 -> 7.1650039 | P41: =($E41/$AB41)*100 -> 8.7320993 | Q41: =($F41/$AD41)*100 -> 0 | R41: =($F41/$AB41)*100 -> 0 | S41: =U41+W41 -> 1.531919 | T41: =V41+X41 -> 1.866973 | U41: =($H41/$AD41)*100 -> 0.6565367 | V41: =($H41/AB41)*100 -> 0.80013127 | W41: =($I41/$AD41)*100 -> 0.87538227 | X41: =($I41/$AB41)*100 -> 1.0668417 | Y41: =($J41/$AD41)*100 -> 0 | Z41: =($J41/$AB41)*100 -> 0 | AA41: 1.2265157e+12 | AB41: 1226.5157 | AC41: 1.4947734e+12 | AD41: 1494.7734
A42: CAN | B42: Q2.2020 | C42: =D42+E42 -> 86.382127 | D42: 2.8794042 | E42: 83.502722 | F42: 61.18734 | G42: =H42+I42 -> 50.389574 | H42: 3.5992553 | I42: 46.790319 | J42: 0 | K42: =M42+O42 -> 5.0914693 | L42: =N42+P42 -> 5.0120522 | M42: =($D42/$AD42)*100 -> 0.16971564 | N42: =($D42/$AB42)*100 -> 0.16706841 | O42: =($E42/$AD42)*100 -> 4.9217536 | P42: =($E42/$AB42)*100 -> 4.8449838 | Q42: =($F42/$AD42)*100 -> 3.6064574 | R42: =($F42/$AB42)*100 -> 3.5502037 | S42: =U42+W42 -> 2.9700237 | T42: =V42+X42 -> 2.9236971 | U42: =($H42/$AD42)*100 -> 0.21214455 | V42: =($H42/AB42)*100 -> 0.20883551 | W42: =($I42/$AD42)*100 -> 2.7578792 | X42: =($I42/$AB42)*100 -> 2.7148616 | Y42: =($J42/$AD42)*100 -> 0 | Z42: =($J42/$AB42)*100 -> 0 | AA42: 1.7234882e+12 | AB42: 1723.4882 | AC42: 1.6966051e+12 | AD42: 1696.6051
A43: FRA | B43: Q2.2020 | C43: =D43+E43 -> 62.619278 | D43: 8.7426566 | E43: 53.876621 | F43: 60.65218 | G43: =H43+I43 -> 380.30556 | H43: 22.949473 | I43: 357.35609 | J43: 0 | K43: =M43+O43 -> 2.3929601 | L43: =N43+P43 -> 2.154019 | M43: =($D43/$AD43)*100 -> 0.33409565 | N43: =($D43/$AB43)*100 -> 0.30073564 | O43: =($E43/$AD43)*100 -> 2.0588644 | P43: =($E43/$AB43)*100 -> 1.8532834 | Q43: =($F43/$AD43)*100 -> 2.3177885 | R43: =($F43/$AB43)*100 -> 2.0863535 | S43: =U43+W43 -> 14.533161 | T43: =V43+X43 -> 13.082 | U43: =($H43/$AD43)*100 -> 0.87700107 | V43: =($H43/AB43)*100 -> 0.78943106 | W43: =($I43/$AD43)*100 -> 13.65616 | X43: =($I43/$AB43)*100 -> 12.292569 | Y43: =($J43/$AD43)*100 -> 0 | Z43: =($J43/$AB43)*100 -> 0 | AA43: 2.9070902e+12 | AB43: 2907.0902 | AC43: 2.6168125e+12 | AD43: 2616.8125
A44: DEU | B44: Q2.2020 | C44: =D44+E44 -> 332.22095 | D44: 25.135138 | E44: 307.08581 | F44: 0 | G44: =H44+I44 -> 1114.6887 | H44: 218.56641 | I44: 896.1223 | J44: 0 | K44: =M44+O44 -> 9.2352417 | L44: =N44+P44 -> 7.9826558 | M44: =($D44/$AD44)*100 -> 0.69871894 | N44: =($D44/$AB44)*100 -> 0.60395093 | O44: =($E44/$AD44)*100 -> 8.5365227 | P44: =($E44/$AB44)*100 -> 7.3787049 | Q44: =($F44/$AD44)*100 -> 0 | R44: =($F44/$AB44)*100 -> 0 | S44: =U44+W44 -> 30.986666 | T44: =V44+X44 -> 26.783911 | U44: =($H44/$AD44)*100 -> 6.0758169 | V44: =($H44/AB44)*100 -> 5.2517472 | W44: =($I44/$AD44)*100 -> 24.910849 | X44: =($I44/$AB44)*100 -> 21.532164 | Y44: =($J44/$AD44)*100 -> 0 | Z44: =($J44/$AB44)*100 -> 0 | AA44: 4.1617847e+12 | AB44: 4161.7847 | AC44: 3.5973173e+12 | AD44: 3597.3173
A45: ITA | B45: Q2.2020 | C45: =D45+E45 -> 60.105764 | D45: 7.1034085 | E45: 53.002355 | F45: 7.6498245 | G45: =H45+I45 -> 582.80734 | H45: 3.6063458 | I45: 579.201 | J45: 0 | K45: =M45+O45 -> 3.1335154 | L45: =N45+P45 -> 2.5711938 | M45: =($D45/$AD45)*100 -> 0.37032454 | N45: =($D45/$AB45)*100 -> 0.30386836 | O45: =($E45/$AD45)*100 -> 2.7631908 | P45: =($E45/$AB45)*100 -> 2.2673254 | Q45: =($F45/$AD45)*100 -> 0.39881105 | R45: =($F45/$AB45)*100 -> 0.32724285 | S45: =U45+W45 -> 30.383705 | T45: =V45+X45 -> 24.93123 | U45: =($H45/$AD45)*100 -> 0.18801092 | V45: =($H45/AB45)*100 -> 0.15427163 | W45: =($I45/$AD45)*100 -> 30.195694 | X45: =($I45/$AB45)*100 -> 24.776958 | Y45: =($J45/$AD45)*100 -> 0 | Z45: =($J45/$AB45)*100 -> 0 | AA45: 2.3376598e+12 | AB45: 2337.6598 | AC45: 1.9181576e+12 | AD45: 1918.1576
A46: JPN | B46: Q2.2020 | C46: =D46+E46 -> 551.10682 | D46: 38.427517 | E46: 512.67931 | F46: 243.68669 | G46: =H46+I46 -> 147.14927 | H46: 0 | I46: 147.14927 | J46: 1021.6096 | K46: =M46+O46 -> 12.074204 | L46: =N46+P46 -> 10.349711 | M46: =($D46/$AD46)*100 -> 0.84190878 | N46: =($D46/$AB46)*100 -> 0.72166353 | O46: =($E46/$AD46)*100 -> 11.232295 | P46: =($E46/$AB46)*100 -> 9.6280476 | Q46: =($F46/$AD46)*100 -> 5.3389337 | R46: =($F46/$AB46)*100 -> 4.5764029 | S46: =U46+W46 -> 3.2238946 | T46: =V46+X46 -> 2.7634433 | U46: =($H46/$AD46)*100 -> 0 | V46: =($H46/AB46)*100 -> 0 | W46: =($I46/$AD46)*100 -> 3.2238946 | X46: =($I46/$AB46)*100 -> 2.7634433 | Y46: =($J46/$AD46)*100 -> 22.382453 | Z46: =($J46/$AB46)*100 -> 19.185689 | AA46: 5.3248522e+12 | AB46: 5324.8522 | AC46: 4.5643326e+12 | AD46: 4564.3326
A47: KOR | B47: Q2.2020 | C47: =D47+E47 -> 47.759349 | D47: 3.7812909 | E47: 43.978058 | F47: 27.126652 | G47: =H47+I47 -> 28.030874 | H47: 0 | I47: 28.030874 | J47: 120.83691 | K47: =M47+O47 -> 2.9154496 | L47: =N47+P47 -> 2.2146289 | M47: =($D47/$AD47)*100 -> 0.23082733 | N47: =($D47/$AB47)*100 -> 0.17534067 | O47: =($E47/$AD47)*100 -> 2.6846222 | P47: =($E47/$AB47)*100 -> 2.0392882 | Q47: =($F47/$AD47)*100 -> 1.6559352 | R47: =($F47/$AB47)*100 -> 1.2578787 | S47: =U47+W47 -> 1.7111331 | T47: =V47+X47 -> 1.299808 | U47: =($H47/$AD47)*100 -> 0 | V47: =($H47/AB47)*100 -> 0 | W47: =($I47/$AD47)*100 -> 1.7111331 | X47: =($I47/$AB47)*100 -> 1.299808 | Y47: =($J47/$AD47)*100 -> 7.3764387 | Z47: =($J47/$AB47)*100 -> 5.6032779 | AA47: 2.1565396e+12 | AB47: 2156.5396 | AC47: 1.638147e+12 | AD47: 1638.147
... A58: FIN | B58: Q2.2020 | C58: =D58+E58 -> 7.6050184 | D58: 1.5966277 | E58: 6.0083907 | F58: 5.7373684 | G58: =H58+I58 -> 16.851471 | H58: 2.6446536 | I58: 14.206817 | J58: 1.0928321 | K58: =M58+O58 -> 2.9853553 | L58: =N58+P58 -> 2.9950177 | M58: =($D58/$AD58)*100 -> 0.62675731 | N58: =($D58/$AB58)*100 -> 0.62878587 | O58: =($E58/$AD58)*100 -> 2.358598 | P58: =($E58/$AB58)*100 -> 2.3662318 | Q58: =($F58/$AD58)*100 -> 2.252208 | R58: =($F58/$AB58)*100 -> 2.2594975 | S58: =U58+W58 -> 6.6150567 | T58: =V58+X58 -> 6.6364669 | U58: =($H58/$AD58)*100 -> 1.0381606 | V58: =($H58/AB58)*100 -> 1.0415207 | W58: =($I58/$AD58)*100 -> 5.576896 | X58: =($I58/$AB58)*100 -> 5.5949461 | Y58: =($J58/$AD58)*100 -> 0.428992 | Z58: =($J58/$AB58)*100 -> 0.43038047 | AA58: 2.5392232e+11 | AB58: 253.92232 | AC58: 2.5474416e+11 | AD58: 254.74416
A59: GRC | B59: Q2.2020 | C59: =D59+E59 -> 10.391907 | D59: 0.70761691 | E59: 9.68429 | F59: 0 | G59: =H59+I59 -> 8.9610144 | H59: 6.4199944 | I59: =1.1082+1.43282 -> 2.54102 | J59: 0 | K59: =M59+O59 -> 5.0964951 | L59: =N59+P59 -> 3.4462238 | M59: =($D59/$AD59)*100 -> 0.34703603 | N59: =($D59/$AB59)*100 -> 0.23466398 | O59: =($E59/$AD59)*100 -> 4.7494591 | P59: =($E59/$AB59)*100 -> 3.2115598 | Q59: =($F59/$AD59)*100 -> 0 | R59: =($F59/$AB59)*100 -> 0 | S59: =U59+W59 -> 4.3947436 | T59: =V59+X59 -> 2.971703 | U59: =($H59/$AD59)*100 -> 3.1485531 | V59: =($H59/AB59)*100 -> 2.1290354 | W59: =($I59/$AD59)*100 -> 1.2461905 | X59: =($I59/$AB59)*100 -> 0.84266764 | Y59: =($J59/$AD59)*100 -> 0 | Z59: =($J59/$AB59)*100 -> 0 | AA59: 3.0154475e+11 | AB59: 301.54475 | AC59: 2.0390301e+11 | AD59: 203.90301
A60: ISL | B60: Q2.2020 | C60: =D60+E60 -> 0.8825382 | D60: 0.021328007 | E60: 0.8612102 | F60: 0 | G60: =H60+I60 -> 0.91931063 | H60: 0 | I60: 0.91931063 | J60: 0 | K60: =M60+O60 -> 4.2572996 | L60: =N60+P60 -> 4.6280958 | M60: =($D60/$AD60)*100 -> 0.10288474 | N60: =($D60/$AB60)*100 -> 0.11184565 | O60: =($E60/$AD60)*100 -> 4.1544149 | P60: =($E60/$AB60)*100 -> 4.5162502 | Q60: =($F60/$AD60)*100 -> 0 | R60: =($F60/$AB60)*100 -> 0 | S60: =U60+W60 -> 4.4346871 | T60: =V60+X60 -> 4.8209332 | U60: =($H60/$AD60)*100 -> 0 | V60: =($H60/AB60)*100 -> 0 | W60: =($I60/$AD60)*100 -> 4.4346871 | X60: =($I60/$AB60)*100 -> 4.8209332 | Y60: =($J60/$AD60)*100 -> 0 | Z60: =($J60/$AB60)*100 -> 0 | AA60: 1.9069143e+10 | AB60: 19.069143 | AC60: 2.073e+10 | AD60: 20.73
A61: IRL | B61: Q2.2020 | C61: =D61+E61 -> 23.434809 | D61: 2.2863228 | E61: 21.148486 | F61: 2.8579035 | G61: =H61+I61 -> 6.8589684 | H61: 4.5726456 | I61: 2.2863228 | J61: 0 | K61: =M61+O61 -> 6.3087257 | L61: =N61+P61 -> 5.6078791 | M61: =($D61/$AD61)*100 -> 0.61548543 | N61: =($D61/$AB61)*100 -> 0.54711016 | O61: =($E61/$AD61)*100 -> 5.6932403 | P61: =($E61/$AB61)*100 -> 5.060769 | Q61: =($F61/$AD61)*100 -> 0.76935679 | R61: =($F61/$AB61)*100 -> 0.6838877 | S61: =U61+W61 -> 1.8464563 | T61: =V61+X61 -> 1.6413305 | U61: =($H61/$AD61)*100 -> 1.2309709 | V61: =($H61/AB61)*100 -> 1.0942203 | W61: =($I61/$AD61)*100 -> 0.61548543 | X61: =($I61/$AB61)*100 -> 0.54711016 | Y61: =($J61/$AD61)*100 -> 0 | Z61: =($J61/$AB61)*100 -> 0 | AA61: 4.1789076e+11 | AB61: 417.89076 | AC61: 3.714666e+11 | AD61: 371.4666
A62: ISR | B62: Q2.2020 | C62: =D62+E62 -> 25.918306 | D62: 4.0163262 | E62: 21.90198 | F62: 2.0803992 | G62: =H62+I62 -> 11.153251 | H62: 0.95351629 | I62: 10.199735 | J62: 0 | K62: =M62+O62 -> 7.2304548 | L62: =N62+P62 -> 7.5696716 | M62: =($D62/$AD62)*100 -> 1.1204384 | N62: =($D62/$AB62)*100 -> 1.1730037 | O62: =($E62/$AD62)*100 -> 6.1100164 | P62: =($E62/$AB62)*100 -> 6.3966678 | Q62: =($F62/$AD62)*100 -> 0.58037095 | R62: =($F62/$AB62)*100 -> 0.60759906 | S62: =U62+W62 -> 3.1114331 | T62: =V62+X62 -> 3.2574061 | U62: =($H62/$AD62)*100 -> 0.26600335 | V62: =($H62/AB62)*100 -> 0.2784829 | W62: =($I62/$AD62)*100 -> 2.8454298 | X62: =($I62/$AB62)*100 -> 2.9789232 | Y62: =($J62/$AD62)*100 -> 0 | Z62: =($J62/$AB62)*100 -> 0 | AA62: 3.4239671e+11 | AB62: 342.39671 | AC62: 3.5846025e+11 | AD62: 358.46025
A63: LVA | B63: Q2.2020 | C63: =D63+E63 -> 2.6412118 | D63: 0.23110604 | E63: 2.4101058 | F63: 0 | G63: =H63+I63 -> 1.0485611 | H63: 0.23110604 | I63: 0.81745506 | J63: 0 | K63: =M63+O63 -> 8.7573112 | L63: =N63+P63 -> 4.7655872 | M63: =($D63/$AD63)*100 -> 0.76626473 | N63: =($D63/$AB63)*100 -> 0.41698888 | O63: =($E63/$AD63)*100 -> 7.9910464 | P63: =($E63/$AB63)*100 -> 4.3485983 | Q63: =($F63/$AD63)*100 -> 0 | R63: =($F63/$AB63)*100 -> 0 | S63: =U63+W63 -> 3.4766525 | T63: =V63+X63 -> 1.8919381 | U63: =($H63/$AD63)*100 -> 0.76626473 | V63: =($H63/AB63)*100 -> 0.41698888 | W63: =($I63/$AD63)*100 -> 2.7103878 | X63: =($I63/$AB63)*100 -> 1.4749492 | Y63: =($J63/$AD63)*100 -> 0 | Z63: =($J63/$AB63)*100 -> 0 | AA63: 55422589740 | AB63: 55.42259 | AC63: 3.0160078e+10 | AD63: 30.160078
A64: LTU | B64: Q2.2020 | C64: =D64+E64 -> 2.5949764 | D64: 0.5715807 | E64: 2.0233957 | F64: 2.5035235 | G64: =H64+I64 -> 1.9662376 | H64: 0.36581165 | I64: 1.600426 | J64: 0 | K64: =M64+O64 -> 5.3818961 | L64: =N64+P64 -> 2.6714858 | M64: =($D64/$AD64)*100 -> 1.1854397 | N64: =($D64/$AB64)*100 -> 0.58843299 | O64: =($E64/$AD64)*100 -> 4.1964564 | P64: =($E64/$AB64)*100 -> 2.0830528 | Q64: =($F64/$AD64)*100 -> 5.1922257 | R64: =($F64/$AB64)*100 -> 2.5773365 | S64: =U64+W64 -> 4.0779124 | T64: =V64+X64 -> 2.0242095 | U64: =($H64/$AD64)*100 -> 0.75868139 | V64: =($H64/AB64)*100 -> 0.37659711 | W64: =($I64/$AD64)*100 -> 3.3192311 | X64: =($I64/$AB64)*100 -> 1.6476124 | Y64: =($J64/$AD64)*100 -> 0 | Z64: =($J64/$AB64)*100 -> 0 | AA64: 9.7136073e+10 | AB64: 97.136073 | AC64: 4.8216769e+10 | AD64: 48.216769
A65: LUX | B65: Q2.2020 | C65: =D65+E65 -> 3.5438003 | D65: 0.22863228 | E65: 3.3151681 | F65: 5.2145883 | G65: =H65+I65 -> 2.8579035 | H65: 0 | I65: 2.8579035 | J65: 1.2574775 | K65: =M65+O65 -> 5.3244196 | L65: =N65+P65 -> 5.3415951 | M65: =($D65/$AD65)*100 -> 0.34351094 | N65: =($D65/$AB65)*100 -> 0.34461904 | O65: =($E65/$AD65)*100 -> 4.9809086 | P65: =($E65/$AB65)*100 -> 4.9969761 | Q65: =($F65/$AD65)*100 -> 7.8347123 | R65: =($F65/$AB65)*100 -> 7.8599856 | S65: =U65+W65 -> 4.2938867 | T65: =V65+X65 -> 4.307738 | U65: =($H65/$AD65)*100 -> 0 | V65: =($H65/AB65)*100 -> 0 | W65: =($I65/$AD65)*100 -> 4.2938867 | X65: =($I65/$AB65)*100 -> 4.307738 | Y65: =($J65/$AD65)*100 -> 1.8893102 | Z65: =($J65/$AB65)*100 -> 1.8954047 | AA65: 6.6343484e+10 | AB65: 66.343484 | AC65: 6.6557496e+10 | AD65: 66.557496
A66: NLD | B66: Q2.2020 | C66: =D66+E66 -> 33.987077 | D66: 0.76498245 | E66: 33.222095 | F66: 34.970626 | G66: =H66+I66 -> 33.440661 | H66: 0 | I66: 33.440661 | J66: 0 | K66: =M66+O66 -> 4.0448747 | L66: =N66+P66 -> 3.6449596 | M66: =($D66/$AD66)*100 -> 0.091042197 | N66: =($D66/$AB66)*100 -> 0.082040892 | O66: =($E66/$AD66)*100 -> 3.9538325 | P66: =($E66/$AB66)*100 -> 3.5629187 | Q66: =($F66/$AD66)*100 -> 4.161929 | R66: =($F66/$AB66)*100 -> 3.7504408 | S66: =U66+W66 -> 3.9798446 | T66: =V66+X66 -> 3.586359 | U66: =($H66/$AD66)*100 -> 0 | V66: =($H66/AB66)*100 -> 0 | W66: =($I66/$AD66)*100 -> 3.9798446 | X66: =($I66/$AB66)*100 -> 3.586359 | Y66: =($J66/$AD66)*100 -> 0 | Z66: =($J66/$AB66)*100 -> 0 | AA66: 9.3244043e+11 | AB66: 932.44043 | AC66: 8.4025043e+11 | AD66: 840.25043
A67: NZL | B67: Q2.2020 | C67: =D67+E67 -> 39.211062 | D67: 0.31570903 | E67: 38.895353 | F67: 0 | G67: =H67+I67 -> 7.7980131 | H67: 3.8516502 | I67: 3.9463629 | J67: 0 | K67: =M67+O67 -> 19.321592 | L67: =N67+P67 -> 20.214617 | M67: =($D67/$AD67)*100 -> 0.15556837 | N67: =($D67/$AB67)*100 -> 0.16275859 | O67: =($E67/$AD67)*100 -> 19.166023 | P67: =($E67/$AB67)*100 -> 20.051859 | Q67: =($F67/$AD67)*100 -> 0 | R67: =($F67/$AB67)*100 -> 0 | S67: =U67+W67 -> 3.8425388 | T67: =V67+X67 -> 4.0201372 | U67: =($H67/$AD67)*100 -> 1.8979341 | V67: =($H67/AB67)*100 -> 1.9856548 | W67: =($I67/$AD67)*100 -> 1.9446046 | X67: =($I67/$AB67)*100 -> 2.0344824 | Y67: =($J67/$AD67)*100 -> 0 | Z67: =($J67/$AB67)*100 -> 0 | AA67: 1.9397381e+11 | AB67: 193.97381 | AC67: 2.0293909e+11 | AD67: 202.93909
A68: NOR | B68: Q2.2020 | C68: =D68+E68 -> 0 | D68: 0 | E68: 0 | F68: 0 | G68: =H68+I68 -> 17.749252 | H68: 4.9413284 | I68: 12.807923 | J68: 0 | K68: =M68+O68 -> 0 | L68: =N68+P68 -> 0 | M68: =($D68/$AD68)*100 -> 0 | N68: =($D68/$AB68)*100 -> 0 | O68: =($E68/$AD68)*100 -> 0 | P68: =($E68/$AB68)*100 -> 0 | Q68: =($F68/$AD68)*100 -> 0 | R68: =($F68/$AB68)*100 -> 0 | S68: =U68+W68 -> 4.3264547 | T68: =V68+X68 -> 5.3711673 | U68: =($H68/$AD68)*100 -> 1.2044696 | V68: =($H68/AB68)*100 -> 1.4953138 | W68: =($I68/$AD68)*100 -> 3.1219851 | X68: =($I68/$AB68)*100 -> 3.8758535 | Y68: =($J68/$AD68)*100 -> 0 | Z68: =($J68/$AB68)*100 -> 0 | AA68: 3.3045427e+11 | AB68: 330.45427 | AC68: 4.1024933e+11 | AD68: 410.24933
A69: PRT | B69: Q2.2020 | C69: =D69+E69 -> 7.2019168 | D69: 1.8290582 | E69: 5.3728586 | F69: 9.030975 | G69: =H69+I69 -> 14.861098 | H69: 0 | I69: 14.861098 | J69: 0 | K69: =M69+O69 -> 3.2388198 | L69: =N69+P69 -> 2.1106626 | M69: =($D69/$AD69)*100 -> 0.82255741 | N69: =($D69/$AB69)*100 -> 0.53604129 | O69: =($E69/$AD69)*100 -> 2.4162624 | P69: =($E69/$AB69)*100 -> 1.5746213 | Q69: =($F69/$AD69)*100 -> 4.0613772 | R69: =($F69/$AB69)*100 -> 2.6467038 | S69: =U69+W69 -> 6.6832789 | T69: =V69+X69 -> 4.3553354 | U69: =($H69/$AD69)*100 -> 0 | V69: =($H69/AB69)*100 -> 0 | W69: =($I69/$AD69)*100 -> 6.6832789 | X69: =($I69/$AB69)*100 -> 4.3553354 | Y69: =($J69/$AD69)*100 -> 0 | Z69: =($J69/$AB69)*100 -> 0 | AA69: 3.4121593e+11 | AB69: 341.21593 | AC69: 2.2236238e+11 | AD69: 222.36238
A70: SVK | B70: Q2.2020 | C70: =D70+E70 -> 2.5149551 | D70: 0.18290582 | E70: 2.3320493 | F70: 1.4060885 | G70: =H70+I70 -> 4.5840772 | H70: 0 | I70: 4.5840772 | J70: 0 | K70: =M70+O70 -> 2.5278709 | L70: =N70+P70 -> 1.3840355 | M70: =($D70/$AD70)*100 -> 0.18384516 | N70: =($D70/$AB70)*100 -> 0.10065713 | O70: =($E70/$AD70)*100 -> 2.3440258 | P70: =($E70/$AB70)*100 -> 1.2833784 | Q70: =($F70/$AD70)*100 -> 1.4133097 | R70: =($F70/$AB70)*100 -> 0.77380168 | S70: =U70+W70 -> 4.6076193 | T70: =V70+X70 -> 2.5227193 | U70: =($H70/$AD70)*100 -> 0 | V70: =($H70/AB70)*100 -> 0 | W70: =($I70/$AD70)*100 -> 4.6076193 | X70: =($I70/$AB70)*100 -> 2.5227193 | Y70: =($J70/$AD70)*100 -> 0 | Z70: =($J70/$AB70)*100 -> 0 | AA70: 1.8171174e+11 | AB70: 181.71174 | AC70: 9.9489061e+10 | AD70: 99.489061
A71: SVN | B71: Q2.2020 | C71: =D71+E71 -> 4.115381 | D71: 0.11431614 | E71: 4.0010649 | F71: 0 | G71: =H71+I71 -> 3.3151681 | H71: 0.68589684 | I71: 2.6292712 | J71: 0.11431614 | K71: =M71+O71 -> 8.162527 | L71: =N71+P71 -> 5.412314 | M71: =($D71/$AD71)*100 -> 0.22673686 | N71: =($D71/$AB71)*100 -> 0.15034206 | O71: =($E71/$AD71)*100 -> 7.9357901 | P71: =($E71/$AB71)*100 -> 5.261972 | Q71: =($F71/$AD71)*100 -> 0 | R71: =($F71/$AB71)*100 -> 0 | S71: =U71+W71 -> 6.575369 | T71: =V71+X71 -> 4.3599196 | U71: =($H71/$AD71)*100 -> 1.3604212 | V71: =($H71/AB71)*100 -> 0.90205234 | W71: =($I71/$AD71)*100 -> 5.2149478 | X71: =($I71/$AB71)*100 -> 3.4578673 | Y71: =($J71/$AD71)*100 -> 0.22673686 | Z71: =($J71/$AB71)*100 -> 0.15034206 | AA71: 7.6037366e+10 | AB71: 76.037366 | AC71: 5.0417978e+10 | AD71: 50.417978
... A273: POL | B273: Q2.2021 | C273: =D273+E273 -> 38.516359 | D273: 3.7695771 | E273: 34.746782 | F273: 0 | G273: =H273+I273 -> 28.720588 | H273: 9.7444851 | I273: 18.976103 | J273: 0 | K273: =M273+O273 -> 6.7394837 | L273: =N273+P273 -> 3.1689678 | M273: =($D273/$AD273)*100 -> 0.65958995 | N273: =($D273/$AB273)*100 -> 0.31014532 | O273: =($E273/$AD273)*100 -> 6.0798937 | P273: =($E273/$AB273)*100 -> 2.8588225 | Q273: =($F273/$AD273)*100 -> 0 | R273: =($F273/$AB273)*100 -> 0 | S273: =U273+W273 -> 5.0254472 | T273: =V273+X273 -> 2.3630119 | U273: =($H273/$AD273)*100 -> 1.7050625 | V273: =($H273/AB273)*100 -> 0.8017362 | W273: =($I273/$AD273)*100 -> 3.3203848 | X273: =($I273/$AB273)*100 -> 1.5612757 | Y273: =($J273/$AD273)*100 -> 0 | Z273: =($J273/$AB273)*100 -> 0 | AA273: 1.2154229e+12 | AB273: 1215.4229 | AC273: 5.7150312e+11 | AD273: 571.50312

Sheet diff
A1: Country | B1: Quarter | C1: ab_us | D1: health_us | E1: nhealth_us | F1: acc_us | G1: of_us | H1: be_us | I1: gu_us | J1: qf_us | K1: ab_per | L1: ab_ppp | M1: health_per | N1: health_ppp | O1: nhealth_per | P1: nhealth_ppp | Q1: acc_per | R1: acc_ppp | S1: of_per | T1: of_ppp | U1: be_per | V1: be_ppp | W1: gu_per | X1: gu_ppp | Y1: qf_us | Z1: qf_ppp | AA1: GDP 2019 in US Dollar constant PPP 2019 | AB1: in bn | AC1: GDP 2019 in US Dollar constant Prices 2015 | AD1: in bn
A2: AUS | B2: Q1.2020 | C2: =D2+E2 -> 130.0051 | D2: 2.1168 | E2: 127.8883 | F2: 0 | G2: =H2+I2 -> 24.0029 | H2: 10.3255 | I2: 13.6774 | J2: 0 | K2: =M2+O2 -> 8.6973118 | L2: =N2+P2 -> 10.599546 | M2: =($D2/$AD2)*100 -> 0.14161344 | N2: =($D2/$AB2)*100 -> 0.17258646 | O2: =($E2/$AD2)*100 -> 8.5556983 | P2: =($E2/$AB2)*100 -> 10.42696 | Q2: =($F2/$AD2)*100 -> 0 | R2: =($F2/$AB2)*100 -> 0 | S2: =U2+W2 -> 1.6057886 | T2: =V2+X2 -> 1.956999 | U2: =($H2/$AD2)*100 -> 0.69077361 | V2: =($H2/AB2)*100 -> 0.84185631 | W2: =($I2/$AD2)*100 -> 0.91501497 | X2: =($I2/$AB2)*100 -> 1.1151427 | Y2: =($J2/$AD2)*100 -> 0 | Z2: =($J2/$AB2)*100 -> 0 | AA2: 1.2265157e+12 | AB2: 1226.5157 | AC2: 1.4947734e+12 | AD2: 1494.7734
A3: CAN | B3: Q1.2020 | C3: =D3+E3 -> 81 | D3: 2.4 | E3: 78.6 | F3: 63.75 | G3: =H3+I3 -> 51.7 | H3: 3.7 | I3: 48 | J3: 0 | K3: =M3+O3 -> 4.7742401 | L3: =N3+P3 -> 4.6997712 | M3: =($D3/$AD3)*100 -> 0.14145896 | N3: =($D3/$AB3)*100 -> 0.13925248 | O3: =($E3/$AD3)*100 -> 4.6327811 | P3: =($E3/$AB3)*100 -> 4.5605187 | Q3: =($F3/$AD3)*100 -> 3.7575038 | R3: =($F3/$AB3)*100 -> 3.698894 | S3: =U3+W3 -> 3.0472619 | T3: =V3+X3 -> 2.9997305 | U3: =($H3/$AD3)*100 -> 0.21808257 | V3: =($H3/AB3)*100 -> 0.21468091 | W3: =($I3/$AD3)*100 -> 2.8291793 | X3: =($I3/$AB3)*100 -> 2.7850496 | Y3: =($J3/$AD3)*100 -> 0 | Z3: =($J3/$AB3)*100 -> 0 | AA3: 1.7234882e+12 | AB3: 1723.4882 | AC3: 1.6966051e+12 | AD3: 1696.6051
A4: FRA | B4: Q1.2020 | C4: =D4+E4 -> 16.5 | D4: 5.5 | E4: 11 | F4: 48.5 | G4: =H4+I4 -> 348 | H4: 0 | I4: 348 | J4: 0 | K4: =M4+O4 -> 0.63053811 | L4: =N4+P4 -> 0.56757784 | M4: =($D4/$AD4)*100 -> 0.21017937 | N4: =($D4/$AB4)*100 -> 0.18919261 | O4: =($E4/$AD4)*100 -> 0.42035874 | P4: =($E4/$AB4)*100 -> 0.37838523 | Q4: =($F4/$AD4)*100 -> 1.8533999 | R4: =($F4/$AB4)*100 -> 1.6683349 | S4: =U4+W4 -> 13.298622 | T4: =V4+X4 -> 11.970733 | U4: =($H4/$AD4)*100 -> 0 | V4: =($H4/AB4)*100 -> 0 | W4: =($I4/$AD4)*100 -> 13.298622 | X4: =($I4/$AB4)*100 -> 11.970733 | Y4: =($J4/$AD4)*100 -> 0 | Z4: =($J4/$AB4)*100 -> 0 | AA4: 2.9070902e+12 | AB4: 2907.0902 | AC4: 2.6168125e+12 | AD4: 2616.8125
A5: DEU | B5: Q1.2020 | C5: =D5+E5 -> 143 | D5: 11.2 | E5: 131.8 | F5: 0 | G5: =H5+I5 -> 1072 | H5: 223 | I5: 849 | J5: 0 | K5: =M5+O5 -> 3.9751845 | L5: =N5+P5 -> 3.4360259 | M5: =($D5/$AD5)*100 -> 0.31134312 | N5: =($D5/$AB5)*100 -> 0.26911531 | O5: =($E5/$AD5)*100 -> 3.6638413 | P5: =($E5/$AB5)*100 -> 3.1669106 | Q5: =($F5/$AD5)*100 -> 0 | R5: =($F5/$AB5)*100 -> 0 | S5: =U5+W5 -> 29.799984 | T5: =V5+X5 -> 25.75818 | U5: =($H5/$AD5)*100 -> 6.1990639 | V5: =($H5/AB5)*100 -> 5.3582781 | W5: =($I5/$AD5)*100 -> 23.60092 | X5: =($I5/$AB5)*100 -> 20.399902 | Y5: =($J5/$AD5)*100 -> 0 | Z5: =($J5/$AB5)*100 -> 0 | AA5: 4.1617847e+12 | AB5: 4161.7847 | AC5: 3.5973173e+12 | AD5: 3597.3173
A6: ITA | B6: Q1.2020 | C6: =D6+E6 -> 22 | D6: 3.63 | E6: 18.37 | F6: 0 | G6: =H6+I6 -> 591 | H6: 0 | I6: 591 | J6: 0 | K6: =M6+O6 -> 1.1469339 | L6: =N6+P6 -> 0.94111213 | M6: =($D6/$AD6)*100 -> 0.18924409 | N6: =($D6/$AB6)*100 -> 0.1552835 | O6: =($E6/$AD6)*100 -> 0.95768981 | P6: =($E6/$AB6)*100 -> 0.78582863 | Q6: =($F6/$AD6)*100 -> 0 | R6: =($F6/$AB6)*100 -> 0 | S6: =U6+W6 -> 30.810815 | T6: =V6+X6 -> 25.281694 | U6: =($H6/$AD6)*100 -> 0 | V6: =($H6/AB6)*100 -> 0 | W6: =($I6/$AD6)*100 -> 30.810815 | X6: =($I6/$AB6)*100 -> 25.281694 | Y6: =($J6/$AD6)*100 -> 0 | Z6: =($J6/$AB6)*100 -> 0 | AA6: 2.3376598e+12 | AB6: 2337.6598 | AC6: 1.9181576e+12 | AD6: 1918.1576
A7: JPN | B7: Q1.2020 | C7: =D7+E7 -> 497 | D7: 12.1906 | E7: 484.8094 | F7: 0 | G7: =H7+I7 -> 518 | H7: 499 | I7: 19 | J7: 0 | K7: =M7+O7 -> 10.888777 | L7: =N7+P7 -> 9.3335923 | M7: =($D7/$AD7)*100 -> 0.26708396 | N7: =($D7/$AB7)*100 -> 0.22893781 | O7: =($E7/$AD7)*100 -> 10.621693 | P7: =($E7/$AB7)*100 -> 9.1046545 | Q7: =($F7/$AD7)*100 -> 0 | R7: =($F7/$AB7)*100 -> 0 | S7: =U7+W7 -> 11.348866 | T7: =V7+X7 -> 9.7279695 | U7: =($H7/$AD7)*100 -> 10.932595 | V7: =($H7/AB7)*100 -> 9.3711521 | W7: =($I7/$AD7)*100 -> 0.41627116 | X7: =($I7/$AB7)*100 -> 0.35681741 | Y7: =($J7/$AD7)*100 -> 0 | Z7: =($J7/$AB7)*100 -> 0 | AA7: 5.3248522e+12 | AB7: 5324.8522 | AC7: 4.5643326e+12 | AD7: 4564.3326
A8: KOR | B8: Q1.2020 | C8: =D8+E8 -> 24 | D8: 2.5 | E8: 21.5 | F8: 14 | G8: =H8+I8 -> 215 | H8: 101 | I8: 114 | J8: 0 | K8: =M8+O8 -> 1.46507 | L8: =N8+P8 -> 1.112894 | M8: =($D8/$AD8)*100 -> 0.15261146 | N8: =($D8/$AB8)*100 -> 0.11592646 | O8: =($E8/$AD8)*100 -> 1.3124586 | P8: =($E8/$AB8)*100 -> 0.99696756 | Q8: =($F8/$AD8)*100 -> 0.85462418 | R8: =($F8/$AB8)*100 -> 0.64918818 | S8: =U8+W8 -> 13.124586 | T8: =V8+X8 -> 9.9696756 | U8: =($H8/$AD8)*100 -> 6.165503 | V8: =($H8/AB8)*100 -> 4.683429 | W8: =($I8/$AD8)*100 -> 6.9590826 | X8: =($I8/$AB8)*100 -> 5.2862466 | Y8: =($J8/$AD8)*100 -> 0 | Z8: =($J8/$AB8)*100 -> 0 | AA8: 2.1565396e+12 | AB8: 2156.5396 | AC8: 1.638147e+12 | AD8: 1638.147
A9: ESP | B9: Q1.2020 | C9: =D9+E9 -> 14.8929 | D9: 4.1786 | E9: 10.7143 | F9: 0 | G9: =H9+I9 -> 175.6152 | H9: 11 | I9: 164.6152 | J9: 11.4316 | K9: =M9+O9 -> 1.1249106 | L9: =N9+P9 -> 0.82898249 | M9: =($D9/$AD9)*100 -> 0.31562366 | N9: =($D9/$AB9)*100 -> 0.23259313 | O9: =($E9/$AD9)*100 -> 0.80928698 | P9: =($E9/$AB9)*100 -> 0.59638936 | Q9: =($F9/$AD9)*100 -> 0 | R9: =($F9/$AB9)*100 -> 0 | S9: =U9+W9 -> 13.264805 | T9: =V9+X9 -> 9.775257 | U9: =($H9/$AD9)*100 -> 0.83086686 | V9: =($H9/AB9)*100 -> 0.61229226 | W9: =($I9/$AD9)*100 -> 12.433938 | X9: =($I9/$AB9)*100 -> 9.1629648 | Y9: =($J9/$AD9)*100 -> 0.86346706 | Z9: =($J9/$AB9)*100 -> 0.63631638 | AA9: 1.7965277e+12 | AB9: 1796.5277 | AC9: 1.3239185e+12 | AD9: 1323.9185
A10: GBR | B10: Q1.2020 | C10: =D10+E10 -> 83 | D10: 6.3846154 | E10: 76.615385 | F10: 0 | G10: =H10+I10 -> 423 | H10: 423 | I10: 0 | J10: 0 | K10: =M10+O10 -> 2.628755 | L10: =N10+P10 -> 2.8212212 | M10: =($D10/$AD10)*100 -> 0.20221192 | N10: =($D10/$AB10)*100 -> 0.21701702 | O10: =($E10/$AD10)*100 -> 2.4265431 | P10: =($E10/$AB10)*100 -> 2.6042042 | Q10: =($F10/$AD10)*100 -> 0 | R10: =($F10/$AB10)*100 -> 0 | S10: =U10+W10 -> 13.397149 | T10: =V10+X10 -> 14.378031 | U10: =($H10/$AD10)*100 -> 13.397149 | V10: =($H10/AB10)*100 -> 14.378031 | W10: =($I10/$AD10)*100 -> 0 | X10: =($I10/$AB10)*100 -> 0 | Y10: =($J10/$AD10)*100 -> 0 | Z10: =($J10/$AB10)*100 -> 0 | AA10: 2.9419883e+12 | AB10: 2941.9883 | AC10: 3.1573882e+12 | AD10: 3157.3882
A11: USA | B11: Q1.2020 | C11: =D11+E11 -> 1395 | D11: 9.45 | E11: 1385.55 | F11: 0 | G11: =H11+I11 -> 859 | H11: 405 | I11: 454 | J11: 0 | K11: =M11+O11 -> 6.9998582 | L11: =N11+P11 -> 6.9840045 | M11: =($D11/$AD11)*100 -> 0.047418394 | N11: =($D11/$AB11)*100 -> 0.047310998 | O11: =($E11/$AD11)*100 -> 6.9524398 | P11: =($E11/$AB11)*100 -> 6.9366935 | Q11: =($F11/$AD11)*100 -> 0 | R11: =($F11/$AB11)*100 -> 0 | S11: =U11+W11 -> 4.3103069 | T11: =V11+X11 -> 4.3005447 | U11: =($H11/$AD11)*100 -> 2.0322169 | V11: =($H11/AB11)*100 -> 2.0276142 | W11: =($I11/$AD11)*100 -> 2.27809 | X11: =($I11/$AB11)*100 -> 2.2729305 | Y11: =($J11/$AD11)*100 -> 0 | Z11: =($J11/$AB11)*100 -> 0 | AA11: 1.9974214e+13 | AB11: 19974.214 | AC11: 19928975197000 | AD11: 19928.975
A12: MEX | B12: Q1.2020 | C12: =D12+E12 -> 7.9 | D12: 7.9 | E12: 0 | F12: 0 | G12: =H12+I12 -> 3.3 | H12: 3.3 | I12: 0 | J12: 0 | K12: =M12+O12 -> 0.61759698 | L12: =N12+P12 -> 0.33170037 | M12: =($D12/$AD12)*100 -> 0.61759698 | N12: =($D12/$AB12)*100 -> 0.33170037 | O12: =($E12/$AD12)*100 -> 0 | P12: =($E12/$AB12)*100 -> 0 | Q12: =($F12/$AD12)*100 -> 0 | R12: =($F12/$AB12)*100 -> 0 | S12: =U12+W12 -> 0.25798355 | T12: =V12+X12 -> 0.13855838 | U12: =($H12/$AD12)*100 -> 0.25798355 | V12: =($H12/AB12)*100 -> 0.13855838 | W12: =($I12/$AD12)*100 -> 0 | X12: =($I12/$AB12)*100 -> 0 | Y12: =($J12/$AD12)*100 -> 0 | Z12: =($J12/$AB12)*100 -> 0 | AA12: 2.3816676e+12 | AB12: 2381.6676 | AC12: 1.2791513e+12 | AD12: 1279.1513
A13: TUR | B13: Q1.2020 | C13: =D13+E13 -> 11 | D13: 11 | E13: 0 | F13: 0 | G13: =H13+I13 -> 3.8 | H13: 0 | I13: 3.8 | J13: 0 | K13: =M13+O13 -> 1.1032507 | L13: =N13+P13 -> 0.47133766 | M13: =($D13/$AD13)*100 -> 1.1032507 | N13: =($D13/$AB13)*100 -> 0.47133766 | O13: =($E13/$AD13)*100 -> 0 | P13: =($E13/$AB13)*100 -> 0 | Q13: =($F13/$AD13)*100 -> 0 | R13: =($F13/$AB13)*100 -> 0 | S13: =U13+W13 -> 0.38112296 | T13: =V13+X13 -> 0.16282574 | U13: =($H13/$AD13)*100 -> 0 | V13: =($H13/AB13)*100 -> 0 | W13: =($I13/$AD13)*100 -> 0.38112296 | X13: =($I13/$AB13)*100 -> 0.16282574 | Y13: =($J13/$AD13)*100 -> 0 | Z13: =($J13/$AB13)*100 -> 0 | AA13: 2.3337834e+12 | AB13: 2333.7834 | AC13: 9.9705355e+11 | AD13: 997.05355
... A27: NLD | B27: Q1.2020 | C27: =D27+E27 -> 22 | D27: 0 | E27: 22 | F27: 45 | G27: =H27+I27 -> 0 | H27: 0 | I27: 0 | J27: 0 | K27: =M27+O27 -> 2.618267 | L27: =N27+P27 -> 2.3594 | M27: =($D27/$AD27)*100 -> 0 | N27: =($D27/$AB27)*100 -> 0 | O27: =($E27/$AD27)*100 -> 2.618267 | P27: =($E27/$AB27)*100 -> 2.3594 | Q27: =($F27/$AD27)*100 -> 5.3555462 | R27: =($F27/$AB27)*100 -> 4.8260455 | S27: =U27+W27 -> 0 | T27: =V27+X27 -> 0 | U27: =($H27/$AD27)*100 -> 0 | V27: =($H27/AB27)*100 -> 0 | W27: =($I27/$AD27)*100 -> 0 | X27: =($I27/$AB27)*100 -> 0 | Y27: =($J27/$AD27)*100 -> 0 | Z27: =($J27/$AB27)*100 -> 0 | AA27: 9.3244043e+11 | AB27: 932.44043 | AC27: 8.4025043e+11 | AD27: 840.25043
A28: NZL | B28: Q1.2020 | C28: =D28+E28 -> 11.088516 | D28: 0.31570903 | E28: 10.772806 | F28: 0 | G28: =H28+I28 -> 6.6522016 | H28: 2.7058387 | I28: 3.9463629 | K28: =M28+O28 -> 5.4639624 | L28: =N28+P28 -> 5.7165015 | M28: =($D28/$AD28)*100 -> 0.15556837 | N28: =($D28/$AB28)*100 -> 0.16275859 | O28: =($E28/$AD28)*100 -> 5.3083941 | P28: =($E28/$AB28)*100 -> 5.5537429 | Q28: =($F28/$AD28)*100 -> 0 | R28: =($F28/$AB28)*100 -> 0 | S28: =U28+W28 -> 3.2779302 | T28: =V28+X28 -> 3.429433 | U28: =($H28/$AD28)*100 -> 1.3333256 | V28: =($H28/AB28)*100 -> 1.3949506 | W28: =($I28/$AD28)*100 -> 1.9446046 | X28: =($I28/$AB28)*100 -> 2.0344824 | Y28: =($J28/$AD28)*100 -> 0 | Z28: =($J28/$AB28)*100 -> 0 | AA28: 1.9397381e+11 | AB28: 193.97381 | AC28: 2.0293909e+11 | AD28: 202.93909
A29: NOR | B29: Q1.2020 | C29: =D29+E29 -> 8.1 | D29: 0 | E29: 8.1 | F29: 0 | G29: =H29+I29 -> 10.6 | H29: 5.3 | I29: 5.3 | J29: 0 | K29: =M29+O29 -> 1.9744091 | L29: =N29+P29 -> 2.4511712 | M29: =($D29/$AD29)*100 -> 0 | N29: =($D29/$AB29)*100 -> 0 | O29: =($E29/$AD29)*100 -> 1.9744091 | P29: =($E29/$AB29)*100 -> 2.4511712 | Q29: =($F29/$AD29)*100 -> 0 | R29: =($F29/$AB29)*100 -> 0 | S29: =U29+W29 -> 2.5837946 | T29: =V29+X29 -> 3.2077056 | U29: =($H29/$AD29)*100 -> 1.2918973 | V29: =($H29/AB29)*100 -> 1.6038528 | W29: =($I29/$AD29)*100 -> 1.2918973 | X29: =($I29/$AB29)*100 -> 1.6038528 | Y29: =($J29/$AD29)*100 -> 0 | Z29: =($J29/$AB29)*100 -> 0 | AA29: 3.3045427e+11 | AB29: 330.45427 | AC29: 4.1024933e+11 | AD29: 410.24933
A30: PRT | B30: Q1.2020 | C30: =D30+E30 -> 7.2019168 | D30: 1.8290582 | E30: 5.3728586 | F30: 9.030975 | G30: =H30+I30 -> 14.861098 | H30: 0 | I30: 14.861098 | J30: 0 | K30: =M30+O30 -> 3.2388198 | L30: =N30+P30 -> 2.1106626 | M30: =($D30/$AD30)*100 -> 0.82255741 | N30: =($D30/$AB30)*100 -> 0.53604129 | O30: =($E30/$AD30)*100 -> 2.4162624 | P30: =($E30/$AB30)*100 -> 1.5746213 | Q30: =($F30/$AD30)*100 -> 4.0613772 | R30: =($F30/$AB30)*100 -> 2.6467038 | S30: =U30+W30 -> 6.6832789 | T30: =V30+X30 -> 4.3553354 | U30: =($H30/$AD30)*100 -> 0 | V30: =($H30/AB30)*100 -> 0 | W30: =($I30/$AD30)*100 -> 6.6832789 | X30: =($I30/$AB30)*100 -> 4.3553354 | Y30: =($J30/$AD30)*100 -> 0 | Z30: =($J30/$AB30)*100 -> 0 | AA30: 3.4121593e+11 | AB30: 341.21593 | AC30: 2.2236238e+11 | AD30: 222.36238
A31: SVK | B31: Q1.2020 | C31: =D31+E31 -> 2.5149551 | D31: 0.18290582 | E31: 2.3320493 | F31: 1.4060885 | G31: =H31+I31 -> 4.5840772 | H31: 0 | I31: 4.5840772 | J31: 0 | K31: =M31+O31 -> 2.5278709 | L31: =N31+P31 -> 1.3840355 | M31: =($D31/$AD31)*100 -> 0.18384516 | N31: =($D31/$AB31)*100 -> 0.10065713 | O31: =($E31/$AD31)*100 -> 2.3440258 | P31: =($E31/$AB31)*100 -> 1.2833784 | Q31: =($F31/$AD31)*100 -> 1.4133097 | R31: =($F31/$AB31)*100 -> 0.77380168 | S31: =U31+W31 -> 4.6076193 | T31: =V31+X31 -> 2.5227193 | U31: =($H31/$AD31)*100 -> 0 | V31: =($H31/AB31)*100 -> 0 | W31: =($I31/$AD31)*100 -> 4.6076193 | X31: =($I31/$AB31)*100 -> 2.5227193 | Y31: =($J31/$AD31)*100 -> 0 | Z31: =($J31/$AB31)*100 -> 0 | AA31: 1.8171174e+11 | AB31: 181.71174 | AC31: 9.9489061e+10 | AD31: 99.489061
A32: SVN | B32: Q1.2020 | C32: =D32+E32 -> 4.115381 | D32: 0.11431614 | E32: 4.0010649 | F32: 0 | G32: =H32+I32 -> 3.3151681 | H32: 0.68589684 | I32: 2.6292712 | J32: 0.11431614 | K32: =M32+O32 -> 8.162527 | L32: =N32+P32 -> 5.412314 | M32: =($D32/$AD32)*100 -> 0.22673686 | N32: =($D32/$AB32)*100 -> 0.15034206 | O32: =($E32/$AD32)*100 -> 7.9357901 | P32: =($E32/$AB32)*100 -> 5.261972 | Q32: =($F32/$AD32)*100 -> 0 | R32: =($F32/$AB32)*100 -> 0 | S32: =U32+W32 -> 6.575369 | T32: =V32+X32 -> 4.3599196 | U32: =($H32/$AD32)*100 -> 1.3604212 | V32: =($H32/AB32)*100 -> 0.90205234 | W32: =($I32/$AD32)*100 -> 5.2149478 | X32: =($I32/$AB32)*100 -> 3.4578673 | Y32: =($J32/$AD32)*100 -> 0.22673686 | Z32: =($J32/$AB32)*100 -> 0.15034206 | AA32: 7.6037366e+10 | AB32: 76.037366 | AC32: 5.0417978e+10 | AD32: 50.417978
A33: SWE | B33: Q1.2020 | C33: =D33+E33 -> 11 | D33: 0 | E33: 11 | F33: 0 | G33: =H33+I33 -> 25 | H33: 0 | I33: 25 | J33: 0 | K33: =M33+O33 -> 2.0006501 | L33: =N33+P33 -> 2.1113062 | M33: =($D33/$AD33)*100 -> 0 | N33: =($D33/$AB33)*100 -> 0 | O33: =($E33/$AD33)*100 -> 2.0006501 | P33: =($E33/$AB33)*100 -> 2.1113062 | Q33: =($F33/$AD33)*100 -> 0 | R33: =($F33/$AB33)*100 -> 0 | S33: =U33+W33 -> 4.546932 | T33: =V33+X33 -> 4.7984231 | U33: =($H33/$AD33)*100 -> 0 | V33: =($H33/AB33)*100 -> 0 | W33: =($I33/$AD33)*100 -> 4.546932 | X33: =($I33/$AB33)*100 -> 4.7984231 | Y33: =($J33/$AD33)*100 -> 0 | Z33: =($J33/$AB33)*100 -> 0 | AA33: 5.2100449e+11 | AB33: 521.00449 | AC33: 5.4982128e+11 | AD33: 549.82128
A34: CHE | B34: Q1.2020 | C34: =D34+E34 -> 1.6825977 | D34: 0 | E34: 1.6825977 | F34: 0 | G34: =H34+I34 -> 0.21161296 | H34: =0.0516129+0.05677419 -> 0.10838709 | I34: =0.10322587 -> 0.10322587 | J34: 0 | K34: =M34+O34 -> 0.22521425 | L34: =N34+P34 -> 0.28479303 | M34: =($D34/$AD34)*100 -> 0 | N34: =($D34/$AB34)*100 -> 0 | O34: =($E34/$AD34)*100 -> 0.22521425 | P34: =($E34/$AB34)*100 -> 0.28479303 | Q34: =($F34/$AD34)*100 -> 0 | R34: =($F34/$AB34)*100 -> 0 | S34: =U34+W34 -> 0.028324212 | T34: =V34+X34 -> 0.035817175 | U34: =($H34/$AD34)*100 -> 0.014507519 | V34: =($H34/AB34)*100 -> 0.018345376 | W34: =($I34/$AD34)*100 -> 0.013816694 | X34: =($I34/$AB34)*100 -> 0.017471799 | Y34: =($J34/$AD34)*100 -> 0 | Z34: =($J34/$AB34)*100 -> 0 | AA34: 5.9081422e+11 | AB34: 590.81422 | AC34: 7.4710978e+11 | AD34: 747.10978
A35: CHL | B35: Q1.2020 | C35: =D35+E35 -> 4.6 | D35: 1 | E35: 3.6 | F35: 4.7152702 | G35: =H35+I35 -> 2.4 | H35: 2.4 | I35: 0 | J35: 0 | K35: =M35+O35 -> 1.7559969 | L35: =N35+P35 -> 1.0424015 | M35: =($D35/$AD35)*100 -> 0.38173846 | N35: =($D35/$AB35)*100 -> 0.22660903 | O35: =($E35/$AD35)*100 -> 1.3742585 | P35: =($E35/$AB35)*100 -> 0.81579252 | Q35: =($F35/$AD35)*100 -> 1.8 | R35: =($F35/$AB35)*100 -> 1.0685228 | S35: =U35+W35 -> 0.91617231 | T35: =V35+X35 -> 0.54386168 | U35: =($H35/$AD35)*100 -> 0.91617231 | V35: =($H35/AB35)*100 -> 0.54386168 | W35: =($I35/$AD35)*100 -> 0 | X35: =($I35/$AB35)*100 -> 0 | Y35: =($J35/$AD35)*100 -> 0 | Z35: =($J35/$AB35)*100 -> 0 | AA35: 4.4128868e+11 | AB35: 441.28868 | AC35: 2.6195946e+11 | AD35: 261.95946
A36: COL | B36: Q1.2020 | C36: =D36+E36 -> 0 | D36: 0 | E36: 0 | F36: 0 | G36: =H36+I36 -> 0.1 | H36: 0.1 | I36: 0 | J36: 0 | K36: =M36+O36 -> 0 | L36: =N36+P36 -> 0 | M36: =($D36/$AD36)*100 -> 0 | N36: =($D36/$AB36)*100 -> 0 | O36: =($E36/$AD36)*100 -> 0 | P36: =($E36/$AB36)*100 -> 0 | Q36: =($F36/$AD36)*100 -> 0 | R36: =($F36/$AB36)*100 -> 0 | S36: =U36+W36 -> 0.031113334 | T36: =V36+X36 -> 0.014482907 | U36: =($H36/$AD36)*100 -> 0.031113334 | V36: =($H36/AB36)*100 -> 0.014482907 | W36: =($I36/$AD36)*100 -> 0 | X36: =($I36/$AB36)*100 -> 0 | Y36: =($J36/$AD36)*100 -> 0 | Z36: =($J36/$AB36)*100 -> 0 | AA36: 6.9046913e+11 | AB36: 690.46913 | AC36: 3.2140561e+11 | AD36: 321.40561
A37: CRI | B37: Q1.2020 | C37: =D37+E37 -> 0.717434 | D37: 0.17 | E37: 0.547434 | F37: 0 | G37: =H37+I37 -> 0 | H37: 0 | I37: 0 | J37: 0 | K37: =M37+O37 -> 1.1143309 | L37: =N37+P37 -> 0.78637134 | M37: =($D37/$AD37)*100 -> 0.26404693 | N37: =($D37/$AB37)*100 -> 0.18633509 | O37: =($E37/$AD37)*100 -> 0.85028393 | P37: =($E37/$AB37)*100 -> 0.60003625 | Q37: =($F37/$AD37)*100 -> 0 | R37: =($F37/$AB37)*100 -> 0 | S37: =U37+W37 -> 0 | T37: =V37+X37 -> 0 | U37: =($H37/$AD37)*100 -> 0 | V37: =($H37/AB37)*100 -> 0 | W37: =($I37/$AD37)*100 -> 0 | X37: =($I37/$AB37)*100 -> 0 | Y37: =($J37/$AD37)*100 -> 0 | Z37: =($J37/$AB37)*100 -> 0 | AA37: 9.1233488e+10 | AB37: 91.233488 | AC37: 6.4382494e+10 | AD37: 64.382494
A38: HUN | B38: Q1.2020 | C38: =D38+E38 -> 4.419749 | D38: 0 | E38: 4.419749 | F38: 0 | G38: =H38+I38 -> 0 | H38: 0 | I38: 0 | J38: 0 | K38: =M38+O38 -> 2.9987989 | L38: =N38+P38 -> 1.42624 | M38: =($D38/$AD38)*100 -> 0 | N38: =($D38/$AB38)*100 -> 0 | O38: =($E38/$AD38)*100 -> 2.9987989 | P38: =($E38/$AB38)*100 -> 1.42624 | Q38: =($F38/$AD38)*100 -> 0 | R38: =($F38/$AB38)*100 -> 0 | S38: =U38+W38 -> 0 | T38: =V38+X38 -> 0 | U38: =($H38/$AD38)*100 -> 0 | V38: =($H38/AB38)*100 -> 0 | W38: =($I38/$AD38)*100 -> 0 | X38: =($I38/$AB38)*100 -> 0 | Y38: =($J38/$AD38)*100 -> 0 | Z38: =($J38/$AB38)*100 -> 0 | AA38: 3.0988816e+11 | AB38: 309.88816 | AC38: 1.4738397e+11 | AD38: 147.38397
A39: POL | B39: Q1.2020 | C39: =D39+E39 -> 17 | D39: 8 | E39: 9 | F39: 0 | G39: =H39+I39 -> 17 | H39: 0 | I39: 17 | J39: 0 | K39: =M39+O39 -> 2.9746119 | L39: =N39+P39 -> 1.3986902 | M39: =($D39/$AD39)*100 -> 1.3998174 | N39: =($D39/$AB39)*100 -> 0.65820713 | O39: =($E39/$AD39)*100 -> 1.5747946 | P39: =($E39/$AB39)*100 -> 0.74048302 | Q39: =($F39/$AD39)*100 -> 0 | R39: =($F39/$AB39)*100 -> 0 | S39: =U39+W39 -> 2.9746119 | T39: =V39+X39 -> 1.3986902 | U39: =($H39/$AD39)*100 -> 0 | V39: =($H39/AB39)*100 -> 0 | W39: =($I39/$AD39)*100 -> 2.9746119 | X39: =($I39/$AB39)*100 -> 1.3986902 | Y39: =($J39/$AD39)*100 -> 0 | Z39: =($J39/$AB39)*100 -> 0 | AA39: 1.2154229e+12 | AB39: 1215.4229 | AC39: 5.7150312e+11 | AD39: 571.50312
A40: AUS | B40: Q2.2020 | C40: =D40+E40 -> 0.36671522 | D40: =data!D41-data!D2 -> 1.1544453 | E40: =data!E41-data!E2 -> -0.78773004 | F40: =data!F41-data!F2 -> 0 | G40: =H40+I40 -> -1.1041831 | H40: =data!H41-data!H2 -> -0.51176421 | I40: =data!I41-data!I2 -> -0.59241894 | J40: =data!J41-data!J2 -> 0 | K40: =M40+O40 -> 0.024533165 | L40: =N40+P40 -> 0.029898942 | M40: =($D40/$AD40)*100 -> 0.077232127 | N40: =($D40/$AB40)*100 -> 0.094123968 | O40: =($E40/$AD40)*100 -> -0.052698962 | P40: =($E40/$AB40)*100 -> -0.064225027 | Q40: =($F40/$AD40)*100 -> 0 | R40: =($F40/$AB40)*100 -> 0 | S40: =U40+W40 -> -0.073869603 | T40: =V40+X40 -> -0.090026009 | U40: =($H40/$AD40)*100 -> -0.03423691 | V40: =($H40/AB40)*100 -> -0.041725043 | W40: =($I40/$AD40)*100 -> -0.039632693 | X40: =($I40/$AB40)*100 -> -0.048300966 | Y40: =($J40/$AD40)*100 -> 0 | Z40: =($J40/$AB40)*100 -> 0 | AA40: 1.2265157e+12 | AB40: 1226.5157 | AC40: 1.4947734e+12 | AD40: 1494.7734
A41: CAN | B41: Q2.2020 | C41: =D41+E41 -> 5.3821267 | D41: =data!D42-data!D3 -> 0.47940422 | E41: =data!E42-data!E3 -> 4.9027225 | F41: =data!F42-data!F3 -> -2.5626603 | G41: =H41+I41 -> -1.3104261 | H41: =data!H42-data!H3 -> -0.10074472 | I41: =data!I42-data!I3 -> -1.2096814 | J41: =data!J42-data!J3 -> 0 | K41: =M41+O41 -> 0.3172292 | L41: =N41+P41 -> 0.31228104 | M41: =($D41/$AD41)*100 -> 0.028256677 | N41: =($D41/$AB41)*100 -> 0.027815928 | O41: =($E41/$AD41)*100 -> 0.28897252 | P41: =($E41/$AB41)*100 -> 0.28446511 | Q41: =($F41/$AD41)*100 -> -0.15104636 | R41: =($F41/$AB41)*100 -> -0.14869033 | S41: =U41+W41 -> -0.077238133 | T41: =V41+X41 -> -0.076033368 | U41: =($H41/$AD41)*100 -> -0.0059380183 | V41: =($H41/AB41)*100 -> -0.0058453968 | W41: =($I41/$AD41)*100 -> -0.071300115 | X41: =($I41/$AB41)*100 -> -0.070187972 | Y41: =($J41/$AD41)*100 -> 0 | Z41: =($J41/$AB41)*100 -> 0 | AA41: 1.7234882e+12 | AB41: 1723.4882 | AC41: 1.6966051e+12 | AD41: 1696.6051
A42: FRA | B42: Q2.2020 | C42: =D42+E42 -> 46.119278 | D42: =data!D43-data!D4 -> 3.2426566 | E42: =data!E43-data!E4 -> 42.876621 | F42: =data!F43-data!F4 -> 12.15218 | G42: =H42+I42 -> 32.305561 | H42: =data!H43-data!H4 -> 22.949473 | I42: =data!I43-data!I4 -> 9.356087 | J42: =data!J43-data!J4 -> 0 | K42: =M42+O42 -> 1.7624219 | L42: =N42+P42 -> 1.5864412 | M42: =($D42/$AD42)*100 -> 0.12391628 | N42: =($D42/$AB42)*100 -> 0.11154303 | O42: =($E42/$AD42)*100 -> 1.6385057 | P42: =($E42/$AB42)*100 -> 1.4748982 | Q42: =($F42/$AD42)*100 -> 0.46438864 | R42: =($F42/$AB42)*100 -> 0.41801867 | S42: =U42+W42 -> 1.2345386 | T42: =V42+X42 -> 1.1112679 | U42: =($H42/$AD42)*100 -> 0.87700107 | V42: =($H42/AB42)*100 -> 0.78943106 | W42: =($I42/$AD42)*100 -> 0.35753754 | X42: =($I42/$AB42)*100 -> 0.32183683 | Y42: =($J42/$AD42)*100 -> 0 | Z42: =($J42/$AB42)*100 -> 0 | AA42: 2.9070902e+12 | AB42: 2907.0902 | AC42: 2.6168125e+12 | AD42: 2616.8125
A43: DEU | B43: Q2.2020 | C43: =D43+E43 -> 189.22095 | D43: =data!D44-data!D5 -> 13.935138 | E43: =data!E44-data!E5 -> 175.28581 | F43: =data!F44-data!F5 -> 0 | G43: =H43+I43 -> 42.688712 | H43: =data!H44-data!H5 -> -4.4335859 | I43: =data!I44-data!I5 -> 47.122298 | J43: =data!J44-data!J5 -> 0 | K43: =M43+O43 -> 5.2600572 | L43: =N43+P43 -> 4.5466299 | M43: =($D43/$AD43)*100 -> 0.38737582 | N43: =($D43/$AB43)*100 -> 0.33483562 | O43: =($E43/$AD43)*100 -> 4.8726814 | P43: =($E43/$AB43)*100 -> 4.2117943 | Q43: =($F43/$AD43)*100 -> 0 | R43: =($F43/$AB43)*100 -> 0 | S43: =U43+W43 -> 1.1866818 | T43: =V43+X43 -> 1.0257309 | U43: =($H43/$AD43)*100 -> -0.12324701 | V43: =($H43/AB43)*100 -> -0.10653088 | W43: =($I43/$AD43)*100 -> 1.3099289 | X43: =($I43/$AB43)*100 -> 1.1322618 | Y43: =($J43/$AD43)*100 -> 0 | Z43: =($J43/$AB43)*100 -> 0 | AA43: 4.1617847e+12 | AB43: 4161.7847 | AC43: 3.5973173e+12 | AD43: 3597.3173
A44: ITA | B44: Q2.2020 | C44: =D44+E44 -> 38.105764 | D44: =data!D45-data!D6 -> 3.4734085 | E44: =data!E45-data!E6 -> 34.632355 | F44: =data!F45-data!F6 -> 7.6498245 | G44: =H44+I44 -> -8.1926568 | H44: =data!H45-data!H6 -> 3.6063458 | I44: =data!I45-data!I6 -> -11.799003 | J44: =data!J45-data!J6 -> 0 | K44: =M44+O44 -> 1.9865815 | L44: =N44+P44 -> 1.6300817 | M44: =($D44/$AD44)*100 -> 0.18108045 | N44: =($D44/$AB44)*100 -> 0.14858486 | O44: =($E44/$AD44)*100 -> 1.805501 | P44: =($E44/$AB44)*100 -> 1.4814968 | Q44: =($F44/$AD44)*100 -> 0.39881105 | R44: =($F44/$AB44)*100 -> 0.32724285 | S44: =U44+W44 -> -0.42711072 | T44: =V44+X44 -> -0.35046403 | U44: =($H44/$AD44)*100 -> 0.18801092 | V44: =($H44/AB44)*100 -> 0.15427163 | W44: =($I44/$AD44)*100 -> -0.61512164 | X44: =($I44/$AB44)*100 -> -0.50473566 | Y44: =($J44/$AD44)*100 -> 0 | Z44: =($J44/$AB44)*100 -> 0 | AA44: 2.3376598e+12 | AB44: 2337.6598 | AC44: 1.9181576e+12 | AD44: 1918.1576
A45: JPN | B45: Q2.2020 | C45: =D45+E45 -> 54.106824 | D45: =data!D46-data!D7 -> 26.236917 | E45: =data!E46-data!E7 -> 27.869908 | F45: =data!F46-data!F7 -> 243.68669 | G45: =H45+I45 -> 128.14927 | H45: =data!H46-data!H7 -> 0 | I45: =data!I46-data!I7 -> 128.14927 | J45: =data!J46-data!J7 -> 1021.6096 | K45: =M45+O45 -> 1.1854269 | L45: =N45+P45 -> 1.0161188 | M45: =($D45/$AD45)*100 -> 0.57482483 | N45: =($D45/$AB45)*100 -> 0.49272572 | O45: =($E45/$AD45)*100 -> 0.61060204 | P45: =($E45/$AB45)*100 -> 0.52339307 | Q45: =($F45/$AD45)*100 -> 5.3389337 | R45: =($F45/$AB45)*100 -> 4.5764029 | S45: =U45+W45 -> 2.8076235 | T45: =V45+X45 -> 2.4066259 | U45: =($H45/$AD45)*100 -> 0 | V45: =($H45/AB45)*100 -> 0 | W45: =($I45/$AD45)*100 -> 2.8076235 | X45: =($I45/$AB45)*100 -> 2.4066259 | Y45: =($J45/$AD45)*100 -> 22.382453 | Z45: =($J45/$AB45)*100 -> 19.185689 | AA45: 5.3248522e+12 | AB45: 5324.8522 | AC45: 4.5643326e+12 | AD45: 4564.3326
A46: KOR | B46: Q2.2020 | C46: =D46+E46 -> 23.759349 | D46: =data!D47-data!D8 -> 1.2812909 | E46: =data!E47-data!E8 -> 22.478058 | F46: =data!F47-data!F8 -> 13.126652 | G46: =H46+I46 -> -186.96913 | H46: =data!H47-data!H8 -> -101 | I46: =data!I47-data!I8 -> -85.969126 | J46: =data!J47-data!J8 -> 120.83691 | K46: =M46+O46 -> 1.4503796 | L46: =N46+P46 -> 1.1017349 | M46: =($D46/$AD46)*100 -> 0.078215872 | N46: =($D46/$AB46)*100 -> 0.059414209 | O46: =($E46/$AD46)*100 -> 1.3721637 | P46: =($E46/$AB46)*100 -> 1.0423207 | Q46: =($F46/$AD46)*100 -> 0.80131103 | R46: =($F46/$AB46)*100 -> 0.60869054 | S46: =U46+W46 -> -11.413453 | T46: =V46+X46 -> -8.6698676 | U46: =($H46/$AD46)*100 -> -6.165503 | V46: =($H46/AB46)*100 -> -4.683429 | W46: =($I46/$AD46)*100 -> -5.2479495 | X46: =($I46/$AB46)*100 -> -3.9864386 | Y46: =($J46/$AD46)*100 -> 7.3764387 | Z46: =($J46/$AB46)*100 -> 5.6032779 | AA46: 2.1565396e+12 | AB46: 2156.5396 | AC46: 1.638147e+12 | AD46: 1638.147
A47: ESP | B47: Q2.2020 | C47: =D47+E47 -> 24.886187 | D47: =data!D48-data!D9 -> 0.5205779 | E47: =data!E48-data!E9 -> 24.365609 | F47: =data!F48-data!F9 -> 0 | G47: =H47+I47 -> -60.841605 | H47: =data!H48-data!H9 -> -10.864489 | I47: =data!I48-data!I9 -> -49.977116 | J47: =data!J48-data!J9 -> -0.5032793 | K47: =M47+O47 -> 1.8797371 | L47: =N47+P47 -> 1.3852382 | M47: =($D47/$AD47)*100 -> 0.039320993 | N47: =($D47/$AB47)*100 -> 0.028976893 | O47: =($E47/$AD47)*100 -> 1.8404161 | P47: =($E47/$AB47)*100 -> 1.3562613 | Q47: =($F47/$AD47)*100 -> 0 | R47: =($F47/$AB47)*100 -> 0 | S47: =U47+W47 -> -4.5955703 | T47: =V47+X47 -> -3.3866221 | U47: =($H47/$AD47)*100 -> -0.82063125 | V47: =($H47/AB47)*100 -> -0.60474931 | W47: =($I47/$AD47)*100 -> -3.774939 | X47: =($I47/$AB47)*100 -> -2.7818728 | Y47: =($J47/$AD47)*100 -> -0.038014372 | Z47: =($J47/$AB47)*100 -> -0.028014002 | AA47: 1.7965277e+12 | AB47: 1796.5277 | AC47: 1.3239185e+12 | AD47: 1323.9185
A48: GBR | B48: Q2.2020 | C48: =D48+E48 -> 71.618784 | D48: =data!D49-data!D10 -> 1.8120431 | E48: =data!E49-data!E10 -> 69.806741 | F48: =data!F49-data!F10 -> 0 | G48: =H48+I48 -> 0.49401988 | H48: =data!H49-data!H10 -> -421.75808 | I48: =data!I49-data!I10 -> 422.2521 | J48: =data!J49-data!J10 -> 0 | K48: =M48+O48 -> 2.268292 | L48: =N48+P48 -> 2.4343667 | M48: =($D48/$AD48)*100 -> 0.05739057 | N48: =($D48/$AB48)*100 -> 0.061592463 | O48: =($E48/$AD48)*100 -> 2.2109015 | P48: =($E48/$AB48)*100 -> 2.3727742 | Q48: =($F48/$AD48)*100 -> 0 | R48: =($F48/$AB48)*100 -> 0 | S48: =U48+W48 -> 0.015646473 | T48: =V48+X48 -> 0.016792041 | U48: =($H48/$AD48)*100 -> -13.357815 | V48: =($H48/AB48)*100 -> -14.335818 | W48: =($I48/$AD48)*100 -> 13.373462 | X48: =($I48/$AB48)*100 -> 14.35261 | Y48: =($J48/$AD48)*100 -> 0 | Z48: =($J48/$AB48)*100 -> 0 | AA48: 2.9419883e+12 | AB48: 2941.9883 | AC48: 3.1573882e+12 | AD48: 3157.3882
A49: USA | B49: Q2.2020 | C49: =D49+E49 -> 1048 | D49: =data!D50-data!D11 -> 294.55 | E49: =data!E50-data!E11 -> 753.45 | F49: =data!F50-data!F11 -> 0 | G49: =H49+I49 -> 0 | H49: =data!H50-data!H11 -> 0 | I49: =data!I50-data!I11 -> 0 | J49: =data!J50-data!J11 -> 0 | K49: =M49+O49 -> 5.2586748 | L49: =N49+P49 -> 5.2467647 | M49: =($D49/$AD49)*100 -> 1.4779987 | N49: =($D49/$AB49)*100 -> 1.4746513 | O49: =($E49/$AD49)*100 -> 3.7806761 | P49: =($E49/$AB49)*100 -> 3.7721134 | Q49: =($F49/$AD49)*100 -> 0 | R49: =($F49/$AB49)*100 -> 0 | S49: =U49+W49 -> 0 | T49: =V49+X49 -> 0 | U49: =($H49/$AD49)*100 -> 0 | V49: =($H49/AB49)*100 -> 0 | W49: =($I49/$AD49)*100 -> 0 | X49: =($I49/$AB49)*100 -> 0 | Y49: =($J49/$AD49)*100 -> 0 | Z49: =($J49/$AB49)*100 -> 0 | AA49: 1.9974214e+13 | AB49: 19974.214 | AC49: 19928975197000 | AD49: 19928.975
A50: MEX | B50: Q2.2020 | C50: =D50+E50 -> 4.9963816 | D50: =data!D51-data!D12 -> 0.00042542129 | E50: =data!E51-data!E12 -> 4.9959562 | F50: =data!F51-data!F12 -> 2.1604135 | G50: =H50+I50 -> -1.5306958 | H50: =data!H51-data!H12 -> -1.5306958 | I50: =data!I51-data!I12 -> 0 | J50: =data!J51-data!J12 -> 3.0264413 | K50: =M50+O50 -> 0.39060129 | L50: =N50+P50 -> 0.20978501 | M50: =($D50/$AD50)*100 -> 3.325809e-05 | N50: =($D50/$AB50)*100 -> 1.7862329e-05 | O50: =($E50/$AD50)*100 -> 0.39056803 | P50: =($E50/$AB50)*100 -> 0.20976715 | Q50: =($F50/$AD50)*100 -> 0.16889429 | R50: =($F50/$AB50)*100 -> 0.090710119 | S50: =U50+W50 -> -0.11966495 | T50: =V50+X50 -> -0.064269921 | U50: =($H50/$AD50)*100 -> -0.11966495 | V50: =($H50/AB50)*100 -> -0.064269921 | W50: =($I50/$AD50)*100 -> 0 | X50: =($I50/$AB50)*100 -> 0 | Y50: =($J50/$AD50)*100 -> 0.2365976 | Z50: =($J50/$AB50)*100 -> 0.12707237 | AA50: 2.3816676e+12 | AB50: 2381.6676 | AC50: 1.2791513e+12 | AD50: 1279.1513
A51: TUR | B51: Q2.2020 | C51: =D51+E51 -> 1.6541353 | D51: =data!D52-data!D13 -> 0 | E51: =data!E52-data!E13 -> 1.6541353 | F51: =data!F52-data!F13 -> 9.9097744 | G51: =H51+I51 -> 44.019549 | H51: =data!H52-data!H13 -> 3.0075188 | I51: =data!I52-data!I13 -> 41.01203 | J51: =data!J52-data!J13 -> 15.473684 | K51: =M51+O51 -> 0.16590236 | L51: =N51+P51 -> 0.070877843 | M51: =($D51/$AD51)*100 -> 0 | N51: =($D51/$AB51)*100 -> 0 | O51: =($E51/$AD51)*100 -> 0.16590236 | P51: =($E51/$AB51)*100 -> 0.070877843 | Q51: =($F51/$AD51)*100 -> 0.99390594 | R51: =($F51/$AB51)*100 -> 0.42462271 | S51: =U51+W51 -> 4.4149633 | T51: =V51+X51 -> 1.8861883 | U51: =($H51/$AD51)*100 -> 0.30164065 | V51: =($H51/AB51)*100 -> 0.12886881 | W51: =($I51/$AD51)*100 -> 4.1133227 | X51: =($I51/$AB51)*100 -> 1.7573195 | Y51: =($J51/$AD51)*100 -> 1.5519411 | Z51: =($J51/$AB51)*100 -> 0.66303 | AA51: 2.3337834e+12 | AB51: 2333.7834 | AC51: 9.9705355e+11 | AD51: 997.05355
... A77: POL | B77: Q2.2020 | C77: =D77+E77 -> 26.050978 | D77: =data!D78-data!D39 -> -5.7942537 | E77: =data!E78-data!E39 -> 31.845232 | F77: =data!F78-data!F39 -> 0 | G77: =H77+I77 -> 2.2029678 | H77: =data!H78-data!H39 -> 0 | I77: =data!I78-data!I39 -> 2.2029678 | J77: =data!J78-data!J39 -> 9.8869334 | K77: =M77+O77 -> 4.5583265 | L77: =N77+P77 -> 2.1433674 | M77: =($D77/$AD77)*100 -> -1.0138621 | N77: =($D77/$AB77)*100 -> -0.47672739 | O77: =($E77/$AD77)*100 -> 5.5721886 | P77: =($E77/$AB77)*100 -> 2.6200948 | Q77: =($F77/$AD77)*100 -> 0 | R77: =($F77/$AB77)*100 -> 0 | S77: =U77+W77 -> 0.38546909 | T77: =V77+X77 -> 0.18125114 | U77: =($H77/$AD77)*100 -> 0 | V77: =($H77/AB77)*100 -> 0 | W77: =($I77/$AD77)*100 -> 0.38546909 | X77: =($I77/$AB77)*100 -> 0.18125114 | Y77: =($J77/$AD77)*100 -> 1.7299877 | Z77: =($J77/$AB77)*100 -> 0.81345626 | AA77: 1.2154229e+12 | AB77: 1215.4229 | AC77: 5.7150312e+11 | AD77: 571.50312
A79: AUS | B79: Q3.2020 | C79: =D79+E79 -> 156.53523 | D79: 6.6083476 | E79: 149.92689 | F79: 0 | G79: =H79+I79 -> 24.092934 | H79: 10.325543 | I79: 13.767391 | J79: 0 | K79: =M79+O79 -> 10.472172 | L79: =N79+P79 -> 12.762595 | M79: =($D79/$AD79)*100 -> 0.44209696 | N79: =($D79/$AB79)*100 -> 0.53879029 | O79: =($E79/$AD79)*100 -> 10.030075 | P79: =($E79/$AB79)*100 -> 12.223805 | Q79: =($F79/$AD79)*100 -> 0 | R79: =($F79/$AB79)*100 -> 0 | S79: =U79+W79 -> 1.6118118 | T79: =V79+X79 -> 1.9643396 | U79: =($H79/$AD79)*100 -> 0.6907765 | V79: =($H79/AB79)*100 -> 0.84185983 | W79: =($I79/$AD79)*100 -> 0.92103533 | X79: =($I79/$AB79)*100 -> 1.1224798 | Y79: =($J79/$AD79)*100 -> 0 | Z79: =($J79/$AB79)*100 -> 0 | AA79: 1.2265157e+12 | AB79: 1226.5157 | AC79: 1.4947734e+12 | AD79: 1494.7734
A80: CAN | B80: Q3.2020 | C80: =D80+E80 -> 199.62493 | D80: 14.693582 | E80: 184.93134 | F80: 63.078508 | G80: =H80+I80 -> 68.050579 | H80: 3.8589205 | I80: 64.191658 | J80: 0 | K80: =M80+O80 -> 11.76614 | L80: =N80+P80 -> 11.582611 | M80: =($D80/$AD80)*100 -> 0.86605787 | N80: =($D80/$AB80)*100 -> 0.85254905 | O80: =($E80/$AD80)*100 -> 10.900082 | P80: =($E80/$AB80)*100 -> 10.730062 | Q80: =($F80/$AD80)*100 -> 3.7179252 | R80: =($F80/$AB80)*100 -> 3.6599328 | S80: =U80+W80 -> 4.0109852 | T80: =V80+X80 -> 3.9484216 | U80: =($H80/$AD80)*100 -> 0.22744954 | V80: =($H80/AB80)*100 -> 0.22390177 | W80: =($I80/$AD80)*100 -> 3.7835356 | X80: =($I80/$AB80)*100 -> 3.7245198 | Y80: =($J80/$AD80)*100 -> 0 | Z80: =($J80/$AB80)*100 -> 0 | AA80: 1.7234882e+12 | AB80: 1723.4882 | AC80: 1.6966051e+12 | AD80: 1696.6051
A81: FRA | B81: Q3.2020 | C81: =D81+E81 -> 133.52125 | D81: 16.00426 | E81: 117.51699 | F81: 64.588619 | G81: =H81+I81 -> 401.82123 | H81: 24.006389 | I81: 377.81484 | J81: 0 | K81: =M81+O81 -> 5.1024386 | L81: =N81+P81 -> 4.5929517 | M81: =($D81/$AD81)*100 -> 0.61159367 | N81: =($D81/$AB81)*100 -> 0.55052503 | O81: =($E81/$AD81)*100 -> 4.490845 | P81: =($E81/$AB81)*100 -> 4.0424267 | Q81: =($F81/$AD81)*100 -> 2.4682173 | R81: =($F81/$AB81)*100 -> 2.2217617 | S81: =U81+W81 -> 15.35537 | T81: =V81+X81 -> 13.822111 | U81: =($H81/$AD81)*100 -> 0.91739051 | V81: =($H81/AB81)*100 -> 0.82578755 | W81: =($I81/$AD81)*100 -> 14.437979 | X81: =($I81/$AB81)*100 -> 12.996323 | Y81: =($J81/$AD81)*100 -> 0 | Z81: =($J81/$AB81)*100 -> 0 | AA81: 2.9070902e+12 | AB81: 2907.0902 | AC81: 2.6168125e+12 | AD81: 2616.8125
A82: DEU | B82: Q3.2020 | C82: =D82+E82 -> 315.51255 | D82: 26.292712 | E82: 289.21983 | F82: 0 | G82: =H82+I82 -> 1166.0246 | H82: 228.63228 | I82: 937.39235 | J82: 0 | K82: =M82+O82 -> 8.7707732 | L82: =N82+P82 -> 7.5811837 | M82: =($D82/$AD82)*100 -> 0.73089777 | N82: =($D82/$AB82)*100 -> 0.63176531 | O82: =($E82/$AD82)*100 -> 8.0398755 | P82: =($E82/$AB82)*100 -> 6.9494184 | Q82: =($F82/$AD82)*100 -> 0 | R82: =($F82/$AB82)*100 -> 0 | S82: =U82+W82 -> 32.413727 | T82: =V82+X82 -> 28.017418 | U82: =($H82/$AD82)*100 -> 6.3556328 | V82: =($H82/AB82)*100 -> 5.4936114 | W82: =($I82/$AD82)*100 -> 26.058094 | X82: =($I82/$AB82)*100 -> 22.523807 | Y82: =($J82/$AD82)*100 -> 0 | Z82: =($J82/$AB82)*100 -> 0 | AA82: 4.1617847e+12 | AB82: 4161.7847 | AC82: 3.5973173e+12 | AD82: 3597.3173
A83: ITA | B83: Q3.2020 | C83: =D83+E83 -> 91.452912 | D83: 7.4305491 | E83: 84.022363 | F83: 8.0021298 | G83: =H83+I83 -> 609.59082 | H83: 3.7152745 | I83: 605.87554 | J83: 0 | K83: =M83+O83 -> 4.7677475 | L83: =N83+P83 -> 3.9121566 | M83: =($D83/$AD83)*100 -> 0.38737948 | N83: =($D83/$AB83)*100 -> 0.31786272 | O83: =($E83/$AD83)*100 -> 4.380368 | P83: =($E83/$AB83)*100 -> 3.5942938 | Q83: =($F83/$AD83)*100 -> 0.41717791 | R83: =($F83/$AB83)*100 -> 0.3423137 | S83: =U83+W83 -> 31.780017 | T83: =V83+X83 -> 26.076969 | U83: =($H83/$AD83)*100 -> 0.19368974 | V83: =($H83/AB83)*100 -> 0.15893136 | W83: =($I83/$AD83)*100 -> 31.586327 | X83: =($I83/$AB83)*100 -> 25.918037 | Y83: =($J83/$AD83)*100 -> 0 | Z83: =($J83/$AB83)*100 -> 0 | AA83: 2.3376598e+12 | AB83: 2337.6598 | AC83: 1.9181576e+12 | AD83: 1918.1576
A84: JPN | B84: Q3.2020 | C84: =D84+E84 -> 555.08784 | D84: 47.578958 | E84: 507.50888 | F84: 242.55939 | G84: =H84+I84 -> 146.46856 | H84: 0 | I84: 146.46856 | J84: 1016.8836 | K84: =M84+O84 -> 12.161424 | L84: =N84+P84 -> 10.424474 | M84: =($D84/$AD84)*100 -> 1.0424078 | N84: =($D84/$AB84)*100 -> 0.89352635 | O84: =($E84/$AD84)*100 -> 11.119016 | P84: =($E84/$AB84)*100 -> 9.5309477 | Q84: =($F84/$AD84)*100 -> 5.3142358 | R84: =($F84/$AB84)*100 -> 4.5552324 | S84: =U84+W84 -> 3.2089808 | T84: =V84+X84 -> 2.7506596 | U84: =($H84/$AD84)*100 -> 0 | V84: =($H84/AB84)*100 -> 0 | W84: =($I84/$AD84)*100 -> 3.2089808 | X84: =($I84/$AB84)*100 -> 2.7506596 | Y84: =($J84/$AD84)*100 -> 22.278911 | Z84: =($J84/$AB84)*100 -> 19.096936 | AA84: 5.3248522e+12 | AB84: 5324.8522 | AC84: 4.5643326e+12 | AD84: 4564.3326
A85: KOR | B85: Q3.2020 | C85: =D85+E85 -> 55.370458 | D85: 4.259266 | E85: 51.111192 | F85: 27.559956 | G85: =H85+I85 -> 59.212149 | H85: 0 | I85: 59.212149 | J85: 104.39377 | K85: =M85+O85 -> 3.3800666 | L85: =N85+P85 -> 2.5675605 | M85: =($D85/$AD85)*100 -> 0.26000512 | N85: =($D85/$AB85)*100 -> 0.19750465 | O85: =($E85/$AD85)*100 -> 3.1200615 | P85: =($E85/$AB85)*100 -> 2.3700558 | Q85: =($F85/$AD85)*100 -> 1.6823861 | R85: =($F85/$AB85)*100 -> 1.2779713 | S85: =U85+W85 -> 3.614581 | T85: =V85+X85 -> 2.7457019 | U85: =($H85/$AD85)*100 -> 0 | V85: =($H85/AB85)*100 -> 0 | W85: =($I85/$AD85)*100 -> 3.614581 | X85: =($I85/$AB85)*100 -> 2.7457019 | Y85: =($J85/$AD85)*100 -> 6.3726745 | Z85: =($J85/$AB85)*100 -> 4.8408003 | AA85: 2.1565396e+12 | AB85: 2156.5396 | AC85: 1.638147e+12 | AD85: 1638.147
A86: ESP | B86: Q3.2020 | C86: =D86+E86 -> 43.554449 | D86: 6.0587554 | E86: 37.495694 | F86: 0 | G86: =H86+I86 -> 165.30114 | H86: 0.68589684 | I86: 164.61524 | J86: 11.431614 | K86: =M86+O86 -> 3.2898135 | L86: =N86+P86 -> 2.4243684 | M86: =($D86/$AD86)*100 -> 0.4576381 | N86: =($D86/$AB86)*100 -> 0.33724809 | O86: =($E86/$AD86)*100 -> 2.8321754 | P86: =($E86/$AB86)*100 -> 2.0871203 | Q86: =($F86/$AD86)*100 -> 0 | R86: =($F86/$AB86)*100 -> 0 | S86: =U86+W86 -> 12.485749 | T86: =V86+X86 -> 9.2011461 | U86: =($H86/$AD86)*100 -> 0.051808087 | V86: =($H86/AB86)*100 -> 0.038179029 | W86: =($I86/$AD86)*100 -> 12.433941 | X86: =($I86/$AB86)*100 -> 9.1629671 | Y86: =($J86/$AD86)*100 -> 0.86346811 | Z86: =($J86/$AB86)*100 -> 0.63631716 | AA86: 1.7965277e+12 | AB86: 1796.5277 | AC86: 1.3239185e+12 | AD86: 1323.9185
A87: GBR | B87: Q3.2020 | C87: =D87+E87 -> 241.44143 | D87: 40.752852 | E87: 200.68857 | F87: 5.1261449 | G87: =H87+I87 -> 437.00386 | H87: 1.2815362 | I87: 435.72232 | J87: 0 | K87: =M87+O87 -> 7.6468718 | L87: =N87+P87 -> 8.2067432 | M87: =($D87/$AD87)*100 -> 1.290714 | N87: =($D87/$AB87)*100 -> 1.3852146 | O87: =($E87/$AD87)*100 -> 6.3561578 | P87: =($E87/$AB87)*100 -> 6.8215286 | Q87: =($F87/$AD87)*100 -> 0.16235397 | R87: =($F87/$AB87)*100 -> 0.17424083 | S87: =U87+W87 -> 13.840676 | T87: =V87+X87 -> 14.854031 | U87: =($H87/$AD87)*100 -> 0.040588492 | V87: =($H87/AB87)*100 -> 0.043560208 | W87: =($I87/$AD87)*100 -> 13.800087 | X87: =($I87/$AB87)*100 -> 14.810471 | Y87: =($J87/$AD87)*100 -> 0 | Z87: =($J87/$AB87)*100 -> 0 | AA87: 2.9419883e+12 | AB87: 2941.9883 | AC87: 3.1573882e+12 | AD87: 3157.3882
A88: USA | B88: Q3.2020 | C88: =D88+E88 -> 2449 | D88: 304 | E88: 2145 | F88: 18 | G88: =H88+I88 -> 510 | H88: 56 | I88: 454 | J88: 0 | K88: =M88+O88 -> 12.28864 | L88: =N88+P88 -> 12.260808 | M88: =($D88/$AD88)*100 -> 1.5254171 | N88: =($D88/$AB88)*100 -> 1.5219623 | O88: =($E88/$AD88)*100 -> 10.763223 | P88: =($E88/$AB88)*100 -> 10.738846 | Q88: =($F88/$AD88)*100 -> 0.090320751 | R88: =($F88/$AB88)*100 -> 0.090116187 | S88: =U88+W88 -> 2.5590879 | T88: =V88+X88 -> 2.553292 | U88: =($H88/$AD88)*100 -> 0.28099789 | V88: =($H88/AB88)*100 -> 0.28036147 | W88: =($I88/$AD88)*100 -> 2.27809 | X88: =($I88/$AB88)*100 -> 2.2729305 | Y88: =($J88/$AD88)*100 -> 0 | Z88: =($J88/$AB88)*100 -> 0 | AA88: 1.9974214e+13 | AB88: 19974.214 | AC88: 19928975197000 | AD88: 19928.975
A89: MEX | B89: Q3.2020 | C89: =D89+E89 -> 6.7455002 | D89: 1.8317719 | E89: 4.9137282 | F89: 2.1248554 | G89: =H89+I89 -> 1.7401833 | H89: 1.7401833 | I89: 0 | J89: 2.9766294 | K89: =M89+O89 -> 0.52734184 | L89: =N89+P89 -> 0.28322593 | M89: =($D89/$AD89)*100 -> 0.14320213 | N89: =($D89/$AB89)*100 -> 0.076911319 | O89: =($E89/$AD89)*100 -> 0.38413971 | P89: =($E89/$AB89)*100 -> 0.20631461 | Q89: =($F89/$AD89)*100 -> 0.16611447 | R89: =($F89/$AB89)*100 -> 0.08921713 | S89: =U89+W89 -> 0.13604202 | T89: =V89+X89 -> 0.073065753 | U89: =($H89/$AD89)*100 -> 0.13604202 | V89: =($H89/AB89)*100 -> 0.073065753 | W89: =($I89/$AD89)*100 -> 0 | X89: =($I89/$AB89)*100 -> 0 | Y89: =($J89/$AD89)*100 -> 0.23270346 | Z89: =($J89/$AB89)*100 -> 0.12498089 | AA89: 2.3816676e+12 | AB89: 2381.6676 | AC89: 1.2791513e+12 | AD89: 1279.1513
A90: TUR | B90: Q3.2020 | C90: =D90+E90 -> 4.9034694 | D90: 1.9527091 | E90: 2.9507604 | F90: 9.6189002 | G90: =H90+I90 -> 69.096972 | H90: 2.8929023 | I90: 66.20407 | J90: 15.317918 | K90: =M90+O90 -> 0.49179599 | L90: =N90+P90 -> 0.21010816 | M90: =($D90/$AD90)*100 -> 0.19584796 | N90: =($D90/$AB90)*100 -> 0.083671392 | O90: =($E90/$AD90)*100 -> 0.29594803 | P90: =($E90/$AB90)*100 -> 0.12643677 | Q90: =($F90/$AD90)*100 -> 0.96473256 | R90: =($F90/$AB90)*100 -> 0.41215908 | S90: =U90+W90 -> 6.9301164 | T90: =V90+X90 -> 2.9607277 | U90: =($H90/$AD90)*100 -> 0.29014513 | V90: =($H90/AB90)*100 -> 0.12395762 | W90: =($I90/$AD90)*100 -> 6.6399713 | X90: =($I90/$AB90)*100 -> 2.8367701 | Y90: =($J90/$AD90)*100 -> 1.5363185 | Z90: =($J90/$AB90)*100 -> 0.65635559 | AA90: 2.3337834e+12 | AB90: 2333.7834 | AC90: 9.9705355e+11 | AD90: 997.05355
... A272: POL | B272: Q2.2021 | C272: =D272+E272 -> 38.516359 | D272: 3.7695771 | E272: 34.746782 | F272: 0 | G272: =H272+I272 -> 28.720588 | H272: 9.7444851 | I272: 18.976103 | J272: 0 | K272: =M272+O272 -> 6.7394837 | L272: =N272+P272 -> 3.1689678 | M272: =($D272/$AD272)*100 -> 0.65958995 | N272: =($D272/$AB272)*100 -> 0.31014532 | O272: =($E272/$AD272)*100 -> 6.0798937 | P272: =($E272/$AB272)*100 -> 2.8588225 | Q272: =($F272/$AD272)*100 -> 0 | R272: =($F272/$AB272)*100 -> 0 | S272: =U272+W272 -> 5.0254472 | T272: =V272+X272 -> 2.3630119 | U272: =($H272/$AD272)*100 -> 1.7050625 | V272: =($H272/AB272)*100 -> 0.8017362 | W272: =($I272/$AD272)*100 -> 3.3203848 | X272: =($I272/$AB272)*100 -> 1.5612757 | Y272: =($J272/$AD272)*100 -> 0 | Z272: =($J272/$AB272)*100 -> 0 | AA272: 1.2154229e+12 | AB272: 1215.4229 | AC272: 5.7150312e+11 | AD272: 571.50312

Sheet Security
A1: Table 1. Summary of Country Fiscal Measures in Response to the COVID-19 Pandemic since January 2020
A2: (USD billion and percent of 2020 GDP)
A3: USD Billion
B4: Above the line measures | F4: Liquidity support | J4: Above the line measures | N4: Liquidity support
B5: Additional spending or foregone revenues | E5: Accelerated spending / deferred revenue | G5: Below the line measures: equity injections, loans, asset purchase or debt assumptions. | H5: Contingent liabilities | J5: Additional spending or foregone revenues | M5: Accelerated spending / deferred revenue | O5: Below the line measures: equity injections, loans, asset purchase or debt assumptions. | P5: Contingent liabilities
B6: Subtotal | C6: Health sector | D6: Non-health sector | F6: Subtotal | H6: Guarantees | I6: Quasi-fiscal operations | J6: Subtotal | K6: Health sector | L6: Non-health sector | N6: Subtotal | P6: Guarantees | Q6: Quasi-fiscal operations
A7: Australia | B7: =C7+D7 -> 31.278018 | C7: ='2021'!D8-'2020'!D8 -> 2.347535 | D7: ='2021'!E8-'2020'!E8 -> 28.930483 | E7: ='2021'!F8-'2020'!F8 -> 0 | F7: =G7+H7 -> 0.00020812525 | G7: ='2021'!H8-'2020'!H8 -> 8.9196534e-05 | H7: ='2021'!I8-'2020'!I8 -> 0.00011892871 | I7: ='2021'!J8-'2020'!J8 -> 0 | J7: =K7+L7 -> 2.1928209 | K7: ='2021'!L8-'2020'!L8 -> 0.16702133 | L7: ='2021'!M8-'2020'!M8 -> 2.0257995 | M7: ='2021'!N8-'2020'!N8 -> 0 | N7: =O7+P7+Q7 -> -0.01194219 | O7: ='2021'!P8-'2020'!Q8 -> -0.0051180816 | P7: ='2021'!Q8-'2020'!R8 -> -0.0068241088 | Q7: ='2021'!R8-'2020'!S8 -> 0
A8: Canada | B8: =C8+D8 -> 21.685295 | C8: ='2021'!D9-'2020'!D9 -> 6.4210348 | D8: ='2021'!E9-'2020'!E9 -> 15.26426 | E8: ='2021'!F9-'2020'!F9 -> 4.7831846 | F8: =G8+H8 -> -0.97855874 | G8: ='2021'!H9-'2020'!H9 -> 0.0082097879 | H8: ='2021'!I9-'2020'!I9 -> -0.98676853 | I8: ='2021'!J9-'2020'!J9 -> 0 | J8: =K8+L8 -> 1.2774469 | K8: ='2021'!L9-'2020'!L9 -> 0.38377461 | L8: ='2021'!M9-'2020'!M9 -> 0.89367225 | M8: ='2021'!N9-'2020'!N9 -> 0.0017457794 | N8: =O8+P8+Q8 -> -0.070937852 | O8: ='2021'!P9-'2020'!Q9 -> -0.00017065564 | P8: ='2021'!Q9-'2020'!R9 -> -0.070767196 | Q8: ='2021'!R9-'2020'!S9 -> 0
A9: France | B9: =C9+D9 -> 54.826804 | C9: ='2021'!D10-'2020'!D10 -> 18.372481 | D9: ='2021'!E10-'2020'!E10 -> 36.454322 | E9: ='2021'!F10-'2020'!F10 -> 16.600029 | F9: =G9+H9 -> -5.439085 | G9: ='2021'!H10-'2020'!H10 -> -5.8973249 | H9: ='2021'!I10-'2020'!I10 -> 0.45823993 | I9: ='2021'!J10-'2020'!J10 -> 0 | J9: =K9+L9 -> 1.9255432 | K9: ='2021'!L10-'2020'!L10 -> 0.68332762 | L9: ='2021'!M10-'2020'!M10 -> 1.2422156 | M9: ='2021'!N10-'2020'!N10 -> 0.58082224 | N9: =O9+P9+Q9 -> -0.54142283 | O9: ='2021'!P10-'2020'!Q10 -> -0.24445019 | P9: ='2021'!Q10-'2020'!R10 -> -0.29697263 | Q9: ='2021'!R10-'2020'!S10 -> 0
A10: Germany | B10: =C10+D10 -> 171.15877 | C10: ='2021'!D11-'2020'!D11 -> 24.087657 | D10: ='2021'!E11-'2020'!E11 -> 147.07111 | E10: ='2021'!F11-'2020'!F11 -> 0 | F10: =G10+H10 -> 3.5948836 | G10: ='2021'!H11-'2020'!H11 -> 0.30184458 | H10: ='2021'!I11-'2020'!I11 -> 3.293039 | I10: ='2021'!J11-'2020'!J11 -> 0 | J10: =K10+L10 -> 4.4160479 | K10: ='2021'!L11-'2020'!L11 -> 0.60881684 | L10: ='2021'!M11-'2020'!M11 -> 3.8072311 | M10: ='2021'!N11-'2020'!N11 -> 0 | N10: =O10+P10+Q10 -> -0.062561489 | O10: ='2021'!P11-'2020'!Q11 -> -0.0090190619 | P10: ='2021'!Q11-'2020'!R11 -> -0.053542427 | Q10: ='2021'!R11-'2020'!S11 -> 0
A11: Italy | B11: =C11+D11 -> 77.945232 | C11: ='2021'!D12-'2020'!D12 -> 12.012135 | D11: ='2021'!E12-'2020'!E12 -> 65.933098 | E11: ='2021'!F12-'2020'!F12 -> 0.02112912 | F11: =G11+H11 -> 1.75749 | G11: ='2021'!H12-'2020'!H12 -> 0.0098099487 | H11: ='2021'!I12-'2020'!I12 -> 1.7476801 | I11: ='2021'!J12-'2020'!J12 -> 0 | J11: =K11+L11 -> 4.0737001 | K11: ='2021'!L12-'2020'!L12 -> 0.63205663 | L11: ='2021'!M12-'2020'!M12 -> 3.4416435 | M11: ='2021'!N12-'2020'!N12 -> -0.0027207505 | N11: =O11+P11+Q11 -> -0.22630814 | O11: ='2021'!P12-'2020'!Q12 -> -0.0012632056 | P11: ='2021'!Q12-'2020'!R12 -> -0.22504493 | Q11: ='2021'!R12-'2020'!S12 -> 0
A12: Japan | B12: =C12+D12 -> 61.500838 | C12: ='2021'!D13-'2020'!D13 -> 15.056602 | D12: ='2021'!E13-'2020'!E13 -> 46.444236 | E12: ='2021'!F13-'2020'!F13 -> -216.14927 | F12: =G12+H12 -> 0.11736056 | G12: ='2021'!H13-'2020'!H13 -> 0 | H12: ='2021'!I13-'2020'!I13 -> 0.11736056 | I12: ='2021'!J13-'2020'!J13 -> 1.0233542 | J12: =K12+L12 -> 1.1454143 | K12: ='2021'!L13-'2020'!L13 -> 0.28998762 | L12: ='2021'!M13-'2020'!M13 -> 0.85542666 | M12: ='2021'!N13-'2020'!N13 -> -4.3072322 | N12: =O12+P12+Q12 -> -0.11174844 | O12: ='2021'!P13-'2020'!Q13 -> 0 | P12: ='2021'!Q13-'2020'!R13 -> -0.011497054 | Q12: ='2021'!R13-'2020'!S13 -> -0.10025138
A13: Korea | B13: =C13+D13 -> 48.749754 | C13: ='2021'!D14-'2020'!D14 -> 7.6352312 | D13: ='2021'!E14-'2020'!E14 -> 41.114522 | E13: ='2021'!F14-'2020'!F14 -> 0.052710707 | F13: =G13+H13 -> 0.11324815 | G13: ='2021'!H14-'2020'!H14 -> 0 | H13: ='2021'!I14-'2020'!I14 -> 0.11324815 | I13: ='2021'!J14-'2020'!J14 -> 0.19966177 | J13: =K13+L13 -> 2.956667 | K13: ='2021'!L14-'2020'!L14 -> 0.4645934 | L13: ='2021'!M14-'2020'!M14 -> 2.4920736 | M13: ='2021'!N14-'2020'!N14 -> -0.0062597254 | N13: =O13+P13+Q13 -> -0.037160006 | O13: ='2021'!P14-'2020'!Q14 -> 0 | P13: ='2021'!Q14-'2020'!R14 -> -0.013448925 | Q13: ='2021'!R14-'2020'!S14 -> -0.023711081
A14: Spain | B14: =C14+D14 -> 54.977744 | C14: ='2021'!D15-'2020'!D15 -> 16.915665 | D14: ='2021'!E15-'2020'!E15 -> 38.062078 | E14: ='2021'!F15-'2020'!F15 -> -0.56330456 | F14: =G14+H14 -> 0.45650672 | G14: ='2021'!H15-'2020'!H15 -> 0.0019287868 | H14: ='2021'!I15-'2020'!I15 -> 0.45457793 | I14: ='2021'!J15-'2020'!J15 -> 0.030184458 | J14: =K14+L14 -> 4.2618059 | K14: ='2021'!L15-'2020'!L15 -> 1.3180285 | L14: ='2021'!M15-'2020'!M15 -> 2.9437775 | M14: ='2021'!N15-'2020'!N15 -> -0.044364785 | N14: =O14+P14+Q14 -> -0.073182686 | O14: ='2021'!P15-'2020'!Q15 -> -0.00029002745 | P14: ='2021'!Q15-'2020'!R15 -> -0.068353887 | Q14: ='2021'!R15-'2020'!S15 -> -0.0045387707
A15: United Kingdom | B15: =C15+D15 -> 81.621811 | C15: ='2021'!D16-'2020'!D16 -> -13.851556 | D15: ='2021'!E16-'2020'!E16 -> 95.473367 | E15: ='2021'!F16-'2020'!F16 -> 7.0724977 | F15: =G15+H15 -> 16.222002 | G15: ='2021'!H16-'2020'!H16 -> 0.040799588 | H15: ='2021'!I16-'2020'!I16 -> 16.181202 | I15: ='2021'!J16-'2020'!J16 -> 0 | J15: =K15+L15 -> 3.0124735 | K15: ='2021'!L16-'2020'!L16 -> -0.511109 | L15: ='2021'!M16-'2020'!M16 -> 3.5235825 | M15: ='2021'!N16-'2020'!N16 -> 0.26101365 | N15: =O15+P15+Q15 -> 0.59890785 | O15: ='2021'!P16-'2020'!Q16 -> 0.0015063993 | P15: ='2021'!Q16-'2020'!R16 -> 0.59740145 | Q15: ='2021'!R16-'2020'!S16 -> 0
A16: United States | B16: =C16+D16 -> 1825 | C16: ='2021'!D17-'2020'!D17 -> 203.5 | D16: ='2021'!E17-'2020'!E17 -> 1621.5 | E16: ='2021'!F17-'2020'!F17 -> -0.02 | F16: =G16+H16 -> 0 | G16: ='2021'!H17-'2020'!H17 -> 0 | H16: ='2021'!I17-'2020'!I17 -> 0 | I16: ='2021'!J17-'2020'!J17 -> 0 | J16: =K16+L16 -> 8.7825785 | K16: ='2021'!L17-'2020'!L17 -> 0.98059163 | L16: ='2021'!M17-'2020'!M17 -> 7.8019869 | M16: ='2021'!N17-'2020'!N17 -> 0.00015043476 | N16: =O16+P16+Q16 -> 0.0069744531 | O16: ='2021'!P17-'2020'!Q17 -> 0.0007658223 | P16: ='2021'!Q17-'2020'!R17 -> 0.0062086308 | Q16: ='2021'!R17-'2020'!S17 -> 0
A17: Mexico | B17: =C17+D17 -> -0.20002812 | C17: ='2021'!D18-'2020'!D18 -> 2.4564657 | D17: ='2021'!E18-'2020'!E18 -> -2.6564938 | E17: ='2021'!F18-'2020'!F18 -> -0.036082982 | F17: =G17+H17 -> -1.8221374 | G17: ='2021'!H18-'2020'!H18 -> -0.95092364 | H17: ='2021'!I18-'2020'!I18 -> -0.87121376 | I17: ='2021'!J18-'2020'!J18 -> 1.6475248 | J17: =K17+L17 -> -0.026841587 | K17: ='2021'!L18-'2020'!L18 -> 0.22607183 | L17: ='2021'!M18-'2020'!M18 -> -0.25291342 | M17: ='2021'!N18-'2020'!N18 -> -0.0082679245 | N17: =O17+P17+Q17 -> -0.031704201 | O17: ='2021'!P18-'2020'!Q18 -> -0.090643906 | P17: ='2021'!Q18-'2020'!R18 -> -0.082432641 | Q17: ='2021'!R18-'2020'!S18 -> 0.14137235
A18: Turkey | B18: =C18+D18 -> 17.623913 | C18: ='2021'!D19-'2020'!D19 -> 0.75119989 | D18: ='2021'!E19-'2020'!E19 -> 16.872713 | E18: ='2021'!F19-'2020'!F19 -> 0.14605226 | F18: =G18+H18 -> 2.4997121 | G18: ='2021'!H19-'2020'!H19 -> 0.013959679 | H18: ='2021'!I19-'2020'!I19 -> 2.4857524 | I18: ='2021'!J19-'2020'!J19 -> 2.8780291 | J18: =K18+L18 -> 2.4343091 | K18: ='2021'!L19-'2020'!L19 -> 0.1007071 | L18: ='2021'!M19-'2020'!M19 -> 2.333602 | M18: ='2021'!N19-'2020'!N19 -> 0.0024817863 | N18: =O18+P18+Q18 -> 0.63155123 | O18: ='2021'!P19-'2020'!Q19 -> -0.0034410267 | P18: ='2021'!Q19-'2020'!R19 -> 0.26688667 | Q18: ='2021'!R19-'2020'!S19 -> 0.36810559
... A44: Poland | B44: =C44+D44 -> -6.193372 | C44: ='2021'!D45-'2020'!D45 -> 1.6041485 | D44: ='2021'!E45-'2020'!E45 -> -7.7975205 | E44: ='2021'!F45-'2020'!F45 -> 0 | F44: =G44+H44 -> -2.8691942 | G44: ='2021'!H45-'2020'!H45 -> -2.9933302 | H44: ='2021'!I45-'2020'!I45 -> 0.12413598 | I44: ='2021'!J45-'2020'!J45 -> 0 | J44: =K44+L44 -> -1.2136025 | K44: ='2021'!L45-'2020'!L45 -> 0.26074849 | L44: ='2021'!M45-'2020'!M45 -> -1.474351 | M44: ='2021'!N45-'2020'!N45 -> 0 | N44: =O44+P44+Q44 -> -0.6046282 | O44: ='2021'!P45-'2020'!Q45 -> -0.55196541 | P44: ='2021'!Q45-'2020'!R45 -> -0.052662786 | Q44: ='2021'!R45-'2020'!S45 -> 0

Sheet Database
C2: Fiscal Monitor: Database of Country Fiscal Measures in Response to the COVID-19 Pandemic
C3: This database summarizes key fiscal measures governments have announced or taken in selected economies in response to the COVID-19 pandemic as of December 31, 2020 for selected economies. The database categorizes different types of fiscal support (for example, above-the-line and below-the line measures, and contingent liabilities) that have different implications for public finances in the near term and beyond. Please refer to Box 1.1 of the April 2020 Fiscal Monitor for details. The database is not meant for classifying the measures for fiscal reporting, nor for comparison across economies as responses vary depending on country-specific circumstances, including the impact of the pandemic and other shocks. It focuses on government discretionary measures that supplement existing automatic stabilizers. These existing stabilizers differ across countries in their breadth and scope. Estimates included here are preliminary as governments are taking additional measures or finalizing the details of individual measures. The information does not represent views of the IMF on the measures listed. Please see IMF Policy Tracker (https://www.imf.org/COVID19policytracker) for information on a broader range of economies and their monetary and financial policies.
H4: A. Above-the line measures | Q4: B. Below the line measures | T4: C. Contingent liabilities | Y4: Other measures
A5: G20 + Spain | B5: Country Group | C5: Country /1 | D5: Government Level | F5: Unit | G5: Total on-budget (A-D) | H5: Total size | I5: Additional spending and forgone revenue in the health sector | J5: Total size | K5: Additional spending and forgone revenue in areas other than health | L5: Total size | M5: D. Accelerated spending and deferred revenue in areas other than health | O5: Unit | P5: Total off-budget (B+C) | Q5: Total size | R5: Equity injections, asset purchases, loans, debt assumptions, including through extra-budgetary funds | T5: Unit | U5: Total size | V5: Guarantees (on loans, deposits etc.) | W5: Total size | X5: Quasi-fiscal operations (noncommercial activity of public corporations on behalf of government) | Y5: Automatic stabilizers, contingency lines
A6: 1 | B6: AE | C6: Australia | D6: General Government | F6: LC bn | G6: 316.4 | H6: 16.6 | I6: Additional spending (AUD 16.6 bn): •Australia is co-funding the WHO’s Pacific regional coronavirus response plan (together with New Zealand). •The health spending package provides support across primary care, aged care, hospitals and research, to diagnose and treat people with the Coronavirus. •In relation to aged care, temporary measures will be introduced to support the aged care sector, which helps ensure the continuity of residential and home care. •The Commonwealth government will pay for half of all additional costs incurred by states and territories in diagnosing and treating patients with, or suspected of having, COVID-19, and efforts to minimize the spread of the virus. • The 2020-21 Mid-Year Economic and FIscal Outlook (MYEFO), released on December 17, includes cost of vaccine procurement and rollout. | J6: 299.8 | K6: Additional spending (AUD 226 bn): At the Commonwealth government level • Measures include tax-free cash flow assistance, wage subsidies, payments to lower-income Australians (pensioners, other social security and veteran income support recipients, and eligible concession cardholders), and the Home Builder program. • FY2021 budget, released on October 6, includes additional spending measures under the JobMaker program, comprising job hiring credit, infrastructure projects, and others for job creation. • The 2020-21 MYEFO extends coronavirus supplement and other income support measures through end-March 2021. At state and local government levels • Measures include discount utility bills, cash payments to vulnerable households, and construction and infrastructure projects. • The Commonwealth government will help finance fast-track infrastructure projects across States and Territories and the arts industry for job creation, as well as the new home care package for the senior citizens. • Pandemic Leave Disaster Payment has been arranged with the State and Territory governments, which provides a lump sum payment to help workers during their 14-day self-isolation period. Forgone revenue (AUD 74 bn): At the Commonwealth government level • Measures include raising the asset write-off threshold, accelerated depreciation deductions, and COVID-19 Relief and Recovery Fund which provides waiver of fees and charges to affected industries (e.g., aviation industry), regions, and communities. • FY2021 budget includes additional revenue measures under the JobMaker program, comprising extension of immediate expensing, loss carry-backs, income tax cut for lower- and middle-income earners, and tax incentives for R&D. At state and local government levels • Measures include payroll tax relief for businesses. | O6: LC bn | P6: 35 | Q6: 15 | R6: • The Government’s Structured Finance Support Fund provides up to AUD15 bn to the Australian Office of Financial Management to support continued access to structured finance markets used by smaller lenders, providing both consumer and business credit. | T6: LC bn | U6: 20 | V6: • The Coronavirus SME Guarantee Scheme provides a loan guarantee arrangement between the government and participating banks to cover the immediate cash flow needs of SMEs. | Y6: Parliament approved an advance authorization of A$40 billion for unforeseen events.
F7: USD bn | G7: 218.44778 | H7: 11.460914 | J7: 206.98687 | O7: USD bn | P7: 24.164577 | Q7: 10.356247 | T7: USD bn | U7: 13.80833
F8: % GDP | G8: 16.177852 | H8: 0.8487748 | J8: 15.329077 | O8: % GDP | P8: 1.7895854 | Q8: 0.76696518 | T8: % GDP | U8: 1.0226202
A9: 1 | B9: AE | C9: Canada | D9: Central Government | F9: LC bn | G9: 322.7 | H9: 52.7 | I9: Additional spending (CAD 52.7 bn): Support to the health system including • Immediate public health response, including COVID-19 Response Fund; • Funding for personal protective equipment and supplies; PPE and related equipment for essential workers; • Reducing import costs to facilitate access to critical medical goods; • Health and social support for Northern Communities (critical priorities, air carriers, food subsidy enhancement); • COVID-19 medical research and vaccine development (over two years); • Consular assistance; • Virtual care and mental health tools for Canadians; • Enhancing public health measures in indigenous communities; • Provincial safe restart agreement. | J9: 270 | K9: Additional spending (CAD 270 bn): Households (CAN 240.7 bn) of which: • Emergency response benefit (CAN 83.0 bn) • Recovery benefits and enhanced employment insurance (CAN 33.2 bn) • Wage subsidies and protecting jobs (CAN 105.2 bn) • Others, including support to students, seniors, and vulnerable groups (CAN 19.3 bn) Businesses (CAN 29.2 bn) of which: • Emergency business account with 25% loan forgiveness (CAN 14.6 bn) • Emergency commercial rent assistance (CAN 4.4 bn) • Others, including sector-specific support and sub-nationals support (CAN 10.3 bn) | L9: 85 | M9: Deferred revenue (CAD 85 bn): Temporary interest-free tax deferrals for businesses and self employed, amounting to CAD 55 bn in deferred income taxes and CAD 30 bn in deferred GST/HST and customs duties for imports. | O9: LC bn | P9: 88.6 | Q9: 5.2 | R9: • Farm Credit Canada will receive support from the government that will allow for an additional CAD 5.2 bn in lending capacity to producers, agribusinesses, and food processors. | T9: LC bn | U9: 83.4 | V9: • Established a Business Credit Availability Program (BCAP) to provide support through the Business Development Bank of Canada (BDC) and Export Development Canada (EDC), which work with private sector lenders to coordinate on credit solutions for individual businesses, including in sectors such as oil and gas, air transportation, exportation, and tourism. This includes combination of loan guarantees and shared financing arrangements. The BCAP consists of: the Canada Emergency Business Account (for small firms), the Mid-Market Guarantee and Financing Program, the Large Employer Emergency Financing Facility, and Support for the Agriculture and Agri-Food Sector.
F10: USD bn | G10: 240.10444 | H10: 39.211354 | J10: 200.89308 | L10: 63.244119 | O10: USD bn | P10: 65.922694 | Q10: 3.869052 | T10: USD bn | U10: 62.053642
F11: % GDP | G11: 14.646142 | H11: 2.3918552 | J11: 12.254287 | L11: 3.8578309 | O11: % GDP | P11: 4.0212214 | Q11: 0.23600848 | T11: % GDP | U11: 3.7852129
A12: n.a. | B12: n.a. | C12: European Union | F12: LC bn | G12: 427.85 | H12: 0.05 | I12: Additional spending (€0.05 bn): The European Commission redirected funding of €47.5 mn towards research on COVID-19 vaccine development, treatment, and diagnostics. | J12: 427.8 | K12: Additional spending (€427.8 bn): • In April 2020, the European Commission announced that the size of the Corona Response Investment Initiative will be raised to €37 bn, which includes an upfront cash injection of €8 bn from the EU cohesion funds, to support public investment for hospitals, labor markets, and stressed regions. The Commission extended the scope of the EU Solidarity Fund by also including a public health crisis within its scope, in view of mobilizing it if needed for the hardest hit EU member states. The Coronavirus Response Investment Initiative Plus (CRII+) introduced greater flexibility to allow that all non-utilized support from the European cohesion funds can be mobilized to the fullest. •On December 11, EU leaders agreed on the Next Generation EU (NGEU) recovery package, which includes €390 bn in grants to EU members. The main instrument is the Recovery and Resilience Facility (RRF), which will fund member countries’ investments and reforms The NGEU’s grant element comprises: €312.5 bn is from the RRF and will be committed in 2021–2023 (70 percent for 2021 and 2022 and 30 percent for 2023); €47.5 bn to top up cohesion funds (ReactEU) that can be used for investments and expenditures related to the crisis (e.g., investing in active labor market policies, short-time work schemes); €10 bn to top up to the Just Transition Fund to help regions/workers dependent on carbon intensive industries transition away from those industries; R&D (€5 bn); support for private sector investment (€5.6 bn), rural development (€7.5 bn), and rescEU (€1.9 bn). | O12: LC bn | P12: 765 | Q12: 700 | R12: On April 9 2020, the euro area finance ministers (Eurogroup) agreed on establishing safety nets for workers, businesses and sovereigns, amounting to a package of which €340 bn were below-the-line measures: •A new and temporary EU unemployment reinsurance fund (SURE) will provide up to €100 bn in loans on favorable terms to governments, in support of national unemployment and short-time work schemes. Loans will be guaranteed by the EU budget and EU member states. •The ESM will provide Pandemic Crisis Support to its members to finance crisis-related health spending of up to 2 percent of a requesting member’s 2019 GDP. Should all 19 countries draw from the credit line, this would amount to around €240 bn. On December 11, EU leaders agreed on the Next Generation EU (NGEU) recovery package, which includes €360 bn in loans from the Recovery and Resilience Facility (RRF), for which EU members can apply for to finance parts of their national recovery and resilience plans. | T12: LC bn | U12: 65 | V12: •The EU Council agreed on a new pan-European guarantee fund of €25 bn, which could support €200 bn of total financing for hard-hit SMEs throughout the European Investment Bank or national development banks. The guarantee fund comes on top of an earlier support package of up to €40 bn for the European Investment Bank in March, and both packages are likely to be funded by voluntary contributions from member states. | Y12: The European Commission also activated the general escape clause in the EU fiscal rules, which suspends the fiscal adjustment requirements for countries not at their medium-term objective and allow countries to run deficits in excess of 3 percent of GDP. Credit holidays to existing debtors that are negatively affected will be provided.
F13: USD bn | G13: 487.006 | H13: 0.056913171 | J13: 486.94909 | O13: USD bn | P13: 870.77151 | Q13: 796.78439 | T13: USD bn | U13: 73.987122
F14: % GDP | G14: 3.804947 | H14: 0.00044465899 | J14: 3.8045023 | O14: % GDP | P14: 6.8032825 | Q14: 6.2252259 | T14: % GDP | U14: 0.57805669
A15: 1 | B15: AE | C15: France | D15: General Government | F15: LC bn | G15: 174 | H15: 17.8 | I15: Additional spending (€17.8 bn): • Support for streamlining and boosting health insurance (paid sick leave) for the sick or their caregivers, higher spending on health supplies; bonuses for health workers. • Additional investment and equipment in the health sector announced in the Plan de Relance for 2021 and beyond. | J15: 156.2 | K15: Additional spending (€126.5 bn): Support for wages of workers under the subsidized short-time work scheme; direct financial support for affected affected small and very small enterprises (and regardless of size for heavily affected firms in December 2020), liberal professions, and independent workers; direct transfers for low-income families; extension of expiring unemployment and other benefits; additional transfers for self-employed; additional spending in social programs (expired); incentives to purchase greener vehicles; subsidies for green investment for the auto and aerospace sectors. The recovery plan includes spending mostly from 2021 onward. Key measures include: subsidies for energy renovation of buildings; investment aimed at ecological transformation of the transport sector and the development of clean energy; extension of the short-time work scheme; financing for training programs; hiring subsidies and other support for youth workers; further increase in social transfers for low-income households. Foregone revenue (€29.7 bn): Exoneration of social security contributions for affected firms in selected sectors; carry back for corporate income taxes; permanent tax cuts (production taxes) announced in the Plan de Relance for 2021 onward. | L15: 55 | M15: Accelerated spending (€17 bn): Accelerated refund of tax credits (e.g. CIT and VAT). Deferred revenue (€38 bn): Postponement of social security contributions and tax payment for companies. | O15: LC bn | P15: 355.5 | Q15: 21 | R15: • The authorities announced potential direct equity support to firms (€21 bn euros), mostly in strategic companies. | T15: LC bn | U15: 334.5 | V15: • State guarantees for bank loans to companies and credit reinsurance schemes (€315 bn); other guarantees (€12.5 bn). • The Plan de Relance includes the creation of a up to €20 bn fund leveraged by public guarantees (€7 bn), to provide quasi-equity support or equity loans to firms. | Y15: Liquidity support through postponement of social security contributions and tax payment for companies (€33.5 bn).
F16: USD bn | G16: 198.05783 | H16: 20.261089 | J16: 177.79675 | L16: 62.604488 | O16: USD bn | P16: 404.65264 | Q16: 23.903532 | T16: USD bn | U16: 380.74911
F17: % GDP | G17: 7.7103009 | H17: 0.78875492 | J17: 6.921546 | L17: 2.4371641 | O17: % GDP | P17: 15.752942 | Q17: 0.93055356 | T17: % GDP | U17: 14.822389
A18: 1 | B18: AE | C18: Germany | D18: General Government | F18: LC bn | G18: 367 | H18: 40 | I18: Additional spending (€40 bn): on hospital capacity, medical equipment, research, and information campaigns. | J18: 327 | K18: Additional spending (€286 bn): including grants to hard hit small businesses and self-employed, increased access to childcare and basic social security benefits, temporary relief to affected tenants, income support for families, and incentivizing green and digital investment. There is also support to firms and households provided through the “Kurzabeit” program, part of which is considered discretionary because the program parameters have been changed. Forgone revenue (€42 bn): a temporary VAT reduction, corporate tax reliefs, personal income reliefs, and social security contribution reduction. | M18: Deferred revenue: including options for deferring tax payments and reducing prepayments until the year-end without penalties. | O18: LC bn | P18: 926.3 | Q18: 100 | R18: • An economic stabilization fund (WSF) of €600 bn is established with three components: (i) €100 bn for government equity investments in significantly affected companies; (ii) €100 bn loan to state development bank KfW for financing affected firms that do not have access to KfW’s existing programs; | T18: LC bn | U18: 826.3 | V18: (iii) €400 bn to provide additional state guarantees to non-financial corporations to alleviate liquidity bottlenecks and support refinancing. • For the new and expansion of the existing KfW-programs, the guarantee framework of the federal government was increased by €357 bn. • Total guarantees provided by state governments to be increased by €69.3 bn. | Y18: The government provides options for deferring tax payments and reducing prepayments; while tax penalties will not be levied until the end of this year.
F19: USD bn | G19: 417.74267 | H19: 45.530537 | J19: 372.21214 | O19: USD bn | P19: 1054.3734 | Q19: 113.82634 | T19: USD bn | U19: 940.54706
F20: % GDP | G20: 11.033705 | H20: 1.2025837 | J20: 9.8311217 | O20: % GDP | P20: 27.848832 | Q20: 3.0064592 | T20: % GDP | U20: 24.842373
A21: 1 | B21: AE | C21: Italy | D21: General Government | F21: LC bn | G21: 112 | H21: 9.5 | I21: Additional spending (€9 bn): including on medical equipment, staff, and vaccine. Forgone revenue (€0.5 bn): zero VAT rate on targeted medical equipment. | J21: 102.5 | K21: Additional spending (€93.5 bn): including broadening the wage supplementation fund to provide income support to laid-off workers and the self-employed, vouchers for the payment of babysitters (€56.5 bn), grants for SME to cover rents and utility bill (€29 bn), education (€4 bn), and other (€4 bn) . Forgone revenue (€9 bn): corporate income tax credits and social security contribution reduction. | L21: 7 | M21: Deferred revenue: mostly due to postponement of VAT, CIT, and social security contributions as well as property taxes. | O21: LC bn | P21: 582.25 | Q21: 3.25 | R21: • Equity injection to Alitalia (€3.3 bn) | T21: LC bn | U21: 579 | V21: The total guarantee is estimated at about 579 bn euros, aimed to unlock more than 750 billion euros of liquidity for businesses and households. | Y21: Other measures to support businesses, including tax deferrals and postponement of utility bill payments in most affected municipalities (€6.4 bn), a moratorium on loan repayments for households and SMEs, including on mortgages and overdrafts (€220 bn), incentives for financial and non-financial companies in the form of Deferred Tax Activities
F22: USD bn | G22: 127.4855 | H22: 10.813502 | J22: 116.672 | L22: 7.9678439 | O22: USD bn | P22: 662.75387 | Q22: 3.6993561 | T22: USD bn | U22: 659.05452
F23: % GDP | G23: 6.8248555 | H23: 0.57889399 | J23: 6.2459615 | L23: 0.42655347 | O23: % GDP | P23: 35.480108 | Q23: 0.19804268 | T23: % GDP | U23: 35.282066
A24: 1 | B24: AE | C24: Japan | D24: General Government | F24: LC bn | G24: 83600 | H24: 9600 | I24: Additional spending (JPY 9.6 tn): • Production, procurement and distribution of critical equipment such as masks and ventilators (JPY 0.8 tn) •Transfers to local governments to be used for their health- and long-term care related measures including cash handouts to medical and long-term care practitioners (JPY 3.7 tn) • Other health-related measures (procurement of vaccines, etc.) (JPY 4.8 tn) | J24: 74000 | K24: Additional spending (JPY 74 tn): Key spending measures in the Emergency Economics Package against COVID-19 include: • Cash handout of JPY 100K per person (JPY 12.9 tn); • Lump-sum transfer to affected firms (JPY 2 mn per SME, JPY 1 mn for the self-employed) (JPY 2.3 tn); • Subsidies for financial institutions' lending (JPY 3.8 tn); • Expansion of work subsidies (JPY 0.9 tn); • Incentives to accelerate recovery, including for consumption in service sectors and infrastructure investments (JPY 10.8 tn); • Transfers to local governments for COVID-19 (JPY 1 tn). Additional measures announced May 27 include: • Transfers to local governments (JPY 2 tn); • Expansion of work subsidies (JPY 1.3 tn); • Subsidies for public/private financial institutions' lending (JPY 11.7 tn); • Replenishment of cash transfers for firms (JPY 1.9 tn); • Subsidies to affected firms for rent payment (JPY 2 tn). The government announced additional measures on December 8, including: • Incentives for firms to invest in green technologies (JPY 2.0 tn) • Subsidies to accelerate business restructuring of SMEs (JPY 1.1 tn) • Extension of the Employment Adjustment Subsidy (JPY 1.5 tn) • Transfers to the local governments (JPY1.5 tn) • Subsidies for financial institutions' lending (JPY 3.2 tn) • Measures to enhance national resilience (primarily public investments) (JPY 4.4 tn) In April 2020 onwards, the government decided to spend a part of the COVID-19 reserve fund on the health and non-health measures (including below measures) totaling JPY 4.7 tn (excluding the spending approved on December 11, which is a part of the December 2020 package. • Replenishment of the cash transfer program for affected firms (JPY 0.9 tn) • Replenishment of the emergency loan program for affected households (JPY 0.5 tn) • Enhancement of healthcare capacity (JPY1.7 tn) • Procurement of vaccines (JPY 0.8 tn) • Top up the Employment Adjustment Subsidy (JPY 0.4 tn) Forgone revenue: Revenue measures included in the past economic packages include expansion of the loss carry-back and carry-forward schemes, tax incentives for firms’ decarbonization and digitalization, and reduction of property tax and the aviation fuel tax. | L24: 26000 | M24: Deferred revenue (JPY 26 tn): Deferral of payment of taxes and social security premiums by affected firms and households for one year. | O24: LC bn | P24: 152600 | T24: LC bn | U24: 15700 | V24: • Guarantees on bonds/borrowing by the Development Bank of Japan and the Japan Finance Corporation (JPY 7.6 tn). • Guarantees on external bonds issued by the Development Bank of Japan and Japan Bank for International Cooperation (JPY 1.1 tn). • Guarantees on bonds/borrowings by other public financial institutions for their equity injection programs. (JPY2.5 tn). • Expanded the guarantee cap on the capital injection scheme into banks (JPY 3 tn). • Expanded the insurance capacity of the Nippon Export and Investment Insurance (JPY1.5 tn). | W24: 136900 | X24: • Concessional loans and guarantees to affected firms through the public and private financial institutions. (JPY 112 tn)• Public financial institutions' provision of subordinated loans (quasi-equity) and equities (JPY 2.7 tn) • Public financial institutions' loans to affected hospitals and clinics (JPY 3.5 tn) • The university fund (JPY 4.0 tn) • Other quasi-fiscal operations using the Development Bank of Japan and other agencies (primarily for infrastructure projects) (JPY 15 tn) | Y24: Japan has made a contribution of SDR14 mn (US$19 mn) to the IMF’s Catastrophe Containment and Relief Trust. The deadline for tax return filing and payment of personal income tax, gift tax, and consumption tax (for the self-employed) was extended from mid-March to mid-April; tax payments for people and businesses negatively impacted by the COVID-19 outbreak are deferred. In addition, the ¥26 tn (about 4.8 percent of GDP) December 2019 stimulus package is being used to offset the adverse impact of COVID-19 on the economy as well as counter the economic slowdown.
F25: USD bn | G25: 782.33295 | H25: 89.837276 | J25: 692.49567 | L25: 243.30929 | O25: USD bn | P25: 1428.0384 | T25: USD bn | U25: 146.92138 | W25: 1281.117
F26: % GDP | G26: 15.580393 | H26: 1.789136 | J26: 13.791257 | L26: 4.8455768 | O26: % GDP | P26: 28.439808 | T26: % GDP | U26: 2.9259829 | W26: 25.513825
A27: 1 | B27: AE | C27: Korea | D27: General Government | F27: LC bn | G27: 66300 | H27: 5100 | I27: Additional spending: • Emergency spending and first supplementary budget (KRW 2.1 tn): Epidemic prevention and treatment, support for medical institutions and quarantined households. • Third supplementary budget (KRW 2.4 tn): Expanding diagnostic and treatment facilities and smart medical centers; promoting treatment and vaccine development; promoting test-trace-treatment to be a global standard and increasing official development aid of K COVID-19 response kits and tools. • Additional health spending (KRW 600 bn). | J27: 61200 | K27: Additional Spending (KRW 57.8 tn): • The government has announced consumption coupons for the poor, emergency family care support, and support for business re-opening (KRW 5.6 tn). • The 1st supplementary budget included support for SMEs, additional consumption coupons, and grants to local governments (KRW 8.8 tn). • The 2nd supplementary budget included cash transfers to bottom 70% of households (KRW 14.3 tn). • The 3rd supplementary budget includes support for companies, employment, and social safety nets; boost to consumption, investment, and local economies; and Korean new deal for digital and green investment (KRW 21.3 tn). •The 4th supplementary budget: KRW 7.8 tn (KRW 3.9 tn for SME support, KRW 1.5 tn for employment relationship, KRW 0.4 tn support for unemployed and low income household, KRW 1.8 tn in daycare support and mobile bills, and KRW 0.2 tn for emergency disease prevention). Forgone revenue (KRW 3.4 tn): • Temporary corporate/income tax cuts for landlords who reduce commercial rents. • Rental fees reduction for tenants of public properties • Rental fees reduction for tenants of commercial properties and reduction in airport facility fees, ports and terminal charges. • VAT reduction for the self-employed (KRW 0.7 tn). • Corporation tax cut for SMEs located in disaster areas (KRW 0.3 tn). • Consumption tax cut for auto purchases (KRW 0.8 tn). • Raising income tax deduction for credit/debit card and cash receipt expenditure (KRW 0.4 tn). • Raising ceiling of deductible entertainment expenses when calculating corporation tax (KRW 0.2 tn). • Social security (healthcare insurance) contribution cut for households (KRW 0.9 tn). | L27: 33000 | M27: Accelerated spending (KRW 3.3 tn): Make early purchases and prepayments for cash-strapped businesses (KRW 2.1 tn) and frontload construction investment (KRW 1.2 tn), temporarily relaxing government procurement rules. Deferred revenue (KRW 29.7 tn): Tax deferral covering a broad range of taxes for small businesses and the self-employed in medical, tourism, performance, hospitality, and other affected sectors (VAT and corporation tax--KRW 4.9 tn); social security contribution payment and electricity charge deferral for households (KRW 10 tn); additional tax deferral for small shop owners and freelancers for 3 months (KRW 12.4 tn); transportation, energy, environment tax deferral for oil refinement companies and liquor tax deferral for brewing companies (KRW 2tn); deferral of customs duties (KRW 0.4 tn). | O27: LC bn | P27: 195900 | T27: LC bn | U27: 70900 | V27: • First financial support program for small merchants (KRW 16.4 tn). • Second financial support program for small merchants (KRW 10.0 tn). • Full & special guarantees for SMEs and small merchants provided by state-backed financial institutions (policy banks) (KRW 16.8 tn). • Preferential guarantees for SMEs and export companies (KRW 7.9 tn). • P-CBO for companies affected by COVID-19 (KRW 11.7 tn). • Guarantees/loans related to trade financing and overseas projects (KRW 6 tn). • Guarantees/loans for venture capital and start-up (KRW 2.1 tn). | W27: 125000 | X27: • Credit recovery program by KAMCO(KRW 2.0tn) • Loan expansion to SMEs provided by state-backed financial institutions(KRW 21.2tn) • Support package to stabilize corporate bond and short-term funding market (except P-CBO)(KRW 11.1tn) • Low-rated corporate bond and CP purchase program(KRW 20.0tn) • Key Industry Stabilization Fund(KRW 40.0tn) • Stock Market Stabilization Fund(KRW 10.7tn) • Bond Market Stabilization Fund(KRW 20.0tn) | Y27: Tax payment deferral covering a broad range of taxes for small businesses and the self-employed in medical, tourism, performance, hospitality, and other affected sectors. Social security contribution payment deferral for households
F28: USD bn | G28: 56.080292 | H28: 4.3138686 | J28: 51.766423 | L28: 27.913268 | O28: USD bn | P28: 165.70331 | T28: USD bn | U28: 59.971232 | W28: 105.73207
F29: % GDP | G29: 3.4422077 | H29: 0.26478521 | J29: 3.1774225 | L29: 1.713316 | O29: % GDP | P29: 10.170867 | T29: % GDP | U29: 3.6810335 | W29: 6.4898335
A30: 1 | B30: AE | C30: Spain | D30: General Government | F30: LC bn | G30: 46.1 | H30: 4.4 | I30: Additional spending (€4.4 bn): • Budget support from the contingency fund to the Ministry of Health (€1.4 bn); advance transfer to the regions for health services (€2.9 bn); additional healthcare related spending including research related to COVID-19 (€160 mn). | J30: 41.7 | K30: Additional spending (€40.6 bn): • Unemployment benefit for workers temporary laid off under the ERTE due to COVID-19, with no requirement for prior minimum contribution or reduction of accumulated entitlement (about €19 bn depending on duration); and exemptions of social contributions for companies that maintain employment under the ERTEs (about €6.8 bn); • An allowance for self-employed workers affected by economic activity suspension (about €5¾ bn depending on the duration), and exemption of social contributions for self-employed that receive this benefit (about €2.9 bn or more depending on the duration) • Increased sick pay for infected or quarantined workers (€1.4 bn); • Introduction of a new means-tested "minimum income scheme"; and new rental assistance programs for certain vulnerable renters and additional state contribution to the State Housing Plan 2018-21; • Benefits for workers under permanent discontinuous contracts with activities suspended due to COVID-19; temporary entitlement to unemployment benefits for workers unemployed in their probationary period; a temporary monthly allowance for temporary workers whose contracts expired during state of emergency and do not qualify for unemployment benefits; a temporary subsidy for household employees affected by COVID-19; and other support for households and firms. Forgone revenue (€1.1 bn): • Temporary waiver of VAT on purchases of certain medical material, as well COVID-19 tests and vaccines; • Flexibility in filing income tax and VAT installment payment for SMEs and self-employed; • Tax incentives for landlords that reduce rents of properties used for activities related to the hotel, restaurant and tourism industries; • 6-month moratorium on social security contributions for the self-employed and companies in selected industries; • Reduction in the contribution for Employed Agricultural Workers who have completed a maximum of 55 real days of contribution in 2019; • Reduction in VAT on digital publications and other revenue measures. | L30: 0.54 | M30: Deferred revenue: Deferral of social security debts for companies and the self-employed; Deferral of tax debts and debts arising from customs declaration; tax payment deferrals for small and medium enterprises and self-employed for six months, with the first four months exempt from interest. | O30: LC bn | P30: 161.239 | Q30: 0.639 | R30: • Loans through the State Financial Fund for Tourism Competitiveness (FOCIT) to promote the transformation of the tourism sector towards a more sustainable business model (€515 mn). • Loans for the industrial sector to promote digital transformation and modernization (€124 mn). | T30: LC bn | U30: 150.6 | V30: • Up to €100 bn government guarantees for firms and self-employed, covering both loans and commercial paper of medium-sized companies that participate in Spain’s Alternative Fixed Income Market (MARF) • A new Instituto de Crédito Oficial (ICO) line of guarantees to promote investment activities particularly in the areas of environmental sustainability and digitization (€40 billion); • Guarantees for financing operations carried out by the European investment Bank (€2.8 billion) and endorsement to the European SURE instrument (€2.3 billion) • Additional guarantees of up to €2 bn for exporters through the Spanish Export Insurance Credit Company • Guarantees to provide financial assistance on housing expenses for vulnerable households (€1.2 billion) • Additional loan guarantees for SMEs and self-employed through the Compañía Española de Reafianzamiento (€1.1 bn) and line of guarantees for listed companies (€1 billion) • Expansion of the ICO credit lines for the tourism sector (€200 million) • Guarantees for loan maturity extensions to farmers using the special 2017 drought credit lines. | W30: 10 | X30: • Additional funding for the Instituto de Crédito Official (ICO) credit lines (€10 bn)
F31: USD bn | G31: 52.473943 | H31: 5.008359 | J31: 47.465584 | L31: 0.61466224 | O31: USD bn | P31: 183.53245 | Q31: 0.72735032 | T31: USD bn | U31: 171.42247 | W31: 11.382634
F32: % GDP | G32: 4.1298486 | H32: 0.3941721 | J32: 3.7356765 | L32: 0.048375667 | O32: % GDP | P32: 14.444526 | Q32: 0.057244539 | T32: % GDP | U32: 13.491436 | W32: 0.89584568
A33: 1 | B33: AE | C33: United Kingdom | D33: Central Government | F33: LC bn | G33: 344 | H33: 113 | I33: Additional spending (£110.8 bn): • Funding for the National Health Service, including to expand the number of hospital beds, medical staff and equipment. Forgone revenue (£2.2 bn): • Waiver of VAT and customs duties on critical medical import. | J33: 231 | K33: Additional spending (£211.3 bn): • Coronavirus Job Retention Scheme to subsidize furloughed employees' wages and firms' social security contributions (initially for 3 months and extended until March 2021); • Income support for the self-employed (initially for 3 months and extended for 6 months); • Paid sick leave for self-isolating individuals and compensation for small firms for up to 2 weeks, and support for low-income people in need to self-isolate. • Direct grants for small firms in the most-affected (retail and hospitality) sectors; • Support for the vulnerable by expanding the Universal Credit and Working Tax Credit schemes until April 2021; • Rent support by increasing the Local Housing Allowance; • International support, with £150 million made available to the IMF’s Catastrophe Containment and Relief Trust and £2.2 billion loan to the IMF Poverty Reduction and Growth Trust to help low-income countries; • Government support for charities; • Cover the cost of 25 hours' work a week at the National Minimum Wage for six months for hired unemployed up to 24 years old. • Provide support to boost work search, skills, and apprenticeships. • Entitle every diner to a 50% discount of up to £10 in August. • Public sector and social housing decarbonization (£1.1bn) and Green Homes Grant (£3bn). • Support for low-income people in need to self-isolate • Help the job search of those claiming unemployment benefits for at least 13 weeks. • Grant for businesses required to close (£5bn). • Additional transfers to devolved administrations (£2bn). Forgone revenue (£19.7 bn): • Property tax (business rate) holiday for firms in affected sectors for 12 months. • Temporary cut on stamp duty land tax for 10 months. • VAT rate reduction for hospitality, accommodation, and attractions for 8 months. | L33: 7 | M33: Accelerated spending (£4 bn): • Bring forward public infrastructure spending to FY2020/21. Deferred revenue (£3 bn): • Deferral of VAT for the second quarter of 2020 until the end of the financial year; • Deferral of income tax (self-assessment) of the self-employed until the end of January 2021. | O33: LC bn | P33: 341 | Q33: 1 | R33: • The government has put in place a £1 bn program to support firms driving innovation and development through grants and loans. • The government has provided a £30 mn convertible loan to the steel company, Celsa. | T33: LC bn | U33: 340 | V33: • The Coronavirus Business Interruption Loan Scheme (CBILS) launched with the British Business Bank supports SMEs with access to loans of up to £5 mn and for up to 6 years. The government provides lenders with a guarantee of 80% on each loan, and cover the first 12 months of interest payments and any lender-levied fees. • The Coronavirus Large Business Interruption Loan Scheme (CLBILS) provides a government guarantee of 80 percent to enable banks to make loans of up to 25 percent of companies' turnover, or up to £200 mn to firms with an annual turnover above £45 mn. • Under the new Covid-19 Corporate Financing Facility (CCFF), the Bank of England will buy short term debt from larger companies. The combined size of the CBILS, CLBILS, and CCCF schemes is £330 bn. • The Bounce Back Loan Scheme will help SMEs to borrow between £2K and £50K for up to 6 years, with the government guaranteeing 100 percent of the loan and SMEs not paying any fees or interest in the first 12 months. • Trade credit Insurance for business-to-business transactions will receive up to £10 billion of government guarantees through the Trade Credit Reinsurance scheme. | Y33: Deferral of income tax for the self employed and VAT payments; property tax (business rate) holiday for firms in most affected sectors, Time to Pay arrangements (tax debt restructuring) for businesses and individuals. To support the international response, the government has made available £150 million to the IMF’s Catastrophe Containment and Relief Trust.
F34: USD bn | G34: 440.54616 | H34: 144.71429 | J34: 295.83187 | L34: 8.964602 | O34: USD bn | P34: 436.70419 | Q34: 1.2806574 | T34: USD bn | U34: 435.42353
F35: % GDP | G35: 16.258004 | H35: 5.3405653 | J35: 10.917439 | L35: 0.33083148 | O35: % GDP | P35: 16.116219 | Q35: 0.04726164 | T35: % GDP | U35: 16.068957
A36: 1 | B36: AE | C36: United States | D36: Central Government | F36: LC bn | G36: 3503.3 | H36: 483.8 | I36: Additional spending ($475 bn) • Coronavirus Preparedness and Response Supplemental Appropriations Act (March 6, 2020) approved with $6.8 bn for treatments, drugs, and public health measures. • Families First Coronavirus Response Act (March 18, 2020) includes health provisions that increase outlays in Medicare, Medicaid, and other programs with federal matching by an estimated cost of $178.9 bn. • Coronavirus Aid, Relief, and Economic Security Act (March 27, 2020) approved $128.8 bn for additional health spending, which includes funding for hospitals ($100 bn), the Center of Disease Control ($4.3 bn), and vaccine development and expanding Medicare payments and provision of tax advantages for certain medical expense. • Paycheck Protection Program and Health Care Enhancement Act (April 23, 2020) includes $75 bn for hospitals and $25 bn for testing, with an estimated budget cost of $99.6 bn. • Consolidated Appropriation Act (Dec.21, 2020) includes $20 bn for vaccine procurement, $9 bn for vaccine distribution, $22 bn for testing/tracing/covid mitigation programs , $9 bn for healthcare providers and other support, with a total estimated cost of $69.5 bn. Forgone revenue ($9 bn) • CARES act includes expansion of qualified medical expenses which is estimated to reduce revenue by $9 bn. | J36: 3019.5 | K36: Additional spending ($2637.0 bn): • Coronavirus Preparedness and Response Supplemental Appropriation (March 6, 2020) of $1.2 bn. • Families First Coronavirus Response Act (March 16, 2020) includes 2 weeks paid sick leave, up to 3 months emergency leave for those infected (at 2/3 pay), food assistance, free virus testing; federal transfers to states for Medicaid (increased by 6.2 percent during emergency period); and $1 bn in expanded unemployment insurance. Estimated cost from this Act is $38.8 bn. • Coronavirus Aid, Relief, and Economic Security Act (March 27, 2020) includes $437 bn unemployment insurance and $350 bn in emergency appropriations, and $349 bn forgivable small business loans and other items. Estimated increase in spending from this Act is $1512 bn. • Paycheck Protection Program and Health Care Enhancement Act (April 23, 2020) includes $62.1 bn for the Small Business Administration's loan programs and other expense, and $321 bn for the Paycheck Protection Program and small business assistance (of the $310 bn for the Paycheck Protection Program only $176 bn was used). • The federal government reallocated (August 8, 2020) $44 billion from the Department of Homeland Security's Disaster Relief Fund to provide extra unemployment benefits of $300 per week following the expiration of enhanced unemployment benefits. Of the $44 bn, $18 bn is estimated to be pre-COVID-19 appropriated funds, therefore counted as additional COVID-19 expenditure. • Consolidated Appropriation Act (Dec.21, 2020) includes $324 bn support to households, $395 bn support for businesses, $92 bn for education and childcare, and $7 bn other support. Forgone revenue ($382.5 bn): • Coronavirus Aid, Relief, and Economic Security Act (March 27, 2020) includes tax rebates: $1+K39,200 for singles/$2,400 for married filing jointly, and $500 per qualifying child; phaseout rate of 5% for Adjusted Gross Income over $75,000 for single/$112,500 for head of household/$150,000 for married filing jointly. The Act also includes higher limits on losses for corporations and individual taxpayers, employee retention credit for affected employers, and other revenue provisions. The total estimated revenue cost is $288 bn. • Families First Coronavirus Response Act (March 16, 2020) has revenue implications on the budget, estimated to cost around $94 bn. | L36: 18 | M36: Deferred revenue: • Coronavirus Aid, Relief, and Economic Security Act (March 27, 2020) includes extension of IRS income tax filing deadline by 90 days and delay of employers' payroll taxes to 2021 and 2022. • The federal government (through Executive Orders by President Trump on August 8, 2020) introduced deferral of employee social security payroll tax ($1.7 bn) and extended the delay payment of federal student loans ($4.3 bn). | O36: LC bn | P36: 510 | Q36: 56 | R36: • Coronavirus Aid, Relief, and Economic Security Act (March 27, 2020) includes $56 bn in loans for distress businesses (e.g., passenger and cargo air carriers, postal service). | T36: LC bn | U36: 454 | V36: • Coronavirus Aid, Relief, and Economic Security Act (March 27, 2020) includes $454 bn to backstop section 13(3) Federal Reserve facilities that purchase corporate obligations in primary or secondary market. | Y36: IRS extended income tax filing deadline by 90 days; Delay of employers' payroll taxes to 2021 and 2022
F37: USD bn | G37: 3503.3 | H37: 483.8 | J37: 3019.5 | L37: 18 | O37: USD bn | P37: 510 | Q37: 56 | T37: USD bn | U37: 454
F38: % GDP | G38: 16.719306 | H38: 2.3089088 | J38: 14.410397 | L38: 0.085904007 | O38: % GDP | P38: 2.4339469 | Q38: 0.26725691 | T38: % GDP | U38: 2.16669
A39: 1 | B39: EM | C39: Argentina | D39: Central Government | F39: LC bn | G39: 1037.5 | H39: 78 | I39: Additional spending (AR $48.9 bn): • Budget increase for Health Ministry to improve virus diagnostics, purchase hospital equipment, and build temporary emergency treatment centers. • Budget transfers to specific hospitals. • Four monthly bonuses of AR $5K for healthcare workers (AR $12 bn). • Health Strategy for Families and Communities. • Financial Assistance for Health Insurance Agents. • Other (non-costed) support for the health sector includes discretionary transfers related to healthcare to provinces. Forgone revenue (AR $29.1 bn): • Exemption from import duties and statistical tax for medical supplies (April-August). • Tax aliquots on credits and debits in bank accounts and other operations of 2.5 and 5 percent for health service operations. • 95 percent reduction in the aliquot of employer social security contributions for a period of 90 days for health workers (April-June). • Special tax compensation scheme for those who make sales of essential goods, including a VAT refund for milk sales. | J39: 959.5 | K39: Additional spending (AR $892.4 bn): • One-off additional allowances for pensioners, beneficiaries of child, pregnancy, and other social allowances, as well as food stamps. • Emergency family allowance for monotributistas, informal workers, and unemployed. • Assistance to community kitchens (comedores) and retiree centers for food distribution. • Transfers to provincial governments. • Wage subsidies and complementary wages for affected SMEs. • Higher spending on public works/infrastructure, particularly in the health sector. • Unemployment insurance increased by AR $4K to AR $10K. • Financing for infrastructure in industrial parks. • Small-scale supports for tourism and entertainment industries, science, education, external and security sectors. • Transfers to state-guaranteed funds (FOGAR/FONDEP) for credit to SMEs and monotributistas. Forgone revenue (AR $67.1 bn): • Most affected sectors granted 95% reduction in employers’ contributions to the pension system. • Reduction in employers' contributions to Social Security. • Special benefits (tax breaks) for police and security at the forefront of COVID response. | L39: 10 | M39: Accelerated spending: • Advance tax reimbursements to exporters of manufactured products. Deferred revenue: • Extension of the grace period of repayment of loans granted by the Social Security to retirees and beneficiaries of non-contributory pensions. • Deferrals in employers’ contributions to Social Security for 60 days. | O39: LC bn | P39: 530.1 | T39: LC bn | U39: 530.1 | V39: • State guaranteed, subsidized bank lending (estimated at 2 percent of GDP): • Banco Nación and ANSES loans, subsidies, and transfers for housing projects; • Subsidized loans for the construction and repair of houses. • Financing for SMEs to help implement remote working facilities; • Suspension of public service cuts for 180 days due to non-payment of up to 3 consecutive invoices.
F40: USD bn | G40: 14.691369 | H40: 1.1045077 | J40: 13.586861 | L40: 0.14160355 | O40: USD bn | P40: 7.5064044 | T40: USD bn | U40: 7.5064044 | Y40: Credit lines amounting to ARS 350 billion will be provided to finance wage payments and production inputs of small and medium sized industries and commerce. The funds will come almost entirely (ARS 320 billion) from local banks. The BCRA will announce in coming days a specific regulation facilitating this.
F41: % GDP | G41: 3.7991928 | H41: 0.28562606 | J41: 3.5135668 | L41: 0.036618726 | O41: % GDP | P41: 1.9411587 | T41: % GDP | U41: 1.9411587
A42: 1 | B42: EM | C42: Brazil | D42: General Government | F42: LC bn | G42: 610.2 | H42: 86.4 | I42: Additional spending (BRL 79.3 bn): Federal Government spending (BRL 69.3 bn) and transfers to Local Governments (BRL 10 bn) to combat the health crisis and cover higher health spending. Forgone revenue (BRL 7.1 bn): a temporary reduction in taxes (IPI, the Industrialized Products Tax, and zero import taxes) for listed imported and domestic goods necessary to combat Covid-19. IPI reduction expires in December 2020 | J42: 523.8 | K42: Additional spending (BRL 504.7 bn): • Targeted assistance for the elderly, poor, and unemployed, including include (i) expanding the cash transfer program 'Bolsa Família' to accommodate 1.2 million new beneficiaries; (ii) “Covid-19” cash transfer ("Emergency Aid) for informal workers and low-income households, of BRL600 per month in April-August and BRL 300 per month in September-December; (iii) a subsidized job retention scheme, allowing temporary suspension or reduction of private sector employees working contracts; and (iv) temporary electricity consumption subsidies for poor families. The Federal Government provided extraordinary transfers to subnational governments to compensate for revenue losses and cover larger social assistance and health costs, and granted a stay on debt service payments. Subnational governments were also allowed to renegotiate debts with public banks and multilateral financial institutions. Forgone revenue (BRL 19.1 bn): • Elimination of the financial transactions tax (during 9 months) | L42: 201.8 | M42: Accelerated spending (BRL 58.7 bn): Advance payment of 13th pension benefit, wage bonuses to low-income workers, and sickness/disability benefits. Deferred revenue (BRL 143.1 bn): • 4-month deferral of social contributions paid by firms and employers, 3-month deferral of small business taxes, and delayed PIT filling. Deferral of taxes paid by the telecommunications sector and of tax debt payment obligations. | O42: LC bn | P42: 457.7 | Q42: 79.9 | R42: • BRL 6.8 billion credit line to SMEs (to finance payroll costs during 7 months); BRL 48.1 billion support to funds which lend to microbusinesses; BRL 20 billion support to a investment guarantee fund (to finance SMEs), 5bn credit support to the tourism sector. | T42: LC bn | W42: 377.8 | X42: Credit lines from public banks to SMEs, micro-firms, and individuals (BNDES: BRL 55.4bn, Caixa: BRL 154bn, Banco do Brasil: BRL100): • BNDES opened a working capital loan line for tourism and service sectors (small and medium-sized firms); renegotiated loan terms benefiting sectors such as oil and gas, airports, ports, energy, transportation, urban mobility, health, industry and commerce and services; and expanded credit lines to micro and small firms; created a BRL 2 bn credit line to expand emergency beds and purchase of medical and hospital equipment, for regions with less infrastructure. • Caixa extended credit lines to small-and medium-sized firms to finance working capital, purchased payroll-backed and vehicle loan portfolios from small and medium-size banks, expanded real estate and agricultural credit, and renegotiated credit to hospitals. • Banco do Brasil announced an increase in its credit lines for businesses (working capital, investments, prepayment of receivables, agribusiness) and to individuals. • Authorization of new withdrawals from mandatory savings accounts for unemployment (FGTS) - BRL 36.2 bn • Temporary cut of small employers contributions to training funds (Sistema S) and deferral of all employers contributions to an extra-budgetary mandatory savings fund (FGTS) - BRL 32.2 bn. | Y42: Payment of employers’ contributions to the FGTS and small business taxes will be postponed by 3 months.
F43: USD bn | G43: 117.69146 | H43: 16.664277 | J43: 101.02718 | L43: 38.921888 | O43: USD bn | P43: 88.278235 | Q43: 15.410599 | T43: USD bn | W43: 72.867637
F44: % GDP | G44: 8.2569415 | H44: 1.1691245 | J44: 7.087817 | L44: 2.7306634 | O44: % GDP | P44: 6.1933827 | Q44: 1.0811695 | T44: % GDP | W44: 5.1122132
A45: 1 | B45: EM | C45: China | D45: General Government | F45: LC bn | G45: 4904 | H45: 147 | I45: Additional spending (RMB 147 bn): Expenditure to improve epidemic prevention and control and the national public health emergency management system. Forgone revenue: Tariffs were exempted for the import of medicines, medical supplies, and other vehicles used to fight against the outbreak. | J45: 4757 | K45: Additional spending (RMB 3.1 tn): • Help local governments finance employment initiatives, meet basic living needs, and protect market entities. • Increase the coverage and benefits of Dibao: extending social assistance programs to cover families affected by the COVID-19 and falling into poverty. • Companies that do not lay off employees or minimize layoffs receive a refund of 2019 insurance premiums. • Two-year extension of NEV (New Emission Vehicle) subsidy on purchases to the end of 2022. • Extend unemployment benefits or "minimum living guarantees" (e.g. social transfers) to migrant workers. • Increasing ceiling on special local government bond issuance, which can be spent on investment projects. Forgone revenue (RMB 1.8 tn): • VAT exemptions for goods and services related to epidemic control and for small taxpayers in Hubei; and VAT rate cut from 3% to 1% in other regions until the year end. • Waived VAT on interest payments to financial institutions who extend loans of RMB 1 million or less to SMEs and sole proprietors. Instituted a 0.5 percentage point VAT reduction on secondhand vehicles sold by dealers from May until end-2023. • Corporate income tax relief for businesses in affected sectors through a longer tax loss carryover to 8 years or one-off 100 percent investment expensing deduction. • Social security contributions by employers in Hubei province and SMEs (50 percent for large firms) in the other provinces are waived until the end of December. • Allow companies suffering from serious difficulties to postpone social insurance payments until end-2020. | L45: 1600 | M45: Accelerated spending: Accelerated issuance of an increase in special local government bonds (RMB 1.6 tn). Deferred revenue: Firms are allowed to defer their social security payments by 6 months, and the due date for contributing to the “housing provident fund” is extended to end-June. In late June, the government announced that it will allow companies suffering from serious production or operation difficulties to postpone social insurance payments until the end of 2020. Collection of income tax for small and micro enterprises and self-employed deferred until 2021. | O45: LC bn | P45: 1330 | Q45: 0 | R45: • Allow China’s state-funded infrastructure projects to use up to 15% of investment for a project to pay wages. Previously only 10 percent was earmarked for worker salaries. • The central government transfer payment rate to provinces was increased from 3% to 4% for pensions. • Tax collection retention ratio for local budgets raised to 5% (March 1 to June 30). | T45: LC bn | U45: 400 | V45: • The national guarantee fund will work with banks providing loan guarantee services, planning to increase re-guarantee business by RMB 400 bn in 2020. Local government-backed guarantee/re-guarantee agencies are required to lower guarantee service costs to below 1 percent for SMEs. | W45: 930 | X45: • Starting May 21, three policy banks will issue coupons that waive loan interest payments to qualified small/micro firms and individually-owned businesses (no estimate). • The State Council announced SOEs will expand recruitment for college graduates for two consecutive years. Also, Central SOEs should provide more positions for job seekers in counties under the poverty line after surveying employment demand (no estimate). • Road tolls were exempted beginning February 17, and some service fees charged by airports and railways were cut. Road tolls were reinstated on May 6. • Electricity prices were cut by 5%, which were extended to end-2020 except those in high-energy-consuming industries. • Railway logistic fee was lowered by 50% until end-June. • The port construction fee has been exempted till end-2020, and some other port-related fees were cut. • Exempt rent payments by SMEs in the service sector on state-owned properties for three months. Landlords who offer rent reduction or exemption will receive tax cuts and loans with preferential interest rates. | Y45: Road tolls were exempted; some service fees charged by airports and railways were cut; and the price of electricity was cut by 5% with an estimated cost reduction of 60 bn RMB Railway logistic fee lowered by 50% until Jun 30 with an estimated cost of RMB 350 million. From Mar 1 to Jun 30, the port construction fee will be exempted and fees such as ‘harbor dues on cargo’ will be cut by 20%.
F46: USD bn | G46: 710.76584 | H46: 21.305583 | J46: 689.46026 | L46: 231.8975 | O46: USD bn | P46: 192.7648 | T46: USD bn | U46: 57.974375 | W46: 134.79042
F47: % GDP | G47: 4.7347943 | H47: 0.14192797 | J47: 4.5928664 | L47: 1.5447942 | O47: % GDP | P47: 1.2841102 | T47: % GDP | U47: 0.38619856 | W47: 0.89791165
A48: 1 | B48: EM | C48: India | D48: Central Government | F48: LC bn | G48: 5998.7 | H48: 360 | I48: Additional spending (Rs 360 bn): • Additional spending on health infrastructure, including for COVID-19 testing facilities, personal protective equipment, isolation beds, ICU beds, ventilators and medical screening. | J48: 5638.7 | K48: Additional spending (Rs 5638.7 bn): • On March 26, the central government announced a package that provides insurance coverage for workers in the healthcare sector, substantial in-kind (food; cooking gas) and cash transfers, as well as wage support to poor households (Rs 1.49 tn). • Between May 13 and 17, additions to this initial package were announced. These focused on extending the government's existing rural employment guarantee scheme (additional Rs 400 bn), extension of food support to migrants (Rs 35 bn) and miscellaneous other measures (about Rs 93 bn). • On June 30, authorities extended the provision of food rations to vulnerable households (Rs 829 bn). • On August 20, authorities extended and expanded unemployment benefits for workers who are covered under the Employees State Insurance Corporation (ESIC) scheme. • On October 12, authorities announced measures targeting consumption and public investment. On the consumption side authorities: i) offered public sector employees a cash payment which can be used to buy (via digital mode) goods that attract GST of 12% or more (i.e. discretionary, nonessential items) (Rs 56.8 bn): ii) a Special Festive Advance Scheme which is an interest-free advance to central government employees (Rs 40 bn). On the public investment side authorities announced i) additional spending by the central government (Rs 250 bn) and a lending scheme for state governments, involving a 50-year interest free loan (Rs 120 bn). • On November 12, authorities announced a new package (Rs 2650.8 bn) which included: (i) a Production Linked Incentive scheme targeting 13 priority sectors (1459.8 billion Rs.) to be disbursed over 5 years (no impact on the current fiscal year); (ii) more spending on fertilizer subsidies (650 billion Rs.); (iii) spending on urban housing projects (180 billion Rs.); (iv) additional capital expenditure and industrial infrastructure and incentives (102 billion Rs.); (v) support for rural employment (100 billion Rs.) and employment support in the formal sector (60 billion Rs.). | L48: 1340 | M48: Accelerated Spending (Rs 660 bn: • On March 26, 2020, the government accelerated the first installment of payments to lower income farmers under PM KISAN (160 billion rupees). As part of the scheme announced on June 20th, 2020, the government expedited the implementation of a set of public works projects spanning 12 different ministries, to boost employment and livelihood opportunities for migrant workers returning to villages (500 billion rupees) Deferred revenue (Rs 680 bn): • Extension of income tax filing deadline (3 months); reduction of penalty for late payments; date for filing fiscal year 18/19 GST tax liability extended (3 months); other miscellaneous relaxation of tax regulatory/administrative requirements. • Reduction in up-front tax deductions for workers (Rs 500bn). | O48: LC bn | P48: 9991 | Q48: 641 | R48: • Equity infusion for micro, small, and medium-sized enterprises (500 billion Rs.) and a viability-gap funding scheme for private sector involvement in social infrastructure (81 billion Rs.), both announced in May; and equity infusion in infrastructure financing funds and platforms (60 billion Rs.) announced in November. | T48: LC bn | U48: 8450 | V48: • Full guarantees for a collateral-free lending program (Rs 3 tn). • Liquidity provision and partial credit-guarantee schemes for non-bank financial companies (Rs 750 bn). • Subordinate debt provision for MSME sector (Rs 200 bn). • Credit provisions to be guaranteed by government to farmers on concessional terms (Rs 3 tn) and for street vendors and other miscellaneous measures (Rs 160 bn). • Government to provide a guarantee for credit under a new infrastructure fund for agriculture (Rs 1 tn) and for micro-food enterprises (Rs 100 bn). • Numerous miscellaneous guarantee items (Rs 321 bn). •On November 12, the collateral-free lending program was extended to March 31, 2021 and expanded to provide additional support to 26 stressed sectors. | W48: 900 | X48: • Loans to companies in the electricity distribution sector (Rs 900 bn), carried out by Power Finance Crops and Rural Electrification Corps (both SOEs) under state government guarantees. Government also relaxed the borrowing limits of DISCOM companies on a one-time basis, allowing more electricity distribution companies to take advantage of the borrowing scheme.
F49: USD bn | G49: 80.647538 | H49: 4.8399009 | J49: 75.807637 | L49: 18.015187 | O49: USD bn | P49: 134.3207 | Q49: 8.6177125 | T49: USD bn | U49: 113.60323 | W49: 12.099752
F50: % GDP | G50: 3.0568213 | H50: 0.18344902 | J50: 2.8733722 | L50: 0.68283803 | O50: % GDP | P50: 5.09122 | Q50: 0.32664118 | T50: % GDP | U50: 4.3059562 | W50: 0.45862256
A51: 1 | B51: EM | C51: Indonesia | D51: Central Government | F51: LC bn | G51: 424500 | H51: 76000 | I51: Additional spending (IDR 76 tn): • IDR 1 tn initially allocated to cover various outlays, including personal protective equipment, enhanced surveillance at entry gates to Indonesia, hospital treatment, and hospital infrastructure. • On March 31, 2020, the government announced a third larger fiscal package, including IDR 75 tn to boost testing and treatment capability, including the acquisition of personal protective equipment, test kits, ventilators, and the upgrade of 132 referral hospitals to handle COVID-19 patients. | J51: 348500 | K51: Additional spending (IDR 252.2 tn): • The first fiscal package of IDR 10.3 tn includes support to the tourism sector (discounts on airplane tickets and jet-fuel) and to low-income households (social assistance and subsidy for home buyers). • The third fiscal package includes IDR 110 tn additional social assistance spending (later expanded to IDR 172 tn): increasing benefits and coverage of existing social safety nets such as food aid and unemployment benefits, and electricity subsidies. • A fourth stimulus package is announced on May 19 as part of a national economic recovery program. Forgone revenue (IDR 96.3 tn): • The first fiscal package includes tax cuts for the tourism sector. • The second fiscal package of IDR 33.2 tn includes income tax exemptions to workers in the industrial sectors (with an income ceiling). • The third fiscal package includes various tax reliefs and incentives: exemption and reduction of income taxes (with an income ceiling) and a reduction of the corporate income tax from 25 percent to 22 percent. | M51: Accelerated spending: The second fiscal package includes acceleration in VAT refund from April to September. Deferred revenue: The second fiscal package includes delayed payments of income tax for businesses from April to September. | O51: LC bn | P51: 135150 | Q51: 35150 | R51: • Capital injection to SOEs. | T51: LC bn | U51: 100000 | V51: • Government guarantees for bank lending to micro, small, and medium enterprises (IDR 150 tn), expected to be financed by Bank of Indonesia's purchase of new government recovery bonds.
F52: USD bn | G52: 29.092197 | H52: 5.2084969 | J52: 23.8837 | O52: USD bn | P52: 9.2622153 | Q52: 2.4089298 | T52: USD bn | U52: 6.8532854
F53: % GDP | G53: 2.6804101 | H53: 0.47988496 | J53: 2.2005251 | O53: % GDP | P53: 0.85337438 | Q53: 0.2219468 | T53: % GDP | U53: 0.63142758 | Y53: The first package (10.3), second package (22.9) and tax and expenditure measures from the third package (255.1). How the 150 tn from the third package will be used is not fully clear yet, but most likely in the form of liquid support for firms (thus below the line in the budget).
A54: 1 | B54: EM | C54: Mexico | D54: Non-financial Public Sector | F54: LC bn | G54: 154 | H54: 50 | I54: Additional spending: The authorities have increased public health spending and are trying to ensure sufficient supply of medical equipment and materials. | J54: 104 | K54: Additional spending: • Loans with optional repayment to be granted by the Ministry of Economy to SMEs that maintain employees on payroll, self-employed, and domestic workers. Eligibility is assessed using IMSS database • Loans with optional repayment to be granted by the Ministry of Economy to family businesses, previously registered in the Welfare Census • Unemployment subsidy for 3 months to workers that hold a mortgage with the Housing Institute • Expansion of Welfare Programs and improvement program. | L54: 92 | M54: Accelerated spending: • Frontloaded social pension payments for the elderly and disabled people • Procurement processes and VAT refunds are to be accelerated. | O54: LC bn | P54: 289.512 | Q54: 39.3 | R54: • Institute for Social Security and Services (ISSSTE) loans to state workers with low interest rates (MXN 34.3 bn). • Personal loans granted by the Institute of the National Fund for the Consumption of Workers (Fonacot) (MXN 3 bn). • Special Program to Reactivate the Economy against COVID by Housing Fund of the Institute for Social Security and Services(Fovissste) (MXN 2 bn). | T54: LC bn | U54: 24.512 | V54: • Development bank guarantees program | W54: 225.7 | X54: • Development banks to provide loans, particularly to small- and medium-scale enterprises | Y54: At the state-level, several state governments have announced support, including deferral of tax payments or tax holidays.
F55: USD bn | G55: 7.2279883 | H55: 2.3467495 | J55: 4.8812389 | L55: 4.318019 | O55: USD bn | P55: 13.588243 | Q55: 1.8445451 | T55: USD bn | U55: 1.1504705 | W55: 10.593227
F56: % GDP | G56: 0.68126555 | H56: 0.22119012 | J56: 0.46007544 | L56: 0.40698981 | O56: % GDP | P56: 1.2807439 | Q56: 0.17385543 | T56: % GDP | U56: 0.10843624 | W56: 0.99845218
A57: 1 | B57: EM | C57: Russia | D57: Central Government | F57: LC bn | G57: 3012 | H57: 634 | I57: Additional spending: • RUB 140 bn – new infection hospitals, additional beds and re-equipment of existing beds, special ambulances and equipment. • RUB 10 bn – bonus fund for medical staff, R&D in diagnostics and prevention. • RUB 50 bn – federal government top-ups to medical staff wages. • Medical staff directly engaged in coronavirus efforts will receive additional federal compensation. Forgone revenue: • RUB 32 bn - zero import duties for pharmaceuticals, medical supplies and equipment. | J57: 2378 | K57: Additional spending (RUB 1.9 tn): • Sick leave benefits for the quarantined or self-isolating individuals and increases in unemployment and child benefits • Interest rate subsidies for affected companies to finance minimum wages. • Interest rate subsidies for systemically important companies, conditional on employment keeping above 90 percent, to support working capital. • Support for large companies (construction, car-makers, air transportation, light industry). • Credit to affected sectors to protect employment with partial/full asset write-offs if employment is kept above 80%. • Grants for SMEs in affected industries to cover salaries and disinfection/COVID-19 prevention measures. • Support to airlines (RUB 23 bn) (subsidies), airports (RUR 11 billion) (subsidies) and car-K60makers (RUB 25 bn) (state procurement and interest rate subsidies). • Federal transfers to regions. • Construction sector support, including subsidized rates for a new mortgage program (costed at RUB 6 bn). Forgone revenue (RUB 460 bn): • Social contributions by SMEs on wages in excess of the minimum wage reduced from 30 to 15 percent, permanently. • Taxes and social contributions for Q2 written off (excluding VAT) targeting SMEs, Social NGO, sole proprietors (covers 1.5 mn enterprises). • Refund for the self-employed on 2019 taxes and credit of one minimum salary toward 2020 taxes. • Sole proprietors will get a tax credit of one minimum salary toward their social insurance payments. • For SMEs in the affected sectors: zero rent to the federal government for three months. • Tourism firms not to contribute to the tourist reserve fund. • Social contribution and CIT rates for IT firms will be cut permanently: from 14 percent to 7.6 percent for social contributions and from 20 percent to 3 percent for CIT. • Sick leave benefits for the quarantined or self-isolating individuals and increases in unemployment and child benefits • Interest rate subsidies for systemically important and affected companies to finance minimum wages. • Support for large companies (construction, car-makers, air transportation, light industry). • Credit to affected sectors to protect employment with partial/full asset write-offs if employment is kept above 80%. • Grants for SMEs in affected industries to cover salaries. • Support to airlines (RUB 23 bn) and car-makers (RUB 25 bn) (state procurement and interest rate subsidies). • Federal transfers to regions. • Construction sector support, including subsidized rates for a new mortgage program (costed at RUB 6 bn). Forgone revenue (RUB 474 bn): • Social contributions by SMEs on wages in excess of the minimum wage reduced from 30 to 15 percent, permanently. • Taxes and social contributions for Q2 written off (excluding VAT) targeting SMEs, Social NGO, sole proprietors (covers 1.5 mn enterprises). • Refund for the self-employed on 2019 taxes and credit of one minimum salary toward 2020 taxes. • Sole proprietors will get a tax credit of one minimum salary toward their social insurance payments. • For SMEs in the affected sectors: zero rent to the federal government for three months. • Tourism firms not to contribute to the tourist reserve fund. • Social contribution and CIT rates for IT firms will be cut permanently: from 14 percent to 7.6 percent for social contributions and from 20 percent to 3 percent for CIT. | L57: 460 | M57: Deferred revenue: • Tax deferrals for SMEs and most affected companies on most taxes (excluding VAT, PIT, MET, and social contributions). • Deferrals on social contributions for SMEs in affected sectors for 6 months. • For SMEs in the affected sectors: deferrals on rent payments to all levels of government until the end of the year. | O57: LC bn | P57: 1567 | Q57: 567 | R57: • RUB 70 billion for restructuring regional debt to the federal government. • Recapitalization of leasing firms due to potential problems of their clients in the transportation sector. | T57: LC bn | U57: 500 | V57: • The federal government announced guarantees of up to RUB 500 bn on bank lending to firms, including (1) RUB 220 bn in guarantees to VEB to guarantee bank credit to systematically-important enterprises; (2) RUB 160 in supporting domestic aircraft makers by issuing guarantees on domestic leasing companies 2020-21 borrowings for purchasing domestically produced passenger aircrafts and helicopters. | W57: 500 | X57: • The CBR has introduced a new RUB 500 bn facility for SME lending and reduced the interest rate on the existing RUB 175 bn facility. As part of the new RUB 500 bn facility, CBR has introduced a RUB 150 bn credit line to finance 6-month zero-interest loans to SMEs and individual entrepreneurs to cover payroll.
F58: USD bn | G58: 41.633739 | H58: 8.7635426 | J58: 32.870196 | L58: 6.3584063 | O58: USD bn | P58: 21.660049 | Q58: 7.8374269 | T58: USD bn | U58: 6.9113112 | W58: 6.9113112
F59: % GDP | G59: 2.909477 | H59: 0.6124198 | J59: 2.2970572 | L59: 0.44434244 | O59: % GDP | P59: 1.5136622 | Q59: 0.54770036 | T59: % GDP | U59: 0.48298092 | W59: 0.48298092
A60: 1 | B60: EM | C60: Saudi Arabia | D60: General Government | F60: LC bn | G60: 57.6 | H60: 47 | I60: Additional spending (SAR 47 bn): Budget reallocation within the Ministry of Health budget or a reallocation from other parts of the budget for emergency spending to fight COVID-19. | J60: 10.6 | K60: Additional spending (SAR 10.6 bn): • Wage benefits to employers who keep their workers to be provided through the unemployment insurance scheme, SANED (SAR 9 bn). This wage benefits have been extended. • Ministry of Energy announced temporary electricity subsidies to commercial, industrial, and agricultural sectors (SAR 0.9 bn). • The Ministry of Finance program to help businesses defer loan payment due this year (SAR 0.67 bn). | L60: 56 | M60: Deferred revenue (SAR 56 bn): Deferred declaration & payment of taxes for 3 months, waiver of customs duties (30 days to 3 months), waiver of expat fees for 3 months; and waiver of municipal fees on companies for 3 months. | O60: LC bn | P60: 22 | Q60: 22 | R60: • Off-budget support provided by the National Development Funds (NDF): SAR 22 bn distributed as follows: (i) loan rescheduling/restructuring and different loan programs to SMEs: SAR13 bn. (ii) support to employment programs in the private sector: SAR 5 bn. (iii) social loans to families with low incomes: SAR4 bn. | T60: LC bn
F61: USD bn | G61: 15.36 | H61: 12.533333 | J61: 2.8266667 | L61: 14.933333 | O61: USD bn | P61: 5.8666667 | Q61: 5.8666667 | T61: USD bn
F62: % GDP | G62: 2.1908414 | H62: 1.7876657 | J62: 0.40317568 | L62: 2.1299847 | O62: % GDP | P62: 0.83677971 | Q62: 0.83677971 | T62: % GDP
A63: 1 | B63: EM | C63: South Africa | D63: General Government | F63: LC bn | G63: 266 | H63: 20 | I63: Additional spending: for medical equipment and staff for health facilities, and policing the lockdown. Forgone revenue: VAT and customs duty exemptions for essential sanitary products during the pandemic (immune boosters, hand sanitizers, patient monitoring devices, etc.). | J63: 246 | K63: Additional spending (R 220 bn): • Measures to support workers’ unemployment insurance benefits (with R 80 bn funding from Unemployment Insurance Fund); create a New Covid-19 Social Relief of distress grant for the unemployed who do not receive grant or UI payment (extended to Jan 2021). • Increase transfers to households: grants and food distribution and public work program expansions. • Increase child support and all other grants from May till Oct. • Distribute food parcels and provide transfers to SMEs. • Municipalities to use higher central transfers to fund emergency water supply, sanitation of public transport and facilities, and food and shelter for the homeless (R 20 bn). • Contribute R 150 mn Rand to a solidarity fund to combat virus spread, track spread, ill care, support for disrupted lives. • Additional allocations by the Department of Industry and Trade, Department of Tourism, and Department of small enterprises to assist SMEs in distress (R 2.7 bn). Forgone revenue (R 26 bn): • Tax subsidy of up to R 750 to employees with an income below R 6,500 per month. • Skills development levy holiday for four months. | L63: 44 | M63: Deferred revenue: • Deferral of 35 percent of PAYE liability for four months for businesses with expected gross income of less than R 100 mn. • Deferral of 35 percent of provisional tax payments for the next six months for businesses and the self-employed with expected gross income of less than R 100 mn. • A 90-day deferral for alcohol and tobacco excise duty due to be paid in May and June • Three-month deferral for filing and payment date of carbon tax. | O63: LC bn | P63: 203 | T63: LC bn | U63: 200 | V63: The Treasury will guarantee up to R 200 bn in loans where also the banks are taking part of the risk to help businesses (with a cap of R100 million per loan) pay operating expenses including salaries, suppliers etc. | W63: 3 | X63: Programs from the industrial development corporation to support businesses.
F64: USD bn | G64: 16.156544 | H64: 1.2147778 | J64: 14.941767 | L64: 2.6725111 | O64: USD bn | P64: 12.329994 | T64: USD bn | U64: 12.147778 | W64: 0.18221667
F65: % GDP | G65: 5.477479 | H65: 0.41184052 | J65: 5.0656385 | L65: 0.90604915 | O65: % GDP | P65: 4.3006219 | T65: % GDP | U65: 4.1184052 | W65: 0.061776079
A66: 1 | B66: EM | C66: Turkey | D66: Non-financial Public Sector | F66: LC bn | G66: 53.6 | H66: 14.2 | I66: Additional spending: including on Covid-19 treatment (TL1.4 bn), new hospitals (TL5 bn), and performance pay for medics (TL6 bn). | J66: 39.4 | K66: Additional spending: • Raised the minimum pension and cash assistance to families in need. • Increased employment protection by loosening short-term work allowance rules. On July 24, a new bill mandated the state to cover the employee and employer shares of social security contributions for three months after a business exits the short-term work allowance system. • Subsidies to firms for workers placed on unpaid leave and for workers' salaries in firms affected by COVID-19. Forgone revenue: • Reduced taxes for affected industries (particularly tourism): hotel accommodation tax will be suspended until November; • VAT rate on internal travel reduced from 18% to 1%, • On July 31, VAT rate on several affected services sectors, including business rental services, were reduced temporarily till the end of 2020. The personal income tax on rental income and corporate withholding tax for certain lease payments have also been reduced to 10% from 20% previously till end-2020. | L66: 69.5 | M66: Accelerated spending: Early annual bonus payment to pensioners. Deferred revenue: •Tax deferrals for the self-employed, farmers, tailors, grocers, lawyers, financial advisers, architects, engineers, doctors, and dentists. • Tax deferrals for those aged over 65 or those with chronic illnesses. • Postponed payments regarding withholding tax returns and VAT declarations, as well as Social Security Contribution premiums (e.g., for retail/shopping malls, iron-steel, automobiles, logistics-transportation sectors). • Land occupation and revenue sharing payments in leasing of hotels postponed for 6 months. • Accommodation tax deferred. • Retail, shopping malls, iron-steel, automobiles, logistics-transportation, etc. are offered to postpone VAT and Social Security Contribution. | O66: LC bn | P66: 450.6 | Q66: 21 | R66: • Turkey Wealth Fund (TWF) has been granted new rights to take equity in firms affected by Covid-19, and was assigned to inject a core capital of 0.4 percent of GDP into three state banks, funded by issuance of Treasury bonds. | T66: LC bn | U66: 306 | V66: • Treasury guaranteed loans. • Credit guarantee fund (set up in 2016) doubled in size from TL25 to 50 billion as part of the fiscal package. | W66: 123.6 | X66: • All public banks: Principal and interest payments by those firms whose cash flows are affected adversely by Covid-19 will be postponed by minimum 3 months and provided with refinancing. • Various state bank lending schemes, including: extending repayment terms on specified credit card loans; low interest credit packages for low income households; April, May and June repayments by tradespeople extended without penalty; new low interest loans for tradespeople; and new credit cards for merchants with longer repayment periods; new lending campaigns directed to firms "maintaining" employees. • On June 1, public deposit banks (Ziraat Bank, Halkbank and Vakifbank) launched new retail loan campaigns for house purchases and consumer spending.
F67: USD bn | G67: 7.6102085 | H67: 2.0161373 | J67: 5.5940711 | L67: 9.8677143 | O67: USD bn | P67: 63.976864 | Q67: 2.9816115 | T67: USD bn | U67: 43.446339 | W67: 17.548914
F68: % GDP | G68: 1.0708244 | H68: 0.28368856 | J68: 0.78713585 | L68: 1.3884757 | O68: % GDP | P68: 9.0021171 | Q68: 0.41953941 | T68: % GDP | U68: 6.1132886 | W68: 2.4692891
A69: 0 | B69: AE | C69: Belgium | D69: General Government | F69: LC bn | G69: 32.1 | H69: 8.1 | I69: Additional spending (€8.1 bn): on medical equipment, tests, administration etc. Measures include advance payments to hospitals as well as a structural increase in the budget for mental health care and the federal health sector. An additional one-off payment will also be allocated to federal health workers in 2020. | J69: 24 | K69: Additional spending (€19.6 bn): • Federal government eased access to temporary unemployment for firms affected by Covid-19, raised the benefit replacement rate, and introduced a daily premium, as well as eased access to replacement income for the self-employed. It also introduced Covid-19 parental leave and increased unemployment benefits (extension of switching on allowance for the young etc.), social assistance benefits, and support to local social services. Key temporary measures have been extended until end-August, end-December 2020 (replacement income), or end-March 2021 (temporary unemployment), with eligibility widened and benefits increased for some of them to support firms and households through the second lockdown (Nov-Dec). Additional measures have been taken to support hard-hit sectors and vulnerable groups. • Regional governments provided transfers for companies and self-employed affected by closures or significantly reduced turnover; further support to specific, affected sectors in addition to the health care sector; support for utility bills for affected households; and a host of smaller support measures. Similar measures have been reintroduced in Oct-Nov in the context of the re-imposition of restrictions and the second lockdown. Forgone revenue (€4.4 bn): • Suspension of penalties for delays or non-performance of suppliers to the public sector. • Loss carry backward for CIT and PIT, tax exemption for regional support measures (for firms affected by closures and reduced turnover), social security contribution exemption for self-employed, temporary reduction in VAT in the hospitality sector (e.g., food and non-alcoholic beverages), increase in the investment allowance for SMEs and natural persons (extended until end-2022), and increase in the CIT allowance for restaurant and reception costs. | L69: 13.8 | M69: Deferred revenue (€13.8 bn): • Deferred payment of tax and social security contributions for affected firms, self-employed, and households, without application of interest charges and penalties, estimated at about 10 billion euros, and deferral of advance VAT payment in December 2020. Additional deferral of SSC payments due in Q4 for firms affected by the second lockdown. | O69: LC bn | P69: 53 | Q69: 1 | R69: Government loans (0.8bn): • Federal loan to Brussels Airlines; and various (subordinated) loans provided by regional governments for companies and self-employed affected by Covid-19 (facing liquidity problems, etc.); some of which channeled through regional investment vehicles. Equity injections (0.3bn): • Capital increase in Flemish and Brussels regional investment companies that will use the funds to provide capital support to firms in need. | T69: LC bn | U69: 52 | V69: • The federal government launched a guarantee mechanism for all new credits and credit lines, initially with a maximum maturity of 12 months granted by banks to viable non-financial corporations and self-employed. Modified end-July to extend the maturity to 36 months, replace the loss tranching by uniform loss sharing between government and banks (80-20), and ease the viability criterion. The modified scheme applies to 10bn out of a total envelope of 50bn total envelope. Take-up is about 1.5bn. · Regional governments also provide guarantees for affected companies and self-employed in need of bridge loans. Take-up is about 0.4bn. · The federal government signed a memorandum of understanding with Credendo ECA, Assuralia and private credit-insurance firms, committing to provide reinsurance for short-term (< 2yrs) trade credit insurance.
F70: USD bn | G70: 36.538256 | H70: 9.2199337 | J70: 27.318322 | L70: 15.708035 | O70: USD bn | P70: 60.327961 | Q70: 1.1382634 | T70: USD bn | U70: 59.189698
F71: % GDP | G71: 7.2204845 | H71: 1.8219914 | J71: 5.3984931 | L71: 3.1041335 | O71: % GDP | P71: 11.921672 | Q71: 0.22493721 | T71: % GDP | U71: 11.696735
A72: 0 | B72: AE | C72: Czech Republic | D72: General Government | F72: LC bn | G72: 304.4 | H72: 66.6 | I72: Additional spending: • Purchases of medical equipment, vaccine etc. (CZK 19.4bn). • The government approved higher premium payments on state-covered health insurance--increase by CZK500 per person as of June (CZK 21.1bn). • Debt relief of hospitals (CZK 6.6bn). • Bonus for workers in social services, hospitals, emergency responders, hygienically stations (CZK 17.2 bn). • Other health measures: (mobile collection teams, Smart Quarantine establishment, anti-covid programmes for firms) (CZK 2.3bn). | J72: 237.8 | K72: Additional spending: • Payments for employment support: Employees affected during the shutdown due to government measures will receive full wages of which the government covered 80 percent up to CZK 39,000/month (since October the government has covered 100% up to CZK 50,000/month in case of business shutdown due to government measures). Staff in businesses affected receive 60-100% of gross wages with a state contribution of 60% of total labor costs per employee (up to CZK 29,000/month) (CZK 25.6bn). • Care Allowance to parents, who cannot work because they need to care for children up to 13 years, of 80% of eligible income until end of June (calculated based on a progressive table) for sick leave. During the second wave of COVID, care allowance to parents with children up to 10 years, 70% of eligible income (CZK 10.2bn). • Care Allowance to self-employed persons (CZK 434 per day in March, CZK 500 per day since April), who cannot work because they need to care for children up to 13 years. During the second wave of COVID for parents with children up to 10 years, CZK 400 per day (CZK 2.6bn) • The state covers half of business property rents in Q2-Q4 (CZK 8.8bn). • Programs in support of the sports, culture, tourism, transport, restaurants, agriculture and other closed sectors (CZK 28.4bn). • Other expenditure (CZK 3bn). • One-off cash benefit for pensioners in amount of CZK 5000 (CZK 15.2bn). Forgone Revenue: • Waived social security contributions paid by employers (24.8%) with a maximum of 50 employees for the period between June and August. This support will be provided concurrently with the wage compensation if two conditions are satisfied – minimum employment level of 90% and wages paid in March 2020 are at least 90% (CZK 13.3bn). • Loss carryback measure: Taxpayers who report tax losses in 2020 due to the state of emergency, will be able to reduce their tax bases for the tax years 2019 and 2018 by this loss (maximum CZK 30 million) (CZK 20bn). • Reduced VAT rate to 10% for accommodation, sports and culture services (CZK 1.2bn). • Reduced road tax rate for vehicles above 3.5t (CZK 1bn). • Abolition of the real property transfer tax (CZK 13.8bn). • Lower dividends from Airport Prague (CZK 1.5bn). • Self-employed receive lump sum of CZK 500 per day during Mar 12 and Jun 8 (CZK 20.2bn). • Additional lump-sum assistance grant (CZK 500 per day) to micro businesses during Mar 12 and Jun 8. Eligible businesses are limited liability companies with up to two partners and turnover of at least at CZK 180,000 in 2019 (CZK 1.8bn). Additional lump-sum assistance grant (CZK 350 per day) to contract workers (not employees) (CZK 1bn) • Selected (from affected sectors) lump-sum for self-employed persons, small business (Ltd) and contractors (CZK 500 per day) during 5 Oct and 23 Jan (CZK 13.7bn). | L72: 36.3 | M72: Deferred revenue: • Postponement of (i) advance payments on personal and corporate income taxes (CZK 22bn); (ii) advance payments on social security and health insurance contributions for self-employed by 6 months (CZK 14.3bn); (iii) advance payments on road tax • Deferral of the VAT | O72: LC bn | P72: 865 | Q72: 1 | R72: • The CMZRB provided CZK 1bn through interest-free loans, the rest will be handled through state guarantees on loans of commercial banks (COVID I Programme). | T72: LC bn | U72: 864 | V72: • COVID III Program (Guarantees will cover up to 30% of loan principal. The state will issue 80-90% of the guarantees (total amount of CZK 150bn). Estimates of the amount of guarantees offered will allow SMEs to access loans amounting to CZK500bn. • COVID II Program of state guarantees in total amount of CZK 20bn (loans up to CZK 15 million, state contribution on interest costs up to CZK 1 million, state guarantee up to 80% of loan, 3-year maturity) • COVID Plus Program of state guarantees provided by Export Guarantee and Insurance Corporation in the amount of CZK 330bn. • COVID Prague Program (1.6bn). • Other guarantees (National guarantee, Expansion guarantee) (CZK 12bn).
F73: USD bn | G73: 13.066404 | H73: 2.8588124 | J73: 10.207591 | L73: 1.5581815 | O73: USD bn | P73: 37.13022 | Q73: 0.04292511 | T73: USD bn | U73: 37.087295
F74: % GDP | G74: 5.4442335 | H74: 1.1911496 | J74: 4.2530838 | L74: 0.64923021 | O74: % GDP | P74: 15.470637 | Q74: 0.01788513 | T74: % GDP | U74: 15.452752
A75: 0 | B75: AE | C75: Denmark | D75: General Government | F75: LC bn | G75: 40.3 | H75: 0.8 | I75: Additional spending: Resources to hire social and health workers nationwide. | J75: 39.5 | K75: Additional spending: • Compensation scheme for the cancellation and postponement of major events following COVID-19 (Announced: DKK 2.4 billion) • Temporary salary compensation between 75% and 90% of workers salary (Announced: DKK 6.2 billion, Uptake: DKK 12.7 billion) Temporary compensation scheme for self-employed and freelancers (Announced: DKK 14.1 billion Uptake: DKK 5.9 bn). • Sickness benefit reimbursement (Announced: DKK 1.7 billion) and increased access to unemployment benefits and sickness benefits (Announced: DKK 0.3 billion). • Temporary compensation scheme for companies’ fixed costs (Announced: DKK 65.3 billion, Uptake: DKK 7.1 bn). • Boosting liquidity and facilitating the advancement and completion of various construction projects in the Danish municipalities and regions (Announced: DKK 2.5 billion). • Other initiatives (about DKK 2 bn) • UI benefits expanded eligibility (Announced: DKK 0.4 bn) • Extension of cultural aid packages to 8/8 (Announced: DKK 0.1 bn) • One-time grants to low-income families (Announced: DKK 1.8 bn). • Increase in corporate deductions for R&D (Announced DKK 1.3 bn). • Support for tourism sector (Announced DKK 0.8 bn). • Export package (Announced DKK 0.5 bn). | L75: 175.4 | M75: Accelerated spending: • Advance payment of tax credits (DKK 1 bn) Deferred revenue: • Temporary postponement of payment deadlines for A-taxes (withholding tax) and labor market contributions (DKK 90 billion) The payment deadline for VAT for businesses that pay VAT on a monthly basis is postponed (DKK 35 billion) • Small enterprises’ VAT period will be extended from 6 months to 12 months in 2020, while medium-sized enterprises’ VAT periods will be extended from 3 months to 6 months for the first half of 2020 (DKK 35 billion) • Temporary postponement of payment deadlines for B-taxes (provisional tax paid by self-employed businessmen) (DKK 5 billion) • Temporary postponement of payment deadlines for payroll tax for certain businesses. (DKK 0.4 billion) •Further extension of payment deadlines for a-tax and VAT (DKK 9 billion) | O75: LC bn | P75: 96.996 | Q75: 57.083 | R75: • Increase the Danish Students’ Loan Scheme (DKK 1.5 billion). • Interest free loans based on VAT payments and payroll tax payments (DKK 35 billion). • Loans and equity to start-ups and high growth enterprises (Announced: less than DKK 3.4 billion, Uptake: DKK 1.6 bn) State capital injection into Recapitalization Fund (DKK 10 bn) • State capital injection into Restart Fund (administered by the Growth Fund) (DKK 3 bn) • Plan to recapitalize Scandinavian Airlines (up to DKK 6 bn) | T75: LC bn | U75: 39.913 | V75: • The government will guarantee 70% of the value of new loans to 1) large companies that can demonstrate a fall in turnover over more than 30 percent and 2) SMEs that have seen operating profits fall by more than 30 percent (Announced: DKK 60.7 bn Uptake 7.4 bn). • Credit guarantee for Scandinavian Airlines (SAS). (Announced DKK 1 bn) • Increased access to export credit for SMEs. (Announced DKK 1.3 bn Uptake: DKK 30 bn) • Strengthening the Travel Guarantee Fund. (Announced DKK 1.5 bn) | Y75: Another 2 percent of GDP in countercyclical support is expected to come through the stronger automatic stabilizers—including from weaker tax receipts and higher social benefits.
F76: USD bn | G76: 6.1428698 | H76: 0.12194282 | J76: 6.020927 | L76: 26.735964 | O76: USD bn | P76: 14.784958 | Q76: 8.7010778 | T76: USD bn | U76: 6.0838799
F77: % GDP | G77: 1.7728572 | H77: 0.035193196 | J77: 1.737664 | L77: 7.7161081 | O77: % GDP | P77: 4.266999 | Q77: 2.5111665 | T77: % GDP | U77: 1.7558325
A78: 0 | B78: AE | C78: Finland | D78: General Government | F78: LC bn | G78: 6.95 | H78: 1.85 | I78: Additional spending: • The supplementary budget includes €265 million in additional spending for healthcare and testing, PPE and medical equipment. Another supplemental budget has been announced, but not yet passed, that adds another €600 million for health equipment and medicine. • The third supplementary budget includes €16 million for vaccine and drug development research, and the development and maintenance of a contact tracing app. • The fourth supplementary budget includes an additional €310 million for coronavirus vaccine and testing (€110 million) and transfers to hospital district authorities (€200 million). • On September 24, the government submitted a sixth supplementary budget proposal for 2020 which included €200 million to support the rapid increase in cross-border testing capacity and analysis as part of the hybrid strategy for cross-border traffic and travel. •The seventh supplementary budget, submitted on October 23, included EUR 200 million to the country’s hospital districts for pandemic-related costs. It also included $355 million to municipalities for implementing the hybrid testing and tracing strategy. | J78: 5.1 | K78: Additional spending: (i) grants to SMEs through Business Finland and the Employment Centers (€450 million); increased parental allowance (€94 million); additional social assistance and unemployment benefits (€1.547 billion); additional public safety and border controls, etc. measures to support restaurant to employ workers EUR 40 million, measures to support businesses for imposed restrictions on activities, EUR 83 million, Share acquisitions in state ownership steering, EUR 700 mn. The fourth supplementary budget includes additional support for households and employment (€652 million); support for businesses (€520 million); and increased public investment (€963 million). The seventh supplementary budget included EUR 400 million in support to municipalities for basic public services. Forgone revenue: Reduced pension contributions for the period May 1 - 31 December 2020 (€1.05 billion) | L78: 4.25 | M78: Deferred revenue: Deferrals of tax and pension payment obligations for 3 months are estimated to provide an additional €3.5 billion (1.6 percent of GDP) in relief. Adjusted VAT tax payments provide an additional €750 million in relief. | O78: LC bn | P78: 16.32 | Q78: 2.42 | R78: • SME capital injections of €150 million. Share acquisitions in state ownership steering €700 million. • On April 29, the government announced a recapitalization of Finnair of €500 million. Finnair is 56% publicly owned. • Increased capitalization of €300 million into national climate fund. • Increased capital funding for state-owned enterprises of €770 million. | T78: LC bn | U78: 12.9 | V78: • Finland’s Export Credit Agency expands its lending and guarantee capacity to SMEs by €10 bn and the government will increase its coverage of the agency’s credit and guarantee losses from 50 to 80 percent. • State guarantee for Finnair (€ 0.6 bn) and shipping companies (€ 0.6 bn) • As of the Supplementary Budget on May 8, the following guarantees have been added totaling € 1.7 billion: Guarantees for Employment Fund, € 880 million, for SURE, € 432 million, for the EIB, € 372 million. | W78: 1 | X78: The State Pension Fund will invest in commercial paper (€1 bn). | Y78: Deferral of tax and pension payments for 3 months are expected to provide additional short-run relief of €3-4.5 bn. Automatic stabilizers are expected to increase the fiscal deficit significantly, including through an expansion of the coverage of existing unemployment benefits.
F79: USD bn | G79: 7.9109307 | H79: 2.1057873 | J79: 5.8051434 | L79: 4.8376195 | O79: USD bn | P79: 18.576459 | Q79: 2.7545975 | T79: USD bn | U79: 14.683598 | W79: 1.1382634
F80: % GDP | G80: 2.9740073 | H80: 0.79164224 | J80: 2.1823651 | L80: 1.8186376 | O80: % GDP | P80: 6.9835683 | Q80: 1.0355536 | T80: % GDP | U80: 5.5200999 | W80: 0.42791472 | Y80: Short-run relief of €3-4.5 bn (1.9 percent of GDP).
A81: 0 | B81: AE | C81: The Netherlands | D81: General Government | F81: LC bn | G81: 35.6 | H81: 5.9 | I81: Additional spending: including on purchase, distribution, and sale of medical devices; vaccine research; healthcare costs in the Caribbean Netherlands; training additional healthcare personnel. | J81: 29.7 | K81: Additional spending: • Compensation of up to 90 percent of labor costs for companies expecting a reduction in revenues of 20 percent or more; compensation for affected sectors (for example, hospitality services and travel). • Income support for entrepreneurs and self-employed (administered at municipal and regional level) for a period of three months through expedited procedures. • Support for start-ups and small innovation companies through loans provided by government regional agencies. • Scaling up of the short-time working scheme (unemployment benefit compensation available to companies needing to reduce their staff by at least 20 percent). • Allowances for SMEs affected by the outbreak to help them finance their fixed costs. • On August 28, the government announced the third support package which primarily aims at expanding measures already in place on the expenditure side through June 2021. This new package includes additional expenditure of 12.5 billion (or 1.7 percent of GDP), of which 1.5 billion of public investment. Forgone revenue: • Reduction of tourist taxes and taxes in the culture sector. • The interest rate on tax deferrals is reduced from 4% to just above 0%. | L81: 12.6 | M81: Deferred revenue: Tax deferrals for companies that are in financial distress due to the covid-19 crisis. Temporary suspension of penalties for late tax payments. Entrepreneurs can request a deferral of tax payment, without the need to provide evidence. Businesses can calculate provisional tax payments on an expected (reduced) basis. | O81: LC bn | P81: 65 | T81: LC bn | U81: 65 | V81: • The loan guarantee program for businesses (especially those affected by the outbreak) was expanded to cover up to 90 percent of total loan for SMEs (with maturity of 1 year or less) and 80 percent for large firms. • A guarantee scheme for supplier credit was also established. | Y81: Tax deferrals for companies that are in financial distress. Temporary suspension of penalties for late tax payments. Interest rate on tax deferral is reduced from 4 percent to just above 0. Stronger automatic stabilizers given the broad social safety nets.
F82: USD bn | G82: 40.522178 | H82: 6.7157541 | J82: 33.806423 | L82: 14.342119 | O82: USD bn | P82: 73.987122 | T82: USD bn | U82: 73.987122
F83: % GDP | G83: 4.5192778 | H83: 0.74898144 | J83: 3.7702964 | L83: 1.5995197 | O83: % GDP | P83: 8.2514904 | T83: % GDP | U83: 8.2514904
A84: 0 | B84: AE | C84: New Zealand | D84: Central Government | F84: LC bn | G84: 61.6 | H84: 3.9 | I84: Additional spending: doubling resources for public health units; expanding intensive care capacity and equipment at hospitals; expanding health line capacity; support for primary care; the purchasing of vaccines, the cost of managed isolation. | J84: 57.7 | K84: Additional spending (NZ$ 52.3 bn): including wage subsidies available for all employers significantly affected by COVID-19 (NZ $14.8 bn); income relief payment to support people who have lost their job (NZ$ 570 mn); financial support for workers not paid normally during self-isolation (NZ$126 mn); temporary increase in winter energy payment (NZ $480 mn); permanent increase in benefits (NZ$ 2.4 bn in the next four years); infrastructure investment (NZ$ 3.8 bn); support package for the aviation sector (NZ$ 600 mn); tourism recover package (NZ$ 400 mn); government housing program (NZ$ 670 mn); and school infrastructure upgrade (NZ$ 214 mn); and transport projects (NZ$ 600 mn). Forgone revenue (NZ$ 5.9 bn): including the reinstatement of depreciation deductions for commercial and industrial buildings at a 2% diminishing value applying from the 2020-21 tax year (permanent); increasing the threshold for provisional tax from NZ $2.5K to NZ $5K applying from the FY2020-21 tax year (permanent); increasing the threshold for writing off low value assets to NZ $5K for the next tax year, before reverting to NZ$1K in the longer term; time-limited discretion of Inland Revenue to remit use of money interest (the interest on tax debt) if a taxpayer is unable to pay on time due to COVID-19; and tax loss carry-back mechanism for firms to offset a loss in a particular tax year against a profit in a previous year, and receive a refund on the tax paid in the previous profitable year. | O84: LC bn | P84: 8.75 | Q84: 2.5 | R84: • NZ$ 900 mn loan is granted to Air New Zealand, an airline company, of which the government owns 52 percent of shares. • Maximum NZ$100 thousand loan is granted to small businesses that employ 50 or fewer full time equivalent employees (NZ$ 1.6 bn). | T84: LC bn | U84: 6.25 | V84: • A loan guarantee scheme for firms with a turnover of between NZ$ 250 thousand and NZ$ 200 mn per annum, with the Government carrying 80% of the credit risk. The loans will be limited to NZ$ 5 mn for a maximum of five years and expected to be provided by the banks at competitive, transparent rates.
