Workbook
Name FCV_added: OFFSET('Policy select backend'!$O$52,,,2+'Policy select backend'!$B$52)
Name FCV_Scores: OFFSET('Performance across backend'!$H$39,,,2+'Performance across backend'!$P$3)
Name Income_added: OFFSET('Policy select backend'!$O$37,,,4+'Policy select backend'!$B$52)
Name Income_scores: OFFSET('Performance across backend'!$H$24,,,4+'Performance across backend'!$P$3)
Name Lending_added: OFFSET('Policy select backend'!$O$31,,,3+'Policy select backend'!$B$52)
Name Lending_scores: OFFSET('Performance across backend'!$H$18,,,3+'Performance across backend'!$P$3)
Name Regions_added: OFFSET('Policy select backend'!$O$43,,,7+'Policy select backend'!$B$52)
Name Regions_scores: OFFSET('Performance across backend'!$H$30,,,7+'Performance across backend'!$P$3)

Sheet Data
A1: Country | B1: PolicyCategory | C1: PolicyCode | D1: Fullpolicy | E1: Targetability | F1: Speed | G1: Abuse_Resistance | H1: Affordability | I1: Predictability_Cost_Control | J1: Reversibility | K1: Scalability | L1: Administrative_Complexity | M1: Resilience_Health_Measures | N1: Country_Code | O1: Reg | P1: Lendingcategory | Q1: Incomelevel | R1: FCV | S1: GDP change | T1: Fiscal Balance | U1: Debt | V1: Targetability (converted) | W1: Speed (converted) | X1: Abuse_Resistance (converted) | Y1: Affordability (converted) | Z1: Predictability_Cost_Control (converted) | AA1: Reversibility (converted) | AB1: Scalability (converted) | AC1: Administrative_Complexity (converted) | AD1: Resilience_Health_Measures (converted) | AE1: All Regions | AF1: All Income Levels | AG1: IDA | AH1: IBRD | AI1: Neither | AJ1: All | AK1: All Countries | AL1: Other Policy | AM1: Selected Country Ranker | AN1: Region location | AO1: Lending location | AP1: Income location | AQ1: FCV location | AR1: Country location | AS1: Country2 | AT1: Subcategory (clean) | AU1: First of country row (requires sorting alphabetically by country) | AV1: May 1st sample
A2: Afghanistan | B2: 5 | C2: general | D2: Financing requested to the World Bank, Asian Development Bank, Islamic Development Bank, and the IMF. | E2: 1 | F2: -2 | G2: -2 | H2: 2 | I2: -1 | J2: 1 | K2: 1 | L2: 1 | M2: 1 | N2: AFG | O2: South Asia | P2: IDA | Q2: Low Income | R2: 0 | S2: -1.89 | T2: -2.16 | U2: 8.21 | V2: =IF(E2>0,1,IF(E2<0,0,-1)) -> 1 | W2: =IF(F2>0,1,IF(F2<0,0,-1)) -> 0 | X2: =IF(G2>0,1,IF(G2<0,0,-1)) -> 0 | Y2: =IF(H2>0,1,IF(H2<0,0,-1)) -> 1 | Z2: =IF(I2>0,1,IF(I2<0,0,-1)) -> 0 | AA2: =IF(J2>0,1,IF(J2<0,0,-1)) -> 1 | AB2: =IF(K2>0,1,IF(K2<0,0,-1)) -> 1 | AC2: =IF(L2>0,1,IF(L2<0,0,-1)) -> 1 | AD2: =IF(M2>0,1,IF(M2<0,0,-1)) -> 1 | AE2: All Regions | AF2: All Income Levels | AG2: 1 | AH2: 0 | AI2: 0 | AJ2: 1 | AK2: All Countries | AL2: =IF(OR(B2="other",B2="international",B2="Transfers",B2="expenditure"),1,0) -> 0 | AM2: =IF(AND(INDIRECT(AN2)='Sample Select backend'!$C$2,INDIRECT(AO2)=1,INDIRECT(AP2)='Sample Select backend'!$F$2,INDIRECT(AQ2)=1,INDIRECT(AR2)='Sample Select backend'!$M$2),1,0) -> 0 | AN2: =_xlfn.CONCAT('Sample Select backend'!$C$4,ROW(AN2)) -> AE2 | AO2: =_xlfn.CONCAT('Sample Select backend'!$J$2,ROW(AO2)) -> AJ2 | AP2: =_xlfn.CONCAT('Sample Select backend'!$F$4,ROW(AP2)) -> AF2 | AQ2: =_xlfn.CONCAT('Sample Select backend'!$I$10,ROW(AQ2)) -> R2 | AR2: =_xlfn.CONCAT('Sample Select backend'!$M$4,ROW(AR2)) -> AK2 | AS2: =A2 -> Afghanistan | AT2: =IF(ISNUMBER(C2),C2,IF(OR(C2="general",C2="23;general"),"General",IF(OR(C2="exemption",C2="other (exemption)"),"Tax exemption/waiver/suspension","Other"))) -> General | AU2: =IF(A2<>A1,1,0) -> 1 | AV2: 1
A3: Afghanistan | B3: 5 | C3: general | D3: An additional USD 10 million of reserve funds have been earmarked for further health costs of the COVID-19 response. | E3: 1 | F3: -2 | G3: -2 | H3: -1 | I3: -1 | J3: 1 | K3: 1 | L3: 1 | M3: 1 | N3: AFG | O3: South Asia | P3: IDA | Q3: Low Income | R3: 0 | S3: -1.89 | T3: -2.16 | U3: 8.21 | V3: =IF(E3>0,1,IF(E3<0,0,-1)) -> 1 | W3: =IF(F3>0,1,IF(F3<0,0,-1)) -> 0 | X3: =IF(G3>0,1,IF(G3<0,0,-1)) -> 0 | Y3: =IF(H3>0,1,IF(H3<0,0,-1)) -> 0 | Z3: =IF(I3>0,1,IF(I3<0,0,-1)) -> 0 | AA3: =IF(J3>0,1,IF(J3<0,0,-1)) -> 1 | AB3: =IF(K3>0,1,IF(K3<0,0,-1)) -> 1 | AC3: =IF(L3>0,1,IF(L3<0,0,-1)) -> 1 | AD3: =IF(M3>0,1,IF(M3<0,0,-1)) -> 1 | AE3: All Regions | AF3: All Income Levels | AG3: 1 | AH3: 0 | AI3: 0 | AJ3: 1 | AK3: All Countries | AL3: =IF(OR(B3="other",B3="international",B3="Transfers",B3="expenditure"),1,0) -> 0 | AM3: =IF(AND(INDIRECT(AN3)='Sample Select backend'!$C$2,INDIRECT(AO3)=1,INDIRECT(AP3)='Sample Select backend'!$F$2,INDIRECT(AQ3)=1,INDIRECT(AR3)='Sample Select backend'!$M$2),1,0) -> 0 | AN3: =_xlfn.CONCAT('Sample Select backend'!$C$4,ROW(AN3)) -> AE3 | AO3: =_xlfn.CONCAT('Sample Select backend'!$J$2,ROW(AO3)) -> AJ3 | AP3: =_xlfn.CONCAT('Sample Select backend'!$F$4,ROW(AP3)) -> AF3 | AQ3: =_xlfn.CONCAT('Sample Select backend'!$I$10,ROW(AQ3)) -> R3 | AR3: =_xlfn.CONCAT('Sample Select backend'!$M$4,ROW(AR3)) -> AK3 | AS3: =A3 -> Afghanistan | AT3: =IF(ISNUMBER(C3),C3,IF(OR(C3="general",C3="23;general"),"General",IF(OR(C3="exemption",C3="other (exemption)"),"Tax exemption/waiver/suspension","Other"))) -> General | AU3: =IF(A3<>A2,1,0) -> 0 | AV3: 1
A4: Afghanistan | B4: 2 | C4: 13 | D4: Deadline extension for filing tax returns by two months, until May 20 for individual taxpayers. | E4: -2 | F4: 1 | G4: 2 | H4: 1 | I4: 1 | J4: 1 | K4: 1 | L4: 1 | M4: 1 | N4: AFG | O4: South Asia | P4: IDA | Q4: Low Income | R4: 0 | S4: -1.89 | T4: -2.16 | U4: 8.21 | V4: =IF(E4>0,1,IF(E4<0,0,-1)) -> 0 | W4: =IF(F4>0,1,IF(F4<0,0,-1)) -> 1 | X4: =IF(G4>0,1,IF(G4<0,0,-1)) -> 1 | Y4: =IF(H4>0,1,IF(H4<0,0,-1)) -> 1 | Z4: =IF(I4>0,1,IF(I4<0,0,-1)) -> 1 | AA4: =IF(J4>0,1,IF(J4<0,0,-1)) -> 1 | AB4: =IF(K4>0,1,IF(K4<0,0,-1)) -> 1 | AC4: =IF(L4>0,1,IF(L4<0,0,-1)) -> 1 | AD4: =IF(M4>0,1,IF(M4<0,0,-1)) -> 1 | AE4: All Regions | AF4: All Income Levels | AG4: 1 | AH4: 0 | AI4: 0 | AJ4: 1 | AK4: All Countries | AL4: =IF(OR(B4="other",B4="international",B4="Transfers",B4="expenditure"),1,0) -> 0 | AM4: =IF(AND(INDIRECT(AN4)='Sample Select backend'!$C$2,INDIRECT(AO4)=1,INDIRECT(AP4)='Sample Select backend'!$F$2,INDIRECT(AQ4)=1,INDIRECT(AR4)='Sample Select backend'!$M$2),1,0) -> 0 | AN4: =_xlfn.CONCAT('Sample Select backend'!$C$4,ROW(AN4)) -> AE4 | AO4: =_xlfn.CONCAT('Sample Select backend'!$J$2,ROW(AO4)) -> AJ4 | AP4: =_xlfn.CONCAT('Sample Select backend'!$F$4,ROW(AP4)) -> AF4 | AQ4: =_xlfn.CONCAT('Sample Select backend'!$I$10,ROW(AQ4)) -> R4 | AR4: =_xlfn.CONCAT('Sample Select backend'!$M$4,ROW(AR4)) -> AK4 | AS4: =A4 -> Afghanistan | AT4: =IF(ISNUMBER(C4),C4,IF(OR(C4="general",C4="23;general"),"General",IF(OR(C4="exemption",C4="other (exemption)"),"Tax exemption/waiver/suspension","Other"))) -> 13 | AU4: =IF(A4<>A3,1,0) -> 0 | AV4: 1
A5: Afghanistan | B5: 1 | C5: 6 | D5: Tourism, active processing and call centers – as well as small businesses with turnover of Lk14m or less – can defer payments of profit tax to next year. | E5: 2 | F5: 2 | G5: 2 | H5: 1 | I5: 1 | J5: 1 | K5: 1 | L5: 1 | M5: 1 | N5: AFG | O5: South Asia | P5: IDA | Q5: Low Income | R5: 0 | S5: -1.89 | T5: -2.16 | U5: 8.21 | V5: =IF(E5>0,1,IF(E5<0,0,-1)) -> 1 | W5: =IF(F5>0,1,IF(F5<0,0,-1)) -> 1 | X5: =IF(G5>0,1,IF(G5<0,0,-1)) -> 1 | Y5: =IF(H5>0,1,IF(H5<0,0,-1)) -> 1 | Z5: =IF(I5>0,1,IF(I5<0,0,-1)) -> 1 | AA5: =IF(J5>0,1,IF(J5<0,0,-1)) -> 1 | AB5: =IF(K5>0,1,IF(K5<0,0,-1)) -> 1 | AC5: =IF(L5>0,1,IF(L5<0,0,-1)) -> 1 | AD5: =IF(M5>0,1,IF(M5<0,0,-1)) -> 1 | AE5: All Regions | AF5: All Income Levels | AG5: 1 | AH5: 0 | AI5: 0 | AJ5: 1 | AK5: All Countries | AL5: =IF(OR(B5="other",B5="international",B5="Transfers",B5="expenditure"),1,0) -> 0 | AM5: =IF(AND(INDIRECT(AN5)='Sample Select backend'!$C$2,INDIRECT(AO5)=1,INDIRECT(AP5)='Sample Select backend'!$F$2,INDIRECT(AQ5)=1,INDIRECT(AR5)='Sample Select backend'!$M$2),1,0) -> 0 | AN5: =_xlfn.CONCAT('Sample Select backend'!$C$4,ROW(AN5)) -> AE5 | AO5: =_xlfn.CONCAT('Sample Select backend'!$J$2,ROW(AO5)) -> AJ5 | AP5: =_xlfn.CONCAT('Sample Select backend'!$F$4,ROW(AP5)) -> AF5 | AQ5: =_xlfn.CONCAT('Sample Select backend'!$I$10,ROW(AQ5)) -> R5 | AR5: =_xlfn.CONCAT('Sample Select backend'!$M$4,ROW(AR5)) -> AK5 | AS5: =A5 -> Afghanistan | AT5: =IF(ISNUMBER(C5),C5,IF(OR(C5="general",C5="23;general"),"General",IF(OR(C5="exemption",C5="other (exemption)"),"Tax exemption/waiver/suspension","Other"))) -> 6 | AU5: =IF(A5<>A4,1,0) -> 0 | AV5: 1
A6: Afghanistan | B6: 7 | C6: 30 | D6: A sovereign guarantee of Lek 15 billion to provide loans for working capital for the tourism sector as well as active processing exporting companies. The government will bear the interest costs. | E6: 2 | F6: 1 | G6: 1 | H6: 1 | I6: 1 | J6: 2 | K6: 1 | L6: -2 | M6: 1 | N6: AFG | O6: South Asia | P6: IDA | Q6: Low Income | R6: 0 | S6: -1.89 | T6: -2.16 | U6: 8.21 | V6: =IF(E6>0,1,IF(E6<0,0,-1)) -> 1 | W6: =IF(F6>0,1,IF(F6<0,0,-1)) -> 1 | X6: =IF(G6>0,1,IF(G6<0,0,-1)) -> 1 | Y6: =IF(H6>0,1,IF(H6<0,0,-1)) -> 1 | Z6: =IF(I6>0,1,IF(I6<0,0,-1)) -> 1 | AA6: =IF(J6>0,1,IF(J6<0,0,-1)) -> 1 | AB6: =IF(K6>0,1,IF(K6<0,0,-1)) -> 1 | AC6: =IF(L6>0,1,IF(L6<0,0,-1)) -> 0 | AD6: =IF(M6>0,1,IF(M6<0,0,-1)) -> 1 | AE6: All Regions | AF6: All Income Levels | AG6: 1 | AH6: 0 | AI6: 0 | AJ6: 1 | AK6: All Countries | AL6: =IF(OR(B6="other",B6="international",B6="Transfers",B6="expenditure"),1,0) -> 0 | AM6: =IF(AND(INDIRECT(AN6)='Sample Select backend'!$C$2,INDIRECT(AO6)=1,INDIRECT(AP6)='Sample Select backend'!$F$2,INDIRECT(AQ6)=1,INDIRECT(AR6)='Sample Select backend'!$M$2),1,0) -> 0 | AN6: =_xlfn.CONCAT('Sample Select backend'!$C$4,ROW(AN6)) -> AE6 | AO6: =_xlfn.CONCAT('Sample Select backend'!$J$2,ROW(AO6)) -> AJ6 | AP6: =_xlfn.CONCAT('Sample Select backend'!$F$4,ROW(AP6)) -> AF6 | AQ6: =_xlfn.CONCAT('Sample Select backend'!$I$10,ROW(AQ6)) -> R6 | AR6: =_xlfn.CONCAT('Sample Select backend'!$M$4,ROW(AR6)) -> AK6 | AS6: =A6 -> Afghanistan | AT6: =IF(ISNUMBER(C6),C6,IF(OR(C6="general",C6="23;general"),"General",IF(OR(C6="exemption",C6="other (exemption)"),"Tax exemption/waiver/suspension","Other"))) -> 30 | AU6: =IF(A6<>A5,1,0) -> 0 | AV6: 1
A7: Afghanistan | B7: 6 | C7: 25 | D7: One-off transfer of Lk40,000 to employees of small businesses affected by the pandemic, employees of large businesses laid off due to the pandemic, and employees in the tourism sector. | E7: 1 | F7: 1 | G7: 1 | H7: -1 | I7: 2 | J7: 1 | K7: 1 | L7: -2 | M7: 1 | N7: AFG | O7: South Asia | P7: IDA | Q7: Low Income | R7: 0 | S7: -1.89 | T7: -2.16 | U7: 8.21 | V7: =IF(E7>0,1,IF(E7<0,0,-1)) -> 1 | W7: =IF(F7>0,1,IF(F7<0,0,-1)) -> 1 | X7: =IF(G7>0,1,IF(G7<0,0,-1)) -> 1 | Y7: =IF(H7>0,1,IF(H7<0,0,-1)) -> 0 | Z7: =IF(I7>0,1,IF(I7<0,0,-1)) -> 1 | AA7: =IF(J7>0,1,IF(J7<0,0,-1)) -> 1 | AB7: =IF(K7>0,1,IF(K7<0,0,-1)) -> 1 | AC7: =IF(L7>0,1,IF(L7<0,0,-1)) -> 0 | AD7: =IF(M7>0,1,IF(M7<0,0,-1)) -> 1 | AE7: All Regions | AF7: All Income Levels | AG7: 1 | AH7: 0 | AI7: 0 | AJ7: 1 | AK7: All Countries | AL7: =IF(OR(B7="other",B7="international",B7="Transfers",B7="expenditure"),1,0) -> 0 | AM7: =IF(AND(INDIRECT(AN7)='Sample Select backend'!$C$2,INDIRECT(AO7)=1,INDIRECT(AP7)='Sample Select backend'!$F$2,INDIRECT(AQ7)=1,INDIRECT(AR7)='Sample Select backend'!$M$2),1,0) -> 0 | AN7: =_xlfn.CONCAT('Sample Select backend'!$C$4,ROW(AN7)) -> AE7 | AO7: =_xlfn.CONCAT('Sample Select backend'!$J$2,ROW(AO7)) -> AJ7 | AP7: =_xlfn.CONCAT('Sample Select backend'!$F$4,ROW(AP7)) -> AF7 | AQ7: =_xlfn.CONCAT('Sample Select backend'!$I$10,ROW(AQ7)) -> R7 | AR7: =_xlfn.CONCAT('Sample Select backend'!$M$4,ROW(AR7)) -> AK7 | AS7: =A7 -> Afghanistan | AT7: =IF(ISNUMBER(C7),C7,IF(OR(C7="general",C7="23;general"),"General",IF(OR(C7="exemption",C7="other (exemption)"),"Tax exemption/waiver/suspension","Other"))) -> 25 | AU7: =IF(A7<>A6,1,0) -> 0 | AV7: 1
A8: Afghanistan | B8: 1 | C8: 5 | D8: Deadline extension for filing tax returns by two months, until May 20 for business taxpayers. | E8: -2 | F8: 1 | G8: 2 | H8: 1 | I8: 1 | J8: 1 | K8: 1 | L8: 1 | M8: 1 | N8: AFG | O8: South Asia | P8: IDA | Q8: Low Income | R8: 0 | S8: -1.89 | T8: -2.16 | U8: 8.21 | V8: =IF(E8>0,1,IF(E8<0,0,-1)) -> 0 | W8: =IF(F8>0,1,IF(F8<0,0,-1)) -> 1 | X8: =IF(G8>0,1,IF(G8<0,0,-1)) -> 1 | Y8: =IF(H8>0,1,IF(H8<0,0,-1)) -> 1 | Z8: =IF(I8>0,1,IF(I8<0,0,-1)) -> 1 | AA8: =IF(J8>0,1,IF(J8<0,0,-1)) -> 1 | AB8: =IF(K8>0,1,IF(K8<0,0,-1)) -> 1 | AC8: =IF(L8>0,1,IF(L8<0,0,-1)) -> 1 | AD8: =IF(M8>0,1,IF(M8<0,0,-1)) -> 1 | AE8: All Regions | AF8: All Income Levels | AG8: 1 | AH8: 0 | AI8: 0 | AJ8: 1 | AK8: All Countries | AL8: =IF(OR(B8="other",B8="international",B8="Transfers",B8="expenditure"),1,0) -> 0 | AM8: =IF(AND(INDIRECT(AN8)='Sample Select backend'!$C$2,INDIRECT(AO8)=1,INDIRECT(AP8)='Sample Select backend'!$F$2,INDIRECT(AQ8)=1,INDIRECT(AR8)='Sample Select backend'!$M$2),1,0) -> 0 | AN8: =_xlfn.CONCAT('Sample Select backend'!$C$4,ROW(AN8)) -> AE8 | AO8: =_xlfn.CONCAT('Sample Select backend'!$J$2,ROW(AO8)) -> AJ8 | AP8: =_xlfn.CONCAT('Sample Select backend'!$F$4,ROW(AP8)) -> AF8 | AQ8: =_xlfn.CONCAT('Sample Select backend'!$I$10,ROW(AQ8)) -> R8 | AR8: =_xlfn.CONCAT('Sample Select backend'!$M$4,ROW(AR8)) -> AK8 | AS8: =A8 -> Afghanistan | AT8: =IF(ISNUMBER(C8),C8,IF(OR(C8="general",C8="23;general"),"General",IF(OR(C8="exemption",C8="other (exemption)"),"Tax exemption/waiver/suspension","Other"))) -> 5 | AU8: =IF(A8<>A7,1,0) -> 0 | AV8: 1
A9: Afghanistan | B9: 5 | C9: general | D9: The Government has allocated USD 15 million for immediate health emergency response. | E9: 1 | F9: -2 | G9: -2 | H9: -1 | I9: -1 | J9: 1 | K9: 1 | L9: 1 | M9: 1 | N9: AFG | O9: South Asia | P9: IDA | Q9: Low Income | R9: 0 | S9: -1.89 | T9: -2.16 | U9: 8.21 | V9: =IF(E9>0,1,IF(E9<0,0,-1)) -> 1 | W9: =IF(F9>0,1,IF(F9<0,0,-1)) -> 0 | X9: =IF(G9>0,1,IF(G9<0,0,-1)) -> 0 | Y9: =IF(H9>0,1,IF(H9<0,0,-1)) -> 0 | Z9: =IF(I9>0,1,IF(I9<0,0,-1)) -> 0 | AA9: =IF(J9>0,1,IF(J9<0,0,-1)) -> 1 | AB9: =IF(K9>0,1,IF(K9<0,0,-1)) -> 1 | AC9: =IF(L9>0,1,IF(L9<0,0,-1)) -> 1 | AD9: =IF(M9>0,1,IF(M9<0,0,-1)) -> 1 | AE9: All Regions | AF9: All Income Levels | AG9: 1 | AH9: 0 | AI9: 0 | AJ9: 1 | AK9: All Countries | AL9: =IF(OR(B9="other",B9="international",B9="Transfers",B9="expenditure"),1,0) -> 0 | AM9: =IF(AND(INDIRECT(AN9)='Sample Select backend'!$C$2,INDIRECT(AO9)=1,INDIRECT(AP9)='Sample Select backend'!$F$2,INDIRECT(AQ9)=1,INDIRECT(AR9)='Sample Select backend'!$M$2),1,0) -> 0 | AN9: =_xlfn.CONCAT('Sample Select backend'!$C$4,ROW(AN9)) -> AE9 | AO9: =_xlfn.CONCAT('Sample Select backend'!$J$2,ROW(AO9)) -> AJ9 | AP9: =_xlfn.CONCAT('Sample Select backend'!$F$4,ROW(AP9)) -> AF9 | AQ9: =_xlfn.CONCAT('Sample Select backend'!$I$10,ROW(AQ9)) -> R9 | AR9: =_xlfn.CONCAT('Sample Select backend'!$M$4,ROW(AR9)) -> AK9 | AS9: =A9 -> Afghanistan | AT9: =IF(ISNUMBER(C9),C9,IF(OR(C9="general",C9="23;general"),"General",IF(OR(C9="exemption",C9="other (exemption)"),"Tax exemption/waiver/suspension","Other"))) -> General | AU9: =IF(A9<>A8,1,0) -> 0 | AV9: 1
A10: Afghanistan | B10: 6 | C10: 28 | D10: Free bread to about 2.5 million needy and poor people in Kabul. | E10: 1 | F10: 1 | G10: 2 | H10: -1 | I10: 1 | J10: 1 | K10: 1 | L10: 1 | N10: AFG | O10: South Asia | P10: IDA | Q10: Low Income | R10: 0 | S10: -1.89 | T10: -2.16 | U10: 8.21 | V10: =IF(E10>0,1,IF(E10<0,0,-1)) -> 1 | W10: =IF(F10>0,1,IF(F10<0,0,-1)) -> 1 | X10: =IF(G10>0,1,IF(G10<0,0,-1)) -> 1 | Y10: =IF(H10>0,1,IF(H10<0,0,-1)) -> 0 | Z10: =IF(I10>0,1,IF(I10<0,0,-1)) -> 1 | AA10: =IF(J10>0,1,IF(J10<0,0,-1)) -> 1 | AB10: =IF(K10>0,1,IF(K10<0,0,-1)) -> 1 | AC10: =IF(L10>0,1,IF(L10<0,0,-1)) -> 1 | AD10: =IF(M10>0,1,IF(M10<0,0,-1)) -> -1 | AE10: All Regions | AF10: All Income Levels | AG10: 1 | AH10: 0 | AI10: 0 | AJ10: 1 | AK10: All Countries | AL10: =IF(OR(B10="other",B10="international",B10="Transfers",B10="expenditure"),1,0) -> 0 | AM10: =IF(AND(INDIRECT(AN10)='Sample Select backend'!$C$2,INDIRECT(AO10)=1,INDIRECT(AP10)='Sample Select backend'!$F$2,INDIRECT(AQ10)=1,INDIRECT(AR10)='Sample Select backend'!$M$2),1,0) -> 0 | AN10: =_xlfn.CONCAT('Sample Select backend'!$C$4,ROW(AN10)) -> AE10 | AO10: =_xlfn.CONCAT('Sample Select backend'!$J$2,ROW(AO10)) -> AJ10 | AP10: =_xlfn.CONCAT('Sample Select backend'!$F$4,ROW(AP10)) -> AF10 | AQ10: =_xlfn.CONCAT('Sample Select backend'!$I$10,ROW(AQ10)) -> R10 | AR10: =_xlfn.CONCAT('Sample Select backend'!$M$4,ROW(AR10)) -> AK10 | AS10: =A10 -> Afghanistan | AT10: =IF(ISNUMBER(C10),C10,IF(OR(C10="general",C10="23;general"),"General",IF(OR(C10="exemption",C10="other (exemption)"),"Tax exemption/waiver/suspension","Other"))) -> 28 | AU10: =IF(A10<>A9,1,0) -> 0 | AV10: 1
A11: Afghanistan | B11: 6 | C11: 28 | D11: In May, government waived electricity bills of less than AFN 1,000 (USD 13) for family residences in Kabul for two months and paid utility bills of the past two months for 50 percent of households in Kabul. This decision benefited more than 1.5 million Kabul residents. | O11: South Asia | P11: IDA | Q11: Low Income | R11: 0 | S11: -1.89 | T11: -2.16 | U11: 8.21 | V11: -1 | W11: -1 | X11: -1 | Y11: -1 | Z11: -1 | AA11: -1 | AB11: -1 | AC11: -1 | AD11: -1 | AE11: All Regions | AF11: All Income Levels | AG11: 1 | AH11: 0 | AI11: 0 | AJ11: 1 | AK11: All Countries | AL11: =IF(OR(B11="other",B11="international",B11="Transfers",B11="expenditure"),1,0) -> 0 | AM11: =IF(AND(INDIRECT(AN11)='Sample Select backend'!$C$2,INDIRECT(AO11)=1,INDIRECT(AP11)='Sample Select backend'!$F$2,INDIRECT(AQ11)=1,INDIRECT(AR11)='Sample Select backend'!$M$2),1,0) -> 0 | AN11: =_xlfn.CONCAT('Sample Select backend'!$C$4,ROW(AN11)) -> AE11 | AO11: =_xlfn.CONCAT('Sample Select backend'!$J$2,ROW(AO11)) -> AJ11 | AP11: =_xlfn.CONCAT('Sample Select backend'!$F$4,ROW(AP11)) -> AF11 | AQ11: =_xlfn.CONCAT('Sample Select backend'!$I$10,ROW(AQ11)) -> R11 | AR11: =_xlfn.CONCAT('Sample Select backend'!$M$4,ROW(AR11)) -> AK11 | AS11: =A11 -> Afghanistan | AT11: =IF(ISNUMBER(C11),C11,IF(OR(C11="general",C11="23;general"),"General",IF(OR(C11="exemption",C11="other (exemption)"),"Tax exemption/waiver/suspension","Other"))) -> 28 | AU11: =IF(A11<>A10,1,0) -> 0 | AV11: 0
A12: Afghanistan | B12: 2 | C12: 5 | D12: To ease tax compliance, the government extended filing deadlines for the first and second quarter of the fiscal year by 45 days. | O12: South Asia | P12: IDA | Q12: Low Income | R12: 0 | S12: -1.89 | T12: -2.16 | U12: 8.21 | V12: -1 | W12: -1 | X12: -1 | Y12: -1 | Z12: -1 | AA12: -1 | AB12: -1 | AC12: -1 | AD12: -1 | AE12: All Regions | AF12: All Income Levels | AG12: 1 | AH12: 0 | AI12: 0 | AJ12: 1 | AK12: All Countries | AL12: =IF(OR(B12="other",B12="international",B12="Transfers",B12="expenditure"),1,0) -> 0 | AM12: =IF(AND(INDIRECT(AN12)='Sample Select backend'!$C$2,INDIRECT(AO12)=1,INDIRECT(AP12)='Sample Select backend'!$F$2,INDIRECT(AQ12)=1,INDIRECT(AR12)='Sample Select backend'!$M$2),1,0) -> 0 | AN12: =_xlfn.CONCAT('Sample Select backend'!$C$4,ROW(AN12)) -> AE12 | AO12: =_xlfn.CONCAT('Sample Select backend'!$J$2,ROW(AO12)) -> AJ12 | AP12: =_xlfn.CONCAT('Sample Select backend'!$F$4,ROW(AP12)) -> AF12 | AQ12: =_xlfn.CONCAT('Sample Select backend'!$I$10,ROW(AQ12)) -> R12 | AR12: =_xlfn.CONCAT('Sample Select backend'!$M$4,ROW(AR12)) -> AK12 | AS12: =A12 -> Afghanistan | AT12: =IF(ISNUMBER(C12),C12,IF(OR(C12="general",C12="23;general"),"General",IF(OR(C12="exemption",C12="other (exemption)"),"Tax exemption/waiver/suspension","Other"))) -> 5 | AU12: =IF(A12<>A11,1,0) -> 0 | AV12: 0
A13: Afghanistan | B13: 5 | C13: general | D13: Planned health expenditure package amounting to AFN 6.2 billion, including for building hospitals. | O13: South Asia | P13: IDA | Q13: Low Income | R13: 0 | S13: -1.89 | T13: -2.16 | U13: 8.21 | V13: -1 | W13: -1 | X13: -1 | Y13: -1 | Z13: -1 | AA13: -1 | AB13: -1 | AC13: -1 | AD13: -1 | AE13: All Regions | AF13: All Income Levels | AG13: 1 | AH13: 0 | AI13: 0 | AJ13: 1 | AK13: All Countries | AL13: =IF(OR(B13="other",B13="international",B13="Transfers",B13="expenditure"),1,0) -> 0 | AM13: =IF(AND(INDIRECT(AN13)='Sample Select backend'!$C$2,INDIRECT(AO13)=1,INDIRECT(AP13)='Sample Select backend'!$F$2,INDIRECT(AQ13)=1,INDIRECT(AR13)='Sample Select backend'!$M$2),1,0) -> 0 | AN13: =_xlfn.CONCAT('Sample Select backend'!$C$4,ROW(AN13)) -> AE13 | AO13: =_xlfn.CONCAT('Sample Select backend'!$J$2,ROW(AO13)) -> AJ13 | AP13: =_xlfn.CONCAT('Sample Select backend'!$F$4,ROW(AP13)) -> AF13 | AQ13: =_xlfn.CONCAT('Sample Select backend'!$I$10,ROW(AQ13)) -> R13 | AR13: =_xlfn.CONCAT('Sample Select backend'!$M$4,ROW(AR13)) -> AK13 | AS13: =A13 -> Afghanistan | AT13: =IF(ISNUMBER(C13),C13,IF(OR(C13="general",C13="23;general"),"General",IF(OR(C13="exemption",C13="other (exemption)"),"Tax exemption/waiver/suspension","Other"))) -> General | AU13: =IF(A13<>A12,1,0) -> 0 | AV13: 0
A14: Afghanistan | B14: 6 | D14: Planned expenditure of AF 1.7 billion on wheat purchase program | O14: South Asia | P14: IDA | Q14: Low Income | R14: 0 | S14: -1.89 | T14: -2.16 | U14: 8.21 | V14: -1 | W14: -1 | X14: -1 | Y14: -1 | Z14: -1 | AA14: -1 | AB14: -1 | AC14: -1 | AD14: -1 | AE14: All Regions | AF14: All Income Levels | AG14: 1 | AH14: 0 | AI14: 0 | AJ14: 1 | AK14: All Countries | AL14: =IF(OR(B14="other",B14="international",B14="Transfers",B14="expenditure"),1,0) -> 0 | AM14: =IF(AND(INDIRECT(AN14)='Sample Select backend'!$C$2,INDIRECT(AO14)=1,INDIRECT(AP14)='Sample Select backend'!$F$2,INDIRECT(AQ14)=1,INDIRECT(AR14)='Sample Select backend'!$M$2),1,0) -> 0 | AN14: =_xlfn.CONCAT('Sample Select backend'!$C$4,ROW(AN14)) -> AE14 | AO14: =_xlfn.CONCAT('Sample Select backend'!$J$2,ROW(AO14)) -> AJ14 | AP14: =_xlfn.CONCAT('Sample Select backend'!$F$4,ROW(AP14)) -> AF14 | AQ14: =_xlfn.CONCAT('Sample Select backend'!$I$10,ROW(AQ14)) -> R14 | AR14: =_xlfn.CONCAT('Sample Select backend'!$M$4,ROW(AR14)) -> AK14 | AS14: =A14 -> Afghanistan | AT14: =IF(ISNUMBER(C14),C14,IF(OR(C14="general",C14="23;general"),"General",IF(OR(C14="exemption",C14="other (exemption)"),"Tax exemption/waiver/suspension","Other"))) -> Other | AU14: =IF(A14<>A13,1,0) -> 0 | AV14: 0
A15: Afghanistan | B15: 6 | D15: Planned transfers of AFN 2.3 billion to provinces to finance COVID-19 response | O15: South Asia | P15: IDA | Q15: Low Income | R15: 0 | S15: -1.89 | T15: -2.16 | U15: 8.21 | V15: -1 | W15: -1 | X15: -1 | Y15: -1 | Z15: -1 | AA15: -1 | AB15: -1 | AC15: -1 | AD15: -1 | AE15: All Regions | AF15: All Income Levels | AG15: 1 | AH15: 0 | AI15: 0 | AJ15: 1 | AK15: All Countries | AL15: =IF(OR(B15="other",B15="international",B15="Transfers",B15="expenditure"),1,0) -> 0 | AM15: =IF(AND(INDIRECT(AN15)='Sample Select backend'!$C$2,INDIRECT(AO15)=1,INDIRECT(AP15)='Sample Select backend'!$F$2,INDIRECT(AQ15)=1,INDIRECT(AR15)='Sample Select backend'!$M$2),1,0) -> 0 | AN15: =_xlfn.CONCAT('Sample Select backend'!$C$4,ROW(AN15)) -> AE15 | AO15: =_xlfn.CONCAT('Sample Select backend'!$J$2,ROW(AO15)) -> AJ15 | AP15: =_xlfn.CONCAT('Sample Select backend'!$F$4,ROW(AP15)) -> AF15 | AQ15: =_xlfn.CONCAT('Sample Select backend'!$I$10,ROW(AQ15)) -> R15 | AR15: =_xlfn.CONCAT('Sample Select backend'!$M$4,ROW(AR15)) -> AK15 | AS15: =A15 -> Afghanistan | AT15: =IF(ISNUMBER(C15),C15,IF(OR(C15="general",C15="23;general"),"General",IF(OR(C15="exemption",C15="other (exemption)"),"Tax exemption/waiver/suspension","Other"))) -> Other | AU15: =IF(A15<>A14,1,0) -> 0 | AV15: 0
A16: Afghanistan | B16: 6 | D16: Planned agriculture support package of AFN 5.9 billion | O16: South Asia | P16: IDA | Q16: Low Income | R16: 0 | S16: -1.89 | T16: -2.16 | U16: 8.21 | V16: -1 | W16: -1 | X16: -1 | Y16: -1 | Z16: -1 | AA16: -1 | AB16: -1 | AC16: -1 | AD16: -1 | AE16: All Regions | AF16: All Income Levels | AG16: 1 | AH16: 0 | AI16: 0 | AJ16: 1 | AK16: All Countries | AL16: =IF(OR(B16="other",B16="international",B16="Transfers",B16="expenditure"),1,0) -> 0 | AM16: =IF(AND(INDIRECT(AN16)='Sample Select backend'!$C$2,INDIRECT(AO16)=1,INDIRECT(AP16)='Sample Select backend'!$F$2,INDIRECT(AQ16)=1,INDIRECT(AR16)='Sample Select backend'!$M$2),1,0) -> 0 | AN16: =_xlfn.CONCAT('Sample Select backend'!$C$4,ROW(AN16)) -> AE16 | AO16: =_xlfn.CONCAT('Sample Select backend'!$J$2,ROW(AO16)) -> AJ16 | AP16: =_xlfn.CONCAT('Sample Select backend'!$F$4,ROW(AP16)) -> AF16 | AQ16: =_xlfn.CONCAT('Sample Select backend'!$I$10,ROW(AQ16)) -> R16 | AR16: =_xlfn.CONCAT('Sample Select backend'!$M$4,ROW(AR16)) -> AK16 | AS16: =A16 -> Afghanistan | AT16: =IF(ISNUMBER(C16),C16,IF(OR(C16="general",C16="23;general"),"General",IF(OR(C16="exemption",C16="other (exemption)"),"Tax exemption/waiver/suspension","Other"))) -> Other | AU16: =IF(A16<>A15,1,0) -> 0 | AV16: 0
A17: Afghanistan | B17: 6 | D17: Planned expenditure of AF 1 billion to support short-term jobs | O17: South Asia | P17: IDA | Q17: Low Income | R17: 0 | S17: -1.89 | T17: -2.16 | U17: 8.21 | V17: -1 | W17: -1 | X17: -1 | Y17: -1 | Z17: -1 | AA17: -1 | AB17: -1 | AC17: -1 | AD17: -1 | AE17: All Regions | AF17: All Income Levels | AG17: 1 | AH17: 0 | AI17: 0 | AJ17: 1 | AK17: All Countries | AL17: =IF(OR(B17="other",B17="international",B17="Transfers",B17="expenditure"),1,0) -> 0 | AM17: =IF(AND(INDIRECT(AN17)='Sample Select backend'!$C$2,INDIRECT(AO17)=1,INDIRECT(AP17)='Sample Select backend'!$F$2,INDIRECT(AQ17)=1,INDIRECT(AR17)='Sample Select backend'!$M$2),1,0) -> 0 | AN17: =_xlfn.CONCAT('Sample Select backend'!$C$4,ROW(AN17)) -> AE17 | AO17: =_xlfn.CONCAT('Sample Select backend'!$J$2,ROW(AO17)) -> AJ17 | AP17: =_xlfn.CONCAT('Sample Select backend'!$F$4,ROW(AP17)) -> AF17 | AQ17: =_xlfn.CONCAT('Sample Select backend'!$I$10,ROW(AQ17)) -> R17 | AR17: =_xlfn.CONCAT('Sample Select backend'!$M$4,ROW(AR17)) -> AK17 | AS17: =A17 -> Afghanistan | AT17: =IF(ISNUMBER(C17),C17,IF(OR(C17="general",C17="23;general"),"General",IF(OR(C17="exemption",C17="other (exemption)"),"Tax exemption/waiver/suspension","Other"))) -> Other | AU17: =IF(A17<>A16,1,0) -> 0 | AV17: 0
A18: Albania | B18: 6 | C18: 25/27 | D18: Self-employed families will receive a special benefit equivalent to a state-set monthly salary. | E18: -1 | F18: 1 | G18: -2 | H18: -1 | I18: -2 | J18: -2 | K18: 1 | L18: -2 | M18: 1 | N18: ALB | O18: Europe & Central Asia | P18: IBRD | Q18: Upper Middle Income | R18: 0 | S18: -4.74 | T18: -4.77 | U18: 80.04 | V18: =IF(E18>0,1,IF(E18<0,0,-1)) -> 0 | W18: =IF(F18>0,1,IF(F18<0,0,-1)) -> 1 | X18: =IF(G18>0,1,IF(G18<0,0,-1)) -> 0 | Y18: =IF(H18>0,1,IF(H18<0,0,-1)) -> 0 | Z18: =IF(I18>0,1,IF(I18<0,0,-1)) -> 0 | AA18: =IF(J18>0,1,IF(J18<0,0,-1)) -> 0 | AB18: =IF(K18>0,1,IF(K18<0,0,-1)) -> 1 | AC18: =IF(L18>0,1,IF(L18<0,0,-1)) -> 0 | AD18: =IF(M18>0,1,IF(M18<0,0,-1)) -> 1 | AE18: All Regions | AF18: All Income Levels | AG18: 0 | AH18: 1 | AI18: 0 | AJ18: 1 | AK18: All Countries | AL18: =IF(OR(B18="other",B18="international",B18="Transfers",B18="expenditure"),1,0) -> 0 | AM18: =IF(AND(INDIRECT(AN18)='Sample Select backend'!$C$2,INDIRECT(AO18)=1,INDIRECT(AP18)='Sample Select backend'!$F$2,INDIRECT(AQ18)=1,INDIRECT(AR18)='Sample Select backend'!$M$2),1,0) -> 0 | AN18: =_xlfn.CONCAT('Sample Select backend'!$C$4,ROW(AN18)) -> AE18 | AO18: =_xlfn.CONCAT('Sample Select backend'!$J$2,ROW(AO18)) -> AJ18 | AP18: =_xlfn.CONCAT('Sample Select backend'!$F$4,ROW(AP18)) -> AF18 | AQ18: =_xlfn.CONCAT('Sample Select backend'!$I$10,ROW(AQ18)) -> R18 | AR18: =_xlfn.CONCAT('Sample Select backend'!$M$4,ROW(AR18)) -> AK18 | AS18: =A18 -> Albania | AT18: =IF(ISNUMBER(C18),C18,IF(OR(C18="general",C18="23;general"),"General",IF(OR(C18="exemption",C18="other (exemption)"),"Tax exemption/waiver/suspension","Other"))) -> Other | AU18: =IF(A18<>A17,1,0) -> 1 | AV18: 1
A19: Albania | B19: 1 | C19: other (exemption) | D19: for taxpayers with an annual turnover up to ALL 14 million it is removed | E19: 2 | F19: 2 | G19: -2 | H19: -1 | I19: -2 | J19: 2 | K19: 1 | L19: 2 | M19: 1 | N19: ALB | O19: Europe & Central Asia | P19: IBRD | Q19: Upper Middle Income | R19: 0 | S19: -4.74 | T19: -4.77 | U19: 80.04 | V19: =IF(E19>0,1,IF(E19<0,0,-1)) -> 1 | W19: =IF(F19>0,1,IF(F19<0,0,-1)) -> 1 | X19: =IF(G19>0,1,IF(G19<0,0,-1)) -> 0 | Y19: =IF(H19>0,1,IF(H19<0,0,-1)) -> 0 | Z19: =IF(I19>0,1,IF(I19<0,0,-1)) -> 0 | AA19: =IF(J19>0,1,IF(J19<0,0,-1)) -> 1 | AB19: =IF(K19>0,1,IF(K19<0,0,-1)) -> 1 | AC19: =IF(L19>0,1,IF(L19<0,0,-1)) -> 1 | AD19: =IF(M19>0,1,IF(M19<0,0,-1)) -> 1 | AE19: All Regions | AF19: All Income Levels | AG19: 0 | AH19: 1 | AI19: 0 | AJ19: 1 | AK19: All Countries | AL19: =IF(OR(B19="other",B19="international",B19="Transfers",B19="expenditure"),1,0) -> 0 | AM19: =IF(AND(INDIRECT(AN19)='Sample Select backend'!$C$2,INDIRECT(AO19)=1,INDIRECT(AP19)='Sample Select backend'!$F$2,INDIRECT(AQ19)=1,INDIRECT(AR19)='Sample Select backend'!$M$2),1,0) -> 0 | AN19: =_xlfn.CONCAT('Sample Select backend'!$C$4,ROW(AN19)) -> AE19 | AO19: =_xlfn.CONCAT('Sample Select backend'!$J$2,ROW(AO19)) -> AJ19 | AP19: =_xlfn.CONCAT('Sample Select backend'!$F$4,ROW(AP19)) -> AF19 | AQ19: =_xlfn.CONCAT('Sample Select backend'!$I$10,ROW(AQ19)) -> R19 | AR19: =_xlfn.CONCAT('Sample Select backend'!$M$4,ROW(AR19)) -> AK19 | AS19: =A19 -> Albania | AT19: =IF(ISNUMBER(C19),C19,IF(OR(C19="general",C19="23;general"),"General",IF(OR(C19="exemption",C19="other (exemption)"),"Tax exemption/waiver/suspension","Other"))) -> Tax exemption/waiver/suspension | AU19: =IF(A19<>A18,1,0) -> 0 | AV19: 1
A20: Albania | B20: 5 | C20: general | D20: Additional funding for health sector in the amount of Lk 3.5 billion. | E20: 1 | F20: -2 | G20: -2 | H20: -1 | I20: -1 | J20: 1 | K20: 1 | L20: 1 | M20: 1 | N20: ALB | O20: Europe & Central Asia | P20: IBRD | Q20: Upper Middle Income | R20: 0 | S20: -4.74 | T20: -4.77 | U20: 80.04 | V20: =IF(E20>0,1,IF(E20<0,0,-1)) -> 1 | W20: =IF(F20>0,1,IF(F20<0,0,-1)) -> 0 | X20: =IF(G20>0,1,IF(G20<0,0,-1)) -> 0 | Y20: =IF(H20>0,1,IF(H20<0,0,-1)) -> 0 | Z20: =IF(I20>0,1,IF(I20<0,0,-1)) -> 0 | AA20: =IF(J20>0,1,IF(J20<0,0,-1)) -> 1 | AB20: =IF(K20>0,1,IF(K20<0,0,-1)) -> 1 | AC20: =IF(L20>0,1,IF(L20<0,0,-1)) -> 1 | AD20: =IF(M20>0,1,IF(M20<0,0,-1)) -> 1 | AE20: All Regions | AF20: All Income Levels | AG20: 0 | AH20: 1 | AI20: 0 | AJ20: 1 | AK20: All Countries | AL20: =IF(OR(B20="other",B20="international",B20="Transfers",B20="expenditure"),1,0) -> 0 | AM20: =IF(AND(INDIRECT(AN20)='Sample Select backend'!$C$2,INDIRECT(AO20)=1,INDIRECT(AP20)='Sample Select backend'!$F$2,INDIRECT(AQ20)=1,INDIRECT(AR20)='Sample Select backend'!$M$2),1,0) -> 0 | AN20: =_xlfn.CONCAT('Sample Select backend'!$C$4,ROW(AN20)) -> AE20 | AO20: =_xlfn.CONCAT('Sample Select backend'!$J$2,ROW(AO20)) -> AJ20 | AP20: =_xlfn.CONCAT('Sample Select backend'!$F$4,ROW(AP20)) -> AF20 | AQ20: =_xlfn.CONCAT('Sample Select backend'!$I$10,ROW(AQ20)) -> R20 | AR20: =_xlfn.CONCAT('Sample Select backend'!$M$4,ROW(AR20)) -> AK20 | AS20: =A20 -> Albania | AT20: =IF(ISNUMBER(C20),C20,IF(OR(C20="general",C20="23;general"),"General",IF(OR(C20="exemption",C20="other (exemption)"),"Tax exemption/waiver/suspension","Other"))) -> General | AU20: =IF(A20<>A19,1,0) -> 0 | AV20: 1
A21: Albania | B21: 6 | C21: 27 | D21: Increase in pensions. | E21: 1 | F21: 1 | G21: 1 | H21: -1 | I21: 1 | J21: -2 | K21: 1 | L21: 1 | M21: 1 | N21: ALB | O21: Europe & Central Asia | P21: IBRD | Q21: Upper Middle Income | R21: 0 | S21: -4.74 | T21: -4.77 | U21: 80.04 | V21: =IF(E21>0,1,IF(E21<0,0,-1)) -> 1 | W21: =IF(F21>0,1,IF(F21<0,0,-1)) -> 1 | X21: =IF(G21>0,1,IF(G21<0,0,-1)) -> 1 | Y21: =IF(H21>0,1,IF(H21<0,0,-1)) -> 0 | Z21: =IF(I21>0,1,IF(I21<0,0,-1)) -> 1 | AA21: =IF(J21>0,1,IF(J21<0,0,-1)) -> 0 | AB21: =IF(K21>0,1,IF(K21<0,0,-1)) -> 1 | AC21: =IF(L21>0,1,IF(L21<0,0,-1)) -> 1 | AD21: =IF(M21>0,1,IF(M21<0,0,-1)) -> 1 | AE21: All Regions | AF21: All Income Levels | AG21: 0 | AH21: 1 | AI21: 0 | AJ21: 1 | AK21: All Countries | AL21: =IF(OR(B21="other",B21="international",B21="Transfers",B21="expenditure"),1,0) -> 0 | AM21: =IF(AND(INDIRECT(AN21)='Sample Select backend'!$C$2,INDIRECT(AO21)=1,INDIRECT(AP21)='Sample Select backend'!$F$2,INDIRECT(AQ21)=1,INDIRECT(AR21)='Sample Select backend'!$M$2),1,0) -> 0 | AN21: =_xlfn.CONCAT('Sample Select backend'!$C$4,ROW(AN21)) -> AE21 | AO21: =_xlfn.CONCAT('Sample Select backend'!$J$2,ROW(AO21)) -> AJ21 | AP21: =_xlfn.CONCAT('Sample Select backend'!$F$4,ROW(AP21)) -> AF21 | AQ21: =_xlfn.CONCAT('Sample Select backend'!$I$10,ROW(AQ21)) -> R21 | AR21: =_xlfn.CONCAT('Sample Select backend'!$M$4,ROW(AR21)) -> AK21 | AS21: =A21 -> Albania | AT21: =IF(ISNUMBER(C21),C21,IF(OR(C21="general",C21="23;general"),"General",IF(OR(C21="exemption",C21="other (exemption)"),"Tax exemption/waiver/suspension","Other"))) -> 27 | AU21: =IF(A21<>A20,1,0) -> 0 | AV21: 1
A22: Albania | B22: 1 | C22: 5 | D22: Extension of deadline to submit CIT financial statements to July 31, 2020 | E22: -2 | F22: 2 | G22: 2 | H22: 1 | I22: 2 | J22: 1 | K22: 1 | L22: 1 | M22: 1 | N22: ALB | O22: Europe & Central Asia | P22: IBRD | Q22: Upper Middle Income | R22: 0 | S22: -4.74 | T22: -4.77 | U22: 80.04 | V22: =IF(E22>0,1,IF(E22<0,0,-1)) -> 0 | W22: =IF(F22>0,1,IF(F22<0,0,-1)) -> 1 | X22: =IF(G22>0,1,IF(G22<0,0,-1)) -> 1 | Y22: =IF(H22>0,1,IF(H22<0,0,-1)) -> 1 | Z22: =IF(I22>0,1,IF(I22<0,0,-1)) -> 1 | AA22: =IF(J22>0,1,IF(J22<0,0,-1)) -> 1 | AB22: =IF(K22>0,1,IF(K22<0,0,-1)) -> 1 | AC22: =IF(L22>0,1,IF(L22<0,0,-1)) -> 1 | AD22: =IF(M22>0,1,IF(M22<0,0,-1)) -> 1 | AE22: All Regions | AF22: All Income Levels | AG22: 0 | AH22: 1 | AI22: 0 | AJ22: 1 | AK22: All Countries | AL22: =IF(OR(B22="other",B22="international",B22="Transfers",B22="expenditure"),1,0) -> 0 | AM22: =IF(AND(INDIRECT(AN22)='Sample Select backend'!$C$2,INDIRECT(AO22)=1,INDIRECT(AP22)='Sample Select backend'!$F$2,INDIRECT(AQ22)=1,INDIRECT(AR22)='Sample Select backend'!$M$2),1,0) -> 0 | AN22: =_xlfn.CONCAT('Sample Select backend'!$C$4,ROW(AN22)) -> AE22 | AO22: =_xlfn.CONCAT('Sample Select backend'!$J$2,ROW(AO22)) -> AJ22 | AP22: =_xlfn.CONCAT('Sample Select backend'!$F$4,ROW(AP22)) -> AF22 | AQ22: =_xlfn.CONCAT('Sample Select backend'!$I$10,ROW(AQ22)) -> R22 | AR22: =_xlfn.CONCAT('Sample Select backend'!$M$4,ROW(AR22)) -> AK22 | AS22: =A22 -> Albania | AT22: =IF(ISNUMBER(C22),C22,IF(OR(C22="general",C22="23;general"),"General",IF(OR(C22="exemption",C22="other (exemption)"),"Tax exemption/waiver/suspension","Other"))) -> 5 | AU22: =IF(A22<>A21,1,0) -> 0 | AV22: 1
A23: Albania | B23: 6 | C23: 26 | D23: Unemployment benefits will be doubled. | E23: 1 | F23: 1 | G23: 2 | H23: -1 | I23: -2 | J23: -2 | K23: 1 | L23: 1 | M23: 1 | N23: ALB | O23: Europe & Central Asia | P23: IBRD | Q23: Upper Middle Income | R23: 0 | S23: -4.74 | T23: -4.77 | U23: 80.04 | V23: =IF(E23>0,1,IF(E23<0,0,-1)) -> 1 | W23: =IF(F23>0,1,IF(F23<0,0,-1)) -> 1 | X23: =IF(G23>0,1,IF(G23<0,0,-1)) -> 1 | Y23: =IF(H23>0,1,IF(H23<0,0,-1)) -> 0 | Z23: =IF(I23>0,1,IF(I23<0,0,-1)) -> 0 | AA23: =IF(J23>0,1,IF(J23<0,0,-1)) -> 0 | AB23: =IF(K23>0,1,IF(K23<0,0,-1)) -> 1 | AC23: =IF(L23>0,1,IF(L23<0,0,-1)) -> 1 | AD23: =IF(M23>0,1,IF(M23<0,0,-1)) -> 1 | AE23: All Regions | AF23: All Income Levels | AG23: 0 | AH23: 1 | AI23: 0 | AJ23: 1 | AK23: All Countries | AL23: =IF(OR(B23="other",B23="international",B23="Transfers",B23="expenditure"),1,0) -> 0 | AM23: =IF(AND(INDIRECT(AN23)='Sample Select backend'!$C$2,INDIRECT(AO23)=1,INDIRECT(AP23)='Sample Select backend'!$F$2,INDIRECT(AQ23)=1,INDIRECT(AR23)='Sample Select backend'!$M$2),1,0) -> 0 | AN23: =_xlfn.CONCAT('Sample Select backend'!$C$4,ROW(AN23)) -> AE23 | AO23: =_xlfn.CONCAT('Sample Select backend'!$J$2,ROW(AO23)) -> AJ23 | AP23: =_xlfn.CONCAT('Sample Select backend'!$F$4,ROW(AP23)) -> AF23 | AQ23: =_xlfn.CONCAT('Sample Select backend'!$I$10,ROW(AQ23)) -> R23 | AR23: =_xlfn.CONCAT('Sample Select backend'!$M$4,ROW(AR23)) -> AK23 | AS23: =A23 -> Albania | AT23: =IF(ISNUMBER(C23),C23,IF(OR(C23="general",C23="23;general"),"General",IF(OR(C23="exemption",C23="other (exemption)"),"Tax exemption/waiver/suspension","Other"))) -> 26 | AU23: =IF(A23<>A22,1,0) -> 0 | AV23: 1
A24: Albania | B24: 1 | C24: 6 | D24: for taxpayers engaged in tourism, inward processing regime and call-centers it is postponed to April-December 2021 | E24: 2 | F24: 2 | G24: 2 | H24: 1 | I24: 2 | J24: 2 | K24: 1 | L24: 1 | M24: 1 | N24: ALB | O24: Europe & Central Asia | P24: IBRD | Q24: Upper Middle Income | R24: 0 | S24: -4.74 | T24: -4.77 | U24: 80.04 | V24: =IF(E24>0,1,IF(E24<0,0,-1)) -> 1 | W24: =IF(F24>0,1,IF(F24<0,0,-1)) -> 1 | X24: =IF(G24>0,1,IF(G24<0,0,-1)) -> 1 | Y24: =IF(H24>0,1,IF(H24<0,0,-1)) -> 1 | Z24: =IF(I24>0,1,IF(I24<0,0,-1)) -> 1 | AA24: =IF(J24>0,1,IF(J24<0,0,-1)) -> 1 | AB24: =IF(K24>0,1,IF(K24<0,0,-1)) -> 1 | AC24: =IF(L24>0,1,IF(L24<0,0,-1)) -> 1 | AD24: =IF(M24>0,1,IF(M24<0,0,-1)) -> 1 | AE24: All Regions | AF24: All Income Levels | AG24: 0 | AH24: 1 | AI24: 0 | AJ24: 1 | AK24: All Countries | AL24: =IF(OR(B24="other",B24="international",B24="Transfers",B24="expenditure"),1,0) -> 0 | AM24: =IF(AND(INDIRECT(AN24)='Sample Select backend'!$C$2,INDIRECT(AO24)=1,INDIRECT(AP24)='Sample Select backend'!$F$2,INDIRECT(AQ24)=1,INDIRECT(AR24)='Sample Select backend'!$M$2),1,0) -> 0 | AN24: =_xlfn.CONCAT('Sample Select backend'!$C$4,ROW(AN24)) -> AE24 | AO24: =_xlfn.CONCAT('Sample Select backend'!$J$2,ROW(AO24)) -> AJ24 | AP24: =_xlfn.CONCAT('Sample Select backend'!$F$4,ROW(AP24)) -> AF24 | AQ24: =_xlfn.CONCAT('Sample Select backend'!$I$10,ROW(AQ24)) -> R24 | AR24: =_xlfn.CONCAT('Sample Select backend'!$M$4,ROW(AR24)) -> AK24 | AS24: =A24 -> Albania | AT24: =IF(ISNUMBER(C24),C24,IF(OR(C24="general",C24="23;general"),"General",IF(OR(C24="exemption",C24="other (exemption)"),"Tax exemption/waiver/suspension","Other"))) -> 6 | AU24: =IF(A24<>A23,1,0) -> 0 | AV24: 1
A25: Albania | B25: 1 | C25: 6 | D25: for taxpayers with a turnover of more than that, it is postponed to April-September 2021 | E25: -2 | F25: 2 | G25: 2 | H25: 1 | I25: 2 | J25: 2 | K25: 1 | L25: 1 | M25: 1 | N25: ALB | O25: Europe & Central Asia | P25: IBRD | Q25: Upper Middle Income | R25: 0 | S25: -4.74 | T25: -4.77 | U25: 80.04 | V25: =IF(E25>0,1,IF(E25<0,0,-1)) -> 0 | W25: =IF(F25>0,1,IF(F25<0,0,-1)) -> 1 | X25: =IF(G25>0,1,IF(G25<0,0,-1)) -> 1 | Y25: =IF(H25>0,1,IF(H25<0,0,-1)) -> 1 | Z25: =IF(I25>0,1,IF(I25<0,0,-1)) -> 1 | AA25: =IF(J25>0,1,IF(J25<0,0,-1)) -> 1 | AB25: =IF(K25>0,1,IF(K25<0,0,-1)) -> 1 | AC25: =IF(L25>0,1,IF(L25<0,0,-1)) -> 1 | AD25: =IF(M25>0,1,IF(M25<0,0,-1)) -> 1 | AE25: All Regions | AF25: All Income Levels | AG25: 0 | AH25: 1 | AI25: 0 | AJ25: 1 | AK25: All Countries | AL25: =IF(OR(B25="other",B25="international",B25="Transfers",B25="expenditure"),1,0) -> 0 | AM25: =IF(AND(INDIRECT(AN25)='Sample Select backend'!$C$2,INDIRECT(AO25)=1,INDIRECT(AP25)='Sample Select backend'!$F$2,INDIRECT(AQ25)=1,INDIRECT(AR25)='Sample Select backend'!$M$2),1,0) -> 0 | AN25: =_xlfn.CONCAT('Sample Select backend'!$C$4,ROW(AN25)) -> AE25 | AO25: =_xlfn.CONCAT('Sample Select backend'!$J$2,ROW(AO25)) -> AJ25 | AP25: =_xlfn.CONCAT('Sample Select backend'!$F$4,ROW(AP25)) -> AF25 | AQ25: =_xlfn.CONCAT('Sample Select backend'!$I$10,ROW(AQ25)) -> R25 | AR25: =_xlfn.CONCAT('Sample Select backend'!$M$4,ROW(AR25)) -> AK25 | AS25: =A25 -> Albania | AT25: =IF(ISNUMBER(C25),C25,IF(OR(C25="general",C25="23;general"),"General",IF(OR(C25="exemption",C25="other (exemption)"),"Tax exemption/waiver/suspension","Other"))) -> 6 | AU25: =IF(A25<>A24,1,0) -> 0 | AV25: 1
A26: Albania | B26: 6 | C26: 28 | D26: Postponement for the property/premises/house rent payments for two months (April and May) for individuals/business (up to 14 million ALL turnover)/students. | E26: 2 | F26: 1 | G26: 2 | H26: 1 | I26: 2 | J26: 1 | K26: 1 | L26: 1 | M26: 1 | N26: ALB | O26: Europe & Central Asia | P26: IBRD | Q26: Upper Middle Income | R26: 0 | S26: -4.74 | T26: -4.77 | U26: 80.04 | V26: =IF(E26>0,1,IF(E26<0,0,-1)) -> 1 | W26: =IF(F26>0,1,IF(F26<0,0,-1)) -> 1 | X26: =IF(G26>0,1,IF(G26<0,0,-1)) -> 1 | Y26: =IF(H26>0,1,IF(H26<0,0,-1)) -> 1 | Z26: =IF(I26>0,1,IF(I26<0,0,-1)) -> 1 | AA26: =IF(J26>0,1,IF(J26<0,0,-1)) -> 1 | AB26: =IF(K26>0,1,IF(K26<0,0,-1)) -> 1 | AC26: =IF(L26>0,1,IF(L26<0,0,-1)) -> 1 | AD26: =IF(M26>0,1,IF(M26<0,0,-1)) -> 1 | AE26: All Regions | AF26: All Income Levels | AG26: 0 | AH26: 1 | AI26: 0 | AJ26: 1 | AK26: All Countries | AL26: =IF(OR(B26="other",B26="international",B26="Transfers",B26="expenditure"),1,0) -> 0 | AM26: =IF(AND(INDIRECT(AN26)='Sample Select backend'!$C$2,INDIRECT(AO26)=1,INDIRECT(AP26)='Sample Select backend'!$F$2,INDIRECT(AQ26)=1,INDIRECT(AR26)='Sample Select backend'!$M$2),1,0) -> 0 | AN26: =_xlfn.CONCAT('Sample Select backend'!$C$4,ROW(AN26)) -> AE26 | AO26: =_xlfn.CONCAT('Sample Select backend'!$J$2,ROW(AO26)) -> AJ26 | AP26: =_xlfn.CONCAT('Sample Select backend'!$F$4,ROW(AP26)) -> AF26 | AQ26: =_xlfn.CONCAT('Sample Select backend'!$I$10,ROW(AQ26)) -> R26 | AR26: =_xlfn.CONCAT('Sample Select backend'!$M$4,ROW(AR26)) -> AK26 | AS26: =A26 -> Albania | AT26: =IF(ISNUMBER(C26),C26,IF(OR(C26="general",C26="23;general"),"General",IF(OR(C26="exemption",C26="other (exemption)"),"Tax exemption/waiver/suspension","Other"))) -> 28 | AU26: =IF(A26<>A25,1,0) -> 0 | AV26: 1
A27: Albania | B27: 1 | C27: 6 | D27: Deferral of profit tax installment payments for small companies (announced). | E27: 2 | F27: 2 | G27: 2 | H27: 1 | I27: 2 | J27: 1 | K27: 1 | L27: 1 | M27: 1 | N27: ALB | O27: Europe & Central Asia | P27: IBRD | Q27: Upper Middle Income | R27: 0 | S27: -4.74 | T27: -4.77 | U27: 80.04 | V27: =IF(E27>0,1,IF(E27<0,0,-1)) -> 1 | W27: =IF(F27>0,1,IF(F27<0,0,-1)) -> 1 | X27: =IF(G27>0,1,IF(G27<0,0,-1)) -> 1 | Y27: =IF(H27>0,1,IF(H27<0,0,-1)) -> 1 | Z27: =IF(I27>0,1,IF(I27<0,0,-1)) -> 1 | AA27: =IF(J27>0,1,IF(J27<0,0,-1)) -> 1 | AB27: =IF(K27>0,1,IF(K27<0,0,-1)) -> 1 | AC27: =IF(L27>0,1,IF(L27<0,0,-1)) -> 1 | AD27: =IF(M27>0,1,IF(M27<0,0,-1)) -> 1 | AE27: All Regions | AF27: All Income Levels | AG27: 0 | AH27: 1 | AI27: 0 | AJ27: 1 | AK27: All Countries | AL27: =IF(OR(B27="other",B27="international",B27="Transfers",B27="expenditure"),1,0) -> 0 | AM27: =IF(AND(INDIRECT(AN27)='Sample Select backend'!$C$2,INDIRECT(AO27)=1,INDIRECT(AP27)='Sample Select backend'!$F$2,INDIRECT(AQ27)=1,INDIRECT(AR27)='Sample Select backend'!$M$2),1,0) -> 0 | AN27: =_xlfn.CONCAT('Sample Select backend'!$C$4,ROW(AN27)) -> AE27 | AO27: =_xlfn.CONCAT('Sample Select backend'!$J$2,ROW(AO27)) -> AJ27 | AP27: =_xlfn.CONCAT('Sample Select backend'!$F$4,ROW(AP27)) -> AF27 | AQ27: =_xlfn.CONCAT('Sample Select backend'!$I$10,ROW(AQ27)) -> R27 | AR27: =_xlfn.CONCAT('Sample Select backend'!$M$4,ROW(AR27)) -> AK27 | AS27: =A27 -> Albania | AT27: =IF(ISNUMBER(C27),C27,IF(OR(C27="general",C27="23;general"),"General",IF(OR(C27="exemption",C27="other (exemption)"),"Tax exemption/waiver/suspension","Other"))) -> 6 | AU27: =IF(A27<>A26,1,0) -> 0 | AV27: 1
A28: Albania | B28: 2 | C28: 13 | D28: Extension of deadline for submission of the individual tax return for individuals with an annual income exceeding ALL 2 million in 2019 to 31 July 2020 | E28: -1 | F28: 2 | G28: 2 | H28: 1 | I28: 2 | J28: 1 | K28: 1 | L28: 1 | M28: 1 | N28: ALB | O28: Europe & Central Asia | P28: IBRD | Q28: Upper Middle Income | R28: 0 | S28: -4.74 | T28: -4.77 | U28: 80.04 | V28: =IF(E28>0,1,IF(E28<0,0,-1)) -> 0 | W28: =IF(F28>0,1,IF(F28<0,0,-1)) -> 1 | X28: =IF(G28>0,1,IF(G28<0,0,-1)) -> 1 | Y28: =IF(H28>0,1,IF(H28<0,0,-1)) -> 1 | Z28: =IF(I28>0,1,IF(I28<0,0,-1)) -> 1 | AA28: =IF(J28>0,1,IF(J28<0,0,-1)) -> 1 | AB28: =IF(K28>0,1,IF(K28<0,0,-1)) -> 1 | AC28: =IF(L28>0,1,IF(L28<0,0,-1)) -> 1 | AD28: =IF(M28>0,1,IF(M28<0,0,-1)) -> 1 | AE28: All Regions | AF28: All Income Levels | AG28: 0 | AH28: 1 | AI28: 0 | AJ28: 1 | AK28: All Countries | AL28: =IF(OR(B28="other",B28="international",B28="Transfers",B28="expenditure"),1,0) -> 0 | AM28: =IF(AND(INDIRECT(AN28)='Sample Select backend'!$C$2,INDIRECT(AO28)=1,INDIRECT(AP28)='Sample Select backend'!$F$2,INDIRECT(AQ28)=1,INDIRECT(AR28)='Sample Select backend'!$M$2),1,0) -> 0 | AN28: =_xlfn.CONCAT('Sample Select backend'!$C$4,ROW(AN28)) -> AE28 | AO28: =_xlfn.CONCAT('Sample Select backend'!$J$2,ROW(AO28)) -> AJ28 | AP28: =_xlfn.CONCAT('Sample Select backend'!$F$4,ROW(AP28)) -> AF28 | AQ28: =_xlfn.CONCAT('Sample Select backend'!$I$10,ROW(AQ28)) -> R28 | AR28: =_xlfn.CONCAT('Sample Select backend'!$M$4,ROW(AR28)) -> AK28 | AS28: =A28 -> Albania | AT28: =IF(ISNUMBER(C28),C28,IF(OR(C28="general",C28="23;general"),"General",IF(OR(C28="exemption",C28="other (exemption)"),"Tax exemption/waiver/suspension","Other"))) -> 13 | AU28: =IF(A28<>A27,1,0) -> 0 | AV28: 1
A29: Albania | B29: 6 | C29: 29 | D29: Payment of the minimum wage to employees of firms with a turnover up to 14,000 which have interrupted their activities because of the COVID-19 outbreak. | E29: 1 | F29: 1 | G29: 1 | H29: -1 | I29: -2 | J29: 1 | K29: 1 | L29: -2 | M29: 1 | N29: ALB | O29: Europe & Central Asia | P29: IBRD | Q29: Upper Middle Income | R29: 0 | S29: -4.74 | T29: -4.77 | U29: 80.04 | V29: =IF(E29>0,1,IF(E29<0,0,-1)) -> 1 | W29: =IF(F29>0,1,IF(F29<0,0,-1)) -> 1 | X29: =IF(G29>0,1,IF(G29<0,0,-1)) -> 1 | Y29: =IF(H29>0,1,IF(H29<0,0,-1)) -> 0 | Z29: =IF(I29>0,1,IF(I29<0,0,-1)) -> 0 | AA29: =IF(J29>0,1,IF(J29<0,0,-1)) -> 1 | AB29: =IF(K29>0,1,IF(K29<0,0,-1)) -> 1 | AC29: =IF(L29>0,1,IF(L29<0,0,-1)) -> 0 | AD29: =IF(M29>0,1,IF(M29<0,0,-1)) -> 1 | AE29: All Regions | AF29: All Income Levels | AG29: 0 | AH29: 1 | AI29: 0 | AJ29: 1 | AK29: All Countries | AL29: =IF(OR(B29="other",B29="international",B29="Transfers",B29="expenditure"),1,0) -> 0 | AM29: =IF(AND(INDIRECT(AN29)='Sample Select backend'!$C$2,INDIRECT(AO29)=1,INDIRECT(AP29)='Sample Select backend'!$F$2,INDIRECT(AQ29)=1,INDIRECT(AR29)='Sample Select backend'!$M$2),1,0) -> 0 | AN29: =_xlfn.CONCAT('Sample Select backend'!$C$4,ROW(AN29)) -> AE29 | AO29: =_xlfn.CONCAT('Sample Select backend'!$J$2,ROW(AO29)) -> AJ29 | AP29: =_xlfn.CONCAT('Sample Select backend'!$F$4,ROW(AP29)) -> AF29 | AQ29: =_xlfn.CONCAT('Sample Select backend'!$I$10,ROW(AQ29)) -> R29 | AR29: =_xlfn.CONCAT('Sample Select backend'!$M$4,ROW(AR29)) -> AK29 | AS29: =A29 -> Albania | AT29: =IF(ISNUMBER(C29),C29,IF(OR(C29="general",C29="23;general"),"General",IF(OR(C29="exemption",C29="other (exemption)"),"Tax exemption/waiver/suspension","Other"))) -> 29 | AU29: =IF(A29<>A28,1,0) -> 0 | AV29: 1
A30: Albania | B30: 7 | C30: 30 | D30: Lk11bn (0.6% of GDP) sovereign guarantee fund for companies to access overdrafts in the banking system to pay wages for their employees for up to 3 months with an interest rate capped at 2.85% for a maturity of up to 2 years. | E30: -1 | F30: 1 | G30: 1 | H30: 1 | I30: 1 | J30: 1 | K30: 1 | L30: -1 | M30: 1 | N30: ALB | O30: Europe & Central Asia | P30: IBRD | Q30: Upper Middle Income | R30: 0 | S30: -4.74 | T30: -4.77 | U30: 80.04 | V30: =IF(E30>0,1,IF(E30<0,0,-1)) -> 0 | W30: =IF(F30>0,1,IF(F30<0,0,-1)) -> 1 | X30: =IF(G30>0,1,IF(G30<0,0,-1)) -> 1 | Y30: =IF(H30>0,1,IF(H30<0,0,-1)) -> 1 | Z30: =IF(I30>0,1,IF(I30<0,0,-1)) -> 1 | AA30: =IF(J30>0,1,IF(J30<0,0,-1)) -> 1 | AB30: =IF(K30>0,1,IF(K30<0,0,-1)) -> 1 | AC30: =IF(L30>0,1,IF(L30<0,0,-1)) -> 0 | AD30: =IF(M30>0,1,IF(M30<0,0,-1)) -> 1 | AE30: All Regions | AF30: All Income Levels | AG30: 0 | AH30: 1 | AI30: 0 | AJ30: 1 | AK30: All Countries | AL30: =IF(OR(B30="other",B30="international",B30="Transfers",B30="expenditure"),1,0) -> 0 | AM30: =IF(AND(INDIRECT(AN30)='Sample Select backend'!$C$2,INDIRECT(AO30)=1,INDIRECT(AP30)='Sample Select backend'!$F$2,INDIRECT(AQ30)=1,INDIRECT(AR30)='Sample Select backend'!$M$2),1,0) -> 0 | AN30: =_xlfn.CONCAT('Sample Select backend'!$C$4,ROW(AN30)) -> AE30 | AO30: =_xlfn.CONCAT('Sample Select backend'!$J$2,ROW(AO30)) -> AJ30 | AP30: =_xlfn.CONCAT('Sample Select backend'!$F$4,ROW(AP30)) -> AF30 | AQ30: =_xlfn.CONCAT('Sample Select backend'!$I$10,ROW(AQ30)) -> R30 | AR30: =_xlfn.CONCAT('Sample Select backend'!$M$4,ROW(AR30)) -> AK30 | AS30: =A30 -> Albania | AT30: =IF(ISNUMBER(C30),C30,IF(OR(C30="general",C30="23;general"),"General",IF(OR(C30="exemption",C30="other (exemption)"),"Tax exemption/waiver/suspension","Other"))) -> 30 | AU30: =IF(A30<>A29,1,0) -> 0 | AV30: 1
A31: Albania | B31: 6 | C31: 27 | D31: Benefits under the Ndihma Economike (flagship cash transfer program) will be doubled. | E31: 1 | F31: 1 | G31: 1 | H31: -1 | I31: 2 | J31: -2 | K31: 1 | L31: 1 | M31: 1 | N31: ALB | O31: Europe & Central Asia | P31: IBRD | Q31: Upper Middle Income | R31: 0 | S31: -4.74 | T31: -4.77 | U31: 80.04 | V31: =IF(E31>0,1,IF(E31<0,0,-1)) -> 1 | W31: =IF(F31>0,1,IF(F31<0,0,-1)) -> 1 | X31: =IF(G31>0,1,IF(G31<0,0,-1)) -> 1 | Y31: =IF(H31>0,1,IF(H31<0,0,-1)) -> 0 | Z31: =IF(I31>0,1,IF(I31<0,0,-1)) -> 1 | AA31: =IF(J31>0,1,IF(J31<0,0,-1)) -> 0 | AB31: =IF(K31>0,1,IF(K31<0,0,-1)) -> 1 | AC31: =IF(L31>0,1,IF(L31<0,0,-1)) -> 1 | AD31: =IF(M31>0,1,IF(M31<0,0,-1)) -> 1 | AE31: All Regions | AF31: All Income Levels | AG31: 0 | AH31: 1 | AI31: 0 | AJ31: 1 | AK31: All Countries | AL31: =IF(OR(B31="other",B31="international",B31="Transfers",B31="expenditure"),1,0) -> 0 | AM31: =IF(AND(INDIRECT(AN31)='Sample Select backend'!$C$2,INDIRECT(AO31)=1,INDIRECT(AP31)='Sample Select backend'!$F$2,INDIRECT(AQ31)=1,INDIRECT(AR31)='Sample Select backend'!$M$2),1,0) -> 0 | AN31: =_xlfn.CONCAT('Sample Select backend'!$C$4,ROW(AN31)) -> AE31 | AO31: =_xlfn.CONCAT('Sample Select backend'!$J$2,ROW(AO31)) -> AJ31 | AP31: =_xlfn.CONCAT('Sample Select backend'!$F$4,ROW(AP31)) -> AF31 | AQ31: =_xlfn.CONCAT('Sample Select backend'!$I$10,ROW(AQ31)) -> R31 | AR31: =_xlfn.CONCAT('Sample Select backend'!$M$4,ROW(AR31)) -> AK31 | AS31: =A31 -> Albania | AT31: =IF(ISNUMBER(C31),C31,IF(OR(C31="general",C31="23;general"),"General",IF(OR(C31="exemption",C31="other (exemption)"),"Tax exemption/waiver/suspension","Other"))) -> 27 | AU31: =IF(A31<>A30,1,0) -> 0 | AV31: 1
A32: Albania | B32: 6 | C32: 25 | D32: One-off transfer of Lek 40,000 to employees of small businesses affected by the pandemic and not covered by the earlier support package, employees of large businesses laid off due to the pandemic, and employees in the tourism sector. | O32: Europe & Central Asia | P32: IBRD | Q32: Upper Middle Income | R32: 0 | S32: -4.74 | T32: -4.77 | U32: 80.04 | V32: -1 | W32: -1 | X32: -1 | Y32: -1 | Z32: -1 | AA32: -1 | AB32: -1 | AC32: -1 | AD32: -1 | AE32: All Regions | AF32: All Income Levels | AG32: 0 | AH32: 1 | AI32: 0 | AJ32: 1 | AK32: All Countries | AL32: =IF(OR(B32="other",B32="international",B32="Transfers",B32="expenditure"),1,0) -> 0 | AM32: =IF(AND(INDIRECT(AN32)='Sample Select backend'!$C$2,INDIRECT(AO32)=1,INDIRECT(AP32)='Sample Select backend'!$F$2,INDIRECT(AQ32)=1,INDIRECT(AR32)='Sample Select backend'!$M$2),1,0) -> 0 | AN32: =_xlfn.CONCAT('Sample Select backend'!$C$4,ROW(AN32)) -> AE32 | AO32: =_xlfn.CONCAT('Sample Select backend'!$J$2,ROW(AO32)) -> AJ32 | AP32: =_xlfn.CONCAT('Sample Select backend'!$F$4,ROW(AP32)) -> AF32 | AQ32: =_xlfn.CONCAT('Sample Select backend'!$I$10,ROW(AQ32)) -> R32 | AR32: =_xlfn.CONCAT('Sample Select backend'!$M$4,ROW(AR32)) -> AK32 | AS32: =A32 -> Albania | AT32: =IF(ISNUMBER(C32),C32,IF(OR(C32="general",C32="23;general"),"General",IF(OR(C32="exemption",C32="other (exemption)"),"Tax exemption/waiver/suspension","Other"))) -> 25 | AU32: =IF(A32<>A31,1,0) -> 0 | AV32: 0
A33: Albania | B33: 7 | C33: 30 | D33: A sovereign guarantee of Lek 15 billion (0.9 percent of GDP) to provide loans for working capital for all private companies that were tax-compliant and solvent before the pandemic. The government will guarantee 60 percent of the loans, and interest is capped at 5 percent. As of August 13th, 95% of the overall budgeted direct support measures had been paid out while the take up for the first guarantee scheme was 60 percent and for the second scheme 22 percent. | O33: Europe & Central Asia | P33: IBRD | Q33: Upper Middle Income | R33: 0 | S33: -4.74 | T33: -4.77 | U33: 80.04 | V33: -1 | W33: -1 | X33: -1 | Y33: -1 | Z33: -1 | AA33: -1 | AB33: -1 | AC33: -1 | AD33: -1 | AE33: All Regions | AF33: All Income Levels | AG33: 0 | AH33: 1 | AI33: 0 | AJ33: 1 | AK33: All Countries | AL33: =IF(OR(B33="other",B33="international",B33="Transfers",B33="expenditure"),1,0) -> 0 | AM33: =IF(AND(INDIRECT(AN33)='Sample Select backend'!$C$2,INDIRECT(AO33)=1,INDIRECT(AP33)='Sample Select backend'!$F$2,INDIRECT(AQ33)=1,INDIRECT(AR33)='Sample Select backend'!$M$2),1,0) -> 0 | AN33: =_xlfn.CONCAT('Sample Select backend'!$C$4,ROW(AN33)) -> AE33 | AO33: =_xlfn.CONCAT('Sample Select backend'!$J$2,ROW(AO33)) -> AJ33 | AP33: =_xlfn.CONCAT('Sample Select backend'!$F$4,ROW(AP33)) -> AF33 | AQ33: =_xlfn.CONCAT('Sample Select backend'!$I$10,ROW(AQ33)) -> R33 | AR33: =_xlfn.CONCAT('Sample Select backend'!$M$4,ROW(AR33)) -> AK33 | AS33: =A33 -> Albania | AT33: =IF(ISNUMBER(C33),C33,IF(OR(C33="general",C33="23;general"),"General",IF(OR(C33="exemption",C33="other (exemption)"),"Tax exemption/waiver/suspension","Other"))) -> 30 | AU33: =IF(A33<>A32,1,0) -> 0 | AV33: 0
A34: Albania | B34: 8 | C34: other | D34: Starting in April, cabinet ministers and lawmakers will receive half of their salaries for the next three months with the savings going to the Anti-Covid 19 social support fund. | O34: Europe & Central Asia | P34: IBRD | Q34: Upper Middle Income | R34: 0 | S34: -4.74 | T34: -4.77 | U34: 80.04 | V34: -1 | W34: -1 | X34: -1 | Y34: -1 | Z34: -1 | AA34: -1 | AB34: -1 | AC34: -1 | AD34: -1 | AE34: All Regions | AF34: All Income Levels | AG34: 0 | AH34: 1 | AI34: 0 | AJ34: 1 | AK34: All Countries | AL34: =IF(OR(B34="other",B34="international",B34="Transfers",B34="expenditure"),1,0) -> 0 | AM34: =IF(AND(INDIRECT(AN34)='Sample Select backend'!$C$2,INDIRECT(AO34)=1,INDIRECT(AP34)='Sample Select backend'!$F$2,INDIRECT(AQ34)=1,INDIRECT(AR34)='Sample Select backend'!$M$2),1,0) -> 0 | AN34: =_xlfn.CONCAT('Sample Select backend'!$C$4,ROW(AN34)) -> AE34 | AO34: =_xlfn.CONCAT('Sample Select backend'!$J$2,ROW(AO34)) -> AJ34 | AP34: =_xlfn.CONCAT('Sample Select backend'!$F$4,ROW(AP34)) -> AF34 | AQ34: =_xlfn.CONCAT('Sample Select backend'!$I$10,ROW(AQ34)) -> R34 | AR34: =_xlfn.CONCAT('Sample Select backend'!$M$4,ROW(AR34)) -> AK34 | AS34: =A34 -> Albania | AT34: =IF(ISNUMBER(C34),C34,IF(OR(C34="general",C34="23;general"),"General",IF(OR(C34="exemption",C34="other (exemption)"),"Tax exemption/waiver/suspension","Other"))) -> Other | AU34: =IF(A34<>A33,1,0) -> 0 | AV34: 0
A35: Albania | B35: Other | C35: 33 | D35: Lek 2bn of defense spending reallocated toward humanitarian relief for the most vulnerable | O35: Europe & Central Asia | P35: IBRD | Q35: Upper Middle Income | R35: 0 | S35: -4.74 | T35: -4.77 | U35: 80.04 | V35: -1 | W35: -1 | X35: -1 | Y35: -1 | Z35: -1 | AA35: -1 | AB35: -1 | AC35: -1 | AD35: -1 | AE35: All Regions | AF35: All Income Levels | AG35: 0 | AH35: 1 | AI35: 0 | AJ35: 1 | AK35: All Countries | AL35: =IF(OR(B35="other",B35="international",B35="Transfers",B35="expenditure"),1,0) -> 1 | AM35: =IF(AND(INDIRECT(AN35)='Sample Select backend'!$C$2,INDIRECT(AO35)=1,INDIRECT(AP35)='Sample Select backend'!$F$2,INDIRECT(AQ35)=1,INDIRECT(AR35)='Sample Select backend'!$M$2),1,0) -> 0 | AN35: =_xlfn.CONCAT('Sample Select backend'!$C$4,ROW(AN35)) -> AE35 | AO35: =_xlfn.CONCAT('Sample Select backend'!$J$2,ROW(AO35)) -> AJ35 | AP35: =_xlfn.CONCAT('Sample Select backend'!$F$4,ROW(AP35)) -> AF35 | AQ35: =_xlfn.CONCAT('Sample Select backend'!$I$10,ROW(AQ35)) -> R35 | AR35: =_xlfn.CONCAT('Sample Select backend'!$M$4,ROW(AR35)) -> AK35 | AS35: =A35 -> Albania | AT35: =IF(ISNUMBER(C35),C35,IF(OR(C35="general",C35="23;general"),"General",IF(OR(C35="exemption",C35="other (exemption)"),"Tax exemption/waiver/suspension","Other"))) -> 33 | AU35: =IF(A35<>A34,1,0) -> 0 | AV35: 0
A36: Albania | B36: 1 | C36: 6 | D36: Deferral of CIT payments and for companies with a turnover up to Lek 14,000. | O36: Europe & Central Asia | P36: IBRD | Q36: Upper Middle Income | R36: 0 | S36: -4.74 | T36: -4.77 | U36: 80.04 | V36: -1 | W36: -1 | X36: -1 | Y36: -1 | Z36: -1 | AA36: -1 | AB36: -1 | AC36: -1 | AD36: -1 | AE36: All Regions | AF36: All Income Levels | AG36: 0 | AH36: 1 | AI36: 0 | AJ36: 1 | AK36: All Countries | AL36: =IF(OR(B36="other",B36="international",B36="Transfers",B36="expenditure"),1,0) -> 0 | AM36: =IF(AND(INDIRECT(AN36)='Sample Select backend'!$C$2,INDIRECT(AO36)=1,INDIRECT(AP36)='Sample Select backend'!$F$2,INDIRECT(AQ36)=1,INDIRECT(AR36)='Sample Select backend'!$M$2),1,0) -> 0 | AN36: =_xlfn.CONCAT('Sample Select backend'!$C$4,ROW(AN36)) -> AE36 | AO36: =_xlfn.CONCAT('Sample Select backend'!$J$2,ROW(AO36)) -> AJ36 | AP36: =_xlfn.CONCAT('Sample Select backend'!$F$4,ROW(AP36)) -> AF36 | AQ36: =_xlfn.CONCAT('Sample Select backend'!$I$10,ROW(AQ36)) -> R36 | AR36: =_xlfn.CONCAT('Sample Select backend'!$M$4,ROW(AR36)) -> AK36 | AS36: =A36 -> Albania | AT36: =IF(ISNUMBER(C36),C36,IF(OR(C36="general",C36="23;general"),"General",IF(OR(C36="exemption",C36="other (exemption)"),"Tax exemption/waiver/suspension","Other"))) -> 6 | AU36: =IF(A36<>A35,1,0) -> 0 | AV36: 0
A37: Algeria | B37: 6 | C37: 25/28 | D37: A benefit of 10,000 Algerian Dinars (79 USD ) is to be extended to poor families impacted by COVID-19 to cover Ramadhan expenses. | E37: 2 | F37: 1 | G37: 2 | H37: -1 | I37: 1 | J37: 1 | K37: -1 | L37: -2 | M37: 1 | N37: DZA | O37: Middle East & North Africa | P37: IBRD | Q37: Lower Middle Income | R37: 0 | S37: -5.48 | T37: -15.74 | U37: 51.4 | V37: =IF(E37>0,1,IF(E37<0,0,-1)) -> 1 | W37: =IF(F37>0,1,IF(F37<0,0,-1)) -> 1 | X37: =IF(G37>0,1,IF(G37<0,0,-1)) -> 1 | Y37: =IF(H37>0,1,IF(H37<0,0,-1)) -> 0 | Z37: =IF(I37>0,1,IF(I37<0,0,-1)) -> 1 | AA37: =IF(J37>0,1,IF(J37<0,0,-1)) -> 1 | AB37: =IF(K37>0,1,IF(K37<0,0,-1)) -> 0 | AC37: =IF(L37>0,1,IF(L37<0,0,-1)) -> 0 | AD37: =IF(M37>0,1,IF(M37<0,0,-1)) -> 1 | AE37: All Regions | AF37: All Income Levels | AG37: 0 | AH37: 1 | AI37: 0 | AJ37: 1 | AK37: All Countries | AL37: =IF(OR(B37="other",B37="international",B37="Transfers",B37="expenditure"),1,0) -> 0 | AM37: =IF(AND(INDIRECT(AN37)='Sample Select backend'!$C$2,INDIRECT(AO37)=1,INDIRECT(AP37)='Sample Select backend'!$F$2,INDIRECT(AQ37)=1,INDIRECT(AR37)='Sample Select backend'!$M$2),1,0) -> 0 | AN37: =_xlfn.CONCAT('Sample Select backend'!$C$4,ROW(AN37)) -> AE37 | AO37: =_xlfn.CONCAT('Sample Select backend'!$J$2,ROW(AO37)) -> AJ37 | AP37: =_xlfn.CONCAT('Sample Select backend'!$F$4,ROW(AP37)) -> AF37 | AQ37: =_xlfn.CONCAT('Sample Select backend'!$I$10,ROW(AQ37)) -> R37 | AR37: =_xlfn.CONCAT('Sample Select backend'!$M$4,ROW(AR37)) -> AK37 | AS37: =A37 -> Algeria | AT37: =IF(ISNUMBER(C37),C37,IF(OR(C37="general",C37="23;general"),"General",IF(OR(C37="exemption",C37="other (exemption)"),"Tax exemption/waiver/suspension","Other"))) -> Other | AU37: =IF(A37<>A36,1,0) -> 1 | AV37: 1
A38: Algeria | B38: 6 | C38: 27 | D38: Beneficiaries (1M) can access Solidarity Allowance benefits at any time (In normal circumstances they need to be collected on the 30th/31st of the month. Uncollected benefits are automatically returned to the Social Development Agency). | E38: 1 | F38: 1 | G38: 1 | H38: 1 | I38: 1 | J38: -2 | K38: -1 | L38: 1 | M38: 1 | N38: DZA | O38: Middle East & North Africa | P38: IBRD | Q38: Lower Middle Income | R38: 0 | S38: -5.48 | T38: -15.74 | U38: 51.4 | V38: =IF(E38>0,1,IF(E38<0,0,-1)) -> 1 | W38: =IF(F38>0,1,IF(F38<0,0,-1)) -> 1 | X38: =IF(G38>0,1,IF(G38<0,0,-1)) -> 1 | Y38: =IF(H38>0,1,IF(H38<0,0,-1)) -> 1 | Z38: =IF(I38>0,1,IF(I38<0,0,-1)) -> 1 | AA38: =IF(J38>0,1,IF(J38<0,0,-1)) -> 0 | AB38: =IF(K38>0,1,IF(K38<0,0,-1)) -> 0 | AC38: =IF(L38>0,1,IF(L38<0,0,-1)) -> 1 | AD38: =IF(M38>0,1,IF(M38<0,0,-1)) -> 1 | AE38: All Regions | AF38: All Income Levels | AG38: 0 | AH38: 1 | AI38: 0 | AJ38: 1 | AK38: All Countries | AL38: =IF(OR(B38="other",B38="international",B38="Transfers",B38="expenditure"),1,0) -> 0 | AM38: =IF(AND(INDIRECT(AN38)='Sample Select backend'!$C$2,INDIRECT(AO38)=1,INDIRECT(AP38)='Sample Select backend'!$F$2,INDIRECT(AQ38)=1,INDIRECT(AR38)='Sample Select backend'!$M$2),1,0) -> 0 | AN38: =_xlfn.CONCAT('Sample Select backend'!$C$4,ROW(AN38)) -> AE38 | AO38: =_xlfn.CONCAT('Sample Select backend'!$J$2,ROW(AO38)) -> AJ38 | AP38: =_xlfn.CONCAT('Sample Select backend'!$F$4,ROW(AP38)) -> AF38 | AQ38: =_xlfn.CONCAT('Sample Select backend'!$I$10,ROW(AQ38)) -> R38 | AR38: =_xlfn.CONCAT('Sample Select backend'!$M$4,ROW(AR38)) -> AK38 | AS38: =A38 -> Algeria | AT38: =IF(ISNUMBER(C38),C38,IF(OR(C38="general",C38="23;general"),"General",IF(OR(C38="exemption",C38="other (exemption)"),"Tax exemption/waiver/suspension","Other"))) -> 27 | AU38: =IF(A38<>A37,1,0) -> 0 | AV38: 1
A39: Algeria | B39: 2 | C39: 14 | D39: The deadline for payment of the tax for passenger vehicles, utility vehicles and passenger transport vehicles for the year 2020 is deferred until 31 May 2020 | E39: -1 | F39: 2 | G39: 2 | H39: 1 | I39: 2 | J39: 1 | K39: 1 | L39: 1 | M39: 1 | N39: DZA | O39: Middle East & North Africa | P39: IBRD | Q39: Lower Middle Income | R39: 0 | S39: -5.48 | T39: -15.74 | U39: 51.4 | V39: =IF(E39>0,1,IF(E39<0,0,-1)) -> 0 | W39: =IF(F39>0,1,IF(F39<0,0,-1)) -> 1 | X39: =IF(G39>0,1,IF(G39<0,0,-1)) -> 1 | Y39: =IF(H39>0,1,IF(H39<0,0,-1)) -> 1 | Z39: =IF(I39>0,1,IF(I39<0,0,-1)) -> 1 | AA39: =IF(J39>0,1,IF(J39<0,0,-1)) -> 1 | AB39: =IF(K39>0,1,IF(K39<0,0,-1)) -> 1 | AC39: =IF(L39>0,1,IF(L39<0,0,-1)) -> 1 | AD39: =IF(M39>0,1,IF(M39<0,0,-1)) -> 1 | AE39: All Regions | AF39: All Income Levels | AG39: 0 | AH39: 1 | AI39: 0 | AJ39: 1 | AK39: All Countries | AL39: =IF(OR(B39="other",B39="international",B39="Transfers",B39="expenditure"),1,0) -> 0 | AM39: =IF(AND(INDIRECT(AN39)='Sample Select backend'!$C$2,INDIRECT(AO39)=1,INDIRECT(AP39)='Sample Select backend'!$F$2,INDIRECT(AQ39)=1,INDIRECT(AR39)='Sample Select backend'!$M$2),1,0) -> 0 | AN39: =_xlfn.CONCAT('Sample Select backend'!$C$4,ROW(AN39)) -> AE39 | AO39: =_xlfn.CONCAT('Sample Select backend'!$J$2,ROW(AO39)) -> AJ39 | AP39: =_xlfn.CONCAT('Sample Select backend'!$F$4,ROW(AP39)) -> AF39 | AQ39: =_xlfn.CONCAT('Sample Select backend'!$I$10,ROW(AQ39)) -> R39 | AR39: =_xlfn.CONCAT('Sample Select backend'!$M$4,ROW(AR39)) -> AK39 | AS39: =A39 -> Algeria | AT39: =IF(ISNUMBER(C39),C39,IF(OR(C39="general",C39="23;general"),"General",IF(OR(C39="exemption",C39="other (exemption)"),"Tax exemption/waiver/suspension","Other"))) -> 14 | AU39: =IF(A39<>A38,1,0) -> 0 | AV39: 1
A40: Algeria | B40: 2 | C40: 14 | D40: Deferral of personal income tax pre-payments until 20 June 2020. Taxpayers who file tax returns electronically are not affected by the measures | E40: -2 | F40: 2 | G40: 2 | H40: 1 | I40: 2 | J40: 1 | K40: 1 | L40: 1 | M40: 1 | N40: DZA | O40: Middle East & North Africa | P40: IBRD | Q40: Lower Middle Income | R40: 0 | S40: -5.48 | T40: -15.74 | U40: 51.4 | V40: =IF(E40>0,1,IF(E40<0,0,-1)) -> 0 | W40: =IF(F40>0,1,IF(F40<0,0,-1)) -> 1 | X40: =IF(G40>0,1,IF(G40<0,0,-1)) -> 1 | Y40: =IF(H40>0,1,IF(H40<0,0,-1)) -> 1 | Z40: =IF(I40>0,1,IF(I40<0,0,-1)) -> 1 | AA40: =IF(J40>0,1,IF(J40<0,0,-1)) -> 1 | AB40: =IF(K40>0,1,IF(K40<0,0,-1)) -> 1 | AC40: =IF(L40>0,1,IF(L40<0,0,-1)) -> 1 | AD40: =IF(M40>0,1,IF(M40<0,0,-1)) -> 1 | AE40: All Regions | AF40: All Income Levels | AG40: 0 | AH40: 1 | AI40: 0 | AJ40: 1 | AK40: All Countries | AL40: =IF(OR(B40="other",B40="international",B40="Transfers",B40="expenditure"),1,0) -> 0 | AM40: =IF(AND(INDIRECT(AN40)='Sample Select backend'!$C$2,INDIRECT(AO40)=1,INDIRECT(AP40)='Sample Select backend'!$F$2,INDIRECT(AQ40)=1,INDIRECT(AR40)='Sample Select backend'!$M$2),1,0) -> 0 | AN40: =_xlfn.CONCAT('Sample Select backend'!$C$4,ROW(AN40)) -> AE40 | AO40: =_xlfn.CONCAT('Sample Select backend'!$J$2,ROW(AO40)) -> AJ40 | AP40: =_xlfn.CONCAT('Sample Select backend'!$F$4,ROW(AP40)) -> AF40 | AQ40: =_xlfn.CONCAT('Sample Select backend'!$I$10,ROW(AQ40)) -> R40 | AR40: =_xlfn.CONCAT('Sample Select backend'!$M$4,ROW(AR40)) -> AK40 | AS40: =A40 -> Algeria | AT40: =IF(ISNUMBER(C40),C40,IF(OR(C40="general",C40="23;general"),"General",IF(OR(C40="exemption",C40="other (exemption)"),"Tax exemption/waiver/suspension","Other"))) -> 14 | AU40: =IF(A40<>A39,1,0) -> 0 | AV40: 1
A41: Algeria | B41: 6 | C41: 28 | D41: Distribution of food and hygiene items to the most vulnerable families, including those living in isolated areas or impacted by the lockdown. | E41: 2 | F41: 1 | G41: 1 | H41: -1 | I41: 1 | J41: 1 | K41: 1 | L41: 2 | M41: -2 | N41: DZA | O41: Middle East & North Africa | P41: IBRD | Q41: Lower Middle Income | R41: 0 | S41: -5.48 | T41: -15.74 | U41: 51.4 | V41: =IF(E41>0,1,IF(E41<0,0,-1)) -> 1 | W41: =IF(F41>0,1,IF(F41<0,0,-1)) -> 1 | X41: =IF(G41>0,1,IF(G41<0,0,-1)) -> 1 | Y41: =IF(H41>0,1,IF(H41<0,0,-1)) -> 0 | Z41: =IF(I41>0,1,IF(I41<0,0,-1)) -> 1 | AA41: =IF(J41>0,1,IF(J41<0,0,-1)) -> 1 | AB41: =IF(K41>0,1,IF(K41<0,0,-1)) -> 1 | AC41: =IF(L41>0,1,IF(L41<0,0,-1)) -> 1 | AD41: =IF(M41>0,1,IF(M41<0,0,-1)) -> 0 | AE41: All Regions | AF41: All Income Levels | AG41: 0 | AH41: 1 | AI41: 0 | AJ41: 1 | AK41: All Countries | AL41: =IF(OR(B41="other",B41="international",B41="Transfers",B41="expenditure"),1,0) -> 0 | AM41: =IF(AND(INDIRECT(AN41)='Sample Select backend'!$C$2,INDIRECT(AO41)=1,INDIRECT(AP41)='Sample Select backend'!$F$2,INDIRECT(AQ41)=1,INDIRECT(AR41)='Sample Select backend'!$M$2),1,0) -> 0 | AN41: =_xlfn.CONCAT('Sample Select backend'!$C$4,ROW(AN41)) -> AE41 | AO41: =_xlfn.CONCAT('Sample Select backend'!$J$2,ROW(AO41)) -> AJ41 | AP41: =_xlfn.CONCAT('Sample Select backend'!$F$4,ROW(AP41)) -> AF41 | AQ41: =_xlfn.CONCAT('Sample Select backend'!$I$10,ROW(AQ41)) -> R41 | AR41: =_xlfn.CONCAT('Sample Select backend'!$M$4,ROW(AR41)) -> AK41 | AS41: =A41 -> Algeria | AT41: =IF(ISNUMBER(C41),C41,IF(OR(C41="general",C41="23;general"),"General",IF(OR(C41="exemption",C41="other (exemption)"),"Tax exemption/waiver/suspension","Other"))) -> 28 | AU41: =IF(A41<>A40,1,0) -> 0 | AV41: 1
A42: Algeria | B42: 1 | C42: 5 | D42: For taxpayers under the authority of the Large Taxpayers Office (Direction des grandes entreprises, DGE), the subscription period for the annual results declaration is extended until 31 May 2020 | E42: -1 | F42: 2 | G42: 2 | H42: 1 | I42: 2 | J42: 1 | K42: 1 | L42: 1 | M42: 1 | N42: DZA | O42: Middle East & North Africa | P42: IBRD | Q42: Lower Middle Income | R42: 0 | S42: -5.48 | T42: -15.74 | U42: 51.4 | V42: =IF(E42>0,1,IF(E42<0,0,-1)) -> 0 | W42: =IF(F42>0,1,IF(F42<0,0,-1)) -> 1 | X42: =IF(G42>0,1,IF(G42<0,0,-1)) -> 1 | Y42: =IF(H42>0,1,IF(H42<0,0,-1)) -> 1 | Z42: =IF(I42>0,1,IF(I42<0,0,-1)) -> 1 | AA42: =IF(J42>0,1,IF(J42<0,0,-1)) -> 1 | AB42: =IF(K42>0,1,IF(K42<0,0,-1)) -> 1 | AC42: =IF(L42>0,1,IF(L42<0,0,-1)) -> 1 | AD42: =IF(M42>0,1,IF(M42<0,0,-1)) -> 1 | AE42: All Regions | AF42: All Income Levels | AG42: 0 | AH42: 1 | AI42: 0 | AJ42: 1 | AK42: All Countries | AL42: =IF(OR(B42="other",B42="international",B42="Transfers",B42="expenditure"),1,0) -> 0 | AM42: =IF(AND(INDIRECT(AN42)='Sample Select backend'!$C$2,INDIRECT(AO42)=1,INDIRECT(AP42)='Sample Select backend'!$F$2,INDIRECT(AQ42)=1,INDIRECT(AR42)='Sample Select backend'!$M$2),1,0) -> 0 | AN42: =_xlfn.CONCAT('Sample Select backend'!$C$4,ROW(AN42)) -> AE42 | AO42: =_xlfn.CONCAT('Sample Select backend'!$J$2,ROW(AO42)) -> AJ42 | AP42: =_xlfn.CONCAT('Sample Select backend'!$F$4,ROW(AP42)) -> AF42 | AQ42: =_xlfn.CONCAT('Sample Select backend'!$I$10,ROW(AQ42)) -> R42 | AR42: =_xlfn.CONCAT('Sample Select backend'!$M$4,ROW(AR42)) -> AK42 | AS42: =A42 -> Algeria | AT42: =IF(ISNUMBER(C42),C42,IF(OR(C42="general",C42="23;general"),"General",IF(OR(C42="exemption",C42="other (exemption)"),"Tax exemption/waiver/suspension","Other"))) -> 5 | AU42: =IF(A42<>A41,1,0) -> 0 | AV42: 1
A43: Algeria | B43: 1 | C43: 6 | D43: Deferral of corporate income tax pre-payments until 20 June 2020. Taxpayers who file tax returns electronically are not affected by the measures | E43: -2 | F43: 2 | G43: 2 | H43: 1 | I43: 2 | J43: 1 | K43: 1 | L43: 1 | M43: 1 | N43: DZA | O43: Middle East & North Africa | P43: IBRD | Q43: Lower Middle Income | R43: 0 | S43: -5.48 | T43: -15.74 | U43: 51.4 | V43: =IF(E43>0,1,IF(E43<0,0,-1)) -> 0 | W43: =IF(F43>0,1,IF(F43<0,0,-1)) -> 1 | X43: =IF(G43>0,1,IF(G43<0,0,-1)) -> 1 | Y43: =IF(H43>0,1,IF(H43<0,0,-1)) -> 1 | Z43: =IF(I43>0,1,IF(I43<0,0,-1)) -> 1 | AA43: =IF(J43>0,1,IF(J43<0,0,-1)) -> 1 | AB43: =IF(K43>0,1,IF(K43<0,0,-1)) -> 1 | AC43: =IF(L43>0,1,IF(L43<0,0,-1)) -> 1 | AD43: =IF(M43>0,1,IF(M43<0,0,-1)) -> 1 | AE43: All Regions | AF43: All Income Levels | AG43: 0 | AH43: 1 | AI43: 0 | AJ43: 1 | AK43: All Countries | AL43: =IF(OR(B43="other",B43="international",B43="Transfers",B43="expenditure"),1,0) -> 0 | AM43: =IF(AND(INDIRECT(AN43)='Sample Select backend'!$C$2,INDIRECT(AO43)=1,INDIRECT(AP43)='Sample Select backend'!$F$2,INDIRECT(AQ43)=1,INDIRECT(AR43)='Sample Select backend'!$M$2),1,0) -> 0 | AN43: =_xlfn.CONCAT('Sample Select backend'!$C$4,ROW(AN43)) -> AE43 | AO43: =_xlfn.CONCAT('Sample Select backend'!$J$2,ROW(AO43)) -> AJ43 | AP43: =_xlfn.CONCAT('Sample Select backend'!$F$4,ROW(AP43)) -> AF43 | AQ43: =_xlfn.CONCAT('Sample Select backend'!$I$10,ROW(AQ43)) -> R43 | AR43: =_xlfn.CONCAT('Sample Select backend'!$M$4,ROW(AR43)) -> AK43 | AS43: =A43 -> Algeria | AT43: =IF(ISNUMBER(C43),C43,IF(OR(C43="general",C43="23;general"),"General",IF(OR(C43="exemption",C43="other (exemption)"),"Tax exemption/waiver/suspension","Other"))) -> 6 | AU43: =IF(A43<>A42,1,0) -> 0 | AV43: 1
A44: Algeria | B44: 6 | C44: 27 | D44: Expanded coverage of social security to deliveries in private maternal health facilities. | E44: 2 | F44: 1 | G44: 1 | H44: -1 | I44: 2 | J44: -2 | K44: -1 | L44: 1 | M44: 1 | N44: DZA | O44: Middle East & North Africa | P44: IBRD | Q44: Lower Middle Income | R44: 0 | S44: -5.48 | T44: -15.74 | U44: 51.4 | V44: =IF(E44>0,1,IF(E44<0,0,-1)) -> 1 | W44: =IF(F44>0,1,IF(F44<0,0,-1)) -> 1 | X44: =IF(G44>0,1,IF(G44<0,0,-1)) -> 1 | Y44: =IF(H44>0,1,IF(H44<0,0,-1)) -> 0 | Z44: =IF(I44>0,1,IF(I44<0,0,-1)) -> 1 | AA44: =IF(J44>0,1,IF(J44<0,0,-1)) -> 0 | AB44: =IF(K44>0,1,IF(K44<0,0,-1)) -> 0 | AC44: =IF(L44>0,1,IF(L44<0,0,-1)) -> 1 | AD44: =IF(M44>0,1,IF(M44<0,0,-1)) -> 1 | AE44: All Regions | AF44: All Income Levels | AG44: 0 | AH44: 1 | AI44: 0 | AJ44: 1 | AK44: All Countries | AL44: =IF(OR(B44="other",B44="international",B44="Transfers",B44="expenditure"),1,0) -> 0 | AM44: =IF(AND(INDIRECT(AN44)='Sample Select backend'!$C$2,INDIRECT(AO44)=1,INDIRECT(AP44)='Sample Select backend'!$F$2,INDIRECT(AQ44)=1,INDIRECT(AR44)='Sample Select backend'!$M$2),1,0) -> 0 | AN44: =_xlfn.CONCAT('Sample Select backend'!$C$4,ROW(AN44)) -> AE44 | AO44: =_xlfn.CONCAT('Sample Select backend'!$J$2,ROW(AO44)) -> AJ44 | AP44: =_xlfn.CONCAT('Sample Select backend'!$F$4,ROW(AP44)) -> AF44 | AQ44: =_xlfn.CONCAT('Sample Select backend'!$I$10,ROW(AQ44)) -> R44 | AR44: =_xlfn.CONCAT('Sample Select backend'!$M$4,ROW(AR44)) -> AK44 | AS44: =A44 -> Algeria | AT44: =IF(ISNUMBER(C44),C44,IF(OR(C44="general",C44="23;general"),"General",IF(OR(C44="exemption",C44="other (exemption)"),"Tax exemption/waiver/suspension","Other"))) -> 27 | AU44: =IF(A44<>A43,1,0) -> 0 | AV44: 1
A45: Algeria | B45: 6 | C45: 29 | D45: Temporary paid leave for 50% of employees, all pregnant women, and for women who take care of children, people with chronic diseases or health vulnerabilities. | E45: 1 | F45: 1 | H45: -1 | I45: -2 | J45: 2 | K45: 1 | L45: -1 | M45: 1 | N45: DZA | O45: Middle East & North Africa | P45: IBRD | Q45: Lower Middle Income | R45: 0 | S45: -5.48 | T45: -15.74 | U45: 51.4 | V45: =IF(E45>0,1,IF(E45<0,0,-1)) -> 1 | W45: =IF(F45>0,1,IF(F45<0,0,-1)) -> 1 | X45: =IF(G45>0,1,IF(G45<0,0,-1)) -> -1 | Y45: =IF(H45>0,1,IF(H45<0,0,-1)) -> 0 | Z45: =IF(I45>0,1,IF(I45<0,0,-1)) -> 0 | AA45: =IF(J45>0,1,IF(J45<0,0,-1)) -> 1 | AB45: =IF(K45>0,1,IF(K45<0,0,-1)) -> 1 | AC45: =IF(L45>0,1,IF(L45<0,0,-1)) -> 0 | AD45: =IF(M45>0,1,IF(M45<0,0,-1)) -> 1 | AE45: All Regions | AF45: All Income Levels | AG45: 0 | AH45: 1 | AI45: 0 | AJ45: 1 | AK45: All Countries | AL45: =IF(OR(B45="other",B45="international",B45="Transfers",B45="expenditure"),1,0) -> 0 | AM45: =IF(AND(INDIRECT(AN45)='Sample Select backend'!$C$2,INDIRECT(AO45)=1,INDIRECT(AP45)='Sample Select backend'!$F$2,INDIRECT(AQ45)=1,INDIRECT(AR45)='Sample Select backend'!$M$2),1,0) -> 0 | AN45: =_xlfn.CONCAT('Sample Select backend'!$C$4,ROW(AN45)) -> AE45 | AO45: =_xlfn.CONCAT('Sample Select backend'!$J$2,ROW(AO45)) -> AJ45 | AP45: =_xlfn.CONCAT('Sample Select backend'!$F$4,ROW(AP45)) -> AF45 | AQ45: =_xlfn.CONCAT('Sample Select backend'!$I$10,ROW(AQ45)) -> R45 | AR45: =_xlfn.CONCAT('Sample Select backend'!$M$4,ROW(AR45)) -> AK45 | AS45: =A45 -> Algeria | AT45: =IF(ISNUMBER(C45),C45,IF(OR(C45="general",C45="23;general"),"General",IF(OR(C45="exemption",C45="other (exemption)"),"Tax exemption/waiver/suspension","Other"))) -> 29 | AU45: =IF(A45<>A44,1,0) -> 0 | AV45: 1
A46: Algeria | B46: 5 | C46: general | D46: 7bn dinars allocated for medical supplies | O46: Middle East & North Africa | P46: IBRD | Q46: Lower Middle Income | R46: 0 | S46: -5.48 | T46: -15.74 | U46: 51.4 | V46: -1 | W46: -1 | X46: -1 | Y46: -1 | Z46: -1 | AA46: -1 | AB46: -1 | AC46: -1 | AD46: -1 | AE46: All Regions | AF46: All Income Levels | AG46: 0 | AH46: 1 | AI46: 0 | AJ46: 1 | AK46: All Countries | AL46: =IF(OR(B46="other",B46="international",B46="Transfers",B46="expenditure"),1,0) -> 0 | AM46: =IF(AND(INDIRECT(AN46)='Sample Select backend'!$C$2,INDIRECT(AO46)=1,INDIRECT(AP46)='Sample Select backend'!$F$2,INDIRECT(AQ46)=1,INDIRECT(AR46)='Sample Select backend'!$M$2),1,0) -> 0 | AN46: =_xlfn.CONCAT('Sample Select backend'!$C$4,ROW(AN46)) -> AE46 | AO46: =_xlfn.CONCAT('Sample Select backend'!$J$2,ROW(AO46)) -> AJ46 | AP46: =_xlfn.CONCAT('Sample Select backend'!$F$4,ROW(AP46)) -> AF46 | AQ46: =_xlfn.CONCAT('Sample Select backend'!$I$10,ROW(AQ46)) -> R46 | AR46: =_xlfn.CONCAT('Sample Select backend'!$M$4,ROW(AR46)) -> AK46 | AS46: =A46 -> Algeria | AT46: =IF(ISNUMBER(C46),C46,IF(OR(C46="general",C46="23;general"),"General",IF(OR(C46="exemption",C46="other (exemption)"),"Tax exemption/waiver/suspension","Other"))) -> General | AU46: =IF(A46<>A45,1,0) -> 0 | AV46: 0
A47: Algeria | B47: 5 | C47: general | D47: 16.5bn dinars allocated for bonus payments to health workers | O47: Middle East & North Africa | P47: IBRD | Q47: Lower Middle Income | R47: 0 | S47: -5.48 | T47: -15.74 | U47: 51.4 | V47: -1 | W47: -1 | X47: -1 | Y47: -1 | Z47: -1 | AA47: -1 | AB47: -1 | AC47: -1 | AD47: -1 | AE47: All Regions | AF47: All Income Levels | AG47: 0 | AH47: 1 | AI47: 0 | AJ47: 1 | AK47: All Countries | AL47: =IF(OR(B47="other",B47="international",B47="Transfers",B47="expenditure"),1,0) -> 0 | AM47: =IF(AND(INDIRECT(AN47)='Sample Select backend'!$C$2,INDIRECT(AO47)=1,INDIRECT(AP47)='Sample Select backend'!$F$2,INDIRECT(AQ47)=1,INDIRECT(AR47)='Sample Select backend'!$M$2),1,0) -> 0 | AN47: =_xlfn.CONCAT('Sample Select backend'!$C$4,ROW(AN47)) -> AE47 | AO47: =_xlfn.CONCAT('Sample Select backend'!$J$2,ROW(AO47)) -> AJ47 | AP47: =_xlfn.CONCAT('Sample Select backend'!$F$4,ROW(AP47)) -> AF47 | AQ47: =_xlfn.CONCAT('Sample Select backend'!$I$10,ROW(AQ47)) -> R47 | AR47: =_xlfn.CONCAT('Sample Select backend'!$M$4,ROW(AR47)) -> AK47 | AS47: =A47 -> Algeria | AT47: =IF(ISNUMBER(C47),C47,IF(OR(C47="general",C47="23;general"),"General",IF(OR(C47="exemption",C47="other (exemption)"),"Tax exemption/waiver/suspension","Other"))) -> General | AU47: =IF(A47<>A46,1,0) -> 0 | AV47: 0
A48: Algeria | B48: 5 | C48: general | D48: 8.9bn dinars allocated for the health sector’s development | O48: Middle East & North Africa | P48: IBRD | Q48: Lower Middle Income | R48: 0 | S48: -5.48 | T48: -15.74 | U48: 51.4 | V48: -1 | W48: -1 | X48: -1 | Y48: -1 | Z48: -1 | AA48: -1 | AB48: -1 | AC48: -1 | AD48: -1 | AE48: All Regions | AF48: All Income Levels | AG48: 0 | AH48: 1 | AI48: 0 | AJ48: 1 | AK48: All Countries | AL48: =IF(OR(B48="other",B48="international",B48="Transfers",B48="expenditure"),1,0) -> 0 | AM48: =IF(AND(INDIRECT(AN48)='Sample Select backend'!$C$2,INDIRECT(AO48)=1,INDIRECT(AP48)='Sample Select backend'!$F$2,INDIRECT(AQ48)=1,INDIRECT(AR48)='Sample Select backend'!$M$2),1,0) -> 0 | AN48: =_xlfn.CONCAT('Sample Select backend'!$C$4,ROW(AN48)) -> AE48 | AO48: =_xlfn.CONCAT('Sample Select backend'!$J$2,ROW(AO48)) -> AJ48 | AP48: =_xlfn.CONCAT('Sample Select backend'!$F$4,ROW(AP48)) -> AF48 | AQ48: =_xlfn.CONCAT('Sample Select backend'!$I$10,ROW(AQ48)) -> R48 | AR48: =_xlfn.CONCAT('Sample Select backend'!$M$4,ROW(AR48)) -> AK48 | AS48: =A48 -> Algeria | AT48: =IF(ISNUMBER(C48),C48,IF(OR(C48="general",C48="23;general"),"General",IF(OR(C48="exemption",C48="other (exemption)"),"Tax exemption/waiver/suspension","Other"))) -> General | AU48: =IF(A48<>A47,1,0) -> 0 | AV48: 0
A49: Algeria | B49: 6 | C49: 26 | D49: 20bn dinars for allowances to the unemployed because of COVID | O49: Middle East & North Africa | P49: IBRD | Q49: Lower Middle Income | R49: 0 | S49: -5.48 | T49: -15.74 | U49: 51.4 | V49: -1 | W49: -1 | X49: -1 | Y49: -1 | Z49: -1 | AA49: -1 | AB49: -1 | AC49: -1 | AD49: -1 | AE49: All Regions | AF49: All Income Levels | AG49: 0 | AH49: 1 | AI49: 0 | AJ49: 1 | AK49: All Countries | AL49: =IF(OR(B49="other",B49="international",B49="Transfers",B49="expenditure"),1,0) -> 0 | AM49: =IF(AND(INDIRECT(AN49)='Sample Select backend'!$C$2,INDIRECT(AO49)=1,INDIRECT(AP49)='Sample Select backend'!$F$2,INDIRECT(AQ49)=1,INDIRECT(AR49)='Sample Select backend'!$M$2),1,0) -> 0 | AN49: =_xlfn.CONCAT('Sample Select backend'!$C$4,ROW(AN49)) -> AE49 | AO49: =_xlfn.CONCAT('Sample Select backend'!$J$2,ROW(AO49)) -> AJ49 | AP49: =_xlfn.CONCAT('Sample Select backend'!$F$4,ROW(AP49)) -> AF49 | AQ49: =_xlfn.CONCAT('Sample Select backend'!$I$10,ROW(AQ49)) -> R49 | AR49: =_xlfn.CONCAT('Sample Select backend'!$M$4,ROW(AR49)) -> AK49 | AS49: =A49 -> Algeria | AT49: =IF(ISNUMBER(C49),C49,IF(OR(C49="general",C49="23;general"),"General",IF(OR(C49="exemption",C49="other (exemption)"),"Tax exemption/waiver/suspension","Other"))) -> 26 | AU49: =IF(A49<>A48,1,0) -> 0 | AV49: 0
A50: Algeria | B50: 6 | C50: 25 | D50: 11.5bn for transfers to poor households | O50: Middle East & North Africa | P50: IBRD | Q50: Lower Middle Income | R50: 0 | S50: -5.48 | T50: -15.74 | U50: 51.4 | V50: -1 | W50: -1 | X50: -1 | Y50: -1 | Z50: -1 | AA50: -1 | AB50: -1 | AC50: -1 | AD50: -1 | AE50: All Regions | AF50: All Income Levels | AG50: 0 | AH50: 1 | AI50: 0 | AJ50: 1 | AK50: All Countries | AL50: =IF(OR(B50="other",B50="international",B50="Transfers",B50="expenditure"),1,0) -> 0 | AM50: =IF(AND(INDIRECT(AN50)='Sample Select backend'!$C$2,INDIRECT(AO50)=1,INDIRECT(AP50)='Sample Select backend'!$F$2,INDIRECT(AQ50)=1,INDIRECT(AR50)='Sample Select backend'!$M$2),1,0) -> 0 | AN50: =_xlfn.CONCAT('Sample Select backend'!$C$4,ROW(AN50)) -> AE50 | AO50: =_xlfn.CONCAT('Sample Select backend'!$J$2,ROW(AO50)) -> AJ50 | AP50: =_xlfn.CONCAT('Sample Select backend'!$F$4,ROW(AP50)) -> AF50 | AQ50: =_xlfn.CONCAT('Sample Select backend'!$I$10,ROW(AQ50)) -> R50 | AR50: =_xlfn.CONCAT('Sample Select backend'!$M$4,ROW(AR50)) -> AK50 | AS50: =A50 -> Algeria | AT50: =IF(ISNUMBER(C50),C50,IF(OR(C50="general",C50="23;general"),"General",IF(OR(C50="exemption",C50="other (exemption)"),"Tax exemption/waiver/suspension","Other"))) -> 25 | AU50: =IF(A50<>A49,1,0) -> 0 | AV50: 0
A51: Algeria | B51: Other | C51: N/A | D51: In order to adjust to the new low oil price environment, the SFL plans for a reduction in current and capital spending by 5.7 percent (representing 2.2 percent of 2019 GDP) compared to the initial 2020 budget law. | O51: Middle East & North Africa | P51: IBRD | Q51: Lower Middle Income | R51: 0 | S51: -5.48 | T51: -15.74 | U51: 51.4 | V51: -1 | W51: -1 | X51: -1 | Y51: -1 | Z51: -1 | AA51: -1 | AB51: -1 | AC51: -1 | AD51: -1 | AE51: All Regions | AF51: All Income Levels | AG51: 0 | AH51: 1 | AI51: 0 | AJ51: 1 | AK51: All Countries | AL51: =IF(OR(B51="other",B51="international",B51="Transfers",B51="expenditure"),1,0) -> 1 | AM51: =IF(AND(INDIRECT(AN51)='Sample Select backend'!$C$2,INDIRECT(AO51)=1,INDIRECT(AP51)='Sample Select backend'!$F$2,INDIRECT(AQ51)=1,INDIRECT(AR51)='Sample Select backend'!$M$2),1,0) -> 0 | AN51: =_xlfn.CONCAT('Sample Select backend'!$C$4,ROW(AN51)) -> AE51 | AO51: =_xlfn.CONCAT('Sample Select backend'!$J$2,ROW(AO51)) -> AJ51 | AP51: =_xlfn.CONCAT('Sample Select backend'!$F$4,ROW(AP51)) -> AF51 | AQ51: =_xlfn.CONCAT('Sample Select backend'!$I$10,ROW(AQ51)) -> R51 | AR51: =_xlfn.CONCAT('Sample Select backend'!$M$4,ROW(AR51)) -> AK51 | AS51: =A51 -> Algeria | AT51: =IF(ISNUMBER(C51),C51,IF(OR(C51="general",C51="23;general"),"General",IF(OR(C51="exemption",C51="other (exemption)"),"Tax exemption/waiver/suspension","Other"))) -> Other | AU51: =IF(A51<>A50,1,0) -> 0 | AV51: 0
A52: Algeria | B52: Other | C52: N/A | D52: Contractual deadlines would be relaxed and penalties for companies that experience delays in completing public contracts would be suspended. | O52: Middle East & North Africa | P52: IBRD | Q52: Lower Middle Income | R52: 0 | S52: -5.48 | T52: -15.74 | U52: 51.4 | V52: -1 | W52: -1 | X52: -1 | Y52: -1 | Z52: -1 | AA52: -1 | AB52: -1 | AC52: -1 | AD52: -1 | AE52: All Regions | AF52: All Income Levels | AG52: 0 | AH52: 1 | AI52: 0 | AJ52: 1 | AK52: All Countries | AL52: =IF(OR(B52="other",B52="international",B52="Transfers",B52="expenditure"),1,0) -> 1 | AM52: =IF(AND(INDIRECT(AN52)='Sample Select backend'!$C$2,INDIRECT(AO52)=1,INDIRECT(AP52)='Sample Select backend'!$F$2,INDIRECT(AQ52)=1,INDIRECT(AR52)='Sample Select backend'!$M$2),1,0) -> 0 | AN52: =_xlfn.CONCAT('Sample Select backend'!$C$4,ROW(AN52)) -> AE52 | AO52: =_xlfn.CONCAT('Sample Select backend'!$J$2,ROW(AO52)) -> AJ52 | AP52: =_xlfn.CONCAT('Sample Select backend'!$F$4,ROW(AP52)) -> AF52 | AQ52: =_xlfn.CONCAT('Sample Select backend'!$I$10,ROW(AQ52)) -> R52 | AR52: =_xlfn.CONCAT('Sample Select backend'!$M$4,ROW(AR52)) -> AK52 | AS52: =A52 -> Algeria | AT52: =IF(ISNUMBER(C52),C52,IF(OR(C52="general",C52="23;general"),"General",IF(OR(C52="exemption",C52="other (exemption)"),"Tax exemption/waiver/suspension","Other"))) -> Other | AU52: =IF(A52<>A51,1,0) -> 0 | AV52: 0
A53: Algeria | B53: 2 | C53: 14 | D53: Possibility of requesting a payment schedule for tax debts for taxpayers who find themselves in a difficult financial situation. | O53: Middle East & North Africa | P53: IBRD | Q53: Lower Middle Income | R53: 0 | S53: -5.48 | T53: -15.74 | U53: 51.4 | V53: -1 | W53: -1 | X53: -1 | Y53: -1 | Z53: -1 | AA53: -1 | AB53: -1 | AC53: -1 | AD53: -1 | AE53: All Regions | AF53: All Income Levels | AG53: 0 | AH53: 1 | AI53: 0 | AJ53: 1 | AK53: All Countries | AL53: =IF(OR(B53="other",B53="international",B53="Transfers",B53="expenditure"),1,0) -> 0 | AM53: =IF(AND(INDIRECT(AN53)='Sample Select backend'!$C$2,INDIRECT(AO53)=1,INDIRECT(AP53)='Sample Select backend'!$F$2,INDIRECT(AQ53)=1,INDIRECT(AR53)='Sample Select backend'!$M$2),1,0) -> 0 | AN53: =_xlfn.CONCAT('Sample Select backend'!$C$4,ROW(AN53)) -> AE53 | AO53: =_xlfn.CONCAT('Sample Select backend'!$J$2,ROW(AO53)) -> AJ53 | AP53: =_xlfn.CONCAT('Sample Select backend'!$F$4,ROW(AP53)) -> AF53 | AQ53: =_xlfn.CONCAT('Sample Select backend'!$I$10,ROW(AQ53)) -> R53 | AR53: =_xlfn.CONCAT('Sample Select backend'!$M$4,ROW(AR53)) -> AK53 | AS53: =A53 -> Algeria | AT53: =IF(ISNUMBER(C53),C53,IF(OR(C53="general",C53="23;general"),"General",IF(OR(C53="exemption",C53="other (exemption)"),"Tax exemption/waiver/suspension","Other"))) -> 14 | AU53: =IF(A53<>A52,1,0) -> 0 | AV53: 0
A54: Algeria | B54: 1 | C54: 5 | D54: The deadline for the subscription of the monthly G-50 declaration in February and March and payment of related duties and taxes is extended until 20 May 2020. | O54: Middle East & North Africa | P54: IBRD | Q54: Lower Middle Income | R54: 0 | S54: -5.48 | T54: -15.74 | U54: 51.4 | V54: -1 | W54: -1 | X54: -1 | Y54: -1 | Z54: -1 | AA54: -1 | AB54: -1 | AC54: -1 | AD54: -1 | AE54: All Regions | AF54: All Income Levels | AG54: 0 | AH54: 1 | AI54: 0 | AJ54: 1 | AK54: All Countries | AL54: =IF(OR(B54="other",B54="international",B54="Transfers",B54="expenditure"),1,0) -> 0 | AM54: =IF(AND(INDIRECT(AN54)='Sample Select backend'!$C$2,INDIRECT(AO54)=1,INDIRECT(AP54)='Sample Select backend'!$F$2,INDIRECT(AQ54)=1,INDIRECT(AR54)='Sample Select backend'!$M$2),1,0) -> 0 | AN54: =_xlfn.CONCAT('Sample Select backend'!$C$4,ROW(AN54)) -> AE54 | AO54: =_xlfn.CONCAT('Sample Select backend'!$J$2,ROW(AO54)) -> AJ54 | AP54: =_xlfn.CONCAT('Sample Select backend'!$F$4,ROW(AP54)) -> AF54 | AQ54: =_xlfn.CONCAT('Sample Select backend'!$I$10,ROW(AQ54)) -> R54 | AR54: =_xlfn.CONCAT('Sample Select backend'!$M$4,ROW(AR54)) -> AK54 | AS54: =A54 -> Algeria | AT54: =IF(ISNUMBER(C54),C54,IF(OR(C54="general",C54="23;general"),"General",IF(OR(C54="exemption",C54="other (exemption)"),"Tax exemption/waiver/suspension","Other"))) -> 5 | AU54: =IF(A54<>A53,1,0) -> 0 | AV54: 0
A55: Algeria | B55: 1 | C55: 11 | D55: Suspension of the taxation of unaffected profits in the 2016 and subsequent financial years, provided for by the provisions of Article 15 of the Finance Act for 2020. | O55: Middle East & North Africa | P55: IBRD | Q55: Lower Middle Income | R55: 0 | S55: -5.48 | T55: -15.74 | U55: 51.4 | V55: -1 | W55: -1 | X55: -1 | Y55: -1 | Z55: -1 | AA55: -1 | AB55: -1 | AC55: -1 | AD55: -1 | AE55: All Regions | AF55: All Income Levels | AG55: 0 | AH55: 1 | AI55: 0 | AJ55: 1 | AK55: All Countries | AL55: =IF(OR(B55="other",B55="international",B55="Transfers",B55="expenditure"),1,0) -> 0 | AM55: =IF(AND(INDIRECT(AN55)='Sample Select backend'!$C$2,INDIRECT(AO55)=1,INDIRECT(AP55)='Sample Select backend'!$F$2,INDIRECT(AQ55)=1,INDIRECT(AR55)='Sample Select backend'!$M$2),1,0) -> 0 | AN55: =_xlfn.CONCAT('Sample Select backend'!$C$4,ROW(AN55)) -> AE55 | AO55: =_xlfn.CONCAT('Sample Select backend'!$J$2,ROW(AO55)) -> AJ55 | AP55: =_xlfn.CONCAT('Sample Select backend'!$F$4,ROW(AP55)) -> AF55 | AQ55: =_xlfn.CONCAT('Sample Select backend'!$I$10,ROW(AQ55)) -> R55 | AR55: =_xlfn.CONCAT('Sample Select backend'!$M$4,ROW(AR55)) -> AK55 | AS55: =A55 -> Algeria | AT55: =IF(ISNUMBER(C55),C55,IF(OR(C55="general",C55="23;general"),"General",IF(OR(C55="exemption",C55="other (exemption)"),"Tax exemption/waiver/suspension","Other"))) -> 11 | AU55: =IF(A55<>A54,1,0) -> 0 | AV55: 0
A56: Angola | B56: 1 | C56: 5 | D56: Delays on filing taxes for selected imports were granted. | E56: 2 | F56: 2 | G56: 2 | H56: 1 | I56: 2 | J56: 1 | K56: 1 | L56: 1 | M56: 1 | N56: AGO | O56: Sub-Saharan Africa | P56: IBRD | Q56: Lower Middle Income | R56: 0 | S56: -4.04 | T56: 4.75 | U56: 128.22 | V56: =IF(E56>0,1,IF(E56<0,0,-1)) -> 1 | W56: =IF(F56>0,1,IF(F56<0,0,-1)) -> 1 | X56: =IF(G56>0,1,IF(G56<0,0,-1)) -> 1 | Y56: =IF(H56>0,1,IF(H56<0,0,-1)) -> 1 | Z56: =IF(I56>0,1,IF(I56<0,0,-1)) -> 1 | AA56: =IF(J56>0,1,IF(J56<0,0,-1)) -> 1 | AB56: =IF(K56>0,1,IF(K56<0,0,-1)) -> 1 | AC56: =IF(L56>0,1,IF(L56<0,0,-1)) -> 1 | AD56: =IF(M56>0,1,IF(M56<0,0,-1)) -> 1 | AE56: All Regions | AF56: All Income Levels | AG56: 0 | AH56: 1 | AI56: 0 | AJ56: 1 | AK56: All Countries | AL56: =IF(OR(B56="other",B56="international",B56="Transfers",B56="expenditure"),1,0) -> 0 | AM56: =IF(AND(INDIRECT(AN56)='Sample Select backend'!$C$2,INDIRECT(AO56)=1,INDIRECT(AP56)='Sample Select backend'!$F$2,INDIRECT(AQ56)=1,INDIRECT(AR56)='Sample Select backend'!$M$2),1,0) -> 0 | AN56: =_xlfn.CONCAT('Sample Select backend'!$C$4,ROW(AN56)) -> AE56 | AO56: =_xlfn.CONCAT('Sample Select backend'!$J$2,ROW(AO56)) -> AJ56 | AP56: =_xlfn.CONCAT('Sample Select backend'!$F$4,ROW(AP56)) -> AF56 | AQ56: =_xlfn.CONCAT('Sample Select backend'!$I$10,ROW(AQ56)) -> R56 | AR56: =_xlfn.CONCAT('Sample Select backend'!$M$4,ROW(AR56)) -> AK56 | AS56: =A56 -> Angola | AT56: =IF(ISNUMBER(C56),C56,IF(OR(C56="general",C56="23;general"),"General",IF(OR(C56="exemption",C56="other (exemption)"),"Tax exemption/waiver/suspension","Other"))) -> 5 | AU56: =IF(A56<>A55,1,0) -> 1 | AV56: 1
A57: Angola | B57: 5 | C57: general | D57: Additional health care spending to respond to the virus, estimated at USD 40 million (announced). | E57: 1 | F57: -2 | G57: -2 | H57: -1 | I57: -2 | J57: 1 | K57: 1 | L57: 1 | M57: 1 | N57: AGO | O57: Sub-Saharan Africa | P57: IBRD | Q57: Lower Middle Income | R57: 0 | S57: -4.04 | T57: 4.75 | U57: 128.22 | V57: =IF(E57>0,1,IF(E57<0,0,-1)) -> 1 | W57: =IF(F57>0,1,IF(F57<0,0,-1)) -> 0 | X57: =IF(G57>0,1,IF(G57<0,0,-1)) -> 0 | Y57: =IF(H57>0,1,IF(H57<0,0,-1)) -> 0 | Z57: =IF(I57>0,1,IF(I57<0,0,-1)) -> 0 | AA57: =IF(J57>0,1,IF(J57<0,0,-1)) -> 1 | AB57: =IF(K57>0,1,IF(K57<0,0,-1)) -> 1 | AC57: =IF(L57>0,1,IF(L57<0,0,-1)) -> 1 | AD57: =IF(M57>0,1,IF(M57<0,0,-1)) -> 1 | AE57: All Regions | AF57: All Income Levels | AG57: 0 | AH57: 1 | AI57: 0 | AJ57: 1 | AK57: All Countries | AL57: =IF(OR(B57="other",B57="international",B57="Transfers",B57="expenditure"),1,0) -> 0 | AM57: =IF(AND(INDIRECT(AN57)='Sample Select backend'!$C$2,INDIRECT(AO57)=1,INDIRECT(AP57)='Sample Select backend'!$F$2,INDIRECT(AQ57)=1,INDIRECT(AR57)='Sample Select backend'!$M$2),1,0) -> 0 | AN57: =_xlfn.CONCAT('Sample Select backend'!$C$4,ROW(AN57)) -> AE57 | AO57: =_xlfn.CONCAT('Sample Select backend'!$J$2,ROW(AO57)) -> AJ57 | AP57: =_xlfn.CONCAT('Sample Select backend'!$F$4,ROW(AP57)) -> AF57 | AQ57: =_xlfn.CONCAT('Sample Select backend'!$I$10,ROW(AQ57)) -> R57 | AR57: =_xlfn.CONCAT('Sample Select backend'!$M$4,ROW(AR57)) -> AK57 | AS57: =A57 -> Angola | AT57: =IF(ISNUMBER(C57),C57,IF(OR(C57="general",C57="23;general"),"General",IF(OR(C57="exemption",C57="other (exemption)"),"Tax exemption/waiver/suspension","Other"))) -> General | AU57: =IF(A57<>A56,1,0) -> 0 | AV57: 1
A58: Angola | B58: 3 | C58: exemption | D58: Tax exemptions on humanitarian aid and donations. | E58: 1 | F58: 2 | G58: -2 | H58: -1 | I58: -2 | J58: -2 | K58: -2 | M58: 1 | N58: AGO | O58: Sub-Saharan Africa | P58: IBRD | Q58: Lower Middle Income | R58: 0 | S58: -4.04 | T58: 4.75 | U58: 128.22 | V58: =IF(E58>0,1,IF(E58<0,0,-1)) -> 1 | W58: =IF(F58>0,1,IF(F58<0,0,-1)) -> 1 | X58: =IF(G58>0,1,IF(G58<0,0,-1)) -> 0 | Y58: =IF(H58>0,1,IF(H58<0,0,-1)) -> 0 | Z58: =IF(I58>0,1,IF(I58<0,0,-1)) -> 0 | AA58: =IF(J58>0,1,IF(J58<0,0,-1)) -> 0 | AB58: =IF(K58>0,1,IF(K58<0,0,-1)) -> 0 | AC58: =IF(L58>0,1,IF(L58<0,0,-1)) -> -1 | AD58: =IF(M58>0,1,IF(M58<0,0,-1)) -> 1 | AE58: All Regions | AF58: All Income Levels | AG58: 0 | AH58: 1 | AI58: 0 | AJ58: 1 | AK58: All Countries | AL58: =IF(OR(B58="other",B58="international",B58="Transfers",B58="expenditure"),1,0) -> 0 | AM58: =IF(AND(INDIRECT(AN58)='Sample Select backend'!$C$2,INDIRECT(AO58)=1,INDIRECT(AP58)='Sample Select backend'!$F$2,INDIRECT(AQ58)=1,INDIRECT(AR58)='Sample Select backend'!$M$2),1,0) -> 0 | AN58: =_xlfn.CONCAT('Sample Select backend'!$C$4,ROW(AN58)) -> AE58 | AO58: =_xlfn.CONCAT('Sample Select backend'!$J$2,ROW(AO58)) -> AJ58 | AP58: =_xlfn.CONCAT('Sample Select backend'!$F$4,ROW(AP58)) -> AF58 | AQ58: =_xlfn.CONCAT('Sample Select backend'!$I$10,ROW(AQ58)) -> R58 | AR58: =_xlfn.CONCAT('Sample Select backend'!$M$4,ROW(AR58)) -> AK58 | AS58: =A58 -> Angola | AT58: =IF(ISNUMBER(C58),C58,IF(OR(C58="general",C58="23;general"),"General",IF(OR(C58="exemption",C58="other (exemption)"),"Tax exemption/waiver/suspension","Other"))) -> Tax exemption/waiver/suspension | AU58: =IF(A58<>A57,1,0) -> 0 | AV58: 1
A59: Angola | B59: 1 | C59: 4 | D59: Granting a tax credit for a period of 12 months on VAT over importation of capital and raw material goods necessary to the manufacture of essential goods and other priority national goods as defined in Presidential Decree no. 23/19, of 14 January, such as sugar, flour and oil. | O59: Sub-Saharan Africa | P59: IBRD | Q59: Lower Middle Income | R59: 0 | S59: -4.04 | T59: 4.75 | U59: 128.22 | V59: -1 | W59: -1 | X59: -1 | Y59: -1 | Z59: -1 | AA59: -1 | AB59: -1 | AC59: -1 | AD59: -1 | AE59: All Regions | AF59: All Income Levels | AG59: 0 | AH59: 1 | AI59: 0 | AJ59: 1 | AK59: All Countries | AL59: =IF(OR(B59="other",B59="international",B59="Transfers",B59="expenditure"),1,0) -> 0 | AM59: =IF(AND(INDIRECT(AN59)='Sample Select backend'!$C$2,INDIRECT(AO59)=1,INDIRECT(AP59)='Sample Select backend'!$F$2,INDIRECT(AQ59)=1,INDIRECT(AR59)='Sample Select backend'!$M$2),1,0) -> 0 | AN59: =_xlfn.CONCAT('Sample Select backend'!$C$4,ROW(AN59)) -> AE59 | AO59: =_xlfn.CONCAT('Sample Select backend'!$J$2,ROW(AO59)) -> AJ59 | AP59: =_xlfn.CONCAT('Sample Select backend'!$F$4,ROW(AP59)) -> AF59 | AQ59: =_xlfn.CONCAT('Sample Select backend'!$I$10,ROW(AQ59)) -> R59 | AR59: =_xlfn.CONCAT('Sample Select backend'!$M$4,ROW(AR59)) -> AK59 | AS59: =A59 -> Angola | AT59: =IF(ISNUMBER(C59),C59,IF(OR(C59="general",C59="23;general"),"General",IF(OR(C59="exemption",C59="other (exemption)"),"Tax exemption/waiver/suspension","Other"))) -> 4 | AU59: =IF(A59<>A58,1,0) -> 0 | AV59: 0
A60: Angola | B60: 5 | C60: 24 | D60: US$80 million are being spent on 250 Cuban doctors who arrived in Angola to help. | O60: Sub-Saharan Africa | P60: IBRD | Q60: Lower Middle Income | R60: 0 | S60: -4.04 | T60: 4.75 | U60: 128.22 | V60: -1 | W60: -1 | X60: -1 | Y60: -1 | Z60: -1 | AA60: -1 | AB60: -1 | AC60: -1 | AD60: -1 | AE60: All Regions | AF60: All Income Levels | AG60: 0 | AH60: 1 | AI60: 0 | AJ60: 1 | AK60: All Countries | AL60: =IF(OR(B60="other",B60="international",B60="Transfers",B60="expenditure"),1,0) -> 0 | AM60: =IF(AND(INDIRECT(AN60)='Sample Select backend'!$C$2,INDIRECT(AO60)=1,INDIRECT(AP60)='Sample Select backend'!$F$2,INDIRECT(AQ60)=1,INDIRECT(AR60)='Sample Select backend'!$M$2),1,0) -> 0 | AN60: =_xlfn.CONCAT('Sample Select backend'!$C$4,ROW(AN60)) -> AE60 | AO60: =_xlfn.CONCAT('Sample Select backend'!$J$2,ROW(AO60)) -> AJ60 | AP60: =_xlfn.CONCAT('Sample Select backend'!$F$4,ROW(AP60)) -> AF60 | AQ60: =_xlfn.CONCAT('Sample Select backend'!$I$10,ROW(AQ60)) -> R60 | AR60: =_xlfn.CONCAT('Sample Select backend'!$M$4,ROW(AR60)) -> AK60 | AS60: =A60 -> Angola | AT60: =IF(ISNUMBER(C60),C60,IF(OR(C60="general",C60="23;general"),"General",IF(OR(C60="exemption",C60="other (exemption)"),"Tax exemption/waiver/suspension","Other"))) -> 24 | AU60: =IF(A60<>A59,1,0) -> 0 | AV60: 0
A61: Angola | B61: 1 | C61: 6 | D61: Extension of CIT deadlines to comply with tax obligations, until May 29th for taxpayers within Group B and June 30th for taxpayers within Group A | O61: Sub-Saharan Africa | P61: IBRD | Q61: Lower Middle Income | R61: 0 | S61: -4.04 | T61: 4.75 | U61: 128.22 | V61: -1 | W61: -1 | X61: -1 | Y61: -1 | Z61: -1 | AA61: -1 | AB61: -1 | AC61: -1 | AD61: -1 | AE61: All Regions | AF61: All Income Levels | AG61: 0 | AH61: 1 | AI61: 0 | AJ61: 1 | AK61: All Countries | AL61: =IF(OR(B61="other",B61="international",B61="Transfers",B61="expenditure"),1,0) -> 0 | AM61: =IF(AND(INDIRECT(AN61)='Sample Select backend'!$C$2,INDIRECT(AO61)=1,INDIRECT(AP61)='Sample Select backend'!$F$2,INDIRECT(AQ61)=1,INDIRECT(AR61)='Sample Select backend'!$M$2),1,0) -> 0 | AN61: =_xlfn.CONCAT('Sample Select backend'!$C$4,ROW(AN61)) -> AE61 | AO61: =_xlfn.CONCAT('Sample Select backend'!$J$2,ROW(AO61)) -> AJ61 | AP61: =_xlfn.CONCAT('Sample Select backend'!$F$4,ROW(AP61)) -> AF61 | AQ61: =_xlfn.CONCAT('Sample Select backend'!$I$10,ROW(AQ61)) -> R61 | AR61: =_xlfn.CONCAT('Sample Select backend'!$M$4,ROW(AR61)) -> AK61 | AS61: =A61 -> Angola | AT61: =IF(ISNUMBER(C61),C61,IF(OR(C61="general",C61="23;general"),"General",IF(OR(C61="exemption",C61="other (exemption)"),"Tax exemption/waiver/suspension","Other"))) -> 6 | AU61: =IF(A61<>A60,1,0) -> 0 | AV61: 0
A62: Angola | B62: 1 | C62: 6 | D62: Deferral of payment of social security contributions due by employers (8%), regarding the 2nd quarter of 2020, to be paid in 6 instalments (July to December), interest free | O62: Sub-Saharan Africa | P62: IBRD | Q62: Lower Middle Income | R62: 0 | S62: -4.04 | T62: 4.75 | U62: 128.22 | V62: -1 | W62: -1 | X62: -1 | Y62: -1 | Z62: -1 | AA62: -1 | AB62: -1 | AC62: -1 | AD62: -1 | AE62: All Regions | AF62: All Income Levels | AG62: 0 | AH62: 1 | AI62: 0 | AJ62: 1 | AK62: All Countries | AL62: =IF(OR(B62="other",B62="international",B62="Transfers",B62="expenditure"),1,0) -> 0 | AM62: =IF(AND(INDIRECT(AN62)='Sample Select backend'!$C$2,INDIRECT(AO62)=1,INDIRECT(AP62)='Sample Select backend'!$F$2,INDIRECT(AQ62)=1,INDIRECT(AR62)='Sample Select backend'!$M$2),1,0) -> 0 | AN62: =_xlfn.CONCAT('Sample Select backend'!$C$4,ROW(AN62)) -> AE62 | AO62: =_xlfn.CONCAT('Sample Select backend'!$J$2,ROW(AO62)) -> AJ62 | AP62: =_xlfn.CONCAT('Sample Select backend'!$F$4,ROW(AP62)) -> AF62 | AQ62: =_xlfn.CONCAT('Sample Select backend'!$I$10,ROW(AQ62)) -> R62 | AR62: =_xlfn.CONCAT('Sample Select backend'!$M$4,ROW(AR62)) -> AK62 | AS62: =A62 -> Angola | AT62: =IF(ISNUMBER(C62),C62,IF(OR(C62="general",C62="23;general"),"General",IF(OR(C62="exemption",C62="other (exemption)"),"Tax exemption/waiver/suspension","Other"))) -> 6 | AU62: =IF(A62<>A61,1,0) -> 0 | AV62: 0
A63: Angola | B63: 2 | C63: exemption | D63: In terms of family support, the private sector is allowed to transfer to the employee the contribution to the social security (the employee contribution - 3%), in the months of April, May and June | O63: Sub-Saharan Africa | P63: IBRD | Q63: Lower Middle Income | R63: 0 | S63: -4.04 | T63: 4.75 | U63: 128.22 | V63: -1 | W63: -1 | X63: -1 | Y63: -1 | Z63: -1 | AA63: -1 | AB63: -1 | AC63: -1 | AD63: -1 | AE63: All Regions | AF63: All Income Levels | AG63: 0 | AH63: 1 | AI63: 0 | AJ63: 1 | AK63: All Countries | AL63: =IF(OR(B63="other",B63="international",B63="Transfers",B63="expenditure"),1,0) -> 0 | AM63: =IF(AND(INDIRECT(AN63)='Sample Select backend'!$C$2,INDIRECT(AO63)=1,INDIRECT(AP63)='Sample Select backend'!$F$2,INDIRECT(AQ63)=1,INDIRECT(AR63)='Sample Select backend'!$M$2),1,0) -> 0 | AN63: =_xlfn.CONCAT('Sample Select backend'!$C$4,ROW(AN63)) -> AE63 | AO63: =_xlfn.CONCAT('Sample Select backend'!$J$2,ROW(AO63)) -> AJ63 | AP63: =_xlfn.CONCAT('Sample Select backend'!$F$4,ROW(AP63)) -> AF63 | AQ63: =_xlfn.CONCAT('Sample Select backend'!$I$10,ROW(AQ63)) -> R63 | AR63: =_xlfn.CONCAT('Sample Select backend'!$M$4,ROW(AR63)) -> AK63 | AS63: =A63 -> Angola | AT63: =IF(ISNUMBER(C63),C63,IF(OR(C63="general",C63="23;general"),"General",IF(OR(C63="exemption",C63="other (exemption)"),"Tax exemption/waiver/suspension","Other"))) -> Tax exemption/waiver/suspension | AU63: =IF(A63<>A62,1,0) -> 0 | AV63: 0
A64: Angola | B64: 3 | C64: other | D64: Imported goods, as well as those produced in Angola, donated for the prevention and expansion of COVID-19, are considered as a deductible cost for the purposes of Industrial Tax. The quantities and type of goods donated shall be registered, as well as the respective beneficiaries. | O64: Sub-Saharan Africa | P64: IBRD | Q64: Lower Middle Income | R64: 0 | S64: -4.04 | T64: 4.75 | U64: 128.22 | V64: -1 | W64: -1 | X64: -1 | Y64: -1 | Z64: -1 | AA64: -1 | AB64: -1 | AC64: -1 | AD64: -1 | AE64: All Regions | AF64: All Income Levels | AG64: 0 | AH64: 1 | AI64: 0 | AJ64: 1 | AK64: All Countries | AL64: =IF(OR(B64="other",B64="international",B64="Transfers",B64="expenditure"),1,0) -> 0 | AM64: =IF(AND(INDIRECT(AN64)='Sample Select backend'!$C$2,INDIRECT(AO64)=1,INDIRECT(AP64)='Sample Select backend'!$F$2,INDIRECT(AQ64)=1,INDIRECT(AR64)='Sample Select backend'!$M$2),1,0) -> 0 | AN64: =_xlfn.CONCAT('Sample Select backend'!$C$4,ROW(AN64)) -> AE64 | AO64: =_xlfn.CONCAT('Sample Select backend'!$J$2,ROW(AO64)) -> AJ64 | AP64: =_xlfn.CONCAT('Sample Select backend'!$F$4,ROW(AP64)) -> AF64 | AQ64: =_xlfn.CONCAT('Sample Select backend'!$I$10,ROW(AQ64)) -> R64 | AR64: =_xlfn.CONCAT('Sample Select backend'!$M$4,ROW(AR64)) -> AK64 | AS64: =A64 -> Angola | AT64: =IF(ISNUMBER(C64),C64,IF(OR(C64="general",C64="23;general"),"General",IF(OR(C64="exemption",C64="other (exemption)"),"Tax exemption/waiver/suspension","Other"))) -> Other | AU64: =IF(A64<>A63,1,0) -> 0 | AV64: 0
A65: Angola | B65: 1 | C65: 12 | D65: All external inspection and supervision services are suspended. | O65: Sub-Saharan Africa | P65: IBRD | Q65: Lower Middle Income | R65: 0 | S65: -4.04 | T65: 4.75 | U65: 128.22 | V65: -1 | W65: -1 | X65: -1 | Y65: -1 | Z65: -1 | AA65: -1 | AB65: -1 | AC65: -1 | AD65: -1 | AE65: All Regions | AF65: All Income Levels | AG65: 0 | AH65: 1 | AI65: 0 | AJ65: 1 | AK65: All Countries | AL65: =IF(OR(B65="other",B65="international",B65="Transfers",B65="expenditure"),1,0) -> 0 | AM65: =IF(AND(INDIRECT(AN65)='Sample Select backend'!$C$2,INDIRECT(AO65)=1,INDIRECT(AP65)='Sample Select backend'!$F$2,INDIRECT(AQ65)=1,INDIRECT(AR65)='Sample Select backend'!$M$2),1,0) -> 0 | AN65: =_xlfn.CONCAT('Sample Select backend'!$C$4,ROW(AN65)) -> AE65 | AO65: =_xlfn.CONCAT('Sample Select backend'!$J$2,ROW(AO65)) -> AJ65 | AP65: =_xlfn.CONCAT('Sample Select backend'!$F$4,ROW(AP65)) -> AF65 | AQ65: =_xlfn.CONCAT('Sample Select backend'!$I$10,ROW(AQ65)) -> R65 | AR65: =_xlfn.CONCAT('Sample Select backend'!$M$4,ROW(AR65)) -> AK65 | AS65: =A65 -> Angola | AT65: =IF(ISNUMBER(C65),C65,IF(OR(C65="general",C65="23;general"),"General",IF(OR(C65="exemption",C65="other (exemption)"),"Tax exemption/waiver/suspension","Other"))) -> 12 | AU65: =IF(A65<>A64,1,0) -> 0 | AV65: 0
A66: Angola | B66: 2 | C66: 14 | D66: Property tax can be paid in four instalments. | O66: Sub-Saharan Africa | P66: IBRD | Q66: Lower Middle Income | R66: 0 | S66: -4.04 | T66: 4.75 | U66: 128.22 | V66: -1 | W66: -1 | X66: -1 | Y66: -1 | Z66: -1 | AA66: -1 | AB66: -1 | AC66: -1 | AD66: -1 | AE66: All Regions | AF66: All Income Levels | AG66: 0 | AH66: 1 | AI66: 0 | AJ66: 1 | AK66: All Countries | AL66: =IF(OR(B66="other",B66="international",B66="Transfers",B66="expenditure"),1,0) -> 0 | AM66: =IF(AND(INDIRECT(AN66)='Sample Select backend'!$C$2,INDIRECT(AO66)=1,INDIRECT(AP66)='Sample Select backend'!$F$2,INDIRECT(AQ66)=1,INDIRECT(AR66)='Sample Select backend'!$M$2),1,0) -> 0 | AN66: =_xlfn.CONCAT('Sample Select backend'!$C$4,ROW(AN66)) -> AE66 | AO66: =_xlfn.CONCAT('Sample Select backend'!$J$2,ROW(AO66)) -> AJ66 | AP66: =_xlfn.CONCAT('Sample Select backend'!$F$4,ROW(AP66)) -> AF66 | AQ66: =_xlfn.CONCAT('Sample Select backend'!$I$10,ROW(AQ66)) -> R66 | AR66: =_xlfn.CONCAT('Sample Select backend'!$M$4,ROW(AR66)) -> AK66 | AS66: =A66 -> Angola | AT66: =IF(ISNUMBER(C66),C66,IF(OR(C66="general",C66="23;general"),"General",IF(OR(C66="exemption",C66="other (exemption)"),"Tax exemption/waiver/suspension","Other"))) -> 14 | AU66: =IF(A66<>A65,1,0) -> 0 | AV66: 0
A67: Angola | B67: Other | C67: N/A | D67: Angola reduces ministerial departments from 28 to 21 | O67: Sub-Saharan Africa | P67: IBRD | Q67: Lower Middle Income | R67: 0 | S67: -4.04 | T67: 4.75 | U67: 128.22 | V67: -1 | W67: -1 | X67: -1 | Y67: -1 | Z67: -1 | AA67: -1 | AB67: -1 | AC67: -1 | AD67: -1 | AE67: All Regions | AF67: All Income Levels | AG67: 0 | AH67: 1 | AI67: 0 | AJ67: 1 | AK67: All Countries | AL67: =IF(OR(B67="other",B67="international",B67="Transfers",B67="expenditure"),1,0) -> 1 | AM67: =IF(AND(INDIRECT(AN67)='Sample Select backend'!$C$2,INDIRECT(AO67)=1,INDIRECT(AP67)='Sample Select backend'!$F$2,INDIRECT(AQ67)=1,INDIRECT(AR67)='Sample Select backend'!$M$2),1,0) -> 0 | AN67: =_xlfn.CONCAT('Sample Select backend'!$C$4,ROW(AN67)) -> AE67 | AO67: =_xlfn.CONCAT('Sample Select backend'!$J$2,ROW(AO67)) -> AJ67 | AP67: =_xlfn.CONCAT('Sample Select backend'!$F$4,ROW(AP67)) -> AF67 | AQ67: =_xlfn.CONCAT('Sample Select backend'!$I$10,ROW(AQ67)) -> R67 | AR67: =_xlfn.CONCAT('Sample Select backend'!$M$4,ROW(AR67)) -> AK67 | AS67: =A67 -> Angola | AT67: =IF(ISNUMBER(C67),C67,IF(OR(C67="general",C67="23;general"),"General",IF(OR(C67="exemption",C67="other (exemption)"),"Tax exemption/waiver/suspension","Other"))) -> Other | AU67: =IF(A67<>A66,1,0) -> 0 | AV67: 0
A68: Angola | B68: Other | C68: N/A | D68: Merges institutes and national directorates | O68: Sub-Saharan Africa | P68: IBRD | Q68: Lower Middle Income | R68: 0 | S68: -4.04 | T68: 4.75 | U68: 128.22 | V68: -1 | W68: -1 | X68: -1 | Y68: -1 | Z68: -1 | AA68: -1 | AB68: -1 | AC68: -1 | AD68: -1 | AE68: All Regions | AF68: All Income Levels | AG68: 0 | AH68: 1 | AI68: 0 | AJ68: 1 | AK68: All Countries | AL68: =IF(OR(B68="other",B68="international",B68="Transfers",B68="expenditure"),1,0) -> 1 | AM68: =IF(AND(INDIRECT(AN68)='Sample Select backend'!$C$2,INDIRECT(AO68)=1,INDIRECT(AP68)='Sample Select backend'!$F$2,INDIRECT(AQ68)=1,INDIRECT(AR68)='Sample Select backend'!$M$2),1,0) -> 0 | AN68: =_xlfn.CONCAT('Sample Select backend'!$C$4,ROW(AN68)) -> AE68 | AO68: =_xlfn.CONCAT('Sample Select backend'!$J$2,ROW(AO68)) -> AJ68 | AP68: =_xlfn.CONCAT('Sample Select backend'!$F$4,ROW(AP68)) -> AF68 | AQ68: =_xlfn.CONCAT('Sample Select backend'!$I$10,ROW(AQ68)) -> R68 | AR68: =_xlfn.CONCAT('Sample Select backend'!$M$4,ROW(AR68)) -> AK68 | AS68: =A68 -> Angola | AT68: =IF(ISNUMBER(C68),C68,IF(OR(C68="general",C68="23;general"),"General",IF(OR(C68="exemption",C68="other (exemption)"),"Tax exemption/waiver/suspension","Other"))) -> Other | AU68: =IF(A68<>A67,1,0) -> 0 | AV68: 0
A69: Angola | B69: Other | C69: N/A | D69: Freezes the recruitment of new civil servants | O69: Sub-Saharan Africa | P69: IBRD | Q69: Lower Middle Income | R69: 0 | S69: -4.04 | T69: 4.75 | U69: 128.22 | V69: -1 | W69: -1 | X69: -1 | Y69: -1 | Z69: -1 | AA69: -1 | AB69: -1 | AC69: -1 | AD69: -1 | AE69: All Regions | AF69: All Income Levels | AG69: 0 | AH69: 1 | AI69: 0 | AJ69: 1 | AK69: All Countries | AL69: =IF(OR(B69="other",B69="international",B69="Transfers",B69="expenditure"),1,0) -> 1 | AM69: =IF(AND(INDIRECT(AN69)='Sample Select backend'!$C$2,INDIRECT(AO69)=1,INDIRECT(AP69)='Sample Select backend'!$F$2,INDIRECT(AQ69)=1,INDIRECT(AR69)='Sample Select backend'!$M$2),1,0) -> 0 | AN69: =_xlfn.CONCAT('Sample Select backend'!$C$4,ROW(AN69)) -> AE69 | AO69: =_xlfn.CONCAT('Sample Select backend'!$J$2,ROW(AO69)) -> AJ69 | AP69: =_xlfn.CONCAT('Sample Select backend'!$F$4,ROW(AP69)) -> AF69 | AQ69: =_xlfn.CONCAT('Sample Select backend'!$I$10,ROW(AQ69)) -> R69 | AR69: =_xlfn.CONCAT('Sample Select backend'!$M$4,ROW(AR69)) -> AK69 | AS69: =A69 -> Angola | AT69: =IF(ISNUMBER(C69),C69,IF(OR(C69="general",C69="23;general"),"General",IF(OR(C69="exemption",C69="other (exemption)"),"Tax exemption/waiver/suspension","Other"))) -> Other | AU69: =IF(A69<>A68,1,0) -> 0 | AV69: 0
A70: Angola | B70: Other | C70: N/A | D70: Forbids the export of medical equipment | O70: Sub-Saharan Africa | P70: IBRD | Q70: Lower Middle Income | R70: 0 | S70: -4.04 | T70: 4.75 | U70: 128.22 | V70: -1 | W70: -1 | X70: -1 | Y70: -1 | Z70: -1 | AA70: -1 | AB70: -1 | AC70: -1 | AD70: -1 | AE70: All Regions | AF70: All Income Levels | AG70: 0 | AH70: 1 | AI70: 0 | AJ70: 1 | AK70: All Countries | AL70: =IF(OR(B70="other",B70="international",B70="Transfers",B70="expenditure"),1,0) -> 1 | AM70: =IF(AND(INDIRECT(AN70)='Sample Select backend'!$C$2,INDIRECT(AO70)=1,INDIRECT(AP70)='Sample Select backend'!$F$2,INDIRECT(AQ70)=1,INDIRECT(AR70)='Sample Select backend'!$M$2),1,0) -> 0 | AN70: =_xlfn.CONCAT('Sample Select backend'!$C$4,ROW(AN70)) -> AE70 | AO70: =_xlfn.CONCAT('Sample Select backend'!$J$2,ROW(AO70)) -> AJ70 | AP70: =_xlfn.CONCAT('Sample Select backend'!$F$4,ROW(AP70)) -> AF70 | AQ70: =_xlfn.CONCAT('Sample Select backend'!$I$10,ROW(AQ70)) -> R70 | AR70: =_xlfn.CONCAT('Sample Select backend'!$M$4,ROW(AR70)) -> AK70 | AS70: =A70 -> Angola | AT70: =IF(ISNUMBER(C70),C70,IF(OR(C70="general",C70="23;general"),"General",IF(OR(C70="exemption",C70="other (exemption)"),"Tax exemption/waiver/suspension","Other"))) -> Other | AU70: =IF(A70<>A69,1,0) -> 0 | AV70: 0
A71: Angola | B71: 5 | C71: 22 | D71: The Angolan State has spent five million US dollars to purchase the equipment for four laboratories carrying out COVID-19 tests | O71: Sub-Saharan Africa | P71: IBRD | Q71: Lower Middle Income | R71: 0 | S71: -4.04 | T71: 4.75 | U71: 128.22 | V71: -1 | W71: -1 | X71: -1 | Y71: -1 | Z71: -1 | AA71: -1 | AB71: -1 | AC71: -1 | AD71: -1 | AE71: All Regions | AF71: All Income Levels | AG71: 0 | AH71: 1 | AI71: 0 | AJ71: 1 | AK71: All Countries | AL71: =IF(OR(B71="other",B71="international",B71="Transfers",B71="expenditure"),1,0) -> 0 | AM71: =IF(AND(INDIRECT(AN71)='Sample Select backend'!$C$2,INDIRECT(AO71)=1,INDIRECT(AP71)='Sample Select backend'!$F$2,INDIRECT(AQ71)=1,INDIRECT(AR71)='Sample Select backend'!$M$2),1,0) -> 0 | AN71: =_xlfn.CONCAT('Sample Select backend'!$C$4,ROW(AN71)) -> AE71 | AO71: =_xlfn.CONCAT('Sample Select backend'!$J$2,ROW(AO71)) -> AJ71 | AP71: =_xlfn.CONCAT('Sample Select backend'!$F$4,ROW(AP71)) -> AF71 | AQ71: =_xlfn.CONCAT('Sample Select backend'!$I$10,ROW(AQ71)) -> R71 | AR71: =_xlfn.CONCAT('Sample Select backend'!$M$4,ROW(AR71)) -> AK71 | AS71: =A71 -> Angola | AT71: =IF(ISNUMBER(C71),C71,IF(OR(C71="general",C71="23;general"),"General",IF(OR(C71="exemption",C71="other (exemption)"),"Tax exemption/waiver/suspension","Other"))) -> 22 | AU71: =IF(A71<>A70,1,0) -> 0 | AV71: 0
A72: Angola | B72: 5 | C72: general | D72: The authorities have purchased about 380 tons of biosecurity material from China, including 50 thousand test kits. | O72: Sub-Saharan Africa | P72: IBRD | Q72: Lower Middle Income | R72: 0 | S72: -4.04 | T72: 4.75 | U72: 128.22 | V72: -1 | W72: -1 | X72: -1 | Y72: -1 | Z72: -1 | AA72: -1 | AB72: -1 | AC72: -1 | AD72: -1 | AE72: All Regions | AF72: All Income Levels | AG72: 0 | AH72: 1 | AI72: 0 | AJ72: 1 | AK72: All Countries | AL72: =IF(OR(B72="other",B72="international",B72="Transfers",B72="expenditure"),1,0) -> 0 | AM72: =IF(AND(INDIRECT(AN72)='Sample Select backend'!$C$2,INDIRECT(AO72)=1,INDIRECT(AP72)='Sample Select backend'!$F$2,INDIRECT(AQ72)=1,INDIRECT(AR72)='Sample Select backend'!$M$2),1,0) -> 0 | AN72: =_xlfn.CONCAT('Sample Select backend'!$C$4,ROW(AN72)) -> AE72 | AO72: =_xlfn.CONCAT('Sample Select backend'!$J$2,ROW(AO72)) -> AJ72 | AP72: =_xlfn.CONCAT('Sample Select backend'!$F$4,ROW(AP72)) -> AF72 | AQ72: =_xlfn.CONCAT('Sample Select backend'!$I$10,ROW(AQ72)) -> R72 | AR72: =_xlfn.CONCAT('Sample Select backend'!$M$4,ROW(AR72)) -> AK72 | AS72: =A72 -> Angola | AT72: =IF(ISNUMBER(C72),C72,IF(OR(C72="general",C72="23;general"),"General",IF(OR(C72="exemption",C72="other (exemption)"),"Tax exemption/waiver/suspension","Other"))) -> General | AU72: =IF(A72<>A71,1,0) -> 0 | AV72: 0
A73: Anguilla | B73: 4 | C73: 20 | D73: Waiving of duties and taxes on essential food and hygiene item imports. | E73: 1 | F73: 2 | G73: -2 | H73: -1 | I73: -2 | J73: -2 | K73: -2 | L73: 2 | M73: 1 | N73: AIA | O73: Latin America & the Caribbean | P73: None | Q73: High Income | R73: 0 | V73: =IF(E73>0,1,IF(E73<0,0,-1)) -> 1 | W73: =IF(F73>0,1,IF(F73<0,0,-1)) -> 1 | X73: =IF(G73>0,1,IF(G73<0,0,-1)) -> 0 | Y73: =IF(H73>0,1,IF(H73<0,0,-1)) -> 0 | Z73: =IF(I73>0,1,IF(I73<0,0,-1)) -> 0 | AA73: =IF(J73>0,1,IF(J73<0,0,-1)) -> 0 | AB73: =IF(K73>0,1,IF(K73<0,0,-1)) -> 0 | AC73: =IF(L73>0,1,IF(L73<0,0,-1)) -> 1 | AD73: =IF(M73>0,1,IF(M73<0,0,-1)) -> 1 | AE73: All Regions | AF73: All Income Levels | AG73: 0 | AH73: 0 | AI73: 0 | AJ73: 1 | AK73: All Countries | AL73: =IF(OR(B73="other",B73="international",B73="Transfers",B73="expenditure"),1,0) -> 0 | AM73: =IF(AND(INDIRECT(AN73)='Sample Select backend'!$C$2,INDIRECT(AO73)=1,INDIRECT(AP73)='Sample Select backend'!$F$2,INDIRECT(AQ73)=1,INDIRECT(AR73)='Sample Select backend'!$M$2),1,0) -> 0 | AN73: =_xlfn.CONCAT('Sample Select backend'!$C$4,ROW(AN73)) -> AE73 | AO73: =_xlfn.CONCAT('Sample Select backend'!$J$2,ROW(AO73)) -> AJ73 | AP73: =_xlfn.CONCAT('Sample Select backend'!$F$4,ROW(AP73)) -> AF73 | AQ73: =_xlfn.CONCAT('Sample Select backend'!$I$10,ROW(AQ73)) -> R73 | AR73: =_xlfn.CONCAT('Sample Select backend'!$M$4,ROW(AR73)) -> AK73 | AS73: =A73 -> Anguilla | AT73: =IF(ISNUMBER(C73),C73,IF(OR(C73="general",C73="23;general"),"General",IF(OR(C73="exemption",C73="other (exemption)"),"Tax exemption/waiver/suspension","Other"))) -> 20 | AU73: =IF(A73<>A72,1,0) -> 1 | AV73: 1
A74: Anguilla | B74: 7 | C74: 30 | D74: Fund to grant small low interest loans. | E74: -1 | F74: 1 | G74: 2 | H74: 1 | I74: 2 | J74: 2 | K74: 1 | L74: -1 | M74: 1 | N74: AIA | O74: Latin America & the Caribbean | P74: None | Q74: High Income | R74: 0 | V74: =IF(E74>0,1,IF(E74<0,0,-1)) -> 0 | W74: =IF(F74>0,1,IF(F74<0,0,-1)) -> 1 | X74: =IF(G74>0,1,IF(G74<0,0,-1)) -> 1 | Y74: =IF(H74>0,1,IF(H74<0,0,-1)) -> 1 | Z74: =IF(I74>0,1,IF(I74<0,0,-1)) -> 1 | AA74: =IF(J74>0,1,IF(J74<0,0,-1)) -> 1 | AB74: =IF(K74>0,1,IF(K74<0,0,-1)) -> 1 | AC74: =IF(L74>0,1,IF(L74<0,0,-1)) -> 0 | AD74: =IF(M74>0,1,IF(M74<0,0,-1)) -> 1 | AE74: All Regions | AF74: All Income Levels | AG74: 0 | AH74: 0 | AI74: 0 | AJ74: 1 | AK74: All Countries | AL74: =IF(OR(B74="other",B74="international",B74="Transfers",B74="expenditure"),1,0) -> 0 | AM74: =IF(AND(INDIRECT(AN74)='Sample Select backend'!$C$2,INDIRECT(AO74)=1,INDIRECT(AP74)='Sample Select backend'!$F$2,INDIRECT(AQ74)=1,INDIRECT(AR74)='Sample Select backend'!$M$2),1,0) -> 0 | AN74: =_xlfn.CONCAT('Sample Select backend'!$C$4,ROW(AN74)) -> AE74 | AO74: =_xlfn.CONCAT('Sample Select backend'!$J$2,ROW(AO74)) -> AJ74 | AP74: =_xlfn.CONCAT('Sample Select backend'!$F$4,ROW(AP74)) -> AF74 | AQ74: =_xlfn.CONCAT('Sample Select backend'!$I$10,ROW(AQ74)) -> R74 | AR74: =_xlfn.CONCAT('Sample Select backend'!$M$4,ROW(AR74)) -> AK74 | AS74: =A74 -> Anguilla | AT74: =IF(ISNUMBER(C74),C74,IF(OR(C74="general",C74="23;general"),"General",IF(OR(C74="exemption",C74="other (exemption)"),"Tax exemption/waiver/suspension","Other"))) -> 30 | AU74: =IF(A74<>A73,1,0) -> 0 | AV74: 1
A75: Anguilla | B75: 6 | C75: 25 | D75: For those that do not qualify for the unemployment assistance, direct financial support of up to USD 296 per month. | E75: -2 | F75: 1 | G75: -2 | H75: -1 | I75: 2 | J75: -2 | K75: 1 | L75: -2 | M75: 1 | N75: AIA | O75: Latin America & the Caribbean | P75: None | Q75: High Income | R75: 0 | V75: =IF(E75>0,1,IF(E75<0,0,-1)) -> 0 | W75: =IF(F75>0,1,IF(F75<0,0,-1)) -> 1 | X75: =IF(G75>0,1,IF(G75<0,0,-1)) -> 0 | Y75: =IF(H75>0,1,IF(H75<0,0,-1)) -> 0 | Z75: =IF(I75>0,1,IF(I75<0,0,-1)) -> 1 | AA75: =IF(J75>0,1,IF(J75<0,0,-1)) -> 0 | AB75: =IF(K75>0,1,IF(K75<0,0,-1)) -> 1 | AC75: =IF(L75>0,1,IF(L75<0,0,-1)) -> 0 | AD75: =IF(M75>0,1,IF(M75<0,0,-1)) -> 1 | AE75: All Regions | AF75: All Income Levels | AG75: 0 | AH75: 0 | AI75: 0 | AJ75: 1 | AK75: All Countries | AL75: =IF(OR(B75="other",B75="international",B75="Transfers",B75="expenditure"),1,0) -> 0 | AM75: =IF(AND(INDIRECT(AN75)='Sample Select backend'!$C$2,INDIRECT(AO75)=1,INDIRECT(AP75)='Sample Select backend'!$F$2,INDIRECT(AQ75)=1,INDIRECT(AR75)='Sample Select backend'!$M$2),1,0) -> 0 | AN75: =_xlfn.CONCAT('Sample Select backend'!$C$4,ROW(AN75)) -> AE75 | AO75: =_xlfn.CONCAT('Sample Select backend'!$J$2,ROW(AO75)) -> AJ75 | AP75: =_xlfn.CONCAT('Sample Select backend'!$F$4,ROW(AP75)) -> AF75 | AQ75: =_xlfn.CONCAT('Sample Select backend'!$I$10,ROW(AQ75)) -> R75 | AR75: =_xlfn.CONCAT('Sample Select backend'!$M$4,ROW(AR75)) -> AK75 | AS75: =A75 -> Anguilla | AT75: =IF(ISNUMBER(C75),C75,IF(OR(C75="general",C75="23;general"),"General",IF(OR(C75="exemption",C75="other (exemption)"),"Tax exemption/waiver/suspension","Other"))) -> 25 | AU75: =IF(A75<>A74,1,0) -> 0 | AV75: 1
A76: Anguilla | B76: 6 | C76: 26 | D76: Reintroduction of a temporary unemployment benefit to cater to the unemployed and underemployed through the social security system. Up to USD 370 per month. | E76: 2 | F76: 1 | G76: -2 | H76: -1 | I76: 2 | J76: -2 | K76: 1 | L76: 2 | M76: 1 | N76: AIA | O76: Latin America & the Caribbean | P76: None | Q76: High Income | R76: 0 | V76: =IF(E76>0,1,IF(E76<0,0,-1)) -> 1 | W76: =IF(F76>0,1,IF(F76<0,0,-1)) -> 1 | X76: =IF(G76>0,1,IF(G76<0,0,-1)) -> 0 | Y76: =IF(H76>0,1,IF(H76<0,0,-1)) -> 0 | Z76: =IF(I76>0,1,IF(I76<0,0,-1)) -> 1 | AA76: =IF(J76>0,1,IF(J76<0,0,-1)) -> 0 | AB76: =IF(K76>0,1,IF(K76<0,0,-1)) -> 1 | AC76: =IF(L76>0,1,IF(L76<0,0,-1)) -> 1 | AD76: =IF(M76>0,1,IF(M76<0,0,-1)) -> 1 | AE76: All Regions | AF76: All Income Levels | AG76: 0 | AH76: 0 | AI76: 0 | AJ76: 1 | AK76: All Countries | AL76: =IF(OR(B76="other",B76="international",B76="Transfers",B76="expenditure"),1,0) -> 0 | AM76: =IF(AND(INDIRECT(AN76)='Sample Select backend'!$C$2,INDIRECT(AO76)=1,INDIRECT(AP76)='Sample Select backend'!$F$2,INDIRECT(AQ76)=1,INDIRECT(AR76)='Sample Select backend'!$M$2),1,0) -> 0 | AN76: =_xlfn.CONCAT('Sample Select backend'!$C$4,ROW(AN76)) -> AE76 | AO76: =_xlfn.CONCAT('Sample Select backend'!$J$2,ROW(AO76)) -> AJ76 | AP76: =_xlfn.CONCAT('Sample Select backend'!$F$4,ROW(AP76)) -> AF76 | AQ76: =_xlfn.CONCAT('Sample Select backend'!$I$10,ROW(AQ76)) -> R76 | AR76: =_xlfn.CONCAT('Sample Select backend'!$M$4,ROW(AR76)) -> AK76 | AS76: =A76 -> Anguilla | AT76: =IF(ISNUMBER(C76),C76,IF(OR(C76="general",C76="23;general"),"General",IF(OR(C76="exemption",C76="other (exemption)"),"Tax exemption/waiver/suspension","Other"))) -> 26 | AU76: =IF(A76<>A75,1,0) -> 0 | AV76: 1
A77: Anguilla | B77: 1 | C77: other (exemption) | D77: Waiving all interest and penalties on debt obligations (excluding arrears) and social security payments by employers | E77: -1 | F77: 2 | G77: -2 | J77: -2 | K77: -2 | L77: 2 | M77: 1 | N77: AIA | O77: Latin America & the Caribbean | P77: None | Q77: High Income | R77: 0 | V77: =IF(E77>0,1,IF(E77<0,0,-1)) -> 0 | W77: =IF(F77>0,1,IF(F77<0,0,-1)) -> 1 | X77: =IF(G77>0,1,IF(G77<0,0,-1)) -> 0 | Y77: =IF(H77>0,1,IF(H77<0,0,-1)) -> -1 | Z77: =IF(I77>0,1,IF(I77<0,0,-1)) -> -1 | AA77: =IF(J77>0,1,IF(J77<0,0,-1)) -> 0 | AB77: =IF(K77>0,1,IF(K77<0,0,-1)) -> 0 | AC77: =IF(L77>0,1,IF(L77<0,0,-1)) -> 1 | AD77: =IF(M77>0,1,IF(M77<0,0,-1)) -> 1 | AE77: All Regions | AF77: All Income Levels | AG77: 0 | AH77: 0 | AI77: 0 | AJ77: 1 | AK77: All Countries | AL77: =IF(OR(B77="other",B77="international",B77="Transfers",B77="expenditure"),1,0) -> 0 | AM77: =IF(AND(INDIRECT(AN77)='Sample Select backend'!$C$2,INDIRECT(AO77)=1,INDIRECT(AP77)='Sample Select backend'!$F$2,INDIRECT(AQ77)=1,INDIRECT(AR77)='Sample Select backend'!$M$2),1,0) -> 0 | AN77: =_xlfn.CONCAT('Sample Select backend'!$C$4,ROW(AN77)) -> AE77 | AO77: =_xlfn.CONCAT('Sample Select backend'!$J$2,ROW(AO77)) -> AJ77 | AP77: =_xlfn.CONCAT('Sample Select backend'!$F$4,ROW(AP77)) -> AF77 | AQ77: =_xlfn.CONCAT('Sample Select backend'!$I$10,ROW(AQ77)) -> R77 | AR77: =_xlfn.CONCAT('Sample Select backend'!$M$4,ROW(AR77)) -> AK77 | AS77: =A77 -> Anguilla | AT77: =IF(ISNUMBER(C77),C77,IF(OR(C77="general",C77="23;general"),"General",IF(OR(C77="exemption",C77="other (exemption)"),"Tax exemption/waiver/suspension","Other"))) -> Tax exemption/waiver/suspension | AU77: =IF(A77<>A76,1,0) -> 0 | AV77: 1
A78: Anguilla | B78: 1 | C78: 6 | D78: Extension of the unincorporated business tax (UBT) filing and payments deadlines | E78: 1 | F78: 2 | G78: 2 | H78: 1 | I78: 2 | J78: 1 | K78: 1 | L78: 1 | M78: 1 | N78: AIA | O78: Latin America & the Caribbean | P78: None | Q78: High Income | R78: 0 | V78: =IF(E78>0,1,IF(E78<0,0,-1)) -> 1 | W78: =IF(F78>0,1,IF(F78<0,0,-1)) -> 1 | X78: =IF(G78>0,1,IF(G78<0,0,-1)) -> 1 | Y78: =IF(H78>0,1,IF(H78<0,0,-1)) -> 1 | Z78: =IF(I78>0,1,IF(I78<0,0,-1)) -> 1 | AA78: =IF(J78>0,1,IF(J78<0,0,-1)) -> 1 | AB78: =IF(K78>0,1,IF(K78<0,0,-1)) -> 1 | AC78: =IF(L78>0,1,IF(L78<0,0,-1)) -> 1 | AD78: =IF(M78>0,1,IF(M78<0,0,-1)) -> 1 | AE78: All Regions | AF78: All Income Levels | AG78: 0 | AH78: 0 | AI78: 0 | AJ78: 1 | AK78: All Countries | AL78: =IF(OR(B78="other",B78="international",B78="Transfers",B78="expenditure"),1,0) -> 0 | AM78: =IF(AND(INDIRECT(AN78)='Sample Select backend'!$C$2,INDIRECT(AO78)=1,INDIRECT(AP78)='Sample Select backend'!$F$2,INDIRECT(AQ78)=1,INDIRECT(AR78)='Sample Select backend'!$M$2),1,0) -> 0 | AN78: =_xlfn.CONCAT('Sample Select backend'!$C$4,ROW(AN78)) -> AE78 | AO78: =_xlfn.CONCAT('Sample Select backend'!$J$2,ROW(AO78)) -> AJ78 | AP78: =_xlfn.CONCAT('Sample Select backend'!$F$4,ROW(AP78)) -> AF78 | AQ78: =_xlfn.CONCAT('Sample Select backend'!$I$10,ROW(AQ78)) -> R78 | AR78: =_xlfn.CONCAT('Sample Select backend'!$M$4,ROW(AR78)) -> AK78 | AS78: =A78 -> Anguilla | AT78: =IF(ISNUMBER(C78),C78,IF(OR(C78="general",C78="23;general"),"General",IF(OR(C78="exemption",C78="other (exemption)"),"Tax exemption/waiver/suspension","Other"))) -> 6 | AU78: =IF(A78<>A77,1,0) -> 0 | AV78: 1
A79: Anguilla | B79: 5 | C79: general | D79: Emergency grant of USD 1.5 million to fund the COVID-19 response by the UK government (announced). | E79: 1 | F79: -2 | G79: -2 | H79: -1 | I79: -1 | J79: 1 | K79: 1 | L79: 1 | M79: 1 | N79: AIA | O79: Latin America & the Caribbean | P79: None | Q79: High Income | R79: 0 | V79: =IF(E79>0,1,IF(E79<0,0,-1)) -> 1 | W79: =IF(F79>0,1,IF(F79<0,0,-1)) -> 0 | X79: =IF(G79>0,1,IF(G79<0,0,-1)) -> 0 | Y79: =IF(H79>0,1,IF(H79<0,0,-1)) -> 0 | Z79: =IF(I79>0,1,IF(I79<0,0,-1)) -> 0 | AA79: =IF(J79>0,1,IF(J79<0,0,-1)) -> 1 | AB79: =IF(K79>0,1,IF(K79<0,0,-1)) -> 1 | AC79: =IF(L79>0,1,IF(L79<0,0,-1)) -> 1 | AD79: =IF(M79>0,1,IF(M79<0,0,-1)) -> 1 | AE79: All Regions | AF79: All Income Levels | AG79: 0 | AH79: 0 | AI79: 0 | AJ79: 1 | AK79: All Countries | AL79: =IF(OR(B79="other",B79="international",B79="Transfers",B79="expenditure"),1,0) -> 0 | AM79: =IF(AND(INDIRECT(AN79)='Sample Select backend'!$C$2,INDIRECT(AO79)=1,INDIRECT(AP79)='Sample Select backend'!$F$2,INDIRECT(AQ79)=1,INDIRECT(AR79)='Sample Select backend'!$M$2),1,0) -> 0 | AN79: =_xlfn.CONCAT('Sample Select backend'!$C$4,ROW(AN79)) -> AE79 | AO79: =_xlfn.CONCAT('Sample Select backend'!$J$2,ROW(AO79)) -> AJ79 | AP79: =_xlfn.CONCAT('Sample Select backend'!$F$4,ROW(AP79)) -> AF79 | AQ79: =_xlfn.CONCAT('Sample Select backend'!$I$10,ROW(AQ79)) -> R79 | AR79: =_xlfn.CONCAT('Sample Select backend'!$M$4,ROW(AR79)) -> AK79 | AS79: =A79 -> Anguilla | AT79: =IF(ISNUMBER(C79),C79,IF(OR(C79="general",C79="23;general"),"General",IF(OR(C79="exemption",C79="other (exemption)"),"Tax exemption/waiver/suspension","Other"))) -> General | AU79: =IF(A79<>A78,1,0) -> 0 | AV79: 1
A80: Antigua and Barbuda | B80: 4 | C80: other | D80: One year investment incentives for home renovation and construction. | E80: -1 | F80: 1 | G80: 1 | H80: -1 | I80: -2 | J80: 1 | K80: 1 | L80: -2 | M80: -2 | N80: ATG | O80: Latin America & the Caribbean | P80: IBRD | Q80: High Income | R80: 0 | V80: =IF(E80>0,1,IF(E80<0,0,-1)) -> 0 | W80: =IF(F80>0,1,IF(F80<0,0,-1)) -> 1 | X80: =IF(G80>0,1,IF(G80<0,0,-1)) -> 1 | Y80: =IF(H80>0,1,IF(H80<0,0,-1)) -> 0 | Z80: =IF(I80>0,1,IF(I80<0,0,-1)) -> 0 | AA80: =IF(J80>0,1,IF(J80<0,0,-1)) -> 1 | AB80: =IF(K80>0,1,IF(K80<0,0,-1)) -> 1 | AC80: =IF(L80>0,1,IF(L80<0,0,-1)) -> 0 | AD80: =IF(M80>0,1,IF(M80<0,0,-1)) -> 0 | AE80: All Regions | AF80: All Income Levels | AG80: 0 | AH80: 1 | AI80: 0 | AJ80: 1 | AK80: All Countries | AL80: =IF(OR(B80="other",B80="international",B80="Transfers",B80="expenditure"),1,0) -> 0 | AM80: =IF(AND(INDIRECT(AN80)='Sample Select backend'!$C$2,INDIRECT(AO80)=1,INDIRECT(AP80)='Sample Select backend'!$F$2,INDIRECT(AQ80)=1,INDIRECT(AR80)='Sample Select backend'!$M$2),1,0) -> 0 | AN80: =_xlfn.CONCAT('Sample Select backend'!$C$4,ROW(AN80)) -> AE80 | AO80: =_xlfn.CONCAT('Sample Select backend'!$J$2,ROW(AO80)) -> AJ80 | AP80: =_xlfn.CONCAT('Sample Select backend'!$F$4,ROW(AP80)) -> AF80 | AQ80: =_xlfn.CONCAT('Sample Select backend'!$I$10,ROW(AQ80)) -> R80 | AR80: =_xlfn.CONCAT('Sample Select backend'!$M$4,ROW(AR80)) -> AK80 | AS80: =A80 -> Antigua and Barbuda | AT80: =IF(ISNUMBER(C80),C80,IF(OR(C80="general",C80="23;general"),"General",IF(OR(C80="exemption",C80="other (exemption)"),"Tax exemption/waiver/suspension","Other"))) -> Other | AU80: =IF(A80<>A79,1,0) -> 1 | AV80: 1
A81: Antigua and Barbuda | B81: 6 | C81: 28 | D81: 20% reduction in electricity costs to the public and fuel costs to fishermen for 90 days. | E81: -1 | F81: 1 | G81: 1 | H81: -1 | I81: 2 | J81: 2 | K81: 1 | L81: 1 | M81: 1 | N81: ATG | O81: Latin America & the Caribbean | P81: IBRD | Q81: High Income | R81: 0 | V81: =IF(E81>0,1,IF(E81<0,0,-1)) -> 0 | W81: =IF(F81>0,1,IF(F81<0,0,-1)) -> 1 | X81: =IF(G81>0,1,IF(G81<0,0,-1)) -> 1 | Y81: =IF(H81>0,1,IF(H81<0,0,-1)) -> 0 | Z81: =IF(I81>0,1,IF(I81<0,0,-1)) -> 1 | AA81: =IF(J81>0,1,IF(J81<0,0,-1)) -> 1 | AB81: =IF(K81>0,1,IF(K81<0,0,-1)) -> 1 | AC81: =IF(L81>0,1,IF(L81<0,0,-1)) -> 1 | AD81: =IF(M81>0,1,IF(M81<0,0,-1)) -> 1 | AE81: All Regions | AF81: All Income Levels | AG81: 0 | AH81: 1 | AI81: 0 | AJ81: 1 | AK81: All Countries | AL81: =IF(OR(B81="other",B81="international",B81="Transfers",B81="expenditure"),1,0) -> 0 | AM81: =IF(AND(INDIRECT(AN81)='Sample Select backend'!$C$2,INDIRECT(AO81)=1,INDIRECT(AP81)='Sample Select backend'!$F$2,INDIRECT(AQ81)=1,INDIRECT(AR81)='Sample Select backend'!$M$2),1,0) -> 0 | AN81: =_xlfn.CONCAT('Sample Select backend'!$C$4,ROW(AN81)) -> AE81 | AO81: =_xlfn.CONCAT('Sample Select backend'!$J$2,ROW(AO81)) -> AJ81 | AP81: =_xlfn.CONCAT('Sample Select backend'!$F$4,ROW(AP81)) -> AF81 | AQ81: =_xlfn.CONCAT('Sample Select backend'!$I$10,ROW(AQ81)) -> R81 | AR81: =_xlfn.CONCAT('Sample Select backend'!$M$4,ROW(AR81)) -> AK81 | AS81: =A81 -> Antigua and Barbuda | AT81: =IF(ISNUMBER(C81),C81,IF(OR(C81="general",C81="23;general"),"General",IF(OR(C81="exemption",C81="other (exemption)"),"Tax exemption/waiver/suspension","Other"))) -> 28 | AU81: =IF(A81<>A80,1,0) -> 0 | AV81: 1
A82: Antigua and Barbuda | B82: 5 | C82: general | D82: An increase in health spending (0.5% of GDP). | E82: 1 | F82: -2 | G82: -2 | H82: -1 | I82: -2 | J82: 1 | K82: 1 | L82: 1 | M82: 1 | N82: ATG | O82: Latin America & the Caribbean | P82: IBRD | Q82: High Income | R82: 0 | V82: =IF(E82>0,1,IF(E82<0,0,-1)) -> 1 | W82: =IF(F82>0,1,IF(F82<0,0,-1)) -> 0 | X82: =IF(G82>0,1,IF(G82<0,0,-1)) -> 0 | Y82: =IF(H82>0,1,IF(H82<0,0,-1)) -> 0 | Z82: =IF(I82>0,1,IF(I82<0,0,-1)) -> 0 | AA82: =IF(J82>0,1,IF(J82<0,0,-1)) -> 1 | AB82: =IF(K82>0,1,IF(K82<0,0,-1)) -> 1 | AC82: =IF(L82>0,1,IF(L82<0,0,-1)) -> 1 | AD82: =IF(M82>0,1,IF(M82<0,0,-1)) -> 1 | AE82: All Regions | AF82: All Income Levels | AG82: 0 | AH82: 1 | AI82: 0 | AJ82: 1 | AK82: All Countries | AL82: =IF(OR(B82="other",B82="international",B82="Transfers",B82="expenditure"),1,0) -> 0 | AM82: =IF(AND(INDIRECT(AN82)='Sample Select backend'!$C$2,INDIRECT(AO82)=1,INDIRECT(AP82)='Sample Select backend'!$F$2,INDIRECT(AQ82)=1,INDIRECT(AR82)='Sample Select backend'!$M$2),1,0) -> 0 | AN82: =_xlfn.CONCAT('Sample Select backend'!$C$4,ROW(AN82)) -> AE82 | AO82: =_xlfn.CONCAT('Sample Select backend'!$J$2,ROW(AO82)) -> AJ82 | AP82: =_xlfn.CONCAT('Sample Select backend'!$F$4,ROW(AP82)) -> AF82 | AQ82: =_xlfn.CONCAT('Sample Select backend'!$I$10,ROW(AQ82)) -> R82 | AR82: =_xlfn.CONCAT('Sample Select backend'!$M$4,ROW(AR82)) -> AK82 | AS82: =A82 -> Antigua and Barbuda | AT82: =IF(ISNUMBER(C82),C82,IF(OR(C82="general",C82="23;general"),"General",IF(OR(C82="exemption",C82="other (exemption)"),"Tax exemption/waiver/suspension","Other"))) -> General | AU82: =IF(A82<>A81,1,0) -> 0 | AV82: 1
A83: Antigua and Barbuda | B83: 6 | C83: 28 | D83: Relief packages of food and medication to elderly living alone, persons with disabilities, and unemployed adults with children. | E83: 2 | F83: 1 | G83: 1 | H83: -1 | I83: 1 | J83: 2 | K83: 1 | L83: 2 | M83: -2 | N83: ATG | O83: Latin America & the Caribbean | P83: IBRD | Q83: High Income | R83: 0 | V83: =IF(E83>0,1,IF(E83<0,0,-1)) -> 1 | W83: =IF(F83>0,1,IF(F83<0,0,-1)) -> 1 | X83: =IF(G83>0,1,IF(G83<0,0,-1)) -> 1 | Y83: =IF(H83>0,1,IF(H83<0,0,-1)) -> 0 | Z83: =IF(I83>0,1,IF(I83<0,0,-1)) -> 1 | AA83: =IF(J83>0,1,IF(J83<0,0,-1)) -> 1 | AB83: =IF(K83>0,1,IF(K83<0,0,-1)) -> 1 | AC83: =IF(L83>0,1,IF(L83<0,0,-1)) -> 1 | AD83: =IF(M83>0,1,IF(M83<0,0,-1)) -> 0 | AE83: All Regions | AF83: All Income Levels | AG83: 0 | AH83: 1 | AI83: 0 | AJ83: 1 | AK83: All Countries | AL83: =IF(OR(B83="other",B83="international",B83="Transfers",B83="expenditure"),1,0) -> 0 | AM83: =IF(AND(INDIRECT(AN83)='Sample Select backend'!$C$2,INDIRECT(AO83)=1,INDIRECT(AP83)='Sample Select backend'!$F$2,INDIRECT(AQ83)=1,INDIRECT(AR83)='Sample Select backend'!$M$2),1,0) -> 0 | AN83: =_xlfn.CONCAT('Sample Select backend'!$C$4,ROW(AN83)) -> AE83 | AO83: =_xlfn.CONCAT('Sample Select backend'!$J$2,ROW(AO83)) -> AJ83 | AP83: =_xlfn.CONCAT('Sample Select backend'!$F$4,ROW(AP83)) -> AF83 | AQ83: =_xlfn.CONCAT('Sample Select backend'!$I$10,ROW(AQ83)) -> R83 | AR83: =_xlfn.CONCAT('Sample Select backend'!$M$4,ROW(AR83)) -> AK83 | AS83: =A83 -> Antigua and Barbuda | AT83: =IF(ISNUMBER(C83),C83,IF(OR(C83="general",C83="23;general"),"General",IF(OR(C83="exemption",C83="other (exemption)"),"Tax exemption/waiver/suspension","Other"))) -> 28 | AU83: =IF(A83<>A82,1,0) -> 0 | AV83: 1
A84: Antigua and Barbuda | B84: 6 | C84: 26 | D84: Expansion of social safety net programs. | E84: 2 | F84: 1 | G84: 1 | H84: -1 | I84: 1 | J84: -2 | K84: 1 | L84: 1 | M84: 1 | N84: ATG | O84: Latin America & the Caribbean | P84: IBRD | Q84: High Income | R84: 0 | V84: =IF(E84>0,1,IF(E84<0,0,-1)) -> 1 | W84: =IF(F84>0,1,IF(F84<0,0,-1)) -> 1 | X84: =IF(G84>0,1,IF(G84<0,0,-1)) -> 1 | Y84: =IF(H84>0,1,IF(H84<0,0,-1)) -> 0 | Z84: =IF(I84>0,1,IF(I84<0,0,-1)) -> 1 | AA84: =IF(J84>0,1,IF(J84<0,0,-1)) -> 0 | AB84: =IF(K84>0,1,IF(K84<0,0,-1)) -> 1 | AC84: =IF(L84>0,1,IF(L84<0,0,-1)) -> 1 | AD84: =IF(M84>0,1,IF(M84<0,0,-1)) -> 1 | AE84: All Regions | AF84: All Income Levels | AG84: 0 | AH84: 1 | AI84: 0 | AJ84: 1 | AK84: All Countries | AL84: =IF(OR(B84="other",B84="international",B84="Transfers",B84="expenditure"),1,0) -> 0 | AM84: =IF(AND(INDIRECT(AN84)='Sample Select backend'!$C$2,INDIRECT(AO84)=1,INDIRECT(AP84)='Sample Select backend'!$F$2,INDIRECT(AQ84)=1,INDIRECT(AR84)='Sample Select backend'!$M$2),1,0) -> 0 | AN84: =_xlfn.CONCAT('Sample Select backend'!$C$4,ROW(AN84)) -> AE84 | AO84: =_xlfn.CONCAT('Sample Select backend'!$J$2,ROW(AO84)) -> AJ84 | AP84: =_xlfn.CONCAT('Sample Select backend'!$F$4,ROW(AP84)) -> AF84 | AQ84: =_xlfn.CONCAT('Sample Select backend'!$I$10,ROW(AQ84)) -> R84 | AR84: =_xlfn.CONCAT('Sample Select backend'!$M$4,ROW(AR84)) -> AK84 | AS84: =A84 -> Antigua and Barbuda | AT84: =IF(ISNUMBER(C84),C84,IF(OR(C84="general",C84="23;general"),"General",IF(OR(C84="exemption",C84="other (exemption)"),"Tax exemption/waiver/suspension","Other"))) -> 26 | AU84: =IF(A84<>A83,1,0) -> 0 | AV84: 1
A85: Antigua and Barbuda | B85: 2 | C85: exemption | D85: Suspension of the common external tariff on food imports and all new tax measures announced in 2020 budget | O85: Latin America & the Caribbean | P85: IBRD | Q85: High Income | R85: 0 | V85: -1 | W85: -1 | X85: -1 | Y85: -1 | Z85: -1 | AA85: -1 | AB85: -1 | AC85: -1 | AD85: -1 | AE85: All Regions | AF85: All Income Levels | AG85: 0 | AH85: 1 | AI85: 0 | AJ85: 1 | AK85: All Countries | AL85: =IF(OR(B85="other",B85="international",B85="Transfers",B85="expenditure"),1,0) -> 0 | AM85: =IF(AND(INDIRECT(AN85)='Sample Select backend'!$C$2,INDIRECT(AO85)=1,INDIRECT(AP85)='Sample Select backend'!$F$2,INDIRECT(AQ85)=1,INDIRECT(AR85)='Sample Select backend'!$M$2),1,0) -> 0 | AN85: =_xlfn.CONCAT('Sample Select backend'!$C$4,ROW(AN85)) -> AE85 | AO85: =_xlfn.CONCAT('Sample Select backend'!$J$2,ROW(AO85)) -> AJ85 | AP85: =_xlfn.CONCAT('Sample Select backend'!$F$4,ROW(AP85)) -> AF85 | AQ85: =_xlfn.CONCAT('Sample Select backend'!$I$10,ROW(AQ85)) -> R85 | AR85: =_xlfn.CONCAT('Sample Select backend'!$M$4,ROW(AR85)) -> AK85 | AS85: =A85 -> Antigua and Barbuda | AT85: =IF(ISNUMBER(C85),C85,IF(OR(C85="general",C85="23;general"),"General",IF(OR(C85="exemption",C85="other (exemption)"),"Tax exemption/waiver/suspension","Other"))) -> Tax exemption/waiver/suspension | AU85: =IF(A85<>A84,1,0) -> 0 | AV85: 0
A86: Argentina | B86: other | C86: other | D86: Increased spending on public works. | E86: 2 | F86: -2 | G86: -2 | H86: -2 | I86: -2 | J86: 1 | K86: 1 | L86: 1 | M86: -2 | N86: ARG | O86: Latin America & the Caribbean | P86: IBRD | Q86: Upper Middle Income | R86: 0 | S86: -10.03 | T86: -6.56 | U86: 105.58 | V86: =IF(E86>0,1,IF(E86<0,0,-1)) -> 1 | W86: =IF(F86>0,1,IF(F86<0,0,-1)) -> 0 | X86: =IF(G86>0,1,IF(G86<0,0,-1)) -> 0 | Y86: =IF(H86>0,1,IF(H86<0,0,-1)) -> 0 | Z86: =IF(I86>0,1,IF(I86<0,0,-1)) -> 0 | AA86: =IF(J86>0,1,IF(J86<0,0,-1)) -> 1 | AB86: =IF(K86>0,1,IF(K86<0,0,-1)) -> 1 | AC86: =IF(L86>0,1,IF(L86<0,0,-1)) -> 1 | AD86: =IF(M86>0,1,IF(M86<0,0,-1)) -> 0 | AE86: All Regions | AF86: All Income Levels | AG86: 0 | AH86: 1 | AI86: 0 | AJ86: 1 | AK86: All Countries | AL86: =IF(OR(B86="other",B86="international",B86="Transfers",B86="expenditure"),1,0) -> 1 | AM86: =IF(AND(INDIRECT(AN86)='Sample Select backend'!$C$2,INDIRECT(AO86)=1,INDIRECT(AP86)='Sample Select backend'!$F$2,INDIRECT(AQ86)=1,INDIRECT(AR86)='Sample Select backend'!$M$2),1,0) -> 0 | AN86: =_xlfn.CONCAT('Sample Select backend'!$C$4,ROW(AN86)) -> AE86 | AO86: =_xlfn.CONCAT('Sample Select backend'!$J$2,ROW(AO86)) -> AJ86 | AP86: =_xlfn.CONCAT('Sample Select backend'!$F$4,ROW(AP86)) -> AF86 | AQ86: =_xlfn.CONCAT('Sample Select backend'!$I$10,ROW(AQ86)) -> R86 | AR86: =_xlfn.CONCAT('Sample Select backend'!$M$4,ROW(AR86)) -> AK86 | AS86: =A86 -> Argentina | AT86: =IF(ISNUMBER(C86),C86,IF(OR(C86="general",C86="23;general"),"General",IF(OR(C86="exemption",C86="other (exemption)"),"Tax exemption/waiver/suspension","Other"))) -> Other | AU86: =IF(A86<>A85,1,0) -> 1 | AV86: 1
A87: Argentina | B87: 5 | C87: 22 | D87: Increased health spending, including for improvements in virus diagnostics, purchases of hospital equipment, and construction of clinics and hospitals. | E87: 1 | F87: -2 | G87: -2 | H87: -1 | I87: -2 | J87: 1 | K87: 1 | L87: 1 | M87: 1 | N87: ARG | O87: Latin America & the Caribbean | P87: IBRD | Q87: Upper Middle Income | R87: 0 | S87: -10.03 | T87: -6.56 | U87: 105.58 | V87: =IF(E87>0,1,IF(E87<0,0,-1)) -> 1 | W87: =IF(F87>0,1,IF(F87<0,0,-1)) -> 0 | X87: =IF(G87>0,1,IF(G87<0,0,-1)) -> 0 | Y87: =IF(H87>0,1,IF(H87<0,0,-1)) -> 0 | Z87: =IF(I87>0,1,IF(I87<0,0,-1)) -> 0 | AA87: =IF(J87>0,1,IF(J87<0,0,-1)) -> 1 | AB87: =IF(K87>0,1,IF(K87<0,0,-1)) -> 1 | AC87: =IF(L87>0,1,IF(L87<0,0,-1)) -> 1 | AD87: =IF(M87>0,1,IF(M87<0,0,-1)) -> 1 | AE87: All Regions | AF87: All Income Levels | AG87: 0 | AH87: 1 | AI87: 0 | AJ87: 1 | AK87: All Countries | AL87: =IF(OR(B87="other",B87="international",B87="Transfers",B87="expenditure"),1,0) -> 0 | AM87: =IF(AND(INDIRECT(AN87)='Sample Select backend'!$C$2,INDIRECT(AO87)=1,INDIRECT(AP87)='Sample Select backend'!$F$2,INDIRECT(AQ87)=1,INDIRECT(AR87)='Sample Select backend'!$M$2),1,0) -> 0 | AN87: =_xlfn.CONCAT('Sample Select backend'!$C$4,ROW(AN87)) -> AE87 | AO87: =_xlfn.CONCAT('Sample Select backend'!$J$2,ROW(AO87)) -> AJ87 | AP87: =_xlfn.CONCAT('Sample Select backend'!$F$4,ROW(AP87)) -> AF87 | AQ87: =_xlfn.CONCAT('Sample Select backend'!$I$10,ROW(AQ87)) -> R87 | AR87: =_xlfn.CONCAT('Sample Select backend'!$M$4,ROW(AR87)) -> AK87 | AS87: =A87 -> Argentina | AT87: =IF(ISNUMBER(C87),C87,IF(OR(C87="general",C87="23;general"),"General",IF(OR(C87="exemption",C87="other (exemption)"),"Tax exemption/waiver/suspension","Other"))) -> 22 | AU87: =IF(A87<>A86,1,0) -> 0 | AV87: 1
A88: Argentina | B88: 6 | C88: 27 | D88: Increased social security benefits (especially to low-income beneficiaries). | E88: 1 | F88: 1 | G88: 1 | H88: -1 | I88: 1 | J88: -2 | K88: 1 | L88: 1 | M88: 1 | N88: ARG | O88: Latin America & the Caribbean | P88: IBRD | Q88: Upper Middle Income | R88: 0 | S88: -10.03 | T88: -6.56 | U88: 105.58 | V88: =IF(E88>0,1,IF(E88<0,0,-1)) -> 1 | W88: =IF(F88>0,1,IF(F88<0,0,-1)) -> 1 | X88: =IF(G88>0,1,IF(G88<0,0,-1)) -> 1 | Y88: =IF(H88>0,1,IF(H88<0,0,-1)) -> 0 | Z88: =IF(I88>0,1,IF(I88<0,0,-1)) -> 1 | AA88: =IF(J88>0,1,IF(J88<0,0,-1)) -> 0 | AB88: =IF(K88>0,1,IF(K88<0,0,-1)) -> 1 | AC88: =IF(L88>0,1,IF(L88<0,0,-1)) -> 1 | AD88: =IF(M88>0,1,IF(M88<0,0,-1)) -> 1 | AE88: All Regions | AF88: All Income Levels | AG88: 0 | AH88: 1 | AI88: 0 | AJ88: 1 | AK88: All Countries | AL88: =IF(OR(B88="other",B88="international",B88="Transfers",B88="expenditure"),1,0) -> 0 | AM88: =IF(AND(INDIRECT(AN88)='Sample Select backend'!$C$2,INDIRECT(AO88)=1,INDIRECT(AP88)='Sample Select backend'!$F$2,INDIRECT(AQ88)=1,INDIRECT(AR88)='Sample Select backend'!$M$2),1,0) -> 0 | AN88: =_xlfn.CONCAT('Sample Select backend'!$C$4,ROW(AN88)) -> AE88 | AO88: =_xlfn.CONCAT('Sample Select backend'!$J$2,ROW(AO88)) -> AJ88 | AP88: =_xlfn.CONCAT('Sample Select backend'!$F$4,ROW(AP88)) -> AF88 | AQ88: =_xlfn.CONCAT('Sample Select backend'!$I$10,ROW(AQ88)) -> R88 | AR88: =_xlfn.CONCAT('Sample Select backend'!$M$4,ROW(AR88)) -> AK88 | AS88: =A88 -> Argentina | AT88: =IF(ISNUMBER(C88),C88,IF(OR(C88="general",C88="23;general"),"General",IF(OR(C88="exemption",C88="other (exemption)"),"Tax exemption/waiver/suspension","Other"))) -> 27 | AU88: =IF(A88<>A87,1,0) -> 0 | AV88: 1
A89: Argentina | B89: 7 | C89: 30 | D89: Subsidized loans for construction sector. | E89: 2 | F89: 1 | G89: 1 | H89: 1 | I89: 2 | J89: 2 | K89: 1 | L89: -2 | M89: -2 | N89: ARG | O89: Latin America & the Caribbean | P89: IBRD | Q89: Upper Middle Income | R89: 0 | S89: -10.03 | T89: -6.56 | U89: 105.58 | V89: =IF(E89>0,1,IF(E89<0,0,-1)) -> 1 | W89: =IF(F89>0,1,IF(F89<0,0,-1)) -> 1 | X89: =IF(G89>0,1,IF(G89<0,0,-1)) -> 1 | Y89: =IF(H89>0,1,IF(H89<0,0,-1)) -> 1 | Z89: =IF(I89>0,1,IF(I89<0,0,-1)) -> 1 | AA89: =IF(J89>0,1,IF(J89<0,0,-1)) -> 1 | AB89: =IF(K89>0,1,IF(K89<0,0,-1)) -> 1 | AC89: =IF(L89>0,1,IF(L89<0,0,-1)) -> 0 | AD89: =IF(M89>0,1,IF(M89<0,0,-1)) -> 0 | AE89: All Regions | AF89: All Income Levels | AG89: 0 | AH89: 1 | AI89: 0 | AJ89: 1 | AK89: All Countries | AL89: =IF(OR(B89="other",B89="international",B89="Transfers",B89="expenditure"),1,0) -> 0 | AM89: =IF(AND(INDIRECT(AN89)='Sample Select backend'!$C$2,INDIRECT(AO89)=1,INDIRECT(AP89)='Sample Select backend'!$F$2,INDIRECT(AQ89)=1,INDIRECT(AR89)='Sample Select backend'!$M$2),1,0) -> 0 | AN89: =_xlfn.CONCAT('Sample Select backend'!$C$4,ROW(AN89)) -> AE89 | AO89: =_xlfn.CONCAT('Sample Select backend'!$J$2,ROW(AO89)) -> AJ89 | AP89: =_xlfn.CONCAT('Sample Select backend'!$F$4,ROW(AP89)) -> AF89 | AQ89: =_xlfn.CONCAT('Sample Select backend'!$I$10,ROW(AQ89)) -> R89 | AR89: =_xlfn.CONCAT('Sample Select backend'!$M$4,ROW(AR89)) -> AK89 | AS89: =A89 -> Argentina | AT89: =IF(ISNUMBER(C89),C89,IF(OR(C89="general",C89="23;general"),"General",IF(OR(C89="exemption",C89="other (exemption)"),"Tax exemption/waiver/suspension","Other"))) -> 30 | AU89: =IF(A89<>A88,1,0) -> 0 | AV89: 1
A90: Argentina | B90: 1 | C90: 11 | D90: Tax debt payment deferral for SMEs and microenterprises | E90: 2 | F90: 2 | G90: -1 | H90: 2 | I90: 2 | J90: 1 | K90: 1 | L90: 1 | M90: 1 | N90: ARG | O90: Latin America & the Caribbean | P90: IBRD | Q90: Upper Middle Income | R90: 0 | S90: -10.03 | T90: -6.56 | U90: 105.58 | V90: =IF(E90>0,1,IF(E90<0,0,-1)) -> 1 | W90: =IF(F90>0,1,IF(F90<0,0,-1)) -> 1 | X90: =IF(G90>0,1,IF(G90<0,0,-1)) -> 0 | Y90: =IF(H90>0,1,IF(H90<0,0,-1)) -> 1 | Z90: =IF(I90>0,1,IF(I90<0,0,-1)) -> 1 | AA90: =IF(J90>0,1,IF(J90<0,0,-1)) -> 1 | AB90: =IF(K90>0,1,IF(K90<0,0,-1)) -> 1 | AC90: =IF(L90>0,1,IF(L90<0,0,-1)) -> 1 | AD90: =IF(M90>0,1,IF(M90<0,0,-1)) -> 1 | AE90: All Regions | AF90: All Income Levels | AG90: 0 | AH90: 1 | AI90: 0 | AJ90: 1 | AK90: All Countries | AL90: =IF(OR(B90="other",B90="international",B90="Transfers",B90="expenditure"),1,0) -> 0 | AM90: =IF(AND(INDIRECT(AN90)='Sample Select backend'!$C$2,INDIRECT(AO90)=1,INDIRECT(AP90)='Sample Select backend'!$F$2,INDIRECT(AQ90)=1,INDIRECT(AR90)='Sample Select backend'!$M$2),1,0) -> 0 | AN90: =_xlfn.CONCAT('Sample Select backend'!$C$4,ROW(AN90)) -> AE90 | AO90: =_xlfn.CONCAT('Sample Select backend'!$J$2,ROW(AO90)) -> AJ90 | AP90: =_xlfn.CONCAT('Sample Select backend'!$F$4,ROW(AP90)) -> AF90 | AQ90: =_xlfn.CONCAT('Sample Select backend'!$I$10,ROW(AQ90)) -> R90 | AR90: =_xlfn.CONCAT('Sample Select backend'!$M$4,ROW(AR90)) -> AK90 | AS90: =A90 -> Argentina | AT90: =IF(ISNUMBER(C90),C90,IF(OR(C90="general",C90="23;general"),"General",IF(OR(C90="exemption",C90="other (exemption)"),"Tax exemption/waiver/suspension","Other"))) -> 11 | AU90: =IF(A90<>A89,1,0) -> 0 | AV90: 1
A91: Argentina | B91: 6 | C91: 28 | D91: Food support through card or cash value, to be delivered to 2,800,000 recipients. | E91: 2 | F91: 1 | H91: -1 | I91: 2 | J91: 1 | K91: 1 | L91: 2 | N91: ARG | O91: Latin America & the Caribbean | P91: IBRD | Q91: Upper Middle Income | R91: 0 | S91: -10.03 | T91: -6.56 | U91: 105.58 | V91: =IF(E91>0,1,IF(E91<0,0,-1)) -> 1 | W91: =IF(F91>0,1,IF(F91<0,0,-1)) -> 1 | X91: =IF(G91>0,1,IF(G91<0,0,-1)) -> -1 | Y91: =IF(H91>0,1,IF(H91<0,0,-1)) -> 0 | Z91: =IF(I91>0,1,IF(I91<0,0,-1)) -> 1 | AA91: =IF(J91>0,1,IF(J91<0,0,-1)) -> 1 | AB91: =IF(K91>0,1,IF(K91<0,0,-1)) -> 1 | AC91: =IF(L91>0,1,IF(L91<0,0,-1)) -> 1 | AD91: =IF(M91>0,1,IF(M91<0,0,-1)) -> -1 | AE91: All Regions | AF91: All Income Levels | AG91: 0 | AH91: 1 | AI91: 0 | AJ91: 1 | AK91: All Countries | AL91: =IF(OR(B91="other",B91="international",B91="Transfers",B91="expenditure"),1,0) -> 0 | AM91: =IF(AND(INDIRECT(AN91)='Sample Select backend'!$C$2,INDIRECT(AO91)=1,INDIRECT(AP91)='Sample Select backend'!$F$2,INDIRECT(AQ91)=1,INDIRECT(AR91)='Sample Select backend'!$M$2),1,0) -> 0 | AN91: =_xlfn.CONCAT('Sample Select backend'!$C$4,ROW(AN91)) -> AE91 | AO91: =_xlfn.CONCAT('Sample Select backend'!$J$2,ROW(AO91)) -> AJ91 | AP91: =_xlfn.CONCAT('Sample Select backend'!$F$4,ROW(AP91)) -> AF91 | AQ91: =_xlfn.CONCAT('Sample Select backend'!$I$10,ROW(AQ91)) -> R91 | AR91: =_xlfn.CONCAT('Sample Select backend'!$M$4,ROW(AR91)) -> AK91 | AS91: =A91 -> Argentina | AT91: =IF(ISNUMBER(C91),C91,IF(OR(C91="general",C91="23;general"),"General",IF(OR(C91="exemption",C91="other (exemption)"),"Tax exemption/waiver/suspension","Other"))) -> 28 | AU91: =IF(A91<>A90,1,0) -> 0 | AV91: 1
A92: Argentina | B92: 1 | C92: 7 | D92: Deferral or reduction of up to 95% of the payment of employer contributions for SMEs | E92: 2 | F92: 2 | G92: -2 | H92: -1 | I92: -2 | J92: 2 | K92: 1 | L92: 2 | M92: 1 | N92: ARG | O92: Latin America & the Caribbean | P92: IBRD | Q92: Upper Middle Income | R92: 0 | S92: -10.03 | T92: -6.56 | U92: 105.58 | V92: =IF(E92>0,1,IF(E92<0,0,-1)) -> 1 | W92: =IF(F92>0,1,IF(F92<0,0,-1)) -> 1 | X92: =IF(G92>0,1,IF(G92<0,0,-1)) -> 0 | Y92: =IF(H92>0,1,IF(H92<0,0,-1)) -> 0 | Z92: =IF(I92>0,1,IF(I92<0,0,-1)) -> 0 | AA92: =IF(J92>0,1,IF(J92<0,0,-1)) -> 1 | AB92: =IF(K92>0,1,IF(K92<0,0,-1)) -> 1 | AC92: =IF(L92>0,1,IF(L92<0,0,-1)) -> 1 | AD92: =IF(M92>0,1,IF(M92<0,0,-1)) -> 1 | AE92: All Regions | AF92: All Income Levels | AG92: 0 | AH92: 1 | AI92: 0 | AJ92: 1 | AK92: All Countries | AL92: =IF(OR(B92="other",B92="international",B92="Transfers",B92="expenditure"),1,0) -> 0 | AM92: =IF(AND(INDIRECT(AN92)='Sample Select backend'!$C$2,INDIRECT(AO92)=1,INDIRECT(AP92)='Sample Select backend'!$F$2,INDIRECT(AQ92)=1,INDIRECT(AR92)='Sample Select backend'!$M$2),1,0) -> 0 | AN92: =_xlfn.CONCAT('Sample Select backend'!$C$4,ROW(AN92)) -> AE92 | AO92: =_xlfn.CONCAT('Sample Select backend'!$J$2,ROW(AO92)) -> AJ92 | AP92: =_xlfn.CONCAT('Sample Select backend'!$F$4,ROW(AP92)) -> AF92 | AQ92: =_xlfn.CONCAT('Sample Select backend'!$I$10,ROW(AQ92)) -> R92 | AR92: =_xlfn.CONCAT('Sample Select backend'!$M$4,ROW(AR92)) -> AK92 | AS92: =A92 -> Argentina | AT92: =IF(ISNUMBER(C92),C92,IF(OR(C92="general",C92="23;general"),"General",IF(OR(C92="exemption",C92="other (exemption)"),"Tax exemption/waiver/suspension","Other"))) -> 7 | AU92: =IF(A92<>A91,1,0) -> 0 | AV92: 1
A93: Argentina | B93: 1 | C93: 6 | D93: The temporary validity of payment facility plans is extended until June 30, 2020 for all types of taxpayers | E93: -1 | F93: 2 | G93: 2 | H93: 1 | I93: 2 | J93: 2 | K93: 1 | L93: 1 | M93: 1 | N93: ARG | O93: Latin America & the Caribbean | P93: IBRD | Q93: Upper Middle Income | R93: 0 | S93: -10.03 | T93: -6.56 | U93: 105.58 | V93: =IF(E93>0,1,IF(E93<0,0,-1)) -> 0 | W93: =IF(F93>0,1,IF(F93<0,0,-1)) -> 1 | X93: =IF(G93>0,1,IF(G93<0,0,-1)) -> 1 | Y93: =IF(H93>0,1,IF(H93<0,0,-1)) -> 1 | Z93: =IF(I93>0,1,IF(I93<0,0,-1)) -> 1 | AA93: =IF(J93>0,1,IF(J93<0,0,-1)) -> 1 | AB93: =IF(K93>0,1,IF(K93<0,0,-1)) -> 1 | AC93: =IF(L93>0,1,IF(L93<0,0,-1)) -> 1 | AD93: =IF(M93>0,1,IF(M93<0,0,-1)) -> 1 | AE93: All Regions | AF93: All Income Levels | AG93: 0 | AH93: 1 | AI93: 0 | AJ93: 1 | AK93: All Countries | AL93: =IF(OR(B93="other",B93="international",B93="Transfers",B93="expenditure"),1,0) -> 0 | AM93: =IF(AND(INDIRECT(AN93)='Sample Select backend'!$C$2,INDIRECT(AO93)=1,INDIRECT(AP93)='Sample Select backend'!$F$2,INDIRECT(AQ93)=1,INDIRECT(AR93)='Sample Select backend'!$M$2),1,0) -> 0 | AN93: =_xlfn.CONCAT('Sample Select backend'!$C$4,ROW(AN93)) -> AE93 | AO93: =_xlfn.CONCAT('Sample Select backend'!$J$2,ROW(AO93)) -> AJ93 | AP93: =_xlfn.CONCAT('Sample Select backend'!$F$4,ROW(AP93)) -> AF93 | AQ93: =_xlfn.CONCAT('Sample Select backend'!$I$10,ROW(AQ93)) -> R93 | AR93: =_xlfn.CONCAT('Sample Select backend'!$M$4,ROW(AR93)) -> AK93 | AS93: =A93 -> Argentina | AT93: =IF(ISNUMBER(C93),C93,IF(OR(C93="general",C93="23;general"),"General",IF(OR(C93="exemption",C93="other (exemption)"),"Tax exemption/waiver/suspension","Other"))) -> 6 | AU93: =IF(A93<>A92,1,0) -> 0 | AV93: 1
A94: Argentina | B94: 6 | C94: 25 | D94: Transfer of AR$D10,000 to informal workers (3.6 million people). | E94: 1 | F94: 1 | G94: -2 | H94: -1 | I94: 2 | J94: 2 | K94: 1 | L94: -2 | M94: 1 | N94: ARG | O94: Latin America & the Caribbean | P94: IBRD | Q94: Upper Middle Income | R94: 0 | S94: -10.03 | T94: -6.56 | U94: 105.58 | V94: =IF(E94>0,1,IF(E94<0,0,-1)) -> 1 | W94: =IF(F94>0,1,IF(F94<0,0,-1)) -> 1 | X94: =IF(G94>0,1,IF(G94<0,0,-1)) -> 0 | Y94: =IF(H94>0,1,IF(H94<0,0,-1)) -> 0 | Z94: =IF(I94>0,1,IF(I94<0,0,-1)) -> 1 | AA94: =IF(J94>0,1,IF(J94<0,0,-1)) -> 1 | AB94: =IF(K94>0,1,IF(K94<0,0,-1)) -> 1 | AC94: =IF(L94>0,1,IF(L94<0,0,-1)) -> 0 | AD94: =IF(M94>0,1,IF(M94<0,0,-1)) -> 1 | AE94: All Regions | AF94: All Income Levels | AG94: 0 | AH94: 1 | AI94: 0 | AJ94: 1 | AK94: All Countries | AL94: =IF(OR(B94="other",B94="international",B94="Transfers",B94="expenditure"),1,0) -> 0 | AM94: =IF(AND(INDIRECT(AN94)='Sample Select backend'!$C$2,INDIRECT(AO94)=1,INDIRECT(AP94)='Sample Select backend'!$F$2,INDIRECT(AQ94)=1,INDIRECT(AR94)='Sample Select backend'!$M$2),1,0) -> 0 | AN94: =_xlfn.CONCAT('Sample Select backend'!$C$4,ROW(AN94)) -> AE94 | AO94: =_xlfn.CONCAT('Sample Select backend'!$J$2,ROW(AO94)) -> AJ94 | AP94: =_xlfn.CONCAT('Sample Select backend'!$F$4,ROW(AP94)) -> AF94 | AQ94: =_xlfn.CONCAT('Sample Select backend'!$I$10,ROW(AQ94)) -> R94 | AR94: =_xlfn.CONCAT('Sample Select backend'!$M$4,ROW(AR94)) -> AK94 | AS94: =A94 -> Argentina | AT94: =IF(ISNUMBER(C94),C94,IF(OR(C94="general",C94="23;general"),"General",IF(OR(C94="exemption",C94="other (exemption)"),"Tax exemption/waiver/suspension","Other"))) -> 25 | AU94: =IF(A94<>A93,1,0) -> 0 | AV94: 1
A95: Argentina | B95: 6 | C95: 26 | D95: Higher unemployment insurance benefits and payments to minimum-wage workers. | E95: 1 | F95: 1 | G95: 2 | H95: -1 | I95: -2 | J95: -2 | K95: 1 | L95: 1 | M95: 1 | N95: ARG | O95: Latin America & the Caribbean | P95: IBRD | Q95: Upper Middle Income | R95: 0 | S95: -10.03 | T95: -6.56 | U95: 105.58 | V95: =IF(E95>0,1,IF(E95<0,0,-1)) -> 1 | W95: =IF(F95>0,1,IF(F95<0,0,-1)) -> 1 | X95: =IF(G95>0,1,IF(G95<0,0,-1)) -> 1 | Y95: =IF(H95>0,1,IF(H95<0,0,-1)) -> 0 | Z95: =IF(I95>0,1,IF(I95<0,0,-1)) -> 0 | AA95: =IF(J95>0,1,IF(J95<0,0,-1)) -> 0 | AB95: =IF(K95>0,1,IF(K95<0,0,-1)) -> 1 | AC95: =IF(L95>0,1,IF(L95<0,0,-1)) -> 1 | AD95: =IF(M95>0,1,IF(M95<0,0,-1)) -> 1 | AE95: All Regions | AF95: All Income Levels | AG95: 0 | AH95: 1 | AI95: 0 | AJ95: 1 | AK95: All Countries | AL95: =IF(OR(B95="other",B95="international",B95="Transfers",B95="expenditure"),1,0) -> 0 | AM95: =IF(AND(INDIRECT(AN95)='Sample Select backend'!$C$2,INDIRECT(AO95)=1,INDIRECT(AP95)='Sample Select backend'!$F$2,INDIRECT(AQ95)=1,INDIRECT(AR95)='Sample Select backend'!$M$2),1,0) -> 0 | AN95: =_xlfn.CONCAT('Sample Select backend'!$C$4,ROW(AN95)) -> AE95 | AO95: =_xlfn.CONCAT('Sample Select backend'!$J$2,ROW(AO95)) -> AJ95 | AP95: =_xlfn.CONCAT('Sample Select backend'!$F$4,ROW(AP95)) -> AF95 | AQ95: =_xlfn.CONCAT('Sample Select backend'!$I$10,ROW(AQ95)) -> R95 | AR95: =_xlfn.CONCAT('Sample Select backend'!$M$4,ROW(AR95)) -> AK95 | AS95: =A95 -> Argentina | AT95: =IF(ISNUMBER(C95),C95,IF(OR(C95="general",C95="23;general"),"General",IF(OR(C95="exemption",C95="other (exemption)"),"Tax exemption/waiver/suspension","Other"))) -> 26 | AU95: =IF(A95<>A94,1,0) -> 0 | AV95: 1
A96: Argentina | B96: 6 | C96: 27 | D96: Supplementing of pensions up to a certain amount. | E96: 1 | F96: 1 | G96: 1 | H96: -1 | I96: 1 | J96: -2 | K96: 1 | L96: 1 | M96: 1 | N96: ARG | O96: Latin America & the Caribbean | P96: IBRD | Q96: Upper Middle Income | R96: 0 | S96: -10.03 | T96: -6.56 | U96: 105.58 | V96: =IF(E96>0,1,IF(E96<0,0,-1)) -> 1 | W96: =IF(F96>0,1,IF(F96<0,0,-1)) -> 1 | X96: =IF(G96>0,1,IF(G96<0,0,-1)) -> 1 | Y96: =IF(H96>0,1,IF(H96<0,0,-1)) -> 0 | Z96: =IF(I96>0,1,IF(I96<0,0,-1)) -> 1 | AA96: =IF(J96>0,1,IF(J96<0,0,-1)) -> 0 | AB96: =IF(K96>0,1,IF(K96<0,0,-1)) -> 1 | AC96: =IF(L96>0,1,IF(L96<0,0,-1)) -> 1 | AD96: =IF(M96>0,1,IF(M96<0,0,-1)) -> 1 | AE96: All Regions | AF96: All Income Levels | AG96: 0 | AH96: 1 | AI96: 0 | AJ96: 1 | AK96: All Countries | AL96: =IF(OR(B96="other",B96="international",B96="Transfers",B96="expenditure"),1,0) -> 0 | AM96: =IF(AND(INDIRECT(AN96)='Sample Select backend'!$C$2,INDIRECT(AO96)=1,INDIRECT(AP96)='Sample Select backend'!$F$2,INDIRECT(AQ96)=1,INDIRECT(AR96)='Sample Select backend'!$M$2),1,0) -> 0 | AN96: =_xlfn.CONCAT('Sample Select backend'!$C$4,ROW(AN96)) -> AE96 | AO96: =_xlfn.CONCAT('Sample Select backend'!$J$2,ROW(AO96)) -> AJ96 | AP96: =_xlfn.CONCAT('Sample Select backend'!$F$4,ROW(AP96)) -> AF96 | AQ96: =_xlfn.CONCAT('Sample Select backend'!$I$10,ROW(AQ96)) -> R96 | AR96: =_xlfn.CONCAT('Sample Select backend'!$M$4,ROW(AR96)) -> AK96 | AS96: =A96 -> Argentina | AT96: =IF(ISNUMBER(C96),C96,IF(OR(C96="general",C96="23;general"),"General",IF(OR(C96="exemption",C96="other (exemption)"),"Tax exemption/waiver/suspension","Other"))) -> 27 | AU96: =IF(A96<>A95,1,0) -> 0 | AV96: 1
A97: Argentina | B97: 2 | C97: other | D97: The repatriation of financial assets located abroad due date was extended for the 2019 fiscal year until April 30, 2020 | E97: -1 | F97: 2 | G97: -2 | H97: 1 | I97: 2 | J97: 2 | K97: 1 | L97: 1 | M97: 1 | N97: ARG | O97: Latin America & the Caribbean | P97: IBRD | Q97: Upper Middle Income | R97: 0 | S97: -10.03 | T97: -6.56 | U97: 105.58 | V97: =IF(E97>0,1,IF(E97<0,0,-1)) -> 0 | W97: =IF(F97>0,1,IF(F97<0,0,-1)) -> 1 | X97: =IF(G97>0,1,IF(G97<0,0,-1)) -> 0 | Y97: =IF(H97>0,1,IF(H97<0,0,-1)) -> 1 | Z97: =IF(I97>0,1,IF(I97<0,0,-1)) -> 1 | AA97: =IF(J97>0,1,IF(J97<0,0,-1)) -> 1 | AB97: =IF(K97>0,1,IF(K97<0,0,-1)) -> 1 | AC97: =IF(L97>0,1,IF(L97<0,0,-1)) -> 1 | AD97: =IF(M97>0,1,IF(M97<0,0,-1)) -> 1 | AE97: All Regions | AF97: All Income Levels | AG97: 0 | AH97: 1 | AI97: 0 | AJ97: 1 | AK97: All Countries | AL97: =IF(OR(B97="other",B97="international",B97="Transfers",B97="expenditure"),1,0) -> 0 | AM97: =IF(AND(INDIRECT(AN97)='Sample Select backend'!$C$2,INDIRECT(AO97)=1,INDIRECT(AP97)='Sample Select backend'!$F$2,INDIRECT(AQ97)=1,INDIRECT(AR97)='Sample Select backend'!$M$2),1,0) -> 0 | AN97: =_xlfn.CONCAT('Sample Select backend'!$C$4,ROW(AN97)) -> AE97 | AO97: =_xlfn.CONCAT('Sample Select backend'!$J$2,ROW(AO97)) -> AJ97 | AP97: =_xlfn.CONCAT('Sample Select backend'!$F$4,ROW(AP97)) -> AF97 | AQ97: =_xlfn.CONCAT('Sample Select backend'!$I$10,ROW(AQ97)) -> R97 | AR97: =_xlfn.CONCAT('Sample Select backend'!$M$4,ROW(AR97)) -> AK97 | AS97: =A97 -> Argentina | AT97: =IF(ISNUMBER(C97),C97,IF(OR(C97="general",C97="23;general"),"General",IF(OR(C97="exemption",C97="other (exemption)"),"Tax exemption/waiver/suspension","Other"))) -> Other | AU97: =IF(A97<>A96,1,0) -> 0 | AV97: 1
A98: Argentina | B98: 3 | C98: exemption | D98: The Government exempted medical supplies and vaccines from VAT and import duties | E98: 1 | F98: 1 | G98: -2 | H98: -1 | I98: -2 | J98: -2 | K98: -2 | M98: 1 | N98: ARG | O98: Latin America & the Caribbean | P98: IBRD | Q98: Upper Middle Income | R98: 0 | S98: -10.03 | T98: -6.56 | U98: 105.58 | V98: =IF(E98>0,1,IF(E98<0,0,-1)) -> 1 | W98: =IF(F98>0,1,IF(F98<0,0,-1)) -> 1 | X98: =IF(G98>0,1,IF(G98<0,0,-1)) -> 0 | Y98: =IF(H98>0,1,IF(H98<0,0,-1)) -> 0 | Z98: =IF(I98>0,1,IF(I98<0,0,-1)) -> 0 | AA98: =IF(J98>0,1,IF(J98<0,0,-1)) -> 0 | AB98: =IF(K98>0,1,IF(K98<0,0,-1)) -> 0 | AC98: =IF(L98>0,1,IF(L98<0,0,-1)) -> -1 | AD98: =IF(M98>0,1,IF(M98<0,0,-1)) -> 1 | AE98: All Regions | AF98: All Income Levels | AG98: 0 | AH98: 1 | AI98: 0 | AJ98: 1 | AK98: All Countries | AL98: =IF(OR(B98="other",B98="international",B98="Transfers",B98="expenditure"),1,0) -> 0 | AM98: =IF(AND(INDIRECT(AN98)='Sample Select backend'!$C$2,INDIRECT(AO98)=1,INDIRECT(AP98)='Sample Select backend'!$F$2,INDIRECT(AQ98)=1,INDIRECT(AR98)='Sample Select backend'!$M$2),1,0) -> 0 | AN98: =_xlfn.CONCAT('Sample Select backend'!$C$4,ROW(AN98)) -> AE98 | AO98: =_xlfn.CONCAT('Sample Select backend'!$J$2,ROW(AO98)) -> AJ98 | AP98: =_xlfn.CONCAT('Sample Select backend'!$F$4,ROW(AP98)) -> AF98 | AQ98: =_xlfn.CONCAT('Sample Select backend'!$I$10,ROW(AQ98)) -> R98 | AR98: =_xlfn.CONCAT('Sample Select backend'!$M$4,ROW(AR98)) -> AK98 | AS98: =A98 -> Argentina | AT98: =IF(ISNUMBER(C98),C98,IF(OR(C98="general",C98="23;general"),"General",IF(OR(C98="exemption",C98="other (exemption)"),"Tax exemption/waiver/suspension","Other"))) -> Tax exemption/waiver/suspension | AU98: =IF(A98<>A97,1,0) -> 0 | AV98: 1
A99: Argentina | B99: 6 | C99: 25 | D99: Increased transfers to poor families. | E99: 2 | F99: 1 | G99: 1 | H99: -1 | I99: 2 | J99: -2 | K99: 1 | L99: 1 | M99: 1 | N99: ARG | O99: Latin America & the Caribbean | P99: IBRD | Q99: Upper Middle Income | R99: 0 | S99: -10.03 | T99: -6.56 | U99: 105.58 | V99: =IF(E99>0,1,IF(E99<0,0,-1)) -> 1 | W99: =IF(F99>0,1,IF(F99<0,0,-1)) -> 1 | X99: =IF(G99>0,1,IF(G99<0,0,-1)) -> 1 | Y99: =IF(H99>0,1,IF(H99<0,0,-1)) -> 0 | Z99: =IF(I99>0,1,IF(I99<0,0,-1)) -> 1 | AA99: =IF(J99>0,1,IF(J99<0,0,-1)) -> 0 | AB99: =IF(K99>0,1,IF(K99<0,0,-1)) -> 1 | AC99: =IF(L99>0,1,IF(L99<0,0,-1)) -> 1 | AD99: =IF(M99>0,1,IF(M99<0,0,-1)) -> 1 | AE99: All Regions | AF99: All Income Levels | AG99: 0 | AH99: 1 | AI99: 0 | AJ99: 1 | AK99: All Countries | AL99: =IF(OR(B99="other",B99="international",B99="Transfers",B99="expenditure"),1,0) -> 0 | AM99: =IF(AND(INDIRECT(AN99)='Sample Select backend'!$C$2,INDIRECT(AO99)=1,INDIRECT(AP99)='Sample Select backend'!$F$2,INDIRECT(AQ99)=1,INDIRECT(AR99)='Sample Select backend'!$M$2),1,0) -> 0 | AN99: =_xlfn.CONCAT('Sample Select backend'!$C$4,ROW(AN99)) -> AE99 | AO99: =_xlfn.CONCAT('Sample Select backend'!$J$2,ROW(AO99)) -> AJ99 | AP99: =_xlfn.CONCAT('Sample Select backend'!$F$4,ROW(AP99)) -> AF99 | AQ99: =_xlfn.CONCAT('Sample Select backend'!$I$10,ROW(AQ99)) -> R99 | AR99: =_xlfn.CONCAT('Sample Select backend'!$M$4,ROW(AR99)) -> AK99 | AS99: =A99 -> Argentina | AT99: =IF(ISNUMBER(C99),C99,IF(OR(C99="general",C99="23;general"),"General",IF(OR(C99="exemption",C99="other (exemption)"),"Tax exemption/waiver/suspension","Other"))) -> 25 | AU99: =IF(A99<>A98,1,0) -> 0 | AV99: 1
A100: Argentina | B100: 1 | C100: 11 | D100: Suspension of collection measures enforced by AFIP in respect of debts of SMEs | E100: 2 | F100: 2 | G100: -1 | H100: 2 | I100: 2 | J100: 2 | K100: 1 | L100: 1 | M100: 1 | N100: ARG | O100: Latin America & the Caribbean | P100: IBRD | Q100: Upper Middle Income | R100: 0 | S100: -10.03 | T100: -6.56 | U100: 105.58 | V100: =IF(E100>0,1,IF(E100<0,0,-1)) -> 1 | W100: =IF(F100>0,1,IF(F100<0,0,-1)) -> 1 | X100: =IF(G100>0,1,IF(G100<0,0,-1)) -> 0 | Y100: =IF(H100>0,1,IF(H100<0,0,-1)) -> 1 | Z100: =IF(I100>0,1,IF(I100<0,0,-1)) -> 1 | AA100: =IF(J100>0,1,IF(J100<0,0,-1)) -> 1 | AB100: =IF(K100>0,1,IF(K100<0,0,-1)) -> 1 | AC100: =IF(L100>0,1,IF(L100<0,0,-1)) -> 1 | AD100: =IF(M100>0,1,IF(M100<0,0,-1)) -> 1 | AE100: All Regions | AF100: All Income Levels | AG100: 0 | AH100: 1 | AI100: 0 | AJ100: 1 | AK100: All Countries | AL100: =IF(OR(B100="other",B100="international",B100="Transfers",B100="expenditure"),1,0) -> 0 | AM100: =IF(AND(INDIRECT(AN100)='Sample Select backend'!$C$2,INDIRECT(AO100)=1,INDIRECT(AP100)='Sample Select backend'!$F$2,INDIRECT(AQ100)=1,INDIRECT(AR100)='Sample Select backend'!$M$2),1,0) -> 0 | AN100: =_xlfn.CONCAT('Sample Select backend'!$C$4,ROW(AN100)) -> AE100 | AO100: =_xlfn.CONCAT('Sample Select backend'!$J$2,ROW(AO100)) -> AJ100 | AP100: =_xlfn.CONCAT('Sample Select backend'!$F$4,ROW(AP100)) -> AF100 | AQ100: =_xlfn.CONCAT('Sample Select backend'!$I$10,ROW(AQ100)) -> R100 | AR100: =_xlfn.CONCAT('Sample Select backend'!$M$4,ROW(AR100)) -> AK100 | AS100: =A100 -> Argentina | AT100: =IF(ISNUMBER(C100),C100,IF(OR(C100="general",C100="23;general"),"General",IF(OR(C100="exemption",C100="other (exemption)"),"Tax exemption/waiver/suspension","Other"))) -> 11 | AU100: =IF(A100<>A99,1,0) -> 0 | AV100: 1
...

Sheet Introduction

Sheet Sample Selection
I2: Number | J2: List of Selected Countries
I3: =IF(MAX('Sample Select backend'!$K$4:$K$205)>=ROW(I3)-2,ROW(I3)-2,"") -> 1 | J3: =IFERROR(VLOOKUP(I3,'Sample Select backend'!$K$4:$L$205,2,FALSE),"No countries selected!") -> Australia
I4: =IF(MAX('Sample Select backend'!$K$4:$K$205)>=ROW(I4)-2,ROW(I4)-2,"") -> 2 | J4: =IFERROR(VLOOKUP(I4,'Sample Select backend'!$K$4:$L$205,2,FALSE),"") -> Canada
I5: =IF(MAX('Sample Select backend'!$K$4:$K$205)>=ROW(I5)-2,ROW(I5)-2,"") -> 3 | J5: =IFERROR(VLOOKUP(I5,'Sample Select backend'!$K$4:$L$205,2,FALSE),"") -> Chile
I6: =IF(MAX('Sample Select backend'!$K$4:$K$205)>=ROW(I6)-2,ROW(I6)-2,"") -> 4 | J6: =IFERROR(VLOOKUP(I6,'Sample Select backend'!$K$4:$L$205,2,FALSE),"") -> Colombia
I7: =IF(MAX('Sample Select backend'!$K$4:$K$205)>=ROW(I7)-2,ROW(I7)-2,"") -> 5 | J7: =IFERROR(VLOOKUP(I7,'Sample Select backend'!$K$4:$L$205,2,FALSE),"") -> Costa Rica
I8: =IF(MAX('Sample Select backend'!$K$4:$K$205)>=ROW(I8)-2,ROW(I8)-2,"") -> 6 | J8: =IFERROR(VLOOKUP(I8,'Sample Select backend'!$K$4:$L$205,2,FALSE),"") -> Germany
I9: =IF(MAX('Sample Select backend'!$K$4:$K$205)>=ROW(I9)-2,ROW(I9)-2,"") -> 7 | J9: =IFERROR(VLOOKUP(I9,'Sample Select backend'!$K$4:$L$205,2,FALSE),"") -> Greece
I10: =IF(MAX('Sample Select backend'!$K$4:$K$205)>=ROW(I10)-2,ROW(I10)-2,"") -> 8 | J10: =IFERROR(VLOOKUP(I10,'Sample Select backend'!$K$4:$L$205,2,FALSE),"") -> Ireland
I11: =IF(MAX('Sample Select backend'!$K$4:$K$205)>=ROW(I11)-2,ROW(I11)-2,"") -> 9 | J11: =IFERROR(VLOOKUP(I11,'Sample Select backend'!$K$4:$L$205,2,FALSE),"") -> Italy
I12: =IF(MAX('Sample Select backend'!$K$4:$K$205)>=ROW(I12)-2,ROW(I12)-2,"") -> 10 | J12: =IFERROR(VLOOKUP(I12,'Sample Select backend'!$K$4:$L$205,2,FALSE),"") -> Netherlands
I13: =IF(MAX('Sample Select backend'!$K$4:$K$205)>=ROW(I13)-2,ROW(I13)-2,"") -> 11 | J13: =IFERROR(VLOOKUP(I13,'Sample Select backend'!$K$4:$L$205,2,FALSE),"") -> Portugal
I14: =IF(MAX('Sample Select backend'!$K$4:$K$205)>=ROW(I14)-2,ROW(I14)-2,"") -> 12 | J14: =IFERROR(VLOOKUP(I14,'Sample Select backend'!$K$4:$L$205,2,FALSE),"") -> Spain
I15: =IF(MAX('Sample Select backend'!$K$4:$K$205)>=ROW(I15)-2,ROW(I15)-2,"") -> 13 | J15: =IFERROR(VLOOKUP(I15,'Sample Select backend'!$K$4:$L$205,2,FALSE),"") -> Turkey
... I204: =IF(MAX('Sample Select backend'!$K$4:$K$205)>=ROW(I204)-2,ROW(I204)-2,"") | J204: =IFERROR(VLOOKUP(I204,'Sample Select backend'!$K$4:$L$205,2,FALSE),"")

Sheet Sample Select backend
B2: 1 | C2: =OFFSET(B2,B2,0) -> All Regions | E2: 1 | F2: =OFFSET(E2,E2,0) -> All Income Levels | H2: 1 | I2: =OFFSET(H2,H2,1) -> Data!$AJ:$AJ | J2: =RIGHT(OFFSET(H2,H2,1),2) -> AJ | L2: 1 | M2: =OFFSET(L2,L2,0) -> All Countries | AC2: # of policies | AD2: rank | AE2: rownum | AF2: nth of rank | AG2: % of total
B3: All Regions | C3: =IF(B2>1,"Data!$O:$O","Data!$AE:$AE") -> Data!$AE:$AE | E3: All Income Levels | F3: =IF(E2>1,"Data!$Q:$Q","Data!$AF:$AF") -> Data!$AF:$AF | H3: All Lending Categories | I3: Data!$AJ:$AJ | L3: All Countries | M3: =IF(L2>1,"Data!$A:$A","Data!$AK:$AK") -> Data!$AK:$AK | P3: 1 | Q3: Revenue Measures to protect businesses | R3: 1 | S3: Accelerated asset depreciation (CIT) | Y3: 7 | Z3: Credit and equity measures | AA3: Other | AB3: Other | AC3: =COUNTIFS(Data!$B:$B,$Y3,Data!$AT:$AT,$AA3,INDIRECT($C$3),$C$2,INDIRECT($F$3),$F$2,INDIRECT($I$2),1,INDIRECT($M$3),$M$2,INDIRECT($I$9),1) -> 9 | AD3: =IF(AC3>0,RANK(AC3,AC$3:AC$55),#N/A) -> 22 | AE3: =ROW(AE3) -> 3 | AF3: =COUNTIF(AD$3:AD3,AD3) -> 1 | AG3: =AC3/$AH$17*100 -> 1.5 | AO3: =Z3 -> Credit and equity measures | AP3: =AB3 -> Other | AQ3: =AC3 -> 9
B4: Europe & Central Asia | C4: =IF(B2>1,"O","AE") -> AE | E4: Low Income | F4: =IF(E2>1,"Q","AF") -> AF | H4: IDA/Blend only | I4: Data!$AG:$AG | K4: =IF(VLOOKUP($L4,Data!$A$2:$AM$3992,39,FALSE)=1,1+MAX($K$3:K3),0) -> 0 | L4: Afghanistan | M4: =IF(L2>1,"A","AK") -> AK | P4: 1 | Q4: Revenue Measures to protect businesses | R4: 2 | S4: Extend loss carry-forward (CIT) | Y4: 7 | Z4: Credit and equity measures | AA4: 32 | AB4: Preferential loans to households | AC4: =COUNTIFS(Data!$B:$B,$Y4,Data!$AT:$AT,$AA4,INDIRECT($C$3),$C$2,INDIRECT($F$3),$F$2,INDIRECT($I$2),1,INDIRECT($M$3),$M$2,INDIRECT($I$9),1) -> 5 | AD4: =IF(AC4>0,RANK(AC4,AC$3:AC$55),#N/A) -> 34 | AE4: =ROW(AE4) -> 4 | AF4: =COUNTIF(AD$3:AD4,AD4) -> 1 | AG4: =AC4/$AH$17*100 -> 0.83333333 | AP4: =AB4 -> Preferential loans to households | AQ4: =AC4 -> 5
B5: Latin America & the Caribbean | E5: Lower Middle Income | H5: IBRD only | I5: Data!$AH:$AH | K5: =IF(VLOOKUP($L5,Data!$A$2:$AM$3992,39,FALSE)=1,1+MAX($K$3:K4),0) -> 0 | L5: Albania | P5: 1 | Q5: Revenue Measures to protect businesses | R5: 3 | S5: Broaden tax deductibility | Y5: 7 | Z5: Credit and equity measures | AA5: 31 | AB5: One-off grants | AC5: =COUNTIFS(Data!$B:$B,$Y5,Data!$AT:$AT,$AA5,INDIRECT($C$3),$C$2,INDIRECT($F$3),$F$2,INDIRECT($I$2),1,INDIRECT($M$3),$M$2,INDIRECT($I$9),1) -> 14 | AD5: =IF(AC5>0,RANK(AC5,AC$3:AC$55),#N/A) -> 14 | AE5: =ROW(AE5) -> 5 | AF5: =COUNTIF(AD$3:AD5,AD5) -> 1 | AG5: =AC5/$AH$17*100 -> 2.3333333 | AP5: =AB5 -> One-off grants | AQ5: =AC5 -> 14 | AT5: May 1 2020 | AU5: Sept 1 2020
B6: South Asia | E6: Upper Middle Income | H6: Neither IDA nor IBRD | I6: Data!$AI:$AI | K6: =IF(VLOOKUP($L6,Data!$A$2:$AM$3992,39,FALSE)=1,1+MAX($K$3:K5),0) -> 0 | L6: Algeria | P6: 1 | Q6: Revenue Measures to protect businesses | R6: 4 | S6: Tax credits | Y6: 7 | Z6: Credit and equity measures | AA6: 30 | AB6: Preferential loans to firms | AC6: =COUNTIFS(Data!$B:$B,$Y6,Data!$AT:$AT,$AA6,INDIRECT($C$3),$C$2,INDIRECT($F$3),$F$2,INDIRECT($I$2),1,INDIRECT($M$3),$M$2,INDIRECT($I$9),1) -> 54 | AD6: =IF(AC6>0,RANK(AC6,AC$3:AC$55),#N/A) -> 2 | AE6: =ROW(AE6) -> 6 | AF6: =COUNTIF(AD$3:AD6,AD6) -> 1 | AG6: =AC6/$AH$17*100 -> 9 | AH6: =_xlfn.CONCAT("Total revenue measures: ",AH7) -> Total revenue measures: 290 | AP6: =AB6 -> Preferential loans to firms | AQ6: =AC6 -> 54 | AT6: =COUNTIFS(Data!$AM:$AM,1,Data!$AV:$AV,1) -> 365 | AU6: =AH17-AT6 -> 235
B7: Sub-Saharan Africa | E7: High Income | I7: =OFFSET(H2,H2,0) -> All Lending Categories | K7: =IF(VLOOKUP($L7,Data!$A$2:$AM$3992,39,FALSE)=1,1+MAX($K$3:K6),0) -> 0 | L7: Angola | P7: 1 | Q7: Revenue Measures to protect businesses | R7: 5 | S7: Deferral of tax filing | AH7: =SUM(Q57:Q61) -> 290 | AO7: =Z8 -> Expenditure Measures for cash transfers to individuals | AP7: =AB8 -> Other | AQ7: =AC8 -> 8
B8: Middle East & North Africa | K8: =IF(VLOOKUP($L8,Data!$A$2:$AM$3992,39,FALSE)=1,1+MAX($K$3:K7),0) -> 0 | L8: Anguilla | P8: 1 | Q8: Revenue Measures to protect businesses | R8: 6 | S8: Deferral of tax payments | Y8: 6 | Z8: Expenditure Measures for cash transfers to individuals | AA8: Other | AB8: Other | AC8: =COUNTIFS(Data!$B:$B,$Y8,Data!$AT:$AT,$AA8,INDIRECT($C$3),$C$2,INDIRECT($F$3),$F$2,INDIRECT($I$2),1,INDIRECT($M$3),$M$2,INDIRECT($I$9),1) -> 8 | AD8: =IF(AC8>0,RANK(AC8,AC$3:AC$55),#N/A) -> 26 | AE8: =ROW(AE8) -> 8 | AF8: =COUNTIF(AD$3:AD8,AD8) -> 1 | AG8: =AC8/$AH$17*100 -> 1.3333333 | AP8: =AB9 -> Wage compensation/ enhanced paid leave | AQ8: =AC9 -> 38
B9: East Asia & Pacific | G9: FCV: | H9: TRUE | I9: =IF(H9,"Data!$R:$R","Data!$AJ:$AJ") -> Data!$R:$R | K9: =IF(VLOOKUP($L9,Data!$A$2:$AM$3992,39,FALSE)=1,1+MAX($K$3:K8),0) -> 0 | L9: Antigua and Barbuda | P9: 1 | Q9: Revenue Measures to protect businesses | R9: 7 | S9: Tax rate reduction | Y9: 6 | Z9: Expenditure Measures for cash transfers to individuals | AA9: 29 | AB9: Wage compensation/ enhanced paid leave | AC9: =COUNTIFS(Data!$B:$B,$Y9,Data!$AT:$AT,$AA9,INDIRECT($C$3),$C$2,INDIRECT($F$3),$F$2,INDIRECT($I$2),1,INDIRECT($M$3),$M$2,INDIRECT($I$9),1) -> 38 | AD9: =IF(AC9>0,RANK(AC9,AC$3:AC$55),#N/A) -> 3 | AE9: =ROW(AE9) -> 9 | AF9: =COUNTIF(AD$3:AD9,AD9) -> 1 | AG9: =AC9/$AH$17*100 -> 6.3333333 | AH9: =_xlfn.CONCAT("Total expenditure measures: ",AH10) -> Total expenditure measures: 212 | AP9: =AB10 -> Supplementary ad hoc programs | AQ9: =AC10 -> 33
B10: North America | G10: =IF(H9,"FCV","both FCV and Non-FCV") -> FCV | I10: =IF(H9,"R","AJ") -> R | K10: =IF(VLOOKUP($L10,Data!$A$2:$AM$3992,39,FALSE)=1,1+MAX($K$3:K9),0) -> 0 | L10: Argentina | P10: 1 | Q10: Revenue Measures to protect businesses | R10: 8 | S10: Tax amnesty / incentives | Y10: 6 | Z10: Expenditure Measures for cash transfers to individuals | AA10: 28 | AB10: Supplementary ad hoc programs | AC10: =COUNTIFS(Data!$B:$B,$Y10,Data!$AT:$AT,$AA10,INDIRECT($C$3),$C$2,INDIRECT($F$3),$F$2,INDIRECT($I$2),1,INDIRECT($M$3),$M$2,INDIRECT($I$9),1) -> 33 | AD10: =IF(AC10>0,RANK(AC10,AC$3:AC$55),#N/A) -> 4 | AE10: =ROW(AE10) -> 10 | AF10: =COUNTIF(AD$3:AD10,AD10) -> 1 | AG10: =AC10/$AH$17*100 -> 5.5 | AH10: =SUM(Q54:Q56) -> 212 | AP10: =AB11 -> Temporary expansion of existing benefits | AQ10: =AC11 -> 21
K11: =IF(VLOOKUP($L11,Data!$A$2:$AM$3992,39,FALSE)=1,1+MAX($K$3:K10),0) -> 0 | L11: Armenia | P11: 1 | Q11: Revenue Measures to protect businesses | R11: 9 | S11: Accelerating refunds | Y11: 6 | Z11: Expenditure Measures for cash transfers to individuals | AA11: 27 | AB11: Temporary expansion of existing benefits | AC11: =COUNTIFS(Data!$B:$B,$Y11,Data!$AT:$AT,$AA11,INDIRECT($C$3),$C$2,INDIRECT($F$3),$F$2,INDIRECT($I$2),1,INDIRECT($M$3),$M$2,INDIRECT($I$9),1) -> 21 | AD11: =IF(AC11>0,RANK(AC11,AC$3:AC$55),#N/A) -> 7 | AE11: =ROW(AE11) -> 11 | AF11: =COUNTIF(AD$3:AD11,AD11) -> 1 | AG11: =AC11/$AH$17*100 -> 3.5 | AP11: =AB12 -> Expansion of unemployment benefits | AQ11: =AC12 -> 18
K12: =IF(VLOOKUP($L12,Data!$A$2:$AM$3992,39,FALSE)=1,1+MAX($K$3:K11),0) -> 0 | L12: Aruba | P12: 1 | Q12: Revenue Measures to protect businesses | R12: 10 | S12: Lower advance payment | Y12: 6 | Z12: Expenditure Measures for cash transfers to individuals | AA12: 26 | AB12: Expansion of unemployment benefits | AC12: =COUNTIFS(Data!$B:$B,$Y12,Data!$AT:$AT,$AA12,INDIRECT($C$3),$C$2,INDIRECT($F$3),$F$2,INDIRECT($I$2),1,INDIRECT($M$3),$M$2,INDIRECT($I$9),1) -> 18 | AD12: =IF(AC12>0,RANK(AC12,AC$3:AC$55),#N/A) -> 10 | AE12: =ROW(AE12) -> 12 | AF12: =COUNTIF(AD$3:AD12,AD12) -> 1 | AG12: =AC12/$AH$17*100 -> 3 | AH12: =_xlfn.CONCAT("Total credit and equity measures: ",Q53) -> Total credit and equity measures: 82 | AP12: =AB13 -> Direct cash transfers for individuals | AQ12: =AC13 -> 29
K13: =IF(VLOOKUP($L13,Data!$A$2:$AM$3992,39,FALSE)=1,1+MAX($K$3:K12),0) -> 1 | L13: Australia | P13: 1 | Q13: Revenue Measures to protect businesses | R13: 11 | S13: Suspend debt collection | Y13: 6 | Z13: Expenditure Measures for cash transfers to individuals | AA13: 25 | AB13: Direct cash transfers for individuals | AC13: =COUNTIFS(Data!$B:$B,$Y13,Data!$AT:$AT,$AA13,INDIRECT($C$3),$C$2,INDIRECT($F$3),$F$2,INDIRECT($I$2),1,INDIRECT($M$3),$M$2,INDIRECT($I$9),1) -> 29 | AD13: =IF(AC13>0,RANK(AC13,AC$3:AC$55),#N/A) -> 5 | AE13: =ROW(AE13) -> 13 | AF13: =COUNTIF(AD$3:AD13,AD13) -> 1 | AG13: =AC13/$AH$17*100 -> 4.8333333 | AO13: =Z15 -> Health Expenditures measures | AP13: =AB15 -> General | AQ13: =AC15 -> 21
K14: =IF(VLOOKUP($L14,Data!$A$2:$AM$3992,39,FALSE)=1,1+MAX($K$3:K13),0) -> 0 | L14: Austria | P14: 1 | Q14: Revenue Measures to protect businesses | R14: 12 | S14: Suspend audit activities | AH14: =_xlfn.CONCAT("Total other measures: ",Q52) -> Total other measures: 16 | AP14: =AB16 -> Expansion of human resources | AQ14: =AC16 -> 4
K15: =IF(VLOOKUP($L15,Data!$A$2:$AM$3992,39,FALSE)=1,1+MAX($K$3:K14),0) -> 0 | L15: Azerbaijan | P15: 1 | Q15: Revenue Measures to protect businesses | R15: exemption | S15: Tax exemption/waiver/suspension | Y15: 5 | Z15: Health Expenditures measures | AA15: General | AB15: General | AC15: =COUNTIFS(Data!$B:$B,$Y15,Data!$AT:$AT,$AA15,INDIRECT($C$3),$C$2,INDIRECT($F$3),$F$2,INDIRECT($I$2),1,INDIRECT($M$3),$M$2,INDIRECT($I$9),1) -> 21 | AD15: =IF(AC15>0,RANK(AC15,AC$3:AC$55),#N/A) -> 7 | AE15: =ROW(AE15) -> 15 | AF15: =COUNTIF(AD$3:AD15,AD15) -> 2 | AG15: =AC15/$AH$17*100 -> 3.5 | AP15: =AB17 -> Targeted infrastructure investments | AQ15: =AC17 -> 8
K16: =IF(VLOOKUP($L16,Data!$A$2:$AM$3992,39,FALSE)=1,1+MAX($K$3:K15),0) -> 0 | L16: Bahamas, The | P16: 1 | Q16: Revenue Measures to protect businesses | R16: other | S16: Other | Y16: 5 | Z16: Health Expenditures measures | AA16: 24 | AB16: Expansion of human resources | AC16: =COUNTIFS(Data!$B:$B,$Y16,Data!$AT:$AT,$AA16,INDIRECT($C$3),$C$2,INDIRECT($F$3),$F$2,INDIRECT($I$2),1,INDIRECT($M$3),$M$2,INDIRECT($I$9),1) -> 4 | AD16: =IF(AC16>0,RANK(AC16,AC$3:AC$55),#N/A) -> 36 | AE16: =ROW(AE16) -> 16 | AF16: =COUNTIF(AD$3:AD16,AD16) -> 1 | AG16: =AC16/$AH$17*100 -> 0.66666667 | AH16: =_xlfn.CONCAT("Total measures: ",AH17) -> Total measures: 600 | AP16: =AB18 -> Supply of high cost medical items | AQ16: =AC18 -> 1
K17: =IF(VLOOKUP($L17,Data!$A$2:$AM$3992,39,FALSE)=1,1+MAX($K$3:K16),0) -> 0 | L17: Bahrain | P17: 2 | Q17: Revenue Measures to protect individuals | R17: 13 | S17: Deferral of tax filing | Y17: 5 | Z17: Health Expenditures measures | AA17: 23 | AB17: Targeted infrastructure investments | AC17: =COUNTIFS(Data!$B:$B,$Y17,Data!$AT:$AT,$AA17,INDIRECT($C$3),$C$2,INDIRECT($F$3),$F$2,INDIRECT($I$2),1,INDIRECT($M$3),$M$2,INDIRECT($I$9),1) -> 8 | AD17: =IF(AC17>0,RANK(AC17,AC$3:AC$55),#N/A) -> 26 | AE17: =ROW(AE17) -> 17 | AF17: =COUNTIF(AD$3:AD17,AD17) -> 2 | AG17: =AC17/$AH$17*100 -> 1.3333333 | AH17: =SUM(AH7,AH10,Q52,Q53) -> 600 | AP17: =AB19 -> Supply of low cost medical items | AQ17: =AC19 -> 0
C18: =_xlfn.CONCAT("Current sample: ",IF(MAX(K4:K202)=0,"No countries",IF(L2>1,M2,_xlfn.CONCAT(F2,", ",I7,", ",G10,", from ",C2)))) -> Current sample: All Income Levels, All Lending Categories, FCV, from All Regions | K18: =IF(VLOOKUP($L18,Data!$A$2:$AM$3992,39,FALSE)=1,1+MAX($K$3:K17),0) -> 0 | L18: Bangladesh | P18: 2 | Q18: Revenue Measures to protect individuals | R18: 14 | S18: Deferral of tax payments | Y18: 5 | Z18: Health Expenditures measures | AA18: 22 | AB18: Supply of high cost medical items | AC18: =COUNTIFS(Data!$B:$B,$Y18,Data!$AT:$AT,$AA18,INDIRECT($C$3),$C$2,INDIRECT($F$3),$F$2,INDIRECT($I$2),1,INDIRECT($M$3),$M$2,INDIRECT($I$9),1) -> 1 | AD18: =IF(AC18>0,RANK(AC18,AC$3:AC$55),#N/A) -> 43 | AE18: =ROW(AE18) -> 18 | AF18: =COUNTIF(AD$3:AD18,AD18) -> 1 | AG18: =AC18/$AH$17*100 -> 0.16666667 | AO18: =Z21 -> Revenue Measures to boost consumption / demand | AP18: =AB21 -> Other | AQ18: =AC21 -> 9
K19: =IF(VLOOKUP($L19,Data!$A$2:$AM$3992,39,FALSE)=1,1+MAX($K$3:K18),0) -> 0 | L19: Barbados | P19: 2 | Q19: Revenue Measures to protect individuals | R19: 15 | S19: Tax rate reduction | Y19: 5 | Z19: Health Expenditures measures | AA19: 21 | AB19: Supply of low cost medical items | AC19: =COUNTIFS(Data!$B:$B,$Y19,Data!$AT:$AT,$AA19,INDIRECT($C$3),$C$2,INDIRECT($F$3),$F$2,INDIRECT($I$2),1,INDIRECT($M$3),$M$2,INDIRECT($I$9),1) -> 0 | AD19: =IF(AC19>0,RANK(AC19,AC$3:AC$55),#N/A) -> #N/A | AE19: =ROW(AE19) -> 19 | AF19: =COUNTIF(AD$3:AD19,AD19) -> 1 | AG19: =AC19/$AH$17*100 -> 0 | AH19: Non-health | AP19: =AB22 -> Tax exemption/waiver/suspension | AQ19: =AC22 -> 4
K20: =IF(VLOOKUP($L20,Data!$A$2:$AM$3992,39,FALSE)=1,1+MAX($K$3:K19),0) -> 0 | L20: Belarus | P20: 2 | Q20: Revenue Measures to protect individuals | R20: 16 | S20: Tax amnesty / incentives | AH20: =AH17-Q56 -> 556 | AP20: =AB23 -> Lower tax rates | AQ20: =AC23 -> 15
K21: =IF(VLOOKUP($L21,Data!$A$2:$AM$3992,39,FALSE)=1,1+MAX($K$3:K20),0) -> 0 | L21: Belgium | P21: 2 | Q21: Revenue Measures to protect individuals | R21: 17 | S21: Broaden tax deductibility | Y21: 4 | Z21: Revenue Measures to boost consumption / demand | AA21: Other | AB21: Other | AC21: =COUNTIFS(Data!$B:$B,$Y21,Data!$AT:$AT,$AA21,INDIRECT($C$3),$C$2,INDIRECT($F$3),$F$2,INDIRECT($I$2),1,INDIRECT($M$3),$M$2,INDIRECT($I$9),1) -> 9 | AD21: =IF(AC21>0,RANK(AC21,AC$3:AC$55),#N/A) -> 22 | AE21: =ROW(AE21) -> 21 | AF21: =COUNTIF(AD$3:AD21,AD21) -> 2 | AG21: =AC21/$AH$17*100 -> 1.5 | AO21: =Z25 -> Revenue Measures to promote availability of medical items | AP21: =AB25 -> Other | AQ21: =AC25 -> 7
B22: Comparator for "performance within sample" sheet | K22: =IF(VLOOKUP($L22,Data!$A$2:$AM$3992,39,FALSE)=1,1+MAX($K$3:K21),0) -> 0 | L22: Belize | P22: 2 | Q22: Revenue Measures to protect individuals | R22: 18 | S22: Tax credits | Y22: 4 | Z22: Revenue Measures to boost consumption / demand | AA22: Tax exemption/waiver/suspension | AB22: Tax exemption/waiver/suspension | AC22: =COUNTIFS(Data!$B:$B,$Y22,Data!$AT:$AT,$AA22,INDIRECT($C$3),$C$2,INDIRECT($F$3),$F$2,INDIRECT($I$2),1,INDIRECT($M$3),$M$2,INDIRECT($I$9),1) -> 4 | AD22: =IF(AC22>0,RANK(AC22,AC$3:AC$55),#N/A) -> 36 | AE22: =ROW(AE22) -> 22 | AF22: =COUNTIF(AD$3:AD22,AD22) -> 2 | AG22: =AC22/$AH$17*100 -> 0.66666667 | AP22: =AB26 -> Tax exemption/waiver/suspension | AQ22: =AC26 -> 11
C23: Regions | D23: Income | E23: Lending | F23: FCV | G23: Country | K23: =IF(VLOOKUP($L23,Data!$A$2:$AM$3992,39,FALSE)=1,1+MAX($K$3:K22),0) -> 0 | L23: Benin | P23: 2 | Q23: Revenue Measures to protect individuals | R23: exemption | S23: Tax exemption/waiver/suspension | Y23: 4 | Z23: Revenue Measures to boost consumption / demand | AA23: 20 | AB23: Lower tax rates | AC23: =COUNTIFS(Data!$B:$B,$Y23,Data!$AT:$AT,$AA23,INDIRECT($C$3),$C$2,INDIRECT($F$3),$F$2,INDIRECT($I$2),1,INDIRECT($M$3),$M$2,INDIRECT($I$9),1) -> 15 | AD23: =IF(AC23>0,RANK(AC23,AC$3:AC$55),#N/A) -> 13 | AE23: =ROW(AE23) -> 23 | AF23: =COUNTIF(AD$3:AD23,AD23) -> 1 | AG23: =AC23/$AH$17*100 -> 2.5 | AP23: =AB27 -> Lower tax rates for medical items | AQ23: =AC27 -> 8
B24: Cell link | C24: 1 | D24: 1 | E24: 4 | F24: FALSE | G24: 1 | K24: =IF(VLOOKUP($L24,Data!$A$2:$AM$3992,39,FALSE)=1,1+MAX($K$3:K23),0) -> 0 | L24: Bermuda | P24: 2 | Q24: Revenue Measures to protect individuals | R24: other | S24: Other | AO24: =Z29 -> Revenue Measures to protect individuals | AP24: =AB29 -> Other | AQ24: =AC29 -> 9
B25: Condition | C25: =OFFSET(B2,C24,0) -> All Regions | D25: =OFFSET(E2,D24,0) -> All Income Levels | E25: 1 | F25: 1 | G25: =OFFSET(L2,G24,0) -> All Countries | K25: =IF(VLOOKUP($L25,Data!$A$2:$AM$3992,39,FALSE)=1,1+MAX($K$3:K24),0) -> 0 | L25: Bhutan | P25: 3 | Q25: Revenue Measures to promote availability of medical items | R25: 19 | S25: Lower tax rates for medical items | Y25: 3 | Z25: Revenue Measures to promote availability of medical items | AA25: Other | AB25: Other | AC25: =COUNTIFS(Data!$B:$B,$Y25,Data!$AT:$AT,$AA25,INDIRECT($C$3),$C$2,INDIRECT($F$3),$F$2,INDIRECT($I$2),1,INDIRECT($M$3),$M$2,INDIRECT($I$9),1) -> 7 | AD25: =IF(AC25>0,RANK(AC25,AC$3:AC$55),#N/A) -> 29 | AE25: =ROW(AE25) -> 25 | AF25: =COUNTIF(AD$3:AD25,AD25) -> 1 | AG25: =AC25/$AH$17*100 -> 1.1666667 | AP25: =AB30 -> Tax exemption/waiver/suspension | AQ25: =AC30 -> 6
B26: Address | C26: =IF(C24>1,"Data!$O:$O","Data!$AE:$AE") -> Data!$AE:$AE | D26: =IF(D24>1,"Data!$Q:$Q","Data!$AF:$AF") -> Data!$AF:$AF | E26: =OFFSET(H2,E24,1) -> Data!$AI:$AI | F26: =IF(F24,"Data!$R:$R","Data!$AJ:$AJ") -> Data!$AJ:$AJ | G26: =IF(G24>1,"Data!$A:$A","Data!$AK:$AK") -> Data!$AK:$AK | K26: =IF(VLOOKUP($L26,Data!$A$2:$AM$3992,39,FALSE)=1,1+MAX($K$3:K25),0) -> 0 | L26: Bolivia | P26: 3 | Q26: Revenue Measures to promote availability of medical items | R26: exemption | S26: Tax exemption/waiver/suspension | Y26: 3 | Z26: Revenue Measures to promote availability of medical items | AA26: Tax exemption/waiver/suspension | AB26: Tax exemption/waiver/suspension | AC26: =COUNTIFS(Data!$B:$B,$Y26,Data!$AT:$AT,$AA26,INDIRECT($C$3),$C$2,INDIRECT($F$3),$F$2,INDIRECT($I$2),1,INDIRECT($M$3),$M$2,INDIRECT($I$9),1) -> 11 | AD26: =IF(AC26>0,RANK(AC26,AC$3:AC$55),#N/A) -> 19 | AE26: =ROW(AE26) -> 26 | AF26: =COUNTIF(AD$3:AD26,AD26) -> 1 | AG26: =AC26/$AH$17*100 -> 1.8333333 | AP26: =AB31 -> Tax credits | AQ26: =AC31 -> 0
K27: =IF(VLOOKUP($L27,Data!$A$2:$AM$3992,39,FALSE)=1,1+MAX($K$3:K26),0) -> 0 | L27: Bosnia and Herzegovina | P27: 3 | Q27: Revenue Measures to promote availability of medical items | R27: other | S27: Other | Y27: 3 | Z27: Revenue Measures to promote availability of medical items | AA27: 19 | AB27: Lower tax rates for medical items | AC27: =COUNTIFS(Data!$B:$B,$Y27,Data!$AT:$AT,$AA27,INDIRECT($C$3),$C$2,INDIRECT($F$3),$F$2,INDIRECT($I$2),1,INDIRECT($M$3),$M$2,INDIRECT($I$9),1) -> 8 | AD27: =IF(AC27>0,RANK(AC27,AC$3:AC$55),#N/A) -> 26 | AE27: =ROW(AE27) -> 27 | AF27: =COUNTIF(AD$3:AD27,AD27) -> 3 | AG27: =AC27/$AH$17*100 -> 1.3333333 | AP27: =AB32 -> Broaden tax deductibility | AQ27: =AC32 -> 2
K28: =IF(VLOOKUP($L28,Data!$A$2:$AM$3992,39,FALSE)=1,1+MAX($K$3:K27),0) -> 0 | L28: Botswana | P28: 4 | Q28: Revenue Measures to boost consumption / demand | R28: 20 | S28: Lower tax rates | AP28: =AB33 -> Tax amnesty / incentives | AQ28: =AC33 -> 2
K29: =IF(VLOOKUP($L29,Data!$A$2:$AM$3992,39,FALSE)=1,1+MAX($K$3:K28),0) -> 0 | L29: Brazil | P29: 4 | Q29: Revenue Measures to boost consumption / demand | R29: exemption | S29: Tax exemption/waiver/suspension | Y29: 2 | Z29: Revenue Measures to protect individuals | AA29: Other | AB29: Other | AC29: =COUNTIFS(Data!$B:$B,$Y29,Data!$AT:$AT,$AA29,INDIRECT($C$3),$C$2,INDIRECT($F$3),$F$2,INDIRECT($I$2),1,INDIRECT($M$3),$M$2,INDIRECT($I$9),1) -> 9 | AD29: =IF(AC29>0,RANK(AC29,AC$3:AC$55),#N/A) -> 22 | AE29: =ROW(AE29) -> 29 | AF29: =COUNTIF(AD$3:AD29,AD29) -> 3 | AG29: =AC29/$AH$17*100 -> 1.5 | AP29: =AB34 -> Tax rate reduction | AQ29: =AC34 -> 0
K30: =IF(VLOOKUP($L30,Data!$A$2:$AM$3992,39,FALSE)=1,1+MAX($K$3:K29),0) -> 0 | L30: British Virgin Islands | P30: 4 | Q30: Revenue Measures to boost consumption / demand | R30: other | S30: Other | Y30: 2 | Z30: Revenue Measures to protect individuals | AA30: Tax exemption/waiver/suspension | AB30: Tax exemption/waiver/suspension | AC30: =COUNTIFS(Data!$B:$B,$Y30,Data!$AT:$AT,$AA30,INDIRECT($C$3),$C$2,INDIRECT($F$3),$F$2,INDIRECT($I$2),1,INDIRECT($M$3),$M$2,INDIRECT($I$9),1) -> 6 | AD30: =IF(AC30>0,RANK(AC30,AC$3:AC$55),#N/A) -> 31 | AE30: =ROW(AE30) -> 30 | AF30: =COUNTIF(AD$3:AD30,AD30) -> 1 | AG30: =AC30/$AH$17*100 -> 1 | AP30: =AB35 -> Deferral of tax payments | AQ30: =AC35 -> 13
K31: =IF(VLOOKUP($L31,Data!$A$2:$AM$3992,39,FALSE)=1,1+MAX($K$3:K30),0) -> 0 | L31: Brunei Darussalam | P31: 5 | Q31: Health Expenditures measures | R31: 21 | S31: Supply of low cost medical items | Y31: 2 | Z31: Revenue Measures to protect individuals | AA31: 18 | AB31: Tax credits | AC31: =COUNTIFS(Data!$B:$B,$Y31,Data!$AT:$AT,$AA31,INDIRECT($C$3),$C$2,INDIRECT($F$3),$F$2,INDIRECT($I$2),1,INDIRECT($M$3),$M$2,INDIRECT($I$9),1) -> 0 | AD31: =IF(AC31>0,RANK(AC31,AC$3:AC$55),#N/A) -> #N/A | AE31: =ROW(AE31) -> 31 | AF31: =COUNTIF(AD$3:AD31,AD31) -> 2 | AG31: =AC31/$AH$17*100 -> 0 | AP31: =AB36 -> Deferral of tax filing | AQ31: =AC36 -> 3
K32: =IF(VLOOKUP($L32,Data!$A$2:$AM$3992,39,FALSE)=1,1+MAX($K$3:K31),0) -> 0 | L32: Bulgaria | P32: 5 | Q32: Health Expenditures measures | R32: 22 | S32: Supply of high cost medical items | Y32: 2 | Z32: Revenue Measures to protect individuals | AA32: 17 | AB32: Broaden tax deductibility | AC32: =COUNTIFS(Data!$B:$B,$Y32,Data!$AT:$AT,$AA32,INDIRECT($C$3),$C$2,INDIRECT($F$3),$F$2,INDIRECT($I$2),1,INDIRECT($M$3),$M$2,INDIRECT($I$9),1) -> 2 | AD32: =IF(AC32>0,RANK(AC32,AC$3:AC$55),#N/A) -> 41 | AE32: =ROW(AE32) -> 32 | AF32: =COUNTIF(AD$3:AD32,AD32) -> 1 | AG32: =AC32/$AH$17*100 -> 0.33333333 | AO32: =Z38 -> Revenue Measures to protect businesses | AP32: =AB38 -> Other | AQ32: =AC38 -> 19
K33: =IF(VLOOKUP($L33,Data!$A$2:$AM$3992,39,FALSE)=1,1+MAX($K$3:K32),0) -> 0 | L33: Burkina Faso | P33: 5 | Q33: Health Expenditures measures | R33: 23 | S33: Targeted infrastructure investments | Y33: 2 | Z33: Revenue Measures to protect individuals | AA33: 16 | AB33: Tax amnesty / incentives | AC33: =COUNTIFS(Data!$B:$B,$Y33,Data!$AT:$AT,$AA33,INDIRECT($C$3),$C$2,INDIRECT($F$3),$F$2,INDIRECT($I$2),1,INDIRECT($M$3),$M$2,INDIRECT($I$9),1) -> 2 | AD33: =IF(AC33>0,RANK(AC33,AC$3:AC$55),#N/A) -> 41 | AE33: =ROW(AE33) -> 33 | AF33: =COUNTIF(AD$3:AD33,AD33) -> 2 | AG33: =AC33/$AH$17*100 -> 0.33333333 | AP33: =AB39 -> Tax exemption/waiver/suspension | AQ33: =AC39 -> 25
K34: =IF(VLOOKUP($L34,Data!$A$2:$AM$3992,39,FALSE)=1,1+MAX($K$3:K33),0) -> 0 | L34: Cambodia | P34: 5 | Q34: Health Expenditures measures | R34: 24 | S34: Expansion of human resources | Y34: 2 | Z34: Revenue Measures to protect individuals | AA34: 15 | AB34: Tax rate reduction | AC34: =COUNTIFS(Data!$B:$B,$Y34,Data!$AT:$AT,$AA34,INDIRECT($C$3),$C$2,INDIRECT($F$3),$F$2,INDIRECT($I$2),1,INDIRECT($M$3),$M$2,INDIRECT($I$9),1) -> 0 | AD34: =IF(AC34>0,RANK(AC34,AC$3:AC$55),#N/A) -> #N/A | AE34: =ROW(AE34) -> 34 | AF34: =COUNTIF(AD$3:AD34,AD34) -> 3 | AG34: =AC34/$AH$17*100 -> 0 | AP34: =AB40 -> Suspend audit activities | AQ34: =AC40 -> 6
K35: =IF(VLOOKUP($L35,Data!$A$2:$AM$3992,39,FALSE)=1,1+MAX($K$3:K34),0) -> 0 | L35: Cameroon | P35: 5 | Q35: Health Expenditures measures | R35: general | S35: General | Y35: 2 | Z35: Revenue Measures to protect individuals | AA35: 14 | AB35: Deferral of tax payments | AC35: =COUNTIFS(Data!$B:$B,$Y35,Data!$AT:$AT,$AA35,INDIRECT($C$3),$C$2,INDIRECT($F$3),$F$2,INDIRECT($I$2),1,INDIRECT($M$3),$M$2,INDIRECT($I$9),1) -> 13 | AD35: =IF(AC35>0,RANK(AC35,AC$3:AC$55),#N/A) -> 16 | AE35: =ROW(AE35) -> 35 | AF35: =COUNTIF(AD$3:AD35,AD35) -> 1 | AG35: =AC35/$AH$17*100 -> 2.1666667 | AP35: =AB41 -> Suspend debt collection | AQ35: =AC41 -> 12
K36: =IF(VLOOKUP($L36,Data!$A$2:$AM$3992,39,FALSE)=1,1+MAX($K$3:K35),0) -> 2 | L36: Canada | P36: 6 | Q36: Expenditure Measures for cash transfers to individuals | R36: 25 | S36: Direct cash transfers for individuals | Y36: 2 | Z36: Revenue Measures to protect individuals | AA36: 13 | AB36: Deferral of tax filing | AC36: =COUNTIFS(Data!$B:$B,$Y36,Data!$AT:$AT,$AA36,INDIRECT($C$3),$C$2,INDIRECT($F$3),$F$2,INDIRECT($I$2),1,INDIRECT($M$3),$M$2,INDIRECT($I$9),1) -> 3 | AD36: =IF(AC36>0,RANK(AC36,AC$3:AC$55),#N/A) -> 39 | AE36: =ROW(AE36) -> 36 | AF36: =COUNTIF(AD$3:AD36,AD36) -> 1 | AG36: =AC36/$AH$17*100 -> 0.5 | AP36: =AB42 -> Lower advance payment | AQ36: =AC42 -> 11
K37: =IF(VLOOKUP($L37,Data!$A$2:$AM$3992,39,FALSE)=1,1+MAX($K$3:K36),0) -> 0 | L37: Cape Verde | P37: 6 | Q37: Expenditure Measures for cash transfers to individuals | R37: 26 | S37: Expansion of unemployment benefits | AP37: =AB43 -> Accelerating refunds | AQ37: =AC43 -> 6
K38: =IF(VLOOKUP($L38,Data!$A$2:$AM$3992,39,FALSE)=1,1+MAX($K$3:K37),0) -> 0 | L38: Cayman Islands | P38: 6 | Q38: Expenditure Measures for cash transfers to individuals | R38: 27 | S38: Temporary expansion of existing benefits | Y38: 1 | Z38: Revenue Measures to protect businesses | AA38: Other | AB38: Other | AC38: =COUNTIFS(Data!$B:$B,$Y38,Data!$AT:$AT,$AA38,INDIRECT($C$3),$C$2,INDIRECT($F$3),$F$2,INDIRECT($I$2),1,INDIRECT($M$3),$M$2,INDIRECT($I$9),1) -> 19 | AD38: =IF(AC38>0,RANK(AC38,AC$3:AC$55),#N/A) -> 9 | AE38: =ROW(AE38) -> 38 | AF38: =COUNTIF(AD$3:AD38,AD38) -> 1 | AG38: =AC38/$AH$17*100 -> 3.1666667 | AP38: =AB44 -> Tax amnesty / incentives | AQ38: =AC44 -> 3
K39: =IF(VLOOKUP($L39,Data!$A$2:$AM$3992,39,FALSE)=1,1+MAX($K$3:K38),0) -> 0 | L39: Central African Republic | P39: 6 | Q39: Expenditure Measures for cash transfers to individuals | R39: 28 | S39: Supplementary ad hoc programs | Y39: 1 | Z39: Revenue Measures to protect businesses | AA39: Tax exemption/waiver/suspension | AB39: Tax exemption/waiver/suspension | AC39: =COUNTIFS(Data!$B:$B,$Y39,Data!$AT:$AT,$AA39,INDIRECT($C$3),$C$2,INDIRECT($F$3),$F$2,INDIRECT($I$2),1,INDIRECT($M$3),$M$2,INDIRECT($I$9),1) -> 25 | AD39: =IF(AC39>0,RANK(AC39,AC$3:AC$55),#N/A) -> 6 | AE39: =ROW(AE39) -> 39 | AF39: =COUNTIF(AD$3:AD39,AD39) -> 1 | AG39: =AC39/$AH$17*100 -> 4.1666667 | AP39: =AB45 -> Tax rate reduction | AQ39: =AC45 -> 13
K40: =IF(VLOOKUP($L40,Data!$A$2:$AM$3992,39,FALSE)=1,1+MAX($K$3:K39),0) -> 0 | L40: Chad | P40: 6 | Q40: Expenditure Measures for cash transfers to individuals | R40: 29 | S40: Wage compensation/ enhanced paid leave | Y40: 1 | Z40: Revenue Measures to protect businesses | AA40: 12 | AB40: Suspend audit activities | AC40: =COUNTIFS(Data!$B:$B,$Y40,Data!$AT:$AT,$AA40,INDIRECT($C$3),$C$2,INDIRECT($F$3),$F$2,INDIRECT($I$2),1,INDIRECT($M$3),$M$2,INDIRECT($I$9),1) -> 6 | AD40: =IF(AC40>0,RANK(AC40,AC$3:AC$55),#N/A) -> 31 | AE40: =ROW(AE40) -> 40 | AF40: =COUNTIF(AD$3:AD40,AD40) -> 2 | AG40: =AC40/$AH$17*100 -> 1 | AP40: =AB46 -> Deferral of tax payments | AQ40: =AC46 -> 55
K41: =IF(VLOOKUP($L41,Data!$A$2:$AM$3992,39,FALSE)=1,1+MAX($K$3:K40),0) -> 3 | L41: Chile | P41: 6 | Q41: Expenditure Measures for cash transfers to individuals | R41: other | S41: Other | Y41: 1 | Z41: Revenue Measures to protect businesses | AA41: 11 | AB41: Suspend debt collection | AC41: =COUNTIFS(Data!$B:$B,$Y41,Data!$AT:$AT,$AA41,INDIRECT($C$3),$C$2,INDIRECT($F$3),$F$2,INDIRECT($I$2),1,INDIRECT($M$3),$M$2,INDIRECT($I$9),1) -> 12 | AD41: =IF(AC41>0,RANK(AC41,AC$3:AC$55),#N/A) -> 18 | AE41: =ROW(AE41) -> 41 | AF41: =COUNTIF(AD$3:AD41,AD41) -> 1 | AG41: =AC41/$AH$17*100 -> 2 | AP41: =AB47 -> Deferral of tax filing | AQ41: =AC47 -> 10
K42: =IF(VLOOKUP($L42,Data!$A$2:$AM$3992,39,FALSE)=1,1+MAX($K$3:K41),0) -> 0 | L42: China | P42: 7 | Q42: Credit and equity measures | R42: 30 | S42: Preferential loans to firms | Y42: 1 | Z42: Revenue Measures to protect businesses | AA42: 10 | AB42: Lower advance payment | AC42: =COUNTIFS(Data!$B:$B,$Y42,Data!$AT:$AT,$AA42,INDIRECT($C$3),$C$2,INDIRECT($F$3),$F$2,INDIRECT($I$2),1,INDIRECT($M$3),$M$2,INDIRECT($I$9),1) -> 11 | AD42: =IF(AC42>0,RANK(AC42,AC$3:AC$55),#N/A) -> 19 | AE42: =ROW(AE42) -> 42 | AF42: =COUNTIF(AD$3:AD42,AD42) -> 2 | AG42: =AC42/$AH$17*100 -> 1.8333333 | AP42: =AB48 -> Tax credits | AQ42: =AC48 -> 14
K43: =IF(VLOOKUP($L43,Data!$A$2:$AM$3992,39,FALSE)=1,1+MAX($K$3:K42),0) -> 4 | L43: Colombia | P43: 7 | Q43: Credit and equity measures | R43: 31 | S43: One-off grants | Y43: 1 | Z43: Revenue Measures to protect businesses | AA43: 9 | AB43: Accelerating refunds | AC43: =COUNTIFS(Data!$B:$B,$Y43,Data!$AT:$AT,$AA43,INDIRECT($C$3),$C$2,INDIRECT($F$3),$F$2,INDIRECT($I$2),1,INDIRECT($M$3),$M$2,INDIRECT($I$9),1) -> 6 | AD43: =IF(AC43>0,RANK(AC43,AC$3:AC$55),#N/A) -> 31 | AE43: =ROW(AE43) -> 43 | AF43: =COUNTIF(AD$3:AD43,AD43) -> 3 | AG43: =AC43/$AH$17*100 -> 1 | AP43: =AB49 -> Broaden tax deductibility | AQ43: =AC49 -> 9
K44: =IF(VLOOKUP($L44,Data!$A$2:$AM$3992,39,FALSE)=1,1+MAX($K$3:K43),0) -> 0 | L44: Comoros | P44: 7 | Q44: Credit and equity measures | R44: 32 | S44: Preferential loans to households | Y44: 1 | Z44: Revenue Measures to protect businesses | AA44: 8 | AB44: Tax amnesty / incentives | AC44: =COUNTIFS(Data!$B:$B,$Y44,Data!$AT:$AT,$AA44,INDIRECT($C$3),$C$2,INDIRECT($F$3),$F$2,INDIRECT($I$2),1,INDIRECT($M$3),$M$2,INDIRECT($I$9),1) -> 3 | AD44: =IF(AC44>0,RANK(AC44,AC$3:AC$55),#N/A) -> 39 | AE44: =ROW(AE44) -> 44 | AF44: =COUNTIF(AD$3:AD44,AD44) -> 2 | AG44: =AC44/$AH$17*100 -> 0.5 | AP44: =AB50 -> Extend loss carry-forward (CIT) | AQ44: =AC50 -> 7
K45: =IF(VLOOKUP($L45,Data!$A$2:$AM$3992,39,FALSE)=1,1+MAX($K$3:K44),0) -> 0 | L45: Congo, Democratic Republic of the | P45: 7 | Q45: Credit and equity measures | R45: other | S45: Other | Y45: 1 | Z45: Revenue Measures to protect businesses | AA45: 7 | AB45: Tax rate reduction | AC45: =COUNTIFS(Data!$B:$B,$Y45,Data!$AT:$AT,$AA45,INDIRECT($C$3),$C$2,INDIRECT($F$3),$F$2,INDIRECT($I$2),1,INDIRECT($M$3),$M$2,INDIRECT($I$9),1) -> 13 | AD45: =IF(AC45>0,RANK(AC45,AC$3:AC$55),#N/A) -> 16 | AE45: =ROW(AE45) -> 45 | AF45: =COUNTIF(AD$3:AD45,AD45) -> 2 | AG45: =AC45/$AH$17*100 -> 2.1666667 | AP45: =AB51 -> Accelerated asset depreciation (CIT) | AQ45: =AC51 -> 5
K46: =IF(VLOOKUP($L46,Data!$A$2:$AM$3992,39,FALSE)=1,1+MAX($K$3:K45),0) -> 0 | L46: Congo, Republic of the | P46: 8 | Q46: Revenue Measures to raise revenue | R46: 33 | S46: Revenue increase | Y46: 1 | Z46: Revenue Measures to protect businesses | AA46: 6 | AB46: Deferral of tax payments | AC46: =COUNTIFS(Data!$B:$B,$Y46,Data!$AT:$AT,$AA46,INDIRECT($C$3),$C$2,INDIRECT($F$3),$F$2,INDIRECT($I$2),1,INDIRECT($M$3),$M$2,INDIRECT($I$9),1) -> 55 | AD46: =IF(AC46>0,RANK(AC46,AC$3:AC$55),#N/A) -> 1 | AE46: =ROW(AE46) -> 46 | AF46: =COUNTIF(AD$3:AD46,AD46) -> 1 | AG46: =AC46/$AH$17*100 -> 9.1666667
K47: =IF(VLOOKUP($L47,Data!$A$2:$AM$3992,39,FALSE)=1,1+MAX($K$3:K46),0) -> 0 | L47: Cook Islands | P47: 9 | Q47: Expenditure Measures for businesses | R47: 34 | S47: Income support | Y47: 1 | Z47: Revenue Measures to protect businesses | AA47: 5 | AB47: Deferral of tax filing | AC47: =COUNTIFS(Data!$B:$B,$Y47,Data!$AT:$AT,$AA47,INDIRECT($C$3),$C$2,INDIRECT($F$3),$F$2,INDIRECT($I$2),1,INDIRECT($M$3),$M$2,INDIRECT($I$9),1) -> 10 | AD47: =IF(AC47>0,RANK(AC47,AC$3:AC$55),#N/A) -> 21 | AE47: =ROW(AE47) -> 47 | AF47: =COUNTIF(AD$3:AD47,AD47) -> 1 | AG47: =AC47/$AH$17*100 -> 1.6666667
K48: =IF(VLOOKUP($L48,Data!$A$2:$AM$3992,39,FALSE)=1,1+MAX($K$3:K47),0) -> 5 | L48: Costa Rica | Y48: 1 | Z48: Revenue Measures to protect businesses | AA48: 4 | AB48: Tax credits | AC48: =COUNTIFS(Data!$B:$B,$Y48,Data!$AT:$AT,$AA48,INDIRECT($C$3),$C$2,INDIRECT($F$3),$F$2,INDIRECT($I$2),1,INDIRECT($M$3),$M$2,INDIRECT($I$9),1) -> 14 | AD48: =IF(AC48>0,RANK(AC48,AC$3:AC$55),#N/A) -> 14 | AE48: =ROW(AE48) -> 48 | AF48: =COUNTIF(AD$3:AD48,AD48) -> 2 | AG48: =AC48/$AH$17*100 -> 2.3333333
K49: =IF(VLOOKUP($L49,Data!$A$2:$AM$3992,39,FALSE)=1,1+MAX($K$3:K48),0) -> 0 | L49: Cote d'Ivoire | Y49: 1 | Z49: Revenue Measures to protect businesses | AA49: 3 | AB49: Broaden tax deductibility | AC49: =COUNTIFS(Data!$B:$B,$Y49,Data!$AT:$AT,$AA49,INDIRECT($C$3),$C$2,INDIRECT($F$3),$F$2,INDIRECT($I$2),1,INDIRECT($M$3),$M$2,INDIRECT($I$9),1) -> 9 | AD49: =IF(AC49>0,RANK(AC49,AC$3:AC$55),#N/A) -> 22 | AE49: =ROW(AE49) -> 49 | AF49: =COUNTIF(AD$3:AD49,AD49) -> 4 | AG49: =AC49/$AH$17*100 -> 1.5
K50: =IF(VLOOKUP($L50,Data!$A$2:$AM$3992,39,FALSE)=1,1+MAX($K$3:K49),0) -> 0 | L50: Croatia | Y50: 1 | Z50: Revenue Measures to protect businesses | AA50: 2 | AB50: Extend loss carry-forward (CIT) | AC50: =COUNTIFS(Data!$B:$B,$Y50,Data!$AT:$AT,$AA50,INDIRECT($C$3),$C$2,INDIRECT($F$3),$F$2,INDIRECT($I$2),1,INDIRECT($M$3),$M$2,INDIRECT($I$9),1) -> 7 | AD50: =IF(AC50>0,RANK(AC50,AC$3:AC$55),#N/A) -> 29 | AE50: =ROW(AE50) -> 50 | AF50: =COUNTIF(AD$3:AD50,AD50) -> 2 | AG50: =AC50/$AH$17*100 -> 1.1666667
K51: =IF(VLOOKUP($L51,Data!$A$2:$AM$3992,39,FALSE)=1,1+MAX($K$3:K50),0) -> 0 | L51: Cyprus | P51: Policy category | Y51: 1 | Z51: Revenue Measures to protect businesses | AA51: 1 | AB51: Accelerated asset depreciation (CIT) | AC51: =COUNTIFS(Data!$B:$B,$Y51,Data!$AT:$AT,$AA51,INDIRECT($C$3),$C$2,INDIRECT($F$3),$F$2,INDIRECT($I$2),1,INDIRECT($M$3),$M$2,INDIRECT($I$9),1) -> 5 | AD51: =IF(AC51>0,RANK(AC51,AC$3:AC$55),#N/A) -> 34 | AE51: =ROW(AE51) -> 51 | AF51: =COUNTIF(AD$3:AD51,AD51) -> 2 | AG51: =AC51/$AH$17*100 -> 0.83333333
K52: =IF(VLOOKUP($L52,Data!$A$2:$AM$3992,39,FALSE)=1,1+MAX($K$3:K51),0) -> 0 | L52: Czechia | P52: other | Q52: =COUNTIFS(Data!$AL:$AL,1,INDIRECT($C$3),$C$2,INDIRECT($F$3),$F$2,INDIRECT($I$2),1,INDIRECT($M$3),$M$2,INDIRECT($I$9),1) -> 16 | R52: Other measures
K53: =IF(VLOOKUP($L53,Data!$A$2:$AM$3992,39,FALSE)=1,1+MAX($K$3:K52),0) -> 0 | L53: Denmark | P53: 7 | Q53: =COUNTIFS(Data!$B:$B,$P53,INDIRECT($C$3),$C$2,INDIRECT($F$3),$F$2,INDIRECT($I$2),1,INDIRECT($M$3),$M$2,INDIRECT($I$9),1) -> 82 | R53: =VLOOKUP(P53,$P$3:$Q$47,2,FALSE) -> Credit and equity measures | Z53: Expenditure Measures for businesses | AC53: =Q54 -> 18 | AD53: =IF(AC53>0,RANK(AC53,AC$3:AC$55),#N/A) -> 10 | AE53: =ROW(AE53) -> 53 | AF53: =COUNTIF(AD$3:AD53,AD53) -> 2 | AG53: =AC53/$AH$17*100 -> 3
K54: =IF(VLOOKUP($L54,Data!$A$2:$AM$3992,39,FALSE)=1,1+MAX($K$3:K53),0) -> 0 | L54: Dominica | P54: 9 | Q54: =COUNTIFS(Data!$B:$B,$P54,INDIRECT($C$3),$C$2,INDIRECT($F$3),$F$2,INDIRECT($I$2),1,INDIRECT($M$3),$M$2,INDIRECT($I$9),1) -> 18 | R54: =VLOOKUP(P54,$P$3:$Q$47,2,FALSE) -> Expenditure Measures for businesses | Z54: Other measures | AC54: =Q52 -> 16 | AD54: =IF(AC54>0,RANK(AC54,AC$3:AC$55),#N/A) -> 12 | AE54: =ROW(AE54) -> 54 | AF54: =COUNTIF(AD$3:AD54,AD54) -> 1 | AG54: =AC54/$AH$17*100 -> 2.6666667
K55: =IF(VLOOKUP($L55,Data!$A$2:$AM$3992,39,FALSE)=1,1+MAX($K$3:K54),0) -> 0 | L55: Dominican Republic | P55: 6 | Q55: =COUNTIFS(Data!$B:$B,$P55,INDIRECT($C$3),$C$2,INDIRECT($F$3),$F$2,INDIRECT($I$2),1,INDIRECT($M$3),$M$2,INDIRECT($I$9),1) -> 150 | R55: =VLOOKUP(P55,$P$3:$Q$47,2,FALSE) -> Expenditure Measures for cash transfers to individuals | Z55: Revenue Measures to raise revenue | AC55: =Q57 -> 4 | AD55: =IF(AC55>0,RANK(AC55,AC$3:AC$55),#N/A) -> 36 | AE55: =ROW(AE55) -> 55 | AF55: =COUNTIF(AD$3:AD55,AD55) -> 3 | AG55: =AC55/$AH$17*100 -> 0.66666667
K56: =IF(VLOOKUP($L56,Data!$A$2:$AM$3992,39,FALSE)=1,1+MAX($K$3:K55),0) -> 0 | L56: Ecuador | P56: 5 | Q56: =COUNTIFS(Data!$B:$B,$P56,INDIRECT($C$3),$C$2,INDIRECT($F$3),$F$2,INDIRECT($I$2),1,INDIRECT($M$3),$M$2,INDIRECT($I$9),1) -> 44 | R56: =VLOOKUP(P56,$P$3:$Q$47,2,FALSE) -> Health Expenditures measures
K57: =IF(VLOOKUP($L57,Data!$A$2:$AM$3992,39,FALSE)=1,1+MAX($K$3:K56),0) -> 0 | L57: Egypt | P57: 8 | Q57: =COUNTIFS(Data!$B:$B,$P57,INDIRECT($C$3),$C$2,INDIRECT($F$3),$F$2,INDIRECT($I$2),1,INDIRECT($M$3),$M$2,INDIRECT($I$9),1) -> 4 | R57: =VLOOKUP(P57,$P$3:$Q$47,2,FALSE) -> Revenue Measures to raise revenue
K58: =IF(VLOOKUP($L58,Data!$A$2:$AM$3992,39,FALSE)=1,1+MAX($K$3:K57),0) -> 0 | L58: El Salvador | P58: 4 | Q58: =COUNTIFS(Data!$B:$B,$P58,INDIRECT($C$3),$C$2,INDIRECT($F$3),$F$2,INDIRECT($I$2),1,INDIRECT($M$3),$M$2,INDIRECT($I$9),1) -> 28 | R58: =VLOOKUP(P58,$P$3:$Q$47,2,FALSE) -> Revenue Measures to boost consumption / demand | Z58: nth of rank
K59: =IF(VLOOKUP($L59,Data!$A$2:$AM$3992,39,FALSE)=1,1+MAX($K$3:K58),0) -> 0 | L59: Equatorial Guinea | P59: 3 | Q59: =COUNTIFS(Data!$B:$B,$P59,INDIRECT($C$3),$C$2,INDIRECT($F$3),$F$2,INDIRECT($I$2),1,INDIRECT($M$3),$M$2,INDIRECT($I$9),1) -> 26 | R59: =VLOOKUP(P59,$P$3:$Q$47,2,FALSE) -> Revenue Measures to promote availability of medical items | Z59: =COUNTIF($AA$59:$AA59,$AA59) -> 1 | AA59: 1 | AB59: =SUMIFS(AE:AE,AD:AD,AA59,AF:AF,Z59) -> 46 | AC59: =_xlfn.CONCAT(INDIRECT(_xlfn.CONCAT("Z",AB59)),": ",INDIRECT(_xlfn.CONCAT("AB",AB59))," (n=",INDIRECT(_xlfn.CONCAT("AC",AB59)),", ",TEXT(INDIRECT(_xlfn.CONCAT("AG",AB59)),"#,###"),"% of total)") -> Revenue Measures to protect businesses: Deferral of tax payments (n=55, ,9% of total)
K60: =IF(VLOOKUP($L60,Data!$A$2:$AM$3992,39,FALSE)=1,1+MAX($K$3:K59),0) -> 0 | L60: Estonia | P60: 2 | Q60: =COUNTIFS(Data!$B:$B,$P60,INDIRECT($C$3),$C$2,INDIRECT($F$3),$F$2,INDIRECT($I$2),1,INDIRECT($M$3),$M$2,INDIRECT($I$9),1) -> 35 | R60: =VLOOKUP(P60,$P$3:$Q$47,2,FALSE) -> Revenue Measures to protect individuals | Z60: =COUNTIF($AA$59:$AA60,$AA60) -> 1 | AA60: =IF(SUM(Z65:Z69)=1,"-",IF(Z65>1,1,2)) -> 2 | AB60: =SUMIFS(AE:AE,AD:AD,AA60,AF:AF,Z60) -> 6 | AC60: =IFERROR(_xlfn.CONCAT(INDIRECT(_xlfn.CONCAT("Z",AB60)),": ",INDIRECT(_xlfn.CONCAT("AB",AB60))," (n=",INDIRECT(_xlfn.CONCAT("AC",AB60)),", ",TEXT(INDIRECT(_xlfn.CONCAT("AG",AB60)),"#,###"),"% of total)"),"No further policies") -> Credit and equity measures: Preferential loans to firms (n=54, ,9% of total)
K61: =IF(VLOOKUP($L61,Data!$A$2:$AM$3992,39,FALSE)=1,1+MAX($K$3:K60),0) -> 0 | L61: Eswatini | P61: 1 | Q61: =COUNTIFS(Data!$B:$B,$P61,INDIRECT($C$3),$C$2,INDIRECT($F$3),$F$2,INDIRECT($I$2),1,INDIRECT($M$3),$M$2,INDIRECT($I$9),1) -> 197 | R61: =VLOOKUP(P61,$P$3:$Q$47,2,FALSE) -> Revenue Measures to protect businesses | Z61: =COUNTIF($AA$59:$AA61,$AA61) -> 1 | AA61: =IF(SUM(Z65:Z69)<3,"-",IF(Z65>2,1,IF(Z66>1,2,3))) -> 3 | AB61: =SUMIFS(AE:AE,AD:AD,AA61,AF:AF,Z61) -> 9 | AC61: =IFERROR(_xlfn.CONCAT(INDIRECT(_xlfn.CONCAT("Z",AB61)),": ",INDIRECT(_xlfn.CONCAT("AB",AB61))," (n=",INDIRECT(_xlfn.CONCAT("AC",AB61)),", ",TEXT(INDIRECT(_xlfn.CONCAT("AG",AB61)),"#,###"),"% of total)"),"No further policies") -> Expenditure Measures for cash transfers to individuals: Wage compensation/ enhanced paid leave (n=38, ,6% of total)
K62: =IF(VLOOKUP($L62,Data!$A$2:$AM$3992,39,FALSE)=1,1+MAX($K$3:K61),0) -> 0 | L62: Ethiopia | Z62: =COUNTIF($AA$59:$AA62,$AA62) -> 1 | AA62: =IF(SUM(Z65:Z69)<4,"-",IF(Z65>3,1,IF(Z66>2,2,IF(Z67>1,3,4)))) -> 4 | AB62: =SUMIFS(AE:AE,AD:AD,AA62,AF:AF,Z62) -> 10 | AC62: =IFERROR(_xlfn.CONCAT(INDIRECT(_xlfn.CONCAT("Z",AB62)),": ",INDIRECT(_xlfn.CONCAT("AB",AB62))," (n=",INDIRECT(_xlfn.CONCAT("AC",AB62)),", ",TEXT(INDIRECT(_xlfn.CONCAT("AG",AB62)),"#,###"),"% of total)"),"No further policies") -> Expenditure Measures for cash transfers to individuals: Supplementary ad hoc programs (n=33, ,6% of total)
K63: =IF(VLOOKUP($L63,Data!$A$2:$AM$3992,39,FALSE)=1,1+MAX($K$3:K62),0) -> 0 | L63: European Union | Z63: =COUNTIF($AA$59:$AA63,$AA63) -> 1 | AA63: =IF(SUM(Z65:Z69)<5,"-",IF(Z65>4,1,IF(Z66>3,2,IF(Z67>2,3,IF(Z68>1,4,5))))) -> 5 | AB63: =SUMIFS(AE:AE,AD:AD,AA63,AF:AF,Z63) -> 13 | AC63: =IFERROR(_xlfn.CONCAT(INDIRECT(_xlfn.CONCAT("Z",AB63)),": ",INDIRECT(_xlfn.CONCAT("AB",AB63))," (n=",INDIRECT(_xlfn.CONCAT("AC",AB63)),", ",TEXT(INDIRECT(_xlfn.CONCAT("AG",AB63)),"#,###"),"% of total)"),"No further policies") -> Expenditure Measures for cash transfers to individuals: Direct cash transfers for individuals (n=29, ,5% of total)
K64: =IF(VLOOKUP($L64,Data!$A$2:$AM$3992,39,FALSE)=1,1+MAX($K$3:K63),0) -> 0 | L64: Fiji
K65: =IF(VLOOKUP($L65,Data!$A$2:$AM$3992,39,FALSE)=1,1+MAX($K$3:K64),0) -> 0 | L65: Finland | Y65: 1s | Z65: =COUNTIF($AD$3:$AD$55,1) -> 1 | AB65: =0.1114*100 -> 11.14
K66: =IF(VLOOKUP($L66,Data!$A$2:$AM$3992,39,FALSE)=1,1+MAX($K$3:K65),0) -> 0 | L66: France | Y66: 2s | Z66: =COUNTIF($AD$3:$AD$55,2) -> 1 | AB66: =TEXT(AB65, "#,###") -> 11
K67: =IF(VLOOKUP($L67,Data!$A$2:$AM$3992,39,FALSE)=1,1+MAX($K$3:K66),0) -> 0 | L67: Gabon | Y67: 3s | Z67: =COUNTIF($AD$3:$AD$55,3) -> 1
K68: =IF(VLOOKUP($L68,Data!$A$2:$AM$3992,39,FALSE)=1,1+MAX($K$3:K67),0) -> 0 | L68: Gambia, The | Y68: 4s | Z68: =COUNTIF($AD$3:$AD$55,4) -> 1
K69: =IF(VLOOKUP($L69,Data!$A$2:$AM$3992,39,FALSE)=1,1+MAX($K$3:K68),0) -> 0 | L69: Georgia | Y69: 5s | Z69: =COUNTIF($AD$3:$AD$55,5) -> 1
K70: =IF(VLOOKUP($L70,Data!$A$2:$AM$3992,39,FALSE)=1,1+MAX($K$3:K69),0) -> 6 | L70: Germany
K71: =IF(VLOOKUP($L71,Data!$A$2:$AM$3992,39,FALSE)=1,1+MAX($K$3:K70),0) -> 0 | L71: Ghana
K72: =IF(VLOOKUP($L72,Data!$A$2:$AM$3992,39,FALSE)=1,1+MAX($K$3:K71),0) -> 7 | L72: Greece
K73: =IF(VLOOKUP($L73,Data!$A$2:$AM$3992,39,FALSE)=1,1+MAX($K$3:K72),0) -> 0 | L73: Grenada
K74: =IF(VLOOKUP($L74,Data!$A$2:$AM$3992,39,FALSE)=1,1+MAX($K$3:K73),0) -> 0 | L74: Guatemala
K75: =IF(VLOOKUP($L75,Data!$A$2:$AM$3992,39,FALSE)=1,1+MAX($K$3:K74),0) -> 0 | L75: Guernsey
K76: =IF(VLOOKUP($L76,Data!$A$2:$AM$3992,39,FALSE)=1,1+MAX($K$3:K75),0) -> 0 | L76: Guinea
K77: =IF(VLOOKUP($L77,Data!$A$2:$AM$3992,39,FALSE)=1,1+MAX($K$3:K76),0) -> 0 | L77: Guinea-Bissau
K78: =IF(VLOOKUP($L78,Data!$A$2:$AM$3992,39,FALSE)=1,1+MAX($K$3:K77),0) -> 0 | L78: Guyana
K79: =IF(VLOOKUP($L79,Data!$A$2:$AM$3992,39,FALSE)=1,1+MAX($K$3:K78),0) -> 0 | L79: Haiti
K80: =IF(VLOOKUP($L80,Data!$A$2:$AM$3992,39,FALSE)=1,1+MAX($K$3:K79),0) -> 0 | L80: Honduras
K81: =IF(VLOOKUP($L81,Data!$A$2:$AM$3992,39,FALSE)=1,1+MAX($K$3:K80),0) -> 0 | L81: Hong Kong, China
