Workbook
Name FCV_added: OFFSET('Policy select backend'!$O$52,,,2+'Policy select backend'!$B$52)
Name FCV_Scores: OFFSET('Performance across backend'!$H$39,,,2+'Performance across backend'!$P$3)
Name Income_added: OFFSET('Policy select backend'!$O$37,,,4+'Policy select backend'!$B$52)
Name Income_scores: OFFSET('Performance across backend'!$H$24,,,4+'Performance across backend'!$P$3)
Name Lending_added: OFFSET('Policy select backend'!$O$31,,,3+'Policy select backend'!$B$52)
Name Lending_scores: OFFSET('Performance across backend'!$H$18,,,3+'Performance across backend'!$P$3)
Name Regions_added: OFFSET('Policy select backend'!$O$43,,,7+'Policy select backend'!$B$52)
Name Regions_scores: OFFSET('Performance across backend'!$H$30,,,7+'Performance across backend'!$P$3)

Sheet Data
A1: Treatment | B1: Country | C1: First Case | D1: First Lockdown start | E1: First Lockdown end | F1: Duration | G1: First Fiscal | H1: Jahr implementiert | I1: Treatment | J1: PolicyCategory | K1: PolicyCode | L1: Fullpolicy | M1: Targetability | N1: Speed | O1: Abuse_Resistance | P1: Affordability | Q1: Predictability_Cost_Control | R1: Reversibility | S1: Scalability | T1: Administrative_Complexity | U1: Resilience_Health_Measures | V1: Country_Code | W1: Reg | X1: Lendingcategory | Y1: Incomelevel | Z1: FCV | AA1: Targetability (converted) | AB1: Speed (converted) | AC1: Abuse_Resistance (converted) | AD1: Affordability (converted) | AE1: Predictability_Cost_Control (converted) | AF1: Reversibility (converted) | AG1: Scalability (converted) | AH1: Administrative_Complexity (converted) | AI1: Resilience_Health_Measures (converted) | AJ1: Subcategory (clean) | AK1: First of country row (requires sorting alphabetically by country) | AL1: May 1st sample
A2: 1 | B2: Australia | C2: 43855 | D2: 43919 | E2: 43951 | F2: =DATEDIF(D2,E2,"D") -> 32 | G2: 43919 | H2: 2020 | I2: 1 | J2: 6 | K2: 27 | L2: One-off payment of A$750 to social security, veteran and other income support recipients and eligible concession card holders. | M2: 1 | N2: 1 | O2: 1 | P2: -1 | Q2: 1 | R2: 1 | S2: 1 | T2: 1 | U2: 1 | V2: AUS | W2: East Asia & Pacific | X2: None | Y2: High Income | Z2: 1 | AA2: =IF(M2>0,1,IF(M2<0,0,-1)) -> 1 | AB2: =IF(N2>0,1,IF(N2<0,0,-1)) -> 1 | AC2: =IF(O2>0,1,IF(O2<0,0,-1)) -> 1 | AD2: =IF(P2>0,1,IF(P2<0,0,-1)) -> 0 | AE2: =IF(Q2>0,1,IF(Q2<0,0,-1)) -> 1 | AF2: =IF(R2>0,1,IF(R2<0,0,-1)) -> 1 | AG2: =IF(S2>0,1,IF(S2<0,0,-1)) -> 1 | AH2: =IF(T2>0,1,IF(T2<0,0,-1)) -> 1 | AI2: =IF(U2>0,1,IF(U2<0,0,-1)) -> 1 | AJ2: =IF(ISNUMBER(K2),K2,IF(OR(K2="general",K2="23;general"),"General",IF(OR(K2="exemption",K2="other (exemption)"),"Tax exemption/waiver/suspension","Other"))) -> 27 | AK2: =IF(B2<>#REF!,1,0) -> #REF! | AL2: 1
A3: 1 | B3: Australia | C3: 43855 | D3: 43919 | E3: 43951 | F3: =DATEDIF(D3,E3,"D") -> 32 | G3: 43919 | H3: 2020 | I3: 1 | J3: 1 | K3: 9 | L3: Accelerating refunds: ATO will allow businesses on a quarterly reporting cycle to opt into monthly GST reporting in order to get quicker access to GST refunds they may be entitled to. | M3: -2 | N3: 1 | O3: 2 | P3: 1 | Q3: 2 | R3: -2 | S3: -2 | T3: 2 | U3: 1 | V3: AUS | W3: East Asia & Pacific | X3: None | Y3: High Income | Z3: 1 | AA3: =IF(M3>0,1,IF(M3<0,0,-1)) -> 0 | AB3: =IF(N3>0,1,IF(N3<0,0,-1)) -> 1 | AC3: =IF(O3>0,1,IF(O3<0,0,-1)) -> 1 | AD3: =IF(P3>0,1,IF(P3<0,0,-1)) -> 1 | AE3: =IF(Q3>0,1,IF(Q3<0,0,-1)) -> 1 | AF3: =IF(R3>0,1,IF(R3<0,0,-1)) -> 0 | AG3: =IF(S3>0,1,IF(S3<0,0,-1)) -> 0 | AH3: =IF(T3>0,1,IF(T3<0,0,-1)) -> 1 | AI3: =IF(U3>0,1,IF(U3<0,0,-1)) -> 1 | AJ3: =IF(ISNUMBER(K3),K3,IF(OR(K3="general",K3="23;general"),"General",IF(OR(K3="exemption",K3="other (exemption)"),"Tax exemption/waiver/suspension","Other"))) -> 9 | AK3: =IF(B3<>B2,1,0) -> 0 | AL3: 1
A4: 1 | B4: Australia | C4: 43855 | D4: 43919 | E4: 43951 | F4: =DATEDIF(D4,E4,"D") -> 32 | G4: 43919 | H4: 2020 | I4: 1 | J4: 6 | K4: 27 | L4: Changes to pension deeming rate (cut of lower deeming rate, top rate). Individuals affected by the COVID-19 can access up to A$10,000 of their superannuation in 2019-2020 and a further USD 10,000 in 2020-21. | M4: 1 | N4: 1 | R4: -2 | S4: 1 | T4: 2 | U4: 1 | V4: AUS | W4: East Asia & Pacific | X4: None | Y4: High Income | Z4: 1 | AA4: =IF(M4>0,1,IF(M4<0,0,-1)) -> 1 | AB4: =IF(N4>0,1,IF(N4<0,0,-1)) -> 1 | AC4: =IF(O4>0,1,IF(O4<0,0,-1)) -> -1 | AD4: =IF(P4>0,1,IF(P4<0,0,-1)) -> -1 | AE4: =IF(Q4>0,1,IF(Q4<0,0,-1)) -> -1 | AF4: =IF(R4>0,1,IF(R4<0,0,-1)) -> 0 | AG4: =IF(S4>0,1,IF(S4<0,0,-1)) -> 1 | AH4: =IF(T4>0,1,IF(T4<0,0,-1)) -> 1 | AI4: =IF(U4>0,1,IF(U4<0,0,-1)) -> 1 | AJ4: =IF(ISNUMBER(K4),K4,IF(OR(K4="general",K4="23;general"),"General",IF(OR(K4="exemption",K4="other (exemption)"),"Tax exemption/waiver/suspension","Other"))) -> 27 | AK4: =IF(B4<>B3,1,0) -> 0 | AL4: 1
A5: 1 | B5: Australia | C5: 43855 | D5: 43919 | E5: 43951 | F5: =DATEDIF(D5,E5,"D") -> 32 | G5: 43919 | H5: 2020 | I5: 1 | J5: 6 | K5: 25 | L5: One-off emergency relief payment of USD 250 for individuals and up to USD 1,000 for families who are required to self- quarantine. This will be available to informal casual workers and those on low incomes. | M5: 1 | N5: 1 | O5: -2 | P5: -1 | Q5: 2 | R5: 1 | S5: 1 | T5: -2 | U5: 1 | V5: AUS | W5: East Asia & Pacific | X5: None | Y5: High Income | Z5: 1 | AA5: =IF(M5>0,1,IF(M5<0,0,-1)) -> 1 | AB5: =IF(N5>0,1,IF(N5<0,0,-1)) -> 1 | AC5: =IF(O5>0,1,IF(O5<0,0,-1)) -> 0 | AD5: =IF(P5>0,1,IF(P5<0,0,-1)) -> 0 | AE5: =IF(Q5>0,1,IF(Q5<0,0,-1)) -> 1 | AF5: =IF(R5>0,1,IF(R5<0,0,-1)) -> 1 | AG5: =IF(S5>0,1,IF(S5<0,0,-1)) -> 1 | AH5: =IF(T5>0,1,IF(T5<0,0,-1)) -> 0 | AI5: =IF(U5>0,1,IF(U5<0,0,-1)) -> 1 | AJ5: =IF(ISNUMBER(K5),K5,IF(OR(K5="general",K5="23;general"),"General",IF(OR(K5="exemption",K5="other (exemption)"),"Tax exemption/waiver/suspension","Other"))) -> 25 | AK5: =IF(B5<>B4,1,0) -> 0 | AL5: 1
A6: 1 | B6: Australia | C6: 43855 | D6: 43919 | E6: 43951 | F6: =DATEDIF(D6,E6,"D") -> 32 | G6: 43919 | H6: 2020 | I6: 1 | J6: 7 | K6: 30 | L6: COVID-19 SME Guarantee Scheme which will support small and medium enterprises (SMEs) to get access to working capital to help them get them through the impact of the COVID-19. Under the Scheme, the Government will guarantee 50 per cent of new loans issued by eligible lenders to SMEs. | M6: 2 | N6: 1 | O6: 1 | P6: 1 | Q6: 2 | R6: 2 | S6: 1 | T6: -1 | U6: 1 | V6: AUS | W6: East Asia & Pacific | X6: None | Y6: High Income | Z6: 1 | AA6: =IF(M6>0,1,IF(M6<0,0,-1)) -> 1 | AB6: =IF(N6>0,1,IF(N6<0,0,-1)) -> 1 | AC6: =IF(O6>0,1,IF(O6<0,0,-1)) -> 1 | AD6: =IF(P6>0,1,IF(P6<0,0,-1)) -> 1 | AE6: =IF(Q6>0,1,IF(Q6<0,0,-1)) -> 1 | AF6: =IF(R6>0,1,IF(R6<0,0,-1)) -> 1 | AG6: =IF(S6>0,1,IF(S6<0,0,-1)) -> 1 | AH6: =IF(T6>0,1,IF(T6<0,0,-1)) -> 0 | AI6: =IF(U6>0,1,IF(U6<0,0,-1)) -> 1 | AJ6: =IF(ISNUMBER(K6),K6,IF(OR(K6="general",K6="23;general"),"General",IF(OR(K6="exemption",K6="other (exemption)"),"Tax exemption/waiver/suspension","Other"))) -> 30 | AK6: =IF(B6<>B5,1,0) -> 0 | AL6: 1
A7: 1 | B7: Australia | C7: 43855 | D7: 43919 | E7: 43951 | F7: =DATEDIF(D7,E7,"D") -> 32 | G7: 43919 | H7: 2020 | I7: 1 | J7: 5 | K7: 23 | L7: Commitment to spend A$2.4 billion to strengthen the health system and protect vulnerable people from the outbreak of COVID-19. | M7: 1 | N7: -1 | O7: -2 | P7: -1 | Q7: -2 | R7: 1 | S7: 1 | T7: 1 | U7: 1 | V7: AUS | W7: East Asia & Pacific | X7: None | Y7: High Income | Z7: 1 | AA7: =IF(M7>0,1,IF(M7<0,0,-1)) -> 1 | AB7: =IF(N7>0,1,IF(N7<0,0,-1)) -> 0 | AC7: =IF(O7>0,1,IF(O7<0,0,-1)) -> 0 | AD7: =IF(P7>0,1,IF(P7<0,0,-1)) -> 0 | AE7: =IF(Q7>0,1,IF(Q7<0,0,-1)) -> 0 | AF7: =IF(R7>0,1,IF(R7<0,0,-1)) -> 1 | AG7: =IF(S7>0,1,IF(S7<0,0,-1)) -> 1 | AH7: =IF(T7>0,1,IF(T7<0,0,-1)) -> 1 | AI7: =IF(U7>0,1,IF(U7<0,0,-1)) -> 1 | AJ7: =IF(ISNUMBER(K7),K7,IF(OR(K7="general",K7="23;general"),"General",IF(OR(K7="exemption",K7="other (exemption)"),"Tax exemption/waiver/suspension","Other"))) -> 23 | AK7: =IF(B7<>B6,1,0) -> 0 | AL7: 1
A8: 1 | B8: Australia | C8: 43855 | D8: 43919 | E8: 43951 | F8: =DATEDIF(D8,E8,"D") -> 32 | G8: 43919 | H8: 2020 | I8: 1 | J8: 2 | K8: 17 | L8: From 1 March 2020 to 30 June 2020, taxpayers are allowed to claim AUD 0.80 for each hour working from home for all their running expenses | M8: -2 | O8: -2 | P8: -1 | Q8: 2 | R8: 2 | S8: 1 | T8: -2 | U8: 1 | V8: AUS | W8: East Asia & Pacific | X8: None | Y8: High Income | Z8: 1 | AA8: =IF(M8>0,1,IF(M8<0,0,-1)) -> 0 | AB8: =IF(N8>0,1,IF(N8<0,0,-1)) -> -1 | AC8: =IF(O8>0,1,IF(O8<0,0,-1)) -> 0 | AD8: =IF(P8>0,1,IF(P8<0,0,-1)) -> 0 | AE8: =IF(Q8>0,1,IF(Q8<0,0,-1)) -> 1 | AF8: =IF(R8>0,1,IF(R8<0,0,-1)) -> 1 | AG8: =IF(S8>0,1,IF(S8<0,0,-1)) -> 1 | AH8: =IF(T8>0,1,IF(T8<0,0,-1)) -> 0 | AI8: =IF(U8>0,1,IF(U8<0,0,-1)) -> 1 | AJ8: =IF(ISNUMBER(K8),K8,IF(OR(K8="general",K8="23;general"),"General",IF(OR(K8="exemption",K8="other (exemption)"),"Tax exemption/waiver/suspension","Other"))) -> 17 | AK8: =IF(B8<>B7,1,0) -> 0 | AL8: 1
A9: 1 | B9: Australia | C9: 43855 | D9: 43919 | E9: 43951 | F9: =DATEDIF(D9,E9,"D") -> 32 | G9: 43919 | H9: 2020 | I9: 1 | J9: 6 | K9: 25 | L9: A further A$750 payment to social security and veteran income support recipients and eligible concession card holders, except for those who are receiving an income support payment that is eligible to receive the COVID-19 supplement. | M9: 1 | N9: 1 | O9: 2 | P9: -1 | Q9: 2 | R9: 1 | S9: 1 | T9: 2 | U9: 1 | V9: AUS | W9: East Asia & Pacific | X9: None | Y9: High Income | Z9: 1 | AA9: =IF(M9>0,1,IF(M9<0,0,-1)) -> 1 | AB9: =IF(N9>0,1,IF(N9<0,0,-1)) -> 1 | AC9: =IF(O9>0,1,IF(O9<0,0,-1)) -> 1 | AD9: =IF(P9>0,1,IF(P9<0,0,-1)) -> 0 | AE9: =IF(Q9>0,1,IF(Q9<0,0,-1)) -> 1 | AF9: =IF(R9>0,1,IF(R9<0,0,-1)) -> 1 | AG9: =IF(S9>0,1,IF(S9<0,0,-1)) -> 1 | AH9: =IF(T9>0,1,IF(T9<0,0,-1)) -> 1 | AI9: =IF(U9>0,1,IF(U9<0,0,-1)) -> 1 | AJ9: =IF(ISNUMBER(K9),K9,IF(OR(K9="general",K9="23;general"),"General",IF(OR(K9="exemption",K9="other (exemption)"),"Tax exemption/waiver/suspension","Other"))) -> 25 | AK9: =IF(B9<>B8,1,0) -> 0 | AL9: 1
A10: 1 | B10: Australia | C10: 43855 | D10: 43919 | E10: 43951 | F10: =DATEDIF(D10,E10,"D") -> 32 | G10: 43919 | H10: 2020 | I10: 1 | J10: 6 | K10: 29 | L10: Eligible employers can apply for a wage subsidy of 50% of the apprentice’s or trainee’s wage for up to 9 months from 1 January 2020 to 30 September. Where a small business is not able to retain an apprentice, the subsidy will be available to a new employer that employs that apprentice. | M10: 2 | N10: 1 | O10: -2 | P10: -1 | Q10: -2 | R10: 1 | S10: 1 | T10: -1 | U10: 1 | V10: AUS | W10: East Asia & Pacific | X10: None | Y10: High Income | Z10: 1 | AA10: =IF(M10>0,1,IF(M10<0,0,-1)) -> 1 | AB10: =IF(N10>0,1,IF(N10<0,0,-1)) -> 1 | AC10: =IF(O10>0,1,IF(O10<0,0,-1)) -> 0 | AD10: =IF(P10>0,1,IF(P10<0,0,-1)) -> 0 | AE10: =IF(Q10>0,1,IF(Q10<0,0,-1)) -> 0 | AF10: =IF(R10>0,1,IF(R10<0,0,-1)) -> 1 | AG10: =IF(S10>0,1,IF(S10<0,0,-1)) -> 1 | AH10: =IF(T10>0,1,IF(T10<0,0,-1)) -> 0 | AI10: =IF(U10>0,1,IF(U10<0,0,-1)) -> 1 | AJ10: =IF(ISNUMBER(K10),K10,IF(OR(K10="general",K10="23;general"),"General",IF(OR(K10="exemption",K10="other (exemption)"),"Tax exemption/waiver/suspension","Other"))) -> 29 | AK10: =IF(B10<>B9,1,0) -> 0 | AL10: 1
A11: 1 | B11: Australia | C11: 43855 | D11: 43919 | E11: 43951 | F11: =DATEDIF(D11,E11,"D") -> 32 | G11: 43919 | H11: 2020 | I11: 1 | J11: 9 | K11: 34 | L11: State and Territory governments also announced fiscal stimulus packages, together amounting to A$11.5 billion (0.6% of GDP), including payroll tax relief for businesses and relief for households, such as discount utility bills, cash payments to vulnerable households, and support for health spending. | V11: AUS | W11: East Asia & Pacific | X11: None | Y11: High Income | Z11: 1 | AA11: =IF(M11>0,1,IF(M11<0,0,-1)) -> -1 | AB11: =IF(N11>0,1,IF(N11<0,0,-1)) -> -1 | AC11: =IF(O11>0,1,IF(O11<0,0,-1)) -> -1 | AD11: =IF(P11>0,1,IF(P11<0,0,-1)) -> -1 | AE11: =IF(Q11>0,1,IF(Q11<0,0,-1)) -> -1 | AF11: =IF(R11>0,1,IF(R11<0,0,-1)) -> -1 | AG11: =IF(S11>0,1,IF(S11<0,0,-1)) -> -1 | AH11: =IF(T11>0,1,IF(T11<0,0,-1)) -> -1 | AI11: =IF(U11>0,1,IF(U11<0,0,-1)) -> -1 | AJ11: =IF(ISNUMBER(K11),K11,IF(OR(K11="general",K11="23;general"),"General",IF(OR(K11="exemption",K11="other (exemption)"),"Tax exemption/waiver/suspension","Other"))) -> 34 | AK11: =IF(B11<>B10,1,0) -> 0 | AL11: 0
A12: 1 | B12: Australia | C12: 43855 | D12: 43919 | E12: 43951 | F12: =DATEDIF(D12,E12,"D") -> 32 | G12: 43919 | H12: 2020 | I12: 1 | J12: 6 | K12: 28 | L12: Temporary expansion of eligibility to income support payments and the establishment of a new, time-limited COVID-19 supplement to be paid at a rate of A$550 per fortnight. This will be paid to both existing and new recipients of the JobSeeker Payment, Youth Allowance jobseeker, Parenting Payment, Farm Household Allowance and Special Benefit. | M12: 1 | N12: 1 | O12: 2 | P12: -1 | Q12: -2 | R12: 1 | S12: 1 | T12: -1 | U12: 1 | V12: AUS | W12: East Asia & Pacific | X12: None | Y12: High Income | Z12: 1 | AA12: =IF(M12>0,1,IF(M12<0,0,-1)) -> 1 | AB12: =IF(N12>0,1,IF(N12<0,0,-1)) -> 1 | AC12: =IF(O12>0,1,IF(O12<0,0,-1)) -> 1 | AD12: =IF(P12>0,1,IF(P12<0,0,-1)) -> 0 | AE12: =IF(Q12>0,1,IF(Q12<0,0,-1)) -> 0 | AF12: =IF(R12>0,1,IF(R12<0,0,-1)) -> 1 | AG12: =IF(S12>0,1,IF(S12<0,0,-1)) -> 1 | AH12: =IF(T12>0,1,IF(T12<0,0,-1)) -> 0 | AI12: =IF(U12>0,1,IF(U12<0,0,-1)) -> 1 | AJ12: =IF(ISNUMBER(K12),K12,IF(OR(K12="general",K12="23;general"),"General",IF(OR(K12="exemption",K12="other (exemption)"),"Tax exemption/waiver/suspension","Other"))) -> 28 | AK12: =IF(B12<>B11,1,0) -> 0 | AL12: 1
A13: 1 | B13: Australia | C13: 43855 | D13: 43919 | E13: 43951 | F13: =DATEDIF(D13,E13,"D") -> 32 | G13: 43919 | H13: 2020 | I13: 1 | J13: 6 | K13: 28 | L13: A$1 billion to support those regions and communities that have been disproportionately affected by the economic impacts of the COVID-19, including those heavily reliant on industries such as tourism, agriculture and education. | M13: 2 | N13: 1 | O13: -2 | P13: -1 | Q13: 1 | R13: 2 | S13: 1 | T13: 2 | U13: 1 | V13: AUS | W13: East Asia & Pacific | X13: None | Y13: High Income | Z13: 1 | AA13: =IF(M13>0,1,IF(M13<0,0,-1)) -> 1 | AB13: =IF(N13>0,1,IF(N13<0,0,-1)) -> 1 | AC13: =IF(O13>0,1,IF(O13<0,0,-1)) -> 0 | AD13: =IF(P13>0,1,IF(P13<0,0,-1)) -> 0 | AE13: =IF(Q13>0,1,IF(Q13<0,0,-1)) -> 1 | AF13: =IF(R13>0,1,IF(R13<0,0,-1)) -> 1 | AG13: =IF(S13>0,1,IF(S13<0,0,-1)) -> 1 | AH13: =IF(T13>0,1,IF(T13<0,0,-1)) -> 1 | AI13: =IF(U13>0,1,IF(U13<0,0,-1)) -> 1 | AJ13: =IF(ISNUMBER(K13),K13,IF(OR(K13="general",K13="23;general"),"General",IF(OR(K13="exemption",K13="other (exemption)"),"Tax exemption/waiver/suspension","Other"))) -> 28 | AK13: =IF(B13<>B12,1,0) -> 0 | AL13: 1
A14: 1 | B14: Australia | C14: 43855 | D14: 43919 | E14: 43951 | F14: =DATEDIF(D14,E14,"D") -> 32 | G14: 43919 | H14: 2020 | I14: 1 | J14: 1 | K14: 1 | L14: Accelerated depreciation: Businesses with a turnover of less than A$500 million will be able to deduct 50 per cent of the cost of an eligible asset on installation, with existing depreciation rules applying to the balance of the asset’s cost. | N14: 1 | O14: 2 | P14: -1 | Q14: 2 | R14: -2 | S14: 2 | T14: 2 | U14: 1 | V14: AUS | W14: East Asia & Pacific | X14: None | Y14: High Income | Z14: 1 | AA14: =IF(M14>0,1,IF(M14<0,0,-1)) -> -1 | AB14: =IF(N14>0,1,IF(N14<0,0,-1)) -> 1 | AC14: =IF(O14>0,1,IF(O14<0,0,-1)) -> 1 | AD14: =IF(P14>0,1,IF(P14<0,0,-1)) -> 0 | AE14: =IF(Q14>0,1,IF(Q14<0,0,-1)) -> 1 | AF14: =IF(R14>0,1,IF(R14<0,0,-1)) -> 0 | AG14: =IF(S14>0,1,IF(S14<0,0,-1)) -> 1 | AH14: =IF(T14>0,1,IF(T14<0,0,-1)) -> 1 | AI14: =IF(U14>0,1,IF(U14<0,0,-1)) -> 1 | AJ14: =IF(ISNUMBER(K14),K14,IF(OR(K14="general",K14="23;general"),"General",IF(OR(K14="exemption",K14="other (exemption)"),"Tax exemption/waiver/suspension","Other"))) -> 1 | AK14: =IF(B14<>B13,1,0) -> 0 | AL14: 1
A15: 1 | B15: Australia | C15: 43855 | D15: 43919 | E15: 43951 | F15: =DATEDIF(D15,E15,"D") -> 32 | G15: 43919 | H15: 2020 | I15: 1 | J15: 5 | K15: general | L15: Commonwealth government to spend almost an extra AS5 billion (0.3% of GDP) to strengthen the health system and protect the vulnerable people, including those in aged care, from the outbreak of COVID-19. | M15: 1 | N15: -1 | O15: -2 | P15: -1 | Q15: -2 | R15: 1 | S15: 1 | T15: 1 | U15: 1 | V15: AUS | W15: East Asia & Pacific | X15: None | Y15: High Income | Z15: 1 | AA15: =IF(M15>0,1,IF(M15<0,0,-1)) -> 1 | AB15: =IF(N15>0,1,IF(N15<0,0,-1)) -> 0 | AC15: =IF(O15>0,1,IF(O15<0,0,-1)) -> 0 | AD15: =IF(P15>0,1,IF(P15<0,0,-1)) -> 0 | AE15: =IF(Q15>0,1,IF(Q15<0,0,-1)) -> 0 | AF15: =IF(R15>0,1,IF(R15<0,0,-1)) -> 1 | AG15: =IF(S15>0,1,IF(S15<0,0,-1)) -> 1 | AH15: =IF(T15>0,1,IF(T15<0,0,-1)) -> 1 | AI15: =IF(U15>0,1,IF(U15<0,0,-1)) -> 1 | AJ15: =IF(ISNUMBER(K15),K15,IF(OR(K15="general",K15="23;general"),"General",IF(OR(K15="exemption",K15="other (exemption)"),"Tax exemption/waiver/suspension","Other"))) -> General | AK15: =IF(B15<>B14,1,0) -> 0 | AL15: 1
A16: 1 | B16: Australia | C16: 43855 | D16: 43919 | E16: 43951 | F16: =DATEDIF(D16,E16,"D") -> 32 | G16: 43919 | H16: 2020 | I16: 1 | J16: 9 | K16: 34 | L16: Under the enhanced scheme from the first package, employers will receive a payment equal to 100% of their salary and wages withheld (up from 50%), with the maximum payment being increased from USD 25,000 to USD 50,000. In addition, the minimum payment is being increased from A$2,000 to A$10,000. The payment will be available from April 28. | N16: 1 | P16: -1 | Q16: 2 | R16: 1 | S16: 1 | T16: 2 | U16: 1 | V16: AUS | W16: East Asia & Pacific | X16: None | Y16: High Income | Z16: 1 | AA16: =IF(M16>0,1,IF(M16<0,0,-1)) -> -1 | AB16: =IF(N16>0,1,IF(N16<0,0,-1)) -> 1 | AC16: =IF(O16>0,1,IF(O16<0,0,-1)) -> -1 | AD16: =IF(P16>0,1,IF(P16<0,0,-1)) -> 0 | AE16: =IF(Q16>0,1,IF(Q16<0,0,-1)) -> 1 | AF16: =IF(R16>0,1,IF(R16<0,0,-1)) -> 1 | AG16: =IF(S16>0,1,IF(S16<0,0,-1)) -> 1 | AH16: =IF(T16>0,1,IF(T16<0,0,-1)) -> 1 | AI16: =IF(U16>0,1,IF(U16<0,0,-1)) -> 1 | AJ16: =IF(ISNUMBER(K16),K16,IF(OR(K16="general",K16="23;general"),"General",IF(OR(K16="exemption",K16="other (exemption)"),"Tax exemption/waiver/suspension","Other"))) -> 34 | AK16: =IF(B16<>B15,1,0) -> 0 | AL16: 1
A17: 1 | B17: Australia | C17: 43855 | D17: 43919 | E17: 43951 | F17: =DATEDIF(D17,E17,"D") -> 32 | G17: 43919 | H17: 2020 | I17: 1 | J17: 9 | K17: 34 | L17: SME protection (retroactive to January 1-June 30): SMEs with aggregated annual turnover under A$50 million that withhold tax to the ATO on their employees’ salary and wages will receive a payment equal to 50% of the amount withheld up to a maximum payment of A$25,000. SMEs that pay salary and wages will receive a minimum payment of A$2,000, even if they are not required to withhold tax. | M17: 1 | N17: 1 | O17: 1 | P17: -1 | Q17: 2 | R17: 1 | S17: 1 | T17: -2 | U17: 1 | V17: AUS | W17: East Asia & Pacific | X17: None | Y17: High Income | Z17: 1 | AA17: =IF(M17>0,1,IF(M17<0,0,-1)) -> 1 | AB17: =IF(N17>0,1,IF(N17<0,0,-1)) -> 1 | AC17: =IF(O17>0,1,IF(O17<0,0,-1)) -> 1 | AD17: =IF(P17>0,1,IF(P17<0,0,-1)) -> 0 | AE17: =IF(Q17>0,1,IF(Q17<0,0,-1)) -> 1 | AF17: =IF(R17>0,1,IF(R17<0,0,-1)) -> 1 | AG17: =IF(S17>0,1,IF(S17<0,0,-1)) -> 1 | AH17: =IF(T17>0,1,IF(T17<0,0,-1)) -> 0 | AI17: =IF(U17>0,1,IF(U17<0,0,-1)) -> 1 | AJ17: =IF(ISNUMBER(K17),K17,IF(OR(K17="general",K17="23;general"),"General",IF(OR(K17="exemption",K17="other (exemption)"),"Tax exemption/waiver/suspension","Other"))) -> 34 | AK17: =IF(B17<>B16,1,0) -> 0 | AL17: 1
A18: 1 | B18: Australia | C18: 43855 | D18: 43919 | E18: 43951 | F18: =DATEDIF(D18,E18,"D") -> 32 | G18: 43919 | H18: 2020 | I18: 1 | J18: 2 | K18: 15 | L18: Tax relief measures to individuals experiencing financial hardship, and their tax agents for serious and exceptional circumstances, On 6 October, the Government announced the 2020-21 Federal Budget, which brings forward Stage Two of previously legislated tax cuts by two years, increasing certain tax bracket thresholds to widen the coverage of the relief. The Low and Middle Income Tax Offset will also be retained for an additional year. The Government estimates that more than 7 million Australians will receive a tax relief of approximately A$17.8bn. | M18: 2 | N18: 2 | O18: -2 | P18: -1 | Q18: -2 | R18: -2 | S18: 2 | T18: 2 | U18: 1 | V18: AUS | W18: East Asia & Pacific | X18: None | Y18: High Income | Z18: 1 | AA18: =IF(M18>0,1,IF(M18<0,0,-1)) -> 1 | AB18: =IF(N18>0,1,IF(N18<0,0,-1)) -> 1 | AC18: =IF(O18>0,1,IF(O18<0,0,-1)) -> 0 | AD18: =IF(P18>0,1,IF(P18<0,0,-1)) -> 0 | AE18: =IF(Q18>0,1,IF(Q18<0,0,-1)) -> 0 | AF18: =IF(R18>0,1,IF(R18<0,0,-1)) -> 0 | AG18: =IF(S18>0,1,IF(S18<0,0,-1)) -> 1 | AH18: =IF(T18>0,1,IF(T18<0,0,-1)) -> 1 | AI18: =IF(U18>0,1,IF(U18<0,0,-1)) -> 1 | AJ18: =IF(ISNUMBER(K18),K18,IF(OR(K18="general",K18="23;general"),"General",IF(OR(K18="exemption",K18="other (exemption)"),"Tax exemption/waiver/suspension","Other"))) -> 15 | AK18: =IF(B18<>B17,1,0) -> 0 | AL18: 1
A19: 1 | B19: Australia | C19: 43855 | D19: 43919 | E19: 43951 | F19: =DATEDIF(D19,E19,"D") -> 32 | G19: 43919 | H19: 2020 | I19: 1 | J19: 6 | K19: 28 | L19: The Commonwealth government has committed to provide free childcare to around one million families and announced targeted support to the education system. | M19: 2 | N19: 2 | O19: 1 | P19: -1 | Q19: 2 | R19: -2 | S19: 1 | T19: -2 | U19: -2 | V19: AUS | W19: East Asia & Pacific | X19: None | Y19: High Income | Z19: 1 | AA19: =IF(M19>0,1,IF(M19<0,0,-1)) -> 1 | AB19: =IF(N19>0,1,IF(N19<0,0,-1)) -> 1 | AC19: =IF(O19>0,1,IF(O19<0,0,-1)) -> 1 | AD19: =IF(P19>0,1,IF(P19<0,0,-1)) -> 0 | AE19: =IF(Q19>0,1,IF(Q19<0,0,-1)) -> 1 | AF19: =IF(R19>0,1,IF(R19<0,0,-1)) -> 0 | AG19: =IF(S19>0,1,IF(S19<0,0,-1)) -> 1 | AH19: =IF(T19>0,1,IF(T19<0,0,-1)) -> 0 | AI19: =IF(U19>0,1,IF(U19<0,0,-1)) -> 0 | AJ19: =IF(ISNUMBER(K19),K19,IF(OR(K19="general",K19="23;general"),"General",IF(OR(K19="exemption",K19="other (exemption)"),"Tax exemption/waiver/suspension","Other"))) -> 28 | AK19: =IF(B19<>B18,1,0) -> 0 | AL19: 1
A20: 1 | B20: Australia | C20: 43855 | D20: 43919 | E20: 43951 | F20: =DATEDIF(D20,E20,"D") -> 32 | G20: 43919 | H20: 2020 | I20: 1 | J20: 5 | K20: general | L20: Commonwealth office to share public health costs incurred by States and Territories, estimated at A$544.6 million. | M20: 1 | N20: -1 | O20: -2 | P20: -1 | Q20: -2 | R20: 1 | S20: 1 | T20: 1 | U20: 1 | V20: AUS | W20: East Asia & Pacific | X20: None | Y20: High Income | Z20: 1 | AA20: =IF(M20>0,1,IF(M20<0,0,-1)) -> 1 | AB20: =IF(N20>0,1,IF(N20<0,0,-1)) -> 0 | AC20: =IF(O20>0,1,IF(O20<0,0,-1)) -> 0 | AD20: =IF(P20>0,1,IF(P20<0,0,-1)) -> 0 | AE20: =IF(Q20>0,1,IF(Q20<0,0,-1)) -> 0 | AF20: =IF(R20>0,1,IF(R20<0,0,-1)) -> 1 | AG20: =IF(S20>0,1,IF(S20<0,0,-1)) -> 1 | AH20: =IF(T20>0,1,IF(T20<0,0,-1)) -> 1 | AI20: =IF(U20>0,1,IF(U20<0,0,-1)) -> 1 | AJ20: =IF(ISNUMBER(K20),K20,IF(OR(K20="general",K20="23;general"),"General",IF(OR(K20="exemption",K20="other (exemption)"),"Tax exemption/waiver/suspension","Other"))) -> General | AK20: =IF(B20<>B19,1,0) -> 0 | AL20: 1
A21: 1 | B21: Australia | C21: 43855 | D21: 43919 | E21: 43951 | F21: =DATEDIF(D21,E21,"D") -> 32 | G21: 43919 | H21: 2020 | I21: 1 | J21: 1 | K21: 6 | L21: Deferral: Taxpayers affected by the pandemic are eligible to apply for a deferral of payment of tax liability for up to 6 months without incurring interest or penalties. This deferral may apply to income tax, goods and services tax (GST), fringe benefits tax and excise taxes. Businesses requiring further deferral may be able to access low-interest repayment options. Businesses that vary their PAYG instalment to zero can also claim a refund for any instalments made for the September 2019 and December 2019 quarters. According to the 2020-21 Federal Budget, small, medium and larger businesses with a turnover of up to A$5 billion will be able to write off the full value of eligible assets until June 2022. Losses incurred to June 2022 will also be able to be offset against prior profits made in or after the 2018-19 financial year. The total temporary full expensing will mount to A$31.6bn (1.6% of GDP) over the course of 2020-21/2023-24. | M21: 2 | N21: 2 | O21: 2 | P21: 1 | Q21: 2 | R21: 2 | S21: 1 | T21: 1 | U21: 1 | V21: AUS | W21: East Asia & Pacific | X21: None | Y21: High Income | Z21: 1 | AA21: =IF(M21>0,1,IF(M21<0,0,-1)) -> 1 | AB21: =IF(N21>0,1,IF(N21<0,0,-1)) -> 1 | AC21: =IF(O21>0,1,IF(O21<0,0,-1)) -> 1 | AD21: =IF(P21>0,1,IF(P21<0,0,-1)) -> 1 | AE21: =IF(Q21>0,1,IF(Q21<0,0,-1)) -> 1 | AF21: =IF(R21>0,1,IF(R21<0,0,-1)) -> 1 | AG21: =IF(S21>0,1,IF(S21<0,0,-1)) -> 1 | AH21: =IF(T21>0,1,IF(T21<0,0,-1)) -> 1 | AI21: =IF(U21>0,1,IF(U21<0,0,-1)) -> 1 | AJ21: =IF(ISNUMBER(K21),K21,IF(OR(K21="general",K21="23;general"),"General",IF(OR(K21="exemption",K21="other (exemption)"),"Tax exemption/waiver/suspension","Other"))) -> 6 | AK21: =IF(B21<>B20,1,0) -> 0 | AL21: 1
A22: 1 | B22: Australia | C22: 43855 | D22: 43919 | E22: 43951 | F22: =DATEDIF(D22,E22,"D") -> 32 | G22: 43919 | H22: 2020 | I22: 1 | J22: 9 | K22: 34 | L22: The Government is providing up to A$100,000 to eligible small and medium sized businesses, and not-for-profits (including charities) that employ people, with a minimum payment of A$20,000. These payments will help businesses’ and not-for-profits’ cash flow so they can keep operating, pay their rent, electricity and other bills and retain staff. | M22: 1 | N22: 1 | O22: 1 | P22: -1 | Q22: 2 | R22: 2 | S22: 1 | T22: -2 | U22: 1 | V22: AUS | W22: East Asia & Pacific | X22: None | Y22: High Income | Z22: 1 | AA22: =IF(M22>0,1,IF(M22<0,0,-1)) -> 1 | AB22: =IF(N22>0,1,IF(N22<0,0,-1)) -> 1 | AC22: =IF(O22>0,1,IF(O22<0,0,-1)) -> 1 | AD22: =IF(P22>0,1,IF(P22<0,0,-1)) -> 0 | AE22: =IF(Q22>0,1,IF(Q22<0,0,-1)) -> 1 | AF22: =IF(R22>0,1,IF(R22<0,0,-1)) -> 1 | AG22: =IF(S22>0,1,IF(S22<0,0,-1)) -> 1 | AH22: =IF(T22>0,1,IF(T22<0,0,-1)) -> 0 | AI22: =IF(U22>0,1,IF(U22<0,0,-1)) -> 1 | AJ22: =IF(ISNUMBER(K22),K22,IF(OR(K22="general",K22="23;general"),"General",IF(OR(K22="exemption",K22="other (exemption)"),"Tax exemption/waiver/suspension","Other"))) -> 34 | AK22: =IF(B22<>B21,1,0) -> 0 | AL22: 1
A23: 1 | B23: Australia | C23: 43855 | D23: 43919 | E23: 43951 | F23: =DATEDIF(D23,E23,"D") -> 32 | G23: 43919 | H23: 2020 | I23: 1 | J23: 1 | K23: 3 | L23: Increase the instant asset write-off : instant asset write-off threshold is increased from A$30,000 to A$150,000 with access expanded access to include businesses with aggregated annual turnover of less than A$500 million (up from A$50 million) | M23: -2 | N23: -2 | O23: -2 | P23: -1 | Q23: 2 | R23: -2 | S23: 1 | T23: -2 | U23: 1 | V23: AUS | W23: East Asia & Pacific | X23: None | Y23: High Income | Z23: 1 | AA23: =IF(M23>0,1,IF(M23<0,0,-1)) -> 0 | AB23: =IF(N23>0,1,IF(N23<0,0,-1)) -> 0 | AC23: =IF(O23>0,1,IF(O23<0,0,-1)) -> 0 | AD23: =IF(P23>0,1,IF(P23<0,0,-1)) -> 0 | AE23: =IF(Q23>0,1,IF(Q23<0,0,-1)) -> 1 | AF23: =IF(R23>0,1,IF(R23<0,0,-1)) -> 0 | AG23: =IF(S23>0,1,IF(S23<0,0,-1)) -> 1 | AH23: =IF(T23>0,1,IF(T23<0,0,-1)) -> 0 | AI23: =IF(U23>0,1,IF(U23<0,0,-1)) -> 1 | AJ23: =IF(ISNUMBER(K23),K23,IF(OR(K23="general",K23="23;general"),"General",IF(OR(K23="exemption",K23="other (exemption)"),"Tax exemption/waiver/suspension","Other"))) -> 3 | AK23: =IF(B23<>B22,1,0) -> 0 | AL23: 1
A24: 1 | B24: Australia | C24: 43855 | D24: 43919 | E24: 43951 | F24: =DATEDIF(D24,E24,"D") -> 32 | G24: 43919 | H24: 2020 | I24: 1 | J24: 4 | K24: other | L24: The Commonwealth government will help finance a series of fast-track infrastructure projects across States and Territories (A$3.9 billion) and the arts and screen industries to support job creation under the JobMaker program, 06.10 additional A$73 bn. | V24: AUS | W24: East Asia & Pacific | X24: None | Y24: High Income | Z24: 1 | AA24: -1 | AB24: -1 | AC24: -1 | AD24: -1 | AE24: -1 | AF24: -1 | AG24: -1 | AH24: -1 | AI24: -1 | AJ24: =IF(ISNUMBER(K24),K24,IF(OR(K24="general",K24="23;general"),"General",IF(OR(K24="exemption",K24="other (exemption)"),"Tax exemption/waiver/suspension","Other"))) -> Other | AK24: =IF(B24<>B23,1,0) -> 0 | AL24: 0
A25: 1 | B25: Australia | C25: 43855 | D25: 43919 | E25: 43951 | F25: =DATEDIF(D25,E25,"D") -> 32 | G25: 43919 | H25: 2020 | I25: 1 | J25: 6 | K25: 28 | L25: The Commonwealth government will help finance a home care package to support senior citizens (A$0.3 billion) | V25: AUS | W25: East Asia & Pacific | X25: None | Y25: High Income | Z25: 1 | AA25: -1 | AB25: -1 | AC25: -1 | AD25: -1 | AE25: -1 | AF25: -1 | AG25: -1 | AH25: -1 | AI25: -1 | AJ25: =IF(ISNUMBER(K25),K25,IF(OR(K25="general",K25="23;general"),"General",IF(OR(K25="exemption",K25="other (exemption)"),"Tax exemption/waiver/suspension","Other"))) -> 28 | AK25: =IF(B25<>B24,1,0) -> 0 | AL25: 0
A26: 1 | B26: Australia | C26: 43855 | D26: 43919 | E26: 43951 | F26: =DATEDIF(D26,E26,"D") -> 32 | G26: 43919 | H26: 2020 | I26: 1 | J26: 6 | K26: 26 | L26: The Commonwealth government instituted a new JobTrainer skills package (A$2 billion). | V26: AUS | W26: East Asia & Pacific | X26: None | Y26: High Income | Z26: 1 | AA26: -1 | AB26: -1 | AC26: -1 | AD26: -1 | AE26: -1 | AF26: -1 | AG26: -1 | AH26: -1 | AI26: -1 | AJ26: =IF(ISNUMBER(K26),K26,IF(OR(K26="general",K26="23;general"),"General",IF(OR(K26="exemption",K26="other (exemption)"),"Tax exemption/waiver/suspension","Other"))) -> 26 | AK26: =IF(B26<>B25,1,0) -> 0 | AL26: 0
A27: 1 | B27: Australia | C27: 43855 | D27: 43919 | E27: 43951 | F27: =DATEDIF(D27,E27,"D") -> 32 | G27: 43919 | H27: 2020 | I27: 1 | J27: 6 | K27: 27 | L27: The Government will allow individuals in financial stress as a result of the Coronavirus to access up to $10,000 of their superannuation in 2019-20 and a further $10,000 in 2020-21. Eligible individuals will be able to apply online for access of up to $10,000 of their superannuation before 1 July 2020. Minimum superannuation drawdown requirements have also been reduced and social security deeming rates (the rate of income beneficiaries are assumed to be earning from financial investments) have also been reduced. | V27: AUS | W27: East Asia & Pacific | X27: None | Y27: High Income | Z27: 1 | AA27: -1 | AB27: -1 | AC27: -1 | AD27: -1 | AE27: -1 | AF27: -1 | AG27: -1 | AH27: -1 | AI27: -1 | AJ27: =IF(ISNUMBER(K27),K27,IF(OR(K27="general",K27="23;general"),"General",IF(OR(K27="exemption",K27="other (exemption)"),"Tax exemption/waiver/suspension","Other"))) -> 27 | AK27: =IF(B27<>B26,1,0) -> 0 | AL27: 0
A28: 1 | B28: Australia | C28: 43855 | D28: 43919 | E28: 43951 | F28: =DATEDIF(D28,E28,"D") -> 32 | G28: 43919 | H28: 2020 | I28: 1 | J28: 6 | K28: 27 | L28: The Government is temporarily reducing superannuation minimum drawdown requirements for account based pensions and similar products by 50 per cent for 2019-20 and 2020-21. This measure will benefit retirees by providing them with more flexibility as to how they manage their superannuation assets. | V28: AUS | W28: East Asia & Pacific | X28: None | Y28: High Income | Z28: 1 | AA28: -1 | AB28: -1 | AC28: -1 | AD28: -1 | AE28: -1 | AF28: -1 | AG28: -1 | AH28: -1 | AI28: -1 | AJ28: =IF(ISNUMBER(K28),K28,IF(OR(K28="general",K28="23;general"),"General",IF(OR(K28="exemption",K28="other (exemption)"),"Tax exemption/waiver/suspension","Other"))) -> 27 | AK28: =IF(B28<>B27,1,0) -> 0 | AL28: 0
A29: 1 | B29: Australia | C29: 43855 | D29: 43919 | E29: 43951 | F29: =DATEDIF(D29,E29,"D") -> 32 | G29: 43919 | H29: 2020 | I29: 1 | J29: 3 | K29: 19 | L29: VAT tax rate reduction from 20% to 0% for respiratory masks for deliveries and intra-Community purchases. | V29: AUS | W29: East Asia & Pacific | X29: None | Y29: High Income | Z29: 1 | AA29: -1 | AB29: -1 | AC29: -1 | AD29: -1 | AE29: -1 | AF29: -1 | AG29: -1 | AH29: -1 | AI29: -1 | AJ29: =IF(ISNUMBER(K29),K29,IF(OR(K29="general",K29="23;general"),"General",IF(OR(K29="exemption",K29="other (exemption)"),"Tax exemption/waiver/suspension","Other"))) -> 19 | AK29: =IF(B29<>B28,1,0) -> 0 | AL29: 0
A30: 1 | B30: Australia | C30: 43855 | D30: 43919 | E30: 43951 | F30: =DATEDIF(D30,E30,"D") -> 32 | G30: 43919 | H30: 2020 | I30: 1 | J30: 6 | K30: 27 | L30: There has been a temporary expansion of eligibility for income support payments (the JobSeeker Programme) and the establishment of a new, time-limited Coronavirus supplement to be paid at a rate of A$550 per fortnight until the end of September 2020. This will be paid to both existing and new recipients of various government benefits. On 21 July, the government announced that the supplementary payment will be extended to the end of December 2020, but that the size of the payment will be reduced to A$250 per fortnight. New arrangements for the supplement are expected to cost A$3.8 billion. | V30: AUS | W30: East Asia & Pacific | X30: None | Y30: High Income | Z30: 1 | AA30: -1 | AB30: -1 | AC30: -1 | AD30: -1 | AE30: -1 | AF30: -1 | AG30: -1 | AH30: -1 | AI30: -1 | AJ30: =IF(ISNUMBER(K30),K30,IF(OR(K30="general",K30="23;general"),"General",IF(OR(K30="exemption",K30="other (exemption)"),"Tax exemption/waiver/suspension","Other"))) -> 27 | AK30: =IF(B30<>B29,1,0) -> 0 | AL30: 0
A31: 1 | B31: Australia | C31: 43855 | D31: 43919 | E31: 43951 | F31: =DATEDIF(D31,E31,"D") -> 32 | G31: 43919 | H31: 2020 | I31: 1 | J31: 6 | K31: 25 | L31: On August 3, in response to a rise in COVID-19 cases and tighter confinement measures announced in Victoria, the Federal Government announced $1,500 "disaster payment" for workers who are required to self-isolate because of coronavirus but do not have leave entitlements. | V31: AUS | W31: East Asia & Pacific | X31: None | Y31: High Income | Z31: 1 | AA31: -1 | AB31: -1 | AC31: -1 | AD31: -1 | AE31: -1 | AF31: -1 | AG31: -1 | AH31: -1 | AI31: -1 | AJ31: =IF(ISNUMBER(K31),K31,IF(OR(K31="general",K31="23;general"),"General",IF(OR(K31="exemption",K31="other (exemption)"),"Tax exemption/waiver/suspension","Other"))) -> 25 | AK31: =IF(B31<>B30,1,0) -> 0 | AL31: 0
A32: 1 | B32: Australia | C32: 43855 | D32: 43919 | E32: 43951 | F32: =DATEDIF(D32,E32,"D") -> 32 | G32: 43919 | H32: 2020 | I32: 1 | J32: 6 | K32: 29 | L32: Across a large range of work types (103 of the 121 modern awards), employees will receive two weeks of unpaid pandemic leave. The covered employees will also be allowed to take double the duration of annual leave at half pay. | V32: AUS | W32: East Asia & Pacific | X32: None | Y32: High Income | Z32: 1 | AA32: -1 | AB32: -1 | AC32: -1 | AD32: -1 | AE32: -1 | AF32: -1 | AG32: -1 | AH32: -1 | AI32: -1 | AJ32: =IF(ISNUMBER(K32),K32,IF(OR(K32="general",K32="23;general"),"General",IF(OR(K32="exemption",K32="other (exemption)"),"Tax exemption/waiver/suspension","Other"))) -> 29 | AK32: =IF(B32<>B31,1,0) -> 0 | AL32: 0
A33: 1 | B33: Australia | C33: 43855 | D33: 43919 | E33: 43951 | F33: =DATEDIF(D33,E33,"D") -> 32 | G33: 43919 | H33: 2021 | I33: 1 | J33: 6 | K33: 29 | L33: On 2 April, a subsidy to childcare providers was announced, conditional on them staying open and not charging families for care. The Commonwealth Government will pay 50 per cent of the sector's fee revenue up to the existing hourly rate cap. The funding will apply from 6 April based on the number of children who were in care during the fortnight leading into 2 March, whether or not they are attending services. The existing arrangements will end in mid-July and be replaced by a three month A$708 million support package to the childcare sector. Families will return to paying for childcare, with the reintroduction of the Child Care Subsidy, but the criteria for families impacted by the economic downturn will be loosened. | V33: AUS | AA33: 1 | AB33: -1 | AC33: -1 | AD33: -1 | AE33: 1 | AF33: 1 | AG33: 1 | AH33: 1 | AI33: 1 | AJ33: =IF(ISNUMBER(K33),K33,IF(OR(K33="general",K33="23;general"),"General",IF(OR(K33="exemption",K33="other (exemption)"),"Tax exemption/waiver/suspension","Other"))) -> 29
A34: 1 | B34: Australia | C34: 43855 | D34: 43919 | E34: 43951 | F34: =DATEDIF(D34,E34,"D") -> 32 | G34: 43919 | H34: 2021 | I34: 1 | J34: 6 | K34: 25 | L34: Aged pensioners will receive an additional A$250 payment from December 2020 and a further A$250 payment from March 2021 according to the 2020-21 Federal Budget announced on 6 October. | V34: AUS | AA34: 1 | AB34: -1 | AC34: 1 | AD34: -1 | AE34: 1 | AF34: 1 | AG34: 1 | AH34: 1 | AI34: 1 | AJ34: =IF(ISNUMBER(K34),K34,IF(OR(K34="general",K34="23;general"),"General",IF(OR(K34="exemption",K34="other (exemption)"),"Tax exemption/waiver/suspension","Other"))) -> 25
A35: 1 | B35: Australia | C35: 43855 | D35: 43919 | E35: 43951 | F35: =DATEDIF(D35,E35,"D") -> 32 | G35: 43919 | H35: 2021 | I35: 1 | J35: 4 | K35: other | L35: The government has also announced the HomeBuilder programme to support residential construction activity in the second half of 2020. The programme will provide all eligible owner-occupiers with a grant of A$25,000 to build a new home or substantially renovate an existing home. Construction must be contracted to commence within three months of the contract date. Applicants are subject to eligibility criteria, including caps on household income and the price of a new home or renovation. The program is expected to provide around 27,000 grants at a total cost of around A$680 million. | V35: AUS | AA35: 1 | AB35: -1 | AC35: -1 | AD35: -1 | AE35: 1 | AF35: 1 | AG35: 1 | AH35: 1 | AI35: 1 | AJ35: =IF(ISNUMBER(K35),K35,IF(OR(K35="general",K35="23;general"),"General",IF(OR(K35="exemption",K35="other (exemption)"),"Tax exemption/waiver/suspension","Other"))) -> Other
A36: 1 | B36: Australia | C36: 43855 | D36: 43919 | E36: 43951 | F36: =DATEDIF(D36,E36,"D") -> 32 | G36: 43919 | H36: 2021 | I36: 1 | J36: 4 | K36: other | L36: According to the 2020-21 Federal Budget, an additional A$1 billion of low cost finance will be spent to support the construction of affordable housing. | V36: AUS | AA36: 1 | AB36: -1 | AC36: 1 | AD36: 1 | AE36: 1 | AF36: 1 | AG36: 1 | AH36: 1 | AI36: 1 | AJ36: =IF(ISNUMBER(K36),K36,IF(OR(K36="general",K36="23;general"),"General",IF(OR(K36="exemption",K36="other (exemption)"),"Tax exemption/waiver/suspension","Other"))) -> Other
A37: 1 | B37: Australia | C37: 43855 | D37: 43919 | E37: 43951 | F37: =DATEDIF(D37,E37,"D") -> 32 | G37: 43919 | H37: 2021 | I37: 1 | J37: 2 | K37: 15 | L37: Additional tax reduction for low and middle income households 11. Mai 2021 | V37: AUS | AA37: 1 | AB37: -1 | AC37: -1 | AD37: -1 | AE37: 1 | AF37: 1 | AG37: 1 | AH37: 1 | AI37: 1 | AJ37: =IF(ISNUMBER(K37),K37,IF(OR(K37="general",K37="23;general"),"General",IF(OR(K37="exemption",K37="other (exemption)"),"Tax exemption/waiver/suspension","Other"))) -> 15
A38: 1 | B38: Australia | C38: 43855 | D38: 43919 | E38: 43951 | F38: =DATEDIF(D38,E38,"D") -> 32 | G38: 43919 | H38: 2021 | I38: 1 | J38: 4 | K38: other | L38: Additional Investestments into Infrastructure 11.Mai 2021 | V38: AUS | AA38: -1 | AB38: -1 | AC38: -1 | AD38: -1 | AE38: -1 | AF38: -1 | AG38: 1 | AH38: -1 | AI38: 1 | AJ38: =IF(ISNUMBER(K38),K38,IF(OR(K38="general",K38="23;general"),"General",IF(OR(K38="exemption",K38="other (exemption)"),"Tax exemption/waiver/suspension","Other"))) -> Other
A39: 1 | B39: Australia | C39: 43855 | D39: 43919 | E39: 43951 | F39: =DATEDIF(D39,E39,"D") -> 32 | G39: 43919 | H39: 2021 | I39: 1 | J39: 5 | K39: 22 | L39: A$7 bn. for vaccines | V39: AUS | AA39: -1 | AB39: -1 | AC39: -1 | AD39: -1 | AE39: -1 | AF39: -1 | AG39: 1 | AH39: -1 | AI39: 1 | AJ39: =IF(ISNUMBER(K39),K39,IF(OR(K39="general",K39="23;general"),"General",IF(OR(K39="exemption",K39="other (exemption)"),"Tax exemption/waiver/suspension","Other"))) -> 22
A40: 1 | B40: Australia | C40: 43855 | D40: 43919 | E40: 43951 | F40: =DATEDIF(D40,E40,"D") -> 32 | G40: 43919 | H40: 2021 | I40: 1 | J40: 7 | K40: 30 | L40: Coronavirus SME Guarantee → SME Recovery Loan Scheme (2021/22) – Fortsetzung/Neuauflage mit hoeherer Garantie (bis 80% in 2021; 50% in 2022). | AJ40: =IF(ISNUMBER(K40),K40,IF(OR(K40="general",K40="23;general"),"General",IF(OR(K40="exemption",K40="other (exemption)"),"Tax exemption/waiver/suspension","Other"))) -> 30
A41: 1 | B41: Australia | C41: 43855 | D41: 43919 | E41: 43951 | F41: =DATEDIF(D41,E41,"D") -> 32 | G41: 43919 | H41: 2021 | I41: 1 | J41: 1 | K41: 7 | L41: Aviation-Pakete – DANS/RANS zur Aufrechterhaltung des Linien- und Regionalverkehrs + Gebuehrennachlaesse; insgesamt > A$5.3 Mrd fuer den Sektor. International Freight Assistance Mechanism (IFAM) – Foerdert Luftfracht fuer Exporte/Importe waehrend Grenzschliessungen | AJ41: =IF(ISNUMBER(K41),K41,IF(OR(K41="general",K41="23;general"),"General",IF(OR(K41="exemption",K41="other (exemption)"),"Tax exemption/waiver/suspension","Other"))) -> 7
A42: 1 | B42: Australia | C42: 43855 | D42: 43919 | E42: 43951 | F42: =DATEDIF(D42,E42,"D") -> 32 | G42: 43919 | H42: 2021 | I42: 1 | J42: 7 | K42: 30 | L42: Consumer Travel Support Program (Reisebuero/-veranstalter) – mehrere Runden bis 2022 (z. B. Round 3 A$75.5 Mio). | AJ42: =IF(ISNUMBER(K42),K42,IF(OR(K42="general",K42="23;general"),"General",IF(OR(K42="exemption",K42="other (exemption)"),"Tax exemption/waiver/suspension","Other"))) -> 30
A43: 0 | B43: Austria | C43: 43886 | D43: 43906 | E43: 43970 | F43: =DATEDIF(D43,E43,"D") -> 64 | G43: 43906 | H43: 2020 | I43: 0 | J43: 6 | K43: 27 | L43: Temporary waiving of conditionalities to receive childcare benefits (i.e. obligatory health examinations that usually have to take place at fixed times during pregnancy until age 5 of the child) | M43: 2 | N43: 1 | O43: 2 | P43: -2 | Q43: 2 | R43: 1 | S43: 1 | T43: 1 | U43: 1 | V43: AUT | W43: Europe & Central Asia | X43: None | Y43: High Income | Z43: 0 | AA43: =IF(M43>0,1,IF(M43<0,0,-1)) -> 1 | AB43: =IF(N43>0,1,IF(N43<0,0,-1)) -> 1 | AC43: =IF(O43>0,1,IF(O43<0,0,-1)) -> 1 | AD43: =IF(P43>0,1,IF(P43<0,0,-1)) -> 0 | AE43: =IF(Q43>0,1,IF(Q43<0,0,-1)) -> 1 | AF43: =IF(R43>0,1,IF(R43<0,0,-1)) -> 1 | AG43: =IF(S43>0,1,IF(S43<0,0,-1)) -> 1 | AH43: =IF(T43>0,1,IF(T43<0,0,-1)) -> 1 | AI43: =IF(U43>0,1,IF(U43<0,0,-1)) -> 1 | AJ43: =IF(ISNUMBER(K43),K43,IF(OR(K43="general",K43="23;general"),"General",IF(OR(K43="exemption",K43="other (exemption)"),"Tax exemption/waiver/suspension","Other"))) -> 27 | AK43: =IF(B43<>B32,1,0) -> 1 | AL43: 1
A44: 0 | B44: Austria | C44: 43886 | D44: 43906 | E44: 43970 | F44: =DATEDIF(D44,E44,"D") -> 64 | G44: 43906 | H44: 2020 | I44: 0 | J44: 5 | K44: 21 | L44: VAT exemption for respirator masks. | M44: 1 | N44: 1 | O44: -2 | P44: -1 | Q44: -2 | R44: -2 | S44: -2 | U44: 1 | V44: AUT | W44: Europe & Central Asia | X44: None | Y44: High Income | Z44: 0 | AA44: =IF(M44>0,1,IF(M44<0,0,-1)) -> 1 | AB44: =IF(N44>0,1,IF(N44<0,0,-1)) -> 1 | AC44: =IF(O44>0,1,IF(O44<0,0,-1)) -> 0 | AD44: =IF(P44>0,1,IF(P44<0,0,-1)) -> 0 | AE44: =IF(Q44>0,1,IF(Q44<0,0,-1)) -> 0 | AF44: =IF(R44>0,1,IF(R44<0,0,-1)) -> 0 | AG44: =IF(S44>0,1,IF(S44<0,0,-1)) -> 0 | AH44: =IF(T44>0,1,IF(T44<0,0,-1)) -> -1 | AI44: =IF(U44>0,1,IF(U44<0,0,-1)) -> 1 | AJ44: =IF(ISNUMBER(K44),K44,IF(OR(K44="general",K44="23;general"),"General",IF(OR(K44="exemption",K44="other (exemption)"),"Tax exemption/waiver/suspension","Other"))) -> 21 | AK44: =IF(B44<>B43,1,0) -> 0 | AL44: 1
A45: 0 | B45: Austria | C45: 43886 | D45: 43906 | E45: 43970 | F45: =DATEDIF(D45,E45,"D") -> 64 | G45: 43906 | H45: 2020 | I45: 0 | J45: 1 | K45: exemption | L45: Grants for businesses from public funds for dealing with the COVID-19 crisis will be tax-exempt. | M45: 2 | N45: 2 | O45: -2 | P45: -1 | Q45: -2 | R45: 2 | S45: -2 | T45: 2 | U45: 1 | V45: AUT | W45: Europe & Central Asia | X45: None | Y45: High Income | Z45: 0 | AA45: =IF(M45>0,1,IF(M45<0,0,-1)) -> 1 | AB45: =IF(N45>0,1,IF(N45<0,0,-1)) -> 1 | AC45: =IF(O45>0,1,IF(O45<0,0,-1)) -> 0 | AD45: =IF(P45>0,1,IF(P45<0,0,-1)) -> 0 | AE45: =IF(Q45>0,1,IF(Q45<0,0,-1)) -> 0 | AF45: =IF(R45>0,1,IF(R45<0,0,-1)) -> 1 | AG45: =IF(S45>0,1,IF(S45<0,0,-1)) -> 0 | AH45: =IF(T45>0,1,IF(T45<0,0,-1)) -> 1 | AI45: =IF(U45>0,1,IF(U45<0,0,-1)) -> 1 | AJ45: =IF(ISNUMBER(K45),K45,IF(OR(K45="general",K45="23;general"),"General",IF(OR(K45="exemption",K45="other (exemption)"),"Tax exemption/waiver/suspension","Other"))) -> Tax exemption/waiver/suspension | AK45: =IF(B45<>B44,1,0) -> 0 | AL45: 1
A46: 0 | B46: Austria | C46: 43886 | D46: 43906 | E46: 43970 | F46: =DATEDIF(D46,E46,"D") -> 64 | G46: 43906 | H46: 2020 | I46: 0 | J46: 6 | K46: 27 | L46: Funding for short-term work was increased on April 13, from EUR 3 to EUR 5 billion, and the time frame for the submission of applications extended. | M46: 2 | N46: 1 | O46: 1 | P46: -1 | Q46: 1 | R46: 2 | S46: 1 | T46: 1 | U46: 1 | V46: AUT | W46: Europe & Central Asia | X46: None | Y46: High Income | Z46: 0 | AA46: =IF(M46>0,1,IF(M46<0,0,-1)) -> 1 | AB46: =IF(N46>0,1,IF(N46<0,0,-1)) -> 1 | AC46: =IF(O46>0,1,IF(O46<0,0,-1)) -> 1 | AD46: =IF(P46>0,1,IF(P46<0,0,-1)) -> 0 | AE46: =IF(Q46>0,1,IF(Q46<0,0,-1)) -> 1 | AF46: =IF(R46>0,1,IF(R46<0,0,-1)) -> 1 | AG46: =IF(S46>0,1,IF(S46<0,0,-1)) -> 1 | AH46: =IF(T46>0,1,IF(T46<0,0,-1)) -> 1 | AI46: =IF(U46>0,1,IF(U46<0,0,-1)) -> 1 | AJ46: =IF(ISNUMBER(K46),K46,IF(OR(K46="general",K46="23;general"),"General",IF(OR(K46="exemption",K46="other (exemption)"),"Tax exemption/waiver/suspension","Other"))) -> 27 | AK46: =IF(B46<>B45,1,0) -> 0 | AL46: 1
A47: 0 | B47: Austria | C47: 43886 | D47: 43906 | E47: 43970 | F47: =DATEDIF(D47,E47,"D") -> 64 | G47: 43906 | H47: 2020 | I47: 0 | J47: 7 | K47: 30 | L47: EUR9 billion in guarantees for businesses. | M47: -2 | N47: 1 | O47: 1 | P47: 1 | Q47: 1 | R47: 2 | S47: 1 | T47: -2 | U47: 1 | V47: AUT | W47: Europe & Central Asia | X47: None | Y47: High Income | Z47: 0 | AA47: =IF(M47>0,1,IF(M47<0,0,-1)) -> 0 | AB47: =IF(N47>0,1,IF(N47<0,0,-1)) -> 1 | AC47: =IF(O47>0,1,IF(O47<0,0,-1)) -> 1 | AD47: =IF(P47>0,1,IF(P47<0,0,-1)) -> 1 | AE47: =IF(Q47>0,1,IF(Q47<0,0,-1)) -> 1 | AF47: =IF(R47>0,1,IF(R47<0,0,-1)) -> 1 | AG47: =IF(S47>0,1,IF(S47<0,0,-1)) -> 1 | AH47: =IF(T47>0,1,IF(T47<0,0,-1)) -> 0 | AI47: =IF(U47>0,1,IF(U47<0,0,-1)) -> 1 | AJ47: =IF(ISNUMBER(K47),K47,IF(OR(K47="general",K47="23;general"),"General",IF(OR(K47="exemption",K47="other (exemption)"),"Tax exemption/waiver/suspension","Other"))) -> 30 | AK47: =IF(B47<>B46,1,0) -> 0 | AL47: 1
A48: 0 | B48: Austria | C48: 43886 | D48: 43906 | E48: 43970 | F48: =DATEDIF(D48,E48,"D") -> 64 | G48: 43906 | H48: 2020 | I48: 0 | J48: 6 | K48: 28 | L48: EUR15 billion in emergency aid to households and businesses affected by health measures | M48: 2 | N48: 2 | P48: -1 | Q48: 2 | R48: 2 | S48: 1 | U48: 1 | V48: AUT | W48: Europe & Central Asia | X48: None | Y48: High Income | Z48: 0 | AA48: =IF(M48>0,1,IF(M48<0,0,-1)) -> 1 | AB48: =IF(N48>0,1,IF(N48<0,0,-1)) -> 1 | AC48: =IF(O48>0,1,IF(O48<0,0,-1)) -> -1 | AD48: =IF(P48>0,1,IF(P48<0,0,-1)) -> 0 | AE48: =IF(Q48>0,1,IF(Q48<0,0,-1)) -> 1 | AF48: =IF(R48>0,1,IF(R48<0,0,-1)) -> 1 | AG48: =IF(S48>0,1,IF(S48<0,0,-1)) -> 1 | AH48: =IF(T48>0,1,IF(T48<0,0,-1)) -> -1 | AI48: =IF(U48>0,1,IF(U48<0,0,-1)) -> 1 | AJ48: =IF(ISNUMBER(K48),K48,IF(OR(K48="general",K48="23;general"),"General",IF(OR(K48="exemption",K48="other (exemption)"),"Tax exemption/waiver/suspension","Other"))) -> 28 | AK48: =IF(B48<>B47,1,0) -> 0 | AL48: 1
A49: 0 | B49: Austria | C49: 43886 | D49: 43906 | E49: 43970 | F49: =DATEDIF(D49,E49,"D") -> 64 | G49: 43906 | H49: 2020 | I49: 0 | J49: 9 | K49: 34 | L49: Cash assistance for one-person companies and freelancers affected by the crisis (e.g. service providers, artists, etc.) through a hardship fund, implemented by the Austrian Economic Chamber | M49: 1 | N49: 1 | O49: -2 | P49: -1 | Q49: -2 | R49: -2 | S49: 1 | T49: -2 | U49: 1 | V49: AUT | W49: Europe & Central Asia | X49: None | Y49: High Income | Z49: 0 | AA49: =IF(M49>0,1,IF(M49<0,0,-1)) -> 1 | AB49: =IF(N49>0,1,IF(N49<0,0,-1)) -> 1 | AC49: =IF(O49>0,1,IF(O49<0,0,-1)) -> 0 | AD49: =IF(P49>0,1,IF(P49<0,0,-1)) -> 0 | AE49: =IF(Q49>0,1,IF(Q49<0,0,-1)) -> 0 | AF49: =IF(R49>0,1,IF(R49<0,0,-1)) -> 0 | AG49: =IF(S49>0,1,IF(S49<0,0,-1)) -> 1 | AH49: =IF(T49>0,1,IF(T49<0,0,-1)) -> 0 | AI49: =IF(U49>0,1,IF(U49<0,0,-1)) -> 1 | AJ49: =IF(ISNUMBER(K49),K49,IF(OR(K49="general",K49="23;general"),"General",IF(OR(K49="exemption",K49="other (exemption)"),"Tax exemption/waiver/suspension","Other"))) -> 34 | AK49: =IF(B49<>B48,1,0) -> 0 | AL49: 1
A50: 0 | B50: Austria | C50: 43886 | D50: 43906 | E50: 43970 | F50: =DATEDIF(D50,E50,"D") -> 64 | G50: 43906 | H50: 2020 | I50: 0 | J50: 1 | K50: 5 | L50: The measures to protect businesses are also available for PIT-liable individuals | M50: -2 | N50: 2 | O50: 2 | P50: 1 | Q50: -2 | R50: 2 | S50: 1 | T50: 1 | U50: 1 | V50: AUT | W50: Europe & Central Asia | X50: None | Y50: High Income | Z50: 0 | AA50: =IF(M50>0,1,IF(M50<0,0,-1)) -> 0 | AB50: =IF(N50>0,1,IF(N50<0,0,-1)) -> 1 | AC50: =IF(O50>0,1,IF(O50<0,0,-1)) -> 1 | AD50: =IF(P50>0,1,IF(P50<0,0,-1)) -> 1 | AE50: =IF(Q50>0,1,IF(Q50<0,0,-1)) -> 0 | AF50: =IF(R50>0,1,IF(R50<0,0,-1)) -> 1 | AG50: =IF(S50>0,1,IF(S50<0,0,-1)) -> 1 | AH50: =IF(T50>0,1,IF(T50<0,0,-1)) -> 1 | AI50: =IF(U50>0,1,IF(U50<0,0,-1)) -> 1 | AJ50: =IF(ISNUMBER(K50),K50,IF(OR(K50="general",K50="23;general"),"General",IF(OR(K50="exemption",K50="other (exemption)"),"Tax exemption/waiver/suspension","Other"))) -> 5 | AK50: =IF(B50<>B49,1,0) -> 0 | AL50: 1
A51: 0 | B51: Austria | C51: 43886 | D51: 43906 | E51: 43970 | F51: =DATEDIF(D51,E51,"D") -> 64 | G51: 43906 | H51: 2020 | I51: 0 | J51: 6 | K51: 29 | L51: Government is covering up to 90% of wages/salaries of workers to stay employed, rather than being laid-off. | N51: 1 | P51: -1 | R51: -2 | S51: 1 | T51: -1 | V51: AUT | W51: Europe & Central Asia | X51: None | Y51: High Income | Z51: 0 | AA51: =IF(M51>0,1,IF(M51<0,0,-1)) -> -1 | AB51: =IF(N51>0,1,IF(N51<0,0,-1)) -> 1 | AC51: =IF(O51>0,1,IF(O51<0,0,-1)) -> -1 | AD51: =IF(P51>0,1,IF(P51<0,0,-1)) -> 0 | AE51: =IF(Q51>0,1,IF(Q51<0,0,-1)) -> -1 | AF51: =IF(R51>0,1,IF(R51<0,0,-1)) -> 0 | AG51: =IF(S51>0,1,IF(S51<0,0,-1)) -> 1 | AH51: =IF(T51>0,1,IF(T51<0,0,-1)) -> 0 | AI51: =IF(U51>0,1,IF(U51<0,0,-1)) -> -1 | AJ51: =IF(ISNUMBER(K51),K51,IF(OR(K51="general",K51="23;general"),"General",IF(OR(K51="exemption",K51="other (exemption)"),"Tax exemption/waiver/suspension","Other"))) -> 29 | AK51: =IF(B51<>B50,1,0) -> 0 | AL51: 1
A52: 0 | B52: Austria | C52: 43886 | D52: 43906 | E52: 43970 | F52: =DATEDIF(D52,E52,"D") -> 64 | G52: 43906 | H52: 2020 | I52: 0 | J52: 2 | K52: exemption | L52: Bonus payments by the employer are tax-free up to a maximum of EUR 3,000. The bonus payment will only be fully tax-free, if the actual payment was done in 2020 | M52: -2 | N52: 2 | O52: -2 | P52: -1 | Q52: -2 | R52: 2 | S52: 1 | T52: -2 | U52: 1 | V52: AUT | W52: Europe & Central Asia | X52: None | Y52: High Income | Z52: 0 | AA52: =IF(M52>0,1,IF(M52<0,0,-1)) -> 0 | AB52: =IF(N52>0,1,IF(N52<0,0,-1)) -> 1 | AC52: =IF(O52>0,1,IF(O52<0,0,-1)) -> 0 | AD52: =IF(P52>0,1,IF(P52<0,0,-1)) -> 0 | AE52: =IF(Q52>0,1,IF(Q52<0,0,-1)) -> 0 | AF52: =IF(R52>0,1,IF(R52<0,0,-1)) -> 1 | AG52: =IF(S52>0,1,IF(S52<0,0,-1)) -> 1 | AH52: =IF(T52>0,1,IF(T52<0,0,-1)) -> 0 | AI52: =IF(U52>0,1,IF(U52<0,0,-1)) -> 1 | AJ52: =IF(ISNUMBER(K52),K52,IF(OR(K52="general",K52="23;general"),"General",IF(OR(K52="exemption",K52="other (exemption)"),"Tax exemption/waiver/suspension","Other"))) -> Tax exemption/waiver/suspension | AK52: =IF(B52<>B51,1,0) -> 0 | AL52: 1
A53: 0 | B53: Austria | C53: 43886 | D53: 43906 | E53: 43970 | F53: =DATEDIF(D53,E53,"D") -> 64 | G53: 43906 | H53: 2020 | I53: 0 | J53: 1 | K53: 6 | L53: Applications can be made to reduce and/or not fix the advance payments of income or corporation tax for the fiscal year 2020, to refrain from setting additional interest, to defer and pay instalments, and to suspend deferred interest and late payments | M53: -2 | N53: 2 | O53: 2 | P53: 1 | Q53: 2 | R53: 2 | S53: 1 | U53: 1 | V53: AUT | W53: Europe & Central Asia | X53: None | Y53: High Income | Z53: 0 | AA53: =IF(M53>0,1,IF(M53<0,0,-1)) -> 0 | AB53: =IF(N53>0,1,IF(N53<0,0,-1)) -> 1 | AC53: =IF(O53>0,1,IF(O53<0,0,-1)) -> 1 | AD53: =IF(P53>0,1,IF(P53<0,0,-1)) -> 1 | AE53: =IF(Q53>0,1,IF(Q53<0,0,-1)) -> 1 | AF53: =IF(R53>0,1,IF(R53<0,0,-1)) -> 1 | AG53: =IF(S53>0,1,IF(S53<0,0,-1)) -> 1 | AH53: =IF(T53>0,1,IF(T53<0,0,-1)) -> -1 | AI53: =IF(U53>0,1,IF(U53<0,0,-1)) -> 1 | AJ53: =IF(ISNUMBER(K53),K53,IF(OR(K53="general",K53="23;general"),"General",IF(OR(K53="exemption",K53="other (exemption)"),"Tax exemption/waiver/suspension","Other"))) -> 6 | AK53: =IF(B53<>B52,1,0) -> 0 | AL53: 1
A54: 0 | B54: Austria | C54: 43886 | D54: 43906 | E54: 43970 | F54: =DATEDIF(D54,E54,"D") -> 64 | G54: 43906 | H54: 2020 | I54: 0 | J54: 1 | K54: 6 | L54: Case by case deferrals on VAT; payment dealing of June 30 extended | M54: 2 | N54: 2 | O54: -2 | P54: 1 | Q54: 2 | R54: 2 | S54: 1 | U54: 1 | V54: AUT | W54: Europe & Central Asia | X54: None | Y54: High Income | Z54: 0 | AA54: =IF(M54>0,1,IF(M54<0,0,-1)) -> 1 | AB54: =IF(N54>0,1,IF(N54<0,0,-1)) -> 1 | AC54: =IF(O54>0,1,IF(O54<0,0,-1)) -> 0 | AD54: =IF(P54>0,1,IF(P54<0,0,-1)) -> 1 | AE54: =IF(Q54>0,1,IF(Q54<0,0,-1)) -> 1 | AF54: =IF(R54>0,1,IF(R54<0,0,-1)) -> 1 | AG54: =IF(S54>0,1,IF(S54<0,0,-1)) -> 1 | AH54: =IF(T54>0,1,IF(T54<0,0,-1)) -> -1 | AI54: =IF(U54>0,1,IF(U54<0,0,-1)) -> 1 | AJ54: =IF(ISNUMBER(K54),K54,IF(OR(K54="general",K54="23;general"),"General",IF(OR(K54="exemption",K54="other (exemption)"),"Tax exemption/waiver/suspension","Other"))) -> 6 | AK54: =IF(B54<>B53,1,0) -> 0 | AL54: 1
A55: 0 | B55: Austria | C55: 43886 | D55: 43906 | E55: 43970 | F55: =DATEDIF(D55,E55,"D") -> 64 | G55: 43906 | H55: 2020 | I55: 0 | J55: 1 | K55: 6 | L55: The measures to protect businesses are also available for PIT-liable individuals | M55: -2 | N55: 2 | O55: 2 | P55: 1 | Q55: 2 | R55: 2 | S55: 1 | T55: 2 | U55: 1 | V55: AUT | W55: Europe & Central Asia | X55: None | Y55: High Income | Z55: 0 | AA55: =IF(M55>0,1,IF(M55<0,0,-1)) -> 0 | AB55: =IF(N55>0,1,IF(N55<0,0,-1)) -> 1 | AC55: =IF(O55>0,1,IF(O55<0,0,-1)) -> 1 | AD55: =IF(P55>0,1,IF(P55<0,0,-1)) -> 1 | AE55: =IF(Q55>0,1,IF(Q55<0,0,-1)) -> 1 | AF55: =IF(R55>0,1,IF(R55<0,0,-1)) -> 1 | AG55: =IF(S55>0,1,IF(S55<0,0,-1)) -> 1 | AH55: =IF(T55>0,1,IF(T55<0,0,-1)) -> 1 | AI55: =IF(U55>0,1,IF(U55<0,0,-1)) -> 1 | AJ55: =IF(ISNUMBER(K55),K55,IF(OR(K55="general",K55="23;general"),"General",IF(OR(K55="exemption",K55="other (exemption)"),"Tax exemption/waiver/suspension","Other"))) -> 6 | AK55: =IF(B55<>B54,1,0) -> 0 | AL55: 1
A56: 0 | B56: Austria | C56: 43886 | D56: 43906 | E56: 43970 | F56: =DATEDIF(D56,E56,"D") -> 64 | G56: 43906 | H56: 2020 | I56: 0 | J56: 1 | K56: 5 | L56: Filing deadlines for CIT as well as PIT, annual VAT and determination of income is extended until August 31, 2020. Interest for late tax return filing are automatically also waived. | M56: -2 | N56: 2 | O56: 2 | P56: 1 | Q56: 2 | R56: 2 | S56: 1 | T56: 1 | U56: 1 | V56: AUT | W56: Europe & Central Asia | X56: None | Y56: High Income | Z56: 0 | AA56: =IF(M56>0,1,IF(M56<0,0,-1)) -> 0 | AB56: =IF(N56>0,1,IF(N56<0,0,-1)) -> 1 | AC56: =IF(O56>0,1,IF(O56<0,0,-1)) -> 1 | AD56: =IF(P56>0,1,IF(P56<0,0,-1)) -> 1 | AE56: =IF(Q56>0,1,IF(Q56<0,0,-1)) -> 1 | AF56: =IF(R56>0,1,IF(R56<0,0,-1)) -> 1 | AG56: =IF(S56>0,1,IF(S56<0,0,-1)) -> 1 | AH56: =IF(T56>0,1,IF(T56<0,0,-1)) -> 1 | AI56: =IF(U56>0,1,IF(U56<0,0,-1)) -> 1 | AJ56: =IF(ISNUMBER(K56),K56,IF(OR(K56="general",K56="23;general"),"General",IF(OR(K56="exemption",K56="other (exemption)"),"Tax exemption/waiver/suspension","Other"))) -> 5 | AK56: =IF(B56<>B55,1,0) -> 0 | AL56: 1
A57: 0 | B57: Austria | C57: 43886 | D57: 43906 | E57: 43970 | F57: =DATEDIF(D57,E57,"D") -> 64 | G57: 43906 | H57: 2020 | I57: 0 | J57: 3 | K57: exemption | L57: The excise duty-free use of alcohol for the production of disinfectants is to be facilitated by simplifying procedures in order to make alcohol available tax-free. | M57: 1 | N57: 1 | O57: -2 | P57: -1 | Q57: -2 | R57: -2 | S57: -2 | U57: 1 | V57: AUT | W57: Europe & Central Asia | X57: None | Y57: High Income | Z57: 0 | AA57: =IF(M57>0,1,IF(M57<0,0,-1)) -> 1 | AB57: =IF(N57>0,1,IF(N57<0,0,-1)) -> 1 | AC57: =IF(O57>0,1,IF(O57<0,0,-1)) -> 0 | AD57: =IF(P57>0,1,IF(P57<0,0,-1)) -> 0 | AE57: =IF(Q57>0,1,IF(Q57<0,0,-1)) -> 0 | AF57: =IF(R57>0,1,IF(R57<0,0,-1)) -> 0 | AG57: =IF(S57>0,1,IF(S57<0,0,-1)) -> 0 | AH57: =IF(T57>0,1,IF(T57<0,0,-1)) -> -1 | AI57: =IF(U57>0,1,IF(U57<0,0,-1)) -> 1 | AJ57: =IF(ISNUMBER(K57),K57,IF(OR(K57="general",K57="23;general"),"General",IF(OR(K57="exemption",K57="other (exemption)"),"Tax exemption/waiver/suspension","Other"))) -> Tax exemption/waiver/suspension | AK57: =IF(B57<>B56,1,0) -> 0 | AL57: 1
A58: 0 | B58: Austria | C58: 43886 | D58: 43906 | E58: 43970 | F58: =DATEDIF(D58,E58,"D") -> 64 | G58: 43906 | H58: 2020 | I58: 0 | J58: 6 | K58: 29 | L58: Employees with care responsibilities for one or more children under the age of 14 can take up to 3 weeks of care leave (Sonderbetreuungszeit) with full wage replacement (1/3 of the salary will be reimbursed to the employer by the government) | M58: -2 | N58: 1 | O58: 2 | P58: -1 | Q58: -2 | R58: 1 | S58: 1 | T58: -2 | U58: 1 | V58: AUT | W58: Europe & Central Asia | X58: None | Y58: High Income | Z58: 0 | AA58: =IF(M58>0,1,IF(M58<0,0,-1)) -> 0 | AB58: =IF(N58>0,1,IF(N58<0,0,-1)) -> 1 | AC58: =IF(O58>0,1,IF(O58<0,0,-1)) -> 1 | AD58: =IF(P58>0,1,IF(P58<0,0,-1)) -> 0 | AE58: =IF(Q58>0,1,IF(Q58<0,0,-1)) -> 0 | AF58: =IF(R58>0,1,IF(R58<0,0,-1)) -> 1 | AG58: =IF(S58>0,1,IF(S58<0,0,-1)) -> 1 | AH58: =IF(T58>0,1,IF(T58<0,0,-1)) -> 0 | AI58: =IF(U58>0,1,IF(U58<0,0,-1)) -> 1 | AJ58: =IF(ISNUMBER(K58),K58,IF(OR(K58="general",K58="23;general"),"General",IF(OR(K58="exemption",K58="other (exemption)"),"Tax exemption/waiver/suspension","Other"))) -> 29 | AK58: =IF(B58<>B57,1,0) -> 0 | AL58: 1
A59: 0 | B59: Austria | C59: 43886 | D59: 43906 | E59: 43970 | F59: =DATEDIF(D59,E59,"D") -> 64 | G59: 43906 | H59: 2020 | I59: 0 | J59: 4 | K59: 20 | L59: Tax relief measures for the hospitality sector of € 500 million | V59: AUT | W59: Europe & Central Asia | X59: None | Y59: High Income | Z59: 0 | AA59: -1 | AB59: -1 | AC59: -1 | AD59: -1 | AE59: -1 | AF59: -1 | AG59: -1 | AH59: -1 | AI59: -1 | AJ59: =IF(ISNUMBER(K59),K59,IF(OR(K59="general",K59="23;general"),"General",IF(OR(K59="exemption",K59="other (exemption)"),"Tax exemption/waiver/suspension","Other"))) -> 20 | AK59: =IF(B59<>B58,1,0) -> 0 | AL59: 0
A60: 0 | B60: Austria | C60: 43886 | D60: 43906 | E60: 43970 | F60: =DATEDIF(D60,E60,"D") -> 64 | G60: 43906 | H60: 2020 | I60: 0 | J60: 9 | K60: 34 | L60: support to non-profit organizations of € 700 million open for 6 months | V60: AUT | W60: Europe & Central Asia | X60: None | Y60: High Income | Z60: 0 | AA60: -1 | AB60: -1 | AC60: -1 | AD60: -1 | AE60: -1 | AF60: -1 | AG60: -1 | AH60: -1 | AI60: -1 | AJ60: =IF(ISNUMBER(K60),K60,IF(OR(K60="general",K60="23;general"),"General",IF(OR(K60="exemption",K60="other (exemption)"),"Tax exemption/waiver/suspension","Other"))) -> 34 | AK60: =IF(B60<>B59,1,0) -> 0 | AL60: 0
A61: 0 | B61: Austria | C61: 43886 | D61: 43906 | E61: 43970 | F61: =DATEDIF(D61,E61,"D") -> 64 | G61: 43906 | H61: 2020 | I61: 0 | J61: 2 | K61: 16 | L61: To jump-start the economy, a new tax incentive was introduced for companies that recruit apprentices, with € 2,000 per position created during March 16 and October 31 of this year. | V61: AUT | W61: Europe & Central Asia | X61: None | Y61: High Income | Z61: 0 | AA61: -1 | AB61: -1 | AC61: -1 | AD61: -1 | AE61: -1 | AF61: -1 | AG61: -1 | AH61: -1 | AI61: -1 | AJ61: =IF(ISNUMBER(K61),K61,IF(OR(K61="general",K61="23;general"),"General",IF(OR(K61="exemption",K61="other (exemption)"),"Tax exemption/waiver/suspension","Other"))) -> 16 | AK61: =IF(B61<>B60,1,0) -> 0 | AL61: 0
A62: 0 | B62: Austria | C62: 43886 | D62: 43906 | E62: 43970 | F62: =DATEDIF(D62,E62,"D") -> 64 | G62: 43906 | H62: 2020 | I62: 0 | J62: 5 | K62: general | L62: Expenditure: Government investment in climate protection | V62: AUT | W62: Europe & Central Asia | X62: None | Y62: High Income | Z62: 0 | AA62: -1 | AB62: -1 | AC62: -1 | AD62: -1 | AE62: -1 | AF62: -1 | AG62: -1 | AH62: -1 | AI62: -1 | AJ62: =IF(ISNUMBER(K62),K62,IF(OR(K62="general",K62="23;general"),"General",IF(OR(K62="exemption",K62="other (exemption)"),"Tax exemption/waiver/suspension","Other"))) -> General | AK62: =IF(B62<>B61,1,0) -> 0 | AL62: 0
A63: 0 | B63: Austria | C63: 43886 | D63: 43906 | E63: 43970 | F63: =DATEDIF(D63,E63,"D") -> 64 | G63: 43906 | H63: 2020 | I63: 0 | J63: 6 | K63: 28 | L63: Expenditure: Government investment in affordable housing | V63: AUT | W63: Europe & Central Asia | X63: None | Y63: High Income | Z63: 0 | AA63: -1 | AB63: -1 | AC63: -1 | AD63: -1 | AE63: -1 | AF63: -1 | AG63: -1 | AH63: -1 | AI63: -1 | AJ63: =IF(ISNUMBER(K63),K63,IF(OR(K63="general",K63="23;general"),"General",IF(OR(K63="exemption",K63="other (exemption)"),"Tax exemption/waiver/suspension","Other"))) -> 28 | AK63: =IF(B63<>B62,1,0) -> 0 | AL63: 0
A64: 0 | B64: Austria | C64: 43886 | D64: 43906 | E64: 43970 | F64: =DATEDIF(D64,E64,"D") -> 64 | G64: 43906 | H64: 2020 | I64: 0 | J64: 5 | K64: general | L64: Expenditure: Investment in health | V64: AUT | W64: Europe & Central Asia | X64: None | Y64: High Income | Z64: 0 | AA64: -1 | AB64: -1 | AC64: -1 | AD64: -1 | AE64: -1 | AF64: -1 | AG64: -1 | AH64: -1 | AI64: -1 | AJ64: =IF(ISNUMBER(K64),K64,IF(OR(K64="general",K64="23;general"),"General",IF(OR(K64="exemption",K64="other (exemption)"),"Tax exemption/waiver/suspension","Other"))) -> General | AK64: =IF(B64<>B63,1,0) -> 0 | AL64: 0
A65: 0 | B65: Austria | C65: 43886 | D65: 43906 | E65: 43970 | F65: =DATEDIF(D65,E65,"D") -> 64 | G65: 43906 | H65: 2020 | I65: 0 | J65: 6 | K65: 25 | L65: Expenditure: one-off support for unemployed and families. | V65: AUT | W65: Europe & Central Asia | X65: None | Y65: High Income | Z65: 0 | AA65: -1 | AB65: -1 | AC65: -1 | AD65: -1 | AE65: -1 | AF65: -1 | AG65: -1 | AH65: -1 | AI65: -1 | AJ65: =IF(ISNUMBER(K65),K65,IF(OR(K65="general",K65="23;general"),"General",IF(OR(K65="exemption",K65="other (exemption)"),"Tax exemption/waiver/suspension","Other"))) -> 25 | AK65: =IF(B65<>B64,1,0) -> 0 | AL65: 0
A66: 0 | B66: Austria | C66: 43886 | D66: 43906 | E66: 43970 | F66: =DATEDIF(D66,E66,"D") -> 64 | G66: 43906 | H66: 2020 | I66: 0 | J66: 4 | K66: 20 | L66: Several specific tax relief measures are aimed at the agricultural and forestry sectors, culture and publishing. | V66: AUT | W66: Europe & Central Asia | X66: None | Y66: High Income | Z66: 0 | AA66: -1 | AB66: -1 | AC66: -1 | AD66: -1 | AE66: -1 | AF66: -1 | AG66: -1 | AH66: -1 | AI66: -1 | AJ66: =IF(ISNUMBER(K66),K66,IF(OR(K66="general",K66="23;general"),"General",IF(OR(K66="exemption",K66="other (exemption)"),"Tax exemption/waiver/suspension","Other"))) -> 20 | AK66: =IF(B66<>B65,1,0) -> 0 | AL66: 0
A67: 0 | B67: Austria | C67: 43886 | D67: 43906 | E67: 43970 | F67: =DATEDIF(D67,E67,"D") -> 64 | G67: 43906 | H67: 2020 | I67: 0 | J67: 2 | K67: 15 | L67: The reduction of the lowest income tax rate from 25 to 20 percent, planned for 2021, was brought forward and made retroactive to January 2020. | V67: AUT | W67: Europe & Central Asia | X67: None | Y67: High Income | Z67: 0 | AA67: -1 | AB67: -1 | AC67: -1 | AD67: -1 | AE67: -1 | AF67: -1 | AG67: -1 | AH67: -1 | AI67: -1 | AJ67: =IF(ISNUMBER(K67),K67,IF(OR(K67="general",K67="23;general"),"General",IF(OR(K67="exemption",K67="other (exemption)"),"Tax exemption/waiver/suspension","Other"))) -> 15 | AK67: =IF(B67<>B66,1,0) -> 0 | AL67: 0
A68: 0 | B68: Austria | C68: 43886 | D68: 43906 | E68: 43970 | F68: =DATEDIF(D68,E68,"D") -> 64 | G68: 43906 | H68: 2020 | I68: 0 | J68: 1 | K68: 9 | L68: Easy repayment of tax credits (as the VAT cash refund in the case study) | V68: AUT | W68: Europe & Central Asia | X68: None | Y68: High Income | Z68: 0 | AA68: -1 | AB68: -1 | AC68: -1 | AD68: -1 | AE68: -1 | AF68: -1 | AG68: -1 | AH68: -1 | AI68: -1 | AJ68: =IF(ISNUMBER(K68),K68,IF(OR(K68="general",K68="23;general"),"General",IF(OR(K68="exemption",K68="other (exemption)"),"Tax exemption/waiver/suspension","Other"))) -> 9 | AK68: =IF(B68<>B67,1,0) -> 0 | AL68: 0
A69: 0 | B69: Austria | C69: 43886 | D69: 43906 | E69: 43970 | F69: =DATEDIF(D69,E69,"D") -> 64 | G69: 43906 | H69: 2020 | I69: 0 | J69: 1 | K69: 6 | L69: General moratorium for social contributions which will be due from April to June | V69: AUT | W69: Europe & Central Asia | X69: None | Y69: High Income | Z69: 0 | AA69: -1 | AB69: -1 | AC69: -1 | AD69: -1 | AE69: -1 | AF69: -1 | AG69: -1 | AH69: -1 | AI69: -1 | AJ69: =IF(ISNUMBER(K69),K69,IF(OR(K69="general",K69="23;general"),"General",IF(OR(K69="exemption",K69="other (exemption)"),"Tax exemption/waiver/suspension","Other"))) -> 6 | AK69: =IF(B69<>B68,1,0) -> 0 | AL69: 0
A70: 0 | B70: Austria | C70: 43886 | D70: 43906 | E70: 43970 | F70: =DATEDIF(D70,E70,"D") -> 64 | G70: 43906 | H70: 2020 | I70: 0 | J70: 1 | K70: 12 | L70: Abandonment of all tax audits | V70: AUT | W70: Europe & Central Asia | X70: None | Y70: High Income | Z70: 0 | AA70: -1 | AB70: -1 | AC70: -1 | AD70: -1 | AE70: -1 | AF70: -1 | AG70: -1 | AH70: -1 | AI70: -1 | AJ70: =IF(ISNUMBER(K70),K70,IF(OR(K70="general",K70="23;general"),"General",IF(OR(K70="exemption",K70="other (exemption)"),"Tax exemption/waiver/suspension","Other"))) -> 12 | AK70: =IF(B70<>B69,1,0) -> 0 | AL70: 0
A71: 0 | B71: Austria | C71: 43886 | D71: 43906 | E71: 43970 | F71: =DATEDIF(D71,E71,"D") -> 64 | G71: 43906 | H71: 2020 | I71: 0 | J71: 1 | K71: 11 | L71: Prolongation of publication of (audited) financial statements from September to the end of December 2020. | V71: AUT | W71: Europe & Central Asia | X71: None | Y71: High Income | Z71: 0 | AA71: -1 | AB71: -1 | AC71: -1 | AD71: -1 | AE71: -1 | AF71: -1 | AG71: -1 | AH71: -1 | AI71: -1 | AJ71: =IF(ISNUMBER(K71),K71,IF(OR(K71="general",K71="23;general"),"General",IF(OR(K71="exemption",K71="other (exemption)"),"Tax exemption/waiver/suspension","Other"))) -> 11 | AK71: =IF(B71<>B70,1,0) -> 0 | AL71: 0
A72: 0 | B72: Austria | C72: 43886 | D72: 43906 | E72: 43970 | F72: =DATEDIF(D72,E72,"D") -> 64 | G72: 43906 | H72: 2020 | I72: 0 | J72: 1 | K72: 11 | L72: Prolongation of preparation of the financial statement from May to end of September. | V72: AUT | W72: Europe & Central Asia | X72: None | Y72: High Income | Z72: 0 | AA72: -1 | AB72: -1 | AC72: -1 | AD72: -1 | AE72: -1 | AF72: -1 | AG72: -1 | AH72: -1 | AI72: -1 | AJ72: =IF(ISNUMBER(K72),K72,IF(OR(K72="general",K72="23;general"),"General",IF(OR(K72="exemption",K72="other (exemption)"),"Tax exemption/waiver/suspension","Other"))) -> 11 | AK72: =IF(B72<>B71,1,0) -> 0 | AL72: 0
A73: 0 | B73: Austria | C73: 43886 | D73: 43906 | E73: 43970 | F73: =DATEDIF(D73,E73,"D") -> 64 | G73: 43906 | H73: 2020 | I73: 0 | J73: 4 | K73: 20 | L73: Introduction of a reduced VAT rate of 5% for the catering, tourism and cultural sector. This tax reduction will apply from 1 July 2020 to 31 December 2020 | V73: AUT | W73: Europe & Central Asia | X73: None | Y73: High Income | Z73: 0 | AA73: -1 | AB73: -1 | AC73: -1 | AD73: -1 | AE73: -1 | AF73: -1 | AG73: -1 | AH73: -1 | AI73: -1 | AJ73: =IF(ISNUMBER(K73),K73,IF(OR(K73="general",K73="23;general"),"General",IF(OR(K73="exemption",K73="other (exemption)"),"Tax exemption/waiver/suspension","Other"))) -> 20 | AK73: =IF(B73<>B72,1,0) -> 0 | AL73: 0
A74: 0 | B74: Austria | C74: 43886 | D74: 43906 | E74: 43970 | F74: =DATEDIF(D74,E74,"D") -> 64 | G74: 43906 | H74: 2020 | I74: 0 | J74: 1 | K74: 4 | L74: The Government will make advance payments on credit installments in order to help companies to have sufficient liquidities | V74: AUT | W74: Europe & Central Asia | X74: None | Y74: High Income | Z74: 0 | AA74: -1 | AB74: -1 | AC74: -1 | AD74: -1 | AE74: -1 | AF74: -1 | AG74: -1 | AH74: -1 | AI74: -1 | AJ74: =IF(ISNUMBER(K74),K74,IF(OR(K74="general",K74="23;general"),"General",IF(OR(K74="exemption",K74="other (exemption)"),"Tax exemption/waiver/suspension","Other"))) -> 4 | AK74: =IF(B74<>B73,1,0) -> 0 | AL74: 0
A75: 0 | B75: Austria | C75: 43886 | D75: 43906 | E75: 43970 | F75: =DATEDIF(D75,E75,"D") -> 64 | G75: 43906 | H75: 2020 | I75: 0 | J75: 1 | K75: 6 | L75: Additional tax payment deferal extension for businesses until January 15th, 2021 | V75: AUT | W75: Europe & Central Asia | X75: None | Y75: High Income | Z75: 0 | AA75: -1 | AB75: -1 | AC75: -1 | AD75: -1 | AE75: -1 | AF75: -1 | AG75: -1 | AH75: -1 | AI75: -1 | AJ75: =IF(ISNUMBER(K75),K75,IF(OR(K75="general",K75="23;general"),"General",IF(OR(K75="exemption",K75="other (exemption)"),"Tax exemption/waiver/suspension","Other"))) -> 6 | AK75: =IF(B75<>B74,1,0) -> 0 | AL75: 0
A76: 0 | B76: Austria | C76: 43886 | D76: 43906 | E76: 43970 | F76: =DATEDIF(D76,E76,"D") -> 64 | G76: 43906 | H76: 2020 | I76: 0 | J76: 7 | K76: 31 | L76: Further EUR 36 million are disbursed through an emergency-call for research by the Austrian Research Promotion Agency (FFG) to incentivize eligible research on Covid-19 by Austrian firms. | V76: AUT | W76: Europe & Central Asia | X76: None | Y76: High Income | Z76: 0 | AA76: -1 | AB76: -1 | AC76: -1 | AD76: -1 | AE76: -1 | AF76: -1 | AG76: -1 | AH76: -1 | AI76: -1 | AJ76: =IF(ISNUMBER(K76),K76,IF(OR(K76="general",K76="23;general"),"General",IF(OR(K76="exemption",K76="other (exemption)"),"Tax exemption/waiver/suspension","Other"))) -> 31 | AK76: =IF(B76<>B75,1,0) -> 0 | AL76: 0
A77: 0 | B77: Austria | C77: 43886 | D77: 43906 | E77: 43970 | F77: =DATEDIF(D77,E77,"D") -> 64 | G77: 43906 | H77: 2020 | I77: 0 | J77: 5 | K77: 21 | L77: the government has spent around EUR 13 million on medical supplies | V77: AUT | W77: Europe & Central Asia | X77: None | Y77: High Income | Z77: 0 | AA77: -1 | AB77: -1 | AC77: -1 | AD77: -1 | AE77: -1 | AF77: -1 | AG77: -1 | AH77: -1 | AI77: -1 | AJ77: =IF(ISNUMBER(K77),K77,IF(OR(K77="general",K77="23;general"),"General",IF(OR(K77="exemption",K77="other (exemption)"),"Tax exemption/waiver/suspension","Other"))) -> 21 | AK77: =IF(B77<>B76,1,0) -> 0 | AL77: 0
A78: 0 | B78: Austria | C78: 43886 | D78: 43906 | E78: 43970 | F78: =DATEDIF(D78,E78,"D") -> 64 | G78: 43906 | H78: 2020 | I78: 0 | J78: 5 | K78: general | L78: The government has spent around EUR 10 million to support the care-taking system. | V78: AUT | W78: Europe & Central Asia | X78: None | Y78: High Income | Z78: 0 | AA78: -1 | AB78: -1 | AC78: -1 | AD78: -1 | AE78: -1 | AF78: -1 | AG78: -1 | AH78: -1 | AI78: -1 | AJ78: =IF(ISNUMBER(K78),K78,IF(OR(K78="general",K78="23;general"),"General",IF(OR(K78="exemption",K78="other (exemption)"),"Tax exemption/waiver/suspension","Other"))) -> General | AK78: =IF(B78<>B77,1,0) -> 0 | AL78: 0
A79: 0 | B79: Austria | C79: 43886 | D79: 43906 | E79: 43970 | F79: =DATEDIF(D79,E79,"D") -> 64 | G79: 43906 | H79: 2021 | I79: 0 | J79: 9 | K79: 34 | L79: 16.12.2020 – Verlustersatz (Deckung fuer Verluste; spaeter Verlustersatz II fuer Juli–Dez 2021). 03.11.2020 – Lockdown-Umsatzersatz (spaeter Lockdown-Umsatzersatz II als Folgeregelung).
A80: 0 | B80: Austria | C80: 43886 | D80: 43906 | E80: 43970 | F80: =DATEDIF(D80,E80,"D") -> 64 | G80: 43906 | H80: 2021 | I80: 0 | J80: 7 | K80: 31 | L80: Schutzschirm fuer Veranstaltungen (Absicherungen bei COVID-bedingter Absage/Einschraenkung; Schutzschirm II ab 07/2021).
A81: 0 | B81: Belgium | C81: 43865 | D81: 43908 | E81: 43962 | F81: =DATEDIF(D81,E81,"D") -> 54 | G81: 43914 | H81: 2020 | I81: 0 | J81: 2 | K81: exemption | L81: Exemption from income tax of direct aid granted by the Regions to taxpayers (SMEs, self-employed workers and childcare providers) in order to limit the impact of the COVID. | M81: 2 | N81: 2 | O81: 2 | P81: -1 | Q81: 2 | R81: 2 | S81: -2 | T81: -2 | U81: 1 | V81: BEL | W81: Europe & Central Asia | X81: None | Y81: High Income | Z81: 0 | AA81: =IF(M81>0,1,IF(M81<0,0,-1)) -> 1 | AB81: =IF(N81>0,1,IF(N81<0,0,-1)) -> 1 | AC81: =IF(O81>0,1,IF(O81<0,0,-1)) -> 1 | AD81: =IF(P81>0,1,IF(P81<0,0,-1)) -> 0 | AE81: =IF(Q81>0,1,IF(Q81<0,0,-1)) -> 1 | AF81: =IF(R81>0,1,IF(R81<0,0,-1)) -> 1 | AG81: =IF(S81>0,1,IF(S81<0,0,-1)) -> 0 | AH81: =IF(T81>0,1,IF(T81<0,0,-1)) -> 0 | AI81: =IF(U81>0,1,IF(U81<0,0,-1)) -> 1 | AJ81: =IF(ISNUMBER(K81),K81,IF(OR(K81="general",K81="23;general"),"General",IF(OR(K81="exemption",K81="other (exemption)"),"Tax exemption/waiver/suspension","Other"))) -> Tax exemption/waiver/suspension | AK81: =IF(B81<>#REF!,1,0) -> #REF! | AL81: 1
A82: 0 | B82: Belgium | C82: 43865 | D82: 43908 | E82: 43962 | F82: =DATEDIF(D82,E82,"D") -> 54 | G82: 43914 | H82: 2020 | I82: 0 | J82: 6 | K82: 29 | L82: Exceptional holidays granted in return for days worked between 13 March 2020 and 30 June 2020. | M82: -1 | N82: 1 | O82: -2 | P82: -1 | Q82: 1 | R82: 1 | S82: 1 | T82: 2 | U82: 1 | V82: BEL | W82: Europe & Central Asia | X82: None | Y82: High Income | Z82: 0 | AA82: =IF(M82>0,1,IF(M82<0,0,-1)) -> 0 | AB82: =IF(N82>0,1,IF(N82<0,0,-1)) -> 1 | AC82: =IF(O82>0,1,IF(O82<0,0,-1)) -> 0 | AD82: =IF(P82>0,1,IF(P82<0,0,-1)) -> 0 | AE82: =IF(Q82>0,1,IF(Q82<0,0,-1)) -> 1 | AF82: =IF(R82>0,1,IF(R82<0,0,-1)) -> 1 | AG82: =IF(S82>0,1,IF(S82<0,0,-1)) -> 1 | AH82: =IF(T82>0,1,IF(T82<0,0,-1)) -> 1 | AI82: =IF(U82>0,1,IF(U82<0,0,-1)) -> 1 | AJ82: =IF(ISNUMBER(K82),K82,IF(OR(K82="general",K82="23;general"),"General",IF(OR(K82="exemption",K82="other (exemption)"),"Tax exemption/waiver/suspension","Other"))) -> 29 | AK82: =IF(B82<>B81,1,0) -> 0 | AL82: 1
A83: 0 | B83: Belgium | C83: 43865 | D83: 43908 | E83: 43962 | F83: =DATEDIF(D83,E83,"D") -> 54 | G83: 43914 | H83: 2020 | I83: 0 | J83: 3 | K83: exemption | L83: Temporary measures to allow VAT-free gifts of medical equipment to specified healthcare institutions (no VAT liability; no impact on right for donor to recover associated input VAT). | M83: 1 | N83: 2 | O83: -2 | P83: -1 | Q83: -2 | R83: 2 | S83: 2 | U83: 1 | V83: BEL | W83: Europe & Central Asia | X83: None | Y83: High Income | Z83: 0 | AA83: =IF(M83>0,1,IF(M83<0,0,-1)) -> 1 | AB83: =IF(N83>0,1,IF(N83<0,0,-1)) -> 1 | AC83: =IF(O83>0,1,IF(O83<0,0,-1)) -> 0 | AD83: =IF(P83>0,1,IF(P83<0,0,-1)) -> 0 | AE83: =IF(Q83>0,1,IF(Q83<0,0,-1)) -> 0 | AF83: =IF(R83>0,1,IF(R83<0,0,-1)) -> 1 | AG83: =IF(S83>0,1,IF(S83<0,0,-1)) -> 1 | AH83: =IF(T83>0,1,IF(T83<0,0,-1)) -> -1 | AI83: =IF(U83>0,1,IF(U83<0,0,-1)) -> 1 | AJ83: =IF(ISNUMBER(K83),K83,IF(OR(K83="general",K83="23;general"),"General",IF(OR(K83="exemption",K83="other (exemption)"),"Tax exemption/waiver/suspension","Other"))) -> Tax exemption/waiver/suspension | AK83: =IF(B83<>B82,1,0) -> 0 | AL83: 1
A84: 0 | B84: Belgium | C84: 43865 | D84: 43908 | E84: 43962 | F84: =DATEDIF(D84,E84,"D") -> 54 | G84: 43914 | H84: 2020 | I84: 0 | J84: 1 | K84: 8 | L84: Additional measures to delay or cancel payments of tax arrears linked to the COVID-19 crisis. In certain cases, no late-payment interest will be due and penalties for not paying taxes will be waived. | M84: 2 | N84: 2 | O84: -2 | P84: -1 | Q84: -2 | R84: -2 | S84: -2 | T84: 2 | U84: 1 | V84: BEL | W84: Europe & Central Asia | X84: None | Y84: High Income | Z84: 0 | AA84: =IF(M84>0,1,IF(M84<0,0,-1)) -> 1 | AB84: =IF(N84>0,1,IF(N84<0,0,-1)) -> 1 | AC84: =IF(O84>0,1,IF(O84<0,0,-1)) -> 0 | AD84: =IF(P84>0,1,IF(P84<0,0,-1)) -> 0 | AE84: =IF(Q84>0,1,IF(Q84<0,0,-1)) -> 0 | AF84: =IF(R84>0,1,IF(R84<0,0,-1)) -> 0 | AG84: =IF(S84>0,1,IF(S84<0,0,-1)) -> 0 | AH84: =IF(T84>0,1,IF(T84<0,0,-1)) -> 1 | AI84: =IF(U84>0,1,IF(U84<0,0,-1)) -> 1 | AJ84: =IF(ISNUMBER(K84),K84,IF(OR(K84="general",K84="23;general"),"General",IF(OR(K84="exemption",K84="other (exemption)"),"Tax exemption/waiver/suspension","Other"))) -> 8 | AK84: =IF(B84<>B83,1,0) -> 0 | AL84: 1
A85: 0 | B85: Belgium | C85: 43865 | D85: 43908 | E85: 43962 | F85: =DATEDIF(D85,E85,"D") -> 54 | G85: 43914 | H85: 2020 | I85: 0 | J85: 3 | K85: exemption | L85: Payment period for excise and VAT on the import of medical alcohol has been extended from 1 to 4 weeks. | M85: 2 | N85: 2 | O85: 2 | P85: 2 | Q85: 2 | R85: 1 | S85: 2 | T85: 2 | U85: 1 | V85: BEL | W85: Europe & Central Asia | X85: None | Y85: High Income | Z85: 0 | AA85: =IF(M85>0,1,IF(M85<0,0,-1)) -> 1 | AB85: =IF(N85>0,1,IF(N85<0,0,-1)) -> 1 | AC85: =IF(O85>0,1,IF(O85<0,0,-1)) -> 1 | AD85: =IF(P85>0,1,IF(P85<0,0,-1)) -> 1 | AE85: =IF(Q85>0,1,IF(Q85<0,0,-1)) -> 1 | AF85: =IF(R85>0,1,IF(R85<0,0,-1)) -> 1 | AG85: =IF(S85>0,1,IF(S85<0,0,-1)) -> 1 | AH85: =IF(T85>0,1,IF(T85<0,0,-1)) -> 1 | AI85: =IF(U85>0,1,IF(U85<0,0,-1)) -> 1 | AJ85: =IF(ISNUMBER(K85),K85,IF(OR(K85="general",K85="23;general"),"General",IF(OR(K85="exemption",K85="other (exemption)"),"Tax exemption/waiver/suspension","Other"))) -> Tax exemption/waiver/suspension | AK85: =IF(B85<>B84,1,0) -> 0 | AL85: 1
A86: 0 | B86: Belgium | C86: 43865 | D86: 43908 | E86: 43962 | F86: =DATEDIF(D86,E86,"D") -> 54 | G86: 43914 | H86: 2020 | I86: 0 | J86: 1 | K86: 7 | L86: Local governments committed to freeze local taxes. | M86: -1 | N86: -1 | R86: -1 | U86: 1 | V86: BEL | W86: Europe & Central Asia | X86: None | Y86: High Income | Z86: 0 | AA86: =IF(M86>0,1,IF(M86<0,0,-1)) -> 0 | AB86: =IF(N86>0,1,IF(N86<0,0,-1)) -> 0 | AC86: =IF(O86>0,1,IF(O86<0,0,-1)) -> -1 | AD86: =IF(P86>0,1,IF(P86<0,0,-1)) -> -1 | AE86: =IF(Q86>0,1,IF(Q86<0,0,-1)) -> -1 | AF86: =IF(R86>0,1,IF(R86<0,0,-1)) -> 0 | AG86: =IF(S86>0,1,IF(S86<0,0,-1)) -> -1 | AH86: =IF(T86>0,1,IF(T86<0,0,-1)) -> -1 | AI86: =IF(U86>0,1,IF(U86<0,0,-1)) -> 1 | AJ86: =IF(ISNUMBER(K86),K86,IF(OR(K86="general",K86="23;general"),"General",IF(OR(K86="exemption",K86="other (exemption)"),"Tax exemption/waiver/suspension","Other"))) -> 7 | AK86: =IF(B86<>B85,1,0) -> 0 | AL86: 1
A87: 0 | B87: Belgium | C87: 43865 | D87: 43908 | E87: 43962 | F87: =DATEDIF(D87,E87,"D") -> 54 | G87: 43914 | H87: 2020 | I87: 0 | J87: 2 | K87: exemption | L87: Salary supplements linked to temporary home-based work can be requested to be exempt from income taxation for the period of the COVID-19 crisis. | M87: -2 | N87: 2 | O87: -2 | P87: -1 | Q87: -2 | R87: 2 | S87: -2 | T87: -2 | U87: 1 | V87: BEL | W87: Europe & Central Asia | X87: None | Y87: High Income | Z87: 0 | AA87: =IF(M87>0,1,IF(M87<0,0,-1)) -> 0 | AB87: =IF(N87>0,1,IF(N87<0,0,-1)) -> 1 | AC87: =IF(O87>0,1,IF(O87<0,0,-1)) -> 0 | AD87: =IF(P87>0,1,IF(P87<0,0,-1)) -> 0 | AE87: =IF(Q87>0,1,IF(Q87<0,0,-1)) -> 0 | AF87: =IF(R87>0,1,IF(R87<0,0,-1)) -> 1 | AG87: =IF(S87>0,1,IF(S87<0,0,-1)) -> 0 | AH87: =IF(T87>0,1,IF(T87<0,0,-1)) -> 0 | AI87: =IF(U87>0,1,IF(U87<0,0,-1)) -> 1 | AJ87: =IF(ISNUMBER(K87),K87,IF(OR(K87="general",K87="23;general"),"General",IF(OR(K87="exemption",K87="other (exemption)"),"Tax exemption/waiver/suspension","Other"))) -> Tax exemption/waiver/suspension | AK87: =IF(B87<>B86,1,0) -> 0 | AL87: 1
A88: 0 | B88: Belgium | C88: 43865 | D88: 43908 | E88: 43962 | F88: =DATEDIF(D88,E88,"D") -> 54 | G88: 43914 | H88: 2020 | I88: 0 | J88: 1 | K88: 6 | L88: SSCs due in Q1 and Q2 can be postponed and/or paid in instalments if requested | M88: -1 | N88: 2 | O88: 2 | P88: 2 | Q88: 2 | R88: 2 | S88: 1 | T88: 1 | U88: 1 | V88: BEL | W88: Europe & Central Asia | X88: None | Y88: High Income | Z88: 0 | AA88: =IF(M88>0,1,IF(M88<0,0,-1)) -> 0 | AB88: =IF(N88>0,1,IF(N88<0,0,-1)) -> 1 | AC88: =IF(O88>0,1,IF(O88<0,0,-1)) -> 1 | AD88: =IF(P88>0,1,IF(P88<0,0,-1)) -> 1 | AE88: =IF(Q88>0,1,IF(Q88<0,0,-1)) -> 1 | AF88: =IF(R88>0,1,IF(R88<0,0,-1)) -> 1 | AG88: =IF(S88>0,1,IF(S88<0,0,-1)) -> 1 | AH88: =IF(T88>0,1,IF(T88<0,0,-1)) -> 1 | AI88: =IF(U88>0,1,IF(U88<0,0,-1)) -> 1 | AJ88: =IF(ISNUMBER(K88),K88,IF(OR(K88="general",K88="23;general"),"General",IF(OR(K88="exemption",K88="other (exemption)"),"Tax exemption/waiver/suspension","Other"))) -> 6 | AK88: =IF(B88<>B87,1,0) -> 0 | AL88: 1
A89: 0 | B89: Belgium | C89: 43865 | D89: 43908 | E89: 43962 | F89: =DATEDIF(D89,E89,"D") -> 54 | G89: 43914 | H89: 2020 | I89: 0 | J89: 6 | K89: 28 | L89: Extension of the seasonal suspension of evictions from dwellings (la trêve hivernale). | M89: 1 | N89: 2 | O89: 1 | Q89: -2 | R89: 1 | S89: 1 | T89: 1 | U89: 1 | V89: BEL | W89: Europe & Central Asia | X89: None | Y89: High Income | Z89: 0 | AA89: =IF(M89>0,1,IF(M89<0,0,-1)) -> 1 | AB89: =IF(N89>0,1,IF(N89<0,0,-1)) -> 1 | AC89: =IF(O89>0,1,IF(O89<0,0,-1)) -> 1 | AD89: =IF(P89>0,1,IF(P89<0,0,-1)) -> -1 | AE89: =IF(Q89>0,1,IF(Q89<0,0,-1)) -> 0 | AF89: =IF(R89>0,1,IF(R89<0,0,-1)) -> 1 | AG89: =IF(S89>0,1,IF(S89<0,0,-1)) -> 1 | AH89: =IF(T89>0,1,IF(T89<0,0,-1)) -> 1 | AI89: =IF(U89>0,1,IF(U89<0,0,-1)) -> 1 | AJ89: =IF(ISNUMBER(K89),K89,IF(OR(K89="general",K89="23;general"),"General",IF(OR(K89="exemption",K89="other (exemption)"),"Tax exemption/waiver/suspension","Other"))) -> 28 | AK89: =IF(B89<>B88,1,0) -> 0 | AL89: 1
A90: 0 | B90: Belgium | C90: 43865 | D90: 43908 | E90: 43962 | F90: =DATEDIF(D90,E90,"D") -> 54 | G90: 43914 | H90: 2020 | I90: 0 | J90: 3 | K90: exemption | L90: Extraordinary costs linked to the temporary production of medical equipment can be deducted in the income tax regime. | M90: 2 | N90: 2 | O90: -2 | P90: -2 | Q90: 2 | R90: 2 | S90: -2 | T90: -2 | U90: 1 | V90: BEL | W90: Europe & Central Asia | X90: None | Y90: High Income | Z90: 0 | AA90: =IF(M90>0,1,IF(M90<0,0,-1)) -> 1 | AB90: =IF(N90>0,1,IF(N90<0,0,-1)) -> 1 | AC90: =IF(O90>0,1,IF(O90<0,0,-1)) -> 0 | AD90: =IF(P90>0,1,IF(P90<0,0,-1)) -> 0 | AE90: =IF(Q90>0,1,IF(Q90<0,0,-1)) -> 1 | AF90: =IF(R90>0,1,IF(R90<0,0,-1)) -> 1 | AG90: =IF(S90>0,1,IF(S90<0,0,-1)) -> 0 | AH90: =IF(T90>0,1,IF(T90<0,0,-1)) -> 0 | AI90: =IF(U90>0,1,IF(U90<0,0,-1)) -> 1 | AJ90: =IF(ISNUMBER(K90),K90,IF(OR(K90="general",K90="23;general"),"General",IF(OR(K90="exemption",K90="other (exemption)"),"Tax exemption/waiver/suspension","Other"))) -> Tax exemption/waiver/suspension | AK90: =IF(B90<>B89,1,0) -> 0 | AL90: 1
A91: 0 | B91: Belgium | C91: 43865 | D91: 43908 | E91: 43962 | F91: =DATEDIF(D91,E91,"D") -> 54 | G91: 43914 | H91: 2020 | I91: 0 | J91: 1 | K91: 10 | L91: Reduced advance tax payment rates for self-employed persons and companies to mitigate the effects of the COVID-19 pandemic. | M91: -2 | N91: 2 | O91: 2 | P91: 2 | Q91: 2 | R91: -2 | S91: 2 | T91: 2 | U91: 1 | V91: BEL | W91: Europe & Central Asia | X91: None | Y91: High Income | Z91: 0 | AA91: =IF(M91>0,1,IF(M91<0,0,-1)) -> 0 | AB91: =IF(N91>0,1,IF(N91<0,0,-1)) -> 1 | AC91: =IF(O91>0,1,IF(O91<0,0,-1)) -> 1 | AD91: =IF(P91>0,1,IF(P91<0,0,-1)) -> 1 | AE91: =IF(Q91>0,1,IF(Q91<0,0,-1)) -> 1 | AF91: =IF(R91>0,1,IF(R91<0,0,-1)) -> 0 | AG91: =IF(S91>0,1,IF(S91<0,0,-1)) -> 1 | AH91: =IF(T91>0,1,IF(T91<0,0,-1)) -> 1 | AI91: =IF(U91>0,1,IF(U91<0,0,-1)) -> 1 | AJ91: =IF(ISNUMBER(K91),K91,IF(OR(K91="general",K91="23;general"),"General",IF(OR(K91="exemption",K91="other (exemption)"),"Tax exemption/waiver/suspension","Other"))) -> 10 | AK91: =IF(B91<>B90,1,0) -> 0 | AL91: 1
A92: 0 | B92: Belgium | C92: 43865 | D92: 43908 | E92: 43962 | F92: =DATEDIF(D92,E92,"D") -> 54 | G92: 43914 | H92: 2020 | I92: 0 | J92: 1 | K92: other | L92: No penalties will be imposed by the government for delays in the execution or the cancellation of government contracts related to the COVID-19 crisis. | M92: -1 | N92: 2 | O92: -2 | P92: -1 | Q92: -2 | R92: 2 | S92: -2 | T92: 2 | U92: 1 | V92: BEL | W92: Europe & Central Asia | X92: None | Y92: High Income | Z92: 0 | AA92: =IF(M92>0,1,IF(M92<0,0,-1)) -> 0 | AB92: =IF(N92>0,1,IF(N92<0,0,-1)) -> 1 | AC92: =IF(O92>0,1,IF(O92<0,0,-1)) -> 0 | AD92: =IF(P92>0,1,IF(P92<0,0,-1)) -> 0 | AE92: =IF(Q92>0,1,IF(Q92<0,0,-1)) -> 0 | AF92: =IF(R92>0,1,IF(R92<0,0,-1)) -> 1 | AG92: =IF(S92>0,1,IF(S92<0,0,-1)) -> 0 | AH92: =IF(T92>0,1,IF(T92<0,0,-1)) -> 1 | AI92: =IF(U92>0,1,IF(U92<0,0,-1)) -> 1 | AJ92: =IF(ISNUMBER(K92),K92,IF(OR(K92="general",K92="23;general"),"General",IF(OR(K92="exemption",K92="other (exemption)"),"Tax exemption/waiver/suspension","Other"))) -> Other | AK92: =IF(B92<>B91,1,0) -> 0 | AL92: 1
A93: 0 | B93: Belgium | C93: 43865 | D93: 43908 | E93: 43962 | F93: =DATEDIF(D93,E93,"D") -> 54 | G93: 43914 | H93: 2020 | I93: 0 | J93: 6 | K93: 29 | L93: Self-employed workers who are forced by the government to stop their activities are entitled to a replacement income of EUR 1,291 or EUR 1,614 depending on their family composition. For certain sectors the mandatory waiting period of 7 days has been suspended. | M93: 1 | N93: 1 | O93: -2 | P93: -1 | R93: -2 | S93: 1 | T93: -2 | U93: 1 | V93: BEL | W93: Europe & Central Asia | X93: None | Y93: High Income | Z93: 0 | AA93: =IF(M93>0,1,IF(M93<0,0,-1)) -> 1 | AB93: =IF(N93>0,1,IF(N93<0,0,-1)) -> 1 | AC93: =IF(O93>0,1,IF(O93<0,0,-1)) -> 0 | AD93: =IF(P93>0,1,IF(P93<0,0,-1)) -> 0 | AE93: =IF(Q93>0,1,IF(Q93<0,0,-1)) -> -1 | AF93: =IF(R93>0,1,IF(R93<0,0,-1)) -> 0 | AG93: =IF(S93>0,1,IF(S93<0,0,-1)) -> 1 | AH93: =IF(T93>0,1,IF(T93<0,0,-1)) -> 0 | AI93: =IF(U93>0,1,IF(U93<0,0,-1)) -> 1 | AJ93: =IF(ISNUMBER(K93),K93,IF(OR(K93="general",K93="23;general"),"General",IF(OR(K93="exemption",K93="other (exemption)"),"Tax exemption/waiver/suspension","Other"))) -> 29 | AK93: =IF(B93<>B92,1,0) -> 0 | AL93: 1
A94: 0 | B94: Belgium | C94: 43865 | D94: 43908 | E94: 43962 | F94: =DATEDIF(D94,E94,"D") -> 54 | G94: 43914 | H94: 2020 | I94: 0 | J94: 6 | K94: 25 | L94: Special bonus of up to EUR 1,000 euros in essential sectors (e.g. food sector, energy sector.). | M94: 1 | N94: 1 | O94: 1 | P94: -1 | Q94: 1 | R94: 1 | S94: 1 | T94: -2 | U94: 1 | V94: BEL | W94: Europe & Central Asia | X94: None | Y94: High Income | Z94: 0 | AA94: =IF(M94>0,1,IF(M94<0,0,-1)) -> 1 | AB94: =IF(N94>0,1,IF(N94<0,0,-1)) -> 1 | AC94: =IF(O94>0,1,IF(O94<0,0,-1)) -> 1 | AD94: =IF(P94>0,1,IF(P94<0,0,-1)) -> 0 | AE94: =IF(Q94>0,1,IF(Q94<0,0,-1)) -> 1 | AF94: =IF(R94>0,1,IF(R94<0,0,-1)) -> 1 | AG94: =IF(S94>0,1,IF(S94<0,0,-1)) -> 1 | AH94: =IF(T94>0,1,IF(T94<0,0,-1)) -> 0 | AI94: =IF(U94>0,1,IF(U94<0,0,-1)) -> 1 | AJ94: =IF(ISNUMBER(K94),K94,IF(OR(K94="general",K94="23;general"),"General",IF(OR(K94="exemption",K94="other (exemption)"),"Tax exemption/waiver/suspension","Other"))) -> 25 | AK94: =IF(B94<>B93,1,0) -> 0 | AL94: 1
A95: 0 | B95: Belgium | C95: 43865 | D95: 43908 | E95: 43962 | F95: =DATEDIF(D95,E95,"D") -> 54 | G95: 43914 | H95: 2020 | I95: 0 | J95: 6 | K95: 28 | L95: Some jurisdictions will temporarily cover utility costs for households with a worker facing temporary employment; utilities (water, gas, power) will not be disconnected during the COVID-19 crisis. | M95: -2 | N95: 1 | O95: -2 | P95: -1 | Q95: -1 | R95: 1 | S95: 1 | T95: 2 | U95: 1 | V95: BEL | W95: Europe & Central Asia | X95: None | Y95: High Income | Z95: 0 | AA95: =IF(M95>0,1,IF(M95<0,0,-1)) -> 0 | AB95: =IF(N95>0,1,IF(N95<0,0,-1)) -> 1 | AC95: =IF(O95>0,1,IF(O95<0,0,-1)) -> 0 | AD95: =IF(P95>0,1,IF(P95<0,0,-1)) -> 0 | AE95: =IF(Q95>0,1,IF(Q95<0,0,-1)) -> 0 | AF95: =IF(R95>0,1,IF(R95<0,0,-1)) -> 1 | AG95: =IF(S95>0,1,IF(S95<0,0,-1)) -> 1 | AH95: =IF(T95>0,1,IF(T95<0,0,-1)) -> 1 | AI95: =IF(U95>0,1,IF(U95<0,0,-1)) -> 1 | AJ95: =IF(ISNUMBER(K95),K95,IF(OR(K95="general",K95="23;general"),"General",IF(OR(K95="exemption",K95="other (exemption)"),"Tax exemption/waiver/suspension","Other"))) -> 28 | AK95: =IF(B95<>B94,1,0) -> 0 | AL95: 1
A96: 0 | B96: Belgium | C96: 43865 | D96: 43908 | E96: 43962 | F96: =DATEDIF(D96,E96,"D") -> 54 | G96: 43914 | H96: 2020 | I96: 0 | J96: 7 | K96: 30 | L96: Banks have agreed to allow loan repayments to be postponed until September 2020 for non-financial companies without penalties. | M96: -1 | N96: 1 | O96: 1 | P96: 1 | Q96: 1 | R96: 1 | S96: 1 | T96: 1 | U96: 1 | V96: BEL | W96: Europe & Central Asia | X96: None | Y96: High Income | Z96: 0 | AA96: =IF(M96>0,1,IF(M96<0,0,-1)) -> 0 | AB96: =IF(N96>0,1,IF(N96<0,0,-1)) -> 1 | AC96: =IF(O96>0,1,IF(O96<0,0,-1)) -> 1 | AD96: =IF(P96>0,1,IF(P96<0,0,-1)) -> 1 | AE96: =IF(Q96>0,1,IF(Q96<0,0,-1)) -> 1 | AF96: =IF(R96>0,1,IF(R96<0,0,-1)) -> 1 | AG96: =IF(S96>0,1,IF(S96<0,0,-1)) -> 1 | AH96: =IF(T96>0,1,IF(T96<0,0,-1)) -> 1 | AI96: =IF(U96>0,1,IF(U96<0,0,-1)) -> 1 | AJ96: =IF(ISNUMBER(K96),K96,IF(OR(K96="general",K96="23;general"),"General",IF(OR(K96="exemption",K96="other (exemption)"),"Tax exemption/waiver/suspension","Other"))) -> 30 | AK96: =IF(B96<>B95,1,0) -> 0 | AL96: 1
A97: 0 | B97: Belgium | C97: 43865 | D97: 43908 | E97: 43962 | F97: =DATEDIF(D97,E97,"D") -> 54 | G97: 43914 | H97: 2020 | I97: 0 | J97: 6 | K97: 29 | L97: Self-employed workers who are incapacitated for work for at least 8 days are entitled to an incapacity for work benefit payable by the health insurance scheme from the first day. | M97: 1 | N97: 1 | O97: 1 | Q97: -1 | R97: -2 | S97: 1 | T97: -2 | U97: 1 | V97: BEL | W97: Europe & Central Asia | X97: None | Y97: High Income | Z97: 0 | AA97: =IF(M97>0,1,IF(M97<0,0,-1)) -> 1 | AB97: =IF(N97>0,1,IF(N97<0,0,-1)) -> 1 | AC97: =IF(O97>0,1,IF(O97<0,0,-1)) -> 1 | AD97: =IF(P97>0,1,IF(P97<0,0,-1)) -> -1 | AE97: =IF(Q97>0,1,IF(Q97<0,0,-1)) -> 0 | AF97: =IF(R97>0,1,IF(R97<0,0,-1)) -> 0 | AG97: =IF(S97>0,1,IF(S97<0,0,-1)) -> 1 | AH97: =IF(T97>0,1,IF(T97<0,0,-1)) -> 0 | AI97: =IF(U97>0,1,IF(U97<0,0,-1)) -> 1 | AJ97: =IF(ISNUMBER(K97),K97,IF(OR(K97="general",K97="23;general"),"General",IF(OR(K97="exemption",K97="other (exemption)"),"Tax exemption/waiver/suspension","Other"))) -> 29 | AK97: =IF(B97<>B96,1,0) -> 0 | AL97: 1
A98: 0 | B98: Belgium | C98: 43865 | D98: 43908 | E98: 43962 | F98: =DATEDIF(D98,E98,"D") -> 54 | G98: 43914 | H98: 2020 | I98: 0 | J98: 1 | K98: 9 | L98: Acceleration of VAT refunds. | M98: -1 | N98: 2 | O98: 2 | P98: 2 | Q98: 2 | R98: -2 | S98: -2 | T98: 2 | U98: 1 | V98: BEL | W98: Europe & Central Asia | X98: None | Y98: High Income | Z98: 0 | AA98: =IF(M98>0,1,IF(M98<0,0,-1)) -> 0 | AB98: =IF(N98>0,1,IF(N98<0,0,-1)) -> 1 | AC98: =IF(O98>0,1,IF(O98<0,0,-1)) -> 1 | AD98: =IF(P98>0,1,IF(P98<0,0,-1)) -> 1 | AE98: =IF(Q98>0,1,IF(Q98<0,0,-1)) -> 1 | AF98: =IF(R98>0,1,IF(R98<0,0,-1)) -> 0 | AG98: =IF(S98>0,1,IF(S98<0,0,-1)) -> 0 | AH98: =IF(T98>0,1,IF(T98<0,0,-1)) -> 1 | AI98: =IF(U98>0,1,IF(U98<0,0,-1)) -> 1 | AJ98: =IF(ISNUMBER(K98),K98,IF(OR(K98="general",K98="23;general"),"General",IF(OR(K98="exemption",K98="other (exemption)"),"Tax exemption/waiver/suspension","Other"))) -> 9 | AK98: =IF(B98<>B97,1,0) -> 0 | AL98: 1
A99: 0 | B99: Belgium | C99: 43865 | D99: 43908 | E99: 43962 | F99: =DATEDIF(D99,E99,"D") -> 54 | G99: 43914 | H99: 2020 | I99: 0 | J99: 1 | K99: 6 | L99: Submitting a CIT return can be deferred until 30 April 2020. | M99: -1 | N99: 2 | O99: 2 | P99: 2 | Q99: 2 | R99: 2 | S99: 1 | T99: 1 | U99: 1 | V99: BEL | W99: Europe & Central Asia | X99: None | Y99: High Income | Z99: 0 | AA99: =IF(M99>0,1,IF(M99<0,0,-1)) -> 0 | AB99: =IF(N99>0,1,IF(N99<0,0,-1)) -> 1 | AC99: =IF(O99>0,1,IF(O99<0,0,-1)) -> 1 | AD99: =IF(P99>0,1,IF(P99<0,0,-1)) -> 1 | AE99: =IF(Q99>0,1,IF(Q99<0,0,-1)) -> 1 | AF99: =IF(R99>0,1,IF(R99<0,0,-1)) -> 1 | AG99: =IF(S99>0,1,IF(S99<0,0,-1)) -> 1 | AH99: =IF(T99>0,1,IF(T99<0,0,-1)) -> 1 | AI99: =IF(U99>0,1,IF(U99<0,0,-1)) -> 1 | AJ99: =IF(ISNUMBER(K99),K99,IF(OR(K99="general",K99="23;general"),"General",IF(OR(K99="exemption",K99="other (exemption)"),"Tax exemption/waiver/suspension","Other"))) -> 6 | AK99: =IF(B99<>B98,1,0) -> 0 | AL99: 1
A100: 0 | B100: Belgium | C100: 43865 | D100: 43908 | E100: 43962 | F100: =DATEDIF(D100,E100,"D") -> 54 | G100: 43914 | H100: 2020 | I100: 0 | J100: 3 | K100: exemption | L100: 45% tax credit for in-kind donations of medical equipment to hospitals. | M100: 2 | N100: 2 | O100: -2 | P100: -1 | Q100: 2 | R100: -2 | S100: 2 | T100: -2 | U100: 1 | V100: BEL | W100: Europe & Central Asia | X100: None | Y100: High Income | Z100: 0 | AA100: =IF(M100>0,1,IF(M100<0,0,-1)) -> 1 | AB100: =IF(N100>0,1,IF(N100<0,0,-1)) -> 1 | AC100: =IF(O100>0,1,IF(O100<0,0,-1)) -> 0 | AD100: =IF(P100>0,1,IF(P100<0,0,-1)) -> 0 | AE100: =IF(Q100>0,1,IF(Q100<0,0,-1)) -> 1 | AF100: =IF(R100>0,1,IF(R100<0,0,-1)) -> 0 | AG100: =IF(S100>0,1,IF(S100<0,0,-1)) -> 1 | AH100: =IF(T100>0,1,IF(T100<0,0,-1)) -> 0 | AI100: =IF(U100>0,1,IF(U100<0,0,-1)) -> 1 | AJ100: =IF(ISNUMBER(K100),K100,IF(OR(K100="general",K100="23;general"),"General",IF(OR(K100="exemption",K100="other (exemption)"),"Tax exemption/waiver/suspension","Other"))) -> Tax exemption/waiver/suspension | AK100: =IF(B100<>B99,1,0) -> 0 | AL100: 1
...

Sheet Mapping
A1: PolicyCode | B1: PolicyName | C1: PolicyCategory | D1: IMF_Classification | E1: Notes
A2: 1 | B2: Accelerated asset depreciation (CIT) | C2: 1 Revenue Measures to protect businesses | D2: On-Budget | E2: Parameteraenderung der Steuerbasis; Mindereinnahmen. Auch temporaer On-Budget (Timing-Effekt).
A3: 2 | B3: Extend loss carry-forward (CIT) | C3: 1 Revenue Measures to protect businesses | D3: On-Budget | E3: Reduziert kuenftige Steuerbasis; Mindereinnahmen.
A4: 3 | B4: Broaden tax deductibility | C4: 1 Revenue Measures to protect businesses | D4: On-Budget | E4: Parameteraenderung; Mindereinnahmen.
A5: 4 | B5: Tax credits | C5: 1 Revenue Measures to protect businesses | D5: On-Budget | E5: Anrechenbare/auszahlbare Credits; Mindereinnahmen/Ausgaben.
A6: 5 | B6: Deferral of tax filing | C6: 1 Revenue Measures to protect businesses | D6: Off-Budget | E6: Timing/Verwaltung; keine Accrual-Wirkung.
A7: 6 | B7: Deferral of tax payments | C7: 1 Revenue Measures to protect businesses | D7: Off-Budget | E7: Stundung; Liquiditaetsmassnahme.
A8: 7 | B8: Tax rate reduction | C8: 1 Revenue Measures to protect businesses | D8: On-Budget | E8: Mindereinnahmen durch niedrigere Saetze.
A9: 8 | B9: Tax amnesty / incentives | C9: 1 Revenue Measures to protect businesses | D9: On-Budget | E9: Erlass/Reduktion von Steuerschulden = Mindereinnahmen.
A10: 9 | B10: Accelerating refunds | C10: 1 Revenue Measures to protect businesses | D10: Off-Budget | E10: Vorgezogene Rueckerstattungen; Timing-Effekt.
A11: 10 | B11: Lower advance payment | C11: 1 Revenue Measures to protect businesses | D11: Off-Budget | E11: Niedrigere Akontos; Timing/Liquiditaet.
A12: 11 | B12: Suspend debt collection | C12: 1 Revenue Measures to protect businesses | D12: Off-Budget | E12: Vollstreckung ausgesetzt; Timing/Verwaltung.
A13: 12 | B13: Suspend audit activities | C13: 1 Revenue Measures to protect businesses | D13: Off-Budget | E13: Verwaltungsakt; keine unmittelbare Accrual-Wirkung.
A14: exemption | B14: Tax exemption/waiver/suspension | C14: 1 Revenue Measures to protect businesses | D14: Split (see notes) | E14: Echte Befreiung/Erlass = On-Budget; blosse Suspension/Stundung = Off-Budget.
A15: other | B15: Other | C15: 1 Revenue Measures to protect businesses | D15: Context-dependent | E15: Parameteraenderung → On-Budget; reine Timing/Admin → Off-Budget.
A16: 13 | B16: Deferral of tax filing | C16: 2 Revenue Measures to protect individuals | D16: Off-Budget | E16: Wie Code 5; Timing/Verwaltung.
A17: 14 | B17: Deferral of tax payments | C17: 2 Revenue Measures to protect individuals | D17: Off-Budget | E17: Wie Code 6; Stundung.
A18: 15 | B18: Tax rate reduction | C18: 2 Revenue Measures to protect individuals | D18: On-Budget | E18: Mindereinnahmen.
A19: 16 | B19: Tax amnesty / incentives | C19: 2 Revenue Measures to protect individuals | D19: On-Budget | E19: Erlass/Reduktion; Mindereinnahmen.
A20: 17 | B20: Broaden tax deductibility | C20: 2 Revenue Measures to protect individuals | D20: On-Budget | E20: Parameteraenderung; Mindereinnahmen.
A21: 18 | B21: Tax credits | C21: 2 Revenue Measures to protect individuals | D21: On-Budget | E21: Anrechenbare/auszahlbare Credits; Mindereinnahmen/Ausgaben.
A22: exemption | B22: Tax exemption/waiver/suspension | C22: 2 Revenue Measures to protect individuals | D22: Split (see notes) | E22: Befreiung/Erlass = On-Budget; Suspension/Stundung = Off-Budget.
A23: other | B23: Other | C23: 2 Revenue Measures to protect individuals | D23: Context-dependent | E23: Parameteraenderung → On-Budget; reine Timing/Admin → Off-Budget.
A24: 19 | B24: Lower tax rates for medical items | C24: 3 Revenue Measures to promote availability of medical items | D24: On-Budget | E24: Gezielte Mindereinnahmen.
A25: exemption | B25: Tax exemption/waiver/suspension | C25: 3 Revenue Measures to promote availability of medical items | D25: Split (see notes) | E25: Befreiung/Erlass = On-Budget; Suspension/Stundung = Off-Budget.
A26: other | B26: Other | C26: 3 Revenue Measures to promote availability of medical items | D26: Context-dependent | E26: Parameteraenderung → On-Budget; reine Timing/Admin → Off-Budget.
A27: 20 | B27: Lower tax rates | C27: 4 Revenue Measures to boost consumption / demand | D27: On-Budget | E27: Mindereinnahmen (z. B. Mehrwertsteuer).
A28: exemption | B28: Tax exemption/waiver/suspension | C28: 4 Revenue Measures to boost consumption / demand | D28: Split (see notes) | E28: Befreiung/Erlass = On-Budget; Suspension/Stundung = Off-Budget.
A29: other | B29: Other | C29: 4 Revenue Measures to boost consumption / demand | D29: Context-dependent | E29: Parameteraenderung → On-Budget; reine Timing/Admin → Off-Budget.
A30: 21 | B30: Supply of low cost medical items | C30: 5 Health Expenditures measures | D30: On-Budget | E30: Zusaetzliche Sachausgaben.
A31: 22 | B31: Supply of high cost medical items | C31: 5 Health Expenditures measures | D31: On-Budget | E31: Investitionen/hohe Ausgaben.
A32: 23 | B32: Targeted infrastructure investments | C32: 5 Health Expenditures measures | D32: On-Budget | E32: Oeffentliche Investitionen (CapEx).
A33: 24 | B33: Expansion of human resources | C33: 5 Health Expenditures measures | D33: On-Budget | E33: Personal-/Betriebsausgaben.
A34: general | B34: General | C34: 5 Health Expenditures measures | D34: On-Budget | E34: Allgemeine Gesundheitsausgaben.
A35: 25 | B35: Direct cash transfers for individuals | C35: 6 Expenditure Measures for cash transfers to individuals | D35: On-Budget | E35: Transfers erhoehen Ausgaben.
A36: 26 | B36: Expansion of unemployment benefits | C36: 6 Expenditure Measures for cash transfers to individuals | D36: On-Budget | E36: Hoehere Sozialausgaben.
A37: 27 | B37: Temporary expansion of existing benefits | C37: 6 Expenditure Measures for cash transfers to individuals | D37: On-Budget | E37: Hoehere Transfers.
A38: 28 | B38: Supplementary ad hoc programs | C38: 6 Expenditure Measures for cash transfers to individuals | D38: On-Budget | E38: Zusaetzliche Programme/Transfers.
A39: 29 | B39: Wage compensation/ enhanced paid leave | C39: 6 Expenditure Measures for cash transfers to individuals | D39: On-Budget | E39: Subventionen/Transfers.
A40: other | B40: Other | C40: 6 Expenditure Measures for cash transfers to individuals | D40: On-Budget | E40: Andere monetare Transfers/Subventionen.
A41: 30 | B41: Preferential loans to firms | C41: 7 Credit and equity measures | D41: Off-Budget | E41: Kreditvergabe = Finanztransaktion (below the line). Zins-Subventionen waeren On-Budget.
A42: 31 | B42: One-off grants | C42: 7 Credit and equity measures | D42: On-Budget | E42: Nicht rueckzahlbare Zuschuesse = Ausgaben.
A43: 32 | B43: Preferential loans to households | C43: 7 Credit and equity measures | D43: Off-Budget | E43: Kreditvergabe = Finanztransaktion; Zins-Subvention separat On-Budget.
A44: other | B44: Other | C44: 7 Credit and equity measures | D44: Split (see notes) | E44: Kredite/Garantien/Equity = Off-Budget; reine Zuschuesse = On-Budget.
A45: 33 | B45: Revenue increase | C45: 8 Revenue Measures to raise revenue | D45: On-Budget | E45: Erhoeht Einnahmen durch Parameteraenderung.
A46: 34 | B46: Income support | C46: 9 Expenditure Measures for businesses | D46: On-Budget | E46: Transfers/Subventionen an Unternehmen.

Sheet Makro Analysis Count per 2 
A1: PolicyCategory | B1: PolicyCode | C1: Gruppe 0 | D1: Gruppe 1 | E1: Gruppe 0 Share | F1: Gruppe 1 Share | G1: Gruppe 0 pro Land | H1: Gruppe 1 pro Land | I1: Gruppe 0 pro Mio GDP $ ppp | J1: Gruppe 1 pro Mio GDP $ ppp | K1: Gruppe 0 pro Mio GDP $ | L1: Gruppe 1 pro Mio GDP $ | M1: Gruppe 0 pro 100'000 Einwohnende | N1: Gruppe 1 pro 100'000 Einwohnende | O1: Gruppe 0 pro Capita ppp | P1: Gruppe 1 per Capita ppp
A2: 1 | B2: 1 | C2: 3 | D2: 5 | E2: =C2/(C2+D2) -> 0.375 | F2: =1-E2 -> 0.625 | G2: =C2/23 -> 0.13043478 | H2: =D2/15 -> 0.33333333 | I2: =(C2/B$80)*1000 -> 0.15947235 | J2: =(D2/B$81)*1000 -> 0.12590638 | K2: =(C2/D$80)*1000 -> 0.19814443 | L2: =(D2/D$81)*1000 -> 0.13736294 | M2: =(C2/C$84)*100000 -> 0.013436818 | N2: =(D2/D$84)*100000 -> 0.0088376331 | O2: =C2/E$80 -> 0.35604936 | P2: =D2/E$81 -> 0.71233091
A3: 1 | B3: 10 | C3: 12 | D3: 11 | E3: =C3/(C3+D3) -> 0.52173913 | F3: =1-E3 -> 0.47826087 | G3: =C3/23 -> 0.52173913 | H3: =D3/15 -> 0.73333333 | I3: =(C3/B$80)*1000 -> 0.63788939 | J3: =(D3/B$81)*1000 -> 0.27699405 | K3: =(C3/D$80)*1000 -> 0.79257771 | L3: =(D3/D$81)*1000 -> 0.30219848 | M3: =(C3/C$84)*100000 -> 0.053747271 | N3: =(D3/D$84)*100000 -> 0.019442793 | O3: =C3/E$80 -> 1.4241975 | P3: =D3/E$81 -> 1.567128
A4: 1 | B4: 11 | C4: 8 | D4: 15 | E4: =C4/(C4+D4) -> 0.34782609 | F4: =1-E4 -> 0.65217391 | G4: =C4/23 -> 0.34782609 | H4: =D4/15 -> 1 | I4: =(C4/B$80)*1000 -> 0.42525959 | J4: =(D4/B$81)*1000 -> 0.37771915 | K4: =(C4/D$80)*1000 -> 0.52838514 | L4: =(D4/D$81)*1000 -> 0.41208883 | M4: =(C4/C$84)*100000 -> 0.035831514 | N4: =(D4/D$84)*100000 -> 0.026512899 | O4: =C4/E$80 -> 0.94946497 | P4: =D4/E$81 -> 2.1369927
A5: 1 | B5: 12 | C5: 7 | D5: 7 | E5: =C5/(C5+D5) -> 0.5 | F5: =1-E5 -> 0.5 | G5: =C5/23 -> 0.30434783 | H5: =D5/15 -> 0.46666667 | I5: =(C5/B$80)*1000 -> 0.37210214 | J5: =(D5/B$81)*1000 -> 0.17626894 | K5: =(C5/D$80)*1000 -> 0.46233699 | L5: =(D5/D$81)*1000 -> 0.19230812 | M5: =(C5/C$84)*100000 -> 0.031352575 | N5: =(D5/D$84)*100000 -> 0.012372686 | O5: =C5/E$80 -> 0.83078185 | P5: =D5/E$81 -> 0.99726327
A6: 1 | B6: 2 | C6: 6 | D6: 7 | E6: =C6/(C6+D6) -> 0.46153846 | F6: =1-E6 -> 0.53846154 | G6: =C6/23 -> 0.26086957 | H6: =D6/15 -> 0.46666667 | I6: =(C6/B$80)*1000 -> 0.31894469 | J6: =(D6/B$81)*1000 -> 0.17626894 | K6: =(C6/D$80)*1000 -> 0.39628885 | L6: =(D6/D$81)*1000 -> 0.19230812 | M6: =(C6/C$84)*100000 -> 0.026873635 | N6: =(D6/D$84)*100000 -> 0.012372686 | O6: =C6/E$80 -> 0.71209873 | P6: =D6/E$81 -> 0.99726327
A7: 1 | B7: 3 | C7: 16 | D7: 8 | E7: =C7/(C7+D7) -> 0.66666667 | F7: =1-E7 -> 0.33333333 | G7: =C7/23 -> 0.69565217 | H7: =D7/15 -> 0.53333333 | I7: =(C7/B$80)*1000 -> 0.85051918 | J7: =(D7/B$81)*1000 -> 0.20145022 | K7: =(C7/D$80)*1000 -> 1.0567703 | L7: =(D7/D$81)*1000 -> 0.21978071 | M7: =(C7/C$84)*100000 -> 0.071663028 | N7: =(D7/D$84)*100000 -> 0.014140213 | O7: =C7/E$80 -> 1.8989299 | P7: =D7/E$81 -> 1.1397295 | R7: ad-hoc programme
A8: 1 | B8: 4 | C8: 8 | D8: 20 | E8: =C8/(C8+D8) -> 0.28571429 | F8: =1-E8 -> 0.71428571 | G8: =C8/23 -> 0.34782609 | H8: =D8/15 -> 1.3333333 | I8: =(C8/B$80)*1000 -> 0.42525959 | J8: =(D8/B$81)*1000 -> 0.50362554 | K8: =(C8/D$80)*1000 -> 0.52838514 | L8: =(D8/D$81)*1000 -> 0.54945178 | M8: =(C8/C$84)*100000 -> 0.035831514 | N8: =(D8/D$84)*100000 -> 0.035350533 | O8: =C8/E$80 -> 0.94946497 | P8: =D8/E$81 -> 2.8493236
A9: 1 | B9: 5 | C9: 13 | D9: 10 | E9: =C9/(C9+D9) -> 0.56521739 | F9: =1-E9 -> 0.43478261 | G9: =C9/23 -> 0.56521739 | H9: =D9/15 -> 0.66666667 | I9: =(C9/B$80)*1000 -> 0.69104684 | J9: =(D9/B$81)*1000 -> 0.25181277 | K9: =(C9/D$80)*1000 -> 0.85862585 | L9: =(D9/D$81)*1000 -> 0.27472589 | M9: =(C9/C$84)*100000 -> 0.05822621 | N9: =(D9/D$84)*100000 -> 0.017675266 | O9: =C9/E$80 -> 1.5428806 | P9: =D9/E$81 -> 1.4246618
A10: 1 | B10: 6 | C10: 77 | D10: 66 | E10: =C10/(C10+D10) -> 0.53846154 | F10: =1-E10 -> 0.46153846 | G10: =C10/23 -> 3.3478261 | H10: =D10/15 -> 4.4 | I10: =(C10/B$80)*1000 -> 4.0931236 | J10: =(D10/B$81)*1000 -> 1.6619643 | K10: =(C10/D$80)*1000 -> 5.0857069 | L10: =(D10/D$81)*1000 -> 1.8131909 | M10: =(C10/C$84)*100000 -> 0.34487832 | N10: =(D10/D$84)*100000 -> 0.11665676 | O10: =C10/E$80 -> 9.1386003 | P10: =D10/E$81 -> 9.402768
A11: 1 | B11: 7 | C11: 24 | D11: 20 | E11: =C11/(C11+D11) -> 0.54545455 | F11: =1-E11 -> 0.45454545 | G11: =C11/23 -> 1.0434783 | H11: =D11/15 -> 1.3333333 | I11: =(C11/B$80)*1000 -> 1.2757788 | J11: =(D11/B$81)*1000 -> 0.50362554 | K11: =(C11/D$80)*1000 -> 1.5851554 | L11: =(D11/D$81)*1000 -> 0.54945178 | M11: =(C11/C$84)*100000 -> 0.10749454 | N11: =(D11/D$84)*100000 -> 0.035350533 | O11: =C11/E$80 -> 2.8483949 | P11: =D11/E$81 -> 2.8493236
A12: 1 | B12: 8 | C12: 15 | D12: 3 | E12: =C12/(C12+D12) -> 0.83333333 | F12: =1-E12 -> 0.16666667 | G12: =C12/23 -> 0.65217391 | H12: =D12/15 -> 0.2 | I12: =(C12/B$80)*1000 -> 0.79736173 | J12: =(D12/B$81)*1000 -> 0.075543831 | K12: =(C12/D$80)*1000 -> 0.99072213 | L12: =(D12/D$81)*1000 -> 0.082417766 | M12: =(C12/C$84)*100000 -> 0.067184089 | N12: =(D12/D$84)*100000 -> 0.0053025799 | O12: =C12/E$80 -> 1.7802468 | P12: =D12/E$81 -> 0.42739854
A13: 1 | B13: 9 | C13: 13 | D13: 10 | E13: =C13/(C13+D13) -> 0.56521739 | F13: =1-E13 -> 0.43478261 | G13: =C13/23 -> 0.56521739 | H13: =D13/15 -> 0.66666667 | I13: =(C13/B$80)*1000 -> 0.69104684 | J13: =(D13/B$81)*1000 -> 0.25181277 | K13: =(C13/D$80)*1000 -> 0.85862585 | L13: =(D13/D$81)*1000 -> 0.27472589 | M13: =(C13/C$84)*100000 -> 0.05822621 | N13: =(D13/D$84)*100000 -> 0.017675266 | O13: =C13/E$80 -> 1.5428806 | P13: =D13/E$81 -> 1.4246618
A14: 1 | B14: exemption | C14: 38 | D14: 26 | E14: =C14/(C14+D14) -> 0.59375 | F14: =1-E14 -> 0.40625 | G14: =C14/23 -> 1.6521739 | H14: =D14/15 -> 1.7333333 | I14: =(C14/B$80)*1000 -> 2.0199831 | J14: =(D14/B$81)*1000 -> 0.6547132 | K14: =(C14/D$80)*1000 -> 2.5098294 | L14: =(D14/D$81)*1000 -> 0.71428731 | M14: =(C14/C$84)*100000 -> 0.17019969 | N14: =(D14/D$84)*100000 -> 0.045955692 | O14: =C14/E$80 -> 4.5099586 | P14: =D14/E$81 -> 3.7041207
A15: 1 | B15: other | C15: 1 | D15: 7 | E15: =C15/(C15+D15) -> 0.125 | F15: =1-E15 -> 0.875 | G15: =C15/23 -> 0.043478261 | H15: =D15/15 -> 0.46666667 | I15: =(C15/B$80)*1000 -> 0.053157449 | J15: =(D15/B$81)*1000 -> 0.17626894 | K15: =(C15/D$80)*1000 -> 0.066048142 | L15: =(D15/D$81)*1000 -> 0.19230812 | M15: =(C15/C$84)*100000 -> 0.0044789392 | N15: =(D15/D$84)*100000 -> 0.012372686 | O15: =C15/E$80 -> 0.11868312 | P15: =D15/E$81 -> 0.99726327
A16: 2 | B16: 13 | C16: 4 | D16: 3 | E16: =C16/(C16+D16) -> 0.57142857 | F16: =1-E16 -> 0.42857143 | G16: =C16/23 -> 0.17391304 | H16: =D16/15 -> 0.2 | I16: =(C16/B$80)*1000 -> 0.2126298 | J16: =(D16/B$81)*1000 -> 0.075543831 | K16: =(C16/D$80)*1000 -> 0.26419257 | L16: =(D16/D$81)*1000 -> 0.082417766 | M16: =(C16/C$84)*100000 -> 0.017915757 | N16: =(D16/D$84)*100000 -> 0.0053025799 | O16: =C16/E$80 -> 0.47473248 | P16: =D16/E$81 -> 0.42739854
A17: 2 | B17: 14 | C17: 13 | D17: 18 | E17: =C17/(C17+D17) -> 0.41935484 | F17: =1-E17 -> 0.58064516 | G17: =C17/23 -> 0.56521739 | H17: =D17/15 -> 1.2 | I17: =(C17/B$80)*1000 -> 0.69104684 | J17: =(D17/B$81)*1000 -> 0.45326298 | K17: =(C17/D$80)*1000 -> 0.85862585 | L17: =(D17/D$81)*1000 -> 0.4945066 | M17: =(C17/C$84)*100000 -> 0.05822621 | N17: =(D17/D$84)*100000 -> 0.031815479 | O17: =C17/E$80 -> 1.5428806 | P17: =D17/E$81 -> 2.5643913
A18: 2 | B18: 15 | C18: 7 | D18: 2 | E18: =C18/(C18+D18) -> 0.77777778 | F18: =1-E18 -> 0.22222222 | G18: =C18/23 -> 0.30434783 | H18: =D18/15 -> 0.13333333 | I18: =(C18/B$80)*1000 -> 0.37210214 | J18: =(D18/B$81)*1000 -> 0.050362554 | K18: =(C18/D$80)*1000 -> 0.46233699 | L18: =(D18/D$81)*1000 -> 0.054945178 | M18: =(C18/C$84)*100000 -> 0.031352575 | N18: =(D18/D$84)*100000 -> 0.0035350533 | O18: =C18/E$80 -> 0.83078185 | P18: =D18/E$81 -> 0.28493236
A19: 2 | B19: 16 | C19: 2 | D19: 2 | E19: =C19/(C19+D19) -> 0.5 | F19: =1-E19 -> 0.5 | G19: =C19/23 -> 0.086956522 | H19: =D19/15 -> 0.13333333 | I19: =(C19/B$80)*1000 -> 0.1063149 | J19: =(D19/B$81)*1000 -> 0.050362554 | K19: =(C19/D$80)*1000 -> 0.13209628 | L19: =(D19/D$81)*1000 -> 0.054945178 | M19: =(C19/C$84)*100000 -> 0.0089578785 | N19: =(D19/D$84)*100000 -> 0.0035350533 | O19: =C19/E$80 -> 0.23736624 | P19: =D19/E$81 -> 0.28493236
... A45: other | B45: other | C45: 1 | D45: 1 | E45: =C45/(C45+D45) -> 0.5 | F45: =1-E45 -> 0.5 | G45: =C45/23 -> 0.043478261 | H45: =D45/15 -> 0.066666667 | I45: =(C45/B$80)*1000 -> 0.053157449 | J45: =(D45/B$81)*1000 -> 0.025181277 | K45: =(C45/D$80)*1000 -> 0.066048142 | L45: =(D45/D$81)*1000 -> 0.027472589 | M45: =(C45/C$84)*100000 -> 0.0044789392 | N45: =(D45/D$84)*100000 -> 0.0017675266 | O45: =C45/E$80 -> 0.11868312 | P45: =D45/E$81 -> 0.14246618
C76: =C77/23 -> 37.173913 | D76: =D77/15 -> 49.133333
C77: =SUM(C2:C44) -> 855 | D77: =SUM(D2:D44) -> 737
B78: in 10'000 CHF
A79: Group | B79: pre Covid real GDP ppp (2019) | C79: pre Covid real GDP usd (2019) | E79: ppp per Capita | F79: real per Capita
A80: 0 | B80: 18812.039 | D80: 15140.471 | E80: =(B80/C84)*10000 -> 8.425798 | F80: =B80/D84 -> 0.0003325078
A81: 1 | B81: 39712.045 | D81: 36399.919 | E81: =(B81/D84)*10000 -> 7.0192097 | F81: =D81/D84 -> 0.00064337826
A83: AUS | B83: 25334826 | C83: Gruppe 0 | D83: Gruppe 1
A84: AUT | B84: 8877637 | C84: 22326715 | D84: 56576234
A85: BEL | B85: 11489000
A86: CAN | B86: 37618495
A87: CHE | B87: 8575280
A88: CHL | B88: 19107216
A89: COL | B89: 48322807
A90: CRI | B90: 5055238
A91: CZE | B91: 10550313
A92: DEU | B92: 83093000
A93: DNK | B93: 5816940
A94: ESP | B94: 47105358
A95: EST | B95: 1324820
A96: FIN | B96: 5521600
... A120: USA | B120: 330513000
A122: Showing 10 to 38 of 38 entries, 2 total col

Sheet Makro Analysis Count per
A1: PolicyCode | B1: Beschreibung (Beispiel) | C1: Gruppe 0 | D1: Gruppe 1 | E1: Gruppe 0 Share | F1: Gruppe 1 Share | G1: Gruppe 0 pro Land | H1: Gruppe 1 pro Land | I1: Gruppe 0 pro Mio GDP $ ppp | J1: Gruppe 1 pro Mio GDP $ ppp | K1: Gruppe 0 pro Mio GDP $ | L1: Gruppe 1 pro Mio GDP $ | M1: Gruppe 0 pro 100'000 Einwohnende | N1: Gruppe 1 pro 100'000 Einwohnende | O1: Gruppe 0 pro Capita ppp | P1: Gruppe 1 per Capita ppp
A2: other | B2: Sonstige Maßnahmen (nicht klass.) | C2: 112 | D2: 83 | E2: =C2/(C2+D2) -> 0.57435897 | F2: =1-E2 -> 0.42564103 | G2: =C2/23 -> 4.8695652 | H2: =D2/15 -> 5.5333333 | I2: =(C2/B$45)*1000 -> 5.9536343 | J2: =(D2/B$46)*1000 -> 2.090046 | K2: =(C2/D$45)*1000 -> 7.3973919 | L2: =(D2/D$46)*1000 -> 2.2802249 | M2: =(C2/C$49)*100000 -> 0.5016412 | N2: =(D2/D$49)*100000 -> 0.14670471 | O2: =C2/E$45 -> 13.29251 | P2: =D2/E$46 -> 11.824693
A3: 30 | B3: KMU-Kreditgarantie-Programme | C3: 92 | D3: 54 | E3: =C3/(C3+D3) -> 0.63013699 | F3: =1-E3 -> 0.36986301 | G3: =C3/23 -> 4 | H3: =D3/15 -> 3.6 | I3: =(C3/B$45)*1000 -> 4.8904853 | J3: =(D3/B$46)*1000 -> 1.359789 | K3: =(C3/D$45)*1000 -> 6.0764291 | L3: =(D3/D$46)*1000 -> 1.4835198 | M3: =(C3/C$49)*100000 -> 0.41206241 | N3: =(D3/D$49)*100000 -> 0.095446438 | O3: =C3/E$45 -> 10.918847 | P3: =D3/E$46 -> 7.6931738
A4: 6 | B4: Steuerstundungen/-aufschub | C4: 68 | D4: 55 | E4: =C4/(C4+D4) -> 0.55284553 | F4: =1-E4 -> 0.44715447 | G4: =C4/23 -> 2.9565217 | H4: =D4/15 -> 3.6666667 | I4: =(C4/B$45)*1000 -> 3.6147065 | J4: =(D4/B$46)*1000 -> 1.3849702 | K4: =(C4/D$45)*1000 -> 4.4912737 | L4: =(D4/D$46)*1000 -> 1.5109924 | M4: =(C4/C$49)*100000 -> 0.30456787 | N4: =(D4/D$49)*100000 -> 0.097213964 | O4: =C4/E$45 -> 8.0704522 | P4: =D4/E$46 -> 7.83564
A5: exemption | B5: Steuer-/Abgabenbefreiungen | C5: 59 | D5: 46 | E5: =C5/(C5+D5) -> 0.56190476 | F5: =1-E5 -> 0.43809524 | G5: =C5/23 -> 2.5652174 | H5: =D5/15 -> 3.0666667 | I5: =(C5/B$45)*1000 -> 3.1362895 | J5: =(D5/B$46)*1000 -> 1.1583387 | K5: =(C5/D$45)*1000 -> 3.8968404 | L5: =(D5/D$46)*1000 -> 1.2637391 | M5: =(C5/C$49)*100000 -> 0.26425742 | N5: =(D5/D$49)*100000 -> 0.081306225 | O5: =C5/E$45 -> 7.0023041 | P5: =D5/E$46 -> 6.5534444
A6: 29 | B6: Lohnsubventionen (Kurzarbeit etc.) | C6: 63 | D6: 38 | E6: =C6/(C6+D6) -> 0.62376238 | F6: =1-E6 -> 0.37623762 | G6: =C6/23 -> 2.7391304 | H6: =D6/15 -> 2.5333333 | I6: =(C6/B$45)*1000 -> 3.3489193 | J6: =(D6/B$46)*1000 -> 0.95688852 | K6: =(C6/D$45)*1000 -> 4.161033 | L6: =(D6/D$46)*1000 -> 1.0439584 | M6: =(C6/C$49)*100000 -> 0.28217317 | N6: =(D6/D$49)*100000 -> 0.067166012 | O6: =C6/E$45 -> 7.4770366 | P6: =D6/E$46 -> 5.4137149
A7: 28 | B7: Ausweitung Sozialhilfe/Unterstützung | C7: 33 | D7: 33 | E7: =C7/(C7+D7) -> 0.5 | F7: =1-E7 -> 0.5 | G7: =C7/23 -> 1.4347826 | H7: =D7/15 -> 2.2 | I7: =(C7/B$45)*1000 -> 1.7541958 | J7: =(D7/B$46)*1000 -> 0.83098214 | K7: =(C7/D$45)*1000 -> 2.1795887 | L7: =(D7/D$46)*1000 -> 0.90659543 | M7: =(C7/C$49)*100000 -> 0.147805 | N7: =(D7/D$49)*100000 -> 0.058328379 | O7: =C7/E$45 -> 3.916543 | P7: =D7/E$46 -> 4.701384
A8: 34 | B8: Aufgestockte Lohnsubvention (100%) | C8: 48 | D8: 17 | E8: =C8/(C8+D8) -> 0.73846154 | F8: =1-E8 -> 0.26153846 | G8: =C8/23 -> 2.0869565 | H8: =D8/15 -> 1.1333333 | I8: =(C8/B$45)*1000 -> 2.5515575 | J8: =(D8/B$46)*1000 -> 0.42808171 | K8: =(C8/D$45)*1000 -> 3.1703108 | L8: =(D8/D$46)*1000 -> 0.46703401 | M8: =(C8/C$49)*100000 -> 0.21498908 | N8: =(D8/D$49)*100000 -> 0.030047953 | O8: =C8/E$45 -> 5.6967898 | P8: =D8/E$46 -> 2.4219251
A9: general | B9: Allg. fiskalische Stimuluspakete | C9: 27 | D9: 26 | E9: =C9/(C9+D9) -> 0.50943396 | F9: =1-E9 -> 0.49056604 | G9: =C9/23 -> 1.173913 | H9: =D9/15 -> 1.7333333 | I9: =(C9/B$45)*1000 -> 1.4352511 | J9: =(D9/B$46)*1000 -> 0.6547132 | K9: =(C9/D$45)*1000 -> 1.7832998 | L9: =(D9/D$46)*1000 -> 0.71428731 | M9: =(C9/C$49)*100000 -> 0.12093136 | N9: =(D9/D$49)*100000 -> 0.045955692 | O9: =C9/E$45 -> 3.2044443 | P9: =D9/E$46 -> 3.7041207
A10: 25 | B10: Einmalige Hilfszahlung (z.B. 250 $) | C10: 21 | D10: 30 | E10: =C10/(C10+D10) -> 0.41176471 | F10: =1-E10 -> 0.58823529 | G10: =C10/23 -> 0.91304348 | H10: =D10/15 -> 2 | I10: =(C10/B$45)*1000 -> 1.1163064 | J10: =(D10/B$46)*1000 -> 0.75543831 | K10: =(C10/D$45)*1000 -> 1.387011 | L10: =(D10/D$46)*1000 -> 0.82417766 | M10: =(C10/C$49)*100000 -> 0.094057724 | N10: =(D10/D$49)*100000 -> 0.053025799 | O10: =C10/E$45 -> 2.4923455 | P10: =D10/E$46 -> 4.2739854
A11: 26 | B11: Erweiterung Arbeitslosenvers. | C11: 28 | D11: 18 | E11: =C11/(C11+D11) -> 0.60869565 | F11: =1-E11 -> 0.39130435 | G11: =C11/23 -> 1.2173913 | H11: =D11/15 -> 1.2 | I11: =(C11/B$45)*1000 -> 1.4884086 | J11: =(D11/B$46)*1000 -> 0.45326298 | K11: =(C11/D$45)*1000 -> 1.849348 | L11: =(D11/D$46)*1000 -> 0.4945066 | M11: =(C11/C$49)*100000 -> 0.1254103 | N11: =(D11/D$49)*100000 -> 0.031815479 | O11: =C11/E$45 -> 3.3231274 | P11: =D11/E$46 -> 2.5643913
A12: 27 | B12: Weitere Einmalzahlung (z.B. 750 $) | C12: 17 | D12: 21 | E12: =C12/(C12+D12) -> 0.44736842 | F12: =1-E12 -> 0.55263158 | G12: =C12/23 -> 0.73913043 | H12: =D12/15 -> 1.4 | I12: =(C12/B$45)*1000 -> 0.90367663 | J12: =(D12/B$46)*1000 -> 0.52880682 | K12: =(C12/D$45)*1000 -> 1.1228184 | L12: =(D12/D$46)*1000 -> 0.57692436 | M12: =(C12/C$49)*100000 -> 0.076141967 | N12: =(D12/D$49)*100000 -> 0.037118059 | O12: =C12/E$45 -> 2.0176131 | P12: =D12/E$46 -> 2.9917898
A13: 20 | B13: MwSt-Senkung best. Sektoren | C13: 14 | D13: 15 | E13: =C13/(C13+D13) -> 0.48275862 | F13: =1-E13 -> 0.51724138 | G13: =C13/23 -> 0.60869565 | H13: =D13/15 -> 1 | I13: =(C13/B$45)*1000 -> 0.74420428 | J13: =(D13/B$46)*1000 -> 0.37771915 | K13: =(C13/D$45)*1000 -> 0.92467399 | L13: =(D13/D$46)*1000 -> 0.41208883 | M13: =(C13/C$49)*100000 -> 0.062705149 | N13: =(D13/D$49)*100000 -> 0.026512899 | O13: =C13/E$45 -> 1.6615637 | P13: =D13/E$46 -> 2.1369927
A14: 7 | B14: Steuerliche Maßnahme | C14: 16 | D14: 13 | E14: =C14/(C14+D14) -> 0.55172414 | F14: =1-E14 -> 0.44827586 | G14: =C14/23 -> 0.69565217 | H14: =D14/15 -> 0.86666667 | I14: =(C14/B$45)*1000 -> 0.85051918 | J14: =(D14/B$46)*1000 -> 0.3273566 | K14: =(C14/D$45)*1000 -> 1.0567703 | L14: =(D14/D$46)*1000 -> 0.35714365 | M14: =(C14/C$49)*100000 -> 0.071663028 | N14: =(D14/D$49)*100000 -> 0.022977846 | O14: =C14/E$45 -> 1.8989299 | P14: =D14/E$46 -> 1.8520604
A15: 14 | B15: Steuerliche Maßnahme | C15: 12 | D15: 14 | E15: =C15/(C15+D15) -> 0.46153846 | F15: =1-E15 -> 0.53846154 | G15: =C15/23 -> 0.52173913 | H15: =D15/15 -> 0.93333333 | I15: =(C15/B$45)*1000 -> 0.63788939 | J15: =(D15/B$46)*1000 -> 0.35253788 | K15: =(C15/D$45)*1000 -> 0.79257771 | L15: =(D15/D$46)*1000 -> 0.38461624 | M15: =(C15/C$49)*100000 -> 0.053747271 | N15: =(D15/D$49)*100000 -> 0.024745373 | O15: =C15/E$45 -> 1.4241975 | P15: =D15/E$46 -> 1.9945265
A16: 31 | B16: Weitere Kredit-/Garantie-Phase | C16: 11 | D16: 14 | E16: =C16/(C16+D16) -> 0.44 | F16: =1-E16 -> 0.56 | G16: =C16/23 -> 0.47826087 | H16: =D16/15 -> 0.93333333 | I16: =(C16/B$45)*1000 -> 0.58473194 | J16: =(D16/B$46)*1000 -> 0.35253788 | K16: =(C16/D$45)*1000 -> 0.72652956 | L16: =(D16/D$46)*1000 -> 0.38461624 | M16: =(C16/C$49)*100000 -> 0.049268332 | N16: =(D16/D$49)*100000 -> 0.024745373 | O16: =C16/E$45 -> 1.3055143 | P16: =D16/E$46 -> 1.9945265
A17: 3 | B17: Steuerliche Maßnahme | C17: 16 | D17: 9 | E17: =C17/(C17+D17) -> 0.64 | F17: =1-E17 -> 0.36 | G17: =C17/23 -> 0.69565217 | H17: =D17/15 -> 0.6 | I17: =(C17/B$45)*1000 -> 0.85051918 | J17: =(D17/B$46)*1000 -> 0.22663149 | K17: =(C17/D$45)*1000 -> 1.0567703 | L17: =(D17/D$46)*1000 -> 0.2472533 | M17: =(C17/C$49)*100000 -> 0.071663028 | N17: =(D17/D$49)*100000 -> 0.01590774 | O17: =C17/E$45 -> 1.8989299 | P17: =D17/E$46 -> 1.2821956
A18: 10 | B18: Steuerliche Maßnahme | C18: 12 | D18: 11 | E18: =C18/(C18+D18) -> 0.52173913 | F18: =1-E18 -> 0.47826087 | G18: =C18/23 -> 0.52173913 | H18: =D18/15 -> 0.73333333 | I18: =(C18/B$45)*1000 -> 0.63788939 | J18: =(D18/B$46)*1000 -> 0.27699405 | K18: =(C18/D$45)*1000 -> 0.79257771 | L18: =(D18/D$46)*1000 -> 0.30219848 | M18: =(C18/C$49)*100000 -> 0.053747271 | N18: =(D18/D$49)*100000 -> 0.019442793 | O18: =C18/E$45 -> 1.4241975 | P18: =D18/E$46 -> 1.567128
A19: 5 | B19: Steuerliche Maßnahme | C19: 10 | D19: 10 | E19: =C19/(C19+D19) -> 0.5 | F19: =1-E19 -> 0.5 | G19: =C19/23 -> 0.43478261 | H19: =D19/15 -> 0.66666667 | I19: =(C19/B$45)*1000 -> 0.53157449 | J19: =(D19/B$46)*1000 -> 0.25181277 | K19: =(C19/D$45)*1000 -> 0.66048142 | L19: =(D19/D$46)*1000 -> 0.27472589 | M19: =(C19/C$49)*100000 -> 0.044789392 | N19: =(D19/D$49)*100000 -> 0.017675266 | O19: =C19/E$45 -> 1.1868312 | P19: =D19/E$46 -> 1.4246618
A20: 4 | B20: Steuerliche Maßnahme | C20: 5 | D20: 14 | E20: =C20/(C20+D20) -> 0.26315789 | F20: =1-E20 -> 0.73684211 | G20: =C20/23 -> 0.2173913 | H20: =D20/15 -> 0.93333333 | I20: =(C20/B$45)*1000 -> 0.26578724 | J20: =(D20/B$46)*1000 -> 0.35253788 | K20: =(C20/D$45)*1000 -> 0.33024071 | L20: =(D20/D$46)*1000 -> 0.38461624 | M20: =(C20/C$49)*100000 -> 0.022394696 | N20: =(D20/D$49)*100000 -> 0.024745373 | O20: =C20/E$45 -> 0.59341561 | P20: =D20/E$46 -> 1.9945265
A21: 9 | B21: Steuererleichterung (z.B. Rückerstattung) | C21: 12 | D21: 6 | E21: =C21/(C21+D21) -> 0.66666667 | F21: =1-E21 -> 0.33333333 | G21: =C21/23 -> 0.52173913 | H21: =D21/15 -> 0.4 | I21: =(C21/B$45)*1000 -> 0.63788939 | J21: =(D21/B$46)*1000 -> 0.15108766 | K21: =(C21/D$45)*1000 -> 0.79257771 | L21: =(D21/D$46)*1000 -> 0.16483553 | M21: =(C21/C$49)*100000 -> 0.053747271 | N21: =(D21/D$49)*100000 -> 0.01060516 | O21: =C21/E$45 -> 1.4241975 | P21: =D21/E$46 -> 0.85479709
... A33: 15 | B33: Einkommenssteuer-Senkung | C33: 6 | D33: 0 | E33: =C33/(C33+D33) -> 1 | F33: =1-E33 -> 0 | G33: =C33/23 -> 0.26086957 | H33: =D33/15 -> 0 | I33: =(C33/B$45)*1000 -> 0.31894469 | J33: =(D33/B$46)*1000 -> 0 | K33: =(C33/D$45)*1000 -> 0.39628885 | L33: =(D33/D$46)*1000 -> 0 | M33: =(C33/C$49)*100000 -> 0.026873635 | N33: =(D33/D$49)*100000 -> 0 | O33: =C33/E$45 -> 0.71209873 | P33: =D33/E$46 -> 0
A34: other (exemption) | B34: USt-Befreiung (z.B. Masken) | C34: 4 | D34: 0 | E34: =C34/(C34+D34) -> 1 | F34: =1-E34 -> 0 | G34: =C34/23 -> 0.17391304 | H34: =D34/15 -> 0 | I34: =(C34/B$45)*1000 -> 0.2126298 | J34: =(D34/B$46)*1000 -> 0 | K34: =(C34/D$45)*1000 -> 0.26419257 | L34: =(D34/D$46)*1000 -> 0 | M34: =(C34/C$49)*100000 -> 0.017915757 | N34: =(D34/D$49)*100000 -> 0 | O34: =C34/E$45 -> 0.47473248 | P34: =D34/E$46 -> 0
A35: 33 | B35: Sonstige Maßnahme | C35: 1 | D35: 2 | E35: =C35/(C35+D35) -> 0.33333333 | F35: =1-E35 -> 0.66666667 | G35: =C35/23 -> 0.043478261 | H35: =D35/15 -> 0.13333333 | I35: =(C35/B$45)*1000 -> 0.053157449 | J35: =(D35/B$46)*1000 -> 0.050362554 | K35: =(C35/D$45)*1000 -> 0.066048142 | L35: =(D35/D$46)*1000 -> 0.054945178 | M35: =(C35/C$49)*100000 -> 0.0044789392 | N35: =(D35/D$49)*100000 -> 0.0035350533 | O35: =C35/E$45 -> 0.11868312 | P35: =D35/E$46 -> 0.28493236
A36: 16 | B36: Steuerliche Maßnahme | C36: 1 | D36: 2 | E36: =C36/(C36+D36) -> 0.33333333 | F36: =1-E36 -> 0.66666667 | G36: =C36/23 -> 0.043478261 | H36: =D36/15 -> 0.13333333 | I36: =(C36/B$45)*1000 -> 0.053157449 | J36: =(D36/B$46)*1000 -> 0.050362554 | K36: =(C36/D$45)*1000 -> 0.066048142 | L36: =(D36/D$46)*1000 -> 0.054945178 | M36: =(C36/C$49)*100000 -> 0.0044789392 | N36: =(D36/D$49)*100000 -> 0.0035350533 | O36: =C36/E$45 -> 0.11868312 | P36: =D36/E$46 -> 0.28493236
A37: 18 | B37: Spenden steuerlich begünstigt | C37: 2 | D37: 0 | E37: =C37/(C37+D37) -> 1 | F37: =1-E37 -> 0 | G37: =C37/23 -> 0.086956522 | H37: =D37/15 -> 0 | I37: =(C37/B$45)*1000 -> 0.1063149 | J37: =(D37/B$46)*1000 -> 0 | K37: =(C37/D$45)*1000 -> 0.13209628 | L37: =(D37/D$46)*1000 -> 0 | M37: =(C37/C$49)*100000 -> 0.0089578785 | N37: =(D37/D$49)*100000 -> 0 | O37: =C37/E$45 -> 0.23736624 | P37: =D37/E$46 -> 0
A38: 22 | B38: Schutzausrüstung Beschaffung | C38: 0 | D38: 1 | E38: =C38/(C38+D38) -> 0 | F38: =1-E38 -> 1 | G38: =C38/23 -> 0 | H38: =D38/15 -> 0.066666667 | I38: =(C38/B$45)*1000 -> 0 | J38: =(D38/B$46)*1000 -> 0.025181277 | K38: =(C38/D$45)*1000 -> 0 | L38: =(D38/D$46)*1000 -> 0.027472589 | M38: =(C38/C$49)*100000 -> 0 | N38: =(D38/D$49)*100000 -> 0.0017675266 | O38: =C38/E$45 -> 0 | P38: =D38/E$46 -> 0.14246618
A39: 21 | B39: Medizinische Güter Finanzierung | C39: 1 | D39: 0 | E39: =C39/(C39+D39) -> 1 | F39: =1-E39 -> 0 | G39: =C39/23 -> 0.043478261 | H39: =D39/15 -> 0 | I39: =(C39/B$45)*1000 -> 0.053157449 | J39: =(D39/B$46)*1000 -> 0 | K39: =(C39/D$45)*1000 -> 0.066048142 | L39: =(D39/D$46)*1000 -> 0 | M39: =(C39/C$49)*100000 -> 0.0044789392 | N39: =(D39/D$49)*100000 -> 0 | O39: =C39/E$45 -> 0.11868312 | P39: =D39/E$46 -> 0
A40: 25/27 | B40: Zusätzliche Transferzahlung | C40: 0 | D40: 1 | E40: =C40/(C40+D40) -> 0 | F40: =1-E40 -> 1 | G40: =C40/23 -> 0 | H40: =D40/15 -> 0.066666667 | I40: =(C40/B$45)*1000 -> 0 | J40: =(D40/B$46)*1000 -> 0.025181277 | K40: =(C40/D$45)*1000 -> 0 | L40: =(D40/D$46)*1000 -> 0.027472589 | M40: =(C40/C$49)*100000 -> 0 | N40: =(D40/D$49)*100000 -> 0.0017675266 | O40: =C40/E$45 -> 0 | P40: =D40/E$46 -> 0.14246618
C42: =SUM(C2:C40) -> 735 | D42: =SUM(D2:D40) -> 597
B43: in 10'000 CHF
A44: Group | B44: pre Covid real GDP ppp (2019) | C44: pre Covid real GDP usd (2019) | E44: ppp per Capita | F44: real per Capita
A45: 0 | B45: 18812.039 | D45: 15140.471 | E45: =(B45/C49)*10000 -> 8.425798 | F45: =B45/D49 -> 0.0003325078
A46: 1 | B46: 39712.045 | D46: 36399.919 | E46: =(B46/D49)*10000 -> 7.0192097 | F46: =D46/D49 -> 0.00064337826
A48: AUS | B48: 25334826 | C48: Gruppe 0 | D48: Gruppe 1
A49: AUT | B49: 8877637 | C49: 22326715 | D49: 56576234
A50: BEL | B50: 11489000
A51: CAN | B51: 37618495
A52: CHE | B52: 8575280
A53: CHL | B53: 19107216
A54: COL | B54: 48322807
A55: CRI | B55: 5055238
A56: CZE | B56: 10550313
A57: DEU | B57: 83093000
A58: DNK | B58: 5816940
A59: ESP | B59: 47105358
A60: EST | B60: 1324820
A61: FIN | B61: 5521600
... A85: USA | B85: 330513000
A87: Showing 10 to 38 of 38 entries, 2 total col

Sheet PolicyLegende
A1: PolicyCode | F1: Policy Category
A2: 1 | B2: Accelerated asset depreciation (CIT) | F2: 1 | G2: Revenue Measures to protect businesses
A3: 2 | B3: Extend loss carry-forward (CIT) | F3: 1 | G3: Revenue Measures to protect businesses
A4: 3 | B4: Broaden tax deductibility | F4: 1 | G4: Revenue Measures to protect businesses
A5: 4 | B5: Tax credits | F5: 1 | G5: Revenue Measures to protect businesses
A6: 5 | B6: Deferral of tax filing | F6: 1 | G6: Revenue Measures to protect businesses
A7: 6 | B7: Deferral of tax payments | F7: 1 | G7: Revenue Measures to protect businesses
A8: 7 | B8: Tax rate reduction | F8: 1 | G8: Revenue Measures to protect businesses
A9: 8 | B9: Tax amnesty / incentives | F9: 1 | G9: Revenue Measures to protect businesses
A10: 9 | B10: Accelerating refunds | F10: 1 | G10: Revenue Measures to protect businesses
A11: 10 | B11: Lower advance payment | F11: 1 | G11: Revenue Measures to protect businesses
A12: 11 | B12: Suspend debt collection | F12: 1 | G12: Revenue Measures to protect businesses
A13: 12 | B13: Suspend audit activities | F13: 1 | G13: Revenue Measures to protect businesses
A14: exemption | B14: Tax exemption/waiver/suspension | F14: 1 | G14: Revenue Measures to protect businesses
A15: other | B15: Other | F15: 1 | G15: Revenue Measures to protect businesses
A16: 13 | B16: Deferral of tax filing | F16: 2 | G16: Revenue Measures to protect individuals
A17: 14 | B17: Deferral of tax payments | F17: 2 | G17: Revenue Measures to protect individuals
A18: 15 | B18: Tax rate reduction | F18: 2 | G18: Revenue Measures to protect individuals
A19: 16 | B19: Tax amnesty / incentives | F19: 2 | G19: Revenue Measures to protect individuals
A20: 17 | B20: Broaden tax deductibility | F20: 2 | G20: Revenue Measures to protect individuals
A21: 18 | B21: Tax credits | F21: 2 | G21: Revenue Measures to protect individuals
A22: exemption | B22: Tax exemption/waiver/suspension | F22: 2 | G22: Revenue Measures to protect individuals
A23: other | B23: Other | F23: 2 | G23: Revenue Measures to protect individuals
A24: 19 | B24: Lower tax rates for medical items | F24: 3 | G24: Revenue Measures to promote availability of medical items
A25: exemption | B25: Tax exemption/waiver/suspension | F25: 3 | G25: Revenue Measures to promote availability of medical items
A26: other | B26: Other | F26: 3 | G26: Revenue Measures to promote availability of medical items
A27: 20 | B27: Lower tax rates | F27: 4 | G27: Revenue Measures to boost consumption / demand
A28: exemption | B28: Tax exemption/waiver/suspension | F28: 4 | G28: Revenue Measures to boost consumption / demand
A29: other | B29: Other | F29: 4 | G29: Revenue Measures to boost consumption / demand
A30: 21 | B30: Supply of low cost medical items | F30: 5 | G30: Health Expenditures measures
A31: 22 | B31: Supply of high cost medical items | F31: 5 | G31: Health Expenditures measures
A32: 23 | B32: Targeted infrastructure investments | F32: 5 | G32: Health Expenditures measures
A33: 24 | B33: Expansion of human resources | F33: 5 | G33: Health Expenditures measures
A34: general | B34: General | F34: 5 | G34: Health Expenditures measures
A35: 25 | B35: Direct cash transfers for individuals | F35: 6 | G35: Expenditure Measures for cash transfers to individuals
A36: 26 | B36: Expansion of unemployment benefits | F36: 6 | G36: Expenditure Measures for cash transfers to individuals
A37: 27 | B37: Temporary expansion of existing benefits | F37: 6 | G37: Expenditure Measures for cash transfers to individuals
A38: 28 | B38: Supplementary ad hoc programs | F38: 6 | G38: Expenditure Measures for cash transfers to individuals
A39: 29 | B39: Wage compensation/ enhanced paid leave | F39: 6 | G39: Expenditure Measures for cash transfers to individuals
A40: other | B40: Other | F40: 6 | G40: Expenditure Measures for cash transfers to individuals
A41: 30 | B41: Preferential loans to firms | F41: 7 | G41: Credit and equity measures
A42: 31 | B42: One-off grants | F42: 7 | G42: Credit and equity measures
A43: 32 | B43: Preferential loans to households | F43: 7 | G43: Credit and equity measures
A44: other | B44: Other | F44: 7 | G44: Credit and equity measures
A45: 33 | B45: Revenue increase | F45: 8 | G45: Revenue Measures to raise revenue
A46: 34 | B46: Income support | F46: 9 | G46: Expenditure Measures for businesses

Sheet Introduction

Sheet Sample Selection
I2: Number | J2: List of Selected Countries
I3: =IF(MAX('Sample Select backend'!$K$4:$K$205)>=ROW(I3)-2,ROW(I3)-2,"") -> #N/A | J3: =IFERROR(VLOOKUP(I3,'Sample Select backend'!$K$4:$L$205,2,FALSE),"No countries selected!") -> No countries selected!
I4: =IF(MAX('Sample Select backend'!$K$4:$K$205)>=ROW(I4)-2,ROW(I4)-2,"") -> #N/A | J4: =IFERROR(VLOOKUP(I4,'Sample Select backend'!$K$4:$L$205,2,FALSE),"")
I5: =IF(MAX('Sample Select backend'!$K$4:$K$205)>=ROW(I5)-2,ROW(I5)-2,"") -> #N/A | J5: =IFERROR(VLOOKUP(I5,'Sample Select backend'!$K$4:$L$205,2,FALSE),"")
I6: =IF(MAX('Sample Select backend'!$K$4:$K$205)>=ROW(I6)-2,ROW(I6)-2,"") -> #N/A | J6: =IFERROR(VLOOKUP(I6,'Sample Select backend'!$K$4:$L$205,2,FALSE),"")
I7: =IF(MAX('Sample Select backend'!$K$4:$K$205)>=ROW(I7)-2,ROW(I7)-2,"") -> #N/A | J7: =IFERROR(VLOOKUP(I7,'Sample Select backend'!$K$4:$L$205,2,FALSE),"")
I8: =IF(MAX('Sample Select backend'!$K$4:$K$205)>=ROW(I8)-2,ROW(I8)-2,"") -> #N/A | J8: =IFERROR(VLOOKUP(I8,'Sample Select backend'!$K$4:$L$205,2,FALSE),"")
I9: =IF(MAX('Sample Select backend'!$K$4:$K$205)>=ROW(I9)-2,ROW(I9)-2,"") -> #N/A | J9: =IFERROR(VLOOKUP(I9,'Sample Select backend'!$K$4:$L$205,2,FALSE),"")
I10: =IF(MAX('Sample Select backend'!$K$4:$K$205)>=ROW(I10)-2,ROW(I10)-2,"") -> #N/A | J10: =IFERROR(VLOOKUP(I10,'Sample Select backend'!$K$4:$L$205,2,FALSE),"")
I11: =IF(MAX('Sample Select backend'!$K$4:$K$205)>=ROW(I11)-2,ROW(I11)-2,"") -> #N/A | J11: =IFERROR(VLOOKUP(I11,'Sample Select backend'!$K$4:$L$205,2,FALSE),"")
I12: =IF(MAX('Sample Select backend'!$K$4:$K$205)>=ROW(I12)-2,ROW(I12)-2,"") -> #N/A | J12: =IFERROR(VLOOKUP(I12,'Sample Select backend'!$K$4:$L$205,2,FALSE),"")
I13: =IF(MAX('Sample Select backend'!$K$4:$K$205)>=ROW(I13)-2,ROW(I13)-2,"") -> #N/A | J13: =IFERROR(VLOOKUP(I13,'Sample Select backend'!$K$4:$L$205,2,FALSE),"")
I14: =IF(MAX('Sample Select backend'!$K$4:$K$205)>=ROW(I14)-2,ROW(I14)-2,"") -> #N/A | J14: =IFERROR(VLOOKUP(I14,'Sample Select backend'!$K$4:$L$205,2,FALSE),"")
I15: =IF(MAX('Sample Select backend'!$K$4:$K$205)>=ROW(I15)-2,ROW(I15)-2,"") -> #N/A | J15: =IFERROR(VLOOKUP(I15,'Sample Select backend'!$K$4:$L$205,2,FALSE),"")
... I204: =IF(MAX('Sample Select backend'!$K$4:$K$205)>=ROW(I204)-2,ROW(I204)-2,"") -> #N/A | J204: =IFERROR(VLOOKUP(I204,'Sample Select backend'!$K$4:$L$205,2,FALSE),"")

Sheet Sample Select backend
B2: 4 | C2: =OFFSET(B2,B2,0) -> South Asia | E2: 1 | F2: =OFFSET(E2,E2,0) -> All Income Levels | H2: 1 | I2: =OFFSET(H2,H2,1) -> Data!$AJ:$AJ | J2: =RIGHT(OFFSET(H2,H2,1),2) -> AJ | L2: 1 | M2: =OFFSET(L2,L2,0) -> All Countries | AC2: # of policies | AD2: rank | AE2: rownum | AF2: nth of rank | AG2: % of total
B3: All Regions | C3: =IF(B2>1,"Data!$O:$O","Data!$AE:$AE") -> Data!$O:$O | E3: All Income Levels | F3: =IF(E2>1,"Data!$Q:$Q","Data!$AF:$AF") -> Data!$AF:$AF | H3: All Lending Categories | I3: Data!$AJ:$AJ | L3: All Countries | M3: =IF(L2>1,"Data!$A:$A","Data!$AK:$AK") -> Data!$AK:$AK | P3: 1 | Q3: Revenue Measures to protect businesses | R3: 1 | S3: Accelerated asset depreciation (CIT) | Y3: 7 | Z3: Credit and equity measures | AA3: Other | AB3: Other | AC3: =COUNTIFS(Data!$J:$J,$Y3,Data!$AJ:$AJ,$AA3,INDIRECT($C$3),$C$2,INDIRECT($F$3),$F$2,INDIRECT($I$2),1,INDIRECT($M$3),$M$2,INDIRECT($I$9),1) -> 0 | AD3: =IF(AC3>0,RANK(AC3,AC$3:AC$55),#N/A) -> #N/A | AE3: =ROW(AE3) -> 3 | AF3: =COUNTIF(AD$3:AD3,AD3) -> 1 | AG3: =AC3/$AH$17*100 -> #REF! | AO3: =Z3 -> Credit and equity measures | AP3: =AB3 -> Other | AQ3: =AC3 -> 0
B4: Europe & Central Asia | C4: =IF(B2>1,"O","AE") -> O | E4: Low Income | F4: =IF(E2>1,"Q","AF") -> AF | H4: IDA/Blend only | I4: Data!$AG:$AG | K4: =IF(VLOOKUP($L4,Data!$B$2:$AI$1588,39,FALSE)=1,1+MAX($K$3:K3),0) -> #N/A | L4: Afghanistan | M4: =IF(L2>1,"A","AK") -> AK | P4: 1 | Q4: Revenue Measures to protect businesses | R4: 2 | S4: Extend loss carry-forward (CIT) | Y4: 7 | Z4: Credit and equity measures | AA4: 32 | AB4: Preferential loans to households | AC4: =COUNTIFS(Data!$J:$J,$Y4,Data!$AJ:$AJ,$AA4,INDIRECT($C$3),$C$2,INDIRECT($F$3),$F$2,INDIRECT($I$2),1,INDIRECT($M$3),$M$2,INDIRECT($I$9),1) -> 0 | AD4: =IF(AC4>0,RANK(AC4,AC$3:AC$55),#N/A) -> #N/A | AE4: =ROW(AE4) -> 4 | AF4: =COUNTIF(AD$3:AD4,AD4) -> 2 | AG4: =AC4/$AH$17*100 -> #REF! | AP4: =AB4 -> Preferential loans to households | AQ4: =AC4 -> 0
B5: Latin America & the Caribbean | E5: Lower Middle Income | H5: IBRD only | I5: Data!$AH:$AH | K5: =IF(VLOOKUP($L5,Data!$B$2:$AI$1588,39,FALSE)=1,1+MAX($K$3:K4),0) -> #N/A | L5: Albania | P5: 1 | Q5: Revenue Measures to protect businesses | R5: 3 | S5: Broaden tax deductibility | Y5: 7 | Z5: Credit and equity measures | AA5: 31 | AB5: One-off grants | AC5: =COUNTIFS(Data!$J:$J,$Y5,Data!$AJ:$AJ,$AA5,INDIRECT($C$3),$C$2,INDIRECT($F$3),$F$2,INDIRECT($I$2),1,INDIRECT($M$3),$M$2,INDIRECT($I$9),1) -> 0 | AD5: =IF(AC5>0,RANK(AC5,AC$3:AC$55),#N/A) -> #N/A | AE5: =ROW(AE5) -> 5 | AF5: =COUNTIF(AD$3:AD5,AD5) -> 3 | AG5: =AC5/$AH$17*100 -> #REF! | AP5: =AB5 -> One-off grants | AQ5: =AC5 -> 0 | AT5: May 1 2020 | AU5: Sept 1 2020
B6: South Asia | E6: Upper Middle Income | H6: Neither IDA nor IBRD | I6: Data!$AI:$AI | K6: =IF(VLOOKUP($L6,Data!$B$2:$AI$1588,39,FALSE)=1,1+MAX($K$3:K5),0) -> #N/A | L6: Algeria | P6: 1 | Q6: Revenue Measures to protect businesses | R6: 4 | S6: Tax credits | Y6: 7 | Z6: Credit and equity measures | AA6: 30 | AB6: Preferential loans to firms | AC6: =COUNTIFS(Data!$J:$J,$Y6,Data!$AJ:$AJ,$AA6,INDIRECT($C$3),$C$2,INDIRECT($F$3),$F$2,INDIRECT($I$2),1,INDIRECT($M$3),$M$2,INDIRECT($I$9),1) -> 0 | AD6: =IF(AC6>0,RANK(AC6,AC$3:AC$55),#N/A) -> #N/A | AE6: =ROW(AE6) -> 6 | AF6: =COUNTIF(AD$3:AD6,AD6) -> 4 | AG6: =AC6/$AH$17*100 -> #REF! | AH6: =_xlfn.CONCAT("Total revenue measures: ",AH7) -> Total revenue measures: 0 | AP6: =AB6 -> Preferential loans to firms | AQ6: =AC6 -> 0 | AT6: =COUNTIFS(Data!#REF!,1,Data!$AL:$AL,1) -> #REF! | AU6: =AH17-AT6 -> #REF!
B7: Sub-Saharan Africa | E7: High Income | I7: =OFFSET(H2,H2,0) -> All Lending Categories | K7: =IF(VLOOKUP($L7,Data!$B$2:$AI$1588,39,FALSE)=1,1+MAX($K$3:K6),0) -> #N/A | L7: Angola | P7: 1 | Q7: Revenue Measures to protect businesses | R7: 5 | S7: Deferral of tax filing | AH7: =SUM(Q57:Q61) -> 0 | AO7: =Z8 -> Expenditure Measures for cash transfers to individuals | AP7: =AB8 -> Other | AQ7: =AC8 -> 0
B8: Middle East & North Africa | K8: =IF(VLOOKUP($L8,Data!$B$2:$AI$1588,39,FALSE)=1,1+MAX($K$3:K7),0) -> #N/A | L8: Anguilla | P8: 1 | Q8: Revenue Measures to protect businesses | R8: 6 | S8: Deferral of tax payments | Y8: 6 | Z8: Expenditure Measures for cash transfers to individuals | AA8: Other | AB8: Other | AC8: =COUNTIFS(Data!$J:$J,$Y8,Data!$AJ:$AJ,$AA8,INDIRECT($C$3),$C$2,INDIRECT($F$3),$F$2,INDIRECT($I$2),1,INDIRECT($M$3),$M$2,INDIRECT($I$9),1) -> 0 | AD8: =IF(AC8>0,RANK(AC8,AC$3:AC$55),#N/A) -> #N/A | AE8: =ROW(AE8) -> 8 | AF8: =COUNTIF(AD$3:AD8,AD8) -> 5 | AG8: =AC8/$AH$17*100 -> #REF! | AP8: =AB9 -> Wage compensation/ enhanced paid leave | AQ8: =AC9 -> 0
B9: East Asia & Pacific | G9: FCV: | H9: FALSE | I9: =IF(H9,"Data!$R:$R","Data!$AJ:$AJ") -> Data!$AJ:$AJ | K9: =IF(VLOOKUP($L9,Data!$B$2:$AI$1588,39,FALSE)=1,1+MAX($K$3:K8),0) -> #N/A | L9: Antigua and Barbuda | P9: 1 | Q9: Revenue Measures to protect businesses | R9: 7 | S9: Tax rate reduction | Y9: 6 | Z9: Expenditure Measures for cash transfers to individuals | AA9: 29 | AB9: Wage compensation/ enhanced paid leave | AC9: =COUNTIFS(Data!$J:$J,$Y9,Data!$AJ:$AJ,$AA9,INDIRECT($C$3),$C$2,INDIRECT($F$3),$F$2,INDIRECT($I$2),1,INDIRECT($M$3),$M$2,INDIRECT($I$9),1) -> 0 | AD9: =IF(AC9>0,RANK(AC9,AC$3:AC$55),#N/A) -> #N/A | AE9: =ROW(AE9) -> 9 | AF9: =COUNTIF(AD$3:AD9,AD9) -> 6 | AG9: =AC9/$AH$17*100 -> #REF! | AH9: =_xlfn.CONCAT("Total expenditure measures: ",AH10) -> Total expenditure measures: 0 | AP9: =AB10 -> Supplementary ad hoc programs | AQ9: =AC10 -> 0
B10: North America | G10: =IF(H9,"FCV","both FCV and Non-FCV") -> both FCV and Non-FCV | I10: =IF(H9,"R","AJ") -> AJ | K10: =IF(VLOOKUP($L10,Data!$B$2:$AI$1588,39,FALSE)=1,1+MAX($K$3:K9),0) -> #N/A | L10: Argentina | P10: 1 | Q10: Revenue Measures to protect businesses | R10: 8 | S10: Tax amnesty / incentives | Y10: 6 | Z10: Expenditure Measures for cash transfers to individuals | AA10: 28 | AB10: Supplementary ad hoc programs | AC10: =COUNTIFS(Data!$J:$J,$Y10,Data!$AJ:$AJ,$AA10,INDIRECT($C$3),$C$2,INDIRECT($F$3),$F$2,INDIRECT($I$2),1,INDIRECT($M$3),$M$2,INDIRECT($I$9),1) -> 0 | AD10: =IF(AC10>0,RANK(AC10,AC$3:AC$55),#N/A) -> #N/A | AE10: =ROW(AE10) -> 10 | AF10: =COUNTIF(AD$3:AD10,AD10) -> 7 | AG10: =AC10/$AH$17*100 -> #REF! | AH10: =SUM(Q54:Q56) -> 0 | AP10: =AB11 -> Temporary expansion of existing benefits | AQ10: =AC11 -> 0
K11: =IF(VLOOKUP($L11,Data!$B$2:$AI$1588,39,FALSE)=1,1+MAX($K$3:K10),0) -> #N/A | L11: Armenia | P11: 1 | Q11: Revenue Measures to protect businesses | R11: 9 | S11: Accelerating refunds | Y11: 6 | Z11: Expenditure Measures for cash transfers to individuals | AA11: 27 | AB11: Temporary expansion of existing benefits | AC11: =COUNTIFS(Data!$J:$J,$Y11,Data!$AJ:$AJ,$AA11,INDIRECT($C$3),$C$2,INDIRECT($F$3),$F$2,INDIRECT($I$2),1,INDIRECT($M$3),$M$2,INDIRECT($I$9),1) -> 0 | AD11: =IF(AC11>0,RANK(AC11,AC$3:AC$55),#N/A) -> #N/A | AE11: =ROW(AE11) -> 11 | AF11: =COUNTIF(AD$3:AD11,AD11) -> 8 | AG11: =AC11/$AH$17*100 -> #REF! | AP11: =AB12 -> Expansion of unemployment benefits | AQ11: =AC12 -> 0
K12: =IF(VLOOKUP($L12,Data!$B$2:$AI$1588,39,FALSE)=1,1+MAX($K$3:K11),0) -> #N/A | L12: Aruba | P12: 1 | Q12: Revenue Measures to protect businesses | R12: 10 | S12: Lower advance payment | Y12: 6 | Z12: Expenditure Measures for cash transfers to individuals | AA12: 26 | AB12: Expansion of unemployment benefits | AC12: =COUNTIFS(Data!$J:$J,$Y12,Data!$AJ:$AJ,$AA12,INDIRECT($C$3),$C$2,INDIRECT($F$3),$F$2,INDIRECT($I$2),1,INDIRECT($M$3),$M$2,INDIRECT($I$9),1) -> 0 | AD12: =IF(AC12>0,RANK(AC12,AC$3:AC$55),#N/A) -> #N/A | AE12: =ROW(AE12) -> 12 | AF12: =COUNTIF(AD$3:AD12,AD12) -> 9 | AG12: =AC12/$AH$17*100 -> #REF! | AH12: =_xlfn.CONCAT("Total credit and equity measures: ",Q53) -> Total credit and equity measures: 0 | AP12: =AB13 -> Direct cash transfers for individuals | AQ12: =AC13 -> 0
K13: =IF(VLOOKUP($L13,Data!$B$2:$AI$1588,39,FALSE)=1,1+MAX($K$3:K12),0) -> #REF! | L13: Australia | P13: 1 | Q13: Revenue Measures to protect businesses | R13: 11 | S13: Suspend debt collection | Y13: 6 | Z13: Expenditure Measures for cash transfers to individuals | AA13: 25 | AB13: Direct cash transfers for individuals | AC13: =COUNTIFS(Data!$J:$J,$Y13,Data!$AJ:$AJ,$AA13,INDIRECT($C$3),$C$2,INDIRECT($F$3),$F$2,INDIRECT($I$2),1,INDIRECT($M$3),$M$2,INDIRECT($I$9),1) -> 0 | AD13: =IF(AC13>0,RANK(AC13,AC$3:AC$55),#N/A) -> #N/A | AE13: =ROW(AE13) -> 13 | AF13: =COUNTIF(AD$3:AD13,AD13) -> 10 | AG13: =AC13/$AH$17*100 -> #REF! | AO13: =Z15 -> Health Expenditures measures | AP13: =AB15 -> General | AQ13: =AC15 -> 0
K14: =IF(VLOOKUP($L14,Data!$B$2:$AI$1588,39,FALSE)=1,1+MAX($K$3:K13),0) -> #REF! | L14: Austria | P14: 1 | Q14: Revenue Measures to protect businesses | R14: 12 | S14: Suspend audit activities | AH14: =_xlfn.CONCAT("Total other measures: ",Q52) -> #REF! | AP14: =AB16 -> Expansion of human resources | AQ14: =AC16 -> 0
K15: =IF(VLOOKUP($L15,Data!$B$2:$AI$1588,39,FALSE)=1,1+MAX($K$3:K14),0) -> #N/A | L15: Azerbaijan | P15: 1 | Q15: Revenue Measures to protect businesses | R15: exemption | S15: Tax exemption/waiver/suspension | Y15: 5 | Z15: Health Expenditures measures | AA15: General | AB15: General | AC15: =COUNTIFS(Data!$J:$J,$Y15,Data!$AJ:$AJ,$AA15,INDIRECT($C$3),$C$2,INDIRECT($F$3),$F$2,INDIRECT($I$2),1,INDIRECT($M$3),$M$2,INDIRECT($I$9),1) -> 0 | AD15: =IF(AC15>0,RANK(AC15,AC$3:AC$55),#N/A) -> #N/A | AE15: =ROW(AE15) -> 15 | AF15: =COUNTIF(AD$3:AD15,AD15) -> 11 | AG15: =AC15/$AH$17*100 -> #REF! | AP15: =AB17 -> Targeted infrastructure investments | AQ15: =AC17 -> 0
K16: =IF(VLOOKUP($L16,Data!$B$2:$AI$1588,39,FALSE)=1,1+MAX($K$3:K15),0) -> #N/A | L16: Bahamas, The | P16: 1 | Q16: Revenue Measures to protect businesses | R16: other | S16: Other | Y16: 5 | Z16: Health Expenditures measures | AA16: 24 | AB16: Expansion of human resources | AC16: =COUNTIFS(Data!$J:$J,$Y16,Data!$AJ:$AJ,$AA16,INDIRECT($C$3),$C$2,INDIRECT($F$3),$F$2,INDIRECT($I$2),1,INDIRECT($M$3),$M$2,INDIRECT($I$9),1) -> 0 | AD16: =IF(AC16>0,RANK(AC16,AC$3:AC$55),#N/A) -> #N/A | AE16: =ROW(AE16) -> 16 | AF16: =COUNTIF(AD$3:AD16,AD16) -> 12 | AG16: =AC16/$AH$17*100 -> #REF! | AH16: =_xlfn.CONCAT("Total measures: ",AH17) -> #REF! | AP16: =AB18 -> Supply of high cost medical items | AQ16: =AC18 -> 0
K17: =IF(VLOOKUP($L17,Data!$B$2:$AI$1588,39,FALSE)=1,1+MAX($K$3:K16),0) -> #N/A | L17: Bahrain | P17: 2 | Q17: Revenue Measures to protect individuals | R17: 13 | S17: Deferral of tax filing | Y17: 5 | Z17: Health Expenditures measures | AA17: 23 | AB17: Targeted infrastructure investments | AC17: =COUNTIFS(Data!$J:$J,$Y17,Data!$AJ:$AJ,$AA17,INDIRECT($C$3),$C$2,INDIRECT($F$3),$F$2,INDIRECT($I$2),1,INDIRECT($M$3),$M$2,INDIRECT($I$9),1) -> 0 | AD17: =IF(AC17>0,RANK(AC17,AC$3:AC$55),#N/A) -> #N/A | AE17: =ROW(AE17) -> 17 | AF17: =COUNTIF(AD$3:AD17,AD17) -> 13 | AG17: =AC17/$AH$17*100 -> #REF! | AH17: =SUM(AH7,AH10,Q52,Q53) -> #REF! | AP17: =AB19 -> Supply of low cost medical items | AQ17: =AC19 -> 0
C18: =_xlfn.CONCAT("Current sample: ",IF(MAX(K4:K202)=0,"No countries",IF(L2>1,M2,_xlfn.CONCAT(F2,", ",I7,", ",G10,", from ",C2)))) -> #N/A | K18: =IF(VLOOKUP($L18,Data!$B$2:$AI$1588,39,FALSE)=1,1+MAX($K$3:K17),0) -> #N/A | L18: Bangladesh | P18: 2 | Q18: Revenue Measures to protect individuals | R18: 14 | S18: Deferral of tax payments | Y18: 5 | Z18: Health Expenditures measures | AA18: 22 | AB18: Supply of high cost medical items | AC18: =COUNTIFS(Data!$J:$J,$Y18,Data!$AJ:$AJ,$AA18,INDIRECT($C$3),$C$2,INDIRECT($F$3),$F$2,INDIRECT($I$2),1,INDIRECT($M$3),$M$2,INDIRECT($I$9),1) -> 0 | AD18: =IF(AC18>0,RANK(AC18,AC$3:AC$55),#N/A) -> #N/A | AE18: =ROW(AE18) -> 18 | AF18: =COUNTIF(AD$3:AD18,AD18) -> 14 | AG18: =AC18/$AH$17*100 -> #REF! | AO18: =Z21 -> Revenue Measures to boost consumption / demand | AP18: =AB21 -> Other | AQ18: =AC21 -> 0
K19: =IF(VLOOKUP($L19,Data!$B$2:$AI$1588,39,FALSE)=1,1+MAX($K$3:K18),0) -> #N/A | L19: Barbados | P19: 2 | Q19: Revenue Measures to protect individuals | R19: 15 | S19: Tax rate reduction | Y19: 5 | Z19: Health Expenditures measures | AA19: 21 | AB19: Supply of low cost medical items | AC19: =COUNTIFS(Data!$J:$J,$Y19,Data!$AJ:$AJ,$AA19,INDIRECT($C$3),$C$2,INDIRECT($F$3),$F$2,INDIRECT($I$2),1,INDIRECT($M$3),$M$2,INDIRECT($I$9),1) -> 0 | AD19: =IF(AC19>0,RANK(AC19,AC$3:AC$55),#N/A) -> #N/A | AE19: =ROW(AE19) -> 19 | AF19: =COUNTIF(AD$3:AD19,AD19) -> 15 | AG19: =AC19/$AH$17*100 -> #REF! | AH19: Non-health | AP19: =AB22 -> Tax exemption/waiver/suspension | AQ19: =AC22 -> 0
K20: =IF(VLOOKUP($L20,Data!$B$2:$AI$1588,39,FALSE)=1,1+MAX($K$3:K19),0) -> #N/A | L20: Belarus | P20: 2 | Q20: Revenue Measures to protect individuals | R20: 16 | S20: Tax amnesty / incentives | AH20: =AH17-Q56 -> #REF! | AP20: =AB23 -> Lower tax rates | AQ20: =AC23 -> 0
K21: =IF(VLOOKUP($L21,Data!$B$2:$AI$1588,39,FALSE)=1,1+MAX($K$3:K20),0) -> #REF! | L21: Belgium | P21: 2 | Q21: Revenue Measures to protect individuals | R21: 17 | S21: Broaden tax deductibility | Y21: 4 | Z21: Revenue Measures to boost consumption / demand | AA21: Other | AB21: Other | AC21: =COUNTIFS(Data!$J:$J,$Y21,Data!$AJ:$AJ,$AA21,INDIRECT($C$3),$C$2,INDIRECT($F$3),$F$2,INDIRECT($I$2),1,INDIRECT($M$3),$M$2,INDIRECT($I$9),1) -> 0 | AD21: =IF(AC21>0,RANK(AC21,AC$3:AC$55),#N/A) -> #N/A | AE21: =ROW(AE21) -> 21 | AF21: =COUNTIF(AD$3:AD21,AD21) -> 16 | AG21: =AC21/$AH$17*100 -> #REF! | AO21: =Z25 -> Revenue Measures to promote availability of medical items | AP21: =AB25 -> Other | AQ21: =AC25 -> 0
B22: Comparator for "performance within sample" sheet | K22: =IF(VLOOKUP($L22,Data!$B$2:$AI$1588,39,FALSE)=1,1+MAX($K$3:K21),0) -> #N/A | L22: Belize | P22: 2 | Q22: Revenue Measures to protect individuals | R22: 18 | S22: Tax credits | Y22: 4 | Z22: Revenue Measures to boost consumption / demand | AA22: Tax exemption/waiver/suspension | AB22: Tax exemption/waiver/suspension | AC22: =COUNTIFS(Data!$J:$J,$Y22,Data!$AJ:$AJ,$AA22,INDIRECT($C$3),$C$2,INDIRECT($F$3),$F$2,INDIRECT($I$2),1,INDIRECT($M$3),$M$2,INDIRECT($I$9),1) -> 0 | AD22: =IF(AC22>0,RANK(AC22,AC$3:AC$55),#N/A) -> #N/A | AE22: =ROW(AE22) -> 22 | AF22: =COUNTIF(AD$3:AD22,AD22) -> 17 | AG22: =AC22/$AH$17*100 -> #REF! | AP22: =AB26 -> Tax exemption/waiver/suspension | AQ22: =AC26 -> 0
C23: Regions | D23: Income | E23: Lending | F23: FCV | G23: Country | K23: =IF(VLOOKUP($L23,Data!$B$2:$AI$1588,39,FALSE)=1,1+MAX($K$3:K22),0) -> #N/A | L23: Benin | P23: 2 | Q23: Revenue Measures to protect individuals | R23: exemption | S23: Tax exemption/waiver/suspension | Y23: 4 | Z23: Revenue Measures to boost consumption / demand | AA23: 20 | AB23: Lower tax rates | AC23: =COUNTIFS(Data!$J:$J,$Y23,Data!$AJ:$AJ,$AA23,INDIRECT($C$3),$C$2,INDIRECT($F$3),$F$2,INDIRECT($I$2),1,INDIRECT($M$3),$M$2,INDIRECT($I$9),1) -> 0 | AD23: =IF(AC23>0,RANK(AC23,AC$3:AC$55),#N/A) -> #N/A | AE23: =ROW(AE23) -> 23 | AF23: =COUNTIF(AD$3:AD23,AD23) -> 18 | AG23: =AC23/$AH$17*100 -> #REF! | AP23: =AB27 -> Lower tax rates for medical items | AQ23: =AC27 -> 0
B24: Cell link | C24: 1 | D24: 2 | E24: 2 | F24: FALSE | G24: 1 | K24: =IF(VLOOKUP($L24,Data!$B$2:$AI$1588,39,FALSE)=1,1+MAX($K$3:K23),0) -> #N/A | L24: Bermuda | P24: 2 | Q24: Revenue Measures to protect individuals | R24: other | S24: Other | AO24: =Z29 -> Revenue Measures to protect individuals | AP24: =AB29 -> Other | AQ24: =AC29 -> 0
B25: Condition | C25: =OFFSET(B2,C24,0) -> All Regions | D25: =OFFSET(E2,D24,0) -> Low Income | E25: 1 | F25: 1 | G25: =OFFSET(L2,G24,0) -> All Countries | K25: =IF(VLOOKUP($L25,Data!$B$2:$AI$1588,39,FALSE)=1,1+MAX($K$3:K24),0) -> #N/A | L25: Bhutan | P25: 3 | Q25: Revenue Measures to promote availability of medical items | R25: 19 | S25: Lower tax rates for medical items | Y25: 3 | Z25: Revenue Measures to promote availability of medical items | AA25: Other | AB25: Other | AC25: =COUNTIFS(Data!$J:$J,$Y25,Data!$AJ:$AJ,$AA25,INDIRECT($C$3),$C$2,INDIRECT($F$3),$F$2,INDIRECT($I$2),1,INDIRECT($M$3),$M$2,INDIRECT($I$9),1) -> 0 | AD25: =IF(AC25>0,RANK(AC25,AC$3:AC$55),#N/A) -> #N/A | AE25: =ROW(AE25) -> 25 | AF25: =COUNTIF(AD$3:AD25,AD25) -> 19 | AG25: =AC25/$AH$17*100 -> #REF! | AP25: =AB30 -> Tax exemption/waiver/suspension | AQ25: =AC30 -> 0
B26: Address | C26: =IF(C24>1,"Data!$O:$O","Data!$AE:$AE") -> Data!$AE:$AE | D26: =IF(D24>1,"Data!$Q:$Q","Data!$AF:$AF") -> Data!$Q:$Q | E26: =OFFSET(H2,E24,1) -> Data!$AG:$AG | F26: =IF(F24,"Data!$R:$R","Data!$AJ:$AJ") -> Data!$AJ:$AJ | G26: =IF(G24>1,"Data!$A:$A","Data!$AK:$AK") -> Data!$AK:$AK | K26: =IF(VLOOKUP($L26,Data!$B$2:$AI$1588,39,FALSE)=1,1+MAX($K$3:K25),0) -> #N/A | L26: Bolivia | P26: 3 | Q26: Revenue Measures to promote availability of medical items | R26: exemption | S26: Tax exemption/waiver/suspension | Y26: 3 | Z26: Revenue Measures to promote availability of medical items | AA26: Tax exemption/waiver/suspension | AB26: Tax exemption/waiver/suspension | AC26: =COUNTIFS(Data!$J:$J,$Y26,Data!$AJ:$AJ,$AA26,INDIRECT($C$3),$C$2,INDIRECT($F$3),$F$2,INDIRECT($I$2),1,INDIRECT($M$3),$M$2,INDIRECT($I$9),1) -> 0 | AD26: =IF(AC26>0,RANK(AC26,AC$3:AC$55),#N/A) -> #N/A | AE26: =ROW(AE26) -> 26 | AF26: =COUNTIF(AD$3:AD26,AD26) -> 20 | AG26: =AC26/$AH$17*100 -> #REF! | AP26: =AB31 -> Tax credits | AQ26: =AC31 -> 0
K27: =IF(VLOOKUP($L27,Data!$B$2:$AI$1588,39,FALSE)=1,1+MAX($K$3:K26),0) -> #N/A | L27: Bosnia and Herzegovina | P27: 3 | Q27: Revenue Measures to promote availability of medical items | R27: other | S27: Other | Y27: 3 | Z27: Revenue Measures to promote availability of medical items | AA27: 19 | AB27: Lower tax rates for medical items | AC27: =COUNTIFS(Data!$J:$J,$Y27,Data!$AJ:$AJ,$AA27,INDIRECT($C$3),$C$2,INDIRECT($F$3),$F$2,INDIRECT($I$2),1,INDIRECT($M$3),$M$2,INDIRECT($I$9),1) -> 0 | AD27: =IF(AC27>0,RANK(AC27,AC$3:AC$55),#N/A) -> #N/A | AE27: =ROW(AE27) -> 27 | AF27: =COUNTIF(AD$3:AD27,AD27) -> 21 | AG27: =AC27/$AH$17*100 -> #REF! | AP27: =AB32 -> Broaden tax deductibility | AQ27: =AC32 -> 0
K28: =IF(VLOOKUP($L28,Data!$B$2:$AI$1588,39,FALSE)=1,1+MAX($K$3:K27),0) -> #N/A | L28: Botswana | P28: 4 | Q28: Revenue Measures to boost consumption / demand | R28: 20 | S28: Lower tax rates | AP28: =AB33 -> Tax amnesty / incentives | AQ28: =AC33 -> 0
K29: =IF(VLOOKUP($L29,Data!$B$2:$AI$1588,39,FALSE)=1,1+MAX($K$3:K28),0) -> #N/A | L29: Brazil | P29: 4 | Q29: Revenue Measures to boost consumption / demand | R29: exemption | S29: Tax exemption/waiver/suspension | Y29: 2 | Z29: Revenue Measures to protect individuals | AA29: Other | AB29: Other | AC29: =COUNTIFS(Data!$J:$J,$Y29,Data!$AJ:$AJ,$AA29,INDIRECT($C$3),$C$2,INDIRECT($F$3),$F$2,INDIRECT($I$2),1,INDIRECT($M$3),$M$2,INDIRECT($I$9),1) -> 0 | AD29: =IF(AC29>0,RANK(AC29,AC$3:AC$55),#N/A) -> #N/A | AE29: =ROW(AE29) -> 29 | AF29: =COUNTIF(AD$3:AD29,AD29) -> 22 | AG29: =AC29/$AH$17*100 -> #REF! | AP29: =AB34 -> Tax rate reduction | AQ29: =AC34 -> 0
K30: =IF(VLOOKUP($L30,Data!$B$2:$AI$1588,39,FALSE)=1,1+MAX($K$3:K29),0) -> #N/A | L30: British Virgin Islands | P30: 4 | Q30: Revenue Measures to boost consumption / demand | R30: other | S30: Other | Y30: 2 | Z30: Revenue Measures to protect individuals | AA30: Tax exemption/waiver/suspension | AB30: Tax exemption/waiver/suspension | AC30: =COUNTIFS(Data!$J:$J,$Y30,Data!$AJ:$AJ,$AA30,INDIRECT($C$3),$C$2,INDIRECT($F$3),$F$2,INDIRECT($I$2),1,INDIRECT($M$3),$M$2,INDIRECT($I$9),1) -> 0 | AD30: =IF(AC30>0,RANK(AC30,AC$3:AC$55),#N/A) -> #N/A | AE30: =ROW(AE30) -> 30 | AF30: =COUNTIF(AD$3:AD30,AD30) -> 23 | AG30: =AC30/$AH$17*100 -> #REF! | AP30: =AB35 -> Deferral of tax payments | AQ30: =AC35 -> 0
K31: =IF(VLOOKUP($L31,Data!$B$2:$AI$1588,39,FALSE)=1,1+MAX($K$3:K30),0) -> #N/A | L31: Brunei Darussalam | P31: 5 | Q31: Health Expenditures measures | R31: 21 | S31: Supply of low cost medical items | Y31: 2 | Z31: Revenue Measures to protect individuals | AA31: 18 | AB31: Tax credits | AC31: =COUNTIFS(Data!$J:$J,$Y31,Data!$AJ:$AJ,$AA31,INDIRECT($C$3),$C$2,INDIRECT($F$3),$F$2,INDIRECT($I$2),1,INDIRECT($M$3),$M$2,INDIRECT($I$9),1) -> 0 | AD31: =IF(AC31>0,RANK(AC31,AC$3:AC$55),#N/A) -> #N/A | AE31: =ROW(AE31) -> 31 | AF31: =COUNTIF(AD$3:AD31,AD31) -> 24 | AG31: =AC31/$AH$17*100 -> #REF! | AP31: =AB36 -> Deferral of tax filing | AQ31: =AC36 -> 0
K32: =IF(VLOOKUP($L32,Data!$B$2:$AI$1588,39,FALSE)=1,1+MAX($K$3:K31),0) -> #N/A | L32: Bulgaria | P32: 5 | Q32: Health Expenditures measures | R32: 22 | S32: Supply of high cost medical items | Y32: 2 | Z32: Revenue Measures to protect individuals | AA32: 17 | AB32: Broaden tax deductibility | AC32: =COUNTIFS(Data!$J:$J,$Y32,Data!$AJ:$AJ,$AA32,INDIRECT($C$3),$C$2,INDIRECT($F$3),$F$2,INDIRECT($I$2),1,INDIRECT($M$3),$M$2,INDIRECT($I$9),1) -> 0 | AD32: =IF(AC32>0,RANK(AC32,AC$3:AC$55),#N/A) -> #N/A | AE32: =ROW(AE32) -> 32 | AF32: =COUNTIF(AD$3:AD32,AD32) -> 25 | AG32: =AC32/$AH$17*100 -> #REF! | AO32: =Z38 -> Revenue Measures to protect businesses | AP32: =AB38 -> Other | AQ32: =AC38 -> 0
K33: =IF(VLOOKUP($L33,Data!$B$2:$AI$1588,39,FALSE)=1,1+MAX($K$3:K32),0) -> #N/A | L33: Burkina Faso | P33: 5 | Q33: Health Expenditures measures | R33: 23 | S33: Targeted infrastructure investments | Y33: 2 | Z33: Revenue Measures to protect individuals | AA33: 16 | AB33: Tax amnesty / incentives | AC33: =COUNTIFS(Data!$J:$J,$Y33,Data!$AJ:$AJ,$AA33,INDIRECT($C$3),$C$2,INDIRECT($F$3),$F$2,INDIRECT($I$2),1,INDIRECT($M$3),$M$2,INDIRECT($I$9),1) -> 0 | AD33: =IF(AC33>0,RANK(AC33,AC$3:AC$55),#N/A) -> #N/A | AE33: =ROW(AE33) -> 33 | AF33: =COUNTIF(AD$3:AD33,AD33) -> 26 | AG33: =AC33/$AH$17*100 -> #REF! | AP33: =AB39 -> Tax exemption/waiver/suspension | AQ33: =AC39 -> 0
K34: =IF(VLOOKUP($L34,Data!$B$2:$AI$1588,39,FALSE)=1,1+MAX($K$3:K33),0) -> #N/A | L34: Cambodia | P34: 5 | Q34: Health Expenditures measures | R34: 24 | S34: Expansion of human resources | Y34: 2 | Z34: Revenue Measures to protect individuals | AA34: 15 | AB34: Tax rate reduction | AC34: =COUNTIFS(Data!$J:$J,$Y34,Data!$AJ:$AJ,$AA34,INDIRECT($C$3),$C$2,INDIRECT($F$3),$F$2,INDIRECT($I$2),1,INDIRECT($M$3),$M$2,INDIRECT($I$9),1) -> 0 | AD34: =IF(AC34>0,RANK(AC34,AC$3:AC$55),#N/A) -> #N/A | AE34: =ROW(AE34) -> 34 | AF34: =COUNTIF(AD$3:AD34,AD34) -> 27 | AG34: =AC34/$AH$17*100 -> #REF! | AP34: =AB40 -> Suspend audit activities | AQ34: =AC40 -> 0
K35: =IF(VLOOKUP($L35,Data!$B$2:$AI$1588,39,FALSE)=1,1+MAX($K$3:K34),0) -> #N/A | L35: Cameroon | P35: 5 | Q35: Health Expenditures measures | R35: general | S35: General | Y35: 2 | Z35: Revenue Measures to protect individuals | AA35: 14 | AB35: Deferral of tax payments | AC35: =COUNTIFS(Data!$J:$J,$Y35,Data!$AJ:$AJ,$AA35,INDIRECT($C$3),$C$2,INDIRECT($F$3),$F$2,INDIRECT($I$2),1,INDIRECT($M$3),$M$2,INDIRECT($I$9),1) -> 0 | AD35: =IF(AC35>0,RANK(AC35,AC$3:AC$55),#N/A) -> #N/A | AE35: =ROW(AE35) -> 35 | AF35: =COUNTIF(AD$3:AD35,AD35) -> 28 | AG35: =AC35/$AH$17*100 -> #REF! | AP35: =AB41 -> Suspend debt collection | AQ35: =AC41 -> 0
K36: =IF(VLOOKUP($L36,Data!$B$2:$AI$1588,39,FALSE)=1,1+MAX($K$3:K35),0) -> #REF! | L36: Canada | P36: 6 | Q36: Expenditure Measures for cash transfers to individuals | R36: 25 | S36: Direct cash transfers for individuals | Y36: 2 | Z36: Revenue Measures to protect individuals | AA36: 13 | AB36: Deferral of tax filing | AC36: =COUNTIFS(Data!$J:$J,$Y36,Data!$AJ:$AJ,$AA36,INDIRECT($C$3),$C$2,INDIRECT($F$3),$F$2,INDIRECT($I$2),1,INDIRECT($M$3),$M$2,INDIRECT($I$9),1) -> 0 | AD36: =IF(AC36>0,RANK(AC36,AC$3:AC$55),#N/A) -> #N/A | AE36: =ROW(AE36) -> 36 | AF36: =COUNTIF(AD$3:AD36,AD36) -> 29 | AG36: =AC36/$AH$17*100 -> #REF! | AP36: =AB42 -> Lower advance payment | AQ36: =AC42 -> 0
K37: =IF(VLOOKUP($L37,Data!$B$2:$AI$1588,39,FALSE)=1,1+MAX($K$3:K36),0) -> #N/A | L37: Cape Verde | P37: 6 | Q37: Expenditure Measures for cash transfers to individuals | R37: 26 | S37: Expansion of unemployment benefits | AP37: =AB43 -> Accelerating refunds | AQ37: =AC43 -> 0
K38: =IF(VLOOKUP($L38,Data!$B$2:$AI$1588,39,FALSE)=1,1+MAX($K$3:K37),0) -> #N/A | L38: Cayman Islands | P38: 6 | Q38: Expenditure Measures for cash transfers to individuals | R38: 27 | S38: Temporary expansion of existing benefits | Y38: 1 | Z38: Revenue Measures to protect businesses | AA38: Other | AB38: Other | AC38: =COUNTIFS(Data!$J:$J,$Y38,Data!$AJ:$AJ,$AA38,INDIRECT($C$3),$C$2,INDIRECT($F$3),$F$2,INDIRECT($I$2),1,INDIRECT($M$3),$M$2,INDIRECT($I$9),1) -> 0 | AD38: =IF(AC38>0,RANK(AC38,AC$3:AC$55),#N/A) -> #N/A | AE38: =ROW(AE38) -> 38 | AF38: =COUNTIF(AD$3:AD38,AD38) -> 30 | AG38: =AC38/$AH$17*100 -> #REF! | AP38: =AB44 -> Tax amnesty / incentives | AQ38: =AC44 -> 0
K39: =IF(VLOOKUP($L39,Data!$B$2:$AI$1588,39,FALSE)=1,1+MAX($K$3:K38),0) -> #N/A | L39: Central African Republic | P39: 6 | Q39: Expenditure Measures for cash transfers to individuals | R39: 28 | S39: Supplementary ad hoc programs | Y39: 1 | Z39: Revenue Measures to protect businesses | AA39: Tax exemption/waiver/suspension | AB39: Tax exemption/waiver/suspension | AC39: =COUNTIFS(Data!$J:$J,$Y39,Data!$AJ:$AJ,$AA39,INDIRECT($C$3),$C$2,INDIRECT($F$3),$F$2,INDIRECT($I$2),1,INDIRECT($M$3),$M$2,INDIRECT($I$9),1) -> 0 | AD39: =IF(AC39>0,RANK(AC39,AC$3:AC$55),#N/A) -> #N/A | AE39: =ROW(AE39) -> 39 | AF39: =COUNTIF(AD$3:AD39,AD39) -> 31 | AG39: =AC39/$AH$17*100 -> #REF! | AP39: =AB45 -> Tax rate reduction | AQ39: =AC45 -> 0
K40: =IF(VLOOKUP($L40,Data!$B$2:$AI$1588,39,FALSE)=1,1+MAX($K$3:K39),0) -> #N/A | L40: Chad | P40: 6 | Q40: Expenditure Measures for cash transfers to individuals | R40: 29 | S40: Wage compensation/ enhanced paid leave | Y40: 1 | Z40: Revenue Measures to protect businesses | AA40: 12 | AB40: Suspend audit activities | AC40: =COUNTIFS(Data!$J:$J,$Y40,Data!$AJ:$AJ,$AA40,INDIRECT($C$3),$C$2,INDIRECT($F$3),$F$2,INDIRECT($I$2),1,INDIRECT($M$3),$M$2,INDIRECT($I$9),1) -> 0 | AD40: =IF(AC40>0,RANK(AC40,AC$3:AC$55),#N/A) -> #N/A | AE40: =ROW(AE40) -> 40 | AF40: =COUNTIF(AD$3:AD40,AD40) -> 32 | AG40: =AC40/$AH$17*100 -> #REF! | AP40: =AB46 -> Deferral of tax payments | AQ40: =AC46 -> 0
K41: =IF(VLOOKUP($L41,Data!$B$2:$AI$1588,39,FALSE)=1,1+MAX($K$3:K40),0) -> #REF! | L41: Chile | P41: 6 | Q41: Expenditure Measures for cash transfers to individuals | R41: other | S41: Other | Y41: 1 | Z41: Revenue Measures to protect businesses | AA41: 11 | AB41: Suspend debt collection | AC41: =COUNTIFS(Data!$J:$J,$Y41,Data!$AJ:$AJ,$AA41,INDIRECT($C$3),$C$2,INDIRECT($F$3),$F$2,INDIRECT($I$2),1,INDIRECT($M$3),$M$2,INDIRECT($I$9),1) -> 0 | AD41: =IF(AC41>0,RANK(AC41,AC$3:AC$55),#N/A) -> #N/A | AE41: =ROW(AE41) -> 41 | AF41: =COUNTIF(AD$3:AD41,AD41) -> 33 | AG41: =AC41/$AH$17*100 -> #REF! | AP41: =AB47 -> Deferral of tax filing | AQ41: =AC47 -> 0
K42: =IF(VLOOKUP($L42,Data!$B$2:$AI$1588,39,FALSE)=1,1+MAX($K$3:K41),0) -> #N/A | L42: China | P42: 7 | Q42: Credit and equity measures | R42: 30 | S42: Preferential loans to firms | Y42: 1 | Z42: Revenue Measures to protect businesses | AA42: 10 | AB42: Lower advance payment | AC42: =COUNTIFS(Data!$J:$J,$Y42,Data!$AJ:$AJ,$AA42,INDIRECT($C$3),$C$2,INDIRECT($F$3),$F$2,INDIRECT($I$2),1,INDIRECT($M$3),$M$2,INDIRECT($I$9),1) -> 0 | AD42: =IF(AC42>0,RANK(AC42,AC$3:AC$55),#N/A) -> #N/A | AE42: =ROW(AE42) -> 42 | AF42: =COUNTIF(AD$3:AD42,AD42) -> 34 | AG42: =AC42/$AH$17*100 -> #REF! | AP42: =AB48 -> Tax credits | AQ42: =AC48 -> 0
K43: =IF(VLOOKUP($L43,Data!$B$2:$AI$1588,39,FALSE)=1,1+MAX($K$3:K42),0) -> #REF! | L43: Colombia | P43: 7 | Q43: Credit and equity measures | R43: 31 | S43: One-off grants | Y43: 1 | Z43: Revenue Measures to protect businesses | AA43: 9 | AB43: Accelerating refunds | AC43: =COUNTIFS(Data!$J:$J,$Y43,Data!$AJ:$AJ,$AA43,INDIRECT($C$3),$C$2,INDIRECT($F$3),$F$2,INDIRECT($I$2),1,INDIRECT($M$3),$M$2,INDIRECT($I$9),1) -> 0 | AD43: =IF(AC43>0,RANK(AC43,AC$3:AC$55),#N/A) -> #N/A | AE43: =ROW(AE43) -> 43 | AF43: =COUNTIF(AD$3:AD43,AD43) -> 35 | AG43: =AC43/$AH$17*100 -> #REF! | AP43: =AB49 -> Broaden tax deductibility | AQ43: =AC49 -> 0
K44: =IF(VLOOKUP($L44,Data!$B$2:$AI$1588,39,FALSE)=1,1+MAX($K$3:K43),0) -> #N/A | L44: Comoros | P44: 7 | Q44: Credit and equity measures | R44: 32 | S44: Preferential loans to households | Y44: 1 | Z44: Revenue Measures to protect businesses | AA44: 8 | AB44: Tax amnesty / incentives | AC44: =COUNTIFS(Data!$J:$J,$Y44,Data!$AJ:$AJ,$AA44,INDIRECT($C$3),$C$2,INDIRECT($F$3),$F$2,INDIRECT($I$2),1,INDIRECT($M$3),$M$2,INDIRECT($I$9),1) -> 0 | AD44: =IF(AC44>0,RANK(AC44,AC$3:AC$55),#N/A) -> #N/A | AE44: =ROW(AE44) -> 44 | AF44: =COUNTIF(AD$3:AD44,AD44) -> 36 | AG44: =AC44/$AH$17*100 -> #REF! | AP44: =AB50 -> Extend loss carry-forward (CIT) | AQ44: =AC50 -> 0
K45: =IF(VLOOKUP($L45,Data!$B$2:$AI$1588,39,FALSE)=1,1+MAX($K$3:K44),0) -> #N/A | L45: Congo, Democratic Republic of the | P45: 7 | Q45: Credit and equity measures | R45: other | S45: Other | Y45: 1 | Z45: Revenue Measures to protect businesses | AA45: 7 | AB45: Tax rate reduction | AC45: =COUNTIFS(Data!$J:$J,$Y45,Data!$AJ:$AJ,$AA45,INDIRECT($C$3),$C$2,INDIRECT($F$3),$F$2,INDIRECT($I$2),1,INDIRECT($M$3),$M$2,INDIRECT($I$9),1) -> 0 | AD45: =IF(AC45>0,RANK(AC45,AC$3:AC$55),#N/A) -> #N/A | AE45: =ROW(AE45) -> 45 | AF45: =COUNTIF(AD$3:AD45,AD45) -> 37 | AG45: =AC45/$AH$17*100 -> #REF! | AP45: =AB51 -> Accelerated asset depreciation (CIT) | AQ45: =AC51 -> 0
K46: =IF(VLOOKUP($L46,Data!$B$2:$AI$1588,39,FALSE)=1,1+MAX($K$3:K45),0) -> #N/A | L46: Congo, Republic of the | P46: 8 | Q46: Revenue Measures to raise revenue | R46: 33 | S46: Revenue increase | Y46: 1 | Z46: Revenue Measures to protect businesses | AA46: 6 | AB46: Deferral of tax payments | AC46: =COUNTIFS(Data!$J:$J,$Y46,Data!$AJ:$AJ,$AA46,INDIRECT($C$3),$C$2,INDIRECT($F$3),$F$2,INDIRECT($I$2),1,INDIRECT($M$3),$M$2,INDIRECT($I$9),1) -> 0 | AD46: =IF(AC46>0,RANK(AC46,AC$3:AC$55),#N/A) -> #N/A | AE46: =ROW(AE46) -> 46 | AF46: =COUNTIF(AD$3:AD46,AD46) -> 38 | AG46: =AC46/$AH$17*100 -> #REF!
K47: =IF(VLOOKUP($L47,Data!$B$2:$AI$1588,39,FALSE)=1,1+MAX($K$3:K46),0) -> #N/A | L47: Cook Islands | P47: 9 | Q47: Expenditure Measures for businesses | R47: 34 | S47: Income support | Y47: 1 | Z47: Revenue Measures to protect businesses | AA47: 5 | AB47: Deferral of tax filing | AC47: =COUNTIFS(Data!$J:$J,$Y47,Data!$AJ:$AJ,$AA47,INDIRECT($C$3),$C$2,INDIRECT($F$3),$F$2,INDIRECT($I$2),1,INDIRECT($M$3),$M$2,INDIRECT($I$9),1) -> 0 | AD47: =IF(AC47>0,RANK(AC47,AC$3:AC$55),#N/A) -> #N/A | AE47: =ROW(AE47) -> 47 | AF47: =COUNTIF(AD$3:AD47,AD47) -> 39 | AG47: =AC47/$AH$17*100 -> #REF!
K48: =IF(VLOOKUP($L48,Data!$B$2:$AI$1588,39,FALSE)=1,1+MAX($K$3:K47),0) -> #REF! | L48: Costa Rica | Y48: 1 | Z48: Revenue Measures to protect businesses | AA48: 4 | AB48: Tax credits | AC48: =COUNTIFS(Data!$J:$J,$Y48,Data!$AJ:$AJ,$AA48,INDIRECT($C$3),$C$2,INDIRECT($F$3),$F$2,INDIRECT($I$2),1,INDIRECT($M$3),$M$2,INDIRECT($I$9),1) -> 0 | AD48: =IF(AC48>0,RANK(AC48,AC$3:AC$55),#N/A) -> #N/A | AE48: =ROW(AE48) -> 48 | AF48: =COUNTIF(AD$3:AD48,AD48) -> 40 | AG48: =AC48/$AH$17*100 -> #REF!
K49: =IF(VLOOKUP($L49,Data!$B$2:$AI$1588,39,FALSE)=1,1+MAX($K$3:K48),0) -> #N/A | L49: Cote d'Ivoire | Y49: 1 | Z49: Revenue Measures to protect businesses | AA49: 3 | AB49: Broaden tax deductibility | AC49: =COUNTIFS(Data!$J:$J,$Y49,Data!$AJ:$AJ,$AA49,INDIRECT($C$3),$C$2,INDIRECT($F$3),$F$2,INDIRECT($I$2),1,INDIRECT($M$3),$M$2,INDIRECT($I$9),1) -> 0 | AD49: =IF(AC49>0,RANK(AC49,AC$3:AC$55),#N/A) -> #N/A | AE49: =ROW(AE49) -> 49 | AF49: =COUNTIF(AD$3:AD49,AD49) -> 41 | AG49: =AC49/$AH$17*100 -> #REF!
K50: =IF(VLOOKUP($L50,Data!$B$2:$AI$1588,39,FALSE)=1,1+MAX($K$3:K49),0) -> #N/A | L50: Croatia | Y50: 1 | Z50: Revenue Measures to protect businesses | AA50: 2 | AB50: Extend loss carry-forward (CIT) | AC50: =COUNTIFS(Data!$J:$J,$Y50,Data!$AJ:$AJ,$AA50,INDIRECT($C$3),$C$2,INDIRECT($F$3),$F$2,INDIRECT($I$2),1,INDIRECT($M$3),$M$2,INDIRECT($I$9),1) -> 0 | AD50: =IF(AC50>0,RANK(AC50,AC$3:AC$55),#N/A) -> #N/A | AE50: =ROW(AE50) -> 50 | AF50: =COUNTIF(AD$3:AD50,AD50) -> 42 | AG50: =AC50/$AH$17*100 -> #REF!
K51: =IF(VLOOKUP($L51,Data!$B$2:$AI$1588,39,FALSE)=1,1+MAX($K$3:K50),0) -> #N/A | L51: Cyprus | P51: Policy category | Y51: 1 | Z51: Revenue Measures to protect businesses | AA51: 1 | AB51: Accelerated asset depreciation (CIT) | AC51: =COUNTIFS(Data!$J:$J,$Y51,Data!$AJ:$AJ,$AA51,INDIRECT($C$3),$C$2,INDIRECT($F$3),$F$2,INDIRECT($I$2),1,INDIRECT($M$3),$M$2,INDIRECT($I$9),1) -> 0 | AD51: =IF(AC51>0,RANK(AC51,AC$3:AC$55),#N/A) -> #N/A | AE51: =ROW(AE51) -> 51 | AF51: =COUNTIF(AD$3:AD51,AD51) -> 43 | AG51: =AC51/$AH$17*100 -> #REF!
K52: =IF(VLOOKUP($L52,Data!$B$2:$AI$1588,39,FALSE)=1,1+MAX($K$3:K51),0) -> #REF! | L52: Czechia | P52: other | Q52: =COUNTIFS(Data!#REF!,1,INDIRECT($C$3),$C$2,INDIRECT($F$3),$F$2,INDIRECT($I$2),1,INDIRECT($M$3),$M$2,INDIRECT($I$9),1) -> #REF! | R52: Other measures
K53: =IF(VLOOKUP($L53,Data!$B$2:$AI$1588,39,FALSE)=1,1+MAX($K$3:K52),0) -> #REF! | L53: Denmark | P53: 7 | Q53: =COUNTIFS(Data!$J:$J,$P53,INDIRECT($C$3),$C$2,INDIRECT($F$3),$F$2,INDIRECT($I$2),1,INDIRECT($M$3),$M$2,INDIRECT($I$9),1) -> 0 | R53: =VLOOKUP(P53,$P$3:$Q$47,2,FALSE) -> Credit and equity measures | Z53: Expenditure Measures for businesses | AC53: =Q54 -> 0 | AD53: =IF(AC53>0,RANK(AC53,AC$3:AC$55),#N/A) -> #N/A | AE53: =ROW(AE53) -> 53 | AF53: =COUNTIF(AD$3:AD53,AD53) -> 44 | AG53: =AC53/$AH$17*100 -> #REF!
K54: =IF(VLOOKUP($L54,Data!$B$2:$AI$1588,39,FALSE)=1,1+MAX($K$3:K53),0) -> #N/A | L54: Dominica | P54: 9 | Q54: =COUNTIFS(Data!$J:$J,$P54,INDIRECT($C$3),$C$2,INDIRECT($F$3),$F$2,INDIRECT($I$2),1,INDIRECT($M$3),$M$2,INDIRECT($I$9),1) -> 0 | R54: =VLOOKUP(P54,$P$3:$Q$47,2,FALSE) -> Expenditure Measures for businesses | Z54: Other measures | AC54: =Q52 -> #REF! | AD54: =IF(AC54>0,RANK(AC54,AC$3:AC$55),#N/A) -> #REF! | AE54: =ROW(AE54) -> 54 | AF54: =COUNTIF(AD$3:AD54,AD54) -> 1 | AG54: =AC54/$AH$17*100 -> #REF!
K55: =IF(VLOOKUP($L55,Data!$B$2:$AI$1588,39,FALSE)=1,1+MAX($K$3:K54),0) -> #N/A | L55: Dominican Republic | P55: 6 | Q55: =COUNTIFS(Data!$J:$J,$P55,INDIRECT($C$3),$C$2,INDIRECT($F$3),$F$2,INDIRECT($I$2),1,INDIRECT($M$3),$M$2,INDIRECT($I$9),1) -> 0 | R55: =VLOOKUP(P55,$P$3:$Q$47,2,FALSE) -> Expenditure Measures for cash transfers to individuals | Z55: Revenue Measures to raise revenue | AC55: =Q57 -> 0 | AD55: =IF(AC55>0,RANK(AC55,AC$3:AC$55),#N/A) -> #N/A | AE55: =ROW(AE55) -> 55 | AF55: =COUNTIF(AD$3:AD55,AD55) -> 45 | AG55: =AC55/$AH$17*100 -> #REF!
K56: =IF(VLOOKUP($L56,Data!$B$2:$AI$1588,39,FALSE)=1,1+MAX($K$3:K55),0) -> #N/A | L56: Ecuador | P56: 5 | Q56: =COUNTIFS(Data!$J:$J,$P56,INDIRECT($C$3),$C$2,INDIRECT($F$3),$F$2,INDIRECT($I$2),1,INDIRECT($M$3),$M$2,INDIRECT($I$9),1) -> 0 | R56: =VLOOKUP(P56,$P$3:$Q$47,2,FALSE) -> Health Expenditures measures
K57: =IF(VLOOKUP($L57,Data!$B$2:$AI$1588,39,FALSE)=1,1+MAX($K$3:K56),0) -> #N/A | L57: Egypt | P57: 8 | Q57: =COUNTIFS(Data!$J:$J,$P57,INDIRECT($C$3),$C$2,INDIRECT($F$3),$F$2,INDIRECT($I$2),1,INDIRECT($M$3),$M$2,INDIRECT($I$9),1) -> 0 | R57: =VLOOKUP(P57,$P$3:$Q$47,2,FALSE) -> Revenue Measures to raise revenue
K58: =IF(VLOOKUP($L58,Data!$B$2:$AI$1588,39,FALSE)=1,1+MAX($K$3:K57),0) -> #N/A | L58: El Salvador | P58: 4 | Q58: =COUNTIFS(Data!$J:$J,$P58,INDIRECT($C$3),$C$2,INDIRECT($F$3),$F$2,INDIRECT($I$2),1,INDIRECT($M$3),$M$2,INDIRECT($I$9),1) -> 0 | R58: =VLOOKUP(P58,$P$3:$Q$47,2,FALSE) -> Revenue Measures to boost consumption / demand | Z58: nth of rank
K59: =IF(VLOOKUP($L59,Data!$B$2:$AI$1588,39,FALSE)=1,1+MAX($K$3:K58),0) -> #N/A | L59: Equatorial Guinea | P59: 3 | Q59: =COUNTIFS(Data!$J:$J,$P59,INDIRECT($C$3),$C$2,INDIRECT($F$3),$F$2,INDIRECT($I$2),1,INDIRECT($M$3),$M$2,INDIRECT($I$9),1) -> 0 | R59: =VLOOKUP(P59,$P$3:$Q$47,2,FALSE) -> Revenue Measures to promote availability of medical items | Z59: =COUNTIF($AA$59:$AA59,$AA59) -> 1 | AA59: 1 | AB59: =SUMIFS(AE:AE,AD:AD,AA59,AF:AF,Z59) -> 0 | AC59: =_xlfn.CONCAT(INDIRECT(_xlfn.CONCAT("Z",AB59)),": ",INDIRECT(_xlfn.CONCAT("AB",AB59))," (n=",INDIRECT(_xlfn.CONCAT("AC",AB59)),", ",TEXT(INDIRECT(_xlfn.CONCAT("AG",AB59)),"#,###"),"% of total)") -> #REF!
K60: =IF(VLOOKUP($L60,Data!$B$2:$AI$1588,39,FALSE)=1,1+MAX($K$3:K59),0) -> #REF! | L60: Estonia | P60: 2 | Q60: =COUNTIFS(Data!$J:$J,$P60,INDIRECT($C$3),$C$2,INDIRECT($F$3),$F$2,INDIRECT($I$2),1,INDIRECT($M$3),$M$2,INDIRECT($I$9),1) -> 0 | R60: =VLOOKUP(P60,$P$3:$Q$47,2,FALSE) -> Revenue Measures to protect individuals | Z60: =COUNTIF($AA$59:$AA60,$AA60) -> 1 | AA60: =IF(SUM(Z65:Z69)=1,"-",IF(Z65>1,1,2)) -> 2 | AB60: =SUMIFS(AE:AE,AD:AD,AA60,AF:AF,Z60) -> 0 | AC60: =IFERROR(_xlfn.CONCAT(INDIRECT(_xlfn.CONCAT("Z",AB60)),": ",INDIRECT(_xlfn.CONCAT("AB",AB60))," (n=",INDIRECT(_xlfn.CONCAT("AC",AB60)),", ",TEXT(INDIRECT(_xlfn.CONCAT("AG",AB60)),"#,###"),"% of total)"),"No further policies") -> No further policies
K61: =IF(VLOOKUP($L61,Data!$B$2:$AI$1588,39,FALSE)=1,1+MAX($K$3:K60),0) -> #N/A | L61: Eswatini | P61: 1 | Q61: =COUNTIFS(Data!$J:$J,$P61,INDIRECT($C$3),$C$2,INDIRECT($F$3),$F$2,INDIRECT($I$2),1,INDIRECT($M$3),$M$2,INDIRECT($I$9),1) -> 0 | R61: =VLOOKUP(P61,$P$3:$Q$47,2,FALSE) -> Revenue Measures to protect businesses | Z61: =COUNTIF($AA$59:$AA61,$AA61) -> 1 | AA61: =IF(SUM(Z65:Z69)<3,"-",IF(Z65>2,1,IF(Z66>1,2,3))) -> - | AB61: =SUMIFS(AE:AE,AD:AD,AA61,AF:AF,Z61) -> 0 | AC61: =IFERROR(_xlfn.CONCAT(INDIRECT(_xlfn.CONCAT("Z",AB61)),": ",INDIRECT(_xlfn.CONCAT("AB",AB61))," (n=",INDIRECT(_xlfn.CONCAT("AC",AB61)),", ",TEXT(INDIRECT(_xlfn.CONCAT("AG",AB61)),"#,###"),"% of total)"),"No further policies") -> No further policies
K62: =IF(VLOOKUP($L62,Data!$B$2:$AI$1588,39,FALSE)=1,1+MAX($K$3:K61),0) -> #N/A | L62: Ethiopia | Z62: =COUNTIF($AA$59:$AA62,$AA62) -> 2 | AA62: =IF(SUM(Z65:Z69)<4,"-",IF(Z65>3,1,IF(Z66>2,2,IF(Z67>1,3,4)))) -> - | AB62: =SUMIFS(AE:AE,AD:AD,AA62,AF:AF,Z62) -> 0 | AC62: =IFERROR(_xlfn.CONCAT(INDIRECT(_xlfn.CONCAT("Z",AB62)),": ",INDIRECT(_xlfn.CONCAT("AB",AB62))," (n=",INDIRECT(_xlfn.CONCAT("AC",AB62)),", ",TEXT(INDIRECT(_xlfn.CONCAT("AG",AB62)),"#,###"),"% of total)"),"No further policies") -> No further policies
K63: =IF(VLOOKUP($L63,Data!$B$2:$AI$1588,39,FALSE)=1,1+MAX($K$3:K62),0) -> #REF! | L63: European Union | Z63: =COUNTIF($AA$59:$AA63,$AA63) -> 3 | AA63: =IF(SUM(Z65:Z69)<5,"-",IF(Z65>4,1,IF(Z66>3,2,IF(Z67>2,3,IF(Z68>1,4,5))))) -> - | AB63: =SUMIFS(AE:AE,AD:AD,AA63,AF:AF,Z63) -> 0 | AC63: =IFERROR(_xlfn.CONCAT(INDIRECT(_xlfn.CONCAT("Z",AB63)),": ",INDIRECT(_xlfn.CONCAT("AB",AB63))," (n=",INDIRECT(_xlfn.CONCAT("AC",AB63)),", ",TEXT(INDIRECT(_xlfn.CONCAT("AG",AB63)),"#,###"),"% of total)"),"No further policies") -> No further policies
K64: =IF(VLOOKUP($L64,Data!$B$2:$AI$1588,39,FALSE)=1,1+MAX($K$3:K63),0) -> #N/A | L64: Fiji
K65: =IF(VLOOKUP($L65,Data!$B$2:$AI$1588,39,FALSE)=1,1+MAX($K$3:K64),0) -> #REF! | L65: Finland | Y65: 1s | Z65: =COUNTIF($AD$3:$AD$55,1) -> 0 | AB65: =0.1114*100 -> 11.14
K66: =IF(VLOOKUP($L66,Data!$B$2:$AI$1588,39,FALSE)=1,1+MAX($K$3:K65),0) -> #REF! | L66: France | Y66: 2s | Z66: =COUNTIF($AD$3:$AD$55,2) -> 0 | AB66: =TEXT(AB65, "#,###") -> 11
K67: =IF(VLOOKUP($L67,Data!$B$2:$AI$1588,39,FALSE)=1,1+MAX($K$3:K66),0) -> #N/A | L67: Gabon | Y67: 3s | Z67: =COUNTIF($AD$3:$AD$55,3) -> 0
K68: =IF(VLOOKUP($L68,Data!$B$2:$AI$1588,39,FALSE)=1,1+MAX($K$3:K67),0) -> #N/A | L68: Gambia, The | Y68: 4s | Z68: =COUNTIF($AD$3:$AD$55,4) -> 0
K69: =IF(VLOOKUP($L69,Data!$B$2:$AI$1588,39,FALSE)=1,1+MAX($K$3:K68),0) -> #N/A | L69: Georgia | Y69: 5s | Z69: =COUNTIF($AD$3:$AD$55,5) -> 0
K70: =IF(VLOOKUP($L70,Data!$B$2:$AI$1588,39,FALSE)=1,1+MAX($K$3:K69),0) -> #REF! | L70: Germany
K71: =IF(VLOOKUP($L71,Data!$B$2:$AI$1588,39,FALSE)=1,1+MAX($K$3:K70),0) -> #N/A | L71: Ghana
K72: =IF(VLOOKUP($L72,Data!$B$2:$AI$1588,39,FALSE)=1,1+MAX($K$3:K71),0) -> #REF! | L72: Greece
K73: =IF(VLOOKUP($L73,Data!$B$2:$AI$1588,39,FALSE)=1,1+MAX($K$3:K72),0) -> #N/A | L73: Grenada
K74: =IF(VLOOKUP($L74,Data!$B$2:$AI$1588,39,FALSE)=1,1+MAX($K$3:K73),0) -> #N/A | L74: Guatemala
K75: =IF(VLOOKUP($L75,Data!$B$2:$AI$1588,39,FALSE)=1,1+MAX($K$3:K74),0) -> #N/A | L75: Guernsey
K76: =IF(VLOOKUP($L76,Data!$B$2:$AI$1588,39,FALSE)=1,1+MAX($K$3:K75),0) -> #N/A | L76: Guinea
K77: =IF(VLOOKUP($L77,Data!$B$2:$AI$1588,39,FALSE)=1,1+MAX($K$3:K76),0) -> #N/A | L77: Guinea-Bissau
K78: =IF(VLOOKUP($L78,Data!$B$2:$AI$1588,39,FALSE)=1,1+MAX($K$3:K77),0) -> #N/A | L78: Guyana
K79: =IF(VLOOKUP($L79,Data!$B$2:$AI$1588,39,FALSE)=1,1+MAX($K$3:K78),0) -> #N/A | L79: Haiti
K80: =IF(VLOOKUP($L80,Data!$B$2:$AI$1588,39,FALSE)=1,1+MAX($K$3:K79),0) -> #N/A | L80: Honduras
K81: =IF(VLOOKUP($L81,Data!$B$2:$AI$1588,39,FALSE)=1,1+MAX($K$3:K80),0) -> #N/A | L81: Hong Kong, China
... K205: =IF(VLOOKUP($L205,Data!$B$2:$AI$1588,39,FALSE)=1,1+MAX($K$3:K204),0) -> #N/A | L205: Zimbabwe

Sheet MPO Data
A1: Country | B1: Gross Domestic Product at Market Price Volume Millions 2015 real USD % change | C1: Primary Fiscal Balance LCU % of GDP | D1: General Government Debt Stock (Millions of Local Currency) LCU % of GDP
A2: Zimbabwe | B2: #DIV/0! | C2: #DIV/0! | D2: #DIV/0!
A3: Zambia | B3: -1.21 | C3: -6.95 | D3: 84.16
A4: Yemen | B4: -5 | C4: #DIV/0! | D4: #DIV/0!
A5: Vietnam | B5: 2.92 | C5: -2.64 | D5: 56.92
A6: Vanuatu | B6: -10 | C6: #DIV/0! | D6: #DIV/0!
A7: Uzbekistan | B7: 1.6 | C7: -3.82 | D7: 37.89
A8: Uruguay | B8: -5.81 | C8: -2.92 | D8: 66.3
A9: United Arab Emirates | B9: -6.32 | C9: -7.68 | D9: 25
A10: Ukraine | B10: -4.52 | C10: -2.39 | D10: 63.2
A11: Uganda | B11: 2.91 | C11: -4.52 | D11: 41.11
A12: Tonga | B12: -1.5 | C12: #DIV/0! | D12: #DIV/0!
A13: Togo | B13: 0.7 | C13: -3.24 | D13: 57.48
A14: Timor-Leste | B14: -7.34 | C14: -25.65 | D14: 13.1
A15: Thailand | B15: -6.06 | C15: -4.69 | D15: 51.11
A16: Tanzania | B16: 2 | C16: 0.19 | D16: 38.07
A17: Tuvalu | B17: -0.5 | C17: #DIV/0! | D17: #DIV/0!
A18: Tajikistan | B18: 4.53 | C18: -2.35 | D18: 53.47
A19: Turkey | B19: 1.76 | C19: -1.03 | D19: 39.64
A20: Suriname | B20: -14.54 | C20: -12.61 | D20: 148.3
A21: Sudan | B21: -3.63 | C21: -5.86 | D21: 249.05
A22: Saint Vincent and the Grenadines | B22: -4.21 | C22: -4.92 | D22: 87.86
A23: Saint Lucia | B23: -20.36 | C23: -7.95 | D23: 86.49
A24: Sri Lanka | B24: -3.57 | C24: -6.02 | D24: 109.75
A25: Tunisia | B25: -8.82 | C25: -6.18 | D25: 87.17
A26: South Sudan | B26: 9.5 | C26: -4.81 | D26: 42.9
A27: South Africa | B27: -6.96 | C27: -9.28 | D27: 80.46
A28: Somalia | B28: -1.5 | C28: 0.25 | D28: 40.36
A29: Solomon Islands | B29: -5 | C29: #DIV/0! | D29: #DIV/0!
A30: Sierra Leone | B30: -2.16 | C30: -1.47 | D30: 72.03
A31: Seychelles | B31: -13.33 | C31: -14.28 | D31: 102.32
A32: Serbia | B32: -1 | C32: -7.08 | D32: 58.18
A33: Senegal | B33: -0.7 | C33: -4.32 | D33: 67.58
A34: Saudi Arabia | B34: -4.07 | C34: -10.15 | D34: 32.76
A35: Sao Tome and Principe | B35: 3.09 | C35: -4.31 | D35: 90.71
A36: Samoa | B36: -3.5 | C36: #DIV/0! | D36: #DIV/0!
A37: Rwanda | B37: -3.25 | C37: -8.18 | D37: 67.46
A38: Russian Federation | B38: -3.06 | C38: -3.08 | D38: 17.84
A39: Romania | B39: -3.9 | C39: -8.41 | D39: 47.7
A40: Qatar | B40: -3.19 | C40: -1.71 | D40: 64.11
A41: Poland | B41: -2.7 | C41: -7.22 | D41: 58.2
A42: Philippines | B42: -9.51 | C42: -5.5 | D42: 49
A43: Peru | B43: -11.12 | C43: -7.3 | D43: 35.02
A44: Paraguay | B44: -1.05 | C44: -4.96 | D44: 34.19
A45: Papua New Guinea | B45: -3.82 | C45: #DIV/0! | D45: 49.04
A46: Panama | B46: -17.94 | C46: -7.33 | D46: 64.38
A47: West Bank and Gaza | B47: -11.5 | C47: -7.26 | D47: 24.23
A48: Palau | B48: -10 | C48: #DIV/0! | D48: #DIV/0!
A49: Pakistan | B49: -1.5 | C49: -1.75 | D49: 93.59
A50: Oman | B50: -6.29 | C50: -14.66 | D50: 81.21
A51: North Macedonia | B51: -4.53 | C51: -7.69 | D51: 60.24
A52: Nigeria | B52: -1.77 | C52: -4.05 | D52: 25.21
A53: Niger | B53: 0.75 | C53: -4.3 | D53: 41.85
A54: Nicaragua | B54: -2.5 | C54: -2.47 | D54: 65.73
A55: Nepal | B55: -1.88 | C55: -4.53 | D55: 35.99
A56: Nauru | B56: 0.7 | C56: #DIV/0! | D56: #DIV/0!
A57: Namibia | B57: -7.26 | C57: -5.67 | D57: 74.35
A58: Myanmar | B58: 1.7 | C58: -4.82 | D58: 40.61
A59: Mozambique | B59: -1.34 | C59: -1.25 | D59: 121.73
A60: Morocco | B60: -6.96 | C60: -5.15 | D60: 77.77
A61: Montenegro | B61: -14.9 | C61: -8.27 | D61: 104.82
A62: Mongolia | B62: -5.39 | C62: -6.9 | D62: 78.44
A63: Moldova | B63: -7.02 | C63: -4.32 | D63: 33.5
A64: Micronesia Federated States of | B64: -1.5 | C64: #DIV/0! | D64: #DIV/0!
A65: Mexico | B65: -8.24 | C65: -0.91 | D65: 52.27
A66: Mauritius | B66: -15.62 | C66: -13.18 | D66: 90.19
A67: Mauritania | B67: -1.55 | C67: 3.79 | D67: 73.48
A68: Marshall Islands | B68: -4.5 | C68: #DIV/0! | D68: #DIV/0!
A69: Mali | B69: -2 | C69: -4.3 | D69: 44.1
A70: Maldives | B70: -28.01 | C70: -16.39 | D70: 139.29
A71: Malaysia | B71: -5.59 | C71: -3.76 | D71: 62.15
A72: Malawi | B72: 0.77 | C72: -5.05 | D72: 66.41
A73: Madagascar | B73: -4.2 | C73: -4.41 | D73: 45.05
A74: Libya | B74: -31.3 | C74: -45.4 | D74: 137.07
A75: Liberia | B75: -2.89 | C75: -2.35 | D75: 56.65
A76: Lesotho | B76: -5.79 | C76: -3.46 | D76: 65.39
A77: Lebanon | B77: -20.3 | C77: -2.67 | D77: 186.74
A78: Lao People's Democratic Republic | B78: 0.37 | C78: -3.47 | D78: 64.49
A79: Kyrgyzstan | B79: -8.62 | C79: -2.96 | D79: 68.14
A80: Kuwait | B80: -5.4 | C80: -25.42 | D80: 22.55
A81: Kosovo | B81: -6.89 | C81: -7.24 | D81: 22.28
A82: Kiribati | B82: -1.9 | C82: #DIV/0! | D82: #DIV/0!
A83: Kenya | B83: -0.31 | C83: -4.06 | D83: 67.23
A84: Kazakhstan | B84: -2.57 | C84: -2.95 | D84: 24.35
A85: Jordan | B85: -1.76 | C85: -2.55 | D85: 108.98
A86: Jamaica | B86: -10 | C86: 3 | D86: 110.11
A87: Iraq | B87: -11.86 | C87: -3.24 | D87: 69.32
A88: Iran Islamic Rep. | B88: 1.66 | C88: -5.27 | D88: 50.27
A89: Indonesia | B89: -2.07 | C89: -4.16 | D89: 39.36
A90: India | B90: -8.51 | C90: -8.49 | D90: 89.71
A91: Honduras | B91: -8.99 | C91: -4.52 | D91: 53.86
A92: Haiti | B92: -3.36 | C92: -3.49 | D92: 28.8
A93: Guyana | B93: 43.48 | C93: -6.37 | D93: 47.45
A94: Guinea-Bissau | B94: -2.4 | C94: -7.49 | D94: 78.4
... A101: Gabon | B101: -1.9 | C101: -0.14 | D101: 74.96
A102: Fiji | B102: -19.05 | C102: #DIV/0! | D102: #DIV/0!
A103: Ethiopia | B103: 6.1 | C103: -2.3 | D103: 56.5
A104: Eswatini | B104: -3.15 | C104: -6.37 | D104: 45.73
A105: Eritrea | B105: -0.63 | C105: -3.19 | D105: 263.1
A106: Equatorial Guinea | B106: -4.93 | C106: -1.96 | D106: 52.35
...

Sheet Policy Choices within Sample

Sheet Policy Choices across Samples

Sheet Performance within Sample

Sheet Performance within backend
B2: Targetability | C2: Speed | D2: Abuse Resistance | E2: Recoverability | F2: Predictability and Cost Control | G2: Reversibility | H2: Scalability | I2: Administrative Complexity | J2: Resilience to Health Measures
B3: Data!$V:$V | C3: Data!$W:$W | D3: Data!$X:$X | E3: Data!$Y:$Y | F3: Data!$Z:$Z | G3: Data!$AA:$AA | H3: Data!$AB:$AB | I3: Data!$AC:$AC | J3: Data!$AD:$AD
B4: =AVERAGEIFS(INDIRECT(B3),INDIRECT(B3),">=0",INDIRECT('Sample Select backend'!$C$3),'Sample Select backend'!$C$2,INDIRECT('Sample Select backend'!$F$3),'Sample Select backend'!$F$2,INDIRECT('Sample Select backend'!$I$2),1,INDIRECT('Sample Select backend'!$M$3),'Sample Select backend'!$M$2,INDIRECT('Sample Select backend'!$I$9),1,IF($A$20,Data!$J:$J,Data!#REF!),IF($A$20,"<>5",1)) -> #DIV/0! | C4: =AVERAGEIFS(INDIRECT(C3),INDIRECT(C3),">=0",INDIRECT('Sample Select backend'!$C$3),'Sample Select backend'!$C$2,INDIRECT('Sample Select backend'!$F$3),'Sample Select backend'!$F$2,INDIRECT('Sample Select backend'!$I$2),1,INDIRECT('Sample Select backend'!$M$3),'Sample Select backend'!$M$2,INDIRECT('Sample Select backend'!$I$9),1,IF($A$20,Data!$J:$J,Data!#REF!),IF($A$20,"<>5",1)) -> #DIV/0! | D4: =AVERAGEIFS(INDIRECT(D3),INDIRECT(D3),">=0",INDIRECT('Sample Select backend'!$C$3),'Sample Select backend'!$C$2,INDIRECT('Sample Select backend'!$F$3),'Sample Select backend'!$F$2,INDIRECT('Sample Select backend'!$I$2),1,INDIRECT('Sample Select backend'!$M$3),'Sample Select backend'!$M$2,INDIRECT('Sample Select backend'!$I$9),1,IF($A$20,Data!$J:$J,Data!#REF!),IF($A$20,"<>5",1)) -> #DIV/0! | E4: =AVERAGEIFS(INDIRECT(E3),INDIRECT(E3),">=0",INDIRECT('Sample Select backend'!$C$3),'Sample Select backend'!$C$2,INDIRECT('Sample Select backend'!$F$3),'Sample Select backend'!$F$2,INDIRECT('Sample Select backend'!$I$2),1,INDIRECT('Sample Select backend'!$M$3),'Sample Select backend'!$M$2,INDIRECT('Sample Select backend'!$I$9),1,IF($A$20,Data!$J:$J,Data!#REF!),IF($A$20,"<>5",1)) -> #DIV/0! | F4: =AVERAGEIFS(INDIRECT(F3),INDIRECT(F3),">=0",INDIRECT('Sample Select backend'!$C$3),'Sample Select backend'!$C$2,INDIRECT('Sample Select backend'!$F$3),'Sample Select backend'!$F$2,INDIRECT('Sample Select backend'!$I$2),1,INDIRECT('Sample Select backend'!$M$3),'Sample Select backend'!$M$2,INDIRECT('Sample Select backend'!$I$9),1,IF($A$20,Data!$J:$J,Data!#REF!),IF($A$20,"<>5",1)) -> #DIV/0! | G4: =AVERAGEIFS(INDIRECT(G3),INDIRECT(G3),">=0",INDIRECT('Sample Select backend'!$C$3),'Sample Select backend'!$C$2,INDIRECT('Sample Select backend'!$F$3),'Sample Select backend'!$F$2,INDIRECT('Sample Select backend'!$I$2),1,INDIRECT('Sample Select backend'!$M$3),'Sample Select backend'!$M$2,INDIRECT('Sample Select backend'!$I$9),1,IF($A$20,Data!$J:$J,Data!#REF!),IF($A$20,"<>5",1)) -> #DIV/0! | H4: =AVERAGEIFS(INDIRECT(H3),INDIRECT(H3),">=0",INDIRECT('Sample Select backend'!$C$3),'Sample Select backend'!$C$2,INDIRECT('Sample Select backend'!$F$3),'Sample Select backend'!$F$2,INDIRECT('Sample Select backend'!$I$2),1,INDIRECT('Sample Select backend'!$M$3),'Sample Select backend'!$M$2,INDIRECT('Sample Select backend'!$I$9),1,IF($A$20,Data!$J:$J,Data!#REF!),IF($A$20,"<>5",1)) -> #DIV/0! | I4: =AVERAGEIFS(INDIRECT(I3),INDIRECT(I3),">=0",INDIRECT('Sample Select backend'!$C$3),'Sample Select backend'!$C$2,INDIRECT('Sample Select backend'!$F$3),'Sample Select backend'!$F$2,INDIRECT('Sample Select backend'!$I$2),1,INDIRECT('Sample Select backend'!$M$3),'Sample Select backend'!$M$2,INDIRECT('Sample Select backend'!$I$9),1,IF($A$20,Data!$J:$J,Data!#REF!),IF($A$20,"<>5",1)) -> #DIV/0! | J4: =AVERAGEIFS(INDIRECT(J3),INDIRECT(J3),">=0",INDIRECT('Sample Select backend'!$C$3),'Sample Select backend'!$C$2,INDIRECT('Sample Select backend'!$F$3),'Sample Select backend'!$F$2,INDIRECT('Sample Select backend'!$I$2),1,INDIRECT('Sample Select backend'!$M$3),'Sample Select backend'!$M$2,INDIRECT('Sample Select backend'!$I$9),1,IF($A$20,Data!$J:$J,Data!#REF!),IF($A$20,"<>5",1)) -> #DIV/0!
A5: Rank | B5: =IF('Sample Select backend'!L2>1,IF($A$20,VLOOKUP(B4,AW9:AX206,2,FALSE),VLOOKUP(B4,L9:M206,2,FALSE)),MAX(AL9:AL206)) -> 0 | C5: =IF('Sample Select backend'!L2>1,IF($A$20,VLOOKUP(C4,AZ9:BA206,2,FALSE),VLOOKUP(C4,O9:P206,2,FALSE)),MAX(AM9:AM206)) -> 0 | D5: =IF('Sample Select backend'!L2>1,IF($A$20,VLOOKUP(D4,BC9:BD206,2,FALSE),VLOOKUP(D4,R9:S206,2,FALSE)),MAX(AN9:AN206)) -> 0 | E5: =IF('Sample Select backend'!L2>1,IF($A$20,VLOOKUP(E4,BF9:BG206,2,FALSE),VLOOKUP(E4,U9:V206,2,FALSE)),MAX(AO9:AO206)) -> 0 | F5: =IF('Sample Select backend'!L2>1,IF($A$20,VLOOKUP(F4,BI9:BJ206,2,FALSE),VLOOKUP(F4,X9:Y206,2,FALSE)),MAX(AP9:AP206)) -> 0 | G5: =IF('Sample Select backend'!L2>1,IF($A$20,VLOOKUP(G4,BL9:BM206,2,FALSE),VLOOKUP(G4,AA9:AB206,2,FALSE)),MAX(AQ9:AQ206)) -> 0 | H5: =IF('Sample Select backend'!L2>1,IF($A$20,VLOOKUP(H4,BO9:BP206,2,FALSE),VLOOKUP(H4,AD9:AE206,2,FALSE)),MAX(AR9:AR206)) -> 0 | I5: =IF('Sample Select backend'!L2>1,IF($A$20,VLOOKUP(I4,BR9:BS206,2,FALSE),VLOOKUP(I4,AG9:AH206,2,FALSE)),MAX(AS9:AS206)) -> 0 | J5: =IF('Sample Select backend'!L2>1,IF($A$20,VLOOKUP(J4,BU9:BV206,2,FALSE),VLOOKUP(J4,AJ9:AK206,2,FALSE)),MAX(AT9:AT206)) -> 0 | AU5: Not including health measures
A6: AU = 1 for unique country | B6: =_xlfn.CONCAT(B5,IF(OR(B5=11,B5=111,B5=12,B5=112,B5=13,B5=113),"th",IF(RIGHT(B5,1)="1","st",IF(RIGHT(B5,1)="2","nd",IF(RIGHT(B5,1)="3","rd","th"))))) -> 0th | C6: =IFERROR(_xlfn.CONCAT(C5,IF(OR(C5=11,C5=111,C5=12,C5=112,C5=13,C5=113),"th",IF(RIGHT(C5,1)="1","st",IF(RIGHT(C5,1)="2","nd",IF(RIGHT(C5,1)="3","rd","th"))))),"No data") -> 0th | D6: =_xlfn.CONCAT(D5,IF(OR(D5=11,D5=111,D5=12,D5=112,D5=13,D5=113),"th",IF(RIGHT(D5,1)="1","st",IF(RIGHT(D5,1)="2","nd",IF(RIGHT(D5,1)="3","rd","th"))))) -> 0th | E6: =_xlfn.CONCAT(E5,IF(OR(E5=11,E5=111,E5=12,E5=112,E5=13,E5=113),"th",IF(RIGHT(E5,1)="1","st",IF(RIGHT(E5,1)="2","nd",IF(RIGHT(E5,1)="3","rd","th"))))) -> 0th | F6: =_xlfn.CONCAT(F5,IF(OR(F5=11,F5=111,F5=12,F5=112,F5=13,F5=113),"th",IF(RIGHT(F5,1)="1","st",IF(RIGHT(F5,1)="2","nd",IF(RIGHT(F5,1)="3","rd","th"))))) -> 0th | G6: =_xlfn.CONCAT(G5,IF(OR(G5=11,G5=111,G5=12,G5=112,G5=13,G5=113),"th",IF(RIGHT(G5,1)="1","st",IF(RIGHT(G5,1)="2","nd",IF(RIGHT(G5,1)="3","rd","th"))))) -> 0th | H6: =_xlfn.CONCAT(H5,IF(OR(H5=11,H5=111,H5=12,H5=112,H5=13,H5=113),"th",IF(RIGHT(H5,1)="1","st",IF(RIGHT(H5,1)="2","nd",IF(RIGHT(H5,1)="3","rd","th"))))) -> 0th | I6: =_xlfn.CONCAT(I5,IF(OR(I5=11,I5=111,I5=12,I5=112,I5=13,I5=113),"th",IF(RIGHT(I5,1)="1","st",IF(RIGHT(I5,1)="2","nd",IF(RIGHT(I5,1)="3","rd","th"))))) -> 0th | J6: =_xlfn.CONCAT(J5,IF(OR(J5=11,J5=111,J5=12,J5=112,J5=13,J5=113),"th",IF(RIGHT(J5,1)="1","st",IF(RIGHT(J5,1)="2","nd",IF(RIGHT(J5,1)="3","rd","th"))))) -> 0th | K6: Including Health Measures
B7: GDP change | C7: Fiscal Balance | D7: Debt | AL7: Ranking same averages---locator
B8: Data!$S:$S | C8: Data!$T:$T | D8: Data!$U:$U | J8: Rank | K8: Country | L8: Targetability | M8: Rank | N8: Country | O8: Speed | Q8: Country | R8: Abuse Resistance | T8: Country | U8: Affordability | W8: Country | X8: Predictability and Cost Control | Z8: Country | AA8: Reversibility | AC8: Country | AD8: Scalability | AF8: Country | AG8: Administrative Complexity | AI8: Country | AJ8: Resilience to Health Measures | AK8: Rank | AL8: Targetability | AM8: Speed | AN8: Abuse Resistance | AO8: Affordability | AP8: Predictability and Cost Control | AQ8: Reversibility | AR8: Scalability | AS8: Administrative Complexity | AT8: Resilience to Health Measures | AU8: Rank | AV8: Country | AW8: Targetability | AX8: Rank | AY8: Country | AZ8: Speed | BB8: Country | BC8: Abuse Resistance | BE8: Country | BF8: Affordability | BH8: Country | BI8: Predictability and Cost Control | BK8: Country | BL8: Reversibility | BN8: Country | BO8: Scalability | BQ8: Country | BR8: Administrative Complexity | BT8: Country | BU8: Resilience to Health Measures | BV8: Rank
A9: ermrating | B9: =AVERAGEIFS(INDIRECT(B8),INDIRECT('Sample Select backend'!$C$3),'Sample Select backend'!$C$2,INDIRECT('Sample Select backend'!$F$3),'Sample Select backend'!$F$2,INDIRECT('Sample Select backend'!$I$2),1,INDIRECT('Sample Select backend'!$M$3),'Sample Select backend'!$M$2,INDIRECT('Sample Select backend'!$I$9),1,Data!$AK:$AK,1) -> #DIV/0! | C9: =AVERAGEIFS(INDIRECT(C8),INDIRECT('Sample Select backend'!$C$3),'Sample Select backend'!$C$2,INDIRECT('Sample Select backend'!$F$3),'Sample Select backend'!$F$2,INDIRECT('Sample Select backend'!$I$2),1,INDIRECT('Sample Select backend'!$M$3),'Sample Select backend'!$M$2,INDIRECT('Sample Select backend'!$I$9),1,Data!$AK:$AK,1) -> #DIV/0! | D9: =AVERAGEIFS(INDIRECT(D8),INDIRECT('Sample Select backend'!$C$3),'Sample Select backend'!$C$2,INDIRECT('Sample Select backend'!$F$3),'Sample Select backend'!$F$2,INDIRECT('Sample Select backend'!$I$2),1,INDIRECT('Sample Select backend'!$M$3),'Sample Select backend'!$M$2,INDIRECT('Sample Select backend'!$I$9),1,Data!$AK:$AK,1) -> #DIV/0! | E9: Sample | J9: 1 | K9: Angola | L9: =AVERAGEIFS(INDIRECT($B$3),INDIRECT($B$3),">=0",Data!$B:$B,$K9) -> #DIV/0! | M9: 1 | N9: Iceland | O9: =AVERAGEIFS(INDIRECT($C$3),INDIRECT($C$3),">=0",Data!$B:$B,$N9) -> #DIV/0! | P9: 1 | Q9: Cayman Islands | R9: =AVERAGEIFS(INDIRECT($D$3),INDIRECT($D$3),">=0",Data!$B:$B,$Q9) -> #DIV/0! | S9: 1 | T9: Monaco | U9: =AVERAGEIFS(INDIRECT($E$3),INDIRECT($E$3),">=0",Data!$B:$B,$T9) -> #DIV/0! | V9: 1 | W9: Gabon | X9: =AVERAGEIFS(INDIRECT($F$3),INDIRECT($F$3),">=0",Data!$B:$B,$W9) -> #DIV/0! | Y9: 1 | Z9: Afghanistan | AA9: =AVERAGEIFS(INDIRECT($G$3),INDIRECT($G$3),">=0",Data!$B:$B,$Z9) -> #DIV/0! | AB9: 1 | AC9: Afghanistan | AD9: =AVERAGEIFS(INDIRECT($H$3),INDIRECT($H$3),">=0",Data!$B:$B,$AC9) -> #DIV/0! | AE9: 1 | AF9: Angola | AG9: =AVERAGEIFS(INDIRECT($I$3),INDIRECT($I$3),">=0",Data!$B:$B,$AF9) -> #DIV/0! | AH9: 1 | AI9: Zimbabwe | AJ9: =AVERAGEIFS(INDIRECT($J$3),INDIRECT($J$3),">=0",Data!$B:$B,$AI9) -> #DIV/0! | AK9: =J9 -> 1 | AL9: =IFERROR(IF($A$20,IF(B$4=AW9,AX9,IF(AND(B$4<AW9,B$4>AW10),AX10,0)),IF(B$4=L9,M9,IF(AND(B$4<L9,B$4>L10),M10,0))),"-") -> - | AM9: =IFERROR(IF($A$20,IF(C$4=AZ9,BA9,IF(AND(C$4<AZ9,C$4>AZ10),BA10,0)),IF(C$4=O9,P9,IF(AND(C$4<O9,C$4>O10),P10,0))),"-") -> - | AN9: =IFERROR(IF($A$20,IF(D$4=BC9,BD9,IF(AND(D$4<BC9,D$4>BC10),BD10,0)),IF(D$4=R9,S9,IF(AND(D$4<R9,D$4>R10),S10,0))),"-") -> - | AO9: =IFERROR(IF($A$20,IF(E$4=BF9,BG9,IF(AND(E$4<BF9,E$4>BF10),BG10,0)),IF(E$4=U9,V9,IF(AND(E$4<U9,E$4>U10),V10,0))),"-") -> - | AP9: =IFERROR(IF($A$20,IF(F$4=BI9,BJ9,IF(AND(F$4<BI9,F$4>BI10),BJ10,0)),IF(F$4=X9,Y9,IF(AND(F$4<X9,F$4>X10),Y10,0))),"-") -> - | AQ9: =IFERROR(IF($A$20,IF(G$4=BL9,BM9,IF(AND(G$4<BL9,G$4>BL10),BM10,0)),IF(G$4=AA9,AB9,IF(AND(G$4<AA9,G$4>AA10),AB10,0))),"-") -> - | AR9: =IFERROR(IF($A$20,IF(H$4=BO9,BP9,IF(AND(H$4<BO9,H$4>BO10),BP10,0)),IF(H$4=AD9,AE9,IF(AND(H$4<AD9,H$4>AD10),AE10,0))),"-") -> - | AS9: =IFERROR(IF($A$20,IF(I$4=BR9,BS9,IF(AND(I$4<BR9,I$4>BR10),BS10,0)),IF(I$4=AG9,AH9,IF(AND(I$4<AG9,I$4>AG10),AH10,0))),"-") -> - | AT9: =IFERROR(IF($A$20,IF(J$4=BU9,BV9,IF(AND(J$4<BU9,J$4>BU10),BV10,0)),IF(J$4=AJ9,AK9,IF(AND(J$4<AJ9,J$4>AJ10),AK10,0))),"-") -> - | AU9: 1 | AV9: Angola | AW9: =AVERAGEIFS(INDIRECT($B$3),INDIRECT($B$3),">=0",Data!$B:$B,AV9,IF($A$20,Data!$J:$J,Data!#REF!),IF($A$20,"<>5",1)) -> #DIV/0! | AX9: 1 | AY9: Iceland | AZ9: =AVERAGEIFS(INDIRECT($C$3),INDIRECT($C$3),">=0",Data!$B:$B,AY9,IF($A$20,Data!$J:$J,Data!#REF!),IF($A$20,"<>5",1)) -> #DIV/0! | BA9: 1 | BB9: Cayman Islands | BC9: =AVERAGEIFS(INDIRECT($D$3),INDIRECT($D$3),">=0",Data!$B:$B,BB9,IF($A$20,Data!$J:$J,Data!#REF!),IF($A$20,"<>5",1)) -> #DIV/0! | BD9: 1 | BE9: Monaco | BF9: =AVERAGEIFS(INDIRECT($E$3),INDIRECT($E$3),">=0",Data!$B:$B,BE9,IF($A$20,Data!$J:$J,Data!#REF!),IF($A$20,"<>5",1)) -> #DIV/0! | BG9: 1 | BH9: Gabon | BI9: =AVERAGEIFS(INDIRECT($F$3),INDIRECT($F$3),">=0",Data!$B:$B,BH9,IF($A$20,Data!$J:$J,Data!#REF!),IF($A$20,"<>5",1)) -> #DIV/0! | BJ9: 1 | BK9: Afghanistan | BL9: =AVERAGEIFS(INDIRECT($G$3),INDIRECT($G$3),">=0",Data!$B:$B,BK9,IF($A$20,Data!$J:$J,Data!#REF!),IF($A$20,"<>5",1)) -> #DIV/0! | BM9: 1 | BN9: Afghanistan | BO9: =AVERAGEIFS(INDIRECT($H$3),INDIRECT($H$3),">=0",Data!$B:$B,BN9,IF($A$20,Data!$J:$J,Data!#REF!),IF($A$20,"<>5",1)) -> #DIV/0! | BP9: 1 | BQ9: Angola | BR9: =AVERAGEIFS(INDIRECT($I$3),INDIRECT($I$3),">=0",Data!$B:$B,BQ9,IF($A$20,Data!$J:$J,Data!#REF!),IF($A$20,"<>5",1)) -> #DIV/0! | BS9: 1 | BT9: Zimbabwe | BU9: =AVERAGEIFS(INDIRECT($J$3),INDIRECT($J$3),">=0",Data!$B:$B,BT9,IF($A$20,Data!$J:$J,Data!#REF!),IF($A$20,"<>5",1)) -> #DIV/0! | BV9: =AU9 -> 1
A10: U | B10: =AVERAGEIFS(INDIRECT(B8),INDIRECT('Sample Select backend'!$C$26),'Sample Select backend'!$C$25,INDIRECT('Sample Select backend'!$D$26),'Sample Select backend'!$D$25,INDIRECT('Sample Select backend'!$E$26),'Sample Select backend'!$E$25,INDIRECT('Sample Select backend'!$F$26),'Sample Select backend'!$F$25,INDIRECT('Sample Select backend'!$G$26),'Sample Select backend'!$G$25,Data!$AK:$AK,1) -> #DIV/0! | C10: =AVERAGEIFS(INDIRECT(C8),INDIRECT('Sample Select backend'!$C$26),'Sample Select backend'!$C$25,INDIRECT('Sample Select backend'!$D$26),'Sample Select backend'!$D$25,INDIRECT('Sample Select backend'!$E$26),'Sample Select backend'!$E$25,INDIRECT('Sample Select backend'!$F$26),'Sample Select backend'!$F$25,INDIRECT('Sample Select backend'!$G$26),'Sample Select backend'!$G$25,Data!$AK:$AK,1) -> #DIV/0! | D10: =AVERAGEIFS(INDIRECT(D8),INDIRECT('Sample Select backend'!$C$26),'Sample Select backend'!$C$25,INDIRECT('Sample Select backend'!$D$26),'Sample Select backend'!$D$25,INDIRECT('Sample Select backend'!$E$26),'Sample Select backend'!$E$25,INDIRECT('Sample Select backend'!$F$26),'Sample Select backend'!$F$25,INDIRECT('Sample Select backend'!$G$26),'Sample Select backend'!$G$25,Data!$AK:$AK,1) -> #DIV/0! | E10: Comparator | J10: =J9+1 -> 2 | K10: Benin | L10: =AVERAGEIFS(INDIRECT($B$3),INDIRECT($B$3),">=0",Data!$B:$B,$K10) -> #DIV/0! | M10: =IF(L10=L9,M9,$J10) -> #DIV/0! | N10: Denmark | O10: =AVERAGEIFS(INDIRECT($C$3),INDIRECT($C$3),">=0",Data!$B:$B,$N10) -> #DIV/0! | P10: =IF(O10=O9,P9,$J10) -> #DIV/0! | Q10: Algeria | R10: =AVERAGEIFS(INDIRECT($D$3),INDIRECT($D$3),">=0",Data!$B:$B,$Q10) -> #DIV/0! | S10: =IF(R10=R9,S9,$J10) -> #DIV/0! | T10: Mozambique | U10: =AVERAGEIFS(INDIRECT($E$3),INDIRECT($E$3),">=0",Data!$B:$B,$T10) -> #DIV/0! | V10: =IF(U10=U9,V9,$J10) -> #DIV/0! | W10: Saint Lucia | X10: =AVERAGEIFS(INDIRECT($F$3),INDIRECT($F$3),">=0",Data!$B:$B,$W10) -> #DIV/0! | Y10: =IF(X10=X9,Y9,$J10) -> #DIV/0! | Z10: Benin | AA10: =AVERAGEIFS(INDIRECT($G$3),INDIRECT($G$3),">=0",Data!$B:$B,$Z10) -> #DIV/0! | AB10: =IF(AA10=AA9,AB9,$J10) -> #DIV/0! | AC10: Albania | AD10: =AVERAGEIFS(INDIRECT($H$3),INDIRECT($H$3),">=0",Data!$B:$B,$AC10) -> #DIV/0! | AE10: =IF(AD10=AD9,AE9,$J10) -> #DIV/0! | AF10: Benin | AG10: =AVERAGEIFS(INDIRECT($I$3),INDIRECT($I$3),">=0",Data!$B:$B,$AF10) -> #DIV/0! | AH10: =IF(AG10=AG9,AH9,$J10) -> #DIV/0! | AI10: Zambia | AJ10: =AVERAGEIFS(INDIRECT($J$3),INDIRECT($J$3),">=0",Data!$B:$B,$AI10) -> #DIV/0! | AK10: =IF(AJ10=AJ9,AK9,$J10) -> #DIV/0! | AL10: =IFERROR(IF($A$20,IF(B$4=AW10,AX10,IF(AND(B$4<AW10,B$4>AW11),AX11,0)),IF(B$4=L10,M10,IF(AND(B$4<L10,B$4>L11),M11,0))),"-") -> - | AM10: =IFERROR(IF($A$20,IF(C$4=AZ10,BA10,IF(AND(C$4<AZ10,C$4>AZ11),BA11,0)),IF(C$4=O10,P10,IF(AND(C$4<O10,C$4>O11),P11,0))),"-") -> - | AN10: =IFERROR(IF($A$20,IF(D$4=BC10,BD10,IF(AND(D$4<BC10,D$4>BC11),BD11,0)),IF(D$4=R10,S10,IF(AND(D$4<R10,D$4>R11),S11,0))),"-") -> - | AO10: =IFERROR(IF($A$20,IF(E$4=BF10,BG10,IF(AND(E$4<BF10,E$4>BF11),BG11,0)),IF(E$4=U10,V10,IF(AND(E$4<U10,E$4>U11),V11,0))),"-") -> - | AP10: =IFERROR(IF($A$20,IF(F$4=BI10,BJ10,IF(AND(F$4<BI10,F$4>BI11),BJ11,0)),IF(F$4=X10,Y10,IF(AND(F$4<X10,F$4>X11),Y11,0))),"-") -> - | AQ10: =IFERROR(IF($A$20,IF(G$4=BL10,BM10,IF(AND(G$4<BL10,G$4>BL11),BM11,0)),IF(G$4=AA10,AB10,IF(AND(G$4<AA10,G$4>AA11),AB11,0))),"-") -> - | AR10: =IFERROR(IF($A$20,IF(H$4=BO10,BP10,IF(AND(H$4<BO10,H$4>BO11),BP11,0)),IF(H$4=AD10,AE10,IF(AND(H$4<AD10,H$4>AD11),AE11,0))),"-") -> - | AS10: =IFERROR(IF($A$20,IF(I$4=BR10,BS10,IF(AND(I$4<BR10,I$4>BR11),BS11,0)),IF(I$4=AG10,AH10,IF(AND(I$4<AG10,I$4>AG11),AH11,0))),"-") -> - | AT10: =IFERROR(IF($A$20,IF(J$4=BU10,BV10,IF(AND(J$4<BU10,J$4>BU11),BV11,0)),IF(J$4=AJ10,AK10,IF(AND(J$4<AJ10,J$4>AJ11),AK11,0))),"-") -> - | AU10: =AU9+1 -> 2 | AV10: Comoros | AW10: =AVERAGEIFS(INDIRECT($B$3),INDIRECT($B$3),">=0",Data!$B:$B,AV10,IF($A$20,Data!$J:$J,Data!#REF!),IF($A$20,"<>5",1)) -> #DIV/0! | AX10: =IF(AW10=AW9,AX9,$J10) -> #DIV/0! | AY10: Denmark | AZ10: =AVERAGEIFS(INDIRECT($C$3),INDIRECT($C$3),">=0",Data!$B:$B,AY10,IF($A$20,Data!$J:$J,Data!#REF!),IF($A$20,"<>5",1)) -> #DIV/0! | BA10: =IF(AZ10=AZ9,BA9,$J10) -> #DIV/0! | BB10: Algeria | BC10: =AVERAGEIFS(INDIRECT($D$3),INDIRECT($D$3),">=0",Data!$B:$B,BB10,IF($A$20,Data!$J:$J,Data!#REF!),IF($A$20,"<>5",1)) -> #DIV/0! | BD10: =IF(BC10=BC9,BD9,$J10) -> #DIV/0! | BE10: Mozambique | BF10: =AVERAGEIFS(INDIRECT($E$3),INDIRECT($E$3),">=0",Data!$B:$B,BE10,IF($A$20,Data!$J:$J,Data!#REF!),IF($A$20,"<>5",1)) -> #DIV/0! | BG10: =IF(BF10=BF9,BG9,$J10) -> #DIV/0! | BH10: Saint Lucia | BI10: =AVERAGEIFS(INDIRECT($F$3),INDIRECT($F$3),">=0",Data!$B:$B,BH10,IF($A$20,Data!$J:$J,Data!#REF!),IF($A$20,"<>5",1)) -> #DIV/0! | BJ10: =IF(BI10=BI9,BJ9,$J10) -> #DIV/0! | BK10: Bhutan | BL10: =AVERAGEIFS(INDIRECT($G$3),INDIRECT($G$3),">=0",Data!$B:$B,BK10,IF($A$20,Data!$J:$J,Data!#REF!),IF($A$20,"<>5",1)) -> #DIV/0! | BM10: =IF(BL10=BL9,BM9,$J10) -> #DIV/0! | BN10: Albania | BO10: =AVERAGEIFS(INDIRECT($H$3),INDIRECT($H$3),">=0",Data!$B:$B,BN10,IF($A$20,Data!$J:$J,Data!#REF!),IF($A$20,"<>5",1)) -> #DIV/0! | BP10: =IF(BO10=BO9,BP9,$J10) -> #DIV/0! | BQ10: Brunei Darussalam | BR10: =AVERAGEIFS(INDIRECT($I$3),INDIRECT($I$3),">=0",Data!$B:$B,BQ10,IF($A$20,Data!$J:$J,Data!#REF!),IF($A$20,"<>5",1)) -> #DIV/0! | BS10: =IF(BR10=BR9,BS9,$J10) -> #DIV/0! | BT10: Zambia | BU10: =AVERAGEIFS(INDIRECT($J$3),INDIRECT($J$3),">=0",Data!$B:$B,BT10,IF($A$20,Data!$J:$J,Data!#REF!),IF($A$20,"<>5",1)) -> #DIV/0! | BV10: =IF(BU10=BU9,BV9,$J10) -> #DIV/0!
A11: WGI | J11: =J10+1 -> 3 | K11: Central African Republic | L11: =AVERAGEIFS(INDIRECT($B$3),INDIRECT($B$3),">=0",Data!$B:$B,$K11) -> #DIV/0! | M11: =IF(L11=L10,M10,$J11) -> #DIV/0! | N11: Guyana | O11: =AVERAGEIFS(INDIRECT($C$3),INDIRECT($C$3),">=0",Data!$B:$B,$N11) -> #DIV/0! | P11: =IF(O11=O10,P10,$J11) -> #DIV/0! | Q11: Gabon | R11: =AVERAGEIFS(INDIRECT($D$3),INDIRECT($D$3),">=0",Data!$B:$B,$Q11) -> #DIV/0! | S11: =IF(R11=R10,S10,$J11) -> #DIV/0! | T11: Mexico | U11: =AVERAGEIFS(INDIRECT($E$3),INDIRECT($E$3),">=0",Data!$B:$B,$T11) -> #DIV/0! | V11: =IF(U11=U10,V10,$J11) -> #DIV/0! | W11: Monaco | X11: =AVERAGEIFS(INDIRECT($F$3),INDIRECT($F$3),">=0",Data!$B:$B,$W11) -> #DIV/0! | Y11: =IF(X11=X10,Y10,$J11) -> #DIV/0! | Z11: Bhutan | AA11: =AVERAGEIFS(INDIRECT($G$3),INDIRECT($G$3),">=0",Data!$B:$B,$Z11) -> #DIV/0! | AB11: =IF(AA11=AA10,AB10,$J11) -> #DIV/0! | AC11: Armenia | AD11: =AVERAGEIFS(INDIRECT($H$3),INDIRECT($H$3),">=0",Data!$B:$B,$AC11) -> #DIV/0! | AE11: =IF(AD11=AD10,AE10,$J11) -> #DIV/0! | AF11: Brunei Darussalam | AG11: =AVERAGEIFS(INDIRECT($I$3),INDIRECT($I$3),">=0",Data!$B:$B,$AF11) -> #DIV/0! | AH11: =IF(AG11=AG10,AH10,$J11) -> #DIV/0! | AI11: Yemen | AJ11: =AVERAGEIFS(INDIRECT($J$3),INDIRECT($J$3),">=0",Data!$B:$B,$AI11) -> #DIV/0! | AK11: =IF(AJ11=AJ10,AK10,$J11) -> #DIV/0! | AL11: =IFERROR(IF($A$20,IF(B$4=AW11,AX11,IF(AND(B$4<AW11,B$4>AW12),AX12,0)),IF(B$4=L11,M11,IF(AND(B$4<L11,B$4>L12),M12,0))),"-") -> - | AM11: =IFERROR(IF($A$20,IF(C$4=AZ11,BA11,IF(AND(C$4<AZ11,C$4>AZ12),BA12,0)),IF(C$4=O11,P11,IF(AND(C$4<O11,C$4>O12),P12,0))),"-") -> - | AN11: =IFERROR(IF($A$20,IF(D$4=BC11,BD11,IF(AND(D$4<BC11,D$4>BC12),BD12,0)),IF(D$4=R11,S11,IF(AND(D$4<R11,D$4>R12),S12,0))),"-") -> - | AO11: =IFERROR(IF($A$20,IF(E$4=BF11,BG11,IF(AND(E$4<BF11,E$4>BF12),BG12,0)),IF(E$4=U11,V11,IF(AND(E$4<U11,E$4>U12),V12,0))),"-") -> - | AP11: =IFERROR(IF($A$20,IF(F$4=BI11,BJ11,IF(AND(F$4<BI11,F$4>BI12),BJ12,0)),IF(F$4=X11,Y11,IF(AND(F$4<X11,F$4>X12),Y12,0))),"-") -> - | AQ11: =IFERROR(IF($A$20,IF(G$4=BL11,BM11,IF(AND(G$4<BL11,G$4>BL12),BM12,0)),IF(G$4=AA11,AB11,IF(AND(G$4<AA11,G$4>AA12),AB12,0))),"-") -> - | AR11: =IFERROR(IF($A$20,IF(H$4=BO11,BP11,IF(AND(H$4<BO11,H$4>BO12),BP12,0)),IF(H$4=AD11,AE11,IF(AND(H$4<AD11,H$4>AD12),AE12,0))),"-") -> - | AS11: =IFERROR(IF($A$20,IF(I$4=BR11,BS11,IF(AND(I$4<BR11,I$4>BR12),BS12,0)),IF(I$4=AG11,AH11,IF(AND(I$4<AG11,I$4>AG12),AH12,0))),"-") -> - | AT11: =IFERROR(IF($A$20,IF(J$4=BU11,BV11,IF(AND(J$4<BU11,J$4>BU12),BV12,0)),IF(J$4=AJ11,AK11,IF(AND(J$4<AJ11,J$4>AJ12),AK12,0))),"-") -> - | AU11: =AU10+1 -> 3 | AV11: Guinea | AW11: =AVERAGEIFS(INDIRECT($B$3),INDIRECT($B$3),">=0",Data!$B:$B,AV11,IF($A$20,Data!$J:$J,Data!#REF!),IF($A$20,"<>5",1)) -> #DIV/0! | AX11: =IF(AW11=AW10,AX10,$J11) -> #DIV/0! | AY11: Guyana | AZ11: =AVERAGEIFS(INDIRECT($C$3),INDIRECT($C$3),">=0",Data!$B:$B,AY11,IF($A$20,Data!$J:$J,Data!#REF!),IF($A$20,"<>5",1)) -> #DIV/0! | BA11: =IF(AZ11=AZ10,BA10,$J11) -> #DIV/0! | BB11: Gabon | BC11: =AVERAGEIFS(INDIRECT($D$3),INDIRECT($D$3),">=0",Data!$B:$B,BB11,IF($A$20,Data!$J:$J,Data!#REF!),IF($A$20,"<>5",1)) -> #DIV/0! | BD11: =IF(BC11=BC10,BD10,$J11) -> #DIV/0! | BE11: Suriname | BF11: =AVERAGEIFS(INDIRECT($E$3),INDIRECT($E$3),">=0",Data!$B:$B,BE11,IF($A$20,Data!$J:$J,Data!#REF!),IF($A$20,"<>5",1)) -> #DIV/0! | BG11: =IF(BF11=BF10,BG10,$J11) -> #DIV/0! | BH11: Monaco | BI11: =AVERAGEIFS(INDIRECT($F$3),INDIRECT($F$3),">=0",Data!$B:$B,BH11,IF($A$20,Data!$J:$J,Data!#REF!),IF($A$20,"<>5",1)) -> #DIV/0! | BJ11: =IF(BI11=BI10,BJ10,$J11) -> #DIV/0! | BK11: Cote d'Ivoire | BL11: =AVERAGEIFS(INDIRECT($G$3),INDIRECT($G$3),">=0",Data!$B:$B,BK11,IF($A$20,Data!$J:$J,Data!#REF!),IF($A$20,"<>5",1)) -> #DIV/0! | BM11: =IF(BL11=BL10,BM10,$J11) -> #DIV/0! | BN11: Armenia | BO11: =AVERAGEIFS(INDIRECT($H$3),INDIRECT($H$3),">=0",Data!$B:$B,BN11,IF($A$20,Data!$J:$J,Data!#REF!),IF($A$20,"<>5",1)) -> #DIV/0! | BP11: =IF(BO11=BO10,BP10,$J11) -> #DIV/0! | BQ11: Bhutan | BR11: =AVERAGEIFS(INDIRECT($I$3),INDIRECT($I$3),">=0",Data!$B:$B,BQ11,IF($A$20,Data!$J:$J,Data!#REF!),IF($A$20,"<>5",1)) -> #DIV/0! | BS11: =IF(BR11=BR10,BS10,$J11) -> #DIV/0! | BT11: West Bank and Gaza | BU11: =AVERAGEIFS(INDIRECT($J$3),INDIRECT($J$3),">=0",Data!$B:$B,BT11,IF($A$20,Data!$J:$J,Data!#REF!),IF($A$20,"<>5",1)) -> #DIV/0! | BV11: =IF(BU11=BU10,BV10,$J11) -> #DIV/0!
